Workbook

Sheet Summary
B1: Data Centers
B3: Total
C4: 2026 | D4: 2027 | E4: 2028 | F4: 2029
B5: Compensation | C5: =C43+C81 -> 12484861 | D5: =D43+D81 -> 15345429 | E5: =E43+E81 -> 15345429 | F5: =F43+F81 -> 15345429
B6: Bonus | C6: =C44+C82 -> 7260350.9 | D6: =D44+D82 -> 8923863.7 | E6: =E44+E82 -> 8923863.7 | F6: =F44+F82 -> 8923863.7
B7: Essentials Bonus | C7: =C45+C83 -> 0 | D7: =D45+D83 -> 0 | E7: =E45+E83 -> 0 | F7: =F45+F83 -> 0
B8: Payroll Taxes | C8: =C46+C84 -> 1451993.8 | D8: =D46+D84 -> 1784678.8 | E8: =E46+E84 -> 1784678.8 | F8: =F46+F84 -> 1784678.8
B9: Benefits | C9: =C47+C85 -> 1484837.4 | D9: =D47+D85 -> 1825047.6 | E9: =E47+E85 -> 1825047.6 | F9: =F47+F85 -> 1825047.6
B10: Vacation | C10: =C48+C86 -> 54952.65 | D10: =D48+D86 -> 67543.562 | E10: =E48+E86 -> 67543.562 | F10: =F48+F86 -> 67543.562
B11: Other | C11: =C49+C87 -> 0 | D11: =D49+D87 -> 0 | E11: =E49+E87 -> 0 | F11: =F49+F87 -> 0
B12: Contract Labor | C12: =C50+C88 -> 0 | D12: =D50+D88 -> 0 | E12: =E50+E88 -> 0 | F12: =F50+F88 -> 0
B13: LTIP Compensation | C13: =C51+C89 -> 3562244.9 | D13: =D51+D89 -> 6332657.8 | E13: =E51+E89 -> 6332657.8 | F13: =F51+F89 -> 6332657.8
B14: Total Payroll | C14: =SUM(C5:C13) -> 26299241 | D14: =SUM(D5:D13) -> 34279221 | E14: =E52+E90 -> 34279221 | F14: =F52+F90 -> 34279221
B16: Professional Fees | C16: =C54+C92 -> 328734 | D16: =D54+D92 -> 328734 | E16: =E54+E92 -> 328734 | F16: =F54+F92 -> 328734
B17: Occupancy | C17: =C55+C93 -> -65529 | D17: =D55+D93 -> -65529 | E17: =E55+E93 -> -65529 | F17: =F55+F93 -> -65529
B18: Office Expenses | C18: =C56+C94 -> -3040.82 | D18: =D56+D94 -> -3040.82 | E18: =E56+E94 -> -3040.82 | F18: =F56+F94 -> -3040.82
B19: IT Costs | C19: =C57+C95 -> 7089.24 | D19: =D57+D95 -> 7089.24 | E19: =E57+E95 -> 7089.24 | F19: =F57+F95 -> 7089.24
B20: Marketing and Presentation | C20: =C58+C96 -> 0 | D20: =D58+D96 -> 0 | E20: =E58+E96 -> 0 | F20: =F58+F96 -> 0
B21: Travel and Entertainment | C21: =C59+C97 -> 945298.56 | D21: =D59+D97 -> 945298.56 | E21: =E59+E97 -> 945298.56 | F21: =F59+F97 -> 945298.56
B22: Employee events | C22: =C60+C98 -> 119350.72 | D22: =D60+D98 -> 119350.72 | E22: =E60+E98 -> 119350.72 | F22: =F60+F98 -> 119350.72
B23: Insurance Non Property | C23: =C61+C99 -> 0 | D23: =D61+D99 -> 0 | E23: =E61+E99 -> 0 | F23: =F61+F99 -> 0
B24: Licenses | C24: =C62+C100 -> 0 | D24: =D62+D100 -> 0 | E24: =E62+E100 -> 0 | F24: =F62+F100 -> 0
B25: Recruiting and Relocation | C25: =C63+C101 -> 959676.43 | D25: =D63+D101 -> 959676.43 | E25: =E63+E101 -> 959676.43 | F25: =F63+F101 -> 959676.43
B26: Seminars and Training | C26: =C64+C102 -> 36097.76 | D26: =D64+D102 -> 36097.76 | E26: =E64+E102 -> 36097.76 | F26: =F64+F102 -> 36097.76
B27: Shareholder Relations | C27: =C65+C103 -> 0 | D27: =D65+D103 -> 0 | E27: =E65+E103 -> 0 | F27: =F65+F103 -> 0
... B36: Allocated IT & Office Contra | C36: =C74+C112 -> 0 | D36: =D74+D112 -> 0 | E36: =E74+E112 -> 0 | F36: =F74+F112 -> 0
B37: Total Non-Payroll | C37: =SUM(C16:C36) -> 2649576.1 | D37: =SUM(D16:D36) -> 2649576.1 | E37: =E75+E113 -> 2649576.1 | F37: =F75+F113 -> 2649576.1
B39: Total | C39: =C14+C37 -> 28948817 | D39: =D14+D37 -> 36928797 | E39: =E77+E115 -> 36928797 | F39: =F77+F115 -> 36928797
B41: Baseline
C42: 2026 | D42: 2027 | E42: 2028 | F42: 2029
B43: Compensation | C43: =SUMIFS('Base - Payroll'!$E:$E,'Base - Payroll'!$A:$A,Summary!$B43) -> 12484861 | D43: =SUMIFS('Base - Payroll'!$G:$G,'Base - Payroll'!$A:$A,Summary!$B43) -> 15345429 | E43: =SUMIFS('Base - Payroll'!$H:$H,'Base - Payroll'!$A:$A,Summary!$B43) -> 15345429 | F43: =SUMIFS('Base - Payroll'!$I:$I,'Base - Payroll'!$A:$A,Summary!$B43) -> 15345429
B44: Bonus | C44: =SUMIFS('Base - Payroll'!$E:$E,'Base - Payroll'!$A:$A,Summary!$B44) -> 7260350.9 | D44: =SUMIFS('Base - Payroll'!$G:$G,'Base - Payroll'!$A:$A,Summary!$B44) -> 8923863.7 | E44: =SUMIFS('Base - Payroll'!$H:$H,'Base - Payroll'!$A:$A,Summary!$B44) -> 8923863.7 | F44: =SUMIFS('Base - Payroll'!$I:$I,'Base - Payroll'!$A:$A,Summary!$B44) -> 8923863.7
B45: Essentials Bonus | C45: =SUMIFS('Base - Non-Payroll'!$E:$E,'Base - Non-Payroll'!$A:$A,Summary!$B45) -> 0 | D45: =SUMIFS('Base - Non-Payroll'!$H:$H,'Base - Non-Payroll'!$A:$A,Summary!$B45) -> 0 | E45: =SUMIFS('Base - Non-Payroll'!$J:$J,'Base - Non-Payroll'!$A:$A,Summary!$B45) -> 0 | F45: =SUMIFS('Base - Non-Payroll'!$L:$L,'Base - Non-Payroll'!$A:$A,Summary!$B45) -> 0
B46: Payroll Taxes | C46: =SUMIFS('Base - Payroll'!$E:$E,'Base - Payroll'!$A:$A,Summary!$B46) -> 1451993.8 | D46: =SUMIFS('Base - Payroll'!$G:$G,'Base - Payroll'!$A:$A,Summary!$B46) -> 1784678.8 | E46: =SUMIFS('Base - Payroll'!$H:$H,'Base - Payroll'!$A:$A,Summary!$B46) -> 1784678.8 | F46: =SUMIFS('Base - Payroll'!$I:$I,'Base - Payroll'!$A:$A,Summary!$B46) -> 1784678.8
B47: Benefits | C47: =SUMIFS('Base - Payroll'!$E:$E,'Base - Payroll'!$A:$A,Summary!$B47) -> 1484837.4 | D47: =SUMIFS('Base - Payroll'!$G:$G,'Base - Payroll'!$A:$A,Summary!$B47) -> 1825047.6 | E47: =SUMIFS('Base - Payroll'!$H:$H,'Base - Payroll'!$A:$A,Summary!$B47) -> 1825047.6 | F47: =SUMIFS('Base - Payroll'!$I:$I,'Base - Payroll'!$A:$A,Summary!$B47) -> 1825047.6
B48: Vacation | C48: =SUMIFS('Base - Payroll'!$E:$E,'Base - Payroll'!$A:$A,Summary!$B48) -> 54952.65 | D48: =SUMIFS('Base - Payroll'!$G:$G,'Base - Payroll'!$A:$A,Summary!$B48) -> 67543.562 | E48: =SUMIFS('Base - Payroll'!$H:$H,'Base - Payroll'!$A:$A,Summary!$B48) -> 67543.562 | F48: =SUMIFS('Base - Payroll'!$I:$I,'Base - Payroll'!$A:$A,Summary!$B48) -> 67543.562
B49: Other | C49: =SUMIFS('Base - Payroll'!$E:$E,'Base - Payroll'!$A:$A,Summary!$B49) -> 0 | D49: =SUMIFS('Base - Payroll'!$G:$G,'Base - Payroll'!$A:$A,Summary!$B49) -> 0 | E49: =SUMIFS('Base - Payroll'!$H:$H,'Base - Payroll'!$A:$A,Summary!$B49) -> 0 | F49: =SUMIFS('Base - Payroll'!$I:$I,'Base - Payroll'!$A:$A,Summary!$B49) -> 0
B50: Contract Labor | C50: =SUMIFS('Base - Non-Payroll'!$E:$E,'Base - Non-Payroll'!$A:$A,Summary!$B50) -> 0 | D50: =SUMIFS('Base - Non-Payroll'!$H:$H,'Base - Non-Payroll'!$A:$A,Summary!$B50) -> 0 | E50: =SUMIFS('Base - Non-Payroll'!$J:$J,'Base - Non-Payroll'!$A:$A,Summary!$B50) -> 0 | F50: =SUMIFS('Base - Non-Payroll'!$L:$L,'Base - Non-Payroll'!$A:$A,Summary!$B50) -> 0
B51: LTIP Compensation | C51: =SUMIFS('Base - Payroll'!$E:$E,'Base - Payroll'!$A:$A,Summary!$B51) -> 3562244.9 | D51: =SUMIFS('Base - Payroll'!$G:$G,'Base - Payroll'!$A:$A,Summary!$B51) -> 6332657.8 | E51: =SUMIFS('Base - Payroll'!$H:$H,'Base - Payroll'!$A:$A,Summary!$B51) -> 6332657.8 | F51: =SUMIFS('Base - Payroll'!$I:$I,'Base - Payroll'!$A:$A,Summary!$B51) -> 6332657.8
B52: Baseline Payroll | C52: =SUM(C43:C51) -> 26299241 | D52: =SUM(D43:D51) -> 34279221 | E52: =SUM(E43:E51) -> 34279221 | F52: =SUM(F43:F51) -> 34279221
B54: Professional Fees | C54: =SUMIFS('Base - Non-Payroll'!$E:$E,'Base - Non-Payroll'!$A:$A,Summary!$B54) -> 328734 | D54: =SUMIFS('Base - Non-Payroll'!$H:$H,'Base - Non-Payroll'!$A:$A,Summary!$B54) -> 328734 | E54: =SUMIFS('Base - Non-Payroll'!$J:$J,'Base - Non-Payroll'!$A:$A,Summary!$B54) -> 328734 | F54: =SUMIFS('Base - Non-Payroll'!$L:$L,'Base - Non-Payroll'!$A:$A,Summary!$B54) -> 328734
B55: Occupancy | C55: =SUMIFS('Base - Non-Payroll'!$E:$E,'Base - Non-Payroll'!$A:$A,Summary!$B55) -> -65529 | D55: =SUMIFS('Base - Non-Payroll'!$H:$H,'Base - Non-Payroll'!$A:$A,Summary!$B55) -> -65529 | E55: =SUMIFS('Base - Non-Payroll'!$J:$J,'Base - Non-Payroll'!$A:$A,Summary!$B55) -> -65529 | F55: =SUMIFS('Base - Non-Payroll'!$L:$L,'Base - Non-Payroll'!$A:$A,Summary!$B55) -> -65529
B56: Office Expenses | C56: =SUMIFS('Base - Non-Payroll'!$E:$E,'Base - Non-Payroll'!$A:$A,Summary!$B56) -> -3040.82 | D56: =SUMIFS('Base - Non-Payroll'!$H:$H,'Base - Non-Payroll'!$A:$A,Summary!$B56) -> -3040.82 | E56: =SUMIFS('Base - Non-Payroll'!$J:$J,'Base - Non-Payroll'!$A:$A,Summary!$B56) -> -3040.82 | F56: =SUMIFS('Base - Non-Payroll'!$L:$L,'Base - Non-Payroll'!$A:$A,Summary!$B56) -> -3040.82
B57: IT Costs | C57: =SUMIFS('Base - Non-Payroll'!$E:$E,'Base - Non-Payroll'!$A:$A,Summary!$B57) -> 7089.24 | D57: =SUMIFS('Base - Non-Payroll'!$H:$H,'Base - Non-Payroll'!$A:$A,Summary!$B57) -> 7089.24 | E57: =SUMIFS('Base - Non-Payroll'!$J:$J,'Base - Non-Payroll'!$A:$A,Summary!$B57) -> 7089.24 | F57: =SUMIFS('Base - Non-Payroll'!$L:$L,'Base - Non-Payroll'!$A:$A,Summary!$B57) -> 7089.24
B58: Marketing and Presentation | C58: =SUMIFS('Base - Non-Payroll'!$E:$E,'Base - Non-Payroll'!$A:$A,Summary!$B58) -> 0 | D58: =SUMIFS('Base - Non-Payroll'!$H:$H,'Base - Non-Payroll'!$A:$A,Summary!$B58) -> 0 | E58: =SUMIFS('Base - Non-Payroll'!$J:$J,'Base - Non-Payroll'!$A:$A,Summary!$B58) -> 0 | F58: =SUMIFS('Base - Non-Payroll'!$L:$L,'Base - Non-Payroll'!$A:$A,Summary!$B58) -> 0
B59: Travel and Entertainment | C59: =SUMIFS('Base - Non-Payroll'!$E:$E,'Base - Non-Payroll'!$A:$A,Summary!$B59) -> 945298.56 | D59: =SUMIFS('Base - Non-Payroll'!$H:$H,'Base - Non-Payroll'!$A:$A,Summary!$B59) -> 945298.56 | E59: =SUMIFS('Base - Non-Payroll'!$J:$J,'Base - Non-Payroll'!$A:$A,Summary!$B59) -> 945298.56 | F59: =SUMIFS('Base - Non-Payroll'!$L:$L,'Base - Non-Payroll'!$A:$A,Summary!$B59) -> 945298.56
B60: Employee events | C60: =SUMIFS('Base - Non-Payroll'!$E:$E,'Base - Non-Payroll'!$A:$A,Summary!$B60) -> 119350.72 | D60: =SUMIFS('Base - Non-Payroll'!$H:$H,'Base - Non-Payroll'!$A:$A,Summary!$B60) -> 119350.72 | E60: =SUMIFS('Base - Non-Payroll'!$J:$J,'Base - Non-Payroll'!$A:$A,Summary!$B60) -> 119350.72 | F60: =SUMIFS('Base - Non-Payroll'!$L:$L,'Base - Non-Payroll'!$A:$A,Summary!$B60) -> 119350.72
B61: Insurance Non Property | C61: =SUMIFS('Base - Non-Payroll'!$E:$E,'Base - Non-Payroll'!$A:$A,Summary!$B61) -> 0 | D61: =SUMIFS('Base - Non-Payroll'!$H:$H,'Base - Non-Payroll'!$A:$A,Summary!$B61) -> 0 | E61: =SUMIFS('Base - Non-Payroll'!$J:$J,'Base - Non-Payroll'!$A:$A,Summary!$B61) -> 0 | F61: =SUMIFS('Base - Non-Payroll'!$L:$L,'Base - Non-Payroll'!$A:$A,Summary!$B61) -> 0
B62: Licenses | C62: =SUMIFS('Base - Non-Payroll'!$E:$E,'Base - Non-Payroll'!$A:$A,Summary!$B62) -> 0 | D62: =SUMIFS('Base - Non-Payroll'!$H:$H,'Base - Non-Payroll'!$A:$A,Summary!$B62) -> 0 | E62: =SUMIFS('Base - Non-Payroll'!$J:$J,'Base - Non-Payroll'!$A:$A,Summary!$B62) -> 0 | F62: =SUMIFS('Base - Non-Payroll'!$L:$L,'Base - Non-Payroll'!$A:$A,Summary!$B62) -> 0
B63: Recruiting and Relocation | C63: =SUMIFS('Base - Non-Payroll'!$E:$E,'Base - Non-Payroll'!$A:$A,Summary!$B63) -> 959676.43 | D63: =SUMIFS('Base - Non-Payroll'!$H:$H,'Base - Non-Payroll'!$A:$A,Summary!$B63) -> 959676.43 | E63: =SUMIFS('Base - Non-Payroll'!$J:$J,'Base - Non-Payroll'!$A:$A,Summary!$B63) -> 959676.43 | F63: =SUMIFS('Base - Non-Payroll'!$L:$L,'Base - Non-Payroll'!$A:$A,Summary!$B63) -> 959676.43
B64: Seminars and Training | C64: =SUMIFS('Base - Non-Payroll'!$E:$E,'Base - Non-Payroll'!$A:$A,Summary!$B64) -> 36097.76 | D64: =SUMIFS('Base - Non-Payroll'!$H:$H,'Base - Non-Payroll'!$A:$A,Summary!$B64) -> 36097.76 | E64: =SUMIFS('Base - Non-Payroll'!$J:$J,'Base - Non-Payroll'!$A:$A,Summary!$B64) -> 36097.76 | F64: =SUMIFS('Base - Non-Payroll'!$L:$L,'Base - Non-Payroll'!$A:$A,Summary!$B64) -> 36097.76
B65: Shareholder Relations | C65: =SUMIFS('Base - Non-Payroll'!$E:$E,'Base - Non-Payroll'!$A:$A,Summary!$B65) -> 0 | D65: =SUMIFS('Base - Non-Payroll'!$H:$H,'Base - Non-Payroll'!$A:$A,Summary!$B65) -> 0 | E65: =SUMIFS('Base - Non-Payroll'!$J:$J,'Base - Non-Payroll'!$A:$A,Summary!$B65) -> 0 | F65: =SUMIFS('Base - Non-Payroll'!$L:$L,'Base - Non-Payroll'!$A:$A,Summary!$B65) -> 0
... B74: Allocated IT & Office Contra | C74: =SUMIFS('Base - Non-Payroll'!$E:$E,'Base - Non-Payroll'!$A:$A,Summary!$B74) -> 0 | D74: =SUMIFS('Base - Non-Payroll'!$H:$H,'Base - Non-Payroll'!$A:$A,Summary!$B74) -> 0 | E74: =SUMIFS('Base - Non-Payroll'!$J:$J,'Base - Non-Payroll'!$A:$A,Summary!$B74) -> 0 | F74: =SUMIFS('Base - Non-Payroll'!$L:$L,'Base - Non-Payroll'!$A:$A,Summary!$B74) -> 0
B75: Baseline Non-Payroll | C75: =SUM(C54:C74) -> 2649576.1 | D75: =SUM(D54:D74) -> 2649576.1 | E75: =SUM(E54:E74) -> 2649576.1 | F75: =SUM(F54:F74) -> 2649576.1
B77: Total | C77: =C52+C75 -> 28948817 | D77: =D52+D75 -> 36928797 | E77: =E52+E75 -> 36928797 | F77: =F52+F75 -> 36928797
B79: Incremental
D80: 2027 Incremental Spend | E80: 2028 Incremental Spend | F80: 2029 Incremental Spend
B81: Compensation | D81: {=SUMPRODUCT(IFERROR(tblPayrollIncrementalSpend[Base Salary]*tblPayrollIncrementalSpend[2027 Incremental Spend]/(tblPayrollIncrementalSpend[Base Salary]+tblPayrollIncrementalSpend[Bonus]+tblPayrollIncrementalSpend[Payroll Taxes]+tblPayrollIncrementalSpend[Benefits]+tblPayrollIncrementalSpend[Vacation]+tblPayrollIncrementalSpend[Other]),0))} -> 0 | E81: {=SUMPRODUCT(IFERROR(tblPayrollIncrementalSpend[Base Salary]*tblPayrollIncrementalSpend[2028 Incremental Spend]/(tblPayrollIncrementalSpend[Base Salary]+tblPayrollIncrementalSpend[Bonus]+tblPayrollIncrementalSpend[Payroll Taxes]+tblPayrollIncrementalSpend[Benefits]+tblPayrollIncrementalSpend[Vacation]+tblPayrollIncrementalSpend[Other]),0))} -> 0 | F81: {=SUMPRODUCT(IFERROR(tblPayrollIncrementalSpend[Base Salary]*tblPayrollIncrementalSpend[2029 Incremental Spend]/(tblPayrollIncrementalSpend[Base Salary]+tblPayrollIncrementalSpend[Bonus]+tblPayrollIncrementalSpend[Payroll Taxes]+tblPayrollIncrementalSpend[Benefits]+tblPayrollIncrementalSpend[Vacation]+tblPayrollIncrementalSpend[Other]),0))} -> 0
B82: Bonus | D82: {=SUMPRODUCT(IFERROR(tblPayrollIncrementalSpend[Bonus]*tblPayrollIncrementalSpend[2027 Incremental Spend]/(tblPayrollIncrementalSpend[Base Salary]+tblPayrollIncrementalSpend[Bonus]+tblPayrollIncrementalSpend[Payroll Taxes]+tblPayrollIncrementalSpend[Benefits]+tblPayrollIncrementalSpend[Vacation]+tblPayrollIncrementalSpend[Other]),0))} -> 0 | E82: {=SUMPRODUCT(IFERROR(tblPayrollIncrementalSpend[Bonus]*tblPayrollIncrementalSpend[2028 Incremental Spend]/(tblPayrollIncrementalSpend[Base Salary]+tblPayrollIncrementalSpend[Bonus]+tblPayrollIncrementalSpend[Payroll Taxes]+tblPayrollIncrementalSpend[Benefits]+tblPayrollIncrementalSpend[Vacation]+tblPayrollIncrementalSpend[Other]),0))} -> 0 | F82: {=SUMPRODUCT(IFERROR(tblPayrollIncrementalSpend[Bonus]*tblPayrollIncrementalSpend[2029 Incremental Spend]/(tblPayrollIncrementalSpend[Base Salary]+tblPayrollIncrementalSpend[Bonus]+tblPayrollIncrementalSpend[Payroll Taxes]+tblPayrollIncrementalSpend[Benefits]+tblPayrollIncrementalSpend[Vacation]+tblPayrollIncrementalSpend[Other]),0))} -> 0
B83: Essentials Bonus | D83: =SUMIF(tblNonPayrollIncrementalSpend[Type of Expense],$B83,tblNonPayrollIncrementalSpend[2027 Incremental Spend]) -> 0 | E83: =SUMIF(tblNonPayrollIncrementalSpend[Type of Expense],$B83,tblNonPayrollIncrementalSpend[2028 Incremental Spend]) -> 0 | F83: =SUMIF(tblNonPayrollIncrementalSpend[Type of Expense],$B83,tblNonPayrollIncrementalSpend[2029 Incremental Spend]) -> 0
B84: Payroll Taxes | D84: {=SUMPRODUCT(IFERROR(tblPayrollIncrementalSpend[Payroll Taxes]*tblPayrollIncrementalSpend[2027 Incremental Spend]/(tblPayrollIncrementalSpend[Base Salary]+tblPayrollIncrementalSpend[Bonus]+tblPayrollIncrementalSpend[Payroll Taxes]+tblPayrollIncrementalSpend[Benefits]+tblPayrollIncrementalSpend[Vacation]+tblPayrollIncrementalSpend[Other]),0))} -> 0 | E84: {=SUMPRODUCT(IFERROR(tblPayrollIncrementalSpend[Payroll Taxes]*tblPayrollIncrementalSpend[2028 Incremental Spend]/(tblPayrollIncrementalSpend[Base Salary]+tblPayrollIncrementalSpend[Bonus]+tblPayrollIncrementalSpend[Payroll Taxes]+tblPayrollIncrementalSpend[Benefits]+tblPayrollIncrementalSpend[Vacation]+tblPayrollIncrementalSpend[Other]),0))} -> 0 | F84: {=SUMPRODUCT(IFERROR(tblPayrollIncrementalSpend[Payroll Taxes]*tblPayrollIncrementalSpend[2029 Incremental Spend]/(tblPayrollIncrementalSpend[Base Salary]+tblPayrollIncrementalSpend[Bonus]+tblPayrollIncrementalSpend[Payroll Taxes]+tblPayrollIncrementalSpend[Benefits]+tblPayrollIncrementalSpend[Vacation]+tblPayrollIncrementalSpend[Other]),0))} -> 0
B85: Benefits | D85: {=SUMPRODUCT(IFERROR(tblPayrollIncrementalSpend[Benefits]*tblPayrollIncrementalSpend[2027 Incremental Spend]/(tblPayrollIncrementalSpend[Base Salary]+tblPayrollIncrementalSpend[Bonus]+tblPayrollIncrementalSpend[Payroll Taxes]+tblPayrollIncrementalSpend[Benefits]+tblPayrollIncrementalSpend[Vacation]+tblPayrollIncrementalSpend[Other]),0))} -> 0 | E85: {=SUMPRODUCT(IFERROR(tblPayrollIncrementalSpend[Benefits]*tblPayrollIncrementalSpend[2028 Incremental Spend]/(tblPayrollIncrementalSpend[Base Salary]+tblPayrollIncrementalSpend[Bonus]+tblPayrollIncrementalSpend[Payroll Taxes]+tblPayrollIncrementalSpend[Benefits]+tblPayrollIncrementalSpend[Vacation]+tblPayrollIncrementalSpend[Other]),0))} -> 0 | F85: {=SUMPRODUCT(IFERROR(tblPayrollIncrementalSpend[Benefits]*tblPayrollIncrementalSpend[2029 Incremental Spend]/(tblPayrollIncrementalSpend[Base Salary]+tblPayrollIncrementalSpend[Bonus]+tblPayrollIncrementalSpend[Payroll Taxes]+tblPayrollIncrementalSpend[Benefits]+tblPayrollIncrementalSpend[Vacation]+tblPayrollIncrementalSpend[Other]),0))} -> 0
B86: Vacation | D86: {=SUMPRODUCT(IFERROR(tblPayrollIncrementalSpend[Vacation]*tblPayrollIncrementalSpend[2027 Incremental Spend]/(tblPayrollIncrementalSpend[Base Salary]+tblPayrollIncrementalSpend[Bonus]+tblPayrollIncrementalSpend[Payroll Taxes]+tblPayrollIncrementalSpend[Benefits]+tblPayrollIncrementalSpend[Vacation]+tblPayrollIncrementalSpend[Other]),0))} -> 0 | E86: {=SUMPRODUCT(IFERROR(tblPayrollIncrementalSpend[Vacation]*tblPayrollIncrementalSpend[2028 Incremental Spend]/(tblPayrollIncrementalSpend[Base Salary]+tblPayrollIncrementalSpend[Bonus]+tblPayrollIncrementalSpend[Payroll Taxes]+tblPayrollIncrementalSpend[Benefits]+tblPayrollIncrementalSpend[Vacation]+tblPayrollIncrementalSpend[Other]),0))} -> 0 | F86: {=SUMPRODUCT(IFERROR(tblPayrollIncrementalSpend[Vacation]*tblPayrollIncrementalSpend[2029 Incremental Spend]/(tblPayrollIncrementalSpend[Base Salary]+tblPayrollIncrementalSpend[Bonus]+tblPayrollIncrementalSpend[Payroll Taxes]+tblPayrollIncrementalSpend[Benefits]+tblPayrollIncrementalSpend[Vacation]+tblPayrollIncrementalSpend[Other]),0))} -> 0
B87: Other | D87: {=SUMPRODUCT(IFERROR(tblPayrollIncrementalSpend[Other]*tblPayrollIncrementalSpend[2027 Incremental Spend]/(tblPayrollIncrementalSpend[Base Salary]+tblPayrollIncrementalSpend[Bonus]+tblPayrollIncrementalSpend[Payroll Taxes]+tblPayrollIncrementalSpend[Benefits]+tblPayrollIncrementalSpend[Vacation]+tblPayrollIncrementalSpend[Other]),0))} -> 0 | E87: {=SUMPRODUCT(IFERROR(tblPayrollIncrementalSpend[Other]*tblPayrollIncrementalSpend[2028 Incremental Spend]/(tblPayrollIncrementalSpend[Base Salary]+tblPayrollIncrementalSpend[Bonus]+tblPayrollIncrementalSpend[Payroll Taxes]+tblPayrollIncrementalSpend[Benefits]+tblPayrollIncrementalSpend[Vacation]+tblPayrollIncrementalSpend[Other]),0))} -> 0 | F87: {=SUMPRODUCT(IFERROR(tblPayrollIncrementalSpend[Other]*tblPayrollIncrementalSpend[2029 Incremental Spend]/(tblPayrollIncrementalSpend[Base Salary]+tblPayrollIncrementalSpend[Bonus]+tblPayrollIncrementalSpend[Payroll Taxes]+tblPayrollIncrementalSpend[Benefits]+tblPayrollIncrementalSpend[Vacation]+tblPayrollIncrementalSpend[Other]),0))} -> 0
B88: Contract Labor | D88: =SUMIF(tblNonPayrollIncrementalSpend[Type of Expense],$B88,tblNonPayrollIncrementalSpend[2027 Incremental Spend]) -> 0 | E88: =SUMIF(tblNonPayrollIncrementalSpend[Type of Expense],$B88,tblNonPayrollIncrementalSpend[2028 Incremental Spend]) -> 0 | F88: =SUMIF(tblNonPayrollIncrementalSpend[Type of Expense],$B88,tblNonPayrollIncrementalSpend[2029 Incremental Spend]) -> 0
B89: LTIP Compensation | D89: =SUMIF(tblNonPayrollIncrementalSpend[Type of Expense],$B89,tblNonPayrollIncrementalSpend[2027 Incremental Spend]) -> 0 | E89: =SUMIF(tblNonPayrollIncrementalSpend[Type of Expense],$B89,tblNonPayrollIncrementalSpend[2028 Incremental Spend]) -> 0 | F89: =SUMIF(tblNonPayrollIncrementalSpend[Type of Expense],$B89,tblNonPayrollIncrementalSpend[2029 Incremental Spend]) -> 0
B90: Incremental Payroll | D90: =SUM(D81:D89) -> 0 | E90: =SUM(E81:E89) -> 0 | F90: =SUM(F81:F89) -> 0
B92: Professional Fees | D92: =SUMIF('Investment Case Asks - Summary'!$B$28:$B$42,$B92,'Investment Case Asks - Summary'!$D$28:$D$42) -> 0 | E92: =SUMIF('Investment Case Asks - Summary'!$B$28:$B$42,$B92,'Investment Case Asks - Summary'!$E$28:$E$42) -> 0 | F92: =SUMIF('Investment Case Asks - Summary'!$B$28:$B$42,$B92,'Investment Case Asks - Summary'!$F$28:$F$42) -> 0
B93: Occupancy | D93: =SUMIF('Investment Case Asks - Summary'!$B$28:$B$42,$B93,'Investment Case Asks - Summary'!$D$28:$D$42) -> 0 | E93: =SUMIF('Investment Case Asks - Summary'!$B$28:$B$42,$B93,'Investment Case Asks - Summary'!$E$28:$E$42) -> 0 | F93: =SUMIF('Investment Case Asks - Summary'!$B$28:$B$42,$B93,'Investment Case Asks - Summary'!$F$28:$F$42) -> 0
B94: Office Expenses | D94: =SUMIF('Investment Case Asks - Summary'!$B$28:$B$42,$B94,'Investment Case Asks - Summary'!$D$28:$D$42) -> 0 | E94: =SUMIF('Investment Case Asks - Summary'!$B$28:$B$42,$B94,'Investment Case Asks - Summary'!$E$28:$E$42) -> 0 | F94: =SUMIF('Investment Case Asks - Summary'!$B$28:$B$42,$B94,'Investment Case Asks - Summary'!$F$28:$F$42) -> 0
B95: IT Costs | D95: =SUMIF('Investment Case Asks - Summary'!$B$28:$B$42,$B95,'Investment Case Asks - Summary'!$D$28:$D$42) -> 0 | E95: =SUMIF('Investment Case Asks - Summary'!$B$28:$B$42,$B95,'Investment Case Asks - Summary'!$E$28:$E$42) -> 0 | F95: =SUMIF('Investment Case Asks - Summary'!$B$28:$B$42,$B95,'Investment Case Asks - Summary'!$F$28:$F$42) -> 0
B96: Marketing and Presentation | D96: =SUMIF('Investment Case Asks - Summary'!$B$28:$B$42,$B96,'Investment Case Asks - Summary'!$D$28:$D$42) -> 0 | E96: =SUMIF('Investment Case Asks - Summary'!$B$28:$B$42,$B96,'Investment Case Asks - Summary'!$E$28:$E$42) -> 0 | F96: =SUMIF('Investment Case Asks - Summary'!$B$28:$B$42,$B96,'Investment Case Asks - Summary'!$F$28:$F$42) -> 0
B97: Travel and Entertainment | D97: =SUMIF('Investment Case Asks - Summary'!$B$28:$B$42,$B97,'Investment Case Asks - Summary'!$D$28:$D$42) -> 0 | E97: =SUMIF('Investment Case Asks - Summary'!$B$28:$B$42,$B97,'Investment Case Asks - Summary'!$E$28:$E$42) -> 0 | F97: =SUMIF('Investment Case Asks - Summary'!$B$28:$B$42,$B97,'Investment Case Asks - Summary'!$F$28:$F$42) -> 0
B98: Employee events | D98: =SUMIF('Investment Case Asks - Summary'!$B$28:$B$42,$B98,'Investment Case Asks - Summary'!$D$28:$D$42) -> 0 | E98: =SUMIF('Investment Case Asks - Summary'!$B$28:$B$42,$B98,'Investment Case Asks - Summary'!$E$28:$E$42) -> 0 | F98: =SUMIF('Investment Case Asks - Summary'!$B$28:$B$42,$B98,'Investment Case Asks - Summary'!$F$28:$F$42) -> 0
B99: Insurance Non Property | D99: =SUMIF('Investment Case Asks - Summary'!$B$28:$B$42,$B99,'Investment Case Asks - Summary'!$D$28:$D$42) -> 0 | E99: =SUMIF('Investment Case Asks - Summary'!$B$28:$B$42,$B99,'Investment Case Asks - Summary'!$E$28:$E$42) -> 0 | F99: =SUMIF('Investment Case Asks - Summary'!$B$28:$B$42,$B99,'Investment Case Asks - Summary'!$F$28:$F$42) -> 0
B100: Licenses | D100: =SUMIF('Investment Case Asks - Summary'!$B$28:$B$42,$B100,'Investment Case Asks - Summary'!$D$28:$D$42) -> 0 | E100: =SUMIF('Investment Case Asks - Summary'!$B$28:$B$42,$B100,'Investment Case Asks - Summary'!$E$28:$E$42) -> 0 | F100: =SUMIF('Investment Case Asks - Summary'!$B$28:$B$42,$B100,'Investment Case Asks - Summary'!$F$28:$F$42) -> 0
B101: Recruiting and Relocation | D101: =SUMIF('Investment Case Asks - Summary'!$B$28:$B$42,$B101,'Investment Case Asks - Summary'!$D$28:$D$42) -> 0 | E101: =SUMIF('Investment Case Asks - Summary'!$B$28:$B$42,$B101,'Investment Case Asks - Summary'!$E$28:$E$42) -> 0 | F101: =SUMIF('Investment Case Asks - Summary'!$B$28:$B$42,$B101,'Investment Case Asks - Summary'!$F$28:$F$42) -> 0
B102: Seminars and Training | D102: =SUMIF('Investment Case Asks - Summary'!$B$28:$B$42,$B102,'Investment Case Asks - Summary'!$D$28:$D$42) -> 0 | E102: =SUMIF('Investment Case Asks - Summary'!$B$28:$B$42,$B102,'Investment Case Asks - Summary'!$E$28:$E$42) -> 0 | F102: =SUMIF('Investment Case Asks - Summary'!$B$28:$B$42,$B102,'Investment Case Asks - Summary'!$F$28:$F$42) -> 0
B103: Shareholder Relations | D103: =SUMIF('Investment Case Asks - Summary'!$B$28:$B$42,$B103,'Investment Case Asks - Summary'!$D$28:$D$42) -> 0 | E103: =SUMIF('Investment Case Asks - Summary'!$B$28:$B$42,$B103,'Investment Case Asks - Summary'!$E$28:$E$42) -> 0 | F103: =SUMIF('Investment Case Asks - Summary'!$B$28:$B$42,$B103,'Investment Case Asks - Summary'!$F$28:$F$42) -> 0
... B112: Allocated IT & Office Contra | D112: =SUMIF('Investment Case Asks - Summary'!$B$28:$B$42,$B112,'Investment Case Asks - Summary'!$D$28:$D$42) -> 0 | E112: =SUMIF('Investment Case Asks - Summary'!$B$28:$B$42,$B112,'Investment Case Asks - Summary'!$E$28:$E$42) -> 0 | F112: =SUMIF('Investment Case Asks - Summary'!$B$28:$B$42,$B112,'Investment Case Asks - Summary'!$F$28:$F$42) -> 0
B113: Incremental Non-Payroll | D113: =SUM(D92:D112) -> 0 | E113: =SUM(E92:E112) -> 0 | F113: =SUM(F92:F112) -> 0
B115: Total | D115: =D90+D113 -> 0 | E115: =E90+E113 -> 0 | F115: =F90+F113 -> 0

Sheet Investment Case Asks - Summary
A1: Investment Case Asks - Incremental Spend Input
A3: Payroll / Headcount Incremental Spend | T3: Incremental Spend Summary
A4: Job Title | B4: Job Level | C4: Role / Hire | D4: Location (City/Country) | E4: Key Job Responsibilities | F4: Hire Date | G4: Base Salary | H4: Bonus % | I4: Bonus | J4: Payroll Taxes | K4: Benefits | L4: Vacation | M4: Other | N4: Annualized Spend | O4: 2027 Incremental Spend | P4: 2028 Incremental Spend | Q4: 2029 Incremental Spend | R4: Notes / Rationale | T4: Spend Type | U4: 2027 | V4: 2028 | W4: 2029
A5: =IFERROR(IF('Investment Case Asks - Monthly'!A5="","",'Investment Case Asks - Monthly'!A5),"") | B5: =IFERROR(IF('Investment Case Asks - Monthly'!B5="","",'Investment Case Asks - Monthly'!B5),"") | C5: =IFERROR(IF('Investment Case Asks - Monthly'!C5="","",'Investment Case Asks - Monthly'!C5),"") | D5: =IFERROR(IF('Investment Case Asks - Monthly'!D5="","",'Investment Case Asks - Monthly'!D5),"") | E5: =IFERROR(IF('Investment Case Asks - Monthly'!E5="","",'Investment Case Asks - Monthly'!E5),"") | F5: =IFERROR(IF('Investment Case Asks - Monthly'!F5="","",'Investment Case Asks - Monthly'!F5),"") | G5: =IFERROR(IF('Investment Case Asks - Monthly'!G5="","",'Investment Case Asks - Monthly'!G5),"") | H5: =IFERROR(IF('Investment Case Asks - Monthly'!H5="","",'Investment Case Asks - Monthly'!H5),"") | ... N5: =IFERROR(IF('Investment Case Asks - Monthly'!N5="","",'Investment Case Asks - Monthly'!N5),"") | O5: =IFERROR(IF('Investment Case Asks - Monthly'!AA5="","",'Investment Case Asks - Monthly'!AA5),"") | P5: =IFERROR(IF('Investment Case Asks - Monthly'!AN5="","",'Investment Case Asks - Monthly'!AN5),"") | Q5: =IFERROR(IF('Investment Case Asks - Monthly'!BA5="","",'Investment Case Asks - Monthly'!BA5),"") | R5: =IFERROR(IF('Investment Case Asks - Monthly'!BB5="","",'Investment Case Asks - Monthly'!BB5),"") | T5: Payroll / Headcount | U5: =O22 -> 0 | V5: =P22 -> 0 | W5: =Q22 -> 0
A6: =IFERROR(IF('Investment Case Asks - Monthly'!A6="","",'Investment Case Asks - Monthly'!A6),"") | B6: =IFERROR(IF('Investment Case Asks - Monthly'!B6="","",'Investment Case Asks - Monthly'!B6),"") | C6: =IFERROR(IF('Investment Case Asks - Monthly'!C6="","",'Investment Case Asks - Monthly'!C6),"") | D6: =IFERROR(IF('Investment Case Asks - Monthly'!D6="","",'Investment Case Asks - Monthly'!D6),"") | E6: =IFERROR(IF('Investment Case Asks - Monthly'!E6="","",'Investment Case Asks - Monthly'!E6),"") | F6: =IFERROR(IF('Investment Case Asks - Monthly'!F6="","",'Investment Case Asks - Monthly'!F6),"") | G6: =IFERROR(IF('Investment Case Asks - Monthly'!G6="","",'Investment Case Asks - Monthly'!G6),"") | H6: =IFERROR(IF('Investment Case Asks - Monthly'!H6="","",'Investment Case Asks - Monthly'!H6),"") | ... N6: =IFERROR(IF('Investment Case Asks - Monthly'!N6="","",'Investment Case Asks - Monthly'!N6),"") | O6: =IFERROR(IF('Investment Case Asks - Monthly'!AA6="","",'Investment Case Asks - Monthly'!AA6),"") | P6: =IFERROR(IF('Investment Case Asks - Monthly'!AN6="","",'Investment Case Asks - Monthly'!AN6),"") | Q6: =IFERROR(IF('Investment Case Asks - Monthly'!BA6="","",'Investment Case Asks - Monthly'!BA6),"") | R6: =IFERROR(IF('Investment Case Asks - Monthly'!BB6="","",'Investment Case Asks - Monthly'!BB6),"") | T6: Non-Payroll | U6: =D44 -> 0 | V6: =E44 -> 0 | W6: =F44 -> 0
A7: =IFERROR(IF('Investment Case Asks - Monthly'!A7="","",'Investment Case Asks - Monthly'!A7),"") | B7: =IFERROR(IF('Investment Case Asks - Monthly'!B7="","",'Investment Case Asks - Monthly'!B7),"") | C7: =IFERROR(IF('Investment Case Asks - Monthly'!C7="","",'Investment Case Asks - Monthly'!C7),"") | D7: =IFERROR(IF('Investment Case Asks - Monthly'!D7="","",'Investment Case Asks - Monthly'!D7),"") | E7: =IFERROR(IF('Investment Case Asks - Monthly'!E7="","",'Investment Case Asks - Monthly'!E7),"") | F7: =IFERROR(IF('Investment Case Asks - Monthly'!F7="","",'Investment Case Asks - Monthly'!F7),"") | G7: =IFERROR(IF('Investment Case Asks - Monthly'!G7="","",'Investment Case Asks - Monthly'!G7),"") | H7: =IFERROR(IF('Investment Case Asks - Monthly'!H7="","",'Investment Case Asks - Monthly'!H7),"") | ... N7: =IFERROR(IF('Investment Case Asks - Monthly'!N7="","",'Investment Case Asks - Monthly'!N7),"") | O7: =IFERROR(IF('Investment Case Asks - Monthly'!AA7="","",'Investment Case Asks - Monthly'!AA7),"") | P7: =IFERROR(IF('Investment Case Asks - Monthly'!AN7="","",'Investment Case Asks - Monthly'!AN7),"") | Q7: =IFERROR(IF('Investment Case Asks - Monthly'!BA7="","",'Investment Case Asks - Monthly'!BA7),"") | R7: =IFERROR(IF('Investment Case Asks - Monthly'!BB7="","",'Investment Case Asks - Monthly'!BB7),"") | T7: Total Incremental Spend | U7: =SUM(U5:U6) -> 0 | V7: =SUM(V5:V6) -> 0 | W7: =SUM(W5:W6) -> 0
A8: =IFERROR(IF('Investment Case Asks - Monthly'!A8="","",'Investment Case Asks - Monthly'!A8),"") | B8: =IFERROR(IF('Investment Case Asks - Monthly'!B8="","",'Investment Case Asks - Monthly'!B8),"") | C8: =IFERROR(IF('Investment Case Asks - Monthly'!C8="","",'Investment Case Asks - Monthly'!C8),"") | D8: =IFERROR(IF('Investment Case Asks - Monthly'!D8="","",'Investment Case Asks - Monthly'!D8),"") | E8: =IFERROR(IF('Investment Case Asks - Monthly'!E8="","",'Investment Case Asks - Monthly'!E8),"") | F8: =IFERROR(IF('Investment Case Asks - Monthly'!F8="","",'Investment Case Asks - Monthly'!F8),"") | G8: =IFERROR(IF('Investment Case Asks - Monthly'!G8="","",'Investment Case Asks - Monthly'!G8),"") | H8: =IFERROR(IF('Investment Case Asks - Monthly'!H8="","",'Investment Case Asks - Monthly'!H8),"") | ... N8: =IFERROR(IF('Investment Case Asks - Monthly'!N8="","",'Investment Case Asks - Monthly'!N8),"") | O8: =IFERROR(IF('Investment Case Asks - Monthly'!AA8="","",'Investment Case Asks - Monthly'!AA8),"") | P8: =IFERROR(IF('Investment Case Asks - Monthly'!AN8="","",'Investment Case Asks - Monthly'!AN8),"") | Q8: =IFERROR(IF('Investment Case Asks - Monthly'!BA8="","",'Investment Case Asks - Monthly'!BA8),"") | R8: =IFERROR(IF('Investment Case Asks - Monthly'!BB8="","",'Investment Case Asks - Monthly'!BB8),"")
A9: =IFERROR(IF('Investment Case Asks - Monthly'!A9="","",'Investment Case Asks - Monthly'!A9),"") | B9: =IFERROR(IF('Investment Case Asks - Monthly'!B9="","",'Investment Case Asks - Monthly'!B9),"") | C9: =IFERROR(IF('Investment Case Asks - Monthly'!C9="","",'Investment Case Asks - Monthly'!C9),"") | D9: =IFERROR(IF('Investment Case Asks - Monthly'!D9="","",'Investment Case Asks - Monthly'!D9),"") | E9: =IFERROR(IF('Investment Case Asks - Monthly'!E9="","",'Investment Case Asks - Monthly'!E9),"") | F9: =IFERROR(IF('Investment Case Asks - Monthly'!F9="","",'Investment Case Asks - Monthly'!F9),"") | G9: =IFERROR(IF('Investment Case Asks - Monthly'!G9="","",'Investment Case Asks - Monthly'!G9),"") | H9: =IFERROR(IF('Investment Case Asks - Monthly'!H9="","",'Investment Case Asks - Monthly'!H9),"") | ... N9: =IFERROR(IF('Investment Case Asks - Monthly'!N9="","",'Investment Case Asks - Monthly'!N9),"") | O9: =IFERROR(IF('Investment Case Asks - Monthly'!AA9="","",'Investment Case Asks - Monthly'!AA9),"") | P9: =IFERROR(IF('Investment Case Asks - Monthly'!AN9="","",'Investment Case Asks - Monthly'!AN9),"") | Q9: =IFERROR(IF('Investment Case Asks - Monthly'!BA9="","",'Investment Case Asks - Monthly'!BA9),"") | R9: =IFERROR(IF('Investment Case Asks - Monthly'!BB9="","",'Investment Case Asks - Monthly'!BB9),"")
A10: =IFERROR(IF('Investment Case Asks - Monthly'!A10="","",'Investment Case Asks - Monthly'!A10),"") | B10: =IFERROR(IF('Investment Case Asks - Monthly'!B10="","",'Investment Case Asks - Monthly'!B10),"") | C10: =IFERROR(IF('Investment Case Asks - Monthly'!C10="","",'Investment Case Asks - Monthly'!C10),"") | D10: =IFERROR(IF('Investment Case Asks - Monthly'!D10="","",'Investment Case Asks - Monthly'!D10),"") | E10: =IFERROR(IF('Investment Case Asks - Monthly'!E10="","",'Investment Case Asks - Monthly'!E10),"") | F10: =IFERROR(IF('Investment Case Asks - Monthly'!F10="","",'Investment Case Asks - Monthly'!F10),"") | G10: =IFERROR(IF('Investment Case Asks - Monthly'!G10="","",'Investment Case Asks - Monthly'!G10),"") | H10: =IFERROR(IF('Investment Case Asks - Monthly'!H10="","",'Investment Case Asks - Monthly'!H10),"") | ... N10: =IFERROR(IF('Investment Case Asks - Monthly'!N10="","",'Investment Case Asks - Monthly'!N10),"") | O10: =IFERROR(IF('Investment Case Asks - Monthly'!AA10="","",'Investment Case Asks - Monthly'!AA10),"") | P10: =IFERROR(IF('Investment Case Asks - Monthly'!AN10="","",'Investment Case Asks - Monthly'!AN10),"") | Q10: =IFERROR(IF('Investment Case Asks - Monthly'!BA10="","",'Investment Case Asks - Monthly'!BA10),"") | R10: =IFERROR(IF('Investment Case Asks - Monthly'!BB10="","",'Investment Case Asks - Monthly'!BB10),"")
A11: =IFERROR(IF('Investment Case Asks - Monthly'!A11="","",'Investment Case Asks - Monthly'!A11),"") | B11: =IFERROR(IF('Investment Case Asks - Monthly'!B11="","",'Investment Case Asks - Monthly'!B11),"") | C11: =IFERROR(IF('Investment Case Asks - Monthly'!C11="","",'Investment Case Asks - Monthly'!C11),"") | D11: =IFERROR(IF('Investment Case Asks - Monthly'!D11="","",'Investment Case Asks - Monthly'!D11),"") | E11: =IFERROR(IF('Investment Case Asks - Monthly'!E11="","",'Investment Case Asks - Monthly'!E11),"") | F11: =IFERROR(IF('Investment Case Asks - Monthly'!F11="","",'Investment Case Asks - Monthly'!F11),"") | G11: =IFERROR(IF('Investment Case Asks - Monthly'!G11="","",'Investment Case Asks - Monthly'!G11),"") | H11: =IFERROR(IF('Investment Case Asks - Monthly'!H11="","",'Investment Case Asks - Monthly'!H11),"") | ... N11: =IFERROR(IF('Investment Case Asks - Monthly'!N11="","",'Investment Case Asks - Monthly'!N11),"") | O11: =IFERROR(IF('Investment Case Asks - Monthly'!AA11="","",'Investment Case Asks - Monthly'!AA11),"") | P11: =IFERROR(IF('Investment Case Asks - Monthly'!AN11="","",'Investment Case Asks - Monthly'!AN11),"") | Q11: =IFERROR(IF('Investment Case Asks - Monthly'!BA11="","",'Investment Case Asks - Monthly'!BA11),"") | R11: =IFERROR(IF('Investment Case Asks - Monthly'!BB11="","",'Investment Case Asks - Monthly'!BB11),"")
A12: =IFERROR(IF('Investment Case Asks - Monthly'!A12="","",'Investment Case Asks - Monthly'!A12),"") | B12: =IFERROR(IF('Investment Case Asks - Monthly'!B12="","",'Investment Case Asks - Monthly'!B12),"") | C12: =IFERROR(IF('Investment Case Asks - Monthly'!C12="","",'Investment Case Asks - Monthly'!C12),"") | D12: =IFERROR(IF('Investment Case Asks - Monthly'!D12="","",'Investment Case Asks - Monthly'!D12),"") | E12: =IFERROR(IF('Investment Case Asks - Monthly'!E12="","",'Investment Case Asks - Monthly'!E12),"") | F12: =IFERROR(IF('Investment Case Asks - Monthly'!F12="","",'Investment Case Asks - Monthly'!F12),"") | G12: =IFERROR(IF('Investment Case Asks - Monthly'!G12="","",'Investment Case Asks - Monthly'!G12),"") | H12: =IFERROR(IF('Investment Case Asks - Monthly'!H12="","",'Investment Case Asks - Monthly'!H12),"") | ... N12: =IFERROR(IF('Investment Case Asks - Monthly'!N12="","",'Investment Case Asks - Monthly'!N12),"") | O12: =IFERROR(IF('Investment Case Asks - Monthly'!AA12="","",'Investment Case Asks - Monthly'!AA12),"") | P12: =IFERROR(IF('Investment Case Asks - Monthly'!AN12="","",'Investment Case Asks - Monthly'!AN12),"") | Q12: =IFERROR(IF('Investment Case Asks - Monthly'!BA12="","",'Investment Case Asks - Monthly'!BA12),"") | R12: =IFERROR(IF('Investment Case Asks - Monthly'!BB12="","",'Investment Case Asks - Monthly'!BB12),"")
A13: =IFERROR(IF('Investment Case Asks - Monthly'!A13="","",'Investment Case Asks - Monthly'!A13),"") | B13: =IFERROR(IF('Investment Case Asks - Monthly'!B13="","",'Investment Case Asks - Monthly'!B13),"") | C13: =IFERROR(IF('Investment Case Asks - Monthly'!C13="","",'Investment Case Asks - Monthly'!C13),"") | D13: =IFERROR(IF('Investment Case Asks - Monthly'!D13="","",'Investment Case Asks - Monthly'!D13),"") | E13: =IFERROR(IF('Investment Case Asks - Monthly'!E13="","",'Investment Case Asks - Monthly'!E13),"") | F13: =IFERROR(IF('Investment Case Asks - Monthly'!F13="","",'Investment Case Asks - Monthly'!F13),"") | G13: =IFERROR(IF('Investment Case Asks - Monthly'!G13="","",'Investment Case Asks - Monthly'!G13),"") | H13: =IFERROR(IF('Investment Case Asks - Monthly'!H13="","",'Investment Case Asks - Monthly'!H13),"") | ... N13: =IFERROR(IF('Investment Case Asks - Monthly'!N13="","",'Investment Case Asks - Monthly'!N13),"") | O13: =IFERROR(IF('Investment Case Asks - Monthly'!AA13="","",'Investment Case Asks - Monthly'!AA13),"") | P13: =IFERROR(IF('Investment Case Asks - Monthly'!AN13="","",'Investment Case Asks - Monthly'!AN13),"") | Q13: =IFERROR(IF('Investment Case Asks - Monthly'!BA13="","",'Investment Case Asks - Monthly'!BA13),"") | R13: =IFERROR(IF('Investment Case Asks - Monthly'!BB13="","",'Investment Case Asks - Monthly'!BB13),"")
A14: =IFERROR(IF('Investment Case Asks - Monthly'!A14="","",'Investment Case Asks - Monthly'!A14),"") | B14: =IFERROR(IF('Investment Case Asks - Monthly'!B14="","",'Investment Case Asks - Monthly'!B14),"") | C14: =IFERROR(IF('Investment Case Asks - Monthly'!C14="","",'Investment Case Asks - Monthly'!C14),"") | D14: =IFERROR(IF('Investment Case Asks - Monthly'!D14="","",'Investment Case Asks - Monthly'!D14),"") | E14: =IFERROR(IF('Investment Case Asks - Monthly'!E14="","",'Investment Case Asks - Monthly'!E14),"") | F14: =IFERROR(IF('Investment Case Asks - Monthly'!F14="","",'Investment Case Asks - Monthly'!F14),"") | G14: =IFERROR(IF('Investment Case Asks - Monthly'!G14="","",'Investment Case Asks - Monthly'!G14),"") | H14: =IFERROR(IF('Investment Case Asks - Monthly'!H14="","",'Investment Case Asks - Monthly'!H14),"") | ... N14: =IFERROR(IF('Investment Case Asks - Monthly'!N14="","",'Investment Case Asks - Monthly'!N14),"") | O14: =IFERROR(IF('Investment Case Asks - Monthly'!AA14="","",'Investment Case Asks - Monthly'!AA14),"") | P14: =IFERROR(IF('Investment Case Asks - Monthly'!AN14="","",'Investment Case Asks - Monthly'!AN14),"") | Q14: =IFERROR(IF('Investment Case Asks - Monthly'!BA14="","",'Investment Case Asks - Monthly'!BA14),"") | R14: =IFERROR(IF('Investment Case Asks - Monthly'!BB14="","",'Investment Case Asks - Monthly'!BB14),"")
A15: =IFERROR(IF('Investment Case Asks - Monthly'!A15="","",'Investment Case Asks - Monthly'!A15),"") | B15: =IFERROR(IF('Investment Case Asks - Monthly'!B15="","",'Investment Case Asks - Monthly'!B15),"") | C15: =IFERROR(IF('Investment Case Asks - Monthly'!C15="","",'Investment Case Asks - Monthly'!C15),"") | D15: =IFERROR(IF('Investment Case Asks - Monthly'!D15="","",'Investment Case Asks - Monthly'!D15),"") | E15: =IFERROR(IF('Investment Case Asks - Monthly'!E15="","",'Investment Case Asks - Monthly'!E15),"") | F15: =IFERROR(IF('Investment Case Asks - Monthly'!F15="","",'Investment Case Asks - Monthly'!F15),"") | G15: =IFERROR(IF('Investment Case Asks - Monthly'!G15="","",'Investment Case Asks - Monthly'!G15),"") | H15: =IFERROR(IF('Investment Case Asks - Monthly'!H15="","",'Investment Case Asks - Monthly'!H15),"") | ... N15: =IFERROR(IF('Investment Case Asks - Monthly'!N15="","",'Investment Case Asks - Monthly'!N15),"") | O15: =IFERROR(IF('Investment Case Asks - Monthly'!AA15="","",'Investment Case Asks - Monthly'!AA15),"") | P15: =IFERROR(IF('Investment Case Asks - Monthly'!AN15="","",'Investment Case Asks - Monthly'!AN15),"") | Q15: =IFERROR(IF('Investment Case Asks - Monthly'!BA15="","",'Investment Case Asks - Monthly'!BA15),"") | R15: =IFERROR(IF('Investment Case Asks - Monthly'!BB15="","",'Investment Case Asks - Monthly'!BB15),"")
A16: =IFERROR(IF('Investment Case Asks - Monthly'!A16="","",'Investment Case Asks - Monthly'!A16),"") | B16: =IFERROR(IF('Investment Case Asks - Monthly'!B16="","",'Investment Case Asks - Monthly'!B16),"") | C16: =IFERROR(IF('Investment Case Asks - Monthly'!C16="","",'Investment Case Asks - Monthly'!C16),"") | D16: =IFERROR(IF('Investment Case Asks - Monthly'!D16="","",'Investment Case Asks - Monthly'!D16),"") | E16: =IFERROR(IF('Investment Case Asks - Monthly'!E16="","",'Investment Case Asks - Monthly'!E16),"") | F16: =IFERROR(IF('Investment Case Asks - Monthly'!F16="","",'Investment Case Asks - Monthly'!F16),"") | G16: =IFERROR(IF('Investment Case Asks - Monthly'!G16="","",'Investment Case Asks - Monthly'!G16),"") | H16: =IFERROR(IF('Investment Case Asks - Monthly'!H16="","",'Investment Case Asks - Monthly'!H16),"") | ... N16: =IFERROR(IF('Investment Case Asks - Monthly'!N16="","",'Investment Case Asks - Monthly'!N16),"") | O16: =IFERROR(IF('Investment Case Asks - Monthly'!AA16="","",'Investment Case Asks - Monthly'!AA16),"") | P16: =IFERROR(IF('Investment Case Asks - Monthly'!AN16="","",'Investment Case Asks - Monthly'!AN16),"") | Q16: =IFERROR(IF('Investment Case Asks - Monthly'!BA16="","",'Investment Case Asks - Monthly'!BA16),"") | R16: =IFERROR(IF('Investment Case Asks - Monthly'!BB16="","",'Investment Case Asks - Monthly'!BB16),"")
A17: =IFERROR(IF('Investment Case Asks - Monthly'!A17="","",'Investment Case Asks - Monthly'!A17),"") | B17: =IFERROR(IF('Investment Case Asks - Monthly'!B17="","",'Investment Case Asks - Monthly'!B17),"") | C17: =IFERROR(IF('Investment Case Asks - Monthly'!C17="","",'Investment Case Asks - Monthly'!C17),"") | D17: =IFERROR(IF('Investment Case Asks - Monthly'!D17="","",'Investment Case Asks - Monthly'!D17),"") | E17: =IFERROR(IF('Investment Case Asks - Monthly'!E17="","",'Investment Case Asks - Monthly'!E17),"") | F17: =IFERROR(IF('Investment Case Asks - Monthly'!F17="","",'Investment Case Asks - Monthly'!F17),"") | G17: =IFERROR(IF('Investment Case Asks - Monthly'!G17="","",'Investment Case Asks - Monthly'!G17),"") | H17: =IFERROR(IF('Investment Case Asks - Monthly'!H17="","",'Investment Case Asks - Monthly'!H17),"") | ... N17: =IFERROR(IF('Investment Case Asks - Monthly'!N17="","",'Investment Case Asks - Monthly'!N17),"") | O17: =IFERROR(IF('Investment Case Asks - Monthly'!AA17="","",'Investment Case Asks - Monthly'!AA17),"") | P17: =IFERROR(IF('Investment Case Asks - Monthly'!AN17="","",'Investment Case Asks - Monthly'!AN17),"") | Q17: =IFERROR(IF('Investment Case Asks - Monthly'!BA17="","",'Investment Case Asks - Monthly'!BA17),"") | R17: =IFERROR(IF('Investment Case Asks - Monthly'!BB17="","",'Investment Case Asks - Monthly'!BB17),"")
A18: =IFERROR(IF('Investment Case Asks - Monthly'!A18="","",'Investment Case Asks - Monthly'!A18),"") | B18: =IFERROR(IF('Investment Case Asks - Monthly'!B18="","",'Investment Case Asks - Monthly'!B18),"") | C18: =IFERROR(IF('Investment Case Asks - Monthly'!C18="","",'Investment Case Asks - Monthly'!C18),"") | D18: =IFERROR(IF('Investment Case Asks - Monthly'!D18="","",'Investment Case Asks - Monthly'!D18),"") | E18: =IFERROR(IF('Investment Case Asks - Monthly'!E18="","",'Investment Case Asks - Monthly'!E18),"") | F18: =IFERROR(IF('Investment Case Asks - Monthly'!F18="","",'Investment Case Asks - Monthly'!F18),"") | G18: =IFERROR(IF('Investment Case Asks - Monthly'!G18="","",'Investment Case Asks - Monthly'!G18),"") | H18: =IFERROR(IF('Investment Case Asks - Monthly'!H18="","",'Investment Case Asks - Monthly'!H18),"") | ... N18: =IFERROR(IF('Investment Case Asks - Monthly'!N18="","",'Investment Case Asks - Monthly'!N18),"") | O18: =IFERROR(IF('Investment Case Asks - Monthly'!AA18="","",'Investment Case Asks - Monthly'!AA18),"") | P18: =IFERROR(IF('Investment Case Asks - Monthly'!AN18="","",'Investment Case Asks - Monthly'!AN18),"") | Q18: =IFERROR(IF('Investment Case Asks - Monthly'!BA18="","",'Investment Case Asks - Monthly'!BA18),"") | R18: =IFERROR(IF('Investment Case Asks - Monthly'!BB18="","",'Investment Case Asks - Monthly'!BB18),"")
A19: =IFERROR(IF('Investment Case Asks - Monthly'!A19="","",'Investment Case Asks - Monthly'!A19),"") | B19: =IFERROR(IF('Investment Case Asks - Monthly'!B19="","",'Investment Case Asks - Monthly'!B19),"") | C19: =IFERROR(IF('Investment Case Asks - Monthly'!C19="","",'Investment Case Asks - Monthly'!C19),"") | D19: =IFERROR(IF('Investment Case Asks - Monthly'!D19="","",'Investment Case Asks - Monthly'!D19),"") | E19: =IFERROR(IF('Investment Case Asks - Monthly'!E19="","",'Investment Case Asks - Monthly'!E19),"") | F19: =IFERROR(IF('Investment Case Asks - Monthly'!F19="","",'Investment Case Asks - Monthly'!F19),"") | G19: =IFERROR(IF('Investment Case Asks - Monthly'!G19="","",'Investment Case Asks - Monthly'!G19),"") | H19: =IFERROR(IF('Investment Case Asks - Monthly'!H19="","",'Investment Case Asks - Monthly'!H19),"") | ... N19: =IFERROR(IF('Investment Case Asks - Monthly'!N19="","",'Investment Case Asks - Monthly'!N19),"") | O19: =IFERROR(IF('Investment Case Asks - Monthly'!AA19="","",'Investment Case Asks - Monthly'!AA19),"") | P19: =IFERROR(IF('Investment Case Asks - Monthly'!AN19="","",'Investment Case Asks - Monthly'!AN19),"") | Q19: =IFERROR(IF('Investment Case Asks - Monthly'!BA19="","",'Investment Case Asks - Monthly'!BA19),"") | R19: =IFERROR(IF('Investment Case Asks - Monthly'!BB19="","",'Investment Case Asks - Monthly'!BB19),"")
A20: =IFERROR(IF('Investment Case Asks - Monthly'!A20="","",'Investment Case Asks - Monthly'!A20),"") | B20: =IFERROR(IF('Investment Case Asks - Monthly'!B20="","",'Investment Case Asks - Monthly'!B20),"") | C20: =IFERROR(IF('Investment Case Asks - Monthly'!C20="","",'Investment Case Asks - Monthly'!C20),"") | D20: =IFERROR(IF('Investment Case Asks - Monthly'!D20="","",'Investment Case Asks - Monthly'!D20),"") | E20: =IFERROR(IF('Investment Case Asks - Monthly'!E20="","",'Investment Case Asks - Monthly'!E20),"") | F20: =IFERROR(IF('Investment Case Asks - Monthly'!F20="","",'Investment Case Asks - Monthly'!F20),"") | G20: =IFERROR(IF('Investment Case Asks - Monthly'!G20="","",'Investment Case Asks - Monthly'!G20),"") | H20: =IFERROR(IF('Investment Case Asks - Monthly'!H20="","",'Investment Case Asks - Monthly'!H20),"") | ... N20: =IFERROR(IF('Investment Case Asks - Monthly'!N20="","",'Investment Case Asks - Monthly'!N20),"") | O20: =IFERROR(IF('Investment Case Asks - Monthly'!AA20="","",'Investment Case Asks - Monthly'!AA20),"") | P20: =IFERROR(IF('Investment Case Asks - Monthly'!AN20="","",'Investment Case Asks - Monthly'!AN20),"") | Q20: =IFERROR(IF('Investment Case Asks - Monthly'!BA20="","",'Investment Case Asks - Monthly'!BA20),"") | R20: =IFERROR(IF('Investment Case Asks - Monthly'!BB20="","",'Investment Case Asks - Monthly'!BB20),"")
A22: Total Payroll / Headcount Incremental Spend | G22: =SUM(G5:G20) -> 0 | I22: =SUM(I5:I20) -> 0 | J22: =SUM(J5:J20) -> 0 | K22: =SUM(K5:K20) -> 0 | L22: =SUM(L5:L20) -> 0 | M22: =SUM(M5:M20) -> 0 | N22: =SUM(N5:N20) -> 0 | O22: =SUM(O5:O20) -> 0 | P22: =SUM(P5:P20) -> 0 | Q22: =SUM(Q5:Q20) -> 0
A26: Essentials Bonus / Contract Labor / Non-Payroll Incremental Spend
A27: Expense Description | B27: Type of Expense | C27: Vendor | D27: 2027 Incremental Spend | E27: 2028 Incremental Spend | F27: 2029 Incremental Spend | G27: Notes / Rationale
A28: =IFERROR(IF('Investment Case Asks - Monthly'!A28="","",'Investment Case Asks - Monthly'!A28),"") | B28: =IFERROR(IF('Investment Case Asks - Monthly'!B28="","",'Investment Case Asks - Monthly'!B28),"") | C28: =IFERROR(IF('Investment Case Asks - Monthly'!C28="","",'Investment Case Asks - Monthly'!C28),"") | D28: =IFERROR(IF('Investment Case Asks - Monthly'!Q28="","",'Investment Case Asks - Monthly'!Q28),"") -> 0 | E28: =IFERROR(IF('Investment Case Asks - Monthly'!AD28="","",'Investment Case Asks - Monthly'!AD28),"") -> 0 | F28: =IFERROR(IF('Investment Case Asks - Monthly'!AQ28="","",'Investment Case Asks - Monthly'!AQ28),"") -> 0 | G28: =IFERROR(IF('Investment Case Asks - Monthly'!AR28="","",'Investment Case Asks - Monthly'!AR28),"")
A29: =IFERROR(IF('Investment Case Asks - Monthly'!A29="","",'Investment Case Asks - Monthly'!A29),"") | B29: =IFERROR(IF('Investment Case Asks - Monthly'!B29="","",'Investment Case Asks - Monthly'!B29),"") | C29: =IFERROR(IF('Investment Case Asks - Monthly'!C29="","",'Investment Case Asks - Monthly'!C29),"") | D29: =IFERROR(IF('Investment Case Asks - Monthly'!Q29="","",'Investment Case Asks - Monthly'!Q29),"") -> 0 | E29: =IFERROR(IF('Investment Case Asks - Monthly'!AD29="","",'Investment Case Asks - Monthly'!AD29),"") -> 0 | F29: =IFERROR(IF('Investment Case Asks - Monthly'!AQ29="","",'Investment Case Asks - Monthly'!AQ29),"") -> 0 | G29: =IFERROR(IF('Investment Case Asks - Monthly'!AR29="","",'Investment Case Asks - Monthly'!AR29),"")
A30: =IFERROR(IF('Investment Case Asks - Monthly'!A30="","",'Investment Case Asks - Monthly'!A30),"") | B30: =IFERROR(IF('Investment Case Asks - Monthly'!B30="","",'Investment Case Asks - Monthly'!B30),"") | C30: =IFERROR(IF('Investment Case Asks - Monthly'!C30="","",'Investment Case Asks - Monthly'!C30),"") | D30: =IFERROR(IF('Investment Case Asks - Monthly'!Q30="","",'Investment Case Asks - Monthly'!Q30),"") -> 0 | E30: =IFERROR(IF('Investment Case Asks - Monthly'!AD30="","",'Investment Case Asks - Monthly'!AD30),"") -> 0 | F30: =IFERROR(IF('Investment Case Asks - Monthly'!AQ30="","",'Investment Case Asks - Monthly'!AQ30),"") -> 0 | G30: =IFERROR(IF('Investment Case Asks - Monthly'!AR30="","",'Investment Case Asks - Monthly'!AR30),"")
A31: =IFERROR(IF('Investment Case Asks - Monthly'!A31="","",'Investment Case Asks - Monthly'!A31),"") | B31: =IFERROR(IF('Investment Case Asks - Monthly'!B31="","",'Investment Case Asks - Monthly'!B31),"") | C31: =IFERROR(IF('Investment Case Asks - Monthly'!C31="","",'Investment Case Asks - Monthly'!C31),"") | D31: =IFERROR(IF('Investment Case Asks - Monthly'!Q31="","",'Investment Case Asks - Monthly'!Q31),"") -> 0 | E31: =IFERROR(IF('Investment Case Asks - Monthly'!AD31="","",'Investment Case Asks - Monthly'!AD31),"") -> 0 | F31: =IFERROR(IF('Investment Case Asks - Monthly'!AQ31="","",'Investment Case Asks - Monthly'!AQ31),"") -> 0 | G31: =IFERROR(IF('Investment Case Asks - Monthly'!AR31="","",'Investment Case Asks - Monthly'!AR31),"")
A32: =IFERROR(IF('Investment Case Asks - Monthly'!A32="","",'Investment Case Asks - Monthly'!A32),"") | B32: =IFERROR(IF('Investment Case Asks - Monthly'!B32="","",'Investment Case Asks - Monthly'!B32),"") | C32: =IFERROR(IF('Investment Case Asks - Monthly'!C32="","",'Investment Case Asks - Monthly'!C32),"") | D32: =IFERROR(IF('Investment Case Asks - Monthly'!Q32="","",'Investment Case Asks - Monthly'!Q32),"") -> 0 | E32: =IFERROR(IF('Investment Case Asks - Monthly'!AD32="","",'Investment Case Asks - Monthly'!AD32),"") -> 0 | F32: =IFERROR(IF('Investment Case Asks - Monthly'!AQ32="","",'Investment Case Asks - Monthly'!AQ32),"") -> 0 | G32: =IFERROR(IF('Investment Case Asks - Monthly'!AR32="","",'Investment Case Asks - Monthly'!AR32),"")
A33: =IFERROR(IF('Investment Case Asks - Monthly'!A33="","",'Investment Case Asks - Monthly'!A33),"") | B33: =IFERROR(IF('Investment Case Asks - Monthly'!B33="","",'Investment Case Asks - Monthly'!B33),"") | C33: =IFERROR(IF('Investment Case Asks - Monthly'!C33="","",'Investment Case Asks - Monthly'!C33),"") | D33: =IFERROR(IF('Investment Case Asks - Monthly'!Q33="","",'Investment Case Asks - Monthly'!Q33),"") -> 0 | E33: =IFERROR(IF('Investment Case Asks - Monthly'!AD33="","",'Investment Case Asks - Monthly'!AD33),"") -> 0 | F33: =IFERROR(IF('Investment Case Asks - Monthly'!AQ33="","",'Investment Case Asks - Monthly'!AQ33),"") -> 0 | G33: =IFERROR(IF('Investment Case Asks - Monthly'!AR33="","",'Investment Case Asks - Monthly'!AR33),"")
A34: =IFERROR(IF('Investment Case Asks - Monthly'!A34="","",'Investment Case Asks - Monthly'!A34),"") | B34: =IFERROR(IF('Investment Case Asks - Monthly'!B34="","",'Investment Case Asks - Monthly'!B34),"") | C34: =IFERROR(IF('Investment Case Asks - Monthly'!C34="","",'Investment Case Asks - Monthly'!C34),"") | D34: =IFERROR(IF('Investment Case Asks - Monthly'!Q34="","",'Investment Case Asks - Monthly'!Q34),"") -> 0 | E34: =IFERROR(IF('Investment Case Asks - Monthly'!AD34="","",'Investment Case Asks - Monthly'!AD34),"") -> 0 | F34: =IFERROR(IF('Investment Case Asks - Monthly'!AQ34="","",'Investment Case Asks - Monthly'!AQ34),"") -> 0 | G34: =IFERROR(IF('Investment Case Asks - Monthly'!AR34="","",'Investment Case Asks - Monthly'!AR34),"")
A35: =IFERROR(IF('Investment Case Asks - Monthly'!A35="","",'Investment Case Asks - Monthly'!A35),"") | B35: =IFERROR(IF('Investment Case Asks - Monthly'!B35="","",'Investment Case Asks - Monthly'!B35),"") | C35: =IFERROR(IF('Investment Case Asks - Monthly'!C35="","",'Investment Case Asks - Monthly'!C35),"") | D35: =IFERROR(IF('Investment Case Asks - Monthly'!Q35="","",'Investment Case Asks - Monthly'!Q35),"") -> 0 | E35: =IFERROR(IF('Investment Case Asks - Monthly'!AD35="","",'Investment Case Asks - Monthly'!AD35),"") -> 0 | F35: =IFERROR(IF('Investment Case Asks - Monthly'!AQ35="","",'Investment Case Asks - Monthly'!AQ35),"") -> 0 | G35: =IFERROR(IF('Investment Case Asks - Monthly'!AR35="","",'Investment Case Asks - Monthly'!AR35),"")
A36: =IFERROR(IF('Investment Case Asks - Monthly'!A36="","",'Investment Case Asks - Monthly'!A36),"") | B36: =IFERROR(IF('Investment Case Asks - Monthly'!B36="","",'Investment Case Asks - Monthly'!B36),"") | C36: =IFERROR(IF('Investment Case Asks - Monthly'!C36="","",'Investment Case Asks - Monthly'!C36),"") | D36: =IFERROR(IF('Investment Case Asks - Monthly'!Q36="","",'Investment Case Asks - Monthly'!Q36),"") -> 0 | E36: =IFERROR(IF('Investment Case Asks - Monthly'!AD36="","",'Investment Case Asks - Monthly'!AD36),"") -> 0 | F36: =IFERROR(IF('Investment Case Asks - Monthly'!AQ36="","",'Investment Case Asks - Monthly'!AQ36),"") -> 0 | G36: =IFERROR(IF('Investment Case Asks - Monthly'!AR36="","",'Investment Case Asks - Monthly'!AR36),"")
A37: =IFERROR(IF('Investment Case Asks - Monthly'!A37="","",'Investment Case Asks - Monthly'!A37),"") | B37: =IFERROR(IF('Investment Case Asks - Monthly'!B37="","",'Investment Case Asks - Monthly'!B37),"") | C37: =IFERROR(IF('Investment Case Asks - Monthly'!C37="","",'Investment Case Asks - Monthly'!C37),"") | D37: =IFERROR(IF('Investment Case Asks - Monthly'!Q37="","",'Investment Case Asks - Monthly'!Q37),"") -> 0 | E37: =IFERROR(IF('Investment Case Asks - Monthly'!AD37="","",'Investment Case Asks - Monthly'!AD37),"") -> 0 | F37: =IFERROR(IF('Investment Case Asks - Monthly'!AQ37="","",'Investment Case Asks - Monthly'!AQ37),"") -> 0 | G37: =IFERROR(IF('Investment Case Asks - Monthly'!AR37="","",'Investment Case Asks - Monthly'!AR37),"")
A38: =IFERROR(IF('Investment Case Asks - Monthly'!A38="","",'Investment Case Asks - Monthly'!A38),"") | B38: =IFERROR(IF('Investment Case Asks - Monthly'!B38="","",'Investment Case Asks - Monthly'!B38),"") | C38: =IFERROR(IF('Investment Case Asks - Monthly'!C38="","",'Investment Case Asks - Monthly'!C38),"") | D38: =IFERROR(IF('Investment Case Asks - Monthly'!Q38="","",'Investment Case Asks - Monthly'!Q38),"") -> 0 | E38: =IFERROR(IF('Investment Case Asks - Monthly'!AD38="","",'Investment Case Asks - Monthly'!AD38),"") -> 0 | F38: =IFERROR(IF('Investment Case Asks - Monthly'!AQ38="","",'Investment Case Asks - Monthly'!AQ38),"") -> 0 | G38: =IFERROR(IF('Investment Case Asks - Monthly'!AR38="","",'Investment Case Asks - Monthly'!AR38),"")
A39: =IFERROR(IF('Investment Case Asks - Monthly'!A39="","",'Investment Case Asks - Monthly'!A39),"") | B39: =IFERROR(IF('Investment Case Asks - Monthly'!B39="","",'Investment Case Asks - Monthly'!B39),"") | C39: =IFERROR(IF('Investment Case Asks - Monthly'!C39="","",'Investment Case Asks - Monthly'!C39),"") | D39: =IFERROR(IF('Investment Case Asks - Monthly'!Q39="","",'Investment Case Asks - Monthly'!Q39),"") -> 0 | E39: =IFERROR(IF('Investment Case Asks - Monthly'!AD39="","",'Investment Case Asks - Monthly'!AD39),"") -> 0 | F39: =IFERROR(IF('Investment Case Asks - Monthly'!AQ39="","",'Investment Case Asks - Monthly'!AQ39),"") -> 0 | G39: =IFERROR(IF('Investment Case Asks - Monthly'!AR39="","",'Investment Case Asks - Monthly'!AR39),"")
... A42: =IFERROR(IF('Investment Case Asks - Monthly'!A42="","",'Investment Case Asks - Monthly'!A42),"") | B42: =IFERROR(IF('Investment Case Asks - Monthly'!B42="","",'Investment Case Asks - Monthly'!B42),"") | C42: =IFERROR(IF('Investment Case Asks - Monthly'!C42="","",'Investment Case Asks - Monthly'!C42),"") | D42: =IFERROR(IF('Investment Case Asks - Monthly'!Q42="","",'Investment Case Asks - Monthly'!Q42),"") -> 0 | E42: =IFERROR(IF('Investment Case Asks - Monthly'!AD42="","",'Investment Case Asks - Monthly'!AD42),"") -> 0 | F42: =IFERROR(IF('Investment Case Asks - Monthly'!AQ42="","",'Investment Case Asks - Monthly'!AQ42),"") -> 0 | G42: =IFERROR(IF('Investment Case Asks - Monthly'!AR42="","",'Investment Case Asks - Monthly'!AR42),"")
A44: Total Essentials Bonus / Contract Labor / Non-Payroll Incremental Spend | D44: =SUM(D28:D42) -> 0 | E44: =SUM(E28:E42) -> 0 | F44: =SUM(F28:F42) -> 0

Sheet Investment Case Asks - Monthly
A1: Investment Case Asks - Incremental Spend Input
A3: Payroll / Headcount Incremental Spend
A4: Job Title | B4: Job Level | C4: Role / Hire | D4: Location (City/Country) | E4: Key Job Responsibilities | F4: Hire Date | G4: Base Salary | H4: Bonus % | I4: Bonus | J4: Payroll Taxes | K4: Benefits | L4: Vacation | M4: Other | N4: Annualized Spend | O4: Jan-27 | P4: Feb-27 | Q4: Mar-27 | R4: Apr-27 | S4: May-27 | T4: Jun-27 | U4: Jul-27 | V4: Aug-27 | W4: Sep-27 | X4: Oct-27 | Y4: Nov-27 | Z4: Dec-27 | AA4: 2027 Incremental Spend | AB4: Jan-28 | AC4: Feb-28 | AD4: Mar-28 | AE4: Apr-28 | AF4: May-28 | AG4: Jun-28 | AH4: Jul-28 | AI4: Aug-28 | AJ4: Sep-28 | AK4: Oct-28 | AL4: Nov-28 | AM4: Dec-28 | AN4: 2028 Incremental Spend | AO4: Jan-29 | AP4: Feb-29 | AQ4: Mar-29 | AR4: Apr-29 | AS4: May-29 | AT4: Jun-29 | AU4: Jul-29 | AV4: Aug-29 | AW4: Sep-29 | AX4: Oct-29 | AY4: Nov-29 | AZ4: Dec-29 | BA4: 2029 Incremental Spend | BB4: Notes / Rationale
I5: =IF(COUNTA($A5:$H5)>0,IFERROR($G5*$H5,0),"") | J5: =IF(COUNTA($A5:$H5)>0,IFERROR($G5*Summary!$C$46/Summary!$C$43,0),"") | K5: =IF(COUNTA($A5:$H5)>0,IFERROR($G5*Summary!$C$47/Summary!$C$43,0),"") | L5: =IF(COUNTA($A5:$H5)>0,IFERROR($G5*Summary!$C$48/Summary!$C$43,0),"") | M5: =IF(COUNTA($A5:$H5)>0,IFERROR($G5*Summary!$C$49/Summary!$C$43,0),"") | N5: =IF(COUNTA($A5:$H5)>0,IFERROR($G5,0)+SUM(I5:M5),"") | O5: =_xlfn.LET(_xlpm.m,IF(ISNUMBER(O$4),DATE(YEAR(O$4),MONTH(O$4),1),DATEVALUE("1-"&O$4)),IF(OR(COUNTA($A5:$F5)>0,$G5<>""),$N5/12*IF($F5="",1,MAX(0,(EOMONTH(_xlpm.m,0)-MAX($F5,_xlpm.m)+1)/(EOMONTH(_xlpm.m,0)-_xlpm.m+1))),"")) | P5: =_xlfn.LET(_xlpm.m,IF(ISNUMBER(P$4),DATE(YEAR(P$4),MONTH(P$4),1),DATEVALUE("1-"&P$4)),IF(OR(COUNTA($A5:$F5)>0,$G5<>""),$N5/12*IF($F5="",1,MAX(0,(EOMONTH(_xlpm.m,0)-MAX($F5,_xlpm.m)+1)/(EOMONTH(_xlpm.m,0)-_xlpm.m+1))),"")) | Q5: =_xlfn.LET(_xlpm.m,IF(ISNUMBER(Q$4),DATE(YEAR(Q$4),MONTH(Q$4),1),DATEVALUE("1-"&Q$4)),IF(OR(COUNTA($A5:$F5)>0,$G5<>""),$N5/12*IF($F5="",1,MAX(0,(EOMONTH(_xlpm.m,0)-MAX($F5,_xlpm.m)+1)/(EOMONTH(_xlpm.m,0)-_xlpm.m+1))),"")) | R5: =_xlfn.LET(_xlpm.m,IF(ISNUMBER(R$4),DATE(YEAR(R$4),MONTH(R$4),1),DATEVALUE("1-"&R$4)),IF(OR(COUNTA($A5:$F5)>0,$G5<>""),$N5/12*IF($F5="",1,MAX(0,(EOMONTH(_xlpm.m,0)-MAX($F5,_xlpm.m)+1)/(EOMONTH(_xlpm.m,0)-_xlpm.m+1))),"")) | S5: =_xlfn.LET(_xlpm.m,IF(ISNUMBER(S$4),DATE(YEAR(S$4),MONTH(S$4),1),DATEVALUE("1-"&S$4)),IF(OR(COUNTA($A5:$F5)>0,$G5<>""),$N5/12*IF($F5="",1,MAX(0,(EOMONTH(_xlpm.m,0)-MAX($F5,_xlpm.m)+1)/(EOMONTH(_xlpm.m,0)-_xlpm.m+1))),"")) | T5: =_xlfn.LET(_xlpm.m,IF(ISNUMBER(T$4),DATE(YEAR(T$4),MONTH(T$4),1),DATEVALUE("1-"&T$4)),IF(OR(COUNTA($A5:$F5)>0,$G5<>""),$N5/12*IF($F5="",1,MAX(0,(EOMONTH(_xlpm.m,0)-MAX($F5,_xlpm.m)+1)/(EOMONTH(_xlpm.m,0)-_xlpm.m+1))),"")) | U5: =_xlfn.LET(_xlpm.m,IF(ISNUMBER(U$4),DATE(YEAR(U$4),MONTH(U$4),1),DATEVALUE("1-"&U$4)),IF(OR(COUNTA($A5:$F5)>0,$G5<>""),$N5/12*IF($F5="",1,MAX(0,(EOMONTH(_xlpm.m,0)-MAX($F5,_xlpm.m)+1)/(EOMONTH(_xlpm.m,0)-_xlpm.m+1))),"")) | V5: =_xlfn.LET(_xlpm.m,IF(ISNUMBER(V$4),DATE(YEAR(V$4),MONTH(V$4),1),DATEVALUE("1-"&V$4)),IF(OR(COUNTA($A5:$F5)>0,$G5<>""),$N5/12*IF($F5="",1,MAX(0,(EOMONTH(_xlpm.m,0)-MAX($F5,_xlpm.m)+1)/(EOMONTH(_xlpm.m,0)-_xlpm.m+1))),"")) | ... Z5: =_xlfn.LET(_xlpm.m,IF(ISNUMBER(Z$4),DATE(YEAR(Z$4),MONTH(Z$4),1),DATEVALUE("1-"&Z$4)),IF(OR(COUNTA($A5:$F5)>0,$G5<>""),$N5/12*IF($F5="",1,MAX(0,(EOMONTH(_xlpm.m,0)-MAX($F5,_xlpm.m)+1)/(EOMONTH(_xlpm.m,0)-_xlpm.m+1))),"")) | AA5: =IF(OR(COUNTA($A5:$F5)>0,$G5<>""),SUM(O5:Z5),"") | AB5: =_xlfn.LET(_xlpm.m,IF(ISNUMBER(AB$4),DATE(YEAR(AB$4),MONTH(AB$4),1),DATEVALUE("1-"&AB$4)),IF(OR(COUNTA($A5:$F5)>0,$G5<>""),$N5/12*IF($F5="",1,MAX(0,(EOMONTH(_xlpm.m,0)-MAX($F5,_xlpm.m)+1)/(EOMONTH(_xlpm.m,0)-_xlpm.m+1))),"")) | AC5: =_xlfn.LET(_xlpm.m,IF(ISNUMBER(AC$4),DATE(YEAR(AC$4),MONTH(AC$4),1),DATEVALUE("1-"&AC$4)),IF(OR(COUNTA($A5:$F5)>0,$G5<>""),$N5/12*IF($F5="",1,MAX(0,(EOMONTH(_xlpm.m,0)-MAX($F5,_xlpm.m)+1)/(EOMONTH(_xlpm.m,0)-_xlpm.m+1))),"")) | AD5: =_xlfn.LET(_xlpm.m,IF(ISNUMBER(AD$4),DATE(YEAR(AD$4),MONTH(AD$4),1),DATEVALUE("1-"&AD$4)),IF(OR(COUNTA($A5:$F5)>0,$G5<>""),$N5/12*IF($F5="",1,MAX(0,(EOMONTH(_xlpm.m,0)-MAX($F5,_xlpm.m)+1)/(EOMONTH(_xlpm.m,0)-_xlpm.m+1))),"")) | AE5: =_xlfn.LET(_xlpm.m,IF(ISNUMBER(AE$4),DATE(YEAR(AE$4),MONTH(AE$4),1),DATEVALUE("1-"&AE$4)),IF(OR(COUNTA($A5:$F5)>0,$G5<>""),$N5/12*IF($F5="",1,MAX(0,(EOMONTH(_xlpm.m,0)-MAX($F5,_xlpm.m)+1)/(EOMONTH(_xlpm.m,0)-_xlpm.m+1))),"")) | AF5: =_xlfn.LET(_xlpm.m,IF(ISNUMBER(AF$4),DATE(YEAR(AF$4),MONTH(AF$4),1),DATEVALUE("1-"&AF$4)),IF(OR(COUNTA($A5:$F5)>0,$G5<>""),$N5/12*IF($F5="",1,MAX(0,(EOMONTH(_xlpm.m,0)-MAX($F5,_xlpm.m)+1)/(EOMONTH(_xlpm.m,0)-_xlpm.m+1))),"")) | AG5: =_xlfn.LET(_xlpm.m,IF(ISNUMBER(AG$4),DATE(YEAR(AG$4),MONTH(AG$4),1),DATEVALUE("1-"&AG$4)),IF(OR(COUNTA($A5:$F5)>0,$G5<>""),$N5/12*IF($F5="",1,MAX(0,(EOMONTH(_xlpm.m,0)-MAX($F5,_xlpm.m)+1)/(EOMONTH(_xlpm.m,0)-_xlpm.m+1))),"")) | AH5: =_xlfn.LET(_xlpm.m,IF(ISNUMBER(AH$4),DATE(YEAR(AH$4),MONTH(AH$4),1),DATEVALUE("1-"&AH$4)),IF(OR(COUNTA($A5:$F5)>0,$G5<>""),$N5/12*IF($F5="",1,MAX(0,(EOMONTH(_xlpm.m,0)-MAX($F5,_xlpm.m)+1)/(EOMONTH(_xlpm.m,0)-_xlpm.m+1))),"")) | AI5: =_xlfn.LET(_xlpm.m,IF(ISNUMBER(AI$4),DATE(YEAR(AI$4),MONTH(AI$4),1),DATEVALUE("1-"&AI$4)),IF(OR(COUNTA($A5:$F5)>0,$G5<>""),$N5/12*IF($F5="",1,MAX(0,(EOMONTH(_xlpm.m,0)-MAX($F5,_xlpm.m)+1)/(EOMONTH(_xlpm.m,0)-_xlpm.m+1))),"")) | ... AM5: =_xlfn.LET(_xlpm.m,IF(ISNUMBER(AM$4),DATE(YEAR(AM$4),MONTH(AM$4),1),DATEVALUE("1-"&AM$4)),IF(OR(COUNTA($A5:$F5)>0,$G5<>""),$N5/12*IF($F5="",1,MAX(0,(EOMONTH(_xlpm.m,0)-MAX($F5,_xlpm.m)+1)/(EOMONTH(_xlpm.m,0)-_xlpm.m+1))),"")) | AN5: =IF(OR(COUNTA($A5:$F5)>0,$G5<>""),SUM(AB5:AM5),"") | AO5: =_xlfn.LET(_xlpm.m,IF(ISNUMBER(AO$4),DATE(YEAR(AO$4),MONTH(AO$4),1),DATEVALUE("1-"&AO$4)),IF(OR(COUNTA($A5:$F5)>0,$G5<>""),$N5/12*IF($F5="",1,MAX(0,(EOMONTH(_xlpm.m,0)-MAX($F5,_xlpm.m)+1)/(EOMONTH(_xlpm.m,0)-_xlpm.m+1))),"")) | AP5: =_xlfn.LET(_xlpm.m,IF(ISNUMBER(AP$4),DATE(YEAR(AP$4),MONTH(AP$4),1),DATEVALUE("1-"&AP$4)),IF(OR(COUNTA($A5:$F5)>0,$G5<>""),$N5/12*IF($F5="",1,MAX(0,(EOMONTH(_xlpm.m,0)-MAX($F5,_xlpm.m)+1)/(EOMONTH(_xlpm.m,0)-_xlpm.m+1))),"")) | AQ5: =_xlfn.LET(_xlpm.m,IF(ISNUMBER(AQ$4),DATE(YEAR(AQ$4),MONTH(AQ$4),1),DATEVALUE("1-"&AQ$4)),IF(OR(COUNTA($A5:$F5)>0,$G5<>""),$N5/12*IF($F5="",1,MAX(0,(EOMONTH(_xlpm.m,0)-MAX($F5,_xlpm.m)+1)/(EOMONTH(_xlpm.m,0)-_xlpm.m+1))),"")) | AR5: =_xlfn.LET(_xlpm.m,IF(ISNUMBER(AR$4),DATE(YEAR(AR$4),MONTH(AR$4),1),DATEVALUE("1-"&AR$4)),IF(OR(COUNTA($A5:$F5)>0,$G5<>""),$N5/12*IF($F5="",1,MAX(0,(EOMONTH(_xlpm.m,0)-MAX($F5,_xlpm.m)+1)/(EOMONTH(_xlpm.m,0)-_xlpm.m+1))),"")) | AS5: =_xlfn.LET(_xlpm.m,IF(ISNUMBER(AS$4),DATE(YEAR(AS$4),MONTH(AS$4),1),DATEVALUE("1-"&AS$4)),IF(OR(COUNTA($A5:$F5)>0,$G5<>""),$N5/12*IF($F5="",1,MAX(0,(EOMONTH(_xlpm.m,0)-MAX($F5,_xlpm.m)+1)/(EOMONTH(_xlpm.m,0)-_xlpm.m+1))),"")) | AT5: =_xlfn.LET(_xlpm.m,IF(ISNUMBER(AT$4),DATE(YEAR(AT$4),MONTH(AT$4),1),DATEVALUE("1-"&AT$4)),IF(OR(COUNTA($A5:$F5)>0,$G5<>""),$N5/12*IF($F5="",1,MAX(0,(EOMONTH(_xlpm.m,0)-MAX($F5,_xlpm.m)+1)/(EOMONTH(_xlpm.m,0)-_xlpm.m+1))),"")) | AU5: =_xlfn.LET(_xlpm.m,IF(ISNUMBER(AU$4),DATE(YEAR(AU$4),MONTH(AU$4),1),DATEVALUE("1-"&AU$4)),IF(OR(COUNTA($A5:$F5)>0,$G5<>""),$N5/12*IF($F5="",1,MAX(0,(EOMONTH(_xlpm.m,0)-MAX($F5,_xlpm.m)+1)/(EOMONTH(_xlpm.m,0)-_xlpm.m+1))),"")) | AV5: =_xlfn.LET(_xlpm.m,IF(ISNUMBER(AV$4),DATE(YEAR(AV$4),MONTH(AV$4),1),DATEVALUE("1-"&AV$4)),IF(OR(COUNTA($A5:$F5)>0,$G5<>""),$N5/12*IF($F5="",1,MAX(0,(EOMONTH(_xlpm.m,0)-MAX($F5,_xlpm.m)+1)/(EOMONTH(_xlpm.m,0)-_xlpm.m+1))),"")) | ... AZ5: =_xlfn.LET(_xlpm.m,IF(ISNUMBER(AZ$4),DATE(YEAR(AZ$4),MONTH(AZ$4),1),DATEVALUE("1-"&AZ$4)),IF(OR(COUNTA($A5:$F5)>0,$G5<>""),$N5/12*IF($F5="",1,MAX(0,(EOMONTH(_xlpm.m,0)-MAX($F5,_xlpm.m)+1)/(EOMONTH(_xlpm.m,0)-_xlpm.m+1))),"")) | BA5: =IF(OR(COUNTA($A5:$F5)>0,$G5<>""),SUM(AO5:AZ5),"")
I6: =IF(COUNTA($A6:$H6)>0,IFERROR($G6*$H6,0),"") | J6: =IF(COUNTA($A6:$H6)>0,IFERROR($G6*Summary!$C$46/Summary!$C$43,0),"") | K6: =IF(COUNTA($A6:$H6)>0,IFERROR($G6*Summary!$C$47/Summary!$C$43,0),"") | L6: =IF(COUNTA($A6:$H6)>0,IFERROR($G6*Summary!$C$48/Summary!$C$43,0),"") | M6: =IF(COUNTA($A6:$H6)>0,IFERROR($G6*Summary!$C$49/Summary!$C$43,0),"") | N6: =IF(COUNTA($A6:$H6)>0,IFERROR($G6,0)+SUM(I6:M6),"") | O6: =_xlfn.LET(_xlpm.m,IF(ISNUMBER(O$4),DATE(YEAR(O$4),MONTH(O$4),1),DATEVALUE("1-"&O$4)),IF(OR(COUNTA($A6:$F6)>0,$G6<>""),$N6/12*IF($F6="",1,MAX(0,(EOMONTH(_xlpm.m,0)-MAX($F6,_xlpm.m)+1)/(EOMONTH(_xlpm.m,0)-_xlpm.m+1))),"")) | P6: =_xlfn.LET(_xlpm.m,IF(ISNUMBER(P$4),DATE(YEAR(P$4),MONTH(P$4),1),DATEVALUE("1-"&P$4)),IF(OR(COUNTA($A6:$F6)>0,$G6<>""),$N6/12*IF($F6="",1,MAX(0,(EOMONTH(_xlpm.m,0)-MAX($F6,_xlpm.m)+1)/(EOMONTH(_xlpm.m,0)-_xlpm.m+1))),"")) | Q6: =_xlfn.LET(_xlpm.m,IF(ISNUMBER(Q$4),DATE(YEAR(Q$4),MONTH(Q$4),1),DATEVALUE("1-"&Q$4)),IF(OR(COUNTA($A6:$F6)>0,$G6<>""),$N6/12*IF($F6="",1,MAX(0,(EOMONTH(_xlpm.m,0)-MAX($F6,_xlpm.m)+1)/(EOMONTH(_xlpm.m,0)-_xlpm.m+1))),"")) | R6: =_xlfn.LET(_xlpm.m,IF(ISNUMBER(R$4),DATE(YEAR(R$4),MONTH(R$4),1),DATEVALUE("1-"&R$4)),IF(OR(COUNTA($A6:$F6)>0,$G6<>""),$N6/12*IF($F6="",1,MAX(0,(EOMONTH(_xlpm.m,0)-MAX($F6,_xlpm.m)+1)/(EOMONTH(_xlpm.m,0)-_xlpm.m+1))),"")) | S6: =_xlfn.LET(_xlpm.m,IF(ISNUMBER(S$4),DATE(YEAR(S$4),MONTH(S$4),1),DATEVALUE("1-"&S$4)),IF(OR(COUNTA($A6:$F6)>0,$G6<>""),$N6/12*IF($F6="",1,MAX(0,(EOMONTH(_xlpm.m,0)-MAX($F6,_xlpm.m)+1)/(EOMONTH(_xlpm.m,0)-_xlpm.m+1))),"")) | T6: =_xlfn.LET(_xlpm.m,IF(ISNUMBER(T$4),DATE(YEAR(T$4),MONTH(T$4),1),DATEVALUE("1-"&T$4)),IF(OR(COUNTA($A6:$F6)>0,$G6<>""),$N6/12*IF($F6="",1,MAX(0,(EOMONTH(_xlpm.m,0)-MAX($F6,_xlpm.m)+1)/(EOMONTH(_xlpm.m,0)-_xlpm.m+1))),"")) | U6: =_xlfn.LET(_xlpm.m,IF(ISNUMBER(U$4),DATE(YEAR(U$4),MONTH(U$4),1),DATEVALUE("1-"&U$4)),IF(OR(COUNTA($A6:$F6)>0,$G6<>""),$N6/12*IF($F6="",1,MAX(0,(EOMONTH(_xlpm.m,0)-MAX($F6,_xlpm.m)+1)/(EOMONTH(_xlpm.m,0)-_xlpm.m+1))),"")) | V6: =_xlfn.LET(_xlpm.m,IF(ISNUMBER(V$4),DATE(YEAR(V$4),MONTH(V$4),1),DATEVALUE("1-"&V$4)),IF(OR(COUNTA($A6:$F6)>0,$G6<>""),$N6/12*IF($F6="",1,MAX(0,(EOMONTH(_xlpm.m,0)-MAX($F6,_xlpm.m)+1)/(EOMONTH(_xlpm.m,0)-_xlpm.m+1))),"")) | ... Z6: =_xlfn.LET(_xlpm.m,IF(ISNUMBER(Z$4),DATE(YEAR(Z$4),MONTH(Z$4),1),DATEVALUE("1-"&Z$4)),IF(OR(COUNTA($A6:$F6)>0,$G6<>""),$N6/12*IF($F6="",1,MAX(0,(EOMONTH(_xlpm.m,0)-MAX($F6,_xlpm.m)+1)/(EOMONTH(_xlpm.m,0)-_xlpm.m+1))),"")) | AA6: =IF(COUNTA($A6:$H6)>0,SUM(O6:Z6),"") | AB6: =_xlfn.LET(_xlpm.m,IF(ISNUMBER(AB$4),DATE(YEAR(AB$4),MONTH(AB$4),1),DATEVALUE("1-"&AB$4)),IF(OR(COUNTA($A6:$F6)>0,$G6<>""),$N6/12*IF($F6="",1,MAX(0,(EOMONTH(_xlpm.m,0)-MAX($F6,_xlpm.m)+1)/(EOMONTH(_xlpm.m,0)-_xlpm.m+1))),"")) | AC6: =_xlfn.LET(_xlpm.m,IF(ISNUMBER(AC$4),DATE(YEAR(AC$4),MONTH(AC$4),1),DATEVALUE("1-"&AC$4)),IF(OR(COUNTA($A6:$F6)>0,$G6<>""),$N6/12*IF($F6="",1,MAX(0,(EOMONTH(_xlpm.m,0)-MAX($F6,_xlpm.m)+1)/(EOMONTH(_xlpm.m,0)-_xlpm.m+1))),"")) | AD6: =_xlfn.LET(_xlpm.m,IF(ISNUMBER(AD$4),DATE(YEAR(AD$4),MONTH(AD$4),1),DATEVALUE("1-"&AD$4)),IF(OR(COUNTA($A6:$F6)>0,$G6<>""),$N6/12*IF($F6="",1,MAX(0,(EOMONTH(_xlpm.m,0)-MAX($F6,_xlpm.m)+1)/(EOMONTH(_xlpm.m,0)-_xlpm.m+1))),"")) | AE6: =_xlfn.LET(_xlpm.m,IF(ISNUMBER(AE$4),DATE(YEAR(AE$4),MONTH(AE$4),1),DATEVALUE("1-"&AE$4)),IF(OR(COUNTA($A6:$F6)>0,$G6<>""),$N6/12*IF($F6="",1,MAX(0,(EOMONTH(_xlpm.m,0)-MAX($F6,_xlpm.m)+1)/(EOMONTH(_xlpm.m,0)-_xlpm.m+1))),"")) | AF6: =_xlfn.LET(_xlpm.m,IF(ISNUMBER(AF$4),DATE(YEAR(AF$4),MONTH(AF$4),1),DATEVALUE("1-"&AF$4)),IF(OR(COUNTA($A6:$F6)>0,$G6<>""),$N6/12*IF($F6="",1,MAX(0,(EOMONTH(_xlpm.m,0)-MAX($F6,_xlpm.m)+1)/(EOMONTH(_xlpm.m,0)-_xlpm.m+1))),"")) | AG6: =_xlfn.LET(_xlpm.m,IF(ISNUMBER(AG$4),DATE(YEAR(AG$4),MONTH(AG$4),1),DATEVALUE("1-"&AG$4)),IF(OR(COUNTA($A6:$F6)>0,$G6<>""),$N6/12*IF($F6="",1,MAX(0,(EOMONTH(_xlpm.m,0)-MAX($F6,_xlpm.m)+1)/(EOMONTH(_xlpm.m,0)-_xlpm.m+1))),"")) | AH6: =_xlfn.LET(_xlpm.m,IF(ISNUMBER(AH$4),DATE(YEAR(AH$4),MONTH(AH$4),1),DATEVALUE("1-"&AH$4)),IF(OR(COUNTA($A6:$F6)>0,$G6<>""),$N6/12*IF($F6="",1,MAX(0,(EOMONTH(_xlpm.m,0)-MAX($F6,_xlpm.m)+1)/(EOMONTH(_xlpm.m,0)-_xlpm.m+1))),"")) | AI6: =_xlfn.LET(_xlpm.m,IF(ISNUMBER(AI$4),DATE(YEAR(AI$4),MONTH(AI$4),1),DATEVALUE("1-"&AI$4)),IF(OR(COUNTA($A6:$F6)>0,$G6<>""),$N6/12*IF($F6="",1,MAX(0,(EOMONTH(_xlpm.m,0)-MAX($F6,_xlpm.m)+1)/(EOMONTH(_xlpm.m,0)-_xlpm.m+1))),"")) | ... AM6: =_xlfn.LET(_xlpm.m,IF(ISNUMBER(AM$4),DATE(YEAR(AM$4),MONTH(AM$4),1),DATEVALUE("1-"&AM$4)),IF(OR(COUNTA($A6:$F6)>0,$G6<>""),$N6/12*IF($F6="",1,MAX(0,(EOMONTH(_xlpm.m,0)-MAX($F6,_xlpm.m)+1)/(EOMONTH(_xlpm.m,0)-_xlpm.m+1))),"")) | AN6: =IF(COUNTA($A6:$H6)>0,SUM(AB6:AM6),"") | AO6: =_xlfn.LET(_xlpm.m,IF(ISNUMBER(AO$4),DATE(YEAR(AO$4),MONTH(AO$4),1),DATEVALUE("1-"&AO$4)),IF(OR(COUNTA($A6:$F6)>0,$G6<>""),$N6/12*IF($F6="",1,MAX(0,(EOMONTH(_xlpm.m,0)-MAX($F6,_xlpm.m)+1)/(EOMONTH(_xlpm.m,0)-_xlpm.m+1))),"")) | AP6: =_xlfn.LET(_xlpm.m,IF(ISNUMBER(AP$4),DATE(YEAR(AP$4),MONTH(AP$4),1),DATEVALUE("1-"&AP$4)),IF(OR(COUNTA($A6:$F6)>0,$G6<>""),$N6/12*IF($F6="",1,MAX(0,(EOMONTH(_xlpm.m,0)-MAX($F6,_xlpm.m)+1)/(EOMONTH(_xlpm.m,0)-_xlpm.m+1))),"")) | AQ6: =_xlfn.LET(_xlpm.m,IF(ISNUMBER(AQ$4),DATE(YEAR(AQ$4),MONTH(AQ$4),1),DATEVALUE("1-"&AQ$4)),IF(OR(COUNTA($A6:$F6)>0,$G6<>""),$N6/12*IF($F6="",1,MAX(0,(EOMONTH(_xlpm.m,0)-MAX($F6,_xlpm.m)+1)/(EOMONTH(_xlpm.m,0)-_xlpm.m+1))),"")) | AR6: =_xlfn.LET(_xlpm.m,IF(ISNUMBER(AR$4),DATE(YEAR(AR$4),MONTH(AR$4),1),DATEVALUE("1-"&AR$4)),IF(OR(COUNTA($A6:$F6)>0,$G6<>""),$N6/12*IF($F6="",1,MAX(0,(EOMONTH(_xlpm.m,0)-MAX($F6,_xlpm.m)+1)/(EOMONTH(_xlpm.m,0)-_xlpm.m+1))),"")) | AS6: =_xlfn.LET(_xlpm.m,IF(ISNUMBER(AS$4),DATE(YEAR(AS$4),MONTH(AS$4),1),DATEVALUE("1-"&AS$4)),IF(OR(COUNTA($A6:$F6)>0,$G6<>""),$N6/12*IF($F6="",1,MAX(0,(EOMONTH(_xlpm.m,0)-MAX($F6,_xlpm.m)+1)/(EOMONTH(_xlpm.m,0)-_xlpm.m+1))),"")) | AT6: =_xlfn.LET(_xlpm.m,IF(ISNUMBER(AT$4),DATE(YEAR(AT$4),MONTH(AT$4),1),DATEVALUE("1-"&AT$4)),IF(OR(COUNTA($A6:$F6)>0,$G6<>""),$N6/12*IF($F6="",1,MAX(0,(EOMONTH(_xlpm.m,0)-MAX($F6,_xlpm.m)+1)/(EOMONTH(_xlpm.m,0)-_xlpm.m+1))),"")) | AU6: =_xlfn.LET(_xlpm.m,IF(ISNUMBER(AU$4),DATE(YEAR(AU$4),MONTH(AU$4),1),DATEVALUE("1-"&AU$4)),IF(OR(COUNTA($A6:$F6)>0,$G6<>""),$N6/12*IF($F6="",1,MAX(0,(EOMONTH(_xlpm.m,0)-MAX($F6,_xlpm.m)+1)/(EOMONTH(_xlpm.m,0)-_xlpm.m+1))),"")) | AV6: =_xlfn.LET(_xlpm.m,IF(ISNUMBER(AV$4),DATE(YEAR(AV$4),MONTH(AV$4),1),DATEVALUE("1-"&AV$4)),IF(OR(COUNTA($A6:$F6)>0,$G6<>""),$N6/12*IF($F6="",1,MAX(0,(EOMONTH(_xlpm.m,0)-MAX($F6,_xlpm.m)+1)/(EOMONTH(_xlpm.m,0)-_xlpm.m+1))),"")) | ... AZ6: =_xlfn.LET(_xlpm.m,IF(ISNUMBER(AZ$4),DATE(YEAR(AZ$4),MONTH(AZ$4),1),DATEVALUE("1-"&AZ$4)),IF(OR(COUNTA($A6:$F6)>0,$G6<>""),$N6/12*IF($F6="",1,MAX(0,(EOMONTH(_xlpm.m,0)-MAX($F6,_xlpm.m)+1)/(EOMONTH(_xlpm.m,0)-_xlpm.m+1))),"")) | BA6: =IF(COUNTA($A6:$H6)>0,SUM(AO6:AZ6),"")
I7: =IF(COUNTA($A7:$H7)>0,IFERROR($G7*$H7,0),"") | J7: =IF(COUNTA($A7:$H7)>0,IFERROR($G7*Summary!$C$46/Summary!$C$43,0),"") | K7: =IF(COUNTA($A7:$H7)>0,IFERROR($G7*Summary!$C$47/Summary!$C$43,0),"") | L7: =IF(COUNTA($A7:$H7)>0,IFERROR($G7*Summary!$C$48/Summary!$C$43,0),"") | M7: =IF(COUNTA($A7:$H7)>0,IFERROR($G7*Summary!$C$49/Summary!$C$43,0),"") | N7: =IF(COUNTA($A7:$H7)>0,IFERROR($G7,0)+SUM(I7:M7),"") | O7: =_xlfn.LET(_xlpm.m,IF(ISNUMBER(O$4),DATE(YEAR(O$4),MONTH(O$4),1),DATEVALUE("1-"&O$4)),IF(OR(COUNTA($A7:$F7)>0,$G7<>""),$N7/12*IF($F7="",1,MAX(0,(EOMONTH(_xlpm.m,0)-MAX($F7,_xlpm.m)+1)/(EOMONTH(_xlpm.m,0)-_xlpm.m+1))),"")) | P7: =_xlfn.LET(_xlpm.m,IF(ISNUMBER(P$4),DATE(YEAR(P$4),MONTH(P$4),1),DATEVALUE("1-"&P$4)),IF(OR(COUNTA($A7:$F7)>0,$G7<>""),$N7/12*IF($F7="",1,MAX(0,(EOMONTH(_xlpm.m,0)-MAX($F7,_xlpm.m)+1)/(EOMONTH(_xlpm.m,0)-_xlpm.m+1))),"")) | Q7: =_xlfn.LET(_xlpm.m,IF(ISNUMBER(Q$4),DATE(YEAR(Q$4),MONTH(Q$4),1),DATEVALUE("1-"&Q$4)),IF(OR(COUNTA($A7:$F7)>0,$G7<>""),$N7/12*IF($F7="",1,MAX(0,(EOMONTH(_xlpm.m,0)-MAX($F7,_xlpm.m)+1)/(EOMONTH(_xlpm.m,0)-_xlpm.m+1))),"")) | R7: =_xlfn.LET(_xlpm.m,IF(ISNUMBER(R$4),DATE(YEAR(R$4),MONTH(R$4),1),DATEVALUE("1-"&R$4)),IF(OR(COUNTA($A7:$F7)>0,$G7<>""),$N7/12*IF($F7="",1,MAX(0,(EOMONTH(_xlpm.m,0)-MAX($F7,_xlpm.m)+1)/(EOMONTH(_xlpm.m,0)-_xlpm.m+1))),"")) | S7: =_xlfn.LET(_xlpm.m,IF(ISNUMBER(S$4),DATE(YEAR(S$4),MONTH(S$4),1),DATEVALUE("1-"&S$4)),IF(OR(COUNTA($A7:$F7)>0,$G7<>""),$N7/12*IF($F7="",1,MAX(0,(EOMONTH(_xlpm.m,0)-MAX($F7,_xlpm.m)+1)/(EOMONTH(_xlpm.m,0)-_xlpm.m+1))),"")) | T7: =_xlfn.LET(_xlpm.m,IF(ISNUMBER(T$4),DATE(YEAR(T$4),MONTH(T$4),1),DATEVALUE("1-"&T$4)),IF(OR(COUNTA($A7:$F7)>0,$G7<>""),$N7/12*IF($F7="",1,MAX(0,(EOMONTH(_xlpm.m,0)-MAX($F7,_xlpm.m)+1)/(EOMONTH(_xlpm.m,0)-_xlpm.m+1))),"")) | U7: =_xlfn.LET(_xlpm.m,IF(ISNUMBER(U$4),DATE(YEAR(U$4),MONTH(U$4),1),DATEVALUE("1-"&U$4)),IF(OR(COUNTA($A7:$F7)>0,$G7<>""),$N7/12*IF($F7="",1,MAX(0,(EOMONTH(_xlpm.m,0)-MAX($F7,_xlpm.m)+1)/(EOMONTH(_xlpm.m,0)-_xlpm.m+1))),"")) | V7: =_xlfn.LET(_xlpm.m,IF(ISNUMBER(V$4),DATE(YEAR(V$4),MONTH(V$4),1),DATEVALUE("1-"&V$4)),IF(OR(COUNTA($A7:$F7)>0,$G7<>""),$N7/12*IF($F7="",1,MAX(0,(EOMONTH(_xlpm.m,0)-MAX($F7,_xlpm.m)+1)/(EOMONTH(_xlpm.m,0)-_xlpm.m+1))),"")) | ... Z7: =_xlfn.LET(_xlpm.m,IF(ISNUMBER(Z$4),DATE(YEAR(Z$4),MONTH(Z$4),1),DATEVALUE("1-"&Z$4)),IF(OR(COUNTA($A7:$F7)>0,$G7<>""),$N7/12*IF($F7="",1,MAX(0,(EOMONTH(_xlpm.m,0)-MAX($F7,_xlpm.m)+1)/(EOMONTH(_xlpm.m,0)-_xlpm.m+1))),"")) | AA7: =IF(COUNTA($A7:$H7)>0,SUM(O7:Z7),"") | AB7: =_xlfn.LET(_xlpm.m,IF(ISNUMBER(AB$4),DATE(YEAR(AB$4),MONTH(AB$4),1),DATEVALUE("1-"&AB$4)),IF(OR(COUNTA($A7:$F7)>0,$G7<>""),$N7/12*IF($F7="",1,MAX(0,(EOMONTH(_xlpm.m,0)-MAX($F7,_xlpm.m)+1)/(EOMONTH(_xlpm.m,0)-_xlpm.m+1))),"")) | AC7: =_xlfn.LET(_xlpm.m,IF(ISNUMBER(AC$4),DATE(YEAR(AC$4),MONTH(AC$4),1),DATEVALUE("1-"&AC$4)),IF(OR(COUNTA($A7:$F7)>0,$G7<>""),$N7/12*IF($F7="",1,MAX(0,(EOMONTH(_xlpm.m,0)-MAX($F7,_xlpm.m)+1)/(EOMONTH(_xlpm.m,0)-_xlpm.m+1))),"")) | AD7: =_xlfn.LET(_xlpm.m,IF(ISNUMBER(AD$4),DATE(YEAR(AD$4),MONTH(AD$4),1),DATEVALUE("1-"&AD$4)),IF(OR(COUNTA($A7:$F7)>0,$G7<>""),$N7/12*IF($F7="",1,MAX(0,(EOMONTH(_xlpm.m,0)-MAX($F7,_xlpm.m)+1)/(EOMONTH(_xlpm.m,0)-_xlpm.m+1))),"")) | AE7: =_xlfn.LET(_xlpm.m,IF(ISNUMBER(AE$4),DATE(YEAR(AE$4),MONTH(AE$4),1),DATEVALUE("1-"&AE$4)),IF(OR(COUNTA($A7:$F7)>0,$G7<>""),$N7/12*IF($F7="",1,MAX(0,(EOMONTH(_xlpm.m,0)-MAX($F7,_xlpm.m)+1)/(EOMONTH(_xlpm.m,0)-_xlpm.m+1))),"")) | AF7: =_xlfn.LET(_xlpm.m,IF(ISNUMBER(AF$4),DATE(YEAR(AF$4),MONTH(AF$4),1),DATEVALUE("1-"&AF$4)),IF(OR(COUNTA($A7:$F7)>0,$G7<>""),$N7/12*IF($F7="",1,MAX(0,(EOMONTH(_xlpm.m,0)-MAX($F7,_xlpm.m)+1)/(EOMONTH(_xlpm.m,0)-_xlpm.m+1))),"")) | AG7: =_xlfn.LET(_xlpm.m,IF(ISNUMBER(AG$4),DATE(YEAR(AG$4),MONTH(AG$4),1),DATEVALUE("1-"&AG$4)),IF(OR(COUNTA($A7:$F7)>0,$G7<>""),$N7/12*IF($F7="",1,MAX(0,(EOMONTH(_xlpm.m,0)-MAX($F7,_xlpm.m)+1)/(EOMONTH(_xlpm.m,0)-_xlpm.m+1))),"")) | AH7: =_xlfn.LET(_xlpm.m,IF(ISNUMBER(AH$4),DATE(YEAR(AH$4),MONTH(AH$4),1),DATEVALUE("1-"&AH$4)),IF(OR(COUNTA($A7:$F7)>0,$G7<>""),$N7/12*IF($F7="",1,MAX(0,(EOMONTH(_xlpm.m,0)-MAX($F7,_xlpm.m)+1)/(EOMONTH(_xlpm.m,0)-_xlpm.m+1))),"")) | AI7: =_xlfn.LET(_xlpm.m,IF(ISNUMBER(AI$4),DATE(YEAR(AI$4),MONTH(AI$4),1),DATEVALUE("1-"&AI$4)),IF(OR(COUNTA($A7:$F7)>0,$G7<>""),$N7/12*IF($F7="",1,MAX(0,(EOMONTH(_xlpm.m,0)-MAX($F7,_xlpm.m)+1)/(EOMONTH(_xlpm.m,0)-_xlpm.m+1))),"")) | ... AM7: =_xlfn.LET(_xlpm.m,IF(ISNUMBER(AM$4),DATE(YEAR(AM$4),MONTH(AM$4),1),DATEVALUE("1-"&AM$4)),IF(OR(COUNTA($A7:$F7)>0,$G7<>""),$N7/12*IF($F7="",1,MAX(0,(EOMONTH(_xlpm.m,0)-MAX($F7,_xlpm.m)+1)/(EOMONTH(_xlpm.m,0)-_xlpm.m+1))),"")) | AN7: =IF(COUNTA($A7:$H7)>0,SUM(AB7:AM7),"") | AO7: =_xlfn.LET(_xlpm.m,IF(ISNUMBER(AO$4),DATE(YEAR(AO$4),MONTH(AO$4),1),DATEVALUE("1-"&AO$4)),IF(OR(COUNTA($A7:$F7)>0,$G7<>""),$N7/12*IF($F7="",1,MAX(0,(EOMONTH(_xlpm.m,0)-MAX($F7,_xlpm.m)+1)/(EOMONTH(_xlpm.m,0)-_xlpm.m+1))),"")) | AP7: =_xlfn.LET(_xlpm.m,IF(ISNUMBER(AP$4),DATE(YEAR(AP$4),MONTH(AP$4),1),DATEVALUE("1-"&AP$4)),IF(OR(COUNTA($A7:$F7)>0,$G7<>""),$N7/12*IF($F7="",1,MAX(0,(EOMONTH(_xlpm.m,0)-MAX($F7,_xlpm.m)+1)/(EOMONTH(_xlpm.m,0)-_xlpm.m+1))),"")) | AQ7: =_xlfn.LET(_xlpm.m,IF(ISNUMBER(AQ$4),DATE(YEAR(AQ$4),MONTH(AQ$4),1),DATEVALUE("1-"&AQ$4)),IF(OR(COUNTA($A7:$F7)>0,$G7<>""),$N7/12*IF($F7="",1,MAX(0,(EOMONTH(_xlpm.m,0)-MAX($F7,_xlpm.m)+1)/(EOMONTH(_xlpm.m,0)-_xlpm.m+1))),"")) | AR7: =_xlfn.LET(_xlpm.m,IF(ISNUMBER(AR$4),DATE(YEAR(AR$4),MONTH(AR$4),1),DATEVALUE("1-"&AR$4)),IF(OR(COUNTA($A7:$F7)>0,$G7<>""),$N7/12*IF($F7="",1,MAX(0,(EOMONTH(_xlpm.m,0)-MAX($F7,_xlpm.m)+1)/(EOMONTH(_xlpm.m,0)-_xlpm.m+1))),"")) | AS7: =_xlfn.LET(_xlpm.m,IF(ISNUMBER(AS$4),DATE(YEAR(AS$4),MONTH(AS$4),1),DATEVALUE("1-"&AS$4)),IF(OR(COUNTA($A7:$F7)>0,$G7<>""),$N7/12*IF($F7="",1,MAX(0,(EOMONTH(_xlpm.m,0)-MAX($F7,_xlpm.m)+1)/(EOMONTH(_xlpm.m,0)-_xlpm.m+1))),"")) | AT7: =_xlfn.LET(_xlpm.m,IF(ISNUMBER(AT$4),DATE(YEAR(AT$4),MONTH(AT$4),1),DATEVALUE("1-"&AT$4)),IF(OR(COUNTA($A7:$F7)>0,$G7<>""),$N7/12*IF($F7="",1,MAX(0,(EOMONTH(_xlpm.m,0)-MAX($F7,_xlpm.m)+1)/(EOMONTH(_xlpm.m,0)-_xlpm.m+1))),"")) | AU7: =_xlfn.LET(_xlpm.m,IF(ISNUMBER(AU$4),DATE(YEAR(AU$4),MONTH(AU$4),1),DATEVALUE("1-"&AU$4)),IF(OR(COUNTA($A7:$F7)>0,$G7<>""),$N7/12*IF($F7="",1,MAX(0,(EOMONTH(_xlpm.m,0)-MAX($F7,_xlpm.m)+1)/(EOMONTH(_xlpm.m,0)-_xlpm.m+1))),"")) | AV7: =_xlfn.LET(_xlpm.m,IF(ISNUMBER(AV$4),DATE(YEAR(AV$4),MONTH(AV$4),1),DATEVALUE("1-"&AV$4)),IF(OR(COUNTA($A7:$F7)>0,$G7<>""),$N7/12*IF($F7="",1,MAX(0,(EOMONTH(_xlpm.m,0)-MAX($F7,_xlpm.m)+1)/(EOMONTH(_xlpm.m,0)-_xlpm.m+1))),"")) | ... AZ7: =_xlfn.LET(_xlpm.m,IF(ISNUMBER(AZ$4),DATE(YEAR(AZ$4),MONTH(AZ$4),1),DATEVALUE("1-"&AZ$4)),IF(OR(COUNTA($A7:$F7)>0,$G7<>""),$N7/12*IF($F7="",1,MAX(0,(EOMONTH(_xlpm.m,0)-MAX($F7,_xlpm.m)+1)/(EOMONTH(_xlpm.m,0)-_xlpm.m+1))),"")) | BA7: =IF(COUNTA($A7:$H7)>0,SUM(AO7:AZ7),"")
I8: =IF(COUNTA($A8:$H8)>0,IFERROR($G8*$H8,0),"") | J8: =IF(COUNTA($A8:$H8)>0,IFERROR($G8*Summary!$C$46/Summary!$C$43,0),"") | K8: =IF(COUNTA($A8:$H8)>0,IFERROR($G8*Summary!$C$47/Summary!$C$43,0),"") | L8: =IF(COUNTA($A8:$H8)>0,IFERROR($G8*Summary!$C$48/Summary!$C$43,0),"") | M8: =IF(COUNTA($A8:$H8)>0,IFERROR($G8*Summary!$C$49/Summary!$C$43,0),"") | N8: =IF(COUNTA($A8:$H8)>0,IFERROR($G8,0)+SUM(I8:M8),"") | O8: =_xlfn.LET(_xlpm.m,IF(ISNUMBER(O$4),DATE(YEAR(O$4),MONTH(O$4),1),DATEVALUE("1-"&O$4)),IF(OR(COUNTA($A8:$F8)>0,$G8<>""),$N8/12*IF($F8="",1,MAX(0,(EOMONTH(_xlpm.m,0)-MAX($F8,_xlpm.m)+1)/(EOMONTH(_xlpm.m,0)-_xlpm.m+1))),"")) | P8: =_xlfn.LET(_xlpm.m,IF(ISNUMBER(P$4),DATE(YEAR(P$4),MONTH(P$4),1),DATEVALUE("1-"&P$4)),IF(OR(COUNTA($A8:$F8)>0,$G8<>""),$N8/12*IF($F8="",1,MAX(0,(EOMONTH(_xlpm.m,0)-MAX($F8,_xlpm.m)+1)/(EOMONTH(_xlpm.m,0)-_xlpm.m+1))),"")) | Q8: =_xlfn.LET(_xlpm.m,IF(ISNUMBER(Q$4),DATE(YEAR(Q$4),MONTH(Q$4),1),DATEVALUE("1-"&Q$4)),IF(OR(COUNTA($A8:$F8)>0,$G8<>""),$N8/12*IF($F8="",1,MAX(0,(EOMONTH(_xlpm.m,0)-MAX($F8,_xlpm.m)+1)/(EOMONTH(_xlpm.m,0)-_xlpm.m+1))),"")) | R8: =_xlfn.LET(_xlpm.m,IF(ISNUMBER(R$4),DATE(YEAR(R$4),MONTH(R$4),1),DATEVALUE("1-"&R$4)),IF(OR(COUNTA($A8:$F8)>0,$G8<>""),$N8/12*IF($F8="",1,MAX(0,(EOMONTH(_xlpm.m,0)-MAX($F8,_xlpm.m)+1)/(EOMONTH(_xlpm.m,0)-_xlpm.m+1))),"")) | S8: =_xlfn.LET(_xlpm.m,IF(ISNUMBER(S$4),DATE(YEAR(S$4),MONTH(S$4),1),DATEVALUE("1-"&S$4)),IF(OR(COUNTA($A8:$F8)>0,$G8<>""),$N8/12*IF($F8="",1,MAX(0,(EOMONTH(_xlpm.m,0)-MAX($F8,_xlpm.m)+1)/(EOMONTH(_xlpm.m,0)-_xlpm.m+1))),"")) | T8: =_xlfn.LET(_xlpm.m,IF(ISNUMBER(T$4),DATE(YEAR(T$4),MONTH(T$4),1),DATEVALUE("1-"&T$4)),IF(OR(COUNTA($A8:$F8)>0,$G8<>""),$N8/12*IF($F8="",1,MAX(0,(EOMONTH(_xlpm.m,0)-MAX($F8,_xlpm.m)+1)/(EOMONTH(_xlpm.m,0)-_xlpm.m+1))),"")) | U8: =_xlfn.LET(_xlpm.m,IF(ISNUMBER(U$4),DATE(YEAR(U$4),MONTH(U$4),1),DATEVALUE("1-"&U$4)),IF(OR(COUNTA($A8:$F8)>0,$G8<>""),$N8/12*IF($F8="",1,MAX(0,(EOMONTH(_xlpm.m,0)-MAX($F8,_xlpm.m)+1)/(EOMONTH(_xlpm.m,0)-_xlpm.m+1))),"")) | V8: =_xlfn.LET(_xlpm.m,IF(ISNUMBER(V$4),DATE(YEAR(V$4),MONTH(V$4),1),DATEVALUE("1-"&V$4)),IF(OR(COUNTA($A8:$F8)>0,$G8<>""),$N8/12*IF($F8="",1,MAX(0,(EOMONTH(_xlpm.m,0)-MAX($F8,_xlpm.m)+1)/(EOMONTH(_xlpm.m,0)-_xlpm.m+1))),"")) | ... Z8: =_xlfn.LET(_xlpm.m,IF(ISNUMBER(Z$4),DATE(YEAR(Z$4),MONTH(Z$4),1),DATEVALUE("1-"&Z$4)),IF(OR(COUNTA($A8:$F8)>0,$G8<>""),$N8/12*IF($F8="",1,MAX(0,(EOMONTH(_xlpm.m,0)-MAX($F8,_xlpm.m)+1)/(EOMONTH(_xlpm.m,0)-_xlpm.m+1))),"")) | AA8: =IF(COUNTA($A8:$H8)>0,SUM(O8:Z8),"") | AB8: =_xlfn.LET(_xlpm.m,IF(ISNUMBER(AB$4),DATE(YEAR(AB$4),MONTH(AB$4),1),DATEVALUE("1-"&AB$4)),IF(OR(COUNTA($A8:$F8)>0,$G8<>""),$N8/12*IF($F8="",1,MAX(0,(EOMONTH(_xlpm.m,0)-MAX($F8,_xlpm.m)+1)/(EOMONTH(_xlpm.m,0)-_xlpm.m+1))),"")) | AC8: =_xlfn.LET(_xlpm.m,IF(ISNUMBER(AC$4),DATE(YEAR(AC$4),MONTH(AC$4),1),DATEVALUE("1-"&AC$4)),IF(OR(COUNTA($A8:$F8)>0,$G8<>""),$N8/12*IF($F8="",1,MAX(0,(EOMONTH(_xlpm.m,0)-MAX($F8,_xlpm.m)+1)/(EOMONTH(_xlpm.m,0)-_xlpm.m+1))),"")) | AD8: =_xlfn.LET(_xlpm.m,IF(ISNUMBER(AD$4),DATE(YEAR(AD$4),MONTH(AD$4),1),DATEVALUE("1-"&AD$4)),IF(OR(COUNTA($A8:$F8)>0,$G8<>""),$N8/12*IF($F8="",1,MAX(0,(EOMONTH(_xlpm.m,0)-MAX($F8,_xlpm.m)+1)/(EOMONTH(_xlpm.m,0)-_xlpm.m+1))),"")) | AE8: =_xlfn.LET(_xlpm.m,IF(ISNUMBER(AE$4),DATE(YEAR(AE$4),MONTH(AE$4),1),DATEVALUE("1-"&AE$4)),IF(OR(COUNTA($A8:$F8)>0,$G8<>""),$N8/12*IF($F8="",1,MAX(0,(EOMONTH(_xlpm.m,0)-MAX($F8,_xlpm.m)+1)/(EOMONTH(_xlpm.m,0)-_xlpm.m+1))),"")) | AF8: =_xlfn.LET(_xlpm.m,IF(ISNUMBER(AF$4),DATE(YEAR(AF$4),MONTH(AF$4),1),DATEVALUE("1-"&AF$4)),IF(OR(COUNTA($A8:$F8)>0,$G8<>""),$N8/12*IF($F8="",1,MAX(0,(EOMONTH(_xlpm.m,0)-MAX($F8,_xlpm.m)+1)/(EOMONTH(_xlpm.m,0)-_xlpm.m+1))),"")) | AG8: =_xlfn.LET(_xlpm.m,IF(ISNUMBER(AG$4),DATE(YEAR(AG$4),MONTH(AG$4),1),DATEVALUE("1-"&AG$4)),IF(OR(COUNTA($A8:$F8)>0,$G8<>""),$N8/12*IF($F8="",1,MAX(0,(EOMONTH(_xlpm.m,0)-MAX($F8,_xlpm.m)+1)/(EOMONTH(_xlpm.m,0)-_xlpm.m+1))),"")) | AH8: =_xlfn.LET(_xlpm.m,IF(ISNUMBER(AH$4),DATE(YEAR(AH$4),MONTH(AH$4),1),DATEVALUE("1-"&AH$4)),IF(OR(COUNTA($A8:$F8)>0,$G8<>""),$N8/12*IF($F8="",1,MAX(0,(EOMONTH(_xlpm.m,0)-MAX($F8,_xlpm.m)+1)/(EOMONTH(_xlpm.m,0)-_xlpm.m+1))),"")) | AI8: =_xlfn.LET(_xlpm.m,IF(ISNUMBER(AI$4),DATE(YEAR(AI$4),MONTH(AI$4),1),DATEVALUE("1-"&AI$4)),IF(OR(COUNTA($A8:$F8)>0,$G8<>""),$N8/12*IF($F8="",1,MAX(0,(EOMONTH(_xlpm.m,0)-MAX($F8,_xlpm.m)+1)/(EOMONTH(_xlpm.m,0)-_xlpm.m+1))),"")) | ... AM8: =_xlfn.LET(_xlpm.m,IF(ISNUMBER(AM$4),DATE(YEAR(AM$4),MONTH(AM$4),1),DATEVALUE("1-"&AM$4)),IF(OR(COUNTA($A8:$F8)>0,$G8<>""),$N8/12*IF($F8="",1,MAX(0,(EOMONTH(_xlpm.m,0)-MAX($F8,_xlpm.m)+1)/(EOMONTH(_xlpm.m,0)-_xlpm.m+1))),"")) | AN8: =IF(COUNTA($A8:$H8)>0,SUM(AB8:AM8),"") | AO8: =_xlfn.LET(_xlpm.m,IF(ISNUMBER(AO$4),DATE(YEAR(AO$4),MONTH(AO$4),1),DATEVALUE("1-"&AO$4)),IF(OR(COUNTA($A8:$F8)>0,$G8<>""),$N8/12*IF($F8="",1,MAX(0,(EOMONTH(_xlpm.m,0)-MAX($F8,_xlpm.m)+1)/(EOMONTH(_xlpm.m,0)-_xlpm.m+1))),"")) | AP8: =_xlfn.LET(_xlpm.m,IF(ISNUMBER(AP$4),DATE(YEAR(AP$4),MONTH(AP$4),1),DATEVALUE("1-"&AP$4)),IF(OR(COUNTA($A8:$F8)>0,$G8<>""),$N8/12*IF($F8="",1,MAX(0,(EOMONTH(_xlpm.m,0)-MAX($F8,_xlpm.m)+1)/(EOMONTH(_xlpm.m,0)-_xlpm.m+1))),"")) | AQ8: =_xlfn.LET(_xlpm.m,IF(ISNUMBER(AQ$4),DATE(YEAR(AQ$4),MONTH(AQ$4),1),DATEVALUE("1-"&AQ$4)),IF(OR(COUNTA($A8:$F8)>0,$G8<>""),$N8/12*IF($F8="",1,MAX(0,(EOMONTH(_xlpm.m,0)-MAX($F8,_xlpm.m)+1)/(EOMONTH(_xlpm.m,0)-_xlpm.m+1))),"")) | AR8: =_xlfn.LET(_xlpm.m,IF(ISNUMBER(AR$4),DATE(YEAR(AR$4),MONTH(AR$4),1),DATEVALUE("1-"&AR$4)),IF(OR(COUNTA($A8:$F8)>0,$G8<>""),$N8/12*IF($F8="",1,MAX(0,(EOMONTH(_xlpm.m,0)-MAX($F8,_xlpm.m)+1)/(EOMONTH(_xlpm.m,0)-_xlpm.m+1))),"")) | AS8: =_xlfn.LET(_xlpm.m,IF(ISNUMBER(AS$4),DATE(YEAR(AS$4),MONTH(AS$4),1),DATEVALUE("1-"&AS$4)),IF(OR(COUNTA($A8:$F8)>0,$G8<>""),$N8/12*IF($F8="",1,MAX(0,(EOMONTH(_xlpm.m,0)-MAX($F8,_xlpm.m)+1)/(EOMONTH(_xlpm.m,0)-_xlpm.m+1))),"")) | AT8: =_xlfn.LET(_xlpm.m,IF(ISNUMBER(AT$4),DATE(YEAR(AT$4),MONTH(AT$4),1),DATEVALUE("1-"&AT$4)),IF(OR(COUNTA($A8:$F8)>0,$G8<>""),$N8/12*IF($F8="",1,MAX(0,(EOMONTH(_xlpm.m,0)-MAX($F8,_xlpm.m)+1)/(EOMONTH(_xlpm.m,0)-_xlpm.m+1))),"")) | AU8: =_xlfn.LET(_xlpm.m,IF(ISNUMBER(AU$4),DATE(YEAR(AU$4),MONTH(AU$4),1),DATEVALUE("1-"&AU$4)),IF(OR(COUNTA($A8:$F8)>0,$G8<>""),$N8/12*IF($F8="",1,MAX(0,(EOMONTH(_xlpm.m,0)-MAX($F8,_xlpm.m)+1)/(EOMONTH(_xlpm.m,0)-_xlpm.m+1))),"")) | AV8: =_xlfn.LET(_xlpm.m,IF(ISNUMBER(AV$4),DATE(YEAR(AV$4),MONTH(AV$4),1),DATEVALUE("1-"&AV$4)),IF(OR(COUNTA($A8:$F8)>0,$G8<>""),$N8/12*IF($F8="",1,MAX(0,(EOMONTH(_xlpm.m,0)-MAX($F8,_xlpm.m)+1)/(EOMONTH(_xlpm.m,0)-_xlpm.m+1))),"")) | ... AZ8: =_xlfn.LET(_xlpm.m,IF(ISNUMBER(AZ$4),DATE(YEAR(AZ$4),MONTH(AZ$4),1),DATEVALUE("1-"&AZ$4)),IF(OR(COUNTA($A8:$F8)>0,$G8<>""),$N8/12*IF($F8="",1,MAX(0,(EOMONTH(_xlpm.m,0)-MAX($F8,_xlpm.m)+1)/(EOMONTH(_xlpm.m,0)-_xlpm.m+1))),"")) | BA8: =IF(COUNTA($A8:$H8)>0,SUM(AO8:AZ8),"")
I9: =IF(COUNTA($A9:$H9)>0,IFERROR($G9*$H9,0),"") | J9: =IF(COUNTA($A9:$H9)>0,IFERROR($G9*Summary!$C$46/Summary!$C$43,0),"") | K9: =IF(COUNTA($A9:$H9)>0,IFERROR($G9*Summary!$C$47/Summary!$C$43,0),"") | L9: =IF(COUNTA($A9:$H9)>0,IFERROR($G9*Summary!$C$48/Summary!$C$43,0),"") | M9: =IF(COUNTA($A9:$H9)>0,IFERROR($G9*Summary!$C$49/Summary!$C$43,0),"") | N9: =IF(COUNTA($A9:$H9)>0,IFERROR($G9,0)+SUM(I9:M9),"") | O9: =_xlfn.LET(_xlpm.m,IF(ISNUMBER(O$4),DATE(YEAR(O$4),MONTH(O$4),1),DATEVALUE("1-"&O$4)),IF(OR(COUNTA($A9:$F9)>0,$G9<>""),$N9/12*IF($F9="",1,MAX(0,(EOMONTH(_xlpm.m,0)-MAX($F9,_xlpm.m)+1)/(EOMONTH(_xlpm.m,0)-_xlpm.m+1))),"")) | P9: =_xlfn.LET(_xlpm.m,IF(ISNUMBER(P$4),DATE(YEAR(P$4),MONTH(P$4),1),DATEVALUE("1-"&P$4)),IF(OR(COUNTA($A9:$F9)>0,$G9<>""),$N9/12*IF($F9="",1,MAX(0,(EOMONTH(_xlpm.m,0)-MAX($F9,_xlpm.m)+1)/(EOMONTH(_xlpm.m,0)-_xlpm.m+1))),"")) | Q9: =_xlfn.LET(_xlpm.m,IF(ISNUMBER(Q$4),DATE(YEAR(Q$4),MONTH(Q$4),1),DATEVALUE("1-"&Q$4)),IF(OR(COUNTA($A9:$F9)>0,$G9<>""),$N9/12*IF($F9="",1,MAX(0,(EOMONTH(_xlpm.m,0)-MAX($F9,_xlpm.m)+1)/(EOMONTH(_xlpm.m,0)-_xlpm.m+1))),"")) | R9: =_xlfn.LET(_xlpm.m,IF(ISNUMBER(R$4),DATE(YEAR(R$4),MONTH(R$4),1),DATEVALUE("1-"&R$4)),IF(OR(COUNTA($A9:$F9)>0,$G9<>""),$N9/12*IF($F9="",1,MAX(0,(EOMONTH(_xlpm.m,0)-MAX($F9,_xlpm.m)+1)/(EOMONTH(_xlpm.m,0)-_xlpm.m+1))),"")) | S9: =_xlfn.LET(_xlpm.m,IF(ISNUMBER(S$4),DATE(YEAR(S$4),MONTH(S$4),1),DATEVALUE("1-"&S$4)),IF(OR(COUNTA($A9:$F9)>0,$G9<>""),$N9/12*IF($F9="",1,MAX(0,(EOMONTH(_xlpm.m,0)-MAX($F9,_xlpm.m)+1)/(EOMONTH(_xlpm.m,0)-_xlpm.m+1))),"")) | T9: =_xlfn.LET(_xlpm.m,IF(ISNUMBER(T$4),DATE(YEAR(T$4),MONTH(T$4),1),DATEVALUE("1-"&T$4)),IF(OR(COUNTA($A9:$F9)>0,$G9<>""),$N9/12*IF($F9="",1,MAX(0,(EOMONTH(_xlpm.m,0)-MAX($F9,_xlpm.m)+1)/(EOMONTH(_xlpm.m,0)-_xlpm.m+1))),"")) | U9: =_xlfn.LET(_xlpm.m,IF(ISNUMBER(U$4),DATE(YEAR(U$4),MONTH(U$4),1),DATEVALUE("1-"&U$4)),IF(OR(COUNTA($A9:$F9)>0,$G9<>""),$N9/12*IF($F9="",1,MAX(0,(EOMONTH(_xlpm.m,0)-MAX($F9,_xlpm.m)+1)/(EOMONTH(_xlpm.m,0)-_xlpm.m+1))),"")) | V9: =_xlfn.LET(_xlpm.m,IF(ISNUMBER(V$4),DATE(YEAR(V$4),MONTH(V$4),1),DATEVALUE("1-"&V$4)),IF(OR(COUNTA($A9:$F9)>0,$G9<>""),$N9/12*IF($F9="",1,MAX(0,(EOMONTH(_xlpm.m,0)-MAX($F9,_xlpm.m)+1)/(EOMONTH(_xlpm.m,0)-_xlpm.m+1))),"")) | ... Z9: =_xlfn.LET(_xlpm.m,IF(ISNUMBER(Z$4),DATE(YEAR(Z$4),MONTH(Z$4),1),DATEVALUE("1-"&Z$4)),IF(OR(COUNTA($A9:$F9)>0,$G9<>""),$N9/12*IF($F9="",1,MAX(0,(EOMONTH(_xlpm.m,0)-MAX($F9,_xlpm.m)+1)/(EOMONTH(_xlpm.m,0)-_xlpm.m+1))),"")) | AA9: =IF(COUNTA($A9:$H9)>0,SUM(O9:Z9),"") | AB9: =_xlfn.LET(_xlpm.m,IF(ISNUMBER(AB$4),DATE(YEAR(AB$4),MONTH(AB$4),1),DATEVALUE("1-"&AB$4)),IF(OR(COUNTA($A9:$F9)>0,$G9<>""),$N9/12*IF($F9="",1,MAX(0,(EOMONTH(_xlpm.m,0)-MAX($F9,_xlpm.m)+1)/(EOMONTH(_xlpm.m,0)-_xlpm.m+1))),"")) | AC9: =_xlfn.LET(_xlpm.m,IF(ISNUMBER(AC$4),DATE(YEAR(AC$4),MONTH(AC$4),1),DATEVALUE("1-"&AC$4)),IF(OR(COUNTA($A9:$F9)>0,$G9<>""),$N9/12*IF($F9="",1,MAX(0,(EOMONTH(_xlpm.m,0)-MAX($F9,_xlpm.m)+1)/(EOMONTH(_xlpm.m,0)-_xlpm.m+1))),"")) | AD9: =_xlfn.LET(_xlpm.m,IF(ISNUMBER(AD$4),DATE(YEAR(AD$4),MONTH(AD$4),1),DATEVALUE("1-"&AD$4)),IF(OR(COUNTA($A9:$F9)>0,$G9<>""),$N9/12*IF($F9="",1,MAX(0,(EOMONTH(_xlpm.m,0)-MAX($F9,_xlpm.m)+1)/(EOMONTH(_xlpm.m,0)-_xlpm.m+1))),"")) | AE9: =_xlfn.LET(_xlpm.m,IF(ISNUMBER(AE$4),DATE(YEAR(AE$4),MONTH(AE$4),1),DATEVALUE("1-"&AE$4)),IF(OR(COUNTA($A9:$F9)>0,$G9<>""),$N9/12*IF($F9="",1,MAX(0,(EOMONTH(_xlpm.m,0)-MAX($F9,_xlpm.m)+1)/(EOMONTH(_xlpm.m,0)-_xlpm.m+1))),"")) | AF9: =_xlfn.LET(_xlpm.m,IF(ISNUMBER(AF$4),DATE(YEAR(AF$4),MONTH(AF$4),1),DATEVALUE("1-"&AF$4)),IF(OR(COUNTA($A9:$F9)>0,$G9<>""),$N9/12*IF($F9="",1,MAX(0,(EOMONTH(_xlpm.m,0)-MAX($F9,_xlpm.m)+1)/(EOMONTH(_xlpm.m,0)-_xlpm.m+1))),"")) | AG9: =_xlfn.LET(_xlpm.m,IF(ISNUMBER(AG$4),DATE(YEAR(AG$4),MONTH(AG$4),1),DATEVALUE("1-"&AG$4)),IF(OR(COUNTA($A9:$F9)>0,$G9<>""),$N9/12*IF($F9="",1,MAX(0,(EOMONTH(_xlpm.m,0)-MAX($F9,_xlpm.m)+1)/(EOMONTH(_xlpm.m,0)-_xlpm.m+1))),"")) | AH9: =_xlfn.LET(_xlpm.m,IF(ISNUMBER(AH$4),DATE(YEAR(AH$4),MONTH(AH$4),1),DATEVALUE("1-"&AH$4)),IF(OR(COUNTA($A9:$F9)>0,$G9<>""),$N9/12*IF($F9="",1,MAX(0,(EOMONTH(_xlpm.m,0)-MAX($F9,_xlpm.m)+1)/(EOMONTH(_xlpm.m,0)-_xlpm.m+1))),"")) | AI9: =_xlfn.LET(_xlpm.m,IF(ISNUMBER(AI$4),DATE(YEAR(AI$4),MONTH(AI$4),1),DATEVALUE("1-"&AI$4)),IF(OR(COUNTA($A9:$F9)>0,$G9<>""),$N9/12*IF($F9="",1,MAX(0,(EOMONTH(_xlpm.m,0)-MAX($F9,_xlpm.m)+1)/(EOMONTH(_xlpm.m,0)-_xlpm.m+1))),"")) | ... AM9: =_xlfn.LET(_xlpm.m,IF(ISNUMBER(AM$4),DATE(YEAR(AM$4),MONTH(AM$4),1),DATEVALUE("1-"&AM$4)),IF(OR(COUNTA($A9:$F9)>0,$G9<>""),$N9/12*IF($F9="",1,MAX(0,(EOMONTH(_xlpm.m,0)-MAX($F9,_xlpm.m)+1)/(EOMONTH(_xlpm.m,0)-_xlpm.m+1))),"")) | AN9: =IF(COUNTA($A9:$H9)>0,SUM(AB9:AM9),"") | AO9: =_xlfn.LET(_xlpm.m,IF(ISNUMBER(AO$4),DATE(YEAR(AO$4),MONTH(AO$4),1),DATEVALUE("1-"&AO$4)),IF(OR(COUNTA($A9:$F9)>0,$G9<>""),$N9/12*IF($F9="",1,MAX(0,(EOMONTH(_xlpm.m,0)-MAX($F9,_xlpm.m)+1)/(EOMONTH(_xlpm.m,0)-_xlpm.m+1))),"")) | AP9: =_xlfn.LET(_xlpm.m,IF(ISNUMBER(AP$4),DATE(YEAR(AP$4),MONTH(AP$4),1),DATEVALUE("1-"&AP$4)),IF(OR(COUNTA($A9:$F9)>0,$G9<>""),$N9/12*IF($F9="",1,MAX(0,(EOMONTH(_xlpm.m,0)-MAX($F9,_xlpm.m)+1)/(EOMONTH(_xlpm.m,0)-_xlpm.m+1))),"")) | AQ9: =_xlfn.LET(_xlpm.m,IF(ISNUMBER(AQ$4),DATE(YEAR(AQ$4),MONTH(AQ$4),1),DATEVALUE("1-"&AQ$4)),IF(OR(COUNTA($A9:$F9)>0,$G9<>""),$N9/12*IF($F9="",1,MAX(0,(EOMONTH(_xlpm.m,0)-MAX($F9,_xlpm.m)+1)/(EOMONTH(_xlpm.m,0)-_xlpm.m+1))),"")) | AR9: =_xlfn.LET(_xlpm.m,IF(ISNUMBER(AR$4),DATE(YEAR(AR$4),MONTH(AR$4),1),DATEVALUE("1-"&AR$4)),IF(OR(COUNTA($A9:$F9)>0,$G9<>""),$N9/12*IF($F9="",1,MAX(0,(EOMONTH(_xlpm.m,0)-MAX($F9,_xlpm.m)+1)/(EOMONTH(_xlpm.m,0)-_xlpm.m+1))),"")) | AS9: =_xlfn.LET(_xlpm.m,IF(ISNUMBER(AS$4),DATE(YEAR(AS$4),MONTH(AS$4),1),DATEVALUE("1-"&AS$4)),IF(OR(COUNTA($A9:$F9)>0,$G9<>""),$N9/12*IF($F9="",1,MAX(0,(EOMONTH(_xlpm.m,0)-MAX($F9,_xlpm.m)+1)/(EOMONTH(_xlpm.m,0)-_xlpm.m+1))),"")) | AT9: =_xlfn.LET(_xlpm.m,IF(ISNUMBER(AT$4),DATE(YEAR(AT$4),MONTH(AT$4),1),DATEVALUE("1-"&AT$4)),IF(OR(COUNTA($A9:$F9)>0,$G9<>""),$N9/12*IF($F9="",1,MAX(0,(EOMONTH(_xlpm.m,0)-MAX($F9,_xlpm.m)+1)/(EOMONTH(_xlpm.m,0)-_xlpm.m+1))),"")) | AU9: =_xlfn.LET(_xlpm.m,IF(ISNUMBER(AU$4),DATE(YEAR(AU$4),MONTH(AU$4),1),DATEVALUE("1-"&AU$4)),IF(OR(COUNTA($A9:$F9)>0,$G9<>""),$N9/12*IF($F9="",1,MAX(0,(EOMONTH(_xlpm.m,0)-MAX($F9,_xlpm.m)+1)/(EOMONTH(_xlpm.m,0)-_xlpm.m+1))),"")) | AV9: =_xlfn.LET(_xlpm.m,IF(ISNUMBER(AV$4),DATE(YEAR(AV$4),MONTH(AV$4),1),DATEVALUE("1-"&AV$4)),IF(OR(COUNTA($A9:$F9)>0,$G9<>""),$N9/12*IF($F9="",1,MAX(0,(EOMONTH(_xlpm.m,0)-MAX($F9,_xlpm.m)+1)/(EOMONTH(_xlpm.m,0)-_xlpm.m+1))),"")) | ... AZ9: =_xlfn.LET(_xlpm.m,IF(ISNUMBER(AZ$4),DATE(YEAR(AZ$4),MONTH(AZ$4),1),DATEVALUE("1-"&AZ$4)),IF(OR(COUNTA($A9:$F9)>0,$G9<>""),$N9/12*IF($F9="",1,MAX(0,(EOMONTH(_xlpm.m,0)-MAX($F9,_xlpm.m)+1)/(EOMONTH(_xlpm.m,0)-_xlpm.m+1))),"")) | BA9: =IF(COUNTA($A9:$H9)>0,SUM(AO9:AZ9),"")
I10: =IF(COUNTA($A10:$H10)>0,IFERROR($G10*$H10,0),"") | J10: =IF(COUNTA($A10:$H10)>0,IFERROR($G10*Summary!$C$46/Summary!$C$43,0),"") | K10: =IF(COUNTA($A10:$H10)>0,IFERROR($G10*Summary!$C$47/Summary!$C$43,0),"") | L10: =IF(COUNTA($A10:$H10)>0,IFERROR($G10*Summary!$C$48/Summary!$C$43,0),"") | M10: =IF(COUNTA($A10:$H10)>0,IFERROR($G10*Summary!$C$49/Summary!$C$43,0),"") | N10: =IF(COUNTA($A10:$H10)>0,IFERROR($G10,0)+SUM(I10:M10),"") | O10: =_xlfn.LET(_xlpm.m,IF(ISNUMBER(O$4),DATE(YEAR(O$4),MONTH(O$4),1),DATEVALUE("1-"&O$4)),IF(OR(COUNTA($A10:$F10)>0,$G10<>""),$N10/12*IF($F10="",1,MAX(0,(EOMONTH(_xlpm.m,0)-MAX($F10,_xlpm.m)+1)/(EOMONTH(_xlpm.m,0)-_xlpm.m+1))),"")) | P10: =_xlfn.LET(_xlpm.m,IF(ISNUMBER(P$4),DATE(YEAR(P$4),MONTH(P$4),1),DATEVALUE("1-"&P$4)),IF(OR(COUNTA($A10:$F10)>0,$G10<>""),$N10/12*IF($F10="",1,MAX(0,(EOMONTH(_xlpm.m,0)-MAX($F10,_xlpm.m)+1)/(EOMONTH(_xlpm.m,0)-_xlpm.m+1))),"")) | Q10: =_xlfn.LET(_xlpm.m,IF(ISNUMBER(Q$4),DATE(YEAR(Q$4),MONTH(Q$4),1),DATEVALUE("1-"&Q$4)),IF(OR(COUNTA($A10:$F10)>0,$G10<>""),$N10/12*IF($F10="",1,MAX(0,(EOMONTH(_xlpm.m,0)-MAX($F10,_xlpm.m)+1)/(EOMONTH(_xlpm.m,0)-_xlpm.m+1))),"")) | R10: =_xlfn.LET(_xlpm.m,IF(ISNUMBER(R$4),DATE(YEAR(R$4),MONTH(R$4),1),DATEVALUE("1-"&R$4)),IF(OR(COUNTA($A10:$F10)>0,$G10<>""),$N10/12*IF($F10="",1,MAX(0,(EOMONTH(_xlpm.m,0)-MAX($F10,_xlpm.m)+1)/(EOMONTH(_xlpm.m,0)-_xlpm.m+1))),"")) | S10: =_xlfn.LET(_xlpm.m,IF(ISNUMBER(S$4),DATE(YEAR(S$4),MONTH(S$4),1),DATEVALUE("1-"&S$4)),IF(OR(COUNTA($A10:$F10)>0,$G10<>""),$N10/12*IF($F10="",1,MAX(0,(EOMONTH(_xlpm.m,0)-MAX($F10,_xlpm.m)+1)/(EOMONTH(_xlpm.m,0)-_xlpm.m+1))),"")) | T10: =_xlfn.LET(_xlpm.m,IF(ISNUMBER(T$4),DATE(YEAR(T$4),MONTH(T$4),1),DATEVALUE("1-"&T$4)),IF(OR(COUNTA($A10:$F10)>0,$G10<>""),$N10/12*IF($F10="",1,MAX(0,(EOMONTH(_xlpm.m,0)-MAX($F10,_xlpm.m)+1)/(EOMONTH(_xlpm.m,0)-_xlpm.m+1))),"")) | U10: =_xlfn.LET(_xlpm.m,IF(ISNUMBER(U$4),DATE(YEAR(U$4),MONTH(U$4),1),DATEVALUE("1-"&U$4)),IF(OR(COUNTA($A10:$F10)>0,$G10<>""),$N10/12*IF($F10="",1,MAX(0,(EOMONTH(_xlpm.m,0)-MAX($F10,_xlpm.m)+1)/(EOMONTH(_xlpm.m,0)-_xlpm.m+1))),"")) | V10: =_xlfn.LET(_xlpm.m,IF(ISNUMBER(V$4),DATE(YEAR(V$4),MONTH(V$4),1),DATEVALUE("1-"&V$4)),IF(OR(COUNTA($A10:$F10)>0,$G10<>""),$N10/12*IF($F10="",1,MAX(0,(EOMONTH(_xlpm.m,0)-MAX($F10,_xlpm.m)+1)/(EOMONTH(_xlpm.m,0)-_xlpm.m+1))),"")) | ... Z10: =_xlfn.LET(_xlpm.m,IF(ISNUMBER(Z$4),DATE(YEAR(Z$4),MONTH(Z$4),1),DATEVALUE("1-"&Z$4)),IF(OR(COUNTA($A10:$F10)>0,$G10<>""),$N10/12*IF($F10="",1,MAX(0,(EOMONTH(_xlpm.m,0)-MAX($F10,_xlpm.m)+1)/(EOMONTH(_xlpm.m,0)-_xlpm.m+1))),"")) | AA10: =IF(COUNTA($A10:$H10)>0,SUM(O10:Z10),"") | AB10: =_xlfn.LET(_xlpm.m,IF(ISNUMBER(AB$4),DATE(YEAR(AB$4),MONTH(AB$4),1),DATEVALUE("1-"&AB$4)),IF(OR(COUNTA($A10:$F10)>0,$G10<>""),$N10/12*IF($F10="",1,MAX(0,(EOMONTH(_xlpm.m,0)-MAX($F10,_xlpm.m)+1)/(EOMONTH(_xlpm.m,0)-_xlpm.m+1))),"")) | AC10: =_xlfn.LET(_xlpm.m,IF(ISNUMBER(AC$4),DATE(YEAR(AC$4),MONTH(AC$4),1),DATEVALUE("1-"&AC$4)),IF(OR(COUNTA($A10:$F10)>0,$G10<>""),$N10/12*IF($F10="",1,MAX(0,(EOMONTH(_xlpm.m,0)-MAX($F10,_xlpm.m)+1)/(EOMONTH(_xlpm.m,0)-_xlpm.m+1))),"")) | AD10: =_xlfn.LET(_xlpm.m,IF(ISNUMBER(AD$4),DATE(YEAR(AD$4),MONTH(AD$4),1),DATEVALUE("1-"&AD$4)),IF(OR(COUNTA($A10:$F10)>0,$G10<>""),$N10/12*IF($F10="",1,MAX(0,(EOMONTH(_xlpm.m,0)-MAX($F10,_xlpm.m)+1)/(EOMONTH(_xlpm.m,0)-_xlpm.m+1))),"")) | AE10: =_xlfn.LET(_xlpm.m,IF(ISNUMBER(AE$4),DATE(YEAR(AE$4),MONTH(AE$4),1),DATEVALUE("1-"&AE$4)),IF(OR(COUNTA($A10:$F10)>0,$G10<>""),$N10/12*IF($F10="",1,MAX(0,(EOMONTH(_xlpm.m,0)-MAX($F10,_xlpm.m)+1)/(EOMONTH(_xlpm.m,0)-_xlpm.m+1))),"")) | AF10: =_xlfn.LET(_xlpm.m,IF(ISNUMBER(AF$4),DATE(YEAR(AF$4),MONTH(AF$4),1),DATEVALUE("1-"&AF$4)),IF(OR(COUNTA($A10:$F10)>0,$G10<>""),$N10/12*IF($F10="",1,MAX(0,(EOMONTH(_xlpm.m,0)-MAX($F10,_xlpm.m)+1)/(EOMONTH(_xlpm.m,0)-_xlpm.m+1))),"")) | AG10: =_xlfn.LET(_xlpm.m,IF(ISNUMBER(AG$4),DATE(YEAR(AG$4),MONTH(AG$4),1),DATEVALUE("1-"&AG$4)),IF(OR(COUNTA($A10:$F10)>0,$G10<>""),$N10/12*IF($F10="",1,MAX(0,(EOMONTH(_xlpm.m,0)-MAX($F10,_xlpm.m)+1)/(EOMONTH(_xlpm.m,0)-_xlpm.m+1))),"")) | AH10: =_xlfn.LET(_xlpm.m,IF(ISNUMBER(AH$4),DATE(YEAR(AH$4),MONTH(AH$4),1),DATEVALUE("1-"&AH$4)),IF(OR(COUNTA($A10:$F10)>0,$G10<>""),$N10/12*IF($F10="",1,MAX(0,(EOMONTH(_xlpm.m,0)-MAX($F10,_xlpm.m)+1)/(EOMONTH(_xlpm.m,0)-_xlpm.m+1))),"")) | AI10: =_xlfn.LET(_xlpm.m,IF(ISNUMBER(AI$4),DATE(YEAR(AI$4),MONTH(AI$4),1),DATEVALUE("1-"&AI$4)),IF(OR(COUNTA($A10:$F10)>0,$G10<>""),$N10/12*IF($F10="",1,MAX(0,(EOMONTH(_xlpm.m,0)-MAX($F10,_xlpm.m)+1)/(EOMONTH(_xlpm.m,0)-_xlpm.m+1))),"")) | ... AM10: =_xlfn.LET(_xlpm.m,IF(ISNUMBER(AM$4),DATE(YEAR(AM$4),MONTH(AM$4),1),DATEVALUE("1-"&AM$4)),IF(OR(COUNTA($A10:$F10)>0,$G10<>""),$N10/12*IF($F10="",1,MAX(0,(EOMONTH(_xlpm.m,0)-MAX($F10,_xlpm.m)+1)/(EOMONTH(_xlpm.m,0)-_xlpm.m+1))),"")) | AN10: =IF(COUNTA($A10:$H10)>0,SUM(AB10:AM10),"") | AO10: =_xlfn.LET(_xlpm.m,IF(ISNUMBER(AO$4),DATE(YEAR(AO$4),MONTH(AO$4),1),DATEVALUE("1-"&AO$4)),IF(OR(COUNTA($A10:$F10)>0,$G10<>""),$N10/12*IF($F10="",1,MAX(0,(EOMONTH(_xlpm.m,0)-MAX($F10,_xlpm.m)+1)/(EOMONTH(_xlpm.m,0)-_xlpm.m+1))),"")) | AP10: =_xlfn.LET(_xlpm.m,IF(ISNUMBER(AP$4),DATE(YEAR(AP$4),MONTH(AP$4),1),DATEVALUE("1-"&AP$4)),IF(OR(COUNTA($A10:$F10)>0,$G10<>""),$N10/12*IF($F10="",1,MAX(0,(EOMONTH(_xlpm.m,0)-MAX($F10,_xlpm.m)+1)/(EOMONTH(_xlpm.m,0)-_xlpm.m+1))),"")) | AQ10: =_xlfn.LET(_xlpm.m,IF(ISNUMBER(AQ$4),DATE(YEAR(AQ$4),MONTH(AQ$4),1),DATEVALUE("1-"&AQ$4)),IF(OR(COUNTA($A10:$F10)>0,$G10<>""),$N10/12*IF($F10="",1,MAX(0,(EOMONTH(_xlpm.m,0)-MAX($F10,_xlpm.m)+1)/(EOMONTH(_xlpm.m,0)-_xlpm.m+1))),"")) | AR10: =_xlfn.LET(_xlpm.m,IF(ISNUMBER(AR$4),DATE(YEAR(AR$4),MONTH(AR$4),1),DATEVALUE("1-"&AR$4)),IF(OR(COUNTA($A10:$F10)>0,$G10<>""),$N10/12*IF($F10="",1,MAX(0,(EOMONTH(_xlpm.m,0)-MAX($F10,_xlpm.m)+1)/(EOMONTH(_xlpm.m,0)-_xlpm.m+1))),"")) | AS10: =_xlfn.LET(_xlpm.m,IF(ISNUMBER(AS$4),DATE(YEAR(AS$4),MONTH(AS$4),1),DATEVALUE("1-"&AS$4)),IF(OR(COUNTA($A10:$F10)>0,$G10<>""),$N10/12*IF($F10="",1,MAX(0,(EOMONTH(_xlpm.m,0)-MAX($F10,_xlpm.m)+1)/(EOMONTH(_xlpm.m,0)-_xlpm.m+1))),"")) | AT10: =_xlfn.LET(_xlpm.m,IF(ISNUMBER(AT$4),DATE(YEAR(AT$4),MONTH(AT$4),1),DATEVALUE("1-"&AT$4)),IF(OR(COUNTA($A10:$F10)>0,$G10<>""),$N10/12*IF($F10="",1,MAX(0,(EOMONTH(_xlpm.m,0)-MAX($F10,_xlpm.m)+1)/(EOMONTH(_xlpm.m,0)-_xlpm.m+1))),"")) | AU10: =_xlfn.LET(_xlpm.m,IF(ISNUMBER(AU$4),DATE(YEAR(AU$4),MONTH(AU$4),1),DATEVALUE("1-"&AU$4)),IF(OR(COUNTA($A10:$F10)>0,$G10<>""),$N10/12*IF($F10="",1,MAX(0,(EOMONTH(_xlpm.m,0)-MAX($F10,_xlpm.m)+1)/(EOMONTH(_xlpm.m,0)-_xlpm.m+1))),"")) | AV10: =_xlfn.LET(_xlpm.m,IF(ISNUMBER(AV$4),DATE(YEAR(AV$4),MONTH(AV$4),1),DATEVALUE("1-"&AV$4)),IF(OR(COUNTA($A10:$F10)>0,$G10<>""),$N10/12*IF($F10="",1,MAX(0,(EOMONTH(_xlpm.m,0)-MAX($F10,_xlpm.m)+1)/(EOMONTH(_xlpm.m,0)-_xlpm.m+1))),"")) | ... AZ10: =_xlfn.LET(_xlpm.m,IF(ISNUMBER(AZ$4),DATE(YEAR(AZ$4),MONTH(AZ$4),1),DATEVALUE("1-"&AZ$4)),IF(OR(COUNTA($A10:$F10)>0,$G10<>""),$N10/12*IF($F10="",1,MAX(0,(EOMONTH(_xlpm.m,0)-MAX($F10,_xlpm.m)+1)/(EOMONTH(_xlpm.m,0)-_xlpm.m+1))),"")) | BA10: =IF(COUNTA($A10:$H10)>0,SUM(AO10:AZ10),"")
I11: =IF(COUNTA($A11:$H11)>0,IFERROR($G11*$H11,0),"") | J11: =IF(COUNTA($A11:$H11)>0,IFERROR($G11*Summary!$C$46/Summary!$C$43,0),"") | K11: =IF(COUNTA($A11:$H11)>0,IFERROR($G11*Summary!$C$47/Summary!$C$43,0),"") | L11: =IF(COUNTA($A11:$H11)>0,IFERROR($G11*Summary!$C$48/Summary!$C$43,0),"") | M11: =IF(COUNTA($A11:$H11)>0,IFERROR($G11*Summary!$C$49/Summary!$C$43,0),"") | N11: =IF(COUNTA($A11:$H11)>0,IFERROR($G11,0)+SUM(I11:M11),"") | O11: =_xlfn.LET(_xlpm.m,IF(ISNUMBER(O$4),DATE(YEAR(O$4),MONTH(O$4),1),DATEVALUE("1-"&O$4)),IF(OR(COUNTA($A11:$F11)>0,$G11<>""),$N11/12*IF($F11="",1,MAX(0,(EOMONTH(_xlpm.m,0)-MAX($F11,_xlpm.m)+1)/(EOMONTH(_xlpm.m,0)-_xlpm.m+1))),"")) | P11: =_xlfn.LET(_xlpm.m,IF(ISNUMBER(P$4),DATE(YEAR(P$4),MONTH(P$4),1),DATEVALUE("1-"&P$4)),IF(OR(COUNTA($A11:$F11)>0,$G11<>""),$N11/12*IF($F11="",1,MAX(0,(EOMONTH(_xlpm.m,0)-MAX($F11,_xlpm.m)+1)/(EOMONTH(_xlpm.m,0)-_xlpm.m+1))),"")) | Q11: =_xlfn.LET(_xlpm.m,IF(ISNUMBER(Q$4),DATE(YEAR(Q$4),MONTH(Q$4),1),DATEVALUE("1-"&Q$4)),IF(OR(COUNTA($A11:$F11)>0,$G11<>""),$N11/12*IF($F11="",1,MAX(0,(EOMONTH(_xlpm.m,0)-MAX($F11,_xlpm.m)+1)/(EOMONTH(_xlpm.m,0)-_xlpm.m+1))),"")) | R11: =_xlfn.LET(_xlpm.m,IF(ISNUMBER(R$4),DATE(YEAR(R$4),MONTH(R$4),1),DATEVALUE("1-"&R$4)),IF(OR(COUNTA($A11:$F11)>0,$G11<>""),$N11/12*IF($F11="",1,MAX(0,(EOMONTH(_xlpm.m,0)-MAX($F11,_xlpm.m)+1)/(EOMONTH(_xlpm.m,0)-_xlpm.m+1))),"")) | S11: =_xlfn.LET(_xlpm.m,IF(ISNUMBER(S$4),DATE(YEAR(S$4),MONTH(S$4),1),DATEVALUE("1-"&S$4)),IF(OR(COUNTA($A11:$F11)>0,$G11<>""),$N11/12*IF($F11="",1,MAX(0,(EOMONTH(_xlpm.m,0)-MAX($F11,_xlpm.m)+1)/(EOMONTH(_xlpm.m,0)-_xlpm.m+1))),"")) | T11: =_xlfn.LET(_xlpm.m,IF(ISNUMBER(T$4),DATE(YEAR(T$4),MONTH(T$4),1),DATEVALUE("1-"&T$4)),IF(OR(COUNTA($A11:$F11)>0,$G11<>""),$N11/12*IF($F11="",1,MAX(0,(EOMONTH(_xlpm.m,0)-MAX($F11,_xlpm.m)+1)/(EOMONTH(_xlpm.m,0)-_xlpm.m+1))),"")) | U11: =_xlfn.LET(_xlpm.m,IF(ISNUMBER(U$4),DATE(YEAR(U$4),MONTH(U$4),1),DATEVALUE("1-"&U$4)),IF(OR(COUNTA($A11:$F11)>0,$G11<>""),$N11/12*IF($F11="",1,MAX(0,(EOMONTH(_xlpm.m,0)-MAX($F11,_xlpm.m)+1)/(EOMONTH(_xlpm.m,0)-_xlpm.m+1))),"")) | V11: =_xlfn.LET(_xlpm.m,IF(ISNUMBER(V$4),DATE(YEAR(V$4),MONTH(V$4),1),DATEVALUE("1-"&V$4)),IF(OR(COUNTA($A11:$F11)>0,$G11<>""),$N11/12*IF($F11="",1,MAX(0,(EOMONTH(_xlpm.m,0)-MAX($F11,_xlpm.m)+1)/(EOMONTH(_xlpm.m,0)-_xlpm.m+1))),"")) | ... Z11: =_xlfn.LET(_xlpm.m,IF(ISNUMBER(Z$4),DATE(YEAR(Z$4),MONTH(Z$4),1),DATEVALUE("1-"&Z$4)),IF(OR(COUNTA($A11:$F11)>0,$G11<>""),$N11/12*IF($F11="",1,MAX(0,(EOMONTH(_xlpm.m,0)-MAX($F11,_xlpm.m)+1)/(EOMONTH(_xlpm.m,0)-_xlpm.m+1))),"")) | AA11: =IF(COUNTA($A11:$H11)>0,SUM(O11:Z11),"") | AB11: =_xlfn.LET(_xlpm.m,IF(ISNUMBER(AB$4),DATE(YEAR(AB$4),MONTH(AB$4),1),DATEVALUE("1-"&AB$4)),IF(OR(COUNTA($A11:$F11)>0,$G11<>""),$N11/12*IF($F11="",1,MAX(0,(EOMONTH(_xlpm.m,0)-MAX($F11,_xlpm.m)+1)/(EOMONTH(_xlpm.m,0)-_xlpm.m+1))),"")) | AC11: =_xlfn.LET(_xlpm.m,IF(ISNUMBER(AC$4),DATE(YEAR(AC$4),MONTH(AC$4),1),DATEVALUE("1-"&AC$4)),IF(OR(COUNTA($A11:$F11)>0,$G11<>""),$N11/12*IF($F11="",1,MAX(0,(EOMONTH(_xlpm.m,0)-MAX($F11,_xlpm.m)+1)/(EOMONTH(_xlpm.m,0)-_xlpm.m+1))),"")) | AD11: =_xlfn.LET(_xlpm.m,IF(ISNUMBER(AD$4),DATE(YEAR(AD$4),MONTH(AD$4),1),DATEVALUE("1-"&AD$4)),IF(OR(COUNTA($A11:$F11)>0,$G11<>""),$N11/12*IF($F11="",1,MAX(0,(EOMONTH(_xlpm.m,0)-MAX($F11,_xlpm.m)+1)/(EOMONTH(_xlpm.m,0)-_xlpm.m+1))),"")) | AE11: =_xlfn.LET(_xlpm.m,IF(ISNUMBER(AE$4),DATE(YEAR(AE$4),MONTH(AE$4),1),DATEVALUE("1-"&AE$4)),IF(OR(COUNTA($A11:$F11)>0,$G11<>""),$N11/12*IF($F11="",1,MAX(0,(EOMONTH(_xlpm.m,0)-MAX($F11,_xlpm.m)+1)/(EOMONTH(_xlpm.m,0)-_xlpm.m+1))),"")) | AF11: =_xlfn.LET(_xlpm.m,IF(ISNUMBER(AF$4),DATE(YEAR(AF$4),MONTH(AF$4),1),DATEVALUE("1-"&AF$4)),IF(OR(COUNTA($A11:$F11)>0,$G11<>""),$N11/12*IF($F11="",1,MAX(0,(EOMONTH(_xlpm.m,0)-MAX($F11,_xlpm.m)+1)/(EOMONTH(_xlpm.m,0)-_xlpm.m+1))),"")) | AG11: =_xlfn.LET(_xlpm.m,IF(ISNUMBER(AG$4),DATE(YEAR(AG$4),MONTH(AG$4),1),DATEVALUE("1-"&AG$4)),IF(OR(COUNTA($A11:$F11)>0,$G11<>""),$N11/12*IF($F11="",1,MAX(0,(EOMONTH(_xlpm.m,0)-MAX($F11,_xlpm.m)+1)/(EOMONTH(_xlpm.m,0)-_xlpm.m+1))),"")) | AH11: =_xlfn.LET(_xlpm.m,IF(ISNUMBER(AH$4),DATE(YEAR(AH$4),MONTH(AH$4),1),DATEVALUE("1-"&AH$4)),IF(OR(COUNTA($A11:$F11)>0,$G11<>""),$N11/12*IF($F11="",1,MAX(0,(EOMONTH(_xlpm.m,0)-MAX($F11,_xlpm.m)+1)/(EOMONTH(_xlpm.m,0)-_xlpm.m+1))),"")) | AI11: =_xlfn.LET(_xlpm.m,IF(ISNUMBER(AI$4),DATE(YEAR(AI$4),MONTH(AI$4),1),DATEVALUE("1-"&AI$4)),IF(OR(COUNTA($A11:$F11)>0,$G11<>""),$N11/12*IF($F11="",1,MAX(0,(EOMONTH(_xlpm.m,0)-MAX($F11,_xlpm.m)+1)/(EOMONTH(_xlpm.m,0)-_xlpm.m+1))),"")) | ... AM11: =_xlfn.LET(_xlpm.m,IF(ISNUMBER(AM$4),DATE(YEAR(AM$4),MONTH(AM$4),1),DATEVALUE("1-"&AM$4)),IF(OR(COUNTA($A11:$F11)>0,$G11<>""),$N11/12*IF($F11="",1,MAX(0,(EOMONTH(_xlpm.m,0)-MAX($F11,_xlpm.m)+1)/(EOMONTH(_xlpm.m,0)-_xlpm.m+1))),"")) | AN11: =IF(COUNTA($A11:$H11)>0,SUM(AB11:AM11),"") | AO11: =_xlfn.LET(_xlpm.m,IF(ISNUMBER(AO$4),DATE(YEAR(AO$4),MONTH(AO$4),1),DATEVALUE("1-"&AO$4)),IF(OR(COUNTA($A11:$F11)>0,$G11<>""),$N11/12*IF($F11="",1,MAX(0,(EOMONTH(_xlpm.m,0)-MAX($F11,_xlpm.m)+1)/(EOMONTH(_xlpm.m,0)-_xlpm.m+1))),"")) | AP11: =_xlfn.LET(_xlpm.m,IF(ISNUMBER(AP$4),DATE(YEAR(AP$4),MONTH(AP$4),1),DATEVALUE("1-"&AP$4)),IF(OR(COUNTA($A11:$F11)>0,$G11<>""),$N11/12*IF($F11="",1,MAX(0,(EOMONTH(_xlpm.m,0)-MAX($F11,_xlpm.m)+1)/(EOMONTH(_xlpm.m,0)-_xlpm.m+1))),"")) | AQ11: =_xlfn.LET(_xlpm.m,IF(ISNUMBER(AQ$4),DATE(YEAR(AQ$4),MONTH(AQ$4),1),DATEVALUE("1-"&AQ$4)),IF(OR(COUNTA($A11:$F11)>0,$G11<>""),$N11/12*IF($F11="",1,MAX(0,(EOMONTH(_xlpm.m,0)-MAX($F11,_xlpm.m)+1)/(EOMONTH(_xlpm.m,0)-_xlpm.m+1))),"")) | AR11: =_xlfn.LET(_xlpm.m,IF(ISNUMBER(AR$4),DATE(YEAR(AR$4),MONTH(AR$4),1),DATEVALUE("1-"&AR$4)),IF(OR(COUNTA($A11:$F11)>0,$G11<>""),$N11/12*IF($F11="",1,MAX(0,(EOMONTH(_xlpm.m,0)-MAX($F11,_xlpm.m)+1)/(EOMONTH(_xlpm.m,0)-_xlpm.m+1))),"")) | AS11: =_xlfn.LET(_xlpm.m,IF(ISNUMBER(AS$4),DATE(YEAR(AS$4),MONTH(AS$4),1),DATEVALUE("1-"&AS$4)),IF(OR(COUNTA($A11:$F11)>0,$G11<>""),$N11/12*IF($F11="",1,MAX(0,(EOMONTH(_xlpm.m,0)-MAX($F11,_xlpm.m)+1)/(EOMONTH(_xlpm.m,0)-_xlpm.m+1))),"")) | AT11: =_xlfn.LET(_xlpm.m,IF(ISNUMBER(AT$4),DATE(YEAR(AT$4),MONTH(AT$4),1),DATEVALUE("1-"&AT$4)),IF(OR(COUNTA($A11:$F11)>0,$G11<>""),$N11/12*IF($F11="",1,MAX(0,(EOMONTH(_xlpm.m,0)-MAX($F11,_xlpm.m)+1)/(EOMONTH(_xlpm.m,0)-_xlpm.m+1))),"")) | AU11: =_xlfn.LET(_xlpm.m,IF(ISNUMBER(AU$4),DATE(YEAR(AU$4),MONTH(AU$4),1),DATEVALUE("1-"&AU$4)),IF(OR(COUNTA($A11:$F11)>0,$G11<>""),$N11/12*IF($F11="",1,MAX(0,(EOMONTH(_xlpm.m,0)-MAX($F11,_xlpm.m)+1)/(EOMONTH(_xlpm.m,0)-_xlpm.m+1))),"")) | AV11: =_xlfn.LET(_xlpm.m,IF(ISNUMBER(AV$4),DATE(YEAR(AV$4),MONTH(AV$4),1),DATEVALUE("1-"&AV$4)),IF(OR(COUNTA($A11:$F11)>0,$G11<>""),$N11/12*IF($F11="",1,MAX(0,(EOMONTH(_xlpm.m,0)-MAX($F11,_xlpm.m)+1)/(EOMONTH(_xlpm.m,0)-_xlpm.m+1))),"")) | ... AZ11: =_xlfn.LET(_xlpm.m,IF(ISNUMBER(AZ$4),DATE(YEAR(AZ$4),MONTH(AZ$4),1),DATEVALUE("1-"&AZ$4)),IF(OR(COUNTA($A11:$F11)>0,$G11<>""),$N11/12*IF($F11="",1,MAX(0,(EOMONTH(_xlpm.m,0)-MAX($F11,_xlpm.m)+1)/(EOMONTH(_xlpm.m,0)-_xlpm.m+1))),"")) | BA11: =IF(COUNTA($A11:$H11)>0,SUM(AO11:AZ11),"")
I12: =IF(COUNTA($A12:$H12)>0,IFERROR($G12*$H12,0),"") | J12: =IF(COUNTA($A12:$H12)>0,IFERROR($G12*Summary!$C$46/Summary!$C$43,0),"") | K12: =IF(COUNTA($A12:$H12)>0,IFERROR($G12*Summary!$C$47/Summary!$C$43,0),"") | L12: =IF(COUNTA($A12:$H12)>0,IFERROR($G12*Summary!$C$48/Summary!$C$43,0),"") | M12: =IF(COUNTA($A12:$H12)>0,IFERROR($G12*Summary!$C$49/Summary!$C$43,0),"") | N12: =IF(COUNTA($A12:$H12)>0,IFERROR($G12,0)+SUM(I12:M12),"") | O12: =_xlfn.LET(_xlpm.m,IF(ISNUMBER(O$4),DATE(YEAR(O$4),MONTH(O$4),1),DATEVALUE("1-"&O$4)),IF(OR(COUNTA($A12:$F12)>0,$G12<>""),$N12/12*IF($F12="",1,MAX(0,(EOMONTH(_xlpm.m,0)-MAX($F12,_xlpm.m)+1)/(EOMONTH(_xlpm.m,0)-_xlpm.m+1))),"")) | P12: =_xlfn.LET(_xlpm.m,IF(ISNUMBER(P$4),DATE(YEAR(P$4),MONTH(P$4),1),DATEVALUE("1-"&P$4)),IF(OR(COUNTA($A12:$F12)>0,$G12<>""),$N12/12*IF($F12="",1,MAX(0,(EOMONTH(_xlpm.m,0)-MAX($F12,_xlpm.m)+1)/(EOMONTH(_xlpm.m,0)-_xlpm.m+1))),"")) | Q12: =_xlfn.LET(_xlpm.m,IF(ISNUMBER(Q$4),DATE(YEAR(Q$4),MONTH(Q$4),1),DATEVALUE("1-"&Q$4)),IF(OR(COUNTA($A12:$F12)>0,$G12<>""),$N12/12*IF($F12="",1,MAX(0,(EOMONTH(_xlpm.m,0)-MAX($F12,_xlpm.m)+1)/(EOMONTH(_xlpm.m,0)-_xlpm.m+1))),"")) | R12: =_xlfn.LET(_xlpm.m,IF(ISNUMBER(R$4),DATE(YEAR(R$4),MONTH(R$4),1),DATEVALUE("1-"&R$4)),IF(OR(COUNTA($A12:$F12)>0,$G12<>""),$N12/12*IF($F12="",1,MAX(0,(EOMONTH(_xlpm.m,0)-MAX($F12,_xlpm.m)+1)/(EOMONTH(_xlpm.m,0)-_xlpm.m+1))),"")) | S12: =_xlfn.LET(_xlpm.m,IF(ISNUMBER(S$4),DATE(YEAR(S$4),MONTH(S$4),1),DATEVALUE("1-"&S$4)),IF(OR(COUNTA($A12:$F12)>0,$G12<>""),$N12/12*IF($F12="",1,MAX(0,(EOMONTH(_xlpm.m,0)-MAX($F12,_xlpm.m)+1)/(EOMONTH(_xlpm.m,0)-_xlpm.m+1))),"")) | T12: =_xlfn.LET(_xlpm.m,IF(ISNUMBER(T$4),DATE(YEAR(T$4),MONTH(T$4),1),DATEVALUE("1-"&T$4)),IF(OR(COUNTA($A12:$F12)>0,$G12<>""),$N12/12*IF($F12="",1,MAX(0,(EOMONTH(_xlpm.m,0)-MAX($F12,_xlpm.m)+1)/(EOMONTH(_xlpm.m,0)-_xlpm.m+1))),"")) | U12: =_xlfn.LET(_xlpm.m,IF(ISNUMBER(U$4),DATE(YEAR(U$4),MONTH(U$4),1),DATEVALUE("1-"&U$4)),IF(OR(COUNTA($A12:$F12)>0,$G12<>""),$N12/12*IF($F12="",1,MAX(0,(EOMONTH(_xlpm.m,0)-MAX($F12,_xlpm.m)+1)/(EOMONTH(_xlpm.m,0)-_xlpm.m+1))),"")) | V12: =_xlfn.LET(_xlpm.m,IF(ISNUMBER(V$4),DATE(YEAR(V$4),MONTH(V$4),1),DATEVALUE("1-"&V$4)),IF(OR(COUNTA($A12:$F12)>0,$G12<>""),$N12/12*IF($F12="",1,MAX(0,(EOMONTH(_xlpm.m,0)-MAX($F12,_xlpm.m)+1)/(EOMONTH(_xlpm.m,0)-_xlpm.m+1))),"")) | ... Z12: =_xlfn.LET(_xlpm.m,IF(ISNUMBER(Z$4),DATE(YEAR(Z$4),MONTH(Z$4),1),DATEVALUE("1-"&Z$4)),IF(OR(COUNTA($A12:$F12)>0,$G12<>""),$N12/12*IF($F12="",1,MAX(0,(EOMONTH(_xlpm.m,0)-MAX($F12,_xlpm.m)+1)/(EOMONTH(_xlpm.m,0)-_xlpm.m+1))),"")) | AA12: =IF(COUNTA($A12:$H12)>0,SUM(O12:Z12),"") | AB12: =_xlfn.LET(_xlpm.m,IF(ISNUMBER(AB$4),DATE(YEAR(AB$4),MONTH(AB$4),1),DATEVALUE("1-"&AB$4)),IF(OR(COUNTA($A12:$F12)>0,$G12<>""),$N12/12*IF($F12="",1,MAX(0,(EOMONTH(_xlpm.m,0)-MAX($F12,_xlpm.m)+1)/(EOMONTH(_xlpm.m,0)-_xlpm.m+1))),"")) | AC12: =_xlfn.LET(_xlpm.m,IF(ISNUMBER(AC$4),DATE(YEAR(AC$4),MONTH(AC$4),1),DATEVALUE("1-"&AC$4)),IF(OR(COUNTA($A12:$F12)>0,$G12<>""),$N12/12*IF($F12="",1,MAX(0,(EOMONTH(_xlpm.m,0)-MAX($F12,_xlpm.m)+1)/(EOMONTH(_xlpm.m,0)-_xlpm.m+1))),"")) | AD12: =_xlfn.LET(_xlpm.m,IF(ISNUMBER(AD$4),DATE(YEAR(AD$4),MONTH(AD$4),1),DATEVALUE("1-"&AD$4)),IF(OR(COUNTA($A12:$F12)>0,$G12<>""),$N12/12*IF($F12="",1,MAX(0,(EOMONTH(_xlpm.m,0)-MAX($F12,_xlpm.m)+1)/(EOMONTH(_xlpm.m,0)-_xlpm.m+1))),"")) | AE12: =_xlfn.LET(_xlpm.m,IF(ISNUMBER(AE$4),DATE(YEAR(AE$4),MONTH(AE$4),1),DATEVALUE("1-"&AE$4)),IF(OR(COUNTA($A12:$F12)>0,$G12<>""),$N12/12*IF($F12="",1,MAX(0,(EOMONTH(_xlpm.m,0)-MAX($F12,_xlpm.m)+1)/(EOMONTH(_xlpm.m,0)-_xlpm.m+1))),"")) | AF12: =_xlfn.LET(_xlpm.m,IF(ISNUMBER(AF$4),DATE(YEAR(AF$4),MONTH(AF$4),1),DATEVALUE("1-"&AF$4)),IF(OR(COUNTA($A12:$F12)>0,$G12<>""),$N12/12*IF($F12="",1,MAX(0,(EOMONTH(_xlpm.m,0)-MAX($F12,_xlpm.m)+1)/(EOMONTH(_xlpm.m,0)-_xlpm.m+1))),"")) | AG12: =_xlfn.LET(_xlpm.m,IF(ISNUMBER(AG$4),DATE(YEAR(AG$4),MONTH(AG$4),1),DATEVALUE("1-"&AG$4)),IF(OR(COUNTA($A12:$F12)>0,$G12<>""),$N12/12*IF($F12="",1,MAX(0,(EOMONTH(_xlpm.m,0)-MAX($F12,_xlpm.m)+1)/(EOMONTH(_xlpm.m,0)-_xlpm.m+1))),"")) | AH12: =_xlfn.LET(_xlpm.m,IF(ISNUMBER(AH$4),DATE(YEAR(AH$4),MONTH(AH$4),1),DATEVALUE("1-"&AH$4)),IF(OR(COUNTA($A12:$F12)>0,$G12<>""),$N12/12*IF($F12="",1,MAX(0,(EOMONTH(_xlpm.m,0)-MAX($F12,_xlpm.m)+1)/(EOMONTH(_xlpm.m,0)-_xlpm.m+1))),"")) | AI12: =_xlfn.LET(_xlpm.m,IF(ISNUMBER(AI$4),DATE(YEAR(AI$4),MONTH(AI$4),1),DATEVALUE("1-"&AI$4)),IF(OR(COUNTA($A12:$F12)>0,$G12<>""),$N12/12*IF($F12="",1,MAX(0,(EOMONTH(_xlpm.m,0)-MAX($F12,_xlpm.m)+1)/(EOMONTH(_xlpm.m,0)-_xlpm.m+1))),"")) | ... AM12: =_xlfn.LET(_xlpm.m,IF(ISNUMBER(AM$4),DATE(YEAR(AM$4),MONTH(AM$4),1),DATEVALUE("1-"&AM$4)),IF(OR(COUNTA($A12:$F12)>0,$G12<>""),$N12/12*IF($F12="",1,MAX(0,(EOMONTH(_xlpm.m,0)-MAX($F12,_xlpm.m)+1)/(EOMONTH(_xlpm.m,0)-_xlpm.m+1))),"")) | AN12: =IF(COUNTA($A12:$H12)>0,SUM(AB12:AM12),"") | AO12: =_xlfn.LET(_xlpm.m,IF(ISNUMBER(AO$4),DATE(YEAR(AO$4),MONTH(AO$4),1),DATEVALUE("1-"&AO$4)),IF(OR(COUNTA($A12:$F12)>0,$G12<>""),$N12/12*IF($F12="",1,MAX(0,(EOMONTH(_xlpm.m,0)-MAX($F12,_xlpm.m)+1)/(EOMONTH(_xlpm.m,0)-_xlpm.m+1))),"")) | AP12: =_xlfn.LET(_xlpm.m,IF(ISNUMBER(AP$4),DATE(YEAR(AP$4),MONTH(AP$4),1),DATEVALUE("1-"&AP$4)),IF(OR(COUNTA($A12:$F12)>0,$G12<>""),$N12/12*IF($F12="",1,MAX(0,(EOMONTH(_xlpm.m,0)-MAX($F12,_xlpm.m)+1)/(EOMONTH(_xlpm.m,0)-_xlpm.m+1))),"")) | AQ12: =_xlfn.LET(_xlpm.m,IF(ISNUMBER(AQ$4),DATE(YEAR(AQ$4),MONTH(AQ$4),1),DATEVALUE("1-"&AQ$4)),IF(OR(COUNTA($A12:$F12)>0,$G12<>""),$N12/12*IF($F12="",1,MAX(0,(EOMONTH(_xlpm.m,0)-MAX($F12,_xlpm.m)+1)/(EOMONTH(_xlpm.m,0)-_xlpm.m+1))),"")) | AR12: =_xlfn.LET(_xlpm.m,IF(ISNUMBER(AR$4),DATE(YEAR(AR$4),MONTH(AR$4),1),DATEVALUE("1-"&AR$4)),IF(OR(COUNTA($A12:$F12)>0,$G12<>""),$N12/12*IF($F12="",1,MAX(0,(EOMONTH(_xlpm.m,0)-MAX($F12,_xlpm.m)+1)/(EOMONTH(_xlpm.m,0)-_xlpm.m+1))),"")) | AS12: =_xlfn.LET(_xlpm.m,IF(ISNUMBER(AS$4),DATE(YEAR(AS$4),MONTH(AS$4),1),DATEVALUE("1-"&AS$4)),IF(OR(COUNTA($A12:$F12)>0,$G12<>""),$N12/12*IF($F12="",1,MAX(0,(EOMONTH(_xlpm.m,0)-MAX($F12,_xlpm.m)+1)/(EOMONTH(_xlpm.m,0)-_xlpm.m+1))),"")) | AT12: =_xlfn.LET(_xlpm.m,IF(ISNUMBER(AT$4),DATE(YEAR(AT$4),MONTH(AT$4),1),DATEVALUE("1-"&AT$4)),IF(OR(COUNTA($A12:$F12)>0,$G12<>""),$N12/12*IF($F12="",1,MAX(0,(EOMONTH(_xlpm.m,0)-MAX($F12,_xlpm.m)+1)/(EOMONTH(_xlpm.m,0)-_xlpm.m+1))),"")) | AU12: =_xlfn.LET(_xlpm.m,IF(ISNUMBER(AU$4),DATE(YEAR(AU$4),MONTH(AU$4),1),DATEVALUE("1-"&AU$4)),IF(OR(COUNTA($A12:$F12)>0,$G12<>""),$N12/12*IF($F12="",1,MAX(0,(EOMONTH(_xlpm.m,0)-MAX($F12,_xlpm.m)+1)/(EOMONTH(_xlpm.m,0)-_xlpm.m+1))),"")) | AV12: =_xlfn.LET(_xlpm.m,IF(ISNUMBER(AV$4),DATE(YEAR(AV$4),MONTH(AV$4),1),DATEVALUE("1-"&AV$4)),IF(OR(COUNTA($A12:$F12)>0,$G12<>""),$N12/12*IF($F12="",1,MAX(0,(EOMONTH(_xlpm.m,0)-MAX($F12,_xlpm.m)+1)/(EOMONTH(_xlpm.m,0)-_xlpm.m+1))),"")) | ... AZ12: =_xlfn.LET(_xlpm.m,IF(ISNUMBER(AZ$4),DATE(YEAR(AZ$4),MONTH(AZ$4),1),DATEVALUE("1-"&AZ$4)),IF(OR(COUNTA($A12:$F12)>0,$G12<>""),$N12/12*IF($F12="",1,MAX(0,(EOMONTH(_xlpm.m,0)-MAX($F12,_xlpm.m)+1)/(EOMONTH(_xlpm.m,0)-_xlpm.m+1))),"")) | BA12: =IF(COUNTA($A12:$H12)>0,SUM(AO12:AZ12),"")
I13: =IF(COUNTA($A13:$H13)>0,IFERROR($G13*$H13,0),"") | J13: =IF(COUNTA($A13:$H13)>0,IFERROR($G13*Summary!$C$46/Summary!$C$43,0),"") | K13: =IF(COUNTA($A13:$H13)>0,IFERROR($G13*Summary!$C$47/Summary!$C$43,0),"") | L13: =IF(COUNTA($A13:$H13)>0,IFERROR($G13*Summary!$C$48/Summary!$C$43,0),"") | M13: =IF(COUNTA($A13:$H13)>0,IFERROR($G13*Summary!$C$49/Summary!$C$43,0),"") | N13: =IF(COUNTA($A13:$H13)>0,IFERROR($G13,0)+SUM(I13:M13),"") | O13: =_xlfn.LET(_xlpm.m,IF(ISNUMBER(O$4),DATE(YEAR(O$4),MONTH(O$4),1),DATEVALUE("1-"&O$4)),IF(OR(COUNTA($A13:$F13)>0,$G13<>""),$N13/12*IF($F13="",1,MAX(0,(EOMONTH(_xlpm.m,0)-MAX($F13,_xlpm.m)+1)/(EOMONTH(_xlpm.m,0)-_xlpm.m+1))),"")) | P13: =_xlfn.LET(_xlpm.m,IF(ISNUMBER(P$4),DATE(YEAR(P$4),MONTH(P$4),1),DATEVALUE("1-"&P$4)),IF(OR(COUNTA($A13:$F13)>0,$G13<>""),$N13/12*IF($F13="",1,MAX(0,(EOMONTH(_xlpm.m,0)-MAX($F13,_xlpm.m)+1)/(EOMONTH(_xlpm.m,0)-_xlpm.m+1))),"")) | Q13: =_xlfn.LET(_xlpm.m,IF(ISNUMBER(Q$4),DATE(YEAR(Q$4),MONTH(Q$4),1),DATEVALUE("1-"&Q$4)),IF(OR(COUNTA($A13:$F13)>0,$G13<>""),$N13/12*IF($F13="",1,MAX(0,(EOMONTH(_xlpm.m,0)-MAX($F13,_xlpm.m)+1)/(EOMONTH(_xlpm.m,0)-_xlpm.m+1))),"")) | R13: =_xlfn.LET(_xlpm.m,IF(ISNUMBER(R$4),DATE(YEAR(R$4),MONTH(R$4),1),DATEVALUE("1-"&R$4)),IF(OR(COUNTA($A13:$F13)>0,$G13<>""),$N13/12*IF($F13="",1,MAX(0,(EOMONTH(_xlpm.m,0)-MAX($F13,_xlpm.m)+1)/(EOMONTH(_xlpm.m,0)-_xlpm.m+1))),"")) | S13: =_xlfn.LET(_xlpm.m,IF(ISNUMBER(S$4),DATE(YEAR(S$4),MONTH(S$4),1),DATEVALUE("1-"&S$4)),IF(OR(COUNTA($A13:$F13)>0,$G13<>""),$N13/12*IF($F13="",1,MAX(0,(EOMONTH(_xlpm.m,0)-MAX($F13,_xlpm.m)+1)/(EOMONTH(_xlpm.m,0)-_xlpm.m+1))),"")) | T13: =_xlfn.LET(_xlpm.m,IF(ISNUMBER(T$4),DATE(YEAR(T$4),MONTH(T$4),1),DATEVALUE("1-"&T$4)),IF(OR(COUNTA($A13:$F13)>0,$G13<>""),$N13/12*IF($F13="",1,MAX(0,(EOMONTH(_xlpm.m,0)-MAX($F13,_xlpm.m)+1)/(EOMONTH(_xlpm.m,0)-_xlpm.m+1))),"")) | U13: =_xlfn.LET(_xlpm.m,IF(ISNUMBER(U$4),DATE(YEAR(U$4),MONTH(U$4),1),DATEVALUE("1-"&U$4)),IF(OR(COUNTA($A13:$F13)>0,$G13<>""),$N13/12*IF($F13="",1,MAX(0,(EOMONTH(_xlpm.m,0)-MAX($F13,_xlpm.m)+1)/(EOMONTH(_xlpm.m,0)-_xlpm.m+1))),"")) | V13: =_xlfn.LET(_xlpm.m,IF(ISNUMBER(V$4),DATE(YEAR(V$4),MONTH(V$4),1),DATEVALUE("1-"&V$4)),IF(OR(COUNTA($A13:$F13)>0,$G13<>""),$N13/12*IF($F13="",1,MAX(0,(EOMONTH(_xlpm.m,0)-MAX($F13,_xlpm.m)+1)/(EOMONTH(_xlpm.m,0)-_xlpm.m+1))),"")) | ... Z13: =_xlfn.LET(_xlpm.m,IF(ISNUMBER(Z$4),DATE(YEAR(Z$4),MONTH(Z$4),1),DATEVALUE("1-"&Z$4)),IF(OR(COUNTA($A13:$F13)>0,$G13<>""),$N13/12*IF($F13="",1,MAX(0,(EOMONTH(_xlpm.m,0)-MAX($F13,_xlpm.m)+1)/(EOMONTH(_xlpm.m,0)-_xlpm.m+1))),"")) | AA13: =IF(COUNTA($A13:$H13)>0,SUM(O13:Z13),"") | AB13: =_xlfn.LET(_xlpm.m,IF(ISNUMBER(AB$4),DATE(YEAR(AB$4),MONTH(AB$4),1),DATEVALUE("1-"&AB$4)),IF(OR(COUNTA($A13:$F13)>0,$G13<>""),$N13/12*IF($F13="",1,MAX(0,(EOMONTH(_xlpm.m,0)-MAX($F13,_xlpm.m)+1)/(EOMONTH(_xlpm.m,0)-_xlpm.m+1))),"")) | AC13: =_xlfn.LET(_xlpm.m,IF(ISNUMBER(AC$4),DATE(YEAR(AC$4),MONTH(AC$4),1),DATEVALUE("1-"&AC$4)),IF(OR(COUNTA($A13:$F13)>0,$G13<>""),$N13/12*IF($F13="",1,MAX(0,(EOMONTH(_xlpm.m,0)-MAX($F13,_xlpm.m)+1)/(EOMONTH(_xlpm.m,0)-_xlpm.m+1))),"")) | AD13: =_xlfn.LET(_xlpm.m,IF(ISNUMBER(AD$4),DATE(YEAR(AD$4),MONTH(AD$4),1),DATEVALUE("1-"&AD$4)),IF(OR(COUNTA($A13:$F13)>0,$G13<>""),$N13/12*IF($F13="",1,MAX(0,(EOMONTH(_xlpm.m,0)-MAX($F13,_xlpm.m)+1)/(EOMONTH(_xlpm.m,0)-_xlpm.m+1))),"")) | AE13: =_xlfn.LET(_xlpm.m,IF(ISNUMBER(AE$4),DATE(YEAR(AE$4),MONTH(AE$4),1),DATEVALUE("1-"&AE$4)),IF(OR(COUNTA($A13:$F13)>0,$G13<>""),$N13/12*IF($F13="",1,MAX(0,(EOMONTH(_xlpm.m,0)-MAX($F13,_xlpm.m)+1)/(EOMONTH(_xlpm.m,0)-_xlpm.m+1))),"")) | AF13: =_xlfn.LET(_xlpm.m,IF(ISNUMBER(AF$4),DATE(YEAR(AF$4),MONTH(AF$4),1),DATEVALUE("1-"&AF$4)),IF(OR(COUNTA($A13:$F13)>0,$G13<>""),$N13/12*IF($F13="",1,MAX(0,(EOMONTH(_xlpm.m,0)-MAX($F13,_xlpm.m)+1)/(EOMONTH(_xlpm.m,0)-_xlpm.m+1))),"")) | AG13: =_xlfn.LET(_xlpm.m,IF(ISNUMBER(AG$4),DATE(YEAR(AG$4),MONTH(AG$4),1),DATEVALUE("1-"&AG$4)),IF(OR(COUNTA($A13:$F13)>0,$G13<>""),$N13/12*IF($F13="",1,MAX(0,(EOMONTH(_xlpm.m,0)-MAX($F13,_xlpm.m)+1)/(EOMONTH(_xlpm.m,0)-_xlpm.m+1))),"")) | AH13: =_xlfn.LET(_xlpm.m,IF(ISNUMBER(AH$4),DATE(YEAR(AH$4),MONTH(AH$4),1),DATEVALUE("1-"&AH$4)),IF(OR(COUNTA($A13:$F13)>0,$G13<>""),$N13/12*IF($F13="",1,MAX(0,(EOMONTH(_xlpm.m,0)-MAX($F13,_xlpm.m)+1)/(EOMONTH(_xlpm.m,0)-_xlpm.m+1))),"")) | AI13: =_xlfn.LET(_xlpm.m,IF(ISNUMBER(AI$4),DATE(YEAR(AI$4),MONTH(AI$4),1),DATEVALUE("1-"&AI$4)),IF(OR(COUNTA($A13:$F13)>0,$G13<>""),$N13/12*IF($F13="",1,MAX(0,(EOMONTH(_xlpm.m,0)-MAX($F13,_xlpm.m)+1)/(EOMONTH(_xlpm.m,0)-_xlpm.m+1))),"")) | ... AM13: =_xlfn.LET(_xlpm.m,IF(ISNUMBER(AM$4),DATE(YEAR(AM$4),MONTH(AM$4),1),DATEVALUE("1-"&AM$4)),IF(OR(COUNTA($A13:$F13)>0,$G13<>""),$N13/12*IF($F13="",1,MAX(0,(EOMONTH(_xlpm.m,0)-MAX($F13,_xlpm.m)+1)/(EOMONTH(_xlpm.m,0)-_xlpm.m+1))),"")) | AN13: =IF(COUNTA($A13:$H13)>0,SUM(AB13:AM13),"") | AO13: =_xlfn.LET(_xlpm.m,IF(ISNUMBER(AO$4),DATE(YEAR(AO$4),MONTH(AO$4),1),DATEVALUE("1-"&AO$4)),IF(OR(COUNTA($A13:$F13)>0,$G13<>""),$N13/12*IF($F13="",1,MAX(0,(EOMONTH(_xlpm.m,0)-MAX($F13,_xlpm.m)+1)/(EOMONTH(_xlpm.m,0)-_xlpm.m+1))),"")) | AP13: =_xlfn.LET(_xlpm.m,IF(ISNUMBER(AP$4),DATE(YEAR(AP$4),MONTH(AP$4),1),DATEVALUE("1-"&AP$4)),IF(OR(COUNTA($A13:$F13)>0,$G13<>""),$N13/12*IF($F13="",1,MAX(0,(EOMONTH(_xlpm.m,0)-MAX($F13,_xlpm.m)+1)/(EOMONTH(_xlpm.m,0)-_xlpm.m+1))),"")) | AQ13: =_xlfn.LET(_xlpm.m,IF(ISNUMBER(AQ$4),DATE(YEAR(AQ$4),MONTH(AQ$4),1),DATEVALUE("1-"&AQ$4)),IF(OR(COUNTA($A13:$F13)>0,$G13<>""),$N13/12*IF($F13="",1,MAX(0,(EOMONTH(_xlpm.m,0)-MAX($F13,_xlpm.m)+1)/(EOMONTH(_xlpm.m,0)-_xlpm.m+1))),"")) | AR13: =_xlfn.LET(_xlpm.m,IF(ISNUMBER(AR$4),DATE(YEAR(AR$4),MONTH(AR$4),1),DATEVALUE("1-"&AR$4)),IF(OR(COUNTA($A13:$F13)>0,$G13<>""),$N13/12*IF($F13="",1,MAX(0,(EOMONTH(_xlpm.m,0)-MAX($F13,_xlpm.m)+1)/(EOMONTH(_xlpm.m,0)-_xlpm.m+1))),"")) | AS13: =_xlfn.LET(_xlpm.m,IF(ISNUMBER(AS$4),DATE(YEAR(AS$4),MONTH(AS$4),1),DATEVALUE("1-"&AS$4)),IF(OR(COUNTA($A13:$F13)>0,$G13<>""),$N13/12*IF($F13="",1,MAX(0,(EOMONTH(_xlpm.m,0)-MAX($F13,_xlpm.m)+1)/(EOMONTH(_xlpm.m,0)-_xlpm.m+1))),"")) | AT13: =_xlfn.LET(_xlpm.m,IF(ISNUMBER(AT$4),DATE(YEAR(AT$4),MONTH(AT$4),1),DATEVALUE("1-"&AT$4)),IF(OR(COUNTA($A13:$F13)>0,$G13<>""),$N13/12*IF($F13="",1,MAX(0,(EOMONTH(_xlpm.m,0)-MAX($F13,_xlpm.m)+1)/(EOMONTH(_xlpm.m,0)-_xlpm.m+1))),"")) | AU13: =_xlfn.LET(_xlpm.m,IF(ISNUMBER(AU$4),DATE(YEAR(AU$4),MONTH(AU$4),1),DATEVALUE("1-"&AU$4)),IF(OR(COUNTA($A13:$F13)>0,$G13<>""),$N13/12*IF($F13="",1,MAX(0,(EOMONTH(_xlpm.m,0)-MAX($F13,_xlpm.m)+1)/(EOMONTH(_xlpm.m,0)-_xlpm.m+1))),"")) | AV13: =_xlfn.LET(_xlpm.m,IF(ISNUMBER(AV$4),DATE(YEAR(AV$4),MONTH(AV$4),1),DATEVALUE("1-"&AV$4)),IF(OR(COUNTA($A13:$F13)>0,$G13<>""),$N13/12*IF($F13="",1,MAX(0,(EOMONTH(_xlpm.m,0)-MAX($F13,_xlpm.m)+1)/(EOMONTH(_xlpm.m,0)-_xlpm.m+1))),"")) | ... AZ13: =_xlfn.LET(_xlpm.m,IF(ISNUMBER(AZ$4),DATE(YEAR(AZ$4),MONTH(AZ$4),1),DATEVALUE("1-"&AZ$4)),IF(OR(COUNTA($A13:$F13)>0,$G13<>""),$N13/12*IF($F13="",1,MAX(0,(EOMONTH(_xlpm.m,0)-MAX($F13,_xlpm.m)+1)/(EOMONTH(_xlpm.m,0)-_xlpm.m+1))),"")) | BA13: =IF(COUNTA($A13:$H13)>0,SUM(AO13:AZ13),"")
I14: =IF(COUNTA($A14:$H14)>0,IFERROR($G14*$H14,0),"") | J14: =IF(COUNTA($A14:$H14)>0,IFERROR($G14*Summary!$C$46/Summary!$C$43,0),"") | K14: =IF(COUNTA($A14:$H14)>0,IFERROR($G14*Summary!$C$47/Summary!$C$43,0),"") | L14: =IF(COUNTA($A14:$H14)>0,IFERROR($G14*Summary!$C$48/Summary!$C$43,0),"") | M14: =IF(COUNTA($A14:$H14)>0,IFERROR($G14*Summary!$C$49/Summary!$C$43,0),"") | N14: =IF(COUNTA($A14:$H14)>0,IFERROR($G14,0)+SUM(I14:M14),"") | O14: =_xlfn.LET(_xlpm.m,IF(ISNUMBER(O$4),DATE(YEAR(O$4),MONTH(O$4),1),DATEVALUE("1-"&O$4)),IF(OR(COUNTA($A14:$F14)>0,$G14<>""),$N14/12*IF($F14="",1,MAX(0,(EOMONTH(_xlpm.m,0)-MAX($F14,_xlpm.m)+1)/(EOMONTH(_xlpm.m,0)-_xlpm.m+1))),"")) | P14: =_xlfn.LET(_xlpm.m,IF(ISNUMBER(P$4),DATE(YEAR(P$4),MONTH(P$4),1),DATEVALUE("1-"&P$4)),IF(OR(COUNTA($A14:$F14)>0,$G14<>""),$N14/12*IF($F14="",1,MAX(0,(EOMONTH(_xlpm.m,0)-MAX($F14,_xlpm.m)+1)/(EOMONTH(_xlpm.m,0)-_xlpm.m+1))),"")) | Q14: =_xlfn.LET(_xlpm.m,IF(ISNUMBER(Q$4),DATE(YEAR(Q$4),MONTH(Q$4),1),DATEVALUE("1-"&Q$4)),IF(OR(COUNTA($A14:$F14)>0,$G14<>""),$N14/12*IF($F14="",1,MAX(0,(EOMONTH(_xlpm.m,0)-MAX($F14,_xlpm.m)+1)/(EOMONTH(_xlpm.m,0)-_xlpm.m+1))),"")) | R14: =_xlfn.LET(_xlpm.m,IF(ISNUMBER(R$4),DATE(YEAR(R$4),MONTH(R$4),1),DATEVALUE("1-"&R$4)),IF(OR(COUNTA($A14:$F14)>0,$G14<>""),$N14/12*IF($F14="",1,MAX(0,(EOMONTH(_xlpm.m,0)-MAX($F14,_xlpm.m)+1)/(EOMONTH(_xlpm.m,0)-_xlpm.m+1))),"")) | S14: =_xlfn.LET(_xlpm.m,IF(ISNUMBER(S$4),DATE(YEAR(S$4),MONTH(S$4),1),DATEVALUE("1-"&S$4)),IF(OR(COUNTA($A14:$F14)>0,$G14<>""),$N14/12*IF($F14="",1,MAX(0,(EOMONTH(_xlpm.m,0)-MAX($F14,_xlpm.m)+1)/(EOMONTH(_xlpm.m,0)-_xlpm.m+1))),"")) | T14: =_xlfn.LET(_xlpm.m,IF(ISNUMBER(T$4),DATE(YEAR(T$4),MONTH(T$4),1),DATEVALUE("1-"&T$4)),IF(OR(COUNTA($A14:$F14)>0,$G14<>""),$N14/12*IF($F14="",1,MAX(0,(EOMONTH(_xlpm.m,0)-MAX($F14,_xlpm.m)+1)/(EOMONTH(_xlpm.m,0)-_xlpm.m+1))),"")) | U14: =_xlfn.LET(_xlpm.m,IF(ISNUMBER(U$4),DATE(YEAR(U$4),MONTH(U$4),1),DATEVALUE("1-"&U$4)),IF(OR(COUNTA($A14:$F14)>0,$G14<>""),$N14/12*IF($F14="",1,MAX(0,(EOMONTH(_xlpm.m,0)-MAX($F14,_xlpm.m)+1)/(EOMONTH(_xlpm.m,0)-_xlpm.m+1))),"")) | V14: =_xlfn.LET(_xlpm.m,IF(ISNUMBER(V$4),DATE(YEAR(V$4),MONTH(V$4),1),DATEVALUE("1-"&V$4)),IF(OR(COUNTA($A14:$F14)>0,$G14<>""),$N14/12*IF($F14="",1,MAX(0,(EOMONTH(_xlpm.m,0)-MAX($F14,_xlpm.m)+1)/(EOMONTH(_xlpm.m,0)-_xlpm.m+1))),"")) | ... Z14: =_xlfn.LET(_xlpm.m,IF(ISNUMBER(Z$4),DATE(YEAR(Z$4),MONTH(Z$4),1),DATEVALUE("1-"&Z$4)),IF(OR(COUNTA($A14:$F14)>0,$G14<>""),$N14/12*IF($F14="",1,MAX(0,(EOMONTH(_xlpm.m,0)-MAX($F14,_xlpm.m)+1)/(EOMONTH(_xlpm.m,0)-_xlpm.m+1))),"")) | AA14: =IF(COUNTA($A14:$H14)>0,SUM(O14:Z14),"") | AB14: =_xlfn.LET(_xlpm.m,IF(ISNUMBER(AB$4),DATE(YEAR(AB$4),MONTH(AB$4),1),DATEVALUE("1-"&AB$4)),IF(OR(COUNTA($A14:$F14)>0,$G14<>""),$N14/12*IF($F14="",1,MAX(0,(EOMONTH(_xlpm.m,0)-MAX($F14,_xlpm.m)+1)/(EOMONTH(_xlpm.m,0)-_xlpm.m+1))),"")) | AC14: =_xlfn.LET(_xlpm.m,IF(ISNUMBER(AC$4),DATE(YEAR(AC$4),MONTH(AC$4),1),DATEVALUE("1-"&AC$4)),IF(OR(COUNTA($A14:$F14)>0,$G14<>""),$N14/12*IF($F14="",1,MAX(0,(EOMONTH(_xlpm.m,0)-MAX($F14,_xlpm.m)+1)/(EOMONTH(_xlpm.m,0)-_xlpm.m+1))),"")) | AD14: =_xlfn.LET(_xlpm.m,IF(ISNUMBER(AD$4),DATE(YEAR(AD$4),MONTH(AD$4),1),DATEVALUE("1-"&AD$4)),IF(OR(COUNTA($A14:$F14)>0,$G14<>""),$N14/12*IF($F14="",1,MAX(0,(EOMONTH(_xlpm.m,0)-MAX($F14,_xlpm.m)+1)/(EOMONTH(_xlpm.m,0)-_xlpm.m+1))),"")) | AE14: =_xlfn.LET(_xlpm.m,IF(ISNUMBER(AE$4),DATE(YEAR(AE$4),MONTH(AE$4),1),DATEVALUE("1-"&AE$4)),IF(OR(COUNTA($A14:$F14)>0,$G14<>""),$N14/12*IF($F14="",1,MAX(0,(EOMONTH(_xlpm.m,0)-MAX($F14,_xlpm.m)+1)/(EOMONTH(_xlpm.m,0)-_xlpm.m+1))),"")) | AF14: =_xlfn.LET(_xlpm.m,IF(ISNUMBER(AF$4),DATE(YEAR(AF$4),MONTH(AF$4),1),DATEVALUE("1-"&AF$4)),IF(OR(COUNTA($A14:$F14)>0,$G14<>""),$N14/12*IF($F14="",1,MAX(0,(EOMONTH(_xlpm.m,0)-MAX($F14,_xlpm.m)+1)/(EOMONTH(_xlpm.m,0)-_xlpm.m+1))),"")) | AG14: =_xlfn.LET(_xlpm.m,IF(ISNUMBER(AG$4),DATE(YEAR(AG$4),MONTH(AG$4),1),DATEVALUE("1-"&AG$4)),IF(OR(COUNTA($A14:$F14)>0,$G14<>""),$N14/12*IF($F14="",1,MAX(0,(EOMONTH(_xlpm.m,0)-MAX($F14,_xlpm.m)+1)/(EOMONTH(_xlpm.m,0)-_xlpm.m+1))),"")) | AH14: =_xlfn.LET(_xlpm.m,IF(ISNUMBER(AH$4),DATE(YEAR(AH$4),MONTH(AH$4),1),DATEVALUE("1-"&AH$4)),IF(OR(COUNTA($A14:$F14)>0,$G14<>""),$N14/12*IF($F14="",1,MAX(0,(EOMONTH(_xlpm.m,0)-MAX($F14,_xlpm.m)+1)/(EOMONTH(_xlpm.m,0)-_xlpm.m+1))),"")) | AI14: =_xlfn.LET(_xlpm.m,IF(ISNUMBER(AI$4),DATE(YEAR(AI$4),MONTH(AI$4),1),DATEVALUE("1-"&AI$4)),IF(OR(COUNTA($A14:$F14)>0,$G14<>""),$N14/12*IF($F14="",1,MAX(0,(EOMONTH(_xlpm.m,0)-MAX($F14,_xlpm.m)+1)/(EOMONTH(_xlpm.m,0)-_xlpm.m+1))),"")) | ... AM14: =_xlfn.LET(_xlpm.m,IF(ISNUMBER(AM$4),DATE(YEAR(AM$4),MONTH(AM$4),1),DATEVALUE("1-"&AM$4)),IF(OR(COUNTA($A14:$F14)>0,$G14<>""),$N14/12*IF($F14="",1,MAX(0,(EOMONTH(_xlpm.m,0)-MAX($F14,_xlpm.m)+1)/(EOMONTH(_xlpm.m,0)-_xlpm.m+1))),"")) | AN14: =IF(COUNTA($A14:$H14)>0,SUM(AB14:AM14),"") | AO14: =_xlfn.LET(_xlpm.m,IF(ISNUMBER(AO$4),DATE(YEAR(AO$4),MONTH(AO$4),1),DATEVALUE("1-"&AO$4)),IF(OR(COUNTA($A14:$F14)>0,$G14<>""),$N14/12*IF($F14="",1,MAX(0,(EOMONTH(_xlpm.m,0)-MAX($F14,_xlpm.m)+1)/(EOMONTH(_xlpm.m,0)-_xlpm.m+1))),"")) | AP14: =_xlfn.LET(_xlpm.m,IF(ISNUMBER(AP$4),DATE(YEAR(AP$4),MONTH(AP$4),1),DATEVALUE("1-"&AP$4)),IF(OR(COUNTA($A14:$F14)>0,$G14<>""),$N14/12*IF($F14="",1,MAX(0,(EOMONTH(_xlpm.m,0)-MAX($F14,_xlpm.m)+1)/(EOMONTH(_xlpm.m,0)-_xlpm.m+1))),"")) | AQ14: =_xlfn.LET(_xlpm.m,IF(ISNUMBER(AQ$4),DATE(YEAR(AQ$4),MONTH(AQ$4),1),DATEVALUE("1-"&AQ$4)),IF(OR(COUNTA($A14:$F14)>0,$G14<>""),$N14/12*IF($F14="",1,MAX(0,(EOMONTH(_xlpm.m,0)-MAX($F14,_xlpm.m)+1)/(EOMONTH(_xlpm.m,0)-_xlpm.m+1))),"")) | AR14: =_xlfn.LET(_xlpm.m,IF(ISNUMBER(AR$4),DATE(YEAR(AR$4),MONTH(AR$4),1),DATEVALUE("1-"&AR$4)),IF(OR(COUNTA($A14:$F14)>0,$G14<>""),$N14/12*IF($F14="",1,MAX(0,(EOMONTH(_xlpm.m,0)-MAX($F14,_xlpm.m)+1)/(EOMONTH(_xlpm.m,0)-_xlpm.m+1))),"")) | AS14: =_xlfn.LET(_xlpm.m,IF(ISNUMBER(AS$4),DATE(YEAR(AS$4),MONTH(AS$4),1),DATEVALUE("1-"&AS$4)),IF(OR(COUNTA($A14:$F14)>0,$G14<>""),$N14/12*IF($F14="",1,MAX(0,(EOMONTH(_xlpm.m,0)-MAX($F14,_xlpm.m)+1)/(EOMONTH(_xlpm.m,0)-_xlpm.m+1))),"")) | AT14: =_xlfn.LET(_xlpm.m,IF(ISNUMBER(AT$4),DATE(YEAR(AT$4),MONTH(AT$4),1),DATEVALUE("1-"&AT$4)),IF(OR(COUNTA($A14:$F14)>0,$G14<>""),$N14/12*IF($F14="",1,MAX(0,(EOMONTH(_xlpm.m,0)-MAX($F14,_xlpm.m)+1)/(EOMONTH(_xlpm.m,0)-_xlpm.m+1))),"")) | AU14: =_xlfn.LET(_xlpm.m,IF(ISNUMBER(AU$4),DATE(YEAR(AU$4),MONTH(AU$4),1),DATEVALUE("1-"&AU$4)),IF(OR(COUNTA($A14:$F14)>0,$G14<>""),$N14/12*IF($F14="",1,MAX(0,(EOMONTH(_xlpm.m,0)-MAX($F14,_xlpm.m)+1)/(EOMONTH(_xlpm.m,0)-_xlpm.m+1))),"")) | AV14: =_xlfn.LET(_xlpm.m,IF(ISNUMBER(AV$4),DATE(YEAR(AV$4),MONTH(AV$4),1),DATEVALUE("1-"&AV$4)),IF(OR(COUNTA($A14:$F14)>0,$G14<>""),$N14/12*IF($F14="",1,MAX(0,(EOMONTH(_xlpm.m,0)-MAX($F14,_xlpm.m)+1)/(EOMONTH(_xlpm.m,0)-_xlpm.m+1))),"")) | ... AZ14: =_xlfn.LET(_xlpm.m,IF(ISNUMBER(AZ$4),DATE(YEAR(AZ$4),MONTH(AZ$4),1),DATEVALUE("1-"&AZ$4)),IF(OR(COUNTA($A14:$F14)>0,$G14<>""),$N14/12*IF($F14="",1,MAX(0,(EOMONTH(_xlpm.m,0)-MAX($F14,_xlpm.m)+1)/(EOMONTH(_xlpm.m,0)-_xlpm.m+1))),"")) | BA14: =IF(COUNTA($A14:$H14)>0,SUM(AO14:AZ14),"")
I15: =IF(COUNTA($A15:$H15)>0,IFERROR($G15*$H15,0),"") | J15: =IF(COUNTA($A15:$H15)>0,IFERROR($G15*Summary!$C$46/Summary!$C$43,0),"") | K15: =IF(COUNTA($A15:$H15)>0,IFERROR($G15*Summary!$C$47/Summary!$C$43,0),"") | L15: =IF(COUNTA($A15:$H15)>0,IFERROR($G15*Summary!$C$48/Summary!$C$43,0),"") | M15: =IF(COUNTA($A15:$H15)>0,IFERROR($G15*Summary!$C$49/Summary!$C$43,0),"") | N15: =IF(COUNTA($A15:$H15)>0,IFERROR($G15,0)+SUM(I15:M15),"") | O15: =_xlfn.LET(_xlpm.m,IF(ISNUMBER(O$4),DATE(YEAR(O$4),MONTH(O$4),1),DATEVALUE("1-"&O$4)),IF(OR(COUNTA($A15:$F15)>0,$G15<>""),$N15/12*IF($F15="",1,MAX(0,(EOMONTH(_xlpm.m,0)-MAX($F15,_xlpm.m)+1)/(EOMONTH(_xlpm.m,0)-_xlpm.m+1))),"")) | P15: =_xlfn.LET(_xlpm.m,IF(ISNUMBER(P$4),DATE(YEAR(P$4),MONTH(P$4),1),DATEVALUE("1-"&P$4)),IF(OR(COUNTA($A15:$F15)>0,$G15<>""),$N15/12*IF($F15="",1,MAX(0,(EOMONTH(_xlpm.m,0)-MAX($F15,_xlpm.m)+1)/(EOMONTH(_xlpm.m,0)-_xlpm.m+1))),"")) | Q15: =_xlfn.LET(_xlpm.m,IF(ISNUMBER(Q$4),DATE(YEAR(Q$4),MONTH(Q$4),1),DATEVALUE("1-"&Q$4)),IF(OR(COUNTA($A15:$F15)>0,$G15<>""),$N15/12*IF($F15="",1,MAX(0,(EOMONTH(_xlpm.m,0)-MAX($F15,_xlpm.m)+1)/(EOMONTH(_xlpm.m,0)-_xlpm.m+1))),"")) | R15: =_xlfn.LET(_xlpm.m,IF(ISNUMBER(R$4),DATE(YEAR(R$4),MONTH(R$4),1),DATEVALUE("1-"&R$4)),IF(OR(COUNTA($A15:$F15)>0,$G15<>""),$N15/12*IF($F15="",1,MAX(0,(EOMONTH(_xlpm.m,0)-MAX($F15,_xlpm.m)+1)/(EOMONTH(_xlpm.m,0)-_xlpm.m+1))),"")) | S15: =_xlfn.LET(_xlpm.m,IF(ISNUMBER(S$4),DATE(YEAR(S$4),MONTH(S$4),1),DATEVALUE("1-"&S$4)),IF(OR(COUNTA($A15:$F15)>0,$G15<>""),$N15/12*IF($F15="",1,MAX(0,(EOMONTH(_xlpm.m,0)-MAX($F15,_xlpm.m)+1)/(EOMONTH(_xlpm.m,0)-_xlpm.m+1))),"")) | T15: =_xlfn.LET(_xlpm.m,IF(ISNUMBER(T$4),DATE(YEAR(T$4),MONTH(T$4),1),DATEVALUE("1-"&T$4)),IF(OR(COUNTA($A15:$F15)>0,$G15<>""),$N15/12*IF($F15="",1,MAX(0,(EOMONTH(_xlpm.m,0)-MAX($F15,_xlpm.m)+1)/(EOMONTH(_xlpm.m,0)-_xlpm.m+1))),"")) | U15: =_xlfn.LET(_xlpm.m,IF(ISNUMBER(U$4),DATE(YEAR(U$4),MONTH(U$4),1),DATEVALUE("1-"&U$4)),IF(OR(COUNTA($A15:$F15)>0,$G15<>""),$N15/12*IF($F15="",1,MAX(0,(EOMONTH(_xlpm.m,0)-MAX($F15,_xlpm.m)+1)/(EOMONTH(_xlpm.m,0)-_xlpm.m+1))),"")) | V15: =_xlfn.LET(_xlpm.m,IF(ISNUMBER(V$4),DATE(YEAR(V$4),MONTH(V$4),1),DATEVALUE("1-"&V$4)),IF(OR(COUNTA($A15:$F15)>0,$G15<>""),$N15/12*IF($F15="",1,MAX(0,(EOMONTH(_xlpm.m,0)-MAX($F15,_xlpm.m)+1)/(EOMONTH(_xlpm.m,0)-_xlpm.m+1))),"")) | ... Z15: =_xlfn.LET(_xlpm.m,IF(ISNUMBER(Z$4),DATE(YEAR(Z$4),MONTH(Z$4),1),DATEVALUE("1-"&Z$4)),IF(OR(COUNTA($A15:$F15)>0,$G15<>""),$N15/12*IF($F15="",1,MAX(0,(EOMONTH(_xlpm.m,0)-MAX($F15,_xlpm.m)+1)/(EOMONTH(_xlpm.m,0)-_xlpm.m+1))),"")) | AA15: =IF(COUNTA($A15:$H15)>0,SUM(O15:Z15),"") | AB15: =_xlfn.LET(_xlpm.m,IF(ISNUMBER(AB$4),DATE(YEAR(AB$4),MONTH(AB$4),1),DATEVALUE("1-"&AB$4)),IF(OR(COUNTA($A15:$F15)>0,$G15<>""),$N15/12*IF($F15="",1,MAX(0,(EOMONTH(_xlpm.m,0)-MAX($F15,_xlpm.m)+1)/(EOMONTH(_xlpm.m,0)-_xlpm.m+1))),"")) | AC15: =_xlfn.LET(_xlpm.m,IF(ISNUMBER(AC$4),DATE(YEAR(AC$4),MONTH(AC$4),1),DATEVALUE("1-"&AC$4)),IF(OR(COUNTA($A15:$F15)>0,$G15<>""),$N15/12*IF($F15="",1,MAX(0,(EOMONTH(_xlpm.m,0)-MAX($F15,_xlpm.m)+1)/(EOMONTH(_xlpm.m,0)-_xlpm.m+1))),"")) | AD15: =_xlfn.LET(_xlpm.m,IF(ISNUMBER(AD$4),DATE(YEAR(AD$4),MONTH(AD$4),1),DATEVALUE("1-"&AD$4)),IF(OR(COUNTA($A15:$F15)>0,$G15<>""),$N15/12*IF($F15="",1,MAX(0,(EOMONTH(_xlpm.m,0)-MAX($F15,_xlpm.m)+1)/(EOMONTH(_xlpm.m,0)-_xlpm.m+1))),"")) | AE15: =_xlfn.LET(_xlpm.m,IF(ISNUMBER(AE$4),DATE(YEAR(AE$4),MONTH(AE$4),1),DATEVALUE("1-"&AE$4)),IF(OR(COUNTA($A15:$F15)>0,$G15<>""),$N15/12*IF($F15="",1,MAX(0,(EOMONTH(_xlpm.m,0)-MAX($F15,_xlpm.m)+1)/(EOMONTH(_xlpm.m,0)-_xlpm.m+1))),"")) | AF15: =_xlfn.LET(_xlpm.m,IF(ISNUMBER(AF$4),DATE(YEAR(AF$4),MONTH(AF$4),1),DATEVALUE("1-"&AF$4)),IF(OR(COUNTA($A15:$F15)>0,$G15<>""),$N15/12*IF($F15="",1,MAX(0,(EOMONTH(_xlpm.m,0)-MAX($F15,_xlpm.m)+1)/(EOMONTH(_xlpm.m,0)-_xlpm.m+1))),"")) | AG15: =_xlfn.LET(_xlpm.m,IF(ISNUMBER(AG$4),DATE(YEAR(AG$4),MONTH(AG$4),1),DATEVALUE("1-"&AG$4)),IF(OR(COUNTA($A15:$F15)>0,$G15<>""),$N15/12*IF($F15="",1,MAX(0,(EOMONTH(_xlpm.m,0)-MAX($F15,_xlpm.m)+1)/(EOMONTH(_xlpm.m,0)-_xlpm.m+1))),"")) | AH15: =_xlfn.LET(_xlpm.m,IF(ISNUMBER(AH$4),DATE(YEAR(AH$4),MONTH(AH$4),1),DATEVALUE("1-"&AH$4)),IF(OR(COUNTA($A15:$F15)>0,$G15<>""),$N15/12*IF($F15="",1,MAX(0,(EOMONTH(_xlpm.m,0)-MAX($F15,_xlpm.m)+1)/(EOMONTH(_xlpm.m,0)-_xlpm.m+1))),"")) | AI15: =_xlfn.LET(_xlpm.m,IF(ISNUMBER(AI$4),DATE(YEAR(AI$4),MONTH(AI$4),1),DATEVALUE("1-"&AI$4)),IF(OR(COUNTA($A15:$F15)>0,$G15<>""),$N15/12*IF($F15="",1,MAX(0,(EOMONTH(_xlpm.m,0)-MAX($F15,_xlpm.m)+1)/(EOMONTH(_xlpm.m,0)-_xlpm.m+1))),"")) | ... AM15: =_xlfn.LET(_xlpm.m,IF(ISNUMBER(AM$4),DATE(YEAR(AM$4),MONTH(AM$4),1),DATEVALUE("1-"&AM$4)),IF(OR(COUNTA($A15:$F15)>0,$G15<>""),$N15/12*IF($F15="",1,MAX(0,(EOMONTH(_xlpm.m,0)-MAX($F15,_xlpm.m)+1)/(EOMONTH(_xlpm.m,0)-_xlpm.m+1))),"")) | AN15: =IF(COUNTA($A15:$H15)>0,SUM(AB15:AM15),"") | AO15: =_xlfn.LET(_xlpm.m,IF(ISNUMBER(AO$4),DATE(YEAR(AO$4),MONTH(AO$4),1),DATEVALUE("1-"&AO$4)),IF(OR(COUNTA($A15:$F15)>0,$G15<>""),$N15/12*IF($F15="",1,MAX(0,(EOMONTH(_xlpm.m,0)-MAX($F15,_xlpm.m)+1)/(EOMONTH(_xlpm.m,0)-_xlpm.m+1))),"")) | AP15: =_xlfn.LET(_xlpm.m,IF(ISNUMBER(AP$4),DATE(YEAR(AP$4),MONTH(AP$4),1),DATEVALUE("1-"&AP$4)),IF(OR(COUNTA($A15:$F15)>0,$G15<>""),$N15/12*IF($F15="",1,MAX(0,(EOMONTH(_xlpm.m,0)-MAX($F15,_xlpm.m)+1)/(EOMONTH(_xlpm.m,0)-_xlpm.m+1))),"")) | AQ15: =_xlfn.LET(_xlpm.m,IF(ISNUMBER(AQ$4),DATE(YEAR(AQ$4),MONTH(AQ$4),1),DATEVALUE("1-"&AQ$4)),IF(OR(COUNTA($A15:$F15)>0,$G15<>""),$N15/12*IF($F15="",1,MAX(0,(EOMONTH(_xlpm.m,0)-MAX($F15,_xlpm.m)+1)/(EOMONTH(_xlpm.m,0)-_xlpm.m+1))),"")) | AR15: =_xlfn.LET(_xlpm.m,IF(ISNUMBER(AR$4),DATE(YEAR(AR$4),MONTH(AR$4),1),DATEVALUE("1-"&AR$4)),IF(OR(COUNTA($A15:$F15)>0,$G15<>""),$N15/12*IF($F15="",1,MAX(0,(EOMONTH(_xlpm.m,0)-MAX($F15,_xlpm.m)+1)/(EOMONTH(_xlpm.m,0)-_xlpm.m+1))),"")) | AS15: =_xlfn.LET(_xlpm.m,IF(ISNUMBER(AS$4),DATE(YEAR(AS$4),MONTH(AS$4),1),DATEVALUE("1-"&AS$4)),IF(OR(COUNTA($A15:$F15)>0,$G15<>""),$N15/12*IF($F15="",1,MAX(0,(EOMONTH(_xlpm.m,0)-MAX($F15,_xlpm.m)+1)/(EOMONTH(_xlpm.m,0)-_xlpm.m+1))),"")) | AT15: =_xlfn.LET(_xlpm.m,IF(ISNUMBER(AT$4),DATE(YEAR(AT$4),MONTH(AT$4),1),DATEVALUE("1-"&AT$4)),IF(OR(COUNTA($A15:$F15)>0,$G15<>""),$N15/12*IF($F15="",1,MAX(0,(EOMONTH(_xlpm.m,0)-MAX($F15,_xlpm.m)+1)/(EOMONTH(_xlpm.m,0)-_xlpm.m+1))),"")) | AU15: =_xlfn.LET(_xlpm.m,IF(ISNUMBER(AU$4),DATE(YEAR(AU$4),MONTH(AU$4),1),DATEVALUE("1-"&AU$4)),IF(OR(COUNTA($A15:$F15)>0,$G15<>""),$N15/12*IF($F15="",1,MAX(0,(EOMONTH(_xlpm.m,0)-MAX($F15,_xlpm.m)+1)/(EOMONTH(_xlpm.m,0)-_xlpm.m+1))),"")) | AV15: =_xlfn.LET(_xlpm.m,IF(ISNUMBER(AV$4),DATE(YEAR(AV$4),MONTH(AV$4),1),DATEVALUE("1-"&AV$4)),IF(OR(COUNTA($A15:$F15)>0,$G15<>""),$N15/12*IF($F15="",1,MAX(0,(EOMONTH(_xlpm.m,0)-MAX($F15,_xlpm.m)+1)/(EOMONTH(_xlpm.m,0)-_xlpm.m+1))),"")) | ... AZ15: =_xlfn.LET(_xlpm.m,IF(ISNUMBER(AZ$4),DATE(YEAR(AZ$4),MONTH(AZ$4),1),DATEVALUE("1-"&AZ$4)),IF(OR(COUNTA($A15:$F15)>0,$G15<>""),$N15/12*IF($F15="",1,MAX(0,(EOMONTH(_xlpm.m,0)-MAX($F15,_xlpm.m)+1)/(EOMONTH(_xlpm.m,0)-_xlpm.m+1))),"")) | BA15: =IF(COUNTA($A15:$H15)>0,SUM(AO15:AZ15),"")
I16: =IF(COUNTA($A16:$H16)>0,IFERROR($G16*$H16,0),"") | J16: =IF(COUNTA($A16:$H16)>0,IFERROR($G16*Summary!$C$46/Summary!$C$43,0),"") | K16: =IF(COUNTA($A16:$H16)>0,IFERROR($G16*Summary!$C$47/Summary!$C$43,0),"") | L16: =IF(COUNTA($A16:$H16)>0,IFERROR($G16*Summary!$C$48/Summary!$C$43,0),"") | M16: =IF(COUNTA($A16:$H16)>0,IFERROR($G16*Summary!$C$49/Summary!$C$43,0),"") | N16: =IF(COUNTA($A16:$H16)>0,IFERROR($G16,0)+SUM(I16:M16),"") | O16: =_xlfn.LET(_xlpm.m,IF(ISNUMBER(O$4),DATE(YEAR(O$4),MONTH(O$4),1),DATEVALUE("1-"&O$4)),IF(OR(COUNTA($A16:$F16)>0,$G16<>""),$N16/12*IF($F16="",1,MAX(0,(EOMONTH(_xlpm.m,0)-MAX($F16,_xlpm.m)+1)/(EOMONTH(_xlpm.m,0)-_xlpm.m+1))),"")) | P16: =_xlfn.LET(_xlpm.m,IF(ISNUMBER(P$4),DATE(YEAR(P$4),MONTH(P$4),1),DATEVALUE("1-"&P$4)),IF(OR(COUNTA($A16:$F16)>0,$G16<>""),$N16/12*IF($F16="",1,MAX(0,(EOMONTH(_xlpm.m,0)-MAX($F16,_xlpm.m)+1)/(EOMONTH(_xlpm.m,0)-_xlpm.m+1))),"")) | Q16: =_xlfn.LET(_xlpm.m,IF(ISNUMBER(Q$4),DATE(YEAR(Q$4),MONTH(Q$4),1),DATEVALUE("1-"&Q$4)),IF(OR(COUNTA($A16:$F16)>0,$G16<>""),$N16/12*IF($F16="",1,MAX(0,(EOMONTH(_xlpm.m,0)-MAX($F16,_xlpm.m)+1)/(EOMONTH(_xlpm.m,0)-_xlpm.m+1))),"")) | R16: =_xlfn.LET(_xlpm.m,IF(ISNUMBER(R$4),DATE(YEAR(R$4),MONTH(R$4),1),DATEVALUE("1-"&R$4)),IF(OR(COUNTA($A16:$F16)>0,$G16<>""),$N16/12*IF($F16="",1,MAX(0,(EOMONTH(_xlpm.m,0)-MAX($F16,_xlpm.m)+1)/(EOMONTH(_xlpm.m,0)-_xlpm.m+1))),"")) | S16: =_xlfn.LET(_xlpm.m,IF(ISNUMBER(S$4),DATE(YEAR(S$4),MONTH(S$4),1),DATEVALUE("1-"&S$4)),IF(OR(COUNTA($A16:$F16)>0,$G16<>""),$N16/12*IF($F16="",1,MAX(0,(EOMONTH(_xlpm.m,0)-MAX($F16,_xlpm.m)+1)/(EOMONTH(_xlpm.m,0)-_xlpm.m+1))),"")) | T16: =_xlfn.LET(_xlpm.m,IF(ISNUMBER(T$4),DATE(YEAR(T$4),MONTH(T$4),1),DATEVALUE("1-"&T$4)),IF(OR(COUNTA($A16:$F16)>0,$G16<>""),$N16/12*IF($F16="",1,MAX(0,(EOMONTH(_xlpm.m,0)-MAX($F16,_xlpm.m)+1)/(EOMONTH(_xlpm.m,0)-_xlpm.m+1))),"")) | U16: =_xlfn.LET(_xlpm.m,IF(ISNUMBER(U$4),DATE(YEAR(U$4),MONTH(U$4),1),DATEVALUE("1-"&U$4)),IF(OR(COUNTA($A16:$F16)>0,$G16<>""),$N16/12*IF($F16="",1,MAX(0,(EOMONTH(_xlpm.m,0)-MAX($F16,_xlpm.m)+1)/(EOMONTH(_xlpm.m,0)-_xlpm.m+1))),"")) | V16: =_xlfn.LET(_xlpm.m,IF(ISNUMBER(V$4),DATE(YEAR(V$4),MONTH(V$4),1),DATEVALUE("1-"&V$4)),IF(OR(COUNTA($A16:$F16)>0,$G16<>""),$N16/12*IF($F16="",1,MAX(0,(EOMONTH(_xlpm.m,0)-MAX($F16,_xlpm.m)+1)/(EOMONTH(_xlpm.m,0)-_xlpm.m+1))),"")) | ... Z16: =_xlfn.LET(_xlpm.m,IF(ISNUMBER(Z$4),DATE(YEAR(Z$4),MONTH(Z$4),1),DATEVALUE("1-"&Z$4)),IF(OR(COUNTA($A16:$F16)>0,$G16<>""),$N16/12*IF($F16="",1,MAX(0,(EOMONTH(_xlpm.m,0)-MAX($F16,_xlpm.m)+1)/(EOMONTH(_xlpm.m,0)-_xlpm.m+1))),"")) | AA16: =IF(COUNTA($A16:$H16)>0,SUM(O16:Z16),"") | AB16: =_xlfn.LET(_xlpm.m,IF(ISNUMBER(AB$4),DATE(YEAR(AB$4),MONTH(AB$4),1),DATEVALUE("1-"&AB$4)),IF(OR(COUNTA($A16:$F16)>0,$G16<>""),$N16/12*IF($F16="",1,MAX(0,(EOMONTH(_xlpm.m,0)-MAX($F16,_xlpm.m)+1)/(EOMONTH(_xlpm.m,0)-_xlpm.m+1))),"")) | AC16: =_xlfn.LET(_xlpm.m,IF(ISNUMBER(AC$4),DATE(YEAR(AC$4),MONTH(AC$4),1),DATEVALUE("1-"&AC$4)),IF(OR(COUNTA($A16:$F16)>0,$G16<>""),$N16/12*IF($F16="",1,MAX(0,(EOMONTH(_xlpm.m,0)-MAX($F16,_xlpm.m)+1)/(EOMONTH(_xlpm.m,0)-_xlpm.m+1))),"")) | AD16: =_xlfn.LET(_xlpm.m,IF(ISNUMBER(AD$4),DATE(YEAR(AD$4),MONTH(AD$4),1),DATEVALUE("1-"&AD$4)),IF(OR(COUNTA($A16:$F16)>0,$G16<>""),$N16/12*IF($F16="",1,MAX(0,(EOMONTH(_xlpm.m,0)-MAX($F16,_xlpm.m)+1)/(EOMONTH(_xlpm.m,0)-_xlpm.m+1))),"")) | AE16: =_xlfn.LET(_xlpm.m,IF(ISNUMBER(AE$4),DATE(YEAR(AE$4),MONTH(AE$4),1),DATEVALUE("1-"&AE$4)),IF(OR(COUNTA($A16:$F16)>0,$G16<>""),$N16/12*IF($F16="",1,MAX(0,(EOMONTH(_xlpm.m,0)-MAX($F16,_xlpm.m)+1)/(EOMONTH(_xlpm.m,0)-_xlpm.m+1))),"")) | AF16: =_xlfn.LET(_xlpm.m,IF(ISNUMBER(AF$4),DATE(YEAR(AF$4),MONTH(AF$4),1),DATEVALUE("1-"&AF$4)),IF(OR(COUNTA($A16:$F16)>0,$G16<>""),$N16/12*IF($F16="",1,MAX(0,(EOMONTH(_xlpm.m,0)-MAX($F16,_xlpm.m)+1)/(EOMONTH(_xlpm.m,0)-_xlpm.m+1))),"")) | AG16: =_xlfn.LET(_xlpm.m,IF(ISNUMBER(AG$4),DATE(YEAR(AG$4),MONTH(AG$4),1),DATEVALUE("1-"&AG$4)),IF(OR(COUNTA($A16:$F16)>0,$G16<>""),$N16/12*IF($F16="",1,MAX(0,(EOMONTH(_xlpm.m,0)-MAX($F16,_xlpm.m)+1)/(EOMONTH(_xlpm.m,0)-_xlpm.m+1))),"")) | AH16: =_xlfn.LET(_xlpm.m,IF(ISNUMBER(AH$4),DATE(YEAR(AH$4),MONTH(AH$4),1),DATEVALUE("1-"&AH$4)),IF(OR(COUNTA($A16:$F16)>0,$G16<>""),$N16/12*IF($F16="",1,MAX(0,(EOMONTH(_xlpm.m,0)-MAX($F16,_xlpm.m)+1)/(EOMONTH(_xlpm.m,0)-_xlpm.m+1))),"")) | AI16: =_xlfn.LET(_xlpm.m,IF(ISNUMBER(AI$4),DATE(YEAR(AI$4),MONTH(AI$4),1),DATEVALUE("1-"&AI$4)),IF(OR(COUNTA($A16:$F16)>0,$G16<>""),$N16/12*IF($F16="",1,MAX(0,(EOMONTH(_xlpm.m,0)-MAX($F16,_xlpm.m)+1)/(EOMONTH(_xlpm.m,0)-_xlpm.m+1))),"")) | ... AM16: =_xlfn.LET(_xlpm.m,IF(ISNUMBER(AM$4),DATE(YEAR(AM$4),MONTH(AM$4),1),DATEVALUE("1-"&AM$4)),IF(OR(COUNTA($A16:$F16)>0,$G16<>""),$N16/12*IF($F16="",1,MAX(0,(EOMONTH(_xlpm.m,0)-MAX($F16,_xlpm.m)+1)/(EOMONTH(_xlpm.m,0)-_xlpm.m+1))),"")) | AN16: =IF(COUNTA($A16:$H16)>0,SUM(AB16:AM16),"") | AO16: =_xlfn.LET(_xlpm.m,IF(ISNUMBER(AO$4),DATE(YEAR(AO$4),MONTH(AO$4),1),DATEVALUE("1-"&AO$4)),IF(OR(COUNTA($A16:$F16)>0,$G16<>""),$N16/12*IF($F16="",1,MAX(0,(EOMONTH(_xlpm.m,0)-MAX($F16,_xlpm.m)+1)/(EOMONTH(_xlpm.m,0)-_xlpm.m+1))),"")) | AP16: =_xlfn.LET(_xlpm.m,IF(ISNUMBER(AP$4),DATE(YEAR(AP$4),MONTH(AP$4),1),DATEVALUE("1-"&AP$4)),IF(OR(COUNTA($A16:$F16)>0,$G16<>""),$N16/12*IF($F16="",1,MAX(0,(EOMONTH(_xlpm.m,0)-MAX($F16,_xlpm.m)+1)/(EOMONTH(_xlpm.m,0)-_xlpm.m+1))),"")) | AQ16: =_xlfn.LET(_xlpm.m,IF(ISNUMBER(AQ$4),DATE(YEAR(AQ$4),MONTH(AQ$4),1),DATEVALUE("1-"&AQ$4)),IF(OR(COUNTA($A16:$F16)>0,$G16<>""),$N16/12*IF($F16="",1,MAX(0,(EOMONTH(_xlpm.m,0)-MAX($F16,_xlpm.m)+1)/(EOMONTH(_xlpm.m,0)-_xlpm.m+1))),"")) | AR16: =_xlfn.LET(_xlpm.m,IF(ISNUMBER(AR$4),DATE(YEAR(AR$4),MONTH(AR$4),1),DATEVALUE("1-"&AR$4)),IF(OR(COUNTA($A16:$F16)>0,$G16<>""),$N16/12*IF($F16="",1,MAX(0,(EOMONTH(_xlpm.m,0)-MAX($F16,_xlpm.m)+1)/(EOMONTH(_xlpm.m,0)-_xlpm.m+1))),"")) | AS16: =_xlfn.LET(_xlpm.m,IF(ISNUMBER(AS$4),DATE(YEAR(AS$4),MONTH(AS$4),1),DATEVALUE("1-"&AS$4)),IF(OR(COUNTA($A16:$F16)>0,$G16<>""),$N16/12*IF($F16="",1,MAX(0,(EOMONTH(_xlpm.m,0)-MAX($F16,_xlpm.m)+1)/(EOMONTH(_xlpm.m,0)-_xlpm.m+1))),"")) | AT16: =_xlfn.LET(_xlpm.m,IF(ISNUMBER(AT$4),DATE(YEAR(AT$4),MONTH(AT$4),1),DATEVALUE("1-"&AT$4)),IF(OR(COUNTA($A16:$F16)>0,$G16<>""),$N16/12*IF($F16="",1,MAX(0,(EOMONTH(_xlpm.m,0)-MAX($F16,_xlpm.m)+1)/(EOMONTH(_xlpm.m,0)-_xlpm.m+1))),"")) | AU16: =_xlfn.LET(_xlpm.m,IF(ISNUMBER(AU$4),DATE(YEAR(AU$4),MONTH(AU$4),1),DATEVALUE("1-"&AU$4)),IF(OR(COUNTA($A16:$F16)>0,$G16<>""),$N16/12*IF($F16="",1,MAX(0,(EOMONTH(_xlpm.m,0)-MAX($F16,_xlpm.m)+1)/(EOMONTH(_xlpm.m,0)-_xlpm.m+1))),"")) | AV16: =_xlfn.LET(_xlpm.m,IF(ISNUMBER(AV$4),DATE(YEAR(AV$4),MONTH(AV$4),1),DATEVALUE("1-"&AV$4)),IF(OR(COUNTA($A16:$F16)>0,$G16<>""),$N16/12*IF($F16="",1,MAX(0,(EOMONTH(_xlpm.m,0)-MAX($F16,_xlpm.m)+1)/(EOMONTH(_xlpm.m,0)-_xlpm.m+1))),"")) | ... AZ16: =_xlfn.LET(_xlpm.m,IF(ISNUMBER(AZ$4),DATE(YEAR(AZ$4),MONTH(AZ$4),1),DATEVALUE("1-"&AZ$4)),IF(OR(COUNTA($A16:$F16)>0,$G16<>""),$N16/12*IF($F16="",1,MAX(0,(EOMONTH(_xlpm.m,0)-MAX($F16,_xlpm.m)+1)/(EOMONTH(_xlpm.m,0)-_xlpm.m+1))),"")) | BA16: =IF(COUNTA($A16:$H16)>0,SUM(AO16:AZ16),"")
I17: =IF(COUNTA($A17:$H17)>0,IFERROR($G17*$H17,0),"") | J17: =IF(COUNTA($A17:$H17)>0,IFERROR($G17*Summary!$C$46/Summary!$C$43,0),"") | K17: =IF(COUNTA($A17:$H17)>0,IFERROR($G17*Summary!$C$47/Summary!$C$43,0),"") | L17: =IF(COUNTA($A17:$H17)>0,IFERROR($G17*Summary!$C$48/Summary!$C$43,0),"") | M17: =IF(COUNTA($A17:$H17)>0,IFERROR($G17*Summary!$C$49/Summary!$C$43,0),"") | N17: =IF(COUNTA($A17:$H17)>0,IFERROR($G17,0)+SUM(I17:M17),"") | O17: =_xlfn.LET(_xlpm.m,IF(ISNUMBER(O$4),DATE(YEAR(O$4),MONTH(O$4),1),DATEVALUE("1-"&O$4)),IF(OR(COUNTA($A17:$F17)>0,$G17<>""),$N17/12*IF($F17="",1,MAX(0,(EOMONTH(_xlpm.m,0)-MAX($F17,_xlpm.m)+1)/(EOMONTH(_xlpm.m,0)-_xlpm.m+1))),"")) | P17: =_xlfn.LET(_xlpm.m,IF(ISNUMBER(P$4),DATE(YEAR(P$4),MONTH(P$4),1),DATEVALUE("1-"&P$4)),IF(OR(COUNTA($A17:$F17)>0,$G17<>""),$N17/12*IF($F17="",1,MAX(0,(EOMONTH(_xlpm.m,0)-MAX($F17,_xlpm.m)+1)/(EOMONTH(_xlpm.m,0)-_xlpm.m+1))),"")) | Q17: =_xlfn.LET(_xlpm.m,IF(ISNUMBER(Q$4),DATE(YEAR(Q$4),MONTH(Q$4),1),DATEVALUE("1-"&Q$4)),IF(OR(COUNTA($A17:$F17)>0,$G17<>""),$N17/12*IF($F17="",1,MAX(0,(EOMONTH(_xlpm.m,0)-MAX($F17,_xlpm.m)+1)/(EOMONTH(_xlpm.m,0)-_xlpm.m+1))),"")) | R17: =_xlfn.LET(_xlpm.m,IF(ISNUMBER(R$4),DATE(YEAR(R$4),MONTH(R$4),1),DATEVALUE("1-"&R$4)),IF(OR(COUNTA($A17:$F17)>0,$G17<>""),$N17/12*IF($F17="",1,MAX(0,(EOMONTH(_xlpm.m,0)-MAX($F17,_xlpm.m)+1)/(EOMONTH(_xlpm.m,0)-_xlpm.m+1))),"")) | S17: =_xlfn.LET(_xlpm.m,IF(ISNUMBER(S$4),DATE(YEAR(S$4),MONTH(S$4),1),DATEVALUE("1-"&S$4)),IF(OR(COUNTA($A17:$F17)>0,$G17<>""),$N17/12*IF($F17="",1,MAX(0,(EOMONTH(_xlpm.m,0)-MAX($F17,_xlpm.m)+1)/(EOMONTH(_xlpm.m,0)-_xlpm.m+1))),"")) | T17: =_xlfn.LET(_xlpm.m,IF(ISNUMBER(T$4),DATE(YEAR(T$4),MONTH(T$4),1),DATEVALUE("1-"&T$4)),IF(OR(COUNTA($A17:$F17)>0,$G17<>""),$N17/12*IF($F17="",1,MAX(0,(EOMONTH(_xlpm.m,0)-MAX($F17,_xlpm.m)+1)/(EOMONTH(_xlpm.m,0)-_xlpm.m+1))),"")) | U17: =_xlfn.LET(_xlpm.m,IF(ISNUMBER(U$4),DATE(YEAR(U$4),MONTH(U$4),1),DATEVALUE("1-"&U$4)),IF(OR(COUNTA($A17:$F17)>0,$G17<>""),$N17/12*IF($F17="",1,MAX(0,(EOMONTH(_xlpm.m,0)-MAX($F17,_xlpm.m)+1)/(EOMONTH(_xlpm.m,0)-_xlpm.m+1))),"")) | V17: =_xlfn.LET(_xlpm.m,IF(ISNUMBER(V$4),DATE(YEAR(V$4),MONTH(V$4),1),DATEVALUE("1-"&V$4)),IF(OR(COUNTA($A17:$F17)>0,$G17<>""),$N17/12*IF($F17="",1,MAX(0,(EOMONTH(_xlpm.m,0)-MAX($F17,_xlpm.m)+1)/(EOMONTH(_xlpm.m,0)-_xlpm.m+1))),"")) | ... Z17: =_xlfn.LET(_xlpm.m,IF(ISNUMBER(Z$4),DATE(YEAR(Z$4),MONTH(Z$4),1),DATEVALUE("1-"&Z$4)),IF(OR(COUNTA($A17:$F17)>0,$G17<>""),$N17/12*IF($F17="",1,MAX(0,(EOMONTH(_xlpm.m,0)-MAX($F17,_xlpm.m)+1)/(EOMONTH(_xlpm.m,0)-_xlpm.m+1))),"")) | AA17: =IF(COUNTA($A17:$H17)>0,SUM(O17:Z17),"") | AB17: =_xlfn.LET(_xlpm.m,IF(ISNUMBER(AB$4),DATE(YEAR(AB$4),MONTH(AB$4),1),DATEVALUE("1-"&AB$4)),IF(OR(COUNTA($A17:$F17)>0,$G17<>""),$N17/12*IF($F17="",1,MAX(0,(EOMONTH(_xlpm.m,0)-MAX($F17,_xlpm.m)+1)/(EOMONTH(_xlpm.m,0)-_xlpm.m+1))),"")) | AC17: =_xlfn.LET(_xlpm.m,IF(ISNUMBER(AC$4),DATE(YEAR(AC$4),MONTH(AC$4),1),DATEVALUE("1-"&AC$4)),IF(OR(COUNTA($A17:$F17)>0,$G17<>""),$N17/12*IF($F17="",1,MAX(0,(EOMONTH(_xlpm.m,0)-MAX($F17,_xlpm.m)+1)/(EOMONTH(_xlpm.m,0)-_xlpm.m+1))),"")) | AD17: =_xlfn.LET(_xlpm.m,IF(ISNUMBER(AD$4),DATE(YEAR(AD$4),MONTH(AD$4),1),DATEVALUE("1-"&AD$4)),IF(OR(COUNTA($A17:$F17)>0,$G17<>""),$N17/12*IF($F17="",1,MAX(0,(EOMONTH(_xlpm.m,0)-MAX($F17,_xlpm.m)+1)/(EOMONTH(_xlpm.m,0)-_xlpm.m+1))),"")) | AE17: =_xlfn.LET(_xlpm.m,IF(ISNUMBER(AE$4),DATE(YEAR(AE$4),MONTH(AE$4),1),DATEVALUE("1-"&AE$4)),IF(OR(COUNTA($A17:$F17)>0,$G17<>""),$N17/12*IF($F17="",1,MAX(0,(EOMONTH(_xlpm.m,0)-MAX($F17,_xlpm.m)+1)/(EOMONTH(_xlpm.m,0)-_xlpm.m+1))),"")) | AF17: =_xlfn.LET(_xlpm.m,IF(ISNUMBER(AF$4),DATE(YEAR(AF$4),MONTH(AF$4),1),DATEVALUE("1-"&AF$4)),IF(OR(COUNTA($A17:$F17)>0,$G17<>""),$N17/12*IF($F17="",1,MAX(0,(EOMONTH(_xlpm.m,0)-MAX($F17,_xlpm.m)+1)/(EOMONTH(_xlpm.m,0)-_xlpm.m+1))),"")) | AG17: =_xlfn.LET(_xlpm.m,IF(ISNUMBER(AG$4),DATE(YEAR(AG$4),MONTH(AG$4),1),DATEVALUE("1-"&AG$4)),IF(OR(COUNTA($A17:$F17)>0,$G17<>""),$N17/12*IF($F17="",1,MAX(0,(EOMONTH(_xlpm.m,0)-MAX($F17,_xlpm.m)+1)/(EOMONTH(_xlpm.m,0)-_xlpm.m+1))),"")) | AH17: =_xlfn.LET(_xlpm.m,IF(ISNUMBER(AH$4),DATE(YEAR(AH$4),MONTH(AH$4),1),DATEVALUE("1-"&AH$4)),IF(OR(COUNTA($A17:$F17)>0,$G17<>""),$N17/12*IF($F17="",1,MAX(0,(EOMONTH(_xlpm.m,0)-MAX($F17,_xlpm.m)+1)/(EOMONTH(_xlpm.m,0)-_xlpm.m+1))),"")) | AI17: =_xlfn.LET(_xlpm.m,IF(ISNUMBER(AI$4),DATE(YEAR(AI$4),MONTH(AI$4),1),DATEVALUE("1-"&AI$4)),IF(OR(COUNTA($A17:$F17)>0,$G17<>""),$N17/12*IF($F17="",1,MAX(0,(EOMONTH(_xlpm.m,0)-MAX($F17,_xlpm.m)+1)/(EOMONTH(_xlpm.m,0)-_xlpm.m+1))),"")) | ... AM17: =_xlfn.LET(_xlpm.m,IF(ISNUMBER(AM$4),DATE(YEAR(AM$4),MONTH(AM$4),1),DATEVALUE("1-"&AM$4)),IF(OR(COUNTA($A17:$F17)>0,$G17<>""),$N17/12*IF($F17="",1,MAX(0,(EOMONTH(_xlpm.m,0)-MAX($F17,_xlpm.m)+1)/(EOMONTH(_xlpm.m,0)-_xlpm.m+1))),"")) | AN17: =IF(COUNTA($A17:$H17)>0,SUM(AB17:AM17),"") | AO17: =_xlfn.LET(_xlpm.m,IF(ISNUMBER(AO$4),DATE(YEAR(AO$4),MONTH(AO$4),1),DATEVALUE("1-"&AO$4)),IF(OR(COUNTA($A17:$F17)>0,$G17<>""),$N17/12*IF($F17="",1,MAX(0,(EOMONTH(_xlpm.m,0)-MAX($F17,_xlpm.m)+1)/(EOMONTH(_xlpm.m,0)-_xlpm.m+1))),"")) | AP17: =_xlfn.LET(_xlpm.m,IF(ISNUMBER(AP$4),DATE(YEAR(AP$4),MONTH(AP$4),1),DATEVALUE("1-"&AP$4)),IF(OR(COUNTA($A17:$F17)>0,$G17<>""),$N17/12*IF($F17="",1,MAX(0,(EOMONTH(_xlpm.m,0)-MAX($F17,_xlpm.m)+1)/(EOMONTH(_xlpm.m,0)-_xlpm.m+1))),"")) | AQ17: =_xlfn.LET(_xlpm.m,IF(ISNUMBER(AQ$4),DATE(YEAR(AQ$4),MONTH(AQ$4),1),DATEVALUE("1-"&AQ$4)),IF(OR(COUNTA($A17:$F17)>0,$G17<>""),$N17/12*IF($F17="",1,MAX(0,(EOMONTH(_xlpm.m,0)-MAX($F17,_xlpm.m)+1)/(EOMONTH(_xlpm.m,0)-_xlpm.m+1))),"")) | AR17: =_xlfn.LET(_xlpm.m,IF(ISNUMBER(AR$4),DATE(YEAR(AR$4),MONTH(AR$4),1),DATEVALUE("1-"&AR$4)),IF(OR(COUNTA($A17:$F17)>0,$G17<>""),$N17/12*IF($F17="",1,MAX(0,(EOMONTH(_xlpm.m,0)-MAX($F17,_xlpm.m)+1)/(EOMONTH(_xlpm.m,0)-_xlpm.m+1))),"")) | AS17: =_xlfn.LET(_xlpm.m,IF(ISNUMBER(AS$4),DATE(YEAR(AS$4),MONTH(AS$4),1),DATEVALUE("1-"&AS$4)),IF(OR(COUNTA($A17:$F17)>0,$G17<>""),$N17/12*IF($F17="",1,MAX(0,(EOMONTH(_xlpm.m,0)-MAX($F17,_xlpm.m)+1)/(EOMONTH(_xlpm.m,0)-_xlpm.m+1))),"")) | AT17: =_xlfn.LET(_xlpm.m,IF(ISNUMBER(AT$4),DATE(YEAR(AT$4),MONTH(AT$4),1),DATEVALUE("1-"&AT$4)),IF(OR(COUNTA($A17:$F17)>0,$G17<>""),$N17/12*IF($F17="",1,MAX(0,(EOMONTH(_xlpm.m,0)-MAX($F17,_xlpm.m)+1)/(EOMONTH(_xlpm.m,0)-_xlpm.m+1))),"")) | AU17: =_xlfn.LET(_xlpm.m,IF(ISNUMBER(AU$4),DATE(YEAR(AU$4),MONTH(AU$4),1),DATEVALUE("1-"&AU$4)),IF(OR(COUNTA($A17:$F17)>0,$G17<>""),$N17/12*IF($F17="",1,MAX(0,(EOMONTH(_xlpm.m,0)-MAX($F17,_xlpm.m)+1)/(EOMONTH(_xlpm.m,0)-_xlpm.m+1))),"")) | AV17: =_xlfn.LET(_xlpm.m,IF(ISNUMBER(AV$4),DATE(YEAR(AV$4),MONTH(AV$4),1),DATEVALUE("1-"&AV$4)),IF(OR(COUNTA($A17:$F17)>0,$G17<>""),$N17/12*IF($F17="",1,MAX(0,(EOMONTH(_xlpm.m,0)-MAX($F17,_xlpm.m)+1)/(EOMONTH(_xlpm.m,0)-_xlpm.m+1))),"")) | ... AZ17: =_xlfn.LET(_xlpm.m,IF(ISNUMBER(AZ$4),DATE(YEAR(AZ$4),MONTH(AZ$4),1),DATEVALUE("1-"&AZ$4)),IF(OR(COUNTA($A17:$F17)>0,$G17<>""),$N17/12*IF($F17="",1,MAX(0,(EOMONTH(_xlpm.m,0)-MAX($F17,_xlpm.m)+1)/(EOMONTH(_xlpm.m,0)-_xlpm.m+1))),"")) | BA17: =IF(COUNTA($A17:$H17)>0,SUM(AO17:AZ17),"")
... I20: =IF(COUNTA($A20:$H20)>0,IFERROR($G20*$H20,0),"") | J20: =IF(COUNTA($A20:$H20)>0,IFERROR($G20*Summary!$C$46/Summary!$C$43,0),"") | K20: =IF(COUNTA($A20:$H20)>0,IFERROR($G20*Summary!$C$47/Summary!$C$43,0),"") | L20: =IF(COUNTA($A20:$H20)>0,IFERROR($G20*Summary!$C$48/Summary!$C$43,0),"") | M20: =IF(COUNTA($A20:$H20)>0,IFERROR($G20*Summary!$C$49/Summary!$C$43,0),"") | N20: =IF(COUNTA($A20:$H20)>0,IFERROR($G20,0)+SUM(I20:M20),"") | O20: =_xlfn.LET(_xlpm.m,IF(ISNUMBER(O$4),DATE(YEAR(O$4),MONTH(O$4),1),DATEVALUE("1-"&O$4)),IF(OR(COUNTA($A20:$F20)>0,$G20<>""),$N20/12*IF($F20="",1,MAX(0,(EOMONTH(_xlpm.m,0)-MAX($F20,_xlpm.m)+1)/(EOMONTH(_xlpm.m,0)-_xlpm.m+1))),"")) | P20: =_xlfn.LET(_xlpm.m,IF(ISNUMBER(P$4),DATE(YEAR(P$4),MONTH(P$4),1),DATEVALUE("1-"&P$4)),IF(OR(COUNTA($A20:$F20)>0,$G20<>""),$N20/12*IF($F20="",1,MAX(0,(EOMONTH(_xlpm.m,0)-MAX($F20,_xlpm.m)+1)/(EOMONTH(_xlpm.m,0)-_xlpm.m+1))),"")) | Q20: =_xlfn.LET(_xlpm.m,IF(ISNUMBER(Q$4),DATE(YEAR(Q$4),MONTH(Q$4),1),DATEVALUE("1-"&Q$4)),IF(OR(COUNTA($A20:$F20)>0,$G20<>""),$N20/12*IF($F20="",1,MAX(0,(EOMONTH(_xlpm.m,0)-MAX($F20,_xlpm.m)+1)/(EOMONTH(_xlpm.m,0)-_xlpm.m+1))),"")) | R20: =_xlfn.LET(_xlpm.m,IF(ISNUMBER(R$4),DATE(YEAR(R$4),MONTH(R$4),1),DATEVALUE("1-"&R$4)),IF(OR(COUNTA($A20:$F20)>0,$G20<>""),$N20/12*IF($F20="",1,MAX(0,(EOMONTH(_xlpm.m,0)-MAX($F20,_xlpm.m)+1)/(EOMONTH(_xlpm.m,0)-_xlpm.m+1))),"")) | S20: =_xlfn.LET(_xlpm.m,IF(ISNUMBER(S$4),DATE(YEAR(S$4),MONTH(S$4),1),DATEVALUE("1-"&S$4)),IF(OR(COUNTA($A20:$F20)>0,$G20<>""),$N20/12*IF($F20="",1,MAX(0,(EOMONTH(_xlpm.m,0)-MAX($F20,_xlpm.m)+1)/(EOMONTH(_xlpm.m,0)-_xlpm.m+1))),"")) | T20: =_xlfn.LET(_xlpm.m,IF(ISNUMBER(T$4),DATE(YEAR(T$4),MONTH(T$4),1),DATEVALUE("1-"&T$4)),IF(OR(COUNTA($A20:$F20)>0,$G20<>""),$N20/12*IF($F20="",1,MAX(0,(EOMONTH(_xlpm.m,0)-MAX($F20,_xlpm.m)+1)/(EOMONTH(_xlpm.m,0)-_xlpm.m+1))),"")) | U20: =_xlfn.LET(_xlpm.m,IF(ISNUMBER(U$4),DATE(YEAR(U$4),MONTH(U$4),1),DATEVALUE("1-"&U$4)),IF(OR(COUNTA($A20:$F20)>0,$G20<>""),$N20/12*IF($F20="",1,MAX(0,(EOMONTH(_xlpm.m,0)-MAX($F20,_xlpm.m)+1)/(EOMONTH(_xlpm.m,0)-_xlpm.m+1))),"")) | V20: =_xlfn.LET(_xlpm.m,IF(ISNUMBER(V$4),DATE(YEAR(V$4),MONTH(V$4),1),DATEVALUE("1-"&V$4)),IF(OR(COUNTA($A20:$F20)>0,$G20<>""),$N20/12*IF($F20="",1,MAX(0,(EOMONTH(_xlpm.m,0)-MAX($F20,_xlpm.m)+1)/(EOMONTH(_xlpm.m,0)-_xlpm.m+1))),"")) | ... Z20: =_xlfn.LET(_xlpm.m,IF(ISNUMBER(Z$4),DATE(YEAR(Z$4),MONTH(Z$4),1),DATEVALUE("1-"&Z$4)),IF(OR(COUNTA($A20:$F20)>0,$G20<>""),$N20/12*IF($F20="",1,MAX(0,(EOMONTH(_xlpm.m,0)-MAX($F20,_xlpm.m)+1)/(EOMONTH(_xlpm.m,0)-_xlpm.m+1))),"")) | AA20: =IF(COUNTA($A20:$H20)>0,SUM(O20:Z20),"") | AB20: =_xlfn.LET(_xlpm.m,IF(ISNUMBER(AB$4),DATE(YEAR(AB$4),MONTH(AB$4),1),DATEVALUE("1-"&AB$4)),IF(OR(COUNTA($A20:$F20)>0,$G20<>""),$N20/12*IF($F20="",1,MAX(0,(EOMONTH(_xlpm.m,0)-MAX($F20,_xlpm.m)+1)/(EOMONTH(_xlpm.m,0)-_xlpm.m+1))),"")) | AC20: =_xlfn.LET(_xlpm.m,IF(ISNUMBER(AC$4),DATE(YEAR(AC$4),MONTH(AC$4),1),DATEVALUE("1-"&AC$4)),IF(OR(COUNTA($A20:$F20)>0,$G20<>""),$N20/12*IF($F20="",1,MAX(0,(EOMONTH(_xlpm.m,0)-MAX($F20,_xlpm.m)+1)/(EOMONTH(_xlpm.m,0)-_xlpm.m+1))),"")) | AD20: =_xlfn.LET(_xlpm.m,IF(ISNUMBER(AD$4),DATE(YEAR(AD$4),MONTH(AD$4),1),DATEVALUE("1-"&AD$4)),IF(OR(COUNTA($A20:$F20)>0,$G20<>""),$N20/12*IF($F20="",1,MAX(0,(EOMONTH(_xlpm.m,0)-MAX($F20,_xlpm.m)+1)/(EOMONTH(_xlpm.m,0)-_xlpm.m+1))),"")) | AE20: =_xlfn.LET(_xlpm.m,IF(ISNUMBER(AE$4),DATE(YEAR(AE$4),MONTH(AE$4),1),DATEVALUE("1-"&AE$4)),IF(OR(COUNTA($A20:$F20)>0,$G20<>""),$N20/12*IF($F20="",1,MAX(0,(EOMONTH(_xlpm.m,0)-MAX($F20,_xlpm.m)+1)/(EOMONTH(_xlpm.m,0)-_xlpm.m+1))),"")) | AF20: =_xlfn.LET(_xlpm.m,IF(ISNUMBER(AF$4),DATE(YEAR(AF$4),MONTH(AF$4),1),DATEVALUE("1-"&AF$4)),IF(OR(COUNTA($A20:$F20)>0,$G20<>""),$N20/12*IF($F20="",1,MAX(0,(EOMONTH(_xlpm.m,0)-MAX($F20,_xlpm.m)+1)/(EOMONTH(_xlpm.m,0)-_xlpm.m+1))),"")) | AG20: =_xlfn.LET(_xlpm.m,IF(ISNUMBER(AG$4),DATE(YEAR(AG$4),MONTH(AG$4),1),DATEVALUE("1-"&AG$4)),IF(OR(COUNTA($A20:$F20)>0,$G20<>""),$N20/12*IF($F20="",1,MAX(0,(EOMONTH(_xlpm.m,0)-MAX($F20,_xlpm.m)+1)/(EOMONTH(_xlpm.m,0)-_xlpm.m+1))),"")) | AH20: =_xlfn.LET(_xlpm.m,IF(ISNUMBER(AH$4),DATE(YEAR(AH$4),MONTH(AH$4),1),DATEVALUE("1-"&AH$4)),IF(OR(COUNTA($A20:$F20)>0,$G20<>""),$N20/12*IF($F20="",1,MAX(0,(EOMONTH(_xlpm.m,0)-MAX($F20,_xlpm.m)+1)/(EOMONTH(_xlpm.m,0)-_xlpm.m+1))),"")) | AI20: =_xlfn.LET(_xlpm.m,IF(ISNUMBER(AI$4),DATE(YEAR(AI$4),MONTH(AI$4),1),DATEVALUE("1-"&AI$4)),IF(OR(COUNTA($A20:$F20)>0,$G20<>""),$N20/12*IF($F20="",1,MAX(0,(EOMONTH(_xlpm.m,0)-MAX($F20,_xlpm.m)+1)/(EOMONTH(_xlpm.m,0)-_xlpm.m+1))),"")) | ... AM20: =_xlfn.LET(_xlpm.m,IF(ISNUMBER(AM$4),DATE(YEAR(AM$4),MONTH(AM$4),1),DATEVALUE("1-"&AM$4)),IF(OR(COUNTA($A20:$F20)>0,$G20<>""),$N20/12*IF($F20="",1,MAX(0,(EOMONTH(_xlpm.m,0)-MAX($F20,_xlpm.m)+1)/(EOMONTH(_xlpm.m,0)-_xlpm.m+1))),"")) | AN20: =IF(COUNTA($A20:$H20)>0,SUM(AB20:AM20),"") | AO20: =_xlfn.LET(_xlpm.m,IF(ISNUMBER(AO$4),DATE(YEAR(AO$4),MONTH(AO$4),1),DATEVALUE("1-"&AO$4)),IF(OR(COUNTA($A20:$F20)>0,$G20<>""),$N20/12*IF($F20="",1,MAX(0,(EOMONTH(_xlpm.m,0)-MAX($F20,_xlpm.m)+1)/(EOMONTH(_xlpm.m,0)-_xlpm.m+1))),"")) | AP20: =_xlfn.LET(_xlpm.m,IF(ISNUMBER(AP$4),DATE(YEAR(AP$4),MONTH(AP$4),1),DATEVALUE("1-"&AP$4)),IF(OR(COUNTA($A20:$F20)>0,$G20<>""),$N20/12*IF($F20="",1,MAX(0,(EOMONTH(_xlpm.m,0)-MAX($F20,_xlpm.m)+1)/(EOMONTH(_xlpm.m,0)-_xlpm.m+1))),"")) | AQ20: =_xlfn.LET(_xlpm.m,IF(ISNUMBER(AQ$4),DATE(YEAR(AQ$4),MONTH(AQ$4),1),DATEVALUE("1-"&AQ$4)),IF(OR(COUNTA($A20:$F20)>0,$G20<>""),$N20/12*IF($F20="",1,MAX(0,(EOMONTH(_xlpm.m,0)-MAX($F20,_xlpm.m)+1)/(EOMONTH(_xlpm.m,0)-_xlpm.m+1))),"")) | AR20: =_xlfn.LET(_xlpm.m,IF(ISNUMBER(AR$4),DATE(YEAR(AR$4),MONTH(AR$4),1),DATEVALUE("1-"&AR$4)),IF(OR(COUNTA($A20:$F20)>0,$G20<>""),$N20/12*IF($F20="",1,MAX(0,(EOMONTH(_xlpm.m,0)-MAX($F20,_xlpm.m)+1)/(EOMONTH(_xlpm.m,0)-_xlpm.m+1))),"")) | AS20: =_xlfn.LET(_xlpm.m,IF(ISNUMBER(AS$4),DATE(YEAR(AS$4),MONTH(AS$4),1),DATEVALUE("1-"&AS$4)),IF(OR(COUNTA($A20:$F20)>0,$G20<>""),$N20/12*IF($F20="",1,MAX(0,(EOMONTH(_xlpm.m,0)-MAX($F20,_xlpm.m)+1)/(EOMONTH(_xlpm.m,0)-_xlpm.m+1))),"")) | AT20: =_xlfn.LET(_xlpm.m,IF(ISNUMBER(AT$4),DATE(YEAR(AT$4),MONTH(AT$4),1),DATEVALUE("1-"&AT$4)),IF(OR(COUNTA($A20:$F20)>0,$G20<>""),$N20/12*IF($F20="",1,MAX(0,(EOMONTH(_xlpm.m,0)-MAX($F20,_xlpm.m)+1)/(EOMONTH(_xlpm.m,0)-_xlpm.m+1))),"")) | AU20: =_xlfn.LET(_xlpm.m,IF(ISNUMBER(AU$4),DATE(YEAR(AU$4),MONTH(AU$4),1),DATEVALUE("1-"&AU$4)),IF(OR(COUNTA($A20:$F20)>0,$G20<>""),$N20/12*IF($F20="",1,MAX(0,(EOMONTH(_xlpm.m,0)-MAX($F20,_xlpm.m)+1)/(EOMONTH(_xlpm.m,0)-_xlpm.m+1))),"")) | AV20: =_xlfn.LET(_xlpm.m,IF(ISNUMBER(AV$4),DATE(YEAR(AV$4),MONTH(AV$4),1),DATEVALUE("1-"&AV$4)),IF(OR(COUNTA($A20:$F20)>0,$G20<>""),$N20/12*IF($F20="",1,MAX(0,(EOMONTH(_xlpm.m,0)-MAX($F20,_xlpm.m)+1)/(EOMONTH(_xlpm.m,0)-_xlpm.m+1))),"")) | ... AZ20: =_xlfn.LET(_xlpm.m,IF(ISNUMBER(AZ$4),DATE(YEAR(AZ$4),MONTH(AZ$4),1),DATEVALUE("1-"&AZ$4)),IF(OR(COUNTA($A20:$F20)>0,$G20<>""),$N20/12*IF($F20="",1,MAX(0,(EOMONTH(_xlpm.m,0)-MAX($F20,_xlpm.m)+1)/(EOMONTH(_xlpm.m,0)-_xlpm.m+1))),"")) | BA20: =IF(COUNTA($A20:$H20)>0,SUM(AO20:AZ20),"")
A22: Total Payroll / Headcount Incremental Spend | G22: =SUM(G5:G20) -> 0 | I22: =SUM(I5:I20) -> 0 | J22: =SUM(J5:J20) -> 0 | K22: =SUM(K5:K20) -> 0 | L22: =SUM(L5:L20) -> 0 | M22: =SUM(M5:M20) -> 0 | N22: =SUM(N5:N20) -> 0 | O22: =SUM(O5:O20) -> 0 | P22: =SUM(P5:P20) -> 0 | ... BA22: =SUM(BA5:BA20) -> 0
A26: Essentials Bonus / Contract Labor / Non-Payroll Incremental Spend
A27: Expense Description | B27: Type of Expense | C27: Vendor | D27: Annualized Spend | E27: Jan-27 | F27: Feb-27 | G27: Mar-27 | H27: Apr-27 | I27: May-27 | J27: Jun-27 | K27: Jul-27 | L27: Aug-27 | M27: Sep-27 | N27: Oct-27 | O27: Nov-27 | P27: Dec-27 | Q27: 2027 Incremental Spend | R27: Jan-28 | S27: Feb-28 | T27: Mar-28 | U27: Apr-28 | V27: May-28 | W27: Jun-28 | X27: Jul-28 | Y27: Aug-28 | Z27: Sep-28 | AA27: Oct-28 | AB27: Nov-28 | AC27: Dec-28 | AD27: 2028 Incremental Spend | AE27: Jan-29 | AF27: Feb-29 | AG27: Mar-29 | AH27: Apr-29 | AI27: May-29 | AJ27: Jun-29 | AK27: Jul-29 | AL27: Aug-29 | AM27: Sep-29 | AN27: Oct-29 | AO27: Nov-29 | AP27: Dec-29 | AQ27: 2029 Incremental Spend | AR27: Notes / Rationale
E28: =IF(COUNTA($A28:$D28)>0,IFERROR($D28/12,0),"") | F28: =IF(COUNTA($A28:$D28)>0,IFERROR($D28/12,0),"") | G28: =IF(COUNTA($A28:$D28)>0,IFERROR($D28/12,0),"") | H28: =IF(COUNTA($A28:$D28)>0,IFERROR($D28/12,0),"") | I28: =IF(COUNTA($A28:$D28)>0,IFERROR($D28/12,0),"") | J28: =IF(COUNTA($A28:$D28)>0,IFERROR($D28/12,0),"") | K28: =IF(COUNTA($A28:$D28)>0,IFERROR($D28/12,0),"") | L28: =IF(COUNTA($A28:$D28)>0,IFERROR($D28/12,0),"") | ... P28: =IF(COUNTA($A28:$D28)>0,IFERROR($D28/12,0),"") | Q28: =SUM(tblNonPayrollIncrementalSpend3[[#This Row],[Jan-27]:[Dec-27]]) -> 0 | R28: =IF(COUNTA($A28:$D28)>0,IFERROR($D28/12,0),"") | S28: =IF(COUNTA($A28:$D28)>0,IFERROR($D28/12,0),"") | T28: =IF(COUNTA($A28:$D28)>0,IFERROR($D28/12,0),"") | U28: =IF(COUNTA($A28:$D28)>0,IFERROR($D28/12,0),"") | V28: =IF(COUNTA($A28:$D28)>0,IFERROR($D28/12,0),"") | W28: =IF(COUNTA($A28:$D28)>0,IFERROR($D28/12,0),"") | X28: =IF(COUNTA($A28:$D28)>0,IFERROR($D28/12,0),"") | Y28: =IF(COUNTA($A28:$D28)>0,IFERROR($D28/12,0),"") | ... AC28: =IF(COUNTA($A28:$D28)>0,IFERROR($D28/12,0),"") | AD28: =SUM(tblNonPayrollIncrementalSpend3[[#This Row],[Jan-27]:[Dec-27]]) -> 0 | AE28: =IF(COUNTA($A28:$D28)>0,IFERROR($D28/12,0),"") | AF28: =IF(COUNTA($A28:$D28)>0,IFERROR($D28/12,0),"") | AG28: =IF(COUNTA($A28:$D28)>0,IFERROR($D28/12,0),"") | AH28: =IF(COUNTA($A28:$D28)>0,IFERROR($D28/12,0),"") | AI28: =IF(COUNTA($A28:$D28)>0,IFERROR($D28/12,0),"") | AJ28: =IF(COUNTA($A28:$D28)>0,IFERROR($D28/12,0),"") | AK28: =IF(COUNTA($A28:$D28)>0,IFERROR($D28/12,0),"") | AL28: =IF(COUNTA($A28:$D28)>0,IFERROR($D28/12,0),"") | ... AP28: =IF(COUNTA($A28:$D28)>0,IFERROR($D28/12,0),"") | AQ28: =SUM(tblNonPayrollIncrementalSpend3[[#This Row],[Jan-27]:[Dec-27]]) -> 0
E29: =IF(COUNTA($A29:$D29)>0,IFERROR($D29/12,0),"") | F29: =IF(COUNTA($A29:$D29)>0,IFERROR($D29/12,0),"") | G29: =IF(COUNTA($A29:$D29)>0,IFERROR($D29/12,0),"") | H29: =IF(COUNTA($A29:$D29)>0,IFERROR($D29/12,0),"") | I29: =IF(COUNTA($A29:$D29)>0,IFERROR($D29/12,0),"") | J29: =IF(COUNTA($A29:$D29)>0,IFERROR($D29/12,0),"") | K29: =IF(COUNTA($A29:$D29)>0,IFERROR($D29/12,0),"") | L29: =IF(COUNTA($A29:$D29)>0,IFERROR($D29/12,0),"") | ... P29: =IF(COUNTA($A29:$D29)>0,IFERROR($D29/12,0),"") | Q29: =SUM(tblNonPayrollIncrementalSpend3[[#This Row],[Jan-27]:[Dec-27]]) -> 0 | R29: =IF(COUNTA($A29:$D29)>0,IFERROR($D29/12,0),"") | S29: =IF(COUNTA($A29:$D29)>0,IFERROR($D29/12,0),"") | T29: =IF(COUNTA($A29:$D29)>0,IFERROR($D29/12,0),"") | U29: =IF(COUNTA($A29:$D29)>0,IFERROR($D29/12,0),"") | V29: =IF(COUNTA($A29:$D29)>0,IFERROR($D29/12,0),"") | W29: =IF(COUNTA($A29:$D29)>0,IFERROR($D29/12,0),"") | X29: =IF(COUNTA($A29:$D29)>0,IFERROR($D29/12,0),"") | Y29: =IF(COUNTA($A29:$D29)>0,IFERROR($D29/12,0),"") | ... AC29: =IF(COUNTA($A29:$D29)>0,IFERROR($D29/12,0),"") | AD29: =SUM(tblNonPayrollIncrementalSpend3[[#This Row],[Jan-27]:[Dec-27]]) -> 0 | AE29: =IF(COUNTA($A29:$D29)>0,IFERROR($D29/12,0),"") | AF29: =IF(COUNTA($A29:$D29)>0,IFERROR($D29/12,0),"") | AG29: =IF(COUNTA($A29:$D29)>0,IFERROR($D29/12,0),"") | AH29: =IF(COUNTA($A29:$D29)>0,IFERROR($D29/12,0),"") | AI29: =IF(COUNTA($A29:$D29)>0,IFERROR($D29/12,0),"") | AJ29: =IF(COUNTA($A29:$D29)>0,IFERROR($D29/12,0),"") | AK29: =IF(COUNTA($A29:$D29)>0,IFERROR($D29/12,0),"") | AL29: =IF(COUNTA($A29:$D29)>0,IFERROR($D29/12,0),"") | ... AP29: =IF(COUNTA($A29:$D29)>0,IFERROR($D29/12,0),"") | AQ29: =SUM(tblNonPayrollIncrementalSpend3[[#This Row],[Jan-27]:[Dec-27]]) -> 0
E30: =IF(COUNTA($A30:$D30)>0,IFERROR($D30/12,0),"") | F30: =IF(COUNTA($A30:$D30)>0,IFERROR($D30/12,0),"") | G30: =IF(COUNTA($A30:$D30)>0,IFERROR($D30/12,0),"") | H30: =IF(COUNTA($A30:$D30)>0,IFERROR($D30/12,0),"") | I30: =IF(COUNTA($A30:$D30)>0,IFERROR($D30/12,0),"") | J30: =IF(COUNTA($A30:$D30)>0,IFERROR($D30/12,0),"") | K30: =IF(COUNTA($A30:$D30)>0,IFERROR($D30/12,0),"") | L30: =IF(COUNTA($A30:$D30)>0,IFERROR($D30/12,0),"") | ... P30: =IF(COUNTA($A30:$D30)>0,IFERROR($D30/12,0),"") | Q30: =SUM(tblNonPayrollIncrementalSpend3[[#This Row],[Jan-27]:[Dec-27]]) -> 0 | R30: =IF(COUNTA($A30:$D30)>0,IFERROR($D30/12,0),"") | S30: =IF(COUNTA($A30:$D30)>0,IFERROR($D30/12,0),"") | T30: =IF(COUNTA($A30:$D30)>0,IFERROR($D30/12,0),"") | U30: =IF(COUNTA($A30:$D30)>0,IFERROR($D30/12,0),"") | V30: =IF(COUNTA($A30:$D30)>0,IFERROR($D30/12,0),"") | W30: =IF(COUNTA($A30:$D30)>0,IFERROR($D30/12,0),"") | X30: =IF(COUNTA($A30:$D30)>0,IFERROR($D30/12,0),"") | Y30: =IF(COUNTA($A30:$D30)>0,IFERROR($D30/12,0),"") | ... AC30: =IF(COUNTA($A30:$D30)>0,IFERROR($D30/12,0),"") | AD30: =SUM(tblNonPayrollIncrementalSpend3[[#This Row],[Jan-27]:[Dec-27]]) -> 0 | AE30: =IF(COUNTA($A30:$D30)>0,IFERROR($D30/12,0),"") | AF30: =IF(COUNTA($A30:$D30)>0,IFERROR($D30/12,0),"") | AG30: =IF(COUNTA($A30:$D30)>0,IFERROR($D30/12,0),"") | AH30: =IF(COUNTA($A30:$D30)>0,IFERROR($D30/12,0),"") | AI30: =IF(COUNTA($A30:$D30)>0,IFERROR($D30/12,0),"") | AJ30: =IF(COUNTA($A30:$D30)>0,IFERROR($D30/12,0),"") | AK30: =IF(COUNTA($A30:$D30)>0,IFERROR($D30/12,0),"") | AL30: =IF(COUNTA($A30:$D30)>0,IFERROR($D30/12,0),"") | ... AP30: =IF(COUNTA($A30:$D30)>0,IFERROR($D30/12,0),"") | AQ30: =SUM(tblNonPayrollIncrementalSpend3[[#This Row],[Jan-27]:[Dec-27]]) -> 0
E31: =IF(COUNTA($A31:$D31)>0,IFERROR($D31/12,0),"") | F31: =IF(COUNTA($A31:$D31)>0,IFERROR($D31/12,0),"") | G31: =IF(COUNTA($A31:$D31)>0,IFERROR($D31/12,0),"") | H31: =IF(COUNTA($A31:$D31)>0,IFERROR($D31/12,0),"") | I31: =IF(COUNTA($A31:$D31)>0,IFERROR($D31/12,0),"") | J31: =IF(COUNTA($A31:$D31)>0,IFERROR($D31/12,0),"") | K31: =IF(COUNTA($A31:$D31)>0,IFERROR($D31/12,0),"") | L31: =IF(COUNTA($A31:$D31)>0,IFERROR($D31/12,0),"") | ... P31: =IF(COUNTA($A31:$D31)>0,IFERROR($D31/12,0),"") | Q31: =SUM(tblNonPayrollIncrementalSpend3[[#This Row],[Jan-27]:[Dec-27]]) -> 0 | R31: =IF(COUNTA($A31:$D31)>0,IFERROR($D31/12,0),"") | S31: =IF(COUNTA($A31:$D31)>0,IFERROR($D31/12,0),"") | T31: =IF(COUNTA($A31:$D31)>0,IFERROR($D31/12,0),"") | U31: =IF(COUNTA($A31:$D31)>0,IFERROR($D31/12,0),"") | V31: =IF(COUNTA($A31:$D31)>0,IFERROR($D31/12,0),"") | W31: =IF(COUNTA($A31:$D31)>0,IFERROR($D31/12,0),"") | X31: =IF(COUNTA($A31:$D31)>0,IFERROR($D31/12,0),"") | Y31: =IF(COUNTA($A31:$D31)>0,IFERROR($D31/12,0),"") | ... AC31: =IF(COUNTA($A31:$D31)>0,IFERROR($D31/12,0),"") | AD31: =SUM(tblNonPayrollIncrementalSpend3[[#This Row],[Jan-27]:[Dec-27]]) -> 0 | AE31: =IF(COUNTA($A31:$D31)>0,IFERROR($D31/12,0),"") | AF31: =IF(COUNTA($A31:$D31)>0,IFERROR($D31/12,0),"") | AG31: =IF(COUNTA($A31:$D31)>0,IFERROR($D31/12,0),"") | AH31: =IF(COUNTA($A31:$D31)>0,IFERROR($D31/12,0),"") | AI31: =IF(COUNTA($A31:$D31)>0,IFERROR($D31/12,0),"") | AJ31: =IF(COUNTA($A31:$D31)>0,IFERROR($D31/12,0),"") | AK31: =IF(COUNTA($A31:$D31)>0,IFERROR($D31/12,0),"") | AL31: =IF(COUNTA($A31:$D31)>0,IFERROR($D31/12,0),"") | ... AP31: =IF(COUNTA($A31:$D31)>0,IFERROR($D31/12,0),"") | AQ31: =SUM(tblNonPayrollIncrementalSpend3[[#This Row],[Jan-27]:[Dec-27]]) -> 0
E32: =IF(COUNTA($A32:$D32)>0,IFERROR($D32/12,0),"") | F32: =IF(COUNTA($A32:$D32)>0,IFERROR($D32/12,0),"") | G32: =IF(COUNTA($A32:$D32)>0,IFERROR($D32/12,0),"") | H32: =IF(COUNTA($A32:$D32)>0,IFERROR($D32/12,0),"") | I32: =IF(COUNTA($A32:$D32)>0,IFERROR($D32/12,0),"") | J32: =IF(COUNTA($A32:$D32)>0,IFERROR($D32/12,0),"") | K32: =IF(COUNTA($A32:$D32)>0,IFERROR($D32/12,0),"") | L32: =IF(COUNTA($A32:$D32)>0,IFERROR($D32/12,0),"") | ... P32: =IF(COUNTA($A32:$D32)>0,IFERROR($D32/12,0),"") | Q32: =SUM(tblNonPayrollIncrementalSpend3[[#This Row],[Jan-27]:[Dec-27]]) -> 0 | R32: =IF(COUNTA($A32:$D32)>0,IFERROR($D32/12,0),"") | S32: =IF(COUNTA($A32:$D32)>0,IFERROR($D32/12,0),"") | T32: =IF(COUNTA($A32:$D32)>0,IFERROR($D32/12,0),"") | U32: =IF(COUNTA($A32:$D32)>0,IFERROR($D32/12,0),"") | V32: =IF(COUNTA($A32:$D32)>0,IFERROR($D32/12,0),"") | W32: =IF(COUNTA($A32:$D32)>0,IFERROR($D32/12,0),"") | X32: =IF(COUNTA($A32:$D32)>0,IFERROR($D32/12,0),"") | Y32: =IF(COUNTA($A32:$D32)>0,IFERROR($D32/12,0),"") | ... AC32: =IF(COUNTA($A32:$D32)>0,IFERROR($D32/12,0),"") | AD32: =SUM(tblNonPayrollIncrementalSpend3[[#This Row],[Jan-27]:[Dec-27]]) -> 0 | AE32: =IF(COUNTA($A32:$D32)>0,IFERROR($D32/12,0),"") | AF32: =IF(COUNTA($A32:$D32)>0,IFERROR($D32/12,0),"") | AG32: =IF(COUNTA($A32:$D32)>0,IFERROR($D32/12,0),"") | AH32: =IF(COUNTA($A32:$D32)>0,IFERROR($D32/12,0),"") | AI32: =IF(COUNTA($A32:$D32)>0,IFERROR($D32/12,0),"") | AJ32: =IF(COUNTA($A32:$D32)>0,IFERROR($D32/12,0),"") | AK32: =IF(COUNTA($A32:$D32)>0,IFERROR($D32/12,0),"") | AL32: =IF(COUNTA($A32:$D32)>0,IFERROR($D32/12,0),"") | ... AP32: =IF(COUNTA($A32:$D32)>0,IFERROR($D32/12,0),"") | AQ32: =SUM(tblNonPayrollIncrementalSpend3[[#This Row],[Jan-27]:[Dec-27]]) -> 0
E33: =IF(COUNTA($A33:$D33)>0,IFERROR($D33/12,0),"") | F33: =IF(COUNTA($A33:$D33)>0,IFERROR($D33/12,0),"") | G33: =IF(COUNTA($A33:$D33)>0,IFERROR($D33/12,0),"") | H33: =IF(COUNTA($A33:$D33)>0,IFERROR($D33/12,0),"") | I33: =IF(COUNTA($A33:$D33)>0,IFERROR($D33/12,0),"") | J33: =IF(COUNTA($A33:$D33)>0,IFERROR($D33/12,0),"") | K33: =IF(COUNTA($A33:$D33)>0,IFERROR($D33/12,0),"") | L33: =IF(COUNTA($A33:$D33)>0,IFERROR($D33/12,0),"") | ... P33: =IF(COUNTA($A33:$D33)>0,IFERROR($D33/12,0),"") | Q33: =SUM(tblNonPayrollIncrementalSpend3[[#This Row],[Jan-27]:[Dec-27]]) -> 0 | R33: =IF(COUNTA($A33:$D33)>0,IFERROR($D33/12,0),"") | S33: =IF(COUNTA($A33:$D33)>0,IFERROR($D33/12,0),"") | T33: =IF(COUNTA($A33:$D33)>0,IFERROR($D33/12,0),"") | U33: =IF(COUNTA($A33:$D33)>0,IFERROR($D33/12,0),"") | V33: =IF(COUNTA($A33:$D33)>0,IFERROR($D33/12,0),"") | W33: =IF(COUNTA($A33:$D33)>0,IFERROR($D33/12,0),"") | X33: =IF(COUNTA($A33:$D33)>0,IFERROR($D33/12,0),"") | Y33: =IF(COUNTA($A33:$D33)>0,IFERROR($D33/12,0),"") | ... AC33: =IF(COUNTA($A33:$D33)>0,IFERROR($D33/12,0),"") | AD33: =SUM(tblNonPayrollIncrementalSpend3[[#This Row],[Jan-27]:[Dec-27]]) -> 0 | AE33: =IF(COUNTA($A33:$D33)>0,IFERROR($D33/12,0),"") | AF33: =IF(COUNTA($A33:$D33)>0,IFERROR($D33/12,0),"") | AG33: =IF(COUNTA($A33:$D33)>0,IFERROR($D33/12,0),"") | AH33: =IF(COUNTA($A33:$D33)>0,IFERROR($D33/12,0),"") | AI33: =IF(COUNTA($A33:$D33)>0,IFERROR($D33/12,0),"") | AJ33: =IF(COUNTA($A33:$D33)>0,IFERROR($D33/12,0),"") | AK33: =IF(COUNTA($A33:$D33)>0,IFERROR($D33/12,0),"") | AL33: =IF(COUNTA($A33:$D33)>0,IFERROR($D33/12,0),"") | ... AP33: =IF(COUNTA($A33:$D33)>0,IFERROR($D33/12,0),"") | AQ33: =SUM(tblNonPayrollIncrementalSpend3[[#This Row],[Jan-27]:[Dec-27]]) -> 0
E34: =IF(COUNTA($A34:$D34)>0,IFERROR($D34/12,0),"") | F34: =IF(COUNTA($A34:$D34)>0,IFERROR($D34/12,0),"") | G34: =IF(COUNTA($A34:$D34)>0,IFERROR($D34/12,0),"") | H34: =IF(COUNTA($A34:$D34)>0,IFERROR($D34/12,0),"") | I34: =IF(COUNTA($A34:$D34)>0,IFERROR($D34/12,0),"") | J34: =IF(COUNTA($A34:$D34)>0,IFERROR($D34/12,0),"") | K34: =IF(COUNTA($A34:$D34)>0,IFERROR($D34/12,0),"") | L34: =IF(COUNTA($A34:$D34)>0,IFERROR($D34/12,0),"") | ... P34: =IF(COUNTA($A34:$D34)>0,IFERROR($D34/12,0),"") | Q34: =SUM(tblNonPayrollIncrementalSpend3[[#This Row],[Jan-27]:[Dec-27]]) -> 0 | R34: =IF(COUNTA($A34:$D34)>0,IFERROR($D34/12,0),"") | S34: =IF(COUNTA($A34:$D34)>0,IFERROR($D34/12,0),"") | T34: =IF(COUNTA($A34:$D34)>0,IFERROR($D34/12,0),"") | U34: =IF(COUNTA($A34:$D34)>0,IFERROR($D34/12,0),"") | V34: =IF(COUNTA($A34:$D34)>0,IFERROR($D34/12,0),"") | W34: =IF(COUNTA($A34:$D34)>0,IFERROR($D34/12,0),"") | X34: =IF(COUNTA($A34:$D34)>0,IFERROR($D34/12,0),"") | Y34: =IF(COUNTA($A34:$D34)>0,IFERROR($D34/12,0),"") | ... AC34: =IF(COUNTA($A34:$D34)>0,IFERROR($D34/12,0),"") | AD34: =SUM(tblNonPayrollIncrementalSpend3[[#This Row],[Jan-27]:[Dec-27]]) -> 0 | AE34: =IF(COUNTA($A34:$D34)>0,IFERROR($D34/12,0),"") | AF34: =IF(COUNTA($A34:$D34)>0,IFERROR($D34/12,0),"") | AG34: =IF(COUNTA($A34:$D34)>0,IFERROR($D34/12,0),"") | AH34: =IF(COUNTA($A34:$D34)>0,IFERROR($D34/12,0),"") | AI34: =IF(COUNTA($A34:$D34)>0,IFERROR($D34/12,0),"") | AJ34: =IF(COUNTA($A34:$D34)>0,IFERROR($D34/12,0),"") | AK34: =IF(COUNTA($A34:$D34)>0,IFERROR($D34/12,0),"") | AL34: =IF(COUNTA($A34:$D34)>0,IFERROR($D34/12,0),"") | ... AP34: =IF(COUNTA($A34:$D34)>0,IFERROR($D34/12,0),"") | AQ34: =SUM(tblNonPayrollIncrementalSpend3[[#This Row],[Jan-27]:[Dec-27]]) -> 0
E35: =IF(COUNTA($A35:$D35)>0,IFERROR($D35/12,0),"") | F35: =IF(COUNTA($A35:$D35)>0,IFERROR($D35/12,0),"") | G35: =IF(COUNTA($A35:$D35)>0,IFERROR($D35/12,0),"") | H35: =IF(COUNTA($A35:$D35)>0,IFERROR($D35/12,0),"") | I35: =IF(COUNTA($A35:$D35)>0,IFERROR($D35/12,0),"") | J35: =IF(COUNTA($A35:$D35)>0,IFERROR($D35/12,0),"") | K35: =IF(COUNTA($A35:$D35)>0,IFERROR($D35/12,0),"") | L35: =IF(COUNTA($A35:$D35)>0,IFERROR($D35/12,0),"") | ... P35: =IF(COUNTA($A35:$D35)>0,IFERROR($D35/12,0),"") | Q35: =SUM(tblNonPayrollIncrementalSpend3[[#This Row],[Jan-27]:[Dec-27]]) -> 0 | R35: =IF(COUNTA($A35:$D35)>0,IFERROR($D35/12,0),"") | S35: =IF(COUNTA($A35:$D35)>0,IFERROR($D35/12,0),"") | T35: =IF(COUNTA($A35:$D35)>0,IFERROR($D35/12,0),"") | U35: =IF(COUNTA($A35:$D35)>0,IFERROR($D35/12,0),"") | V35: =IF(COUNTA($A35:$D35)>0,IFERROR($D35/12,0),"") | W35: =IF(COUNTA($A35:$D35)>0,IFERROR($D35/12,0),"") | X35: =IF(COUNTA($A35:$D35)>0,IFERROR($D35/12,0),"") | Y35: =IF(COUNTA($A35:$D35)>0,IFERROR($D35/12,0),"") | ... AC35: =IF(COUNTA($A35:$D35)>0,IFERROR($D35/12,0),"") | AD35: =SUM(tblNonPayrollIncrementalSpend3[[#This Row],[Jan-27]:[Dec-27]]) -> 0 | AE35: =IF(COUNTA($A35:$D35)>0,IFERROR($D35/12,0),"") | AF35: =IF(COUNTA($A35:$D35)>0,IFERROR($D35/12,0),"") | AG35: =IF(COUNTA($A35:$D35)>0,IFERROR($D35/12,0),"") | AH35: =IF(COUNTA($A35:$D35)>0,IFERROR($D35/12,0),"") | AI35: =IF(COUNTA($A35:$D35)>0,IFERROR($D35/12,0),"") | AJ35: =IF(COUNTA($A35:$D35)>0,IFERROR($D35/12,0),"") | AK35: =IF(COUNTA($A35:$D35)>0,IFERROR($D35/12,0),"") | AL35: =IF(COUNTA($A35:$D35)>0,IFERROR($D35/12,0),"") | ... AP35: =IF(COUNTA($A35:$D35)>0,IFERROR($D35/12,0),"") | AQ35: =SUM(tblNonPayrollIncrementalSpend3[[#This Row],[Jan-27]:[Dec-27]]) -> 0
E36: =IF(COUNTA($A36:$D36)>0,IFERROR($D36/12,0),"") | F36: =IF(COUNTA($A36:$D36)>0,IFERROR($D36/12,0),"") | G36: =IF(COUNTA($A36:$D36)>0,IFERROR($D36/12,0),"") | H36: =IF(COUNTA($A36:$D36)>0,IFERROR($D36/12,0),"") | I36: =IF(COUNTA($A36:$D36)>0,IFERROR($D36/12,0),"") | J36: =IF(COUNTA($A36:$D36)>0,IFERROR($D36/12,0),"") | K36: =IF(COUNTA($A36:$D36)>0,IFERROR($D36/12,0),"") | L36: =IF(COUNTA($A36:$D36)>0,IFERROR($D36/12,0),"") | ... P36: =IF(COUNTA($A36:$D36)>0,IFERROR($D36/12,0),"") | Q36: =SUM(tblNonPayrollIncrementalSpend3[[#This Row],[Jan-27]:[Dec-27]]) -> 0 | R36: =IF(COUNTA($A36:$D36)>0,IFERROR($D36/12,0),"") | S36: =IF(COUNTA($A36:$D36)>0,IFERROR($D36/12,0),"") | T36: =IF(COUNTA($A36:$D36)>0,IFERROR($D36/12,0),"") | U36: =IF(COUNTA($A36:$D36)>0,IFERROR($D36/12,0),"") | V36: =IF(COUNTA($A36:$D36)>0,IFERROR($D36/12,0),"") | W36: =IF(COUNTA($A36:$D36)>0,IFERROR($D36/12,0),"") | X36: =IF(COUNTA($A36:$D36)>0,IFERROR($D36/12,0),"") | Y36: =IF(COUNTA($A36:$D36)>0,IFERROR($D36/12,0),"") | ... AC36: =IF(COUNTA($A36:$D36)>0,IFERROR($D36/12,0),"") | AD36: =SUM(tblNonPayrollIncrementalSpend3[[#This Row],[Jan-27]:[Dec-27]]) -> 0 | AE36: =IF(COUNTA($A36:$D36)>0,IFERROR($D36/12,0),"") | AF36: =IF(COUNTA($A36:$D36)>0,IFERROR($D36/12,0),"") | AG36: =IF(COUNTA($A36:$D36)>0,IFERROR($D36/12,0),"") | AH36: =IF(COUNTA($A36:$D36)>0,IFERROR($D36/12,0),"") | AI36: =IF(COUNTA($A36:$D36)>0,IFERROR($D36/12,0),"") | AJ36: =IF(COUNTA($A36:$D36)>0,IFERROR($D36/12,0),"") | AK36: =IF(COUNTA($A36:$D36)>0,IFERROR($D36/12,0),"") | AL36: =IF(COUNTA($A36:$D36)>0,IFERROR($D36/12,0),"") | ... AP36: =IF(COUNTA($A36:$D36)>0,IFERROR($D36/12,0),"") | AQ36: =SUM(tblNonPayrollIncrementalSpend3[[#This Row],[Jan-27]:[Dec-27]]) -> 0
E37: =IF(COUNTA($A37:$D37)>0,IFERROR($D37/12,0),"") | F37: =IF(COUNTA($A37:$D37)>0,IFERROR($D37/12,0),"") | G37: =IF(COUNTA($A37:$D37)>0,IFERROR($D37/12,0),"") | H37: =IF(COUNTA($A37:$D37)>0,IFERROR($D37/12,0),"") | I37: =IF(COUNTA($A37:$D37)>0,IFERROR($D37/12,0),"") | J37: =IF(COUNTA($A37:$D37)>0,IFERROR($D37/12,0),"") | K37: =IF(COUNTA($A37:$D37)>0,IFERROR($D37/12,0),"") | L37: =IF(COUNTA($A37:$D37)>0,IFERROR($D37/12,0),"") | ... P37: =IF(COUNTA($A37:$D37)>0,IFERROR($D37/12,0),"") | Q37: =SUM(tblNonPayrollIncrementalSpend3[[#This Row],[Jan-27]:[Dec-27]]) -> 0 | R37: =IF(COUNTA($A37:$D37)>0,IFERROR($D37/12,0),"") | S37: =IF(COUNTA($A37:$D37)>0,IFERROR($D37/12,0),"") | T37: =IF(COUNTA($A37:$D37)>0,IFERROR($D37/12,0),"") | U37: =IF(COUNTA($A37:$D37)>0,IFERROR($D37/12,0),"") | V37: =IF(COUNTA($A37:$D37)>0,IFERROR($D37/12,0),"") | W37: =IF(COUNTA($A37:$D37)>0,IFERROR($D37/12,0),"") | X37: =IF(COUNTA($A37:$D37)>0,IFERROR($D37/12,0),"") | Y37: =IF(COUNTA($A37:$D37)>0,IFERROR($D37/12,0),"") | ... AC37: =IF(COUNTA($A37:$D37)>0,IFERROR($D37/12,0),"") | AD37: =SUM(tblNonPayrollIncrementalSpend3[[#This Row],[Jan-27]:[Dec-27]]) -> 0 | AE37: =IF(COUNTA($A37:$D37)>0,IFERROR($D37/12,0),"") | AF37: =IF(COUNTA($A37:$D37)>0,IFERROR($D37/12,0),"") | AG37: =IF(COUNTA($A37:$D37)>0,IFERROR($D37/12,0),"") | AH37: =IF(COUNTA($A37:$D37)>0,IFERROR($D37/12,0),"") | AI37: =IF(COUNTA($A37:$D37)>0,IFERROR($D37/12,0),"") | AJ37: =IF(COUNTA($A37:$D37)>0,IFERROR($D37/12,0),"") | AK37: =IF(COUNTA($A37:$D37)>0,IFERROR($D37/12,0),"") | AL37: =IF(COUNTA($A37:$D37)>0,IFERROR($D37/12,0),"") | ... AP37: =IF(COUNTA($A37:$D37)>0,IFERROR($D37/12,0),"") | AQ37: =SUM(tblNonPayrollIncrementalSpend3[[#This Row],[Jan-27]:[Dec-27]]) -> 0
E38: =IF(COUNTA($A38:$D38)>0,IFERROR($D38/12,0),"") | F38: =IF(COUNTA($A38:$D38)>0,IFERROR($D38/12,0),"") | G38: =IF(COUNTA($A38:$D38)>0,IFERROR($D38/12,0),"") | H38: =IF(COUNTA($A38:$D38)>0,IFERROR($D38/12,0),"") | I38: =IF(COUNTA($A38:$D38)>0,IFERROR($D38/12,0),"") | J38: =IF(COUNTA($A38:$D38)>0,IFERROR($D38/12,0),"") | K38: =IF(COUNTA($A38:$D38)>0,IFERROR($D38/12,0),"") | L38: =IF(COUNTA($A38:$D38)>0,IFERROR($D38/12,0),"") | ... P38: =IF(COUNTA($A38:$D38)>0,IFERROR($D38/12,0),"") | Q38: =SUM(tblNonPayrollIncrementalSpend3[[#This Row],[Jan-27]:[Dec-27]]) -> 0 | R38: =IF(COUNTA($A38:$D38)>0,IFERROR($D38/12,0),"") | S38: =IF(COUNTA($A38:$D38)>0,IFERROR($D38/12,0),"") | T38: =IF(COUNTA($A38:$D38)>0,IFERROR($D38/12,0),"") | U38: =IF(COUNTA($A38:$D38)>0,IFERROR($D38/12,0),"") | V38: =IF(COUNTA($A38:$D38)>0,IFERROR($D38/12,0),"") | W38: =IF(COUNTA($A38:$D38)>0,IFERROR($D38/12,0),"") | X38: =IF(COUNTA($A38:$D38)>0,IFERROR($D38/12,0),"") | Y38: =IF(COUNTA($A38:$D38)>0,IFERROR($D38/12,0),"") | ... AC38: =IF(COUNTA($A38:$D38)>0,IFERROR($D38/12,0),"") | AD38: =SUM(tblNonPayrollIncrementalSpend3[[#This Row],[Jan-27]:[Dec-27]]) -> 0 | AE38: =IF(COUNTA($A38:$D38)>0,IFERROR($D38/12,0),"") | AF38: =IF(COUNTA($A38:$D38)>0,IFERROR($D38/12,0),"") | AG38: =IF(COUNTA($A38:$D38)>0,IFERROR($D38/12,0),"") | AH38: =IF(COUNTA($A38:$D38)>0,IFERROR($D38/12,0),"") | AI38: =IF(COUNTA($A38:$D38)>0,IFERROR($D38/12,0),"") | AJ38: =IF(COUNTA($A38:$D38)>0,IFERROR($D38/12,0),"") | AK38: =IF(COUNTA($A38:$D38)>0,IFERROR($D38/12,0),"") | AL38: =IF(COUNTA($A38:$D38)>0,IFERROR($D38/12,0),"") | ... AP38: =IF(COUNTA($A38:$D38)>0,IFERROR($D38/12,0),"") | AQ38: =SUM(tblNonPayrollIncrementalSpend3[[#This Row],[Jan-27]:[Dec-27]]) -> 0
E39: =IF(COUNTA($A39:$D39)>0,IFERROR($D39/12,0),"") | F39: =IF(COUNTA($A39:$D39)>0,IFERROR($D39/12,0),"") | G39: =IF(COUNTA($A39:$D39)>0,IFERROR($D39/12,0),"") | H39: =IF(COUNTA($A39:$D39)>0,IFERROR($D39/12,0),"") | I39: =IF(COUNTA($A39:$D39)>0,IFERROR($D39/12,0),"") | J39: =IF(COUNTA($A39:$D39)>0,IFERROR($D39/12,0),"") | K39: =IF(COUNTA($A39:$D39)>0,IFERROR($D39/12,0),"") | L39: =IF(COUNTA($A39:$D39)>0,IFERROR($D39/12,0),"") | ... P39: =IF(COUNTA($A39:$D39)>0,IFERROR($D39/12,0),"") | Q39: =SUM(tblNonPayrollIncrementalSpend3[[#This Row],[Jan-27]:[Dec-27]]) -> 0 | R39: =IF(COUNTA($A39:$D39)>0,IFERROR($D39/12,0),"") | S39: =IF(COUNTA($A39:$D39)>0,IFERROR($D39/12,0),"") | T39: =IF(COUNTA($A39:$D39)>0,IFERROR($D39/12,0),"") | U39: =IF(COUNTA($A39:$D39)>0,IFERROR($D39/12,0),"") | V39: =IF(COUNTA($A39:$D39)>0,IFERROR($D39/12,0),"") | W39: =IF(COUNTA($A39:$D39)>0,IFERROR($D39/12,0),"") | X39: =IF(COUNTA($A39:$D39)>0,IFERROR($D39/12,0),"") | Y39: =IF(COUNTA($A39:$D39)>0,IFERROR($D39/12,0),"") | ... AC39: =IF(COUNTA($A39:$D39)>0,IFERROR($D39/12,0),"") | AD39: =SUM(tblNonPayrollIncrementalSpend3[[#This Row],[Jan-27]:[Dec-27]]) -> 0 | AE39: =IF(COUNTA($A39:$D39)>0,IFERROR($D39/12,0),"") | AF39: =IF(COUNTA($A39:$D39)>0,IFERROR($D39/12,0),"") | AG39: =IF(COUNTA($A39:$D39)>0,IFERROR($D39/12,0),"") | AH39: =IF(COUNTA($A39:$D39)>0,IFERROR($D39/12,0),"") | AI39: =IF(COUNTA($A39:$D39)>0,IFERROR($D39/12,0),"") | AJ39: =IF(COUNTA($A39:$D39)>0,IFERROR($D39/12,0),"") | AK39: =IF(COUNTA($A39:$D39)>0,IFERROR($D39/12,0),"") | AL39: =IF(COUNTA($A39:$D39)>0,IFERROR($D39/12,0),"") | ... AP39: =IF(COUNTA($A39:$D39)>0,IFERROR($D39/12,0),"") | AQ39: =SUM(tblNonPayrollIncrementalSpend3[[#This Row],[Jan-27]:[Dec-27]]) -> 0
... E42: =IF(COUNTA($A42:$D42)>0,IFERROR($D42/12,0),"") | F42: =IF(COUNTA($A42:$D42)>0,IFERROR($D42/12,0),"") | G42: =IF(COUNTA($A42:$D42)>0,IFERROR($D42/12,0),"") | H42: =IF(COUNTA($A42:$D42)>0,IFERROR($D42/12,0),"") | I42: =IF(COUNTA($A42:$D42)>0,IFERROR($D42/12,0),"") | J42: =IF(COUNTA($A42:$D42)>0,IFERROR($D42/12,0),"") | K42: =IF(COUNTA($A42:$D42)>0,IFERROR($D42/12,0),"") | L42: =IF(COUNTA($A42:$D42)>0,IFERROR($D42/12,0),"") | ... P42: =IF(COUNTA($A42:$D42)>0,IFERROR($D42/12,0),"") | Q42: =SUM(tblNonPayrollIncrementalSpend3[[#This Row],[Jan-27]:[Dec-27]]) -> 0 | R42: =IF(COUNTA($A42:$D42)>0,IFERROR($D42/12,0),"") | S42: =IF(COUNTA($A42:$D42)>0,IFERROR($D42/12,0),"") | T42: =IF(COUNTA($A42:$D42)>0,IFERROR($D42/12,0),"") | U42: =IF(COUNTA($A42:$D42)>0,IFERROR($D42/12,0),"") | V42: =IF(COUNTA($A42:$D42)>0,IFERROR($D42/12,0),"") | W42: =IF(COUNTA($A42:$D42)>0,IFERROR($D42/12,0),"") | X42: =IF(COUNTA($A42:$D42)>0,IFERROR($D42/12,0),"") | Y42: =IF(COUNTA($A42:$D42)>0,IFERROR($D42/12,0),"") | ... AC42: =IF(COUNTA($A42:$D42)>0,IFERROR($D42/12,0),"") | AD42: =SUM(tblNonPayrollIncrementalSpend3[[#This Row],[Jan-27]:[Dec-27]]) -> 0 | AE42: =IF(COUNTA($A42:$D42)>0,IFERROR($D42/12,0),"") | AF42: =IF(COUNTA($A42:$D42)>0,IFERROR($D42/12,0),"") | AG42: =IF(COUNTA($A42:$D42)>0,IFERROR($D42/12,0),"") | AH42: =IF(COUNTA($A42:$D42)>0,IFERROR($D42/12,0),"") | AI42: =IF(COUNTA($A42:$D42)>0,IFERROR($D42/12,0),"") | AJ42: =IF(COUNTA($A42:$D42)>0,IFERROR($D42/12,0),"") | AK42: =IF(COUNTA($A42:$D42)>0,IFERROR($D42/12,0),"") | AL42: =IF(COUNTA($A42:$D42)>0,IFERROR($D42/12,0),"") | ... AP42: =IF(COUNTA($A42:$D42)>0,IFERROR($D42/12,0),"") | AQ42: =SUM(tblNonPayrollIncrementalSpend3[[#This Row],[Jan-27]:[Dec-27]]) -> 0
A44: Total Essentials Bonus / Contract Labor / Non-Payroll Incremental Spend | D44: =SUM(D28:D42) -> 0 | E44: =SUM(E28:E42) -> 0 | F44: =SUM(F28:F42) -> 0 | G44: =SUM(G28:G42) -> 0 | H44: =SUM(H28:H42) -> 0 | I44: =SUM(I28:I42) -> 0 | J44: =SUM(J28:J42) -> 0 | K44: =SUM(K28:K42) -> 0 | ... AQ44: =SUM(AQ28:AQ42) -> 0

Sheet Questions to Ask
A1: Questions to Ask - Investment Case
A3: # | B3: Question | C3: Guidance / What to Address
A4: 1 | B4: What strategic objective or growth opportunity does this investment enable? | C4: • What business objective, strategic initiative, or growth opportunity does this investment support? • How does the investment align with priorities and outcomes in the 2027–2029 business plan?
A5: 2 | B5: What business milestone should trigger this investment? | C5: • Describe why the investment is needed now, or identify the business milestone that would warrant the investment in the future. • Explain how the timing of the investment aligns with the expected growth of the business.
A6: 3 | B6: What alternatives were considered? | C6: • What alternatives were evaluated before requesting incremental spend, including process improvements, AI/automation, technology solutions, third-party providers, or redeployment of existing resources? • Why is incremental headcount or G&A the most effective solution?
A7: 4 | B7: What measurable business outcome will this investment deliver? | C7: • What are the expected business outcomes and how will success be measured? • Tie the request to measurable growth or scale, e.g., revenue, AUM, MW deployed, customers served, operating sites, projects delivered, cost savings, or risk reduction.
A8: 5 | B8: What is the impact if this investment is not approved? | C8: • What is the expected business impact if the investment is deferred or not approved? • What are the implications for growth, execution of strategic initiatives, customer commitments, operational performance, financial results, or risk management?

Sheet Baseline Support -->

Sheet Base - Payroll
B1: CC_CL | C1: Account | D1: Actual | E1: 04/2026 - Q126 Earnings FCST | F1: Growth Rate | G1: Model | H1: Model | I1: Model
D2: 2025 | E2: 2026 | F2: 2026 vs. 2025 | G2: 2027 | H2: 2028 | I2: 2029
A3: Compensation | B3: Data Centers | C3: COMP - Compensation | D3: 4558551.3 | E3: 12484861 | F3: =E3/D3-1 -> 1.7387782 | G3: 15345429 | H3: =G3 -> 15345429 | I3: =H3 -> 15345429 | J3: From Current FCST excluding Merit
A4: Payroll Taxes | B4: Data Centers | C4: PAYROLL_TAX - Payroll tax | D4: 501527.88 | E4: 1451993.8 | F4: =E4/D4-1 -> 1.8951407 | G4: =$G$3*E12 -> 1784678.8 | H4: =$H$3*E12 -> 1784678.8 | I4: =$I$3*G12 -> 1784678.8
A5: Benefits | B5: Data Centers | C5: BEN - Benefits | D5: 504236.44 | E5: 1484837.4 | F5: =E5/D5-1 -> 1.9447244 | G5: =$G$3*E13 -> 1825047.6 | H5: =$H$3*E13 -> 1825047.6 | I5: =$I$3*G13 -> 1825047.6
A6: Bonus | B6: Data Centers | C6: BON - Bonus | D6: 2763608.4 | E6: 7260350.9 | F6: =E6/D6-1 -> 1.6271273 | G6: =$G$3*E14 -> 8923863.7 | H6: =$H$3*E14 -> 8923863.7 | I6: =$I$3*G14 -> 8923863.7
A7: Vacation | B7: Data Centers | C7: VAC - Vacation | D7: 15988.92 | E7: 54952.65 | F7: =E7/D7-1 -> 2.4369207 | G7: =$G$3*E15 -> 67543.562 | H7: =$H$3*E15 -> 67543.562 | I7: =$I$3*G15 -> 67543.562
A8: Other | B8: Data Centers | C8: OTHER - Other | D8: 137.37 | E8: 0 | F8: =E8/D8-1 -> -1 | G8: =$G$3*E16 -> 0 | H8: =$H$3*E16 -> 0 | I8: =$I$3*G16 -> 0
A9: LTIP Compensation | B9: Data Centers | C9: LTIP_COMP - LTIP Compensation | D9: 2003832.9 | E9: 3562244.9 | F9: =E9/D9-1 -> 0.77771548 | G9: =((E9/D9-1)+1)*E9 -> 6332657.8 | H9: =G9 -> 6332657.8 | I9: =H9 -> 6332657.8
D10: =SUM(D3:D9) -> 10347883 | E10: =SUM(E3:E9) -> 26299241 | G10: =SUM(G3:G9) -> 34279221 | H10: =SUM(H3:H9) -> 34279221 | I10: =SUM(I3:I9) -> 34279221
B12: Data Centers | C12: PAYROLL_TAX - Payroll tax | D12: =D4/$D$3 -> 0.11001914 | E12: =E4/$E$3 -> 0.11630036 | G12: =G4/$G$3 -> 0.11630036 | H12: =H4/$H$3 -> 0.11630036 | I12: =I4/$I$3 -> 0.11630036
B13: Data Centers | C13: BEN - Benefits | D13: =D5/$D$3 -> 0.11061331 | E13: =E5/$E$3 -> 0.11893103 | G13: =G5/$G$3 -> 0.11893103 | H13: =H5/$H$3 -> 0.11893103 | I13: =I5/$I$3 -> 0.11893103
B14: Data Centers | C14: BON - Bonus | D14: =D6/$D$3 -> 0.60624707 | E14: =E6/$E$3 -> 0.58153237 | G14: =G6/$G$3 -> 0.58153237 | H14: =H6/$H$3 -> 0.58153237 | I14: =I6/$I$3 -> 0.58153237
B15: Data Centers | C15: VAC - Vacation | D15: =D7/$D$3 -> 0.0035074564 | E15: =E7/$E$3 -> 0.0044015427 | G15: =G7/$G$3 -> 0.0044015427 | H15: =H7/$H$3 -> 0.0044015427 | I15: =I7/$I$3 -> 0.0044015427
B16: Data Centers | C16: OTHER - Other | D16: =D8/$D$3 -> 3.0134573e-05 | E16: =E8/$E$3 -> 0 | G16: =G8/$G$3 -> 0 | H16: =H8/$H$3 -> 0 | I16: =I8/$I$3 -> 0
B17: Data Centers | C17: LTIP_COMP - LTIP Compensation | D17: =D9/$D$3 -> 0.4395767 | E17: =E9/$E$3 -> 0.28532515 | G17: =G9/$G$3 -> 0.41267389 | H17: =H9/$H$3 -> 0.41267389 | I17: =I9/$I$3 -> 0.41267389

Sheet Base - Non-Payroll
B1: CC_CL | C1: Account | D1: Actual | E1: 04/2026 - Q126 Earnings FCST | F1: Growth Rate | G1: Growth Rate Override | H1: Model | I1: Growth Rate Override | J1: Model | K1: Growth Rate Override | L1: Model
D2: 2025 | E2: 2026 | F2: 2026 vs. 2025 | H2: 2027 | J2: 2028 | L2: 2029
A3: Professional Fees | B3: Data Centers | C3: GA_PROFESSIONAL_FEES - Professional Fees | D3: 312028.82 | E3: 328734 | F3: =IFERROR(E3/D3-1,0) -> 0.053537298 | G3: 0 | H3: =IF(ISBLANK($G3),($E3*(1+$F3)),($E3*(1+$G3))) -> 328734 | I3: 0 | J3: =IF(ISBLANK($I3),($H3*(1+$F3)),($H3*(1+$I3))) -> 328734 | K3: 0 | L3: =IF(ISBLANK($K3),($J3*(1+$F3)),($J3*(1+$K3))) -> 328734
A4: Occupancy | B4: Data Centers | C4: OCCUP - Occupancy | D4: 0 | E4: -65529 | F4: =IFERROR(E4/D4-1,0) -> 0 | G4: 0 | H4: =IF(ISBLANK($G4),($E4*(1+$F4)),($E4*(1+$G4))) -> -65529 | I4: 0 | J4: =IF(ISBLANK($I4),($H4*(1+$F4)),($H4*(1+$I4))) -> -65529 | K4: 0 | L4: =IF(ISBLANK($K4),($J4*(1+$F4)),($J4*(1+$K4))) -> -65529
A5: Office Expenses | B5: Data Centers | C5: OFFICE_EXP - Office Expenses | D5: 7608.68 | E5: -3040.82 | F5: =IFERROR(E5/D5-1,0) -> -1.3996515 | G5: 0 | H5: =IF(ISBLANK($G5),($E5*(1+$F5)),($E5*(1+$G5))) -> -3040.82 | I5: 0 | J5: =IF(ISBLANK($I5),($H5*(1+$F5)),($H5*(1+$I5))) -> -3040.82 | K5: 0 | L5: =IF(ISBLANK($K5),($J5*(1+$F5)),($J5*(1+$K5))) -> -3040.82
A6: IT Costs | B6: Data Centers | C6: IT_COSTS - IT Costs | D6: 11473.33 | E6: 7089.24 | F6: =IFERROR(E6/D6-1,0) -> -0.38211138 | G6: 0 | H6: =IF(ISBLANK($G6),($E6*(1+$F6)),($E6*(1+$G6))) -> 7089.24 | I6: 0 | J6: =IF(ISBLANK($I6),($H6*(1+$F6)),($H6*(1+$I6))) -> 7089.24 | K6: 0 | L6: =IF(ISBLANK($K6),($J6*(1+$F6)),($J6*(1+$K6))) -> 7089.24
A7: Marketing and Presentation | B7: Data Centers | C7: MKTG_PRES - Marketing and Presentation | D7: 0 | E7: 0 | F7: =IFERROR(E7/D7-1,0) -> 0 | G7: 0 | H7: =IF(ISBLANK($G7),($E7*(1+$F7)),($E7*(1+$G7))) -> 0 | I7: 0 | J7: =IF(ISBLANK($I7),($H7*(1+$F7)),($H7*(1+$I7))) -> 0 | K7: 0 | L7: =IF(ISBLANK($K7),($J7*(1+$F7)),($J7*(1+$K7))) -> 0
A8: Travel and Entertainment | B8: Data Centers | C8: T&E - Travel And Entertainment | D8: 706454.3 | E8: 945298.56 | F8: =IFERROR(E8/D8-1,0) -> 0.33808876 | G8: 0 | H8: =IF(ISBLANK($G8),($E8*(1+$F8)),($E8*(1+$G8))) -> 945298.56 | I8: 0 | J8: =IF(ISBLANK($I8),($H8*(1+$F8)),($H8*(1+$I8))) -> 945298.56 | K8: 0 | L8: =IF(ISBLANK($K8),($J8*(1+$F8)),($J8*(1+$K8))) -> 945298.56
A9: Employee events | B9: Data Centers | C9: EMPLOYEE_EVENTS - Employee events | D9: 66647.45 | E9: 119350.72 | F9: =IFERROR(E9/D9-1,0) -> 0.79077699 | G9: 0 | H9: =IF(ISBLANK($G9),($E9*(1+$F9)),($E9*(1+$G9))) -> 119350.72 | I9: 0 | J9: =IF(ISBLANK($I9),($H9*(1+$F9)),($H9*(1+$I9))) -> 119350.72 | K9: 0 | L9: =IF(ISBLANK($K9),($J9*(1+$F9)),($J9*(1+$K9))) -> 119350.72
A10: Insurance Non Property | B10: Data Centers | C10: INS_NON_PRTY - Insurance Non Property | D10: 0 | E10: 0 | F10: =IFERROR(E10/D10-1,0) -> 0 | G10: 0 | H10: =IF(ISBLANK($G10),($E10*(1+$F10)),($E10*(1+$G10))) -> 0 | I10: 0 | J10: =IF(ISBLANK($I10),($H10*(1+$F10)),($H10*(1+$I10))) -> 0 | K10: 0 | L10: =IF(ISBLANK($K10),($J10*(1+$F10)),($J10*(1+$K10))) -> 0
A11: Licenses | B11: Data Centers | C11: LIC - Licenses | D11: 0 | E11: 0 | F11: =IFERROR(E11/D11-1,0) -> 0 | G11: 0 | H11: =IF(ISBLANK($G11),($E11*(1+$F11)),($E11*(1+$G11))) -> 0 | I11: 0 | J11: =IF(ISBLANK($I11),($H11*(1+$F11)),($H11*(1+$I11))) -> 0 | K11: 0 | L11: =IF(ISBLANK($K11),($J11*(1+$F11)),($J11*(1+$K11))) -> 0
A12: Recruiting and Relocation | B12: Data Centers | C12: RECRUITING_RELOCATION - Recruiting And Relocation | D12: 296969.74 | E12: 959676.43 | F12: =IFERROR(E12/D12-1,0) -> 2.231563 | G12: 0 | H12: =IF(ISBLANK($G12),($E12*(1+$F12)),($E12*(1+$G12))) -> 959676.43 | I12: 0 | J12: =IF(ISBLANK($I12),($H12*(1+$F12)),($H12*(1+$I12))) -> 959676.43 | K12: 0 | L12: =IF(ISBLANK($K12),($J12*(1+$F12)),($J12*(1+$K12))) -> 959676.43
A13: Seminars and Training | B13: Data Centers | C13: SEM_TRG - Seminars And Training | D13: 41335.59 | E13: 36097.76 | F13: =IFERROR(E13/D13-1,0) -> -0.12671478 | G13: 0 | H13: =IF(ISBLANK($G13),($E13*(1+$F13)),($E13*(1+$G13))) -> 36097.76 | I13: 0 | J13: =IF(ISBLANK($I13),($H13*(1+$F13)),($H13*(1+$I13))) -> 36097.76 | K13: 0 | L13: =IF(ISBLANK($K13),($J13*(1+$F13)),($J13*(1+$K13))) -> 36097.76
A14: Shareholder Relations | B14: Data Centers | C14: SHARE_REL - Shareholder Relations | D14: 0 | E14: 0 | F14: =IFERROR(E14/D14-1,0) -> 0 | G14: 0 | H14: =IF(ISBLANK($G14),($E14*(1+$F14)),($E14*(1+$G14))) -> 0 | I14: 0 | J14: =IF(ISBLANK($I14),($H14*(1+$F14)),($H14*(1+$I14))) -> 0 | K14: 0 | L14: =IF(ISBLANK($K14),($J14*(1+$F14)),($J14*(1+$K14))) -> 0
... A25: Contract Labor | B25: Data Centers | C25: CONTRACT - Contract Labor | D25: 0 | E25: 0 | F25: =IFERROR(E25/D25-1,0) -> 0 | G25: 0 | H25: =IF(ISBLANK($G25),($E25*(1+$F25)),($E25*(1+$G25))) -> 0 | I25: 0 | J25: =IF(ISBLANK($I25),($H25*(1+$F25)),($H25*(1+$I25))) -> 0 | K25: 0 | L25: =IF(ISBLANK($K25),($J25*(1+$F25)),($J25*(1+$K25))) -> 0
D26: =SUM(D3:D25) -> 1718191.4 | E26: =SUM(E3:E25) -> 2649576.1 | F26: =E26/D26-1 -> 0.54207268 | G26: =H26/E26-1 -> 0 | H26: =SUM(H3:H25) -> 2649576.1 | I26: =J26/H26-1 -> 0 | J26: =SUM(J3:J25) -> 2649576.1 | K26: =L26/J26-1 -> 0 | L26: =SUM(L3:L25) -> 2649576.1
