Workbook

Sheet Summary
B1: Essentials Operations
B3: Total
C4: 2026 | D4: 2027 | E4: 2028 | F4: 2029 | G4: 2027 vs. 2026 Variance | H4: 2027 vs. 2026 Variance %
B5: Compensation | C5: =C43+C81 -> 11677112 | D5: =D43+D81 -> 12353631 | E5: =E43+E81 -> 12353631 | F5: =F43+F81 -> 12353631 | G5: =D5-C5 -> 676519 | H5: =D5/C5-1 -> 0.057935472
B6: Bonus | C6: =C44+C82 -> 2316552 | D6: =D44+D82 -> 2450762.5 | E6: =E44+E82 -> 2450762.5 | F6: =F44+F82 -> 2450762.5 | G6: =D6-C6 -> 134210.53 | H6: =D6/C6-1 -> 0.057935472
B7: Essentials Bonus | C7: =C45+C83 -> 4466769.9 | D7: =D45+D83 -> 4466769.9 | E7: =E45+E83 -> 4466769.9 | F7: =F45+F83 -> 4466769.9 | G7: =D7-C7 -> 0 | H7: =D7/C7-1 -> 0
B8: Payroll Taxes | C8: =C46+C84 -> 1500352 | D8: =D46+D84 -> 1587275.6 | E8: =E46+E84 -> 1587275.6 | F8: =F46+F84 -> 1587275.6 | G8: =D8-C8 -> 86923.602 | H8: =D8/C8-1 -> 0.057935472
B9: Benefits | C9: =C47+C85 -> 1806053 | D9: =D47+D85 -> 1910687.5 | E9: =E47+E85 -> 1910687.5 | F9: =F47+F85 -> 1910687.5 | G9: =D9-C9 -> 104634.53 | H9: =D9/C9-1 -> 0.057935472
B10: Vacation | C10: =C48+C86 -> 127917 | D10: =D48+D86 -> 135327.93 | E10: =E48+E86 -> 135327.93 | F10: =F48+F86 -> 135327.93 | G10: =D10-C10 -> 7410.9318 | H10: =D10/C10-1 -> 0.057935472
B11: Other | C11: =C49+C87 -> 50 | D11: =D49+D87 -> 52.896774 | E11: =E49+E87 -> 52.896774 | F11: =F49+F87 -> 52.896774 | G11: =D11-C11 -> 2.8967736 | H11: =D11/C11-1 -> 0.057935472
B12: Contract Labor | C12: =C50+C88 -> 798527.16 | D12: =D50+D88 -> 798527.16 | E12: =E50+E88 -> 798527.16 | F12: =F50+F88 -> 798527.16 | G12: =D12-C12 -> 0 | H12: =D12/C12-1 -> 0
B13: LTIP Compensation | C13: =C51+C89 -> 1515941.8 | D13: =D51+D89 -> 1714335 | E13: =E51+E89 -> 1714335 | F13: =F51+F89 -> 1714335 | G13: =D13-C13 -> 198393.2 | H13: =D13/C13-1 -> 0.13087125
B14: Total Payroll | C14: =SUM(C5:C13) -> 24209275 | D14: =SUM(D5:D13) -> 25417370 | E14: =SUM(E5:E13) -> 25417370 | F14: =SUM(F5:F13) -> 25417370 | G14: =SUM(G5:G13) -> 1208094.7 | H14: =D14/C14-1 -> 0.049902143
B16: Professional Fees | C16: =C54+C92 -> 800690.01 | D16: =D54+D92 -> 800690.01 | E16: =E54+E92 -> 800690.01 | F16: =F54+F92 -> 800690.01 | G16: =D16-C16 -> 0 | H16: =IFERROR(D16/C16-1,0) -> 0
B17: Occupancy | C17: =C55+C93 -> 0 | D17: =D55+D93 -> 0 | E17: =E55+E93 -> 0 | F17: =F55+F93 -> 0 | G17: =D17-C17 -> 0 | H17: =IFERROR(D17/C17-1,0) -> 0
B18: Office Expenses | C18: =C56+C94 -> 9004.22 | D18: =D56+D94 -> 9004.22 | E18: =E56+E94 -> 9004.22 | F18: =F56+F94 -> 9004.22 | G18: =D18-C18 -> 0 | H18: =IFERROR(D18/C18-1,0) -> 0
B19: IT Costs | C19: =C57+C95 -> 49202.28 | D19: =D57+D95 -> 49202.28 | E19: =E57+E95 -> 49202.28 | F19: =F57+F95 -> 49202.28 | G19: =D19-C19 -> 0 | H19: =IFERROR(D19/C19-1,0) -> 0
B20: Marketing and Presentation | C20: =C58+C96 -> 36685.95 | D20: =D58+D96 -> 36685.95 | E20: =E58+E96 -> 36685.95 | F20: =F58+F96 -> 36685.95 | G20: =D20-C20 -> 0 | H20: =IFERROR(D20/C20-1,0) -> 0
B21: Travel and Entertainment | C21: =C59+C97 -> 1380796.7 | D21: =D59+D97 -> 1380796.7 | E21: =E59+E97 -> 1380796.7 | F21: =F59+F97 -> 1380796.7 | G21: =D21-C21 -> 0 | H21: =IFERROR(D21/C21-1,0) -> 0
B22: Employee events | C22: =C60+C98 -> 49427.32 | D22: =D60+D98 -> 49427.32 | E22: =E60+E98 -> 49427.32 | F22: =F60+F98 -> 49427.32 | G22: =D22-C22 -> 0 | H22: =IFERROR(D22/C22-1,0) -> 0
B23: Insurance Non Property | C23: =C61+C99 -> 0 | D23: =D61+D99 -> 0 | E23: =E61+E99 -> 0 | F23: =F61+F99 -> 0 | G23: =D23-C23 -> 0 | H23: =IFERROR(D23/C23-1,0) -> 0
B24: Licenses | C24: =C62+C100 -> 0 | D24: =D62+D100 -> 0 | E24: =E62+E100 -> 0 | F24: =F62+F100 -> 0 | G24: =D24-C24 -> 0 | H24: =IFERROR(D24/C24-1,0) -> 0
B25: Recruiting and Relocation | C25: =C63+C101 -> 40000.92 | D25: =D63+D101 -> 40000.92 | E25: =E63+E101 -> 40000.92 | F25: =F63+F101 -> 40000.92 | G25: =D25-C25 -> 0 | H25: =IFERROR(D25/C25-1,0) -> 0
B26: Seminars and Training | C26: =C64+C102 -> 39685.13 | D26: =D64+D102 -> 39685.13 | E26: =E64+E102 -> 39685.13 | F26: =F64+F102 -> 39685.13 | G26: =D26-C26 -> 0 | H26: =IFERROR(D26/C26-1,0) -> 0
B27: Shareholder Relations | C27: =C65+C103 -> 0 | D27: =D65+D103 -> 0 | E27: =E65+E103 -> 0 | F27: =F65+F103 -> 0 | G27: =D27-C27 -> 0 | H27: =IFERROR(D27/C27-1,0) -> 0
... B36: Allocated IT & Office Contra | C36: =C74+C112 -> 0 | D36: =D74+D112 -> 0 | E36: =E74+E112 -> 0 | F36: =F74+F112 -> 0 | G36: =D36-C36 -> 0 | H36: =IFERROR(D36/C36-1,0) -> 0
B37: Total Non-Payroll | C37: =SUM(C16:C36) -> 2405492.9 | D37: =SUM(D16:D36) -> 2405492.9 | E37: =SUM(E16:E36) -> 2405492.9 | F37: =SUM(F16:F36) -> 2405492.9 | G37: =SUM(G16:G36) -> 0 | H37: =IFERROR(D37/C37-1,0) -> 0
B39: Total | C39: =C14+C37 -> 26614768 | D39: =D14+D37 -> 27822862 | E39: =E14+E37 -> 27822862 | F39: =F14+F37 -> 27822862 | G39: =G14+G37 -> 1208094.7 | H39: =IFERROR(D39/C39-1,0) -> 0.045391893
B41: Baseline
C42: 2026 | D42: 2027 | E42: 2028 | F42: 2029 | G42: 2027 vs. 2026 Variance | H42: 2027 vs. 2026 Variance %
B43: Compensation | C43: =SUMIFS('Base - Payroll'!$E:$E,'Base - Payroll'!$A:$A,Summary!$B43) -> 11677112 | D43: =SUMIFS('Base - Payroll'!$G:$G,'Base - Payroll'!$A:$A,Summary!$B43) -> 12353631 | E43: =SUMIFS('Base - Payroll'!$H:$H,'Base - Payroll'!$A:$A,Summary!$B43) -> 12353631 | F43: =SUMIFS('Base - Payroll'!$I:$I,'Base - Payroll'!$A:$A,Summary!$B43) -> 12353631 | G43: =D43-C43 -> 676519 | H43: =IFERROR(D43/C43-1,0) -> 0.057935472
B44: Bonus | C44: =SUMIFS('Base - Payroll'!$E:$E,'Base - Payroll'!$A:$A,Summary!$B44) -> 2316552 | D44: =SUMIFS('Base - Payroll'!$G:$G,'Base - Payroll'!$A:$A,Summary!$B44) -> 2450762.5 | E44: =SUMIFS('Base - Payroll'!$H:$H,'Base - Payroll'!$A:$A,Summary!$B44) -> 2450762.5 | F44: =SUMIFS('Base - Payroll'!$I:$I,'Base - Payroll'!$A:$A,Summary!$B44) -> 2450762.5 | G44: =D44-C44 -> 134210.53 | H44: =IFERROR(D44/C44-1,0) -> 0.057935472
B45: Essentials Bonus | C45: =SUMIFS('Base - Non-Payroll'!$E:$E,'Base - Non-Payroll'!$A:$A,Summary!$B45) -> 4466769.9 | D45: ='Base - Non-Payroll'!H24 -> 4466769.9 | E45: ='Base - Non-Payroll'!J24 -> 4466769.9 | F45: ='Base - Non-Payroll'!L24 -> 4466769.9 | G45: =D45-C45 -> 0 | H45: =IFERROR(D45/C45-1,0) -> 0
B46: Payroll Taxes | C46: =SUMIFS('Base - Payroll'!$E:$E,'Base - Payroll'!$A:$A,Summary!$B46) -> 1500352 | D46: =SUMIFS('Base - Payroll'!$G:$G,'Base - Payroll'!$A:$A,Summary!$B46) -> 1587275.6 | E46: =SUMIFS('Base - Payroll'!$H:$H,'Base - Payroll'!$A:$A,Summary!$B46) -> 1587275.6 | F46: =SUMIFS('Base - Payroll'!$I:$I,'Base - Payroll'!$A:$A,Summary!$B46) -> 1587275.6 | G46: =D46-C46 -> 86923.602 | H46: =IFERROR(D46/C46-1,0) -> 0.057935472
B47: Benefits | C47: =SUMIFS('Base - Payroll'!$E:$E,'Base - Payroll'!$A:$A,Summary!$B47) -> 1806053 | D47: =SUMIFS('Base - Payroll'!$G:$G,'Base - Payroll'!$A:$A,Summary!$B47) -> 1910687.5 | E47: =SUMIFS('Base - Payroll'!$H:$H,'Base - Payroll'!$A:$A,Summary!$B47) -> 1910687.5 | F47: =SUMIFS('Base - Payroll'!$I:$I,'Base - Payroll'!$A:$A,Summary!$B47) -> 1910687.5 | G47: =D47-C47 -> 104634.53 | H47: =IFERROR(D47/C47-1,0) -> 0.057935472
B48: Vacation | C48: =SUMIFS('Base - Payroll'!$E:$E,'Base - Payroll'!$A:$A,Summary!$B48) -> 127917 | D48: =SUMIFS('Base - Payroll'!$G:$G,'Base - Payroll'!$A:$A,Summary!$B48) -> 135327.93 | E48: =SUMIFS('Base - Payroll'!$H:$H,'Base - Payroll'!$A:$A,Summary!$B48) -> 135327.93 | F48: =SUMIFS('Base - Payroll'!$I:$I,'Base - Payroll'!$A:$A,Summary!$B48) -> 135327.93 | G48: =D48-C48 -> 7410.9318 | H48: =IFERROR(D48/C48-1,0) -> 0.057935472
B49: Other | C49: =SUMIFS('Base - Payroll'!$E:$E,'Base - Payroll'!$A:$A,Summary!$B49) -> 50 | D49: =SUMIFS('Base - Payroll'!$G:$G,'Base - Payroll'!$A:$A,Summary!$B49) -> 52.896774 | E49: =SUMIFS('Base - Payroll'!$H:$H,'Base - Payroll'!$A:$A,Summary!$B49) -> 52.896774 | F49: =SUMIFS('Base - Payroll'!$I:$I,'Base - Payroll'!$A:$A,Summary!$B49) -> 52.896774 | G49: =D49-C49 -> 2.8967736 | H49: =IFERROR(D49/C49-1,0) -> 0.057935472
B50: Contract Labor | C50: =SUMIFS('Base - Non-Payroll'!$E:$E,'Base - Non-Payroll'!$A:$A,Summary!$B50) -> 798527.16 | D50: ='Base - Non-Payroll'!H25 -> 798527.16 | E50: ='Base - Non-Payroll'!J25 -> 798527.16 | F50: ='Base - Non-Payroll'!L25 -> 798527.16 | G50: =D50-C50 -> 0 | H50: =IFERROR(D50/C50-1,0) -> 0
B51: LTIP Compensation | C51: =SUMIFS('Base - Payroll'!$E:$E,'Base - Payroll'!$A:$A,Summary!$B51) -> 1515941.8 | D51: =SUMIFS('Base - Payroll'!$G:$G,'Base - Payroll'!$A:$A,Summary!$B51) -> 1714335 | E51: =SUMIFS('Base - Payroll'!$H:$H,'Base - Payroll'!$A:$A,Summary!$B51) -> 1714335 | F51: =SUMIFS('Base - Payroll'!$I:$I,'Base - Payroll'!$A:$A,Summary!$B51) -> 1714335 | G51: =D51-C51 -> 198393.2 | H51: =IFERROR(D51/C51-1,0) -> 0.13087125
B52: Baseline Payroll | C52: =SUM(C43:C51) -> 24209275 | D52: =SUM(D43:D51) -> 25417370 | E52: =SUM(E43:E51) -> 25417370 | F52: =SUM(F43:F51) -> 25417370 | G52: =SUM(G43:G51) -> 1208094.7 | H52: =IFERROR(D52/C52-1,0) -> 0.049902143
B54: Professional Fees | C54: =SUMIFS('Base - Non-Payroll'!$E:$E,'Base - Non-Payroll'!$A:$A,Summary!$B54) -> 800690.01 | D54: =SUMIFS('Base - Non-Payroll'!$H:$H,'Base - Non-Payroll'!$A:$A,Summary!$B54) -> 800690.01 | E54: =SUMIFS('Base - Non-Payroll'!$J:$J,'Base - Non-Payroll'!$A:$A,Summary!$B54) -> 800690.01 | F54: =SUMIFS('Base - Non-Payroll'!$L:$L,'Base - Non-Payroll'!$A:$A,Summary!$B54) -> 800690.01 | G54: =D54-C54 -> 0 | H54: =IFERROR(D54/C54-1,0) -> 0
B55: Occupancy | C55: =SUMIFS('Base - Non-Payroll'!$E:$E,'Base - Non-Payroll'!$A:$A,Summary!$B55) -> 0 | D55: =SUMIFS('Base - Non-Payroll'!$H:$H,'Base - Non-Payroll'!$A:$A,Summary!$B55) -> 0 | E55: =SUMIFS('Base - Non-Payroll'!$J:$J,'Base - Non-Payroll'!$A:$A,Summary!$B55) -> 0 | F55: =SUMIFS('Base - Non-Payroll'!$L:$L,'Base - Non-Payroll'!$A:$A,Summary!$B55) -> 0 | G55: =D55-C55 -> 0 | H55: =IFERROR(D55/C55-1,0) -> 0
B56: Office Expenses | C56: =SUMIFS('Base - Non-Payroll'!$E:$E,'Base - Non-Payroll'!$A:$A,Summary!$B56) -> 9004.22 | D56: =SUMIFS('Base - Non-Payroll'!$H:$H,'Base - Non-Payroll'!$A:$A,Summary!$B56) -> 9004.22 | E56: =SUMIFS('Base - Non-Payroll'!$J:$J,'Base - Non-Payroll'!$A:$A,Summary!$B56) -> 9004.22 | F56: =SUMIFS('Base - Non-Payroll'!$L:$L,'Base - Non-Payroll'!$A:$A,Summary!$B56) -> 9004.22 | G56: =D56-C56 -> 0 | H56: =IFERROR(D56/C56-1,0) -> 0
B57: IT Costs | C57: =SUMIFS('Base - Non-Payroll'!$E:$E,'Base - Non-Payroll'!$A:$A,Summary!$B57) -> 49202.28 | D57: =SUMIFS('Base - Non-Payroll'!$H:$H,'Base - Non-Payroll'!$A:$A,Summary!$B57) -> 49202.28 | E57: =SUMIFS('Base - Non-Payroll'!$J:$J,'Base - Non-Payroll'!$A:$A,Summary!$B57) -> 49202.28 | F57: =SUMIFS('Base - Non-Payroll'!$L:$L,'Base - Non-Payroll'!$A:$A,Summary!$B57) -> 49202.28 | G57: =D57-C57 -> 0 | H57: =IFERROR(D57/C57-1,0) -> 0
B58: Marketing and Presentation | C58: =SUMIFS('Base - Non-Payroll'!$E:$E,'Base - Non-Payroll'!$A:$A,Summary!$B58) -> 36685.95 | D58: =SUMIFS('Base - Non-Payroll'!$H:$H,'Base - Non-Payroll'!$A:$A,Summary!$B58) -> 36685.95 | E58: =SUMIFS('Base - Non-Payroll'!$J:$J,'Base - Non-Payroll'!$A:$A,Summary!$B58) -> 36685.95 | F58: =SUMIFS('Base - Non-Payroll'!$L:$L,'Base - Non-Payroll'!$A:$A,Summary!$B58) -> 36685.95 | G58: =D58-C58 -> 0 | H58: =IFERROR(D58/C58-1,0) -> 0
B59: Travel and Entertainment | C59: =SUMIFS('Base - Non-Payroll'!$E:$E,'Base - Non-Payroll'!$A:$A,Summary!$B59) -> 1380796.7 | D59: =SUMIFS('Base - Non-Payroll'!$H:$H,'Base - Non-Payroll'!$A:$A,Summary!$B59) -> 1380796.7 | E59: =SUMIFS('Base - Non-Payroll'!$J:$J,'Base - Non-Payroll'!$A:$A,Summary!$B59) -> 1380796.7 | F59: =SUMIFS('Base - Non-Payroll'!$L:$L,'Base - Non-Payroll'!$A:$A,Summary!$B59) -> 1380796.7 | G59: =D59-C59 -> 0 | H59: =IFERROR(D59/C59-1,0) -> 0
B60: Employee events | C60: =SUMIFS('Base - Non-Payroll'!$E:$E,'Base - Non-Payroll'!$A:$A,Summary!$B60) -> 49427.32 | D60: =SUMIFS('Base - Non-Payroll'!$H:$H,'Base - Non-Payroll'!$A:$A,Summary!$B60) -> 49427.32 | E60: =SUMIFS('Base - Non-Payroll'!$J:$J,'Base - Non-Payroll'!$A:$A,Summary!$B60) -> 49427.32 | F60: =SUMIFS('Base - Non-Payroll'!$L:$L,'Base - Non-Payroll'!$A:$A,Summary!$B60) -> 49427.32 | G60: =D60-C60 -> 0 | H60: =IFERROR(D60/C60-1,0) -> 0
B61: Insurance Non Property | C61: =SUMIFS('Base - Non-Payroll'!$E:$E,'Base - Non-Payroll'!$A:$A,Summary!$B61) -> 0 | D61: =SUMIFS('Base - Non-Payroll'!$H:$H,'Base - Non-Payroll'!$A:$A,Summary!$B61) -> 0 | E61: =SUMIFS('Base - Non-Payroll'!$J:$J,'Base - Non-Payroll'!$A:$A,Summary!$B61) -> 0 | F61: =SUMIFS('Base - Non-Payroll'!$L:$L,'Base - Non-Payroll'!$A:$A,Summary!$B61) -> 0 | G61: =D61-C61 -> 0 | H61: =IFERROR(D61/C61-1,0) -> 0
B62: Licenses | C62: =SUMIFS('Base - Non-Payroll'!$E:$E,'Base - Non-Payroll'!$A:$A,Summary!$B62) -> 0 | D62: =SUMIFS('Base - Non-Payroll'!$H:$H,'Base - Non-Payroll'!$A:$A,Summary!$B62) -> 0 | E62: =SUMIFS('Base - Non-Payroll'!$J:$J,'Base - Non-Payroll'!$A:$A,Summary!$B62) -> 0 | F62: =SUMIFS('Base - Non-Payroll'!$L:$L,'Base - Non-Payroll'!$A:$A,Summary!$B62) -> 0 | G62: =D62-C62 -> 0 | H62: =IFERROR(D62/C62-1,0) -> 0
B63: Recruiting and Relocation | C63: =SUMIFS('Base - Non-Payroll'!$E:$E,'Base - Non-Payroll'!$A:$A,Summary!$B63) -> 40000.92 | D63: =SUMIFS('Base - Non-Payroll'!$H:$H,'Base - Non-Payroll'!$A:$A,Summary!$B63) -> 40000.92 | E63: =SUMIFS('Base - Non-Payroll'!$J:$J,'Base - Non-Payroll'!$A:$A,Summary!$B63) -> 40000.92 | F63: =SUMIFS('Base - Non-Payroll'!$L:$L,'Base - Non-Payroll'!$A:$A,Summary!$B63) -> 40000.92 | G63: =D63-C63 -> 0 | H63: =IFERROR(D63/C63-1,0) -> 0
B64: Seminars and Training | C64: =SUMIFS('Base - Non-Payroll'!$E:$E,'Base - Non-Payroll'!$A:$A,Summary!$B64) -> 39685.13 | D64: =SUMIFS('Base - Non-Payroll'!$H:$H,'Base - Non-Payroll'!$A:$A,Summary!$B64) -> 39685.13 | E64: =SUMIFS('Base - Non-Payroll'!$J:$J,'Base - Non-Payroll'!$A:$A,Summary!$B64) -> 39685.13 | F64: =SUMIFS('Base - Non-Payroll'!$L:$L,'Base - Non-Payroll'!$A:$A,Summary!$B64) -> 39685.13 | G64: =D64-C64 -> 0 | H64: =IFERROR(D64/C64-1,0) -> 0
B65: Shareholder Relations | C65: =SUMIFS('Base - Non-Payroll'!$E:$E,'Base - Non-Payroll'!$A:$A,Summary!$B65) -> 0 | D65: =SUMIFS('Base - Non-Payroll'!$H:$H,'Base - Non-Payroll'!$A:$A,Summary!$B65) -> 0 | E65: =SUMIFS('Base - Non-Payroll'!$J:$J,'Base - Non-Payroll'!$A:$A,Summary!$B65) -> 0 | F65: =SUMIFS('Base - Non-Payroll'!$L:$L,'Base - Non-Payroll'!$A:$A,Summary!$B65) -> 0 | G65: =D65-C65 -> 0 | H65: =IFERROR(D65/C65-1,0) -> 0
... B74: Allocated IT & Office Contra | C74: =SUMIFS('Base - Non-Payroll'!$E:$E,'Base - Non-Payroll'!$A:$A,Summary!$B74) -> 0 | D74: =SUMIFS('Base - Non-Payroll'!$H:$H,'Base - Non-Payroll'!$A:$A,Summary!$B74) -> 0 | E74: =SUMIFS('Base - Non-Payroll'!$J:$J,'Base - Non-Payroll'!$A:$A,Summary!$B74) -> 0 | F74: =SUMIFS('Base - Non-Payroll'!$L:$L,'Base - Non-Payroll'!$A:$A,Summary!$B74) -> 0 | G74: =D74-C74 -> 0 | H74: =IFERROR(D74/C74-1,0) -> 0
B75: Baseline Non-Payroll | C75: =SUM(C54:C74) -> 2405492.9 | D75: =SUM(D54:D74) -> 2405492.9 | E75: =SUM(E54:E74) -> 2405492.9 | F75: =SUM(F54:F74) -> 2405492.9 | G75: =SUM(G54:G74) -> 0 | H75: =IFERROR(D75/C75-1,0) -> 0
B77: Total | C77: =C52+C75 -> 26614768 | D77: =D52+D75 -> 27822862 | E77: =E52+E75 -> 27822862 | F77: =F52+F75 -> 27822862 | G77: =G52+G75 -> 1208094.7 | H77: =IFERROR(D77/C77-1,0) -> 0.045391893
B79: Incremental
D80: 2027 Incremental Spend | E80: 2028 Incremental Spend | F80: 2029 Incremental Spend
B81: Compensation | D81: {=SUMPRODUCT(IFERROR(tblPayrollIncrementalSpend[Base Salary]*tblPayrollIncrementalSpend[2027 Incremental Spend]/(tblPayrollIncrementalSpend[Base Salary]+tblPayrollIncrementalSpend[Bonus]+tblPayrollIncrementalSpend[Payroll Taxes]+tblPayrollIncrementalSpend[Benefits]+tblPayrollIncrementalSpend[Vacation]+tblPayrollIncrementalSpend[Other]),0))} -> 0 | E81: {=SUMPRODUCT(IFERROR(tblPayrollIncrementalSpend[Base Salary]*tblPayrollIncrementalSpend[2028 Incremental Spend]/(tblPayrollIncrementalSpend[Base Salary]+tblPayrollIncrementalSpend[Bonus]+tblPayrollIncrementalSpend[Payroll Taxes]+tblPayrollIncrementalSpend[Benefits]+tblPayrollIncrementalSpend[Vacation]+tblPayrollIncrementalSpend[Other]),0))} -> 0 | F81: {=SUMPRODUCT(IFERROR(tblPayrollIncrementalSpend[Base Salary]*tblPayrollIncrementalSpend[2029 Incremental Spend]/(tblPayrollIncrementalSpend[Base Salary]+tblPayrollIncrementalSpend[Bonus]+tblPayrollIncrementalSpend[Payroll Taxes]+tblPayrollIncrementalSpend[Benefits]+tblPayrollIncrementalSpend[Vacation]+tblPayrollIncrementalSpend[Other]),0))} -> 0
B82: Bonus | D82: {=SUMPRODUCT(IFERROR(tblPayrollIncrementalSpend[Bonus]*tblPayrollIncrementalSpend[2027 Incremental Spend]/(tblPayrollIncrementalSpend[Base Salary]+tblPayrollIncrementalSpend[Bonus]+tblPayrollIncrementalSpend[Payroll Taxes]+tblPayrollIncrementalSpend[Benefits]+tblPayrollIncrementalSpend[Vacation]+tblPayrollIncrementalSpend[Other]),0))} -> 0 | E82: {=SUMPRODUCT(IFERROR(tblPayrollIncrementalSpend[Bonus]*tblPayrollIncrementalSpend[2028 Incremental Spend]/(tblPayrollIncrementalSpend[Base Salary]+tblPayrollIncrementalSpend[Bonus]+tblPayrollIncrementalSpend[Payroll Taxes]+tblPayrollIncrementalSpend[Benefits]+tblPayrollIncrementalSpend[Vacation]+tblPayrollIncrementalSpend[Other]),0))} -> 0 | F82: {=SUMPRODUCT(IFERROR(tblPayrollIncrementalSpend[Bonus]*tblPayrollIncrementalSpend[2029 Incremental Spend]/(tblPayrollIncrementalSpend[Base Salary]+tblPayrollIncrementalSpend[Bonus]+tblPayrollIncrementalSpend[Payroll Taxes]+tblPayrollIncrementalSpend[Benefits]+tblPayrollIncrementalSpend[Vacation]+tblPayrollIncrementalSpend[Other]),0))} -> 0
B83: Essentials Bonus | D83: =SUMIF(tblNonPayrollIncrementalSpend[Type of Expense],$B83,tblNonPayrollIncrementalSpend[2027 Incremental Spend]) -> 0 | E83: =SUMIF(tblNonPayrollIncrementalSpend3[Type of Expense],$B83,tblNonPayrollIncrementalSpend3[2028 Incremental Spend]) -> 0 | F83: =SUMIF(tblNonPayrollIncrementalSpend3[Type of Expense],$B83,tblNonPayrollIncrementalSpend3[2029 Incremental Spend]) -> 0
B84: Payroll Taxes | D84: {=SUMPRODUCT(IFERROR(tblPayrollIncrementalSpend[Payroll Taxes]*tblPayrollIncrementalSpend[2027 Incremental Spend]/(tblPayrollIncrementalSpend[Base Salary]+tblPayrollIncrementalSpend[Bonus]+tblPayrollIncrementalSpend[Payroll Taxes]+tblPayrollIncrementalSpend[Benefits]+tblPayrollIncrementalSpend[Vacation]+tblPayrollIncrementalSpend[Other]),0))} -> 0 | E84: {=SUMPRODUCT(IFERROR(tblPayrollIncrementalSpend[Payroll Taxes]*tblPayrollIncrementalSpend[2028 Incremental Spend]/(tblPayrollIncrementalSpend[Base Salary]+tblPayrollIncrementalSpend[Bonus]+tblPayrollIncrementalSpend[Payroll Taxes]+tblPayrollIncrementalSpend[Benefits]+tblPayrollIncrementalSpend[Vacation]+tblPayrollIncrementalSpend[Other]),0))} -> 0 | F84: {=SUMPRODUCT(IFERROR(tblPayrollIncrementalSpend[Payroll Taxes]*tblPayrollIncrementalSpend[2029 Incremental Spend]/(tblPayrollIncrementalSpend[Base Salary]+tblPayrollIncrementalSpend[Bonus]+tblPayrollIncrementalSpend[Payroll Taxes]+tblPayrollIncrementalSpend[Benefits]+tblPayrollIncrementalSpend[Vacation]+tblPayrollIncrementalSpend[Other]),0))} -> 0
B85: Benefits | D85: {=SUMPRODUCT(IFERROR(tblPayrollIncrementalSpend[Benefits]*tblPayrollIncrementalSpend[2027 Incremental Spend]/(tblPayrollIncrementalSpend[Base Salary]+tblPayrollIncrementalSpend[Bonus]+tblPayrollIncrementalSpend[Payroll Taxes]+tblPayrollIncrementalSpend[Benefits]+tblPayrollIncrementalSpend[Vacation]+tblPayrollIncrementalSpend[Other]),0))} -> 0 | E85: {=SUMPRODUCT(IFERROR(tblPayrollIncrementalSpend[Benefits]*tblPayrollIncrementalSpend[2028 Incremental Spend]/(tblPayrollIncrementalSpend[Base Salary]+tblPayrollIncrementalSpend[Bonus]+tblPayrollIncrementalSpend[Payroll Taxes]+tblPayrollIncrementalSpend[Benefits]+tblPayrollIncrementalSpend[Vacation]+tblPayrollIncrementalSpend[Other]),0))} -> 0 | F85: {=SUMPRODUCT(IFERROR(tblPayrollIncrementalSpend[Benefits]*tblPayrollIncrementalSpend[2029 Incremental Spend]/(tblPayrollIncrementalSpend[Base Salary]+tblPayrollIncrementalSpend[Bonus]+tblPayrollIncrementalSpend[Payroll Taxes]+tblPayrollIncrementalSpend[Benefits]+tblPayrollIncrementalSpend[Vacation]+tblPayrollIncrementalSpend[Other]),0))} -> 0
B86: Vacation | D86: {=SUMPRODUCT(IFERROR(tblPayrollIncrementalSpend[Vacation]*tblPayrollIncrementalSpend[2027 Incremental Spend]/(tblPayrollIncrementalSpend[Base Salary]+tblPayrollIncrementalSpend[Bonus]+tblPayrollIncrementalSpend[Payroll Taxes]+tblPayrollIncrementalSpend[Benefits]+tblPayrollIncrementalSpend[Vacation]+tblPayrollIncrementalSpend[Other]),0))} -> 0 | E86: {=SUMPRODUCT(IFERROR(tblPayrollIncrementalSpend[Vacation]*tblPayrollIncrementalSpend[2028 Incremental Spend]/(tblPayrollIncrementalSpend[Base Salary]+tblPayrollIncrementalSpend[Bonus]+tblPayrollIncrementalSpend[Payroll Taxes]+tblPayrollIncrementalSpend[Benefits]+tblPayrollIncrementalSpend[Vacation]+tblPayrollIncrementalSpend[Other]),0))} -> 0 | F86: {=SUMPRODUCT(IFERROR(tblPayrollIncrementalSpend[Vacation]*tblPayrollIncrementalSpend[2029 Incremental Spend]/(tblPayrollIncrementalSpend[Base Salary]+tblPayrollIncrementalSpend[Bonus]+tblPayrollIncrementalSpend[Payroll Taxes]+tblPayrollIncrementalSpend[Benefits]+tblPayrollIncrementalSpend[Vacation]+tblPayrollIncrementalSpend[Other]),0))} -> 0
B87: Other | D87: {=SUMPRODUCT(IFERROR(tblPayrollIncrementalSpend[Other]*tblPayrollIncrementalSpend[2027 Incremental Spend]/(tblPayrollIncrementalSpend[Base Salary]+tblPayrollIncrementalSpend[Bonus]+tblPayrollIncrementalSpend[Payroll Taxes]+tblPayrollIncrementalSpend[Benefits]+tblPayrollIncrementalSpend[Vacation]+tblPayrollIncrementalSpend[Other]),0))} -> 0 | E87: {=SUMPRODUCT(IFERROR(tblPayrollIncrementalSpend[Other]*tblPayrollIncrementalSpend[2028 Incremental Spend]/(tblPayrollIncrementalSpend[Base Salary]+tblPayrollIncrementalSpend[Bonus]+tblPayrollIncrementalSpend[Payroll Taxes]+tblPayrollIncrementalSpend[Benefits]+tblPayrollIncrementalSpend[Vacation]+tblPayrollIncrementalSpend[Other]),0))} -> 0 | F87: {=SUMPRODUCT(IFERROR(tblPayrollIncrementalSpend[Other]*tblPayrollIncrementalSpend[2029 Incremental Spend]/(tblPayrollIncrementalSpend[Base Salary]+tblPayrollIncrementalSpend[Bonus]+tblPayrollIncrementalSpend[Payroll Taxes]+tblPayrollIncrementalSpend[Benefits]+tblPayrollIncrementalSpend[Vacation]+tblPayrollIncrementalSpend[Other]),0))} -> 0
B88: Contract Labor | D88: =SUMIF(tblNonPayrollIncrementalSpend[Type of Expense],$B88,tblNonPayrollIncrementalSpend[2027 Incremental Spend]) -> 0 | E88: =SUMIF(tblNonPayrollIncrementalSpend3[Type of Expense],$B88,tblNonPayrollIncrementalSpend3[2028 Incremental Spend]) -> 0 | F88: =SUMIF(tblNonPayrollIncrementalSpend3[Type of Expense],$B88,tblNonPayrollIncrementalSpend3[2029 Incremental Spend]) -> 0
B89: LTIP Compensation | D89: =SUMIF(tblNonPayrollIncrementalSpend[Type of Expense],$B89,tblNonPayrollIncrementalSpend[2027 Incremental Spend]) -> 0 | E89: =SUMIF(tblNonPayrollIncrementalSpend3[Type of Expense],$B89,tblNonPayrollIncrementalSpend3[2028 Incremental Spend]) -> 0 | F89: =SUMIF(tblNonPayrollIncrementalSpend3[Type of Expense],$B89,tblNonPayrollIncrementalSpend3[2029 Incremental Spend]) -> 0
B90: Incremental Payroll | D90: =SUM(D81:D89) -> 0 | E90: =SUM(E81:E89) -> 0 | F90: =SUM(F81:F89) -> 0
B92: Professional Fees | D92: =SUMIF(tblNonPayrollIncrementalSpend[Type of Expense],$B92,tblNonPayrollIncrementalSpend[2027 Incremental Spend]) -> 0 | E92: =SUMIF(tblNonPayrollIncrementalSpend3[Type of Expense],$B92,tblNonPayrollIncrementalSpend3[2028 Incremental Spend]) -> 0 | F92: =SUMIF(tblNonPayrollIncrementalSpend3[Type of Expense],$B92,tblNonPayrollIncrementalSpend3[2029 Incremental Spend]) -> 0
B93: Occupancy | D93: =SUMIF(tblNonPayrollIncrementalSpend[Type of Expense],$B93,tblNonPayrollIncrementalSpend[2027 Incremental Spend]) -> 0 | E93: =SUMIF(tblNonPayrollIncrementalSpend3[Type of Expense],$B93,tblNonPayrollIncrementalSpend3[2028 Incremental Spend]) -> 0 | F93: =SUMIF(tblNonPayrollIncrementalSpend3[Type of Expense],$B93,tblNonPayrollIncrementalSpend3[2029 Incremental Spend]) -> 0
B94: Office Expenses | D94: =SUMIF(tblNonPayrollIncrementalSpend[Type of Expense],$B94,tblNonPayrollIncrementalSpend[2027 Incremental Spend]) -> 0 | E94: =SUMIF(tblNonPayrollIncrementalSpend3[Type of Expense],$B94,tblNonPayrollIncrementalSpend3[2028 Incremental Spend]) -> 0 | F94: =SUMIF(tblNonPayrollIncrementalSpend3[Type of Expense],$B94,tblNonPayrollIncrementalSpend3[2029 Incremental Spend]) -> 0
B95: IT Costs | D95: =SUMIF(tblNonPayrollIncrementalSpend[Type of Expense],$B95,tblNonPayrollIncrementalSpend[2027 Incremental Spend]) -> 0 | E95: =SUMIF(tblNonPayrollIncrementalSpend3[Type of Expense],$B95,tblNonPayrollIncrementalSpend3[2028 Incremental Spend]) -> 0 | F95: =SUMIF(tblNonPayrollIncrementalSpend3[Type of Expense],$B95,tblNonPayrollIncrementalSpend3[2029 Incremental Spend]) -> 0
B96: Marketing and Presentation | D96: =SUMIF(tblNonPayrollIncrementalSpend[Type of Expense],$B96,tblNonPayrollIncrementalSpend[2027 Incremental Spend]) -> 0 | E96: =SUMIF(tblNonPayrollIncrementalSpend3[Type of Expense],$B96,tblNonPayrollIncrementalSpend3[2028 Incremental Spend]) -> 0 | F96: =SUMIF(tblNonPayrollIncrementalSpend3[Type of Expense],$B96,tblNonPayrollIncrementalSpend3[2029 Incremental Spend]) -> 0
B97: Travel and Entertainment | D97: =SUMIF(tblNonPayrollIncrementalSpend[Type of Expense],$B97,tblNonPayrollIncrementalSpend[2027 Incremental Spend]) -> 0 | E97: =SUMIF(tblNonPayrollIncrementalSpend3[Type of Expense],$B97,tblNonPayrollIncrementalSpend3[2028 Incremental Spend]) -> 0 | F97: =SUMIF(tblNonPayrollIncrementalSpend3[Type of Expense],$B97,tblNonPayrollIncrementalSpend3[2029 Incremental Spend]) -> 0
B98: Employee events | D98: =SUMIF(tblNonPayrollIncrementalSpend[Type of Expense],$B98,tblNonPayrollIncrementalSpend[2027 Incremental Spend]) -> 0 | E98: =SUMIF(tblNonPayrollIncrementalSpend3[Type of Expense],$B98,tblNonPayrollIncrementalSpend3[2028 Incremental Spend]) -> 0 | F98: =SUMIF(tblNonPayrollIncrementalSpend3[Type of Expense],$B98,tblNonPayrollIncrementalSpend3[2029 Incremental Spend]) -> 0
B99: Insurance Non Property | D99: =SUMIF(tblNonPayrollIncrementalSpend[Type of Expense],$B99,tblNonPayrollIncrementalSpend[2027 Incremental Spend]) -> 0 | E99: =SUMIF(tblNonPayrollIncrementalSpend3[Type of Expense],$B99,tblNonPayrollIncrementalSpend3[2028 Incremental Spend]) -> 0 | F99: =SUMIF(tblNonPayrollIncrementalSpend3[Type of Expense],$B99,tblNonPayrollIncrementalSpend3[2029 Incremental Spend]) -> 0
B100: Licenses | D100: =SUMIF(tblNonPayrollIncrementalSpend[Type of Expense],$B100,tblNonPayrollIncrementalSpend[2027 Incremental Spend]) -> 0 | E100: =SUMIF(tblNonPayrollIncrementalSpend3[Type of Expense],$B100,tblNonPayrollIncrementalSpend3[2028 Incremental Spend]) -> 0 | F100: =SUMIF(tblNonPayrollIncrementalSpend3[Type of Expense],$B100,tblNonPayrollIncrementalSpend3[2029 Incremental Spend]) -> 0
B101: Recruiting and Relocation | D101: =SUMIF(tblNonPayrollIncrementalSpend[Type of Expense],$B101,tblNonPayrollIncrementalSpend[2027 Incremental Spend]) -> 0 | E101: =SUMIF(tblNonPayrollIncrementalSpend3[Type of Expense],$B101,tblNonPayrollIncrementalSpend3[2028 Incremental Spend]) -> 0 | F101: =SUMIF(tblNonPayrollIncrementalSpend3[Type of Expense],$B101,tblNonPayrollIncrementalSpend3[2029 Incremental Spend]) -> 0
B102: Seminars and Training | D102: =SUMIF(tblNonPayrollIncrementalSpend[Type of Expense],$B102,tblNonPayrollIncrementalSpend[2027 Incremental Spend]) -> 0 | E102: =SUMIF(tblNonPayrollIncrementalSpend3[Type of Expense],$B102,tblNonPayrollIncrementalSpend3[2028 Incremental Spend]) -> 0 | F102: =SUMIF(tblNonPayrollIncrementalSpend3[Type of Expense],$B102,tblNonPayrollIncrementalSpend3[2029 Incremental Spend]) -> 0
B103: Shareholder Relations | D103: =SUMIF(tblNonPayrollIncrementalSpend[Type of Expense],$B103,tblNonPayrollIncrementalSpend[2027 Incremental Spend]) -> 0 | E103: =SUMIF(tblNonPayrollIncrementalSpend3[Type of Expense],$B103,tblNonPayrollIncrementalSpend3[2028 Incremental Spend]) -> 0 | F103: =SUMIF(tblNonPayrollIncrementalSpend3[Type of Expense],$B103,tblNonPayrollIncrementalSpend3[2029 Incremental Spend]) -> 0
... B112: Allocated IT & Office Contra | D112: =SUMIF(tblNonPayrollIncrementalSpend[Type of Expense],$B112,tblNonPayrollIncrementalSpend[2027 Incremental Spend]) -> 0 | E112: =SUMIF(tblNonPayrollIncrementalSpend3[Type of Expense],$B112,tblNonPayrollIncrementalSpend3[2028 Incremental Spend]) -> 0 | F112: =SUMIF(tblNonPayrollIncrementalSpend3[Type of Expense],$B112,tblNonPayrollIncrementalSpend3[2029 Incremental Spend]) -> 0
B113: Incremental Non-Payroll | D113: =SUM(D92:D112) -> 0 | E113: =SUM(E92:E112) -> 0 | F113: =SUM(F92:F112) -> 0
B115: Total | D115: =D90+D113 -> 0 | E115: =E90+E113 -> 0 | F115: =F90+F113 -> 0

Sheet Investment Case Asks - Summary
A1: Investment Case Asks - Incremental Spend Input
A3: Payroll / Headcount Incremental Spend | T3: Incremental Spend Summary
A4: Job Title | B4: Job Level | C4: Role / Hire | D4: Location (City/Country) | E4: Key Job Responsibilities | F4: Hire Date | G4: Base Salary | H4: Bonus % | I4: Bonus | J4: Payroll Taxes | K4: Benefits | L4: Vacation | M4: Other | N4: 2027 Annualized Spend | O4: 2027 Incremental Spend | P4: 2028 Incremental Spend | Q4: 2029 Incremental Spend | R4: Notes / Rationale | T4: Spend Type | U4: 2027 | V4: 2028 | W4: 2029
A5: =IF(ISBLANK('Investment Case Asks - Monthly'!A5),"",'Investment Case Asks - Monthly'!A5) | B5: =IF(ISBLANK('Investment Case Asks - Monthly'!B5),"",'Investment Case Asks - Monthly'!B5) | C5: =IF(ISBLANK('Investment Case Asks - Monthly'!C5),"",'Investment Case Asks - Monthly'!C5) | D5: =IF(ISBLANK('Investment Case Asks - Monthly'!D5),"",'Investment Case Asks - Monthly'!D5) | E5: =IF(ISBLANK('Investment Case Asks - Monthly'!E5),"",'Investment Case Asks - Monthly'!E5) | F5: =IF(ISBLANK('Investment Case Asks - Monthly'!F5),"",'Investment Case Asks - Monthly'!F5) | G5: =IF(ISBLANK('Investment Case Asks - Monthly'!G5),"",'Investment Case Asks - Monthly'!G5) | H5: =IF(ISBLANK('Investment Case Asks - Monthly'!H5),"",'Investment Case Asks - Monthly'!H5) | ... N5: =IF(ISBLANK('Investment Case Asks - Monthly'!N5),"",'Investment Case Asks - Monthly'!N5) | O5: =IF(ISBLANK('Investment Case Asks - Monthly'!AA5),"",'Investment Case Asks - Monthly'!AA5) | P5: =IF(ISBLANK('Investment Case Asks - Monthly'!AN5),"",'Investment Case Asks - Monthly'!AN5) | Q5: =IF(ISBLANK('Investment Case Asks - Monthly'!BA5),"",'Investment Case Asks - Monthly'!BA5) | R5: =IF(ISBLANK('Investment Case Asks - Monthly'!BB5),"",'Investment Case Asks - Monthly'!BB5) | T5: Payroll / Headcount | U5: =O22 -> 0 | V5: =P22 -> 0 | W5: =Q22 -> 0
A6: =IF(ISBLANK('Investment Case Asks - Monthly'!A6),"",'Investment Case Asks - Monthly'!A6) | B6: =IF(ISBLANK('Investment Case Asks - Monthly'!B6),"",'Investment Case Asks - Monthly'!B6) | C6: =IF(ISBLANK('Investment Case Asks - Monthly'!C6),"",'Investment Case Asks - Monthly'!C6) | D6: =IF(ISBLANK('Investment Case Asks - Monthly'!D6),"",'Investment Case Asks - Monthly'!D6) | E6: =IF(ISBLANK('Investment Case Asks - Monthly'!E6),"",'Investment Case Asks - Monthly'!E6) | F6: =IF(ISBLANK('Investment Case Asks - Monthly'!F6),"",'Investment Case Asks - Monthly'!F6) | G6: =IF(ISBLANK('Investment Case Asks - Monthly'!G6),"",'Investment Case Asks - Monthly'!G6) | H6: =IF(ISBLANK('Investment Case Asks - Monthly'!H6),"",'Investment Case Asks - Monthly'!H6) | ... N6: =IF(ISBLANK('Investment Case Asks - Monthly'!N6),"",'Investment Case Asks - Monthly'!N6) | O6: =IF(ISBLANK('Investment Case Asks - Monthly'!AA6),"",'Investment Case Asks - Monthly'!AA6) | P6: =IF(ISBLANK('Investment Case Asks - Monthly'!AN6),"",'Investment Case Asks - Monthly'!AN6) | Q6: =IF(ISBLANK('Investment Case Asks - Monthly'!BA6),"",'Investment Case Asks - Monthly'!BA6) | R6: =IF(ISBLANK('Investment Case Asks - Monthly'!BB6),"",'Investment Case Asks - Monthly'!BB6) | T6: Non-Payroll | U6: =D44 -> 0 | V6: =E44 -> 0 | W6: =F44 -> 0
A7: =IF(ISBLANK('Investment Case Asks - Monthly'!A7),"",'Investment Case Asks - Monthly'!A7) | B7: =IF(ISBLANK('Investment Case Asks - Monthly'!B7),"",'Investment Case Asks - Monthly'!B7) | C7: =IF(ISBLANK('Investment Case Asks - Monthly'!C7),"",'Investment Case Asks - Monthly'!C7) | D7: =IF(ISBLANK('Investment Case Asks - Monthly'!D7),"",'Investment Case Asks - Monthly'!D7) | E7: =IF(ISBLANK('Investment Case Asks - Monthly'!E7),"",'Investment Case Asks - Monthly'!E7) | F7: =IF(ISBLANK('Investment Case Asks - Monthly'!F7),"",'Investment Case Asks - Monthly'!F7) | G7: =IF(ISBLANK('Investment Case Asks - Monthly'!G7),"",'Investment Case Asks - Monthly'!G7) | H7: =IF(ISBLANK('Investment Case Asks - Monthly'!H7),"",'Investment Case Asks - Monthly'!H7) | ... N7: =IF(ISBLANK('Investment Case Asks - Monthly'!N7),"",'Investment Case Asks - Monthly'!N7) | O7: =IF(ISBLANK('Investment Case Asks - Monthly'!AA7),"",'Investment Case Asks - Monthly'!AA7) | P7: =IF(ISBLANK('Investment Case Asks - Monthly'!AN7),"",'Investment Case Asks - Monthly'!AN7) | Q7: =IF(ISBLANK('Investment Case Asks - Monthly'!BA7),"",'Investment Case Asks - Monthly'!BA7) | R7: =IF(ISBLANK('Investment Case Asks - Monthly'!BB7),"",'Investment Case Asks - Monthly'!BB7) | T7: Total Incremental Spend | U7: =SUM(U5:U6) -> 0 | V7: =SUM(V5:V6) -> 0 | W7: =SUM(W5:W6) -> 0
A8: =IF(ISBLANK('Investment Case Asks - Monthly'!A8),"",'Investment Case Asks - Monthly'!A8) | B8: =IF(ISBLANK('Investment Case Asks - Monthly'!B8),"",'Investment Case Asks - Monthly'!B8) | C8: =IF(ISBLANK('Investment Case Asks - Monthly'!C8),"",'Investment Case Asks - Monthly'!C8) | D8: =IF(ISBLANK('Investment Case Asks - Monthly'!D8),"",'Investment Case Asks - Monthly'!D8) | E8: =IF(ISBLANK('Investment Case Asks - Monthly'!E8),"",'Investment Case Asks - Monthly'!E8) | F8: =IF(ISBLANK('Investment Case Asks - Monthly'!F8),"",'Investment Case Asks - Monthly'!F8) | G8: =IF(ISBLANK('Investment Case Asks - Monthly'!G8),"",'Investment Case Asks - Monthly'!G8) | H8: =IF(ISBLANK('Investment Case Asks - Monthly'!H8),"",'Investment Case Asks - Monthly'!H8) | ... N8: =IF(ISBLANK('Investment Case Asks - Monthly'!N8),"",'Investment Case Asks - Monthly'!N8) | O8: =IF(ISBLANK('Investment Case Asks - Monthly'!AA8),"",'Investment Case Asks - Monthly'!AA8) | P8: =IF(ISBLANK('Investment Case Asks - Monthly'!AN8),"",'Investment Case Asks - Monthly'!AN8) | Q8: =IF(ISBLANK('Investment Case Asks - Monthly'!BA8),"",'Investment Case Asks - Monthly'!BA8) | R8: =IF(ISBLANK('Investment Case Asks - Monthly'!BB8),"",'Investment Case Asks - Monthly'!BB8)
A9: =IF(ISBLANK('Investment Case Asks - Monthly'!A9),"",'Investment Case Asks - Monthly'!A9) | B9: =IF(ISBLANK('Investment Case Asks - Monthly'!B9),"",'Investment Case Asks - Monthly'!B9) | C9: =IF(ISBLANK('Investment Case Asks - Monthly'!C9),"",'Investment Case Asks - Monthly'!C9) | D9: =IF(ISBLANK('Investment Case Asks - Monthly'!D9),"",'Investment Case Asks - Monthly'!D9) | E9: =IF(ISBLANK('Investment Case Asks - Monthly'!E9),"",'Investment Case Asks - Monthly'!E9) | F9: =IF(ISBLANK('Investment Case Asks - Monthly'!F9),"",'Investment Case Asks - Monthly'!F9) | G9: =IF(ISBLANK('Investment Case Asks - Monthly'!G9),"",'Investment Case Asks - Monthly'!G9) | H9: =IF(ISBLANK('Investment Case Asks - Monthly'!H9),"",'Investment Case Asks - Monthly'!H9) | ... N9: =IF(ISBLANK('Investment Case Asks - Monthly'!N9),"",'Investment Case Asks - Monthly'!N9) | O9: =IF(ISBLANK('Investment Case Asks - Monthly'!AA9),"",'Investment Case Asks - Monthly'!AA9) | P9: =IF(ISBLANK('Investment Case Asks - Monthly'!AN9),"",'Investment Case Asks - Monthly'!AN9) | Q9: =IF(ISBLANK('Investment Case Asks - Monthly'!BA9),"",'Investment Case Asks - Monthly'!BA9) | R9: =IF(ISBLANK('Investment Case Asks - Monthly'!BB9),"",'Investment Case Asks - Monthly'!BB9)
A10: =IF(ISBLANK('Investment Case Asks - Monthly'!A10),"",'Investment Case Asks - Monthly'!A10) | B10: =IF(ISBLANK('Investment Case Asks - Monthly'!B10),"",'Investment Case Asks - Monthly'!B10) | C10: =IF(ISBLANK('Investment Case Asks - Monthly'!C10),"",'Investment Case Asks - Monthly'!C10) | D10: =IF(ISBLANK('Investment Case Asks - Monthly'!D10),"",'Investment Case Asks - Monthly'!D10) | E10: =IF(ISBLANK('Investment Case Asks - Monthly'!E10),"",'Investment Case Asks - Monthly'!E10) | F10: =IF(ISBLANK('Investment Case Asks - Monthly'!F10),"",'Investment Case Asks - Monthly'!F10) | G10: =IF(ISBLANK('Investment Case Asks - Monthly'!G10),"",'Investment Case Asks - Monthly'!G10) | H10: =IF(ISBLANK('Investment Case Asks - Monthly'!H10),"",'Investment Case Asks - Monthly'!H10) | ... N10: =IF(ISBLANK('Investment Case Asks - Monthly'!N10),"",'Investment Case Asks - Monthly'!N10) | O10: =IF(ISBLANK('Investment Case Asks - Monthly'!AA10),"",'Investment Case Asks - Monthly'!AA10) | P10: =IF(ISBLANK('Investment Case Asks - Monthly'!AN10),"",'Investment Case Asks - Monthly'!AN10) | Q10: =IF(ISBLANK('Investment Case Asks - Monthly'!BA10),"",'Investment Case Asks - Monthly'!BA10) | R10: =IF(ISBLANK('Investment Case Asks - Monthly'!BB10),"",'Investment Case Asks - Monthly'!BB10)
A11: =IF(ISBLANK('Investment Case Asks - Monthly'!A11),"",'Investment Case Asks - Monthly'!A11) | B11: =IF(ISBLANK('Investment Case Asks - Monthly'!B11),"",'Investment Case Asks - Monthly'!B11) | C11: =IF(ISBLANK('Investment Case Asks - Monthly'!C11),"",'Investment Case Asks - Monthly'!C11) | D11: =IF(ISBLANK('Investment Case Asks - Monthly'!D11),"",'Investment Case Asks - Monthly'!D11) | E11: =IF(ISBLANK('Investment Case Asks - Monthly'!E11),"",'Investment Case Asks - Monthly'!E11) | F11: =IF(ISBLANK('Investment Case Asks - Monthly'!F11),"",'Investment Case Asks - Monthly'!F11) | G11: =IF(ISBLANK('Investment Case Asks - Monthly'!G11),"",'Investment Case Asks - Monthly'!G11) | H11: =IF(ISBLANK('Investment Case Asks - Monthly'!H11),"",'Investment Case Asks - Monthly'!H11) | ... N11: =IF(ISBLANK('Investment Case Asks - Monthly'!N11),"",'Investment Case Asks - Monthly'!N11) | O11: =IF(ISBLANK('Investment Case Asks - Monthly'!AA11),"",'Investment Case Asks - Monthly'!AA11) | P11: =IF(ISBLANK('Investment Case Asks - Monthly'!AN11),"",'Investment Case Asks - Monthly'!AN11) | Q11: =IF(ISBLANK('Investment Case Asks - Monthly'!BA11),"",'Investment Case Asks - Monthly'!BA11) | R11: =IF(ISBLANK('Investment Case Asks - Monthly'!BB11),"",'Investment Case Asks - Monthly'!BB11)
A12: =IF(ISBLANK('Investment Case Asks - Monthly'!A12),"",'Investment Case Asks - Monthly'!A12) | B12: =IF(ISBLANK('Investment Case Asks - Monthly'!B12),"",'Investment Case Asks - Monthly'!B12) | C12: =IF(ISBLANK('Investment Case Asks - Monthly'!C12),"",'Investment Case Asks - Monthly'!C12) | D12: =IF(ISBLANK('Investment Case Asks - Monthly'!D12),"",'Investment Case Asks - Monthly'!D12) | E12: =IF(ISBLANK('Investment Case Asks - Monthly'!E12),"",'Investment Case Asks - Monthly'!E12) | F12: =IF(ISBLANK('Investment Case Asks - Monthly'!F12),"",'Investment Case Asks - Monthly'!F12) | G12: =IF(ISBLANK('Investment Case Asks - Monthly'!G12),"",'Investment Case Asks - Monthly'!G12) | H12: =IF(ISBLANK('Investment Case Asks - Monthly'!H12),"",'Investment Case Asks - Monthly'!H12) | ... N12: =IF(ISBLANK('Investment Case Asks - Monthly'!N12),"",'Investment Case Asks - Monthly'!N12) | O12: =IF(ISBLANK('Investment Case Asks - Monthly'!AA12),"",'Investment Case Asks - Monthly'!AA12) | P12: =IF(ISBLANK('Investment Case Asks - Monthly'!AN12),"",'Investment Case Asks - Monthly'!AN12) | Q12: =IF(ISBLANK('Investment Case Asks - Monthly'!BA12),"",'Investment Case Asks - Monthly'!BA12) | R12: =IF(ISBLANK('Investment Case Asks - Monthly'!BB12),"",'Investment Case Asks - Monthly'!BB12)
A13: =IF(ISBLANK('Investment Case Asks - Monthly'!A13),"",'Investment Case Asks - Monthly'!A13) | B13: =IF(ISBLANK('Investment Case Asks - Monthly'!B13),"",'Investment Case Asks - Monthly'!B13) | C13: =IF(ISBLANK('Investment Case Asks - Monthly'!C13),"",'Investment Case Asks - Monthly'!C13) | D13: =IF(ISBLANK('Investment Case Asks - Monthly'!D13),"",'Investment Case Asks - Monthly'!D13) | E13: =IF(ISBLANK('Investment Case Asks - Monthly'!E13),"",'Investment Case Asks - Monthly'!E13) | F13: =IF(ISBLANK('Investment Case Asks - Monthly'!F13),"",'Investment Case Asks - Monthly'!F13) | G13: =IF(ISBLANK('Investment Case Asks - Monthly'!G13),"",'Investment Case Asks - Monthly'!G13) | H13: =IF(ISBLANK('Investment Case Asks - Monthly'!H13),"",'Investment Case Asks - Monthly'!H13) | ... N13: =IF(ISBLANK('Investment Case Asks - Monthly'!N13),"",'Investment Case Asks - Monthly'!N13) | O13: =IF(ISBLANK('Investment Case Asks - Monthly'!AA13),"",'Investment Case Asks - Monthly'!AA13) | P13: =IF(ISBLANK('Investment Case Asks - Monthly'!AN13),"",'Investment Case Asks - Monthly'!AN13) | Q13: =IF(ISBLANK('Investment Case Asks - Monthly'!BA13),"",'Investment Case Asks - Monthly'!BA13) | R13: =IF(ISBLANK('Investment Case Asks - Monthly'!BB13),"",'Investment Case Asks - Monthly'!BB13)
A14: =IF(ISBLANK('Investment Case Asks - Monthly'!A14),"",'Investment Case Asks - Monthly'!A14) | B14: =IF(ISBLANK('Investment Case Asks - Monthly'!B14),"",'Investment Case Asks - Monthly'!B14) | C14: =IF(ISBLANK('Investment Case Asks - Monthly'!C14),"",'Investment Case Asks - Monthly'!C14) | D14: =IF(ISBLANK('Investment Case Asks - Monthly'!D14),"",'Investment Case Asks - Monthly'!D14) | E14: =IF(ISBLANK('Investment Case Asks - Monthly'!E14),"",'Investment Case Asks - Monthly'!E14) | F14: =IF(ISBLANK('Investment Case Asks - Monthly'!F14),"",'Investment Case Asks - Monthly'!F14) | G14: =IF(ISBLANK('Investment Case Asks - Monthly'!G14),"",'Investment Case Asks - Monthly'!G14) | H14: =IF(ISBLANK('Investment Case Asks - Monthly'!H14),"",'Investment Case Asks - Monthly'!H14) | ... N14: =IF(ISBLANK('Investment Case Asks - Monthly'!N14),"",'Investment Case Asks - Monthly'!N14) | O14: =IF(ISBLANK('Investment Case Asks - Monthly'!AA14),"",'Investment Case Asks - Monthly'!AA14) | P14: =IF(ISBLANK('Investment Case Asks - Monthly'!AN14),"",'Investment Case Asks - Monthly'!AN14) | Q14: =IF(ISBLANK('Investment Case Asks - Monthly'!BA14),"",'Investment Case Asks - Monthly'!BA14) | R14: =IF(ISBLANK('Investment Case Asks - Monthly'!BB14),"",'Investment Case Asks - Monthly'!BB14)
A15: =IF(ISBLANK('Investment Case Asks - Monthly'!A15),"",'Investment Case Asks - Monthly'!A15) | B15: =IF(ISBLANK('Investment Case Asks - Monthly'!B15),"",'Investment Case Asks - Monthly'!B15) | C15: =IF(ISBLANK('Investment Case Asks - Monthly'!C15),"",'Investment Case Asks - Monthly'!C15) | D15: =IF(ISBLANK('Investment Case Asks - Monthly'!D15),"",'Investment Case Asks - Monthly'!D15) | E15: =IF(ISBLANK('Investment Case Asks - Monthly'!E15),"",'Investment Case Asks - Monthly'!E15) | F15: =IF(ISBLANK('Investment Case Asks - Monthly'!F15),"",'Investment Case Asks - Monthly'!F15) | G15: =IF(ISBLANK('Investment Case Asks - Monthly'!G15),"",'Investment Case Asks - Monthly'!G15) | H15: =IF(ISBLANK('Investment Case Asks - Monthly'!H15),"",'Investment Case Asks - Monthly'!H15) | ... N15: =IF(ISBLANK('Investment Case Asks - Monthly'!N15),"",'Investment Case Asks - Monthly'!N15) | O15: =IF(ISBLANK('Investment Case Asks - Monthly'!AA15),"",'Investment Case Asks - Monthly'!AA15) | P15: =IF(ISBLANK('Investment Case Asks - Monthly'!AN15),"",'Investment Case Asks - Monthly'!AN15) | Q15: =IF(ISBLANK('Investment Case Asks - Monthly'!BA15),"",'Investment Case Asks - Monthly'!BA15) | R15: =IF(ISBLANK('Investment Case Asks - Monthly'!BB15),"",'Investment Case Asks - Monthly'!BB15)
A16: =IF(ISBLANK('Investment Case Asks - Monthly'!A16),"",'Investment Case Asks - Monthly'!A16) | B16: =IF(ISBLANK('Investment Case Asks - Monthly'!B16),"",'Investment Case Asks - Monthly'!B16) | C16: =IF(ISBLANK('Investment Case Asks - Monthly'!C16),"",'Investment Case Asks - Monthly'!C16) | D16: =IF(ISBLANK('Investment Case Asks - Monthly'!D16),"",'Investment Case Asks - Monthly'!D16) | E16: =IF(ISBLANK('Investment Case Asks - Monthly'!E16),"",'Investment Case Asks - Monthly'!E16) | F16: =IF(ISBLANK('Investment Case Asks - Monthly'!F16),"",'Investment Case Asks - Monthly'!F16) | G16: =IF(ISBLANK('Investment Case Asks - Monthly'!G16),"",'Investment Case Asks - Monthly'!G16) | H16: =IF(ISBLANK('Investment Case Asks - Monthly'!H16),"",'Investment Case Asks - Monthly'!H16) | ... N16: =IF(ISBLANK('Investment Case Asks - Monthly'!N16),"",'Investment Case Asks - Monthly'!N16) | O16: =IF(ISBLANK('Investment Case Asks - Monthly'!AA16),"",'Investment Case Asks - Monthly'!AA16) | P16: =IF(ISBLANK('Investment Case Asks - Monthly'!AN16),"",'Investment Case Asks - Monthly'!AN16) | Q16: =IF(ISBLANK('Investment Case Asks - Monthly'!BA16),"",'Investment Case Asks - Monthly'!BA16) | R16: =IF(ISBLANK('Investment Case Asks - Monthly'!BB16),"",'Investment Case Asks - Monthly'!BB16)
A17: =IF(ISBLANK('Investment Case Asks - Monthly'!A17),"",'Investment Case Asks - Monthly'!A17) | B17: =IF(ISBLANK('Investment Case Asks - Monthly'!B17),"",'Investment Case Asks - Monthly'!B17) | C17: =IF(ISBLANK('Investment Case Asks - Monthly'!C17),"",'Investment Case Asks - Monthly'!C17) | D17: =IF(ISBLANK('Investment Case Asks - Monthly'!D17),"",'Investment Case Asks - Monthly'!D17) | E17: =IF(ISBLANK('Investment Case Asks - Monthly'!E17),"",'Investment Case Asks - Monthly'!E17) | F17: =IF(ISBLANK('Investment Case Asks - Monthly'!F17),"",'Investment Case Asks - Monthly'!F17) | G17: =IF(ISBLANK('Investment Case Asks - Monthly'!G17),"",'Investment Case Asks - Monthly'!G17) | H17: =IF(ISBLANK('Investment Case Asks - Monthly'!H17),"",'Investment Case Asks - Monthly'!H17) | ... N17: =IF(ISBLANK('Investment Case Asks - Monthly'!N17),"",'Investment Case Asks - Monthly'!N17) | O17: =IF(ISBLANK('Investment Case Asks - Monthly'!AA17),"",'Investment Case Asks - Monthly'!AA17) | P17: =IF(ISBLANK('Investment Case Asks - Monthly'!AN17),"",'Investment Case Asks - Monthly'!AN17) | Q17: =IF(ISBLANK('Investment Case Asks - Monthly'!BA17),"",'Investment Case Asks - Monthly'!BA17) | R17: =IF(ISBLANK('Investment Case Asks - Monthly'!BB17),"",'Investment Case Asks - Monthly'!BB17)
A18: =IF(ISBLANK('Investment Case Asks - Monthly'!A18),"",'Investment Case Asks - Monthly'!A18) | B18: =IF(ISBLANK('Investment Case Asks - Monthly'!B18),"",'Investment Case Asks - Monthly'!B18) | C18: =IF(ISBLANK('Investment Case Asks - Monthly'!C18),"",'Investment Case Asks - Monthly'!C18) | D18: =IF(ISBLANK('Investment Case Asks - Monthly'!D18),"",'Investment Case Asks - Monthly'!D18) | E18: =IF(ISBLANK('Investment Case Asks - Monthly'!E18),"",'Investment Case Asks - Monthly'!E18) | F18: =IF(ISBLANK('Investment Case Asks - Monthly'!F18),"",'Investment Case Asks - Monthly'!F18) | G18: =IF(ISBLANK('Investment Case Asks - Monthly'!G18),"",'Investment Case Asks - Monthly'!G18) | H18: =IF(ISBLANK('Investment Case Asks - Monthly'!H18),"",'Investment Case Asks - Monthly'!H18) | ... N18: =IF(ISBLANK('Investment Case Asks - Monthly'!N18),"",'Investment Case Asks - Monthly'!N18) | O18: =IF(ISBLANK('Investment Case Asks - Monthly'!AA18),"",'Investment Case Asks - Monthly'!AA18) | P18: =IF(ISBLANK('Investment Case Asks - Monthly'!AN18),"",'Investment Case Asks - Monthly'!AN18) | Q18: =IF(ISBLANK('Investment Case Asks - Monthly'!BA18),"",'Investment Case Asks - Monthly'!BA18) | R18: =IF(ISBLANK('Investment Case Asks - Monthly'!BB18),"",'Investment Case Asks - Monthly'!BB18)
A19: =IF(ISBLANK('Investment Case Asks - Monthly'!A19),"",'Investment Case Asks - Monthly'!A19) | B19: =IF(ISBLANK('Investment Case Asks - Monthly'!B19),"",'Investment Case Asks - Monthly'!B19) | C19: =IF(ISBLANK('Investment Case Asks - Monthly'!C19),"",'Investment Case Asks - Monthly'!C19) | D19: =IF(ISBLANK('Investment Case Asks - Monthly'!D19),"",'Investment Case Asks - Monthly'!D19) | E19: =IF(ISBLANK('Investment Case Asks - Monthly'!E19),"",'Investment Case Asks - Monthly'!E19) | F19: =IF(ISBLANK('Investment Case Asks - Monthly'!F19),"",'Investment Case Asks - Monthly'!F19) | G19: =IF(ISBLANK('Investment Case Asks - Monthly'!G19),"",'Investment Case Asks - Monthly'!G19) | H19: =IF(ISBLANK('Investment Case Asks - Monthly'!H19),"",'Investment Case Asks - Monthly'!H19) | ... N19: =IF(ISBLANK('Investment Case Asks - Monthly'!N19),"",'Investment Case Asks - Monthly'!N19) | O19: =IF(ISBLANK('Investment Case Asks - Monthly'!AA19),"",'Investment Case Asks - Monthly'!AA19) | P19: =IF(ISBLANK('Investment Case Asks - Monthly'!AN19),"",'Investment Case Asks - Monthly'!AN19) | Q19: =IF(ISBLANK('Investment Case Asks - Monthly'!BA19),"",'Investment Case Asks - Monthly'!BA19) | R19: =IF(ISBLANK('Investment Case Asks - Monthly'!BB19),"",'Investment Case Asks - Monthly'!BB19)
A20: =IF(ISBLANK('Investment Case Asks - Monthly'!A20),"",'Investment Case Asks - Monthly'!A20) | B20: =IF(ISBLANK('Investment Case Asks - Monthly'!B20),"",'Investment Case Asks - Monthly'!B20) | C20: =IF(ISBLANK('Investment Case Asks - Monthly'!C20),"",'Investment Case Asks - Monthly'!C20) | D20: =IF(ISBLANK('Investment Case Asks - Monthly'!D20),"",'Investment Case Asks - Monthly'!D20) | E20: =IF(ISBLANK('Investment Case Asks - Monthly'!E20),"",'Investment Case Asks - Monthly'!E20) | F20: =IF(ISBLANK('Investment Case Asks - Monthly'!F20),"",'Investment Case Asks - Monthly'!F20) | G20: =IF(ISBLANK('Investment Case Asks - Monthly'!G20),"",'Investment Case Asks - Monthly'!G20) | H20: =IF(ISBLANK('Investment Case Asks - Monthly'!H20),"",'Investment Case Asks - Monthly'!H20) | ... N20: =IF(ISBLANK('Investment Case Asks - Monthly'!N20),"",'Investment Case Asks - Monthly'!N20) | O20: =IF(ISBLANK('Investment Case Asks - Monthly'!AA20),"",'Investment Case Asks - Monthly'!AA20) | P20: =IF(ISBLANK('Investment Case Asks - Monthly'!AN20),"",'Investment Case Asks - Monthly'!AN20) | Q20: =IF(ISBLANK('Investment Case Asks - Monthly'!BA20),"",'Investment Case Asks - Monthly'!BA20) | R20: =IF(ISBLANK('Investment Case Asks - Monthly'!BB20),"",'Investment Case Asks - Monthly'!BB20)
A22: Total Payroll / Headcount Incremental Spend | G22: =IF(ISBLANK('Investment Case Asks - Monthly'!G22),"",'Investment Case Asks - Monthly'!G22) -> 0 | I22: =IF(ISBLANK('Investment Case Asks - Monthly'!I22),"",'Investment Case Asks - Monthly'!I22) -> 0 | J22: =IF(ISBLANK('Investment Case Asks - Monthly'!J22),"",'Investment Case Asks - Monthly'!J22) -> 0 | K22: =IF(ISBLANK('Investment Case Asks - Monthly'!K22),"",'Investment Case Asks - Monthly'!K22) -> 0 | L22: =IF(ISBLANK('Investment Case Asks - Monthly'!L22),"",'Investment Case Asks - Monthly'!L22) -> 0 | M22: =IF(ISBLANK('Investment Case Asks - Monthly'!M22),"",'Investment Case Asks - Monthly'!M22) -> 0 | N22: =IF(ISBLANK('Investment Case Asks - Monthly'!N22),"",'Investment Case Asks - Monthly'!N22) -> 0 | O22: =IF(ISBLANK('Investment Case Asks - Monthly'!AA22),"",'Investment Case Asks - Monthly'!AA22) -> 0 | P22: =IF(ISBLANK('Investment Case Asks - Monthly'!AN22),"",'Investment Case Asks - Monthly'!AN22) -> 0 | Q22: =IF(ISBLANK('Investment Case Asks - Monthly'!BA22),"",'Investment Case Asks - Monthly'!BA22) -> 0
A26: Essentials Bonus / Contract Labor / Non-Payroll Incremental Spend
A27: Expense Description | B27: Type of Expense | C27: Vendor | D27: 2027 Incremental Spend | E27: 2028 Incremental Spend | F27: 2029 Incremental Spend | G27: Notes / Rationale
A28: =IF(ISBLANK('Investment Case Asks - Monthly'!A28),"",'Investment Case Asks - Monthly'!A28) | B28: =IF(ISBLANK('Investment Case Asks - Monthly'!B28),"",'Investment Case Asks - Monthly'!B28) | C28: =IF(ISBLANK('Investment Case Asks - Monthly'!C28),"",'Investment Case Asks - Monthly'!C28) | D28: =IF(ISBLANK('Investment Case Asks - Monthly'!Q28),"",'Investment Case Asks - Monthly'!Q28) | E28: =IF(ISBLANK('Investment Case Asks - Monthly'!AD28),"",'Investment Case Asks - Monthly'!AD28) | F28: =IF(ISBLANK('Investment Case Asks - Monthly'!AQ28),"",'Investment Case Asks - Monthly'!AQ28) | G28: =IF(ISBLANK('Investment Case Asks - Monthly'!AR28),"",'Investment Case Asks - Monthly'!AR28)
A29: =IF(ISBLANK('Investment Case Asks - Monthly'!A29),"",'Investment Case Asks - Monthly'!A29) | B29: =IF(ISBLANK('Investment Case Asks - Monthly'!B29),"",'Investment Case Asks - Monthly'!B29) | C29: =IF(ISBLANK('Investment Case Asks - Monthly'!C29),"",'Investment Case Asks - Monthly'!C29) | D29: =IF(ISBLANK('Investment Case Asks - Monthly'!Q29),"",'Investment Case Asks - Monthly'!Q29) | E29: =IF(ISBLANK('Investment Case Asks - Monthly'!AD29),"",'Investment Case Asks - Monthly'!AD29) | F29: =IF(ISBLANK('Investment Case Asks - Monthly'!AQ29),"",'Investment Case Asks - Monthly'!AQ29) | G29: =IF(ISBLANK('Investment Case Asks - Monthly'!AR29),"",'Investment Case Asks - Monthly'!AR29)
A30: =IF(ISBLANK('Investment Case Asks - Monthly'!A30),"",'Investment Case Asks - Monthly'!A30) | B30: =IF(ISBLANK('Investment Case Asks - Monthly'!B30),"",'Investment Case Asks - Monthly'!B30) | C30: =IF(ISBLANK('Investment Case Asks - Monthly'!C30),"",'Investment Case Asks - Monthly'!C30) | D30: =IF(ISBLANK('Investment Case Asks - Monthly'!Q30),"",'Investment Case Asks - Monthly'!Q30) | E30: =IF(ISBLANK('Investment Case Asks - Monthly'!AD30),"",'Investment Case Asks - Monthly'!AD30) | F30: =IF(ISBLANK('Investment Case Asks - Monthly'!AQ30),"",'Investment Case Asks - Monthly'!AQ30) | G30: =IF(ISBLANK('Investment Case Asks - Monthly'!AR30),"",'Investment Case Asks - Monthly'!AR30)
A31: =IF(ISBLANK('Investment Case Asks - Monthly'!A31),"",'Investment Case Asks - Monthly'!A31) | B31: =IF(ISBLANK('Investment Case Asks - Monthly'!B31),"",'Investment Case Asks - Monthly'!B31) | C31: =IF(ISBLANK('Investment Case Asks - Monthly'!C31),"",'Investment Case Asks - Monthly'!C31) | D31: =IF(ISBLANK('Investment Case Asks - Monthly'!Q31),"",'Investment Case Asks - Monthly'!Q31) | E31: =IF(ISBLANK('Investment Case Asks - Monthly'!AD31),"",'Investment Case Asks - Monthly'!AD31) | F31: =IF(ISBLANK('Investment Case Asks - Monthly'!AQ31),"",'Investment Case Asks - Monthly'!AQ31) | G31: =IF(ISBLANK('Investment Case Asks - Monthly'!AR31),"",'Investment Case Asks - Monthly'!AR31)
A32: =IF(ISBLANK('Investment Case Asks - Monthly'!A32),"",'Investment Case Asks - Monthly'!A32) | B32: =IF(ISBLANK('Investment Case Asks - Monthly'!B32),"",'Investment Case Asks - Monthly'!B32) | C32: =IF(ISBLANK('Investment Case Asks - Monthly'!C32),"",'Investment Case Asks - Monthly'!C32) | D32: =IF(ISBLANK('Investment Case Asks - Monthly'!Q32),"",'Investment Case Asks - Monthly'!Q32) | E32: =IF(ISBLANK('Investment Case Asks - Monthly'!AD32),"",'Investment Case Asks - Monthly'!AD32) | F32: =IF(ISBLANK('Investment Case Asks - Monthly'!AQ32),"",'Investment Case Asks - Monthly'!AQ32) | G32: =IF(ISBLANK('Investment Case Asks - Monthly'!AR32),"",'Investment Case Asks - Monthly'!AR32)
A33: =IF(ISBLANK('Investment Case Asks - Monthly'!A33),"",'Investment Case Asks - Monthly'!A33) | B33: =IF(ISBLANK('Investment Case Asks - Monthly'!B33),"",'Investment Case Asks - Monthly'!B33) | C33: =IF(ISBLANK('Investment Case Asks - Monthly'!C33),"",'Investment Case Asks - Monthly'!C33) | D33: =IF(ISBLANK('Investment Case Asks - Monthly'!Q33),"",'Investment Case Asks - Monthly'!Q33) | E33: =IF(ISBLANK('Investment Case Asks - Monthly'!AD33),"",'Investment Case Asks - Monthly'!AD33) | F33: =IF(ISBLANK('Investment Case Asks - Monthly'!AQ33),"",'Investment Case Asks - Monthly'!AQ33) | G33: =IF(ISBLANK('Investment Case Asks - Monthly'!AR33),"",'Investment Case Asks - Monthly'!AR33)
A34: =IF(ISBLANK('Investment Case Asks - Monthly'!A34),"",'Investment Case Asks - Monthly'!A34) | B34: =IF(ISBLANK('Investment Case Asks - Monthly'!B34),"",'Investment Case Asks - Monthly'!B34) | C34: =IF(ISBLANK('Investment Case Asks - Monthly'!C34),"",'Investment Case Asks - Monthly'!C34) | D34: =IF(ISBLANK('Investment Case Asks - Monthly'!Q34),"",'Investment Case Asks - Monthly'!Q34) | E34: =IF(ISBLANK('Investment Case Asks - Monthly'!AD34),"",'Investment Case Asks - Monthly'!AD34) | F34: =IF(ISBLANK('Investment Case Asks - Monthly'!AQ34),"",'Investment Case Asks - Monthly'!AQ34) | G34: =IF(ISBLANK('Investment Case Asks - Monthly'!AR34),"",'Investment Case Asks - Monthly'!AR34)
A35: =IF(ISBLANK('Investment Case Asks - Monthly'!A35),"",'Investment Case Asks - Monthly'!A35) | B35: =IF(ISBLANK('Investment Case Asks - Monthly'!B35),"",'Investment Case Asks - Monthly'!B35) | C35: =IF(ISBLANK('Investment Case Asks - Monthly'!C35),"",'Investment Case Asks - Monthly'!C35) | D35: =IF(ISBLANK('Investment Case Asks - Monthly'!Q35),"",'Investment Case Asks - Monthly'!Q35) | E35: =IF(ISBLANK('Investment Case Asks - Monthly'!AD35),"",'Investment Case Asks - Monthly'!AD35) | F35: =IF(ISBLANK('Investment Case Asks - Monthly'!AQ35),"",'Investment Case Asks - Monthly'!AQ35) | G35: =IF(ISBLANK('Investment Case Asks - Monthly'!AR35),"",'Investment Case Asks - Monthly'!AR35)
A36: =IF(ISBLANK('Investment Case Asks - Monthly'!A36),"",'Investment Case Asks - Monthly'!A36) | B36: =IF(ISBLANK('Investment Case Asks - Monthly'!B36),"",'Investment Case Asks - Monthly'!B36) | C36: =IF(ISBLANK('Investment Case Asks - Monthly'!C36),"",'Investment Case Asks - Monthly'!C36) | D36: =IF(ISBLANK('Investment Case Asks - Monthly'!Q36),"",'Investment Case Asks - Monthly'!Q36) | E36: =IF(ISBLANK('Investment Case Asks - Monthly'!AD36),"",'Investment Case Asks - Monthly'!AD36) | F36: =IF(ISBLANK('Investment Case Asks - Monthly'!AQ36),"",'Investment Case Asks - Monthly'!AQ36) | G36: =IF(ISBLANK('Investment Case Asks - Monthly'!AR36),"",'Investment Case Asks - Monthly'!AR36)
A37: =IF(ISBLANK('Investment Case Asks - Monthly'!A37),"",'Investment Case Asks - Monthly'!A37) | B37: =IF(ISBLANK('Investment Case Asks - Monthly'!B37),"",'Investment Case Asks - Monthly'!B37) | C37: =IF(ISBLANK('Investment Case Asks - Monthly'!C37),"",'Investment Case Asks - Monthly'!C37) | D37: =IF(ISBLANK('Investment Case Asks - Monthly'!Q37),"",'Investment Case Asks - Monthly'!Q37) | E37: =IF(ISBLANK('Investment Case Asks - Monthly'!AD37),"",'Investment Case Asks - Monthly'!AD37) | F37: =IF(ISBLANK('Investment Case Asks - Monthly'!AQ37),"",'Investment Case Asks - Monthly'!AQ37) | G37: =IF(ISBLANK('Investment Case Asks - Monthly'!AR37),"",'Investment Case Asks - Monthly'!AR37)
A38: =IF(ISBLANK('Investment Case Asks - Monthly'!A38),"",'Investment Case Asks - Monthly'!A38) | B38: =IF(ISBLANK('Investment Case Asks - Monthly'!B38),"",'Investment Case Asks - Monthly'!B38) | C38: =IF(ISBLANK('Investment Case Asks - Monthly'!C38),"",'Investment Case Asks - Monthly'!C38) | D38: =IF(ISBLANK('Investment Case Asks - Monthly'!Q38),"",'Investment Case Asks - Monthly'!Q38) | E38: =IF(ISBLANK('Investment Case Asks - Monthly'!AD38),"",'Investment Case Asks - Monthly'!AD38) | F38: =IF(ISBLANK('Investment Case Asks - Monthly'!AQ38),"",'Investment Case Asks - Monthly'!AQ38) | G38: =IF(ISBLANK('Investment Case Asks - Monthly'!AR38),"",'Investment Case Asks - Monthly'!AR38)
A39: =IF(ISBLANK('Investment Case Asks - Monthly'!A39),"",'Investment Case Asks - Monthly'!A39) | B39: =IF(ISBLANK('Investment Case Asks - Monthly'!B39),"",'Investment Case Asks - Monthly'!B39) | C39: =IF(ISBLANK('Investment Case Asks - Monthly'!C39),"",'Investment Case Asks - Monthly'!C39) | D39: =IF(ISBLANK('Investment Case Asks - Monthly'!Q39),"",'Investment Case Asks - Monthly'!Q39) | E39: =IF(ISBLANK('Investment Case Asks - Monthly'!AD39),"",'Investment Case Asks - Monthly'!AD39) | F39: =IF(ISBLANK('Investment Case Asks - Monthly'!AQ39),"",'Investment Case Asks - Monthly'!AQ39) | G39: =IF(ISBLANK('Investment Case Asks - Monthly'!AR39),"",'Investment Case Asks - Monthly'!AR39)
... A42: =IF(ISBLANK('Investment Case Asks - Monthly'!A42),"",'Investment Case Asks - Monthly'!A42) | B42: =IF(ISBLANK('Investment Case Asks - Monthly'!B42),"",'Investment Case Asks - Monthly'!B42) | C42: =IF(ISBLANK('Investment Case Asks - Monthly'!C42),"",'Investment Case Asks - Monthly'!C42) | D42: =IF(ISBLANK('Investment Case Asks - Monthly'!Q42),"",'Investment Case Asks - Monthly'!Q42) | E42: =IF(ISBLANK('Investment Case Asks - Monthly'!AD42),"",'Investment Case Asks - Monthly'!AD42) | F42: =IF(ISBLANK('Investment Case Asks - Monthly'!AQ42),"",'Investment Case Asks - Monthly'!AQ42) | G42: =IF(ISBLANK('Investment Case Asks - Monthly'!AR42),"",'Investment Case Asks - Monthly'!AR42)
A44: Total Essentials Bonus / Contract Labor / Non-Payroll Incremental Spend | D44: =SUM(D28:D42) -> 0 | E44: =SUM(E28:E42) -> 0 | F44: =SUM(F28:F42) -> 0

Sheet Investment Case Asks - Monthly
A1: Investment Case Asks - Incremental Spend Input
A3: Payroll / Headcount Incremental Spend
A4: Job Title | B4: Job Level | C4: Role / Hire | D4: Location (City/Country) | E4: Key Job Responsibilities | F4: Hire Date | G4: Base Salary | H4: Bonus % | I4: Bonus | J4: Payroll Taxes | K4: Benefits | L4: Vacation | M4: Other | N4: Annualized Spend | O4: Jan-27 | P4: Feb-27 | Q4: Mar-27 | R4: Apr-27 | S4: May-27 | T4: Jun-27 | U4: Jul-27 | V4: Aug-27 | W4: Sep-27 | X4: Oct-27 | Y4: Nov-27 | Z4: Dec-27 | AA4: 2027 Incremental Spend | AB4: Jan-28 | AC4: Feb-28 | AD4: Mar-28 | AE4: Apr-28 | AF4: May-28 | AG4: Jun-28 | AH4: Jul-28 | AI4: Aug-28 | AJ4: Sep-28 | AK4: Oct-28 | AL4: Nov-28 | AM4: Dec-28 | AN4: 2028 Incremental Spend | AO4: Jan-29 | AP4: Feb-29 | AQ4: Mar-29 | AR4: Apr-29 | AS4: May-29 | AT4: Jun-29 | AU4: Jul-29 | AV4: Aug-29 | AW4: Sep-29 | AX4: Oct-29 | AY4: Nov-29 | AZ4: Dec-29 | BA4: 2029 Incremental Spend | BB4: Notes / Rationale
I5: =IF(OR(COUNTA(tblPayrollIncrementalSpend2[[#This Row],[Job Title]:[Hire Date]])>0,AND(ROW()=ROW(G5),tblPayrollIncrementalSpend2[[#This Row],[Base Salary]]<>"")),N(tblPayrollIncrementalSpend2[[#This Row],[Base Salary]])*N(tblPayrollIncrementalSpend2[[#This Row],[Bonus %]]),"") | J5: =IF(OR(COUNTA(tblPayrollIncrementalSpend2[[#This Row],[Job Title]:[Hire Date]])>0,AND(ROW()=ROW(G5),tblPayrollIncrementalSpend2[[#This Row],[Base Salary]]<>"")),N(tblPayrollIncrementalSpend2[[#This Row],[Base Salary]])*'Base - Payroll'!$E$12,"") | K5: =IF(OR(COUNTA(tblPayrollIncrementalSpend2[[#This Row],[Job Title]:[Hire Date]])>0,AND(ROW()=ROW(G5),tblPayrollIncrementalSpend2[[#This Row],[Base Salary]]<>"")),N(tblPayrollIncrementalSpend2[[#This Row],[Base Salary]])*'Base - Payroll'!$E$13,"") | L5: =IF(OR(COUNTA(tblPayrollIncrementalSpend2[[#This Row],[Job Title]:[Hire Date]])>0,AND(ROW()=ROW(G5),tblPayrollIncrementalSpend2[[#This Row],[Base Salary]]<>"")),N(tblPayrollIncrementalSpend2[[#This Row],[Base Salary]])*'Base - Payroll'!$E$15,"") | M5: =IF(OR(COUNTA(tblPayrollIncrementalSpend2[[#This Row],[Job Title]:[Hire Date]])>0,AND(ROW()=ROW(G5),tblPayrollIncrementalSpend2[[#This Row],[Base Salary]]<>"")),N(tblPayrollIncrementalSpend2[[#This Row],[Base Salary]])*'Base - Payroll'!$E$16,"") | N5: =IF(OR(COUNTA(tblPayrollIncrementalSpend2[[#This Row],[Job Title]:[Hire Date]])>0,AND(ROW()=ROW(G5),tblPayrollIncrementalSpend2[[#This Row],[Base Salary]]<>"")),N(tblPayrollIncrementalSpend2[[#This Row],[Base Salary]])+SUM(tblPayrollIncrementalSpend2[[#This Row],[Bonus]:[Other]]),"") | O5: =_xlfn.LET(_xlpm.m,IF(ISNUMBER(O$4),DATE(YEAR(O$4),MONTH(O$4),1),DATEVALUE("1-"&O$4)),IF(OR(COUNTA($A5:$F5)>0,$G5<>""),$N5/12*IF($F5="",1,MAX(0,(EOMONTH(_xlpm.m,0)-MAX($F5,_xlpm.m)+1)/(EOMONTH(_xlpm.m,0)-_xlpm.m+1))),"")) | P5: =_xlfn.LET(_xlpm.m,IF(ISNUMBER(P$4),DATE(YEAR(P$4),MONTH(P$4),1),DATEVALUE("1-"&P$4)),IF(OR(COUNTA($A5:$F5)>0,$G5<>""),$N5/12*IF($F5="",1,MAX(0,(EOMONTH(_xlpm.m,0)-MAX($F5,_xlpm.m)+1)/(EOMONTH(_xlpm.m,0)-_xlpm.m+1))),"")) | Q5: =_xlfn.LET(_xlpm.m,IF(ISNUMBER(Q$4),DATE(YEAR(Q$4),MONTH(Q$4),1),DATEVALUE("1-"&Q$4)),IF(OR(COUNTA($A5:$F5)>0,$G5<>""),$N5/12*IF($F5="",1,MAX(0,(EOMONTH(_xlpm.m,0)-MAX($F5,_xlpm.m)+1)/(EOMONTH(_xlpm.m,0)-_xlpm.m+1))),"")) | R5: =_xlfn.LET(_xlpm.m,IF(ISNUMBER(R$4),DATE(YEAR(R$4),MONTH(R$4),1),DATEVALUE("1-"&R$4)),IF(OR(COUNTA($A5:$F5)>0,$G5<>""),$N5/12*IF($F5="",1,MAX(0,(EOMONTH(_xlpm.m,0)-MAX($F5,_xlpm.m)+1)/(EOMONTH(_xlpm.m,0)-_xlpm.m+1))),"")) | S5: =_xlfn.LET(_xlpm.m,IF(ISNUMBER(S$4),DATE(YEAR(S$4),MONTH(S$4),1),DATEVALUE("1-"&S$4)),IF(OR(COUNTA($A5:$F5)>0,$G5<>""),$N5/12*IF($F5="",1,MAX(0,(EOMONTH(_xlpm.m,0)-MAX($F5,_xlpm.m)+1)/(EOMONTH(_xlpm.m,0)-_xlpm.m+1))),"")) | T5: =_xlfn.LET(_xlpm.m,IF(ISNUMBER(T$4),DATE(YEAR(T$4),MONTH(T$4),1),DATEVALUE("1-"&T$4)),IF(OR(COUNTA($A5:$F5)>0,$G5<>""),$N5/12*IF($F5="",1,MAX(0,(EOMONTH(_xlpm.m,0)-MAX($F5,_xlpm.m)+1)/(EOMONTH(_xlpm.m,0)-_xlpm.m+1))),"")) | U5: =_xlfn.LET(_xlpm.m,IF(ISNUMBER(U$4),DATE(YEAR(U$4),MONTH(U$4),1),DATEVALUE("1-"&U$4)),IF(OR(COUNTA($A5:$F5)>0,$G5<>""),$N5/12*IF($F5="",1,MAX(0,(EOMONTH(_xlpm.m,0)-MAX($F5,_xlpm.m)+1)/(EOMONTH(_xlpm.m,0)-_xlpm.m+1))),"")) | V5: =_xlfn.LET(_xlpm.m,IF(ISNUMBER(V$4),DATE(YEAR(V$4),MONTH(V$4),1),DATEVALUE("1-"&V$4)),IF(OR(COUNTA($A5:$F5)>0,$G5<>""),$N5/12*IF($F5="",1,MAX(0,(EOMONTH(_xlpm.m,0)-MAX($F5,_xlpm.m)+1)/(EOMONTH(_xlpm.m,0)-_xlpm.m+1))),"")) | ... Z5: =_xlfn.LET(_xlpm.m,IF(ISNUMBER(Z$4),DATE(YEAR(Z$4),MONTH(Z$4),1),DATEVALUE("1-"&Z$4)),IF(OR(COUNTA($A5:$F5)>0,$G5<>""),$N5/12*IF($F5="",1,MAX(0,(EOMONTH(_xlpm.m,0)-MAX($F5,_xlpm.m)+1)/(EOMONTH(_xlpm.m,0)-_xlpm.m+1))),"")) | AA5: =IF(OR(COUNTA($A5:$F5)>0,$G5<>""),SUM(O5:Z5),"") | AB5: =_xlfn.LET(_xlpm.m,IF(ISNUMBER(AB$4),DATE(YEAR(AB$4),MONTH(AB$4),1),DATEVALUE("1-"&AB$4)),IF(OR(COUNTA($A5:$F5)>0,$G5<>""),$N5/12*IF($F5="",1,MAX(0,(EOMONTH(_xlpm.m,0)-MAX($F5,_xlpm.m)+1)/(EOMONTH(_xlpm.m,0)-_xlpm.m+1))),"")) | AC5: =_xlfn.LET(_xlpm.m,IF(ISNUMBER(AC$4),DATE(YEAR(AC$4),MONTH(AC$4),1),DATEVALUE("1-"&AC$4)),IF(OR(COUNTA($A5:$F5)>0,$G5<>""),$N5/12*IF($F5="",1,MAX(0,(EOMONTH(_xlpm.m,0)-MAX($F5,_xlpm.m)+1)/(EOMONTH(_xlpm.m,0)-_xlpm.m+1))),"")) | AD5: =_xlfn.LET(_xlpm.m,IF(ISNUMBER(AD$4),DATE(YEAR(AD$4),MONTH(AD$4),1),DATEVALUE("1-"&AD$4)),IF(OR(COUNTA($A5:$F5)>0,$G5<>""),$N5/12*IF($F5="",1,MAX(0,(EOMONTH(_xlpm.m,0)-MAX($F5,_xlpm.m)+1)/(EOMONTH(_xlpm.m,0)-_xlpm.m+1))),"")) | AE5: =_xlfn.LET(_xlpm.m,IF(ISNUMBER(AE$4),DATE(YEAR(AE$4),MONTH(AE$4),1),DATEVALUE("1-"&AE$4)),IF(OR(COUNTA($A5:$F5)>0,$G5<>""),$N5/12*IF($F5="",1,MAX(0,(EOMONTH(_xlpm.m,0)-MAX($F5,_xlpm.m)+1)/(EOMONTH(_xlpm.m,0)-_xlpm.m+1))),"")) | AF5: =_xlfn.LET(_xlpm.m,IF(ISNUMBER(AF$4),DATE(YEAR(AF$4),MONTH(AF$4),1),DATEVALUE("1-"&AF$4)),IF(OR(COUNTA($A5:$F5)>0,$G5<>""),$N5/12*IF($F5="",1,MAX(0,(EOMONTH(_xlpm.m,0)-MAX($F5,_xlpm.m)+1)/(EOMONTH(_xlpm.m,0)-_xlpm.m+1))),"")) | AG5: =_xlfn.LET(_xlpm.m,IF(ISNUMBER(AG$4),DATE(YEAR(AG$4),MONTH(AG$4),1),DATEVALUE("1-"&AG$4)),IF(OR(COUNTA($A5:$F5)>0,$G5<>""),$N5/12*IF($F5="",1,MAX(0,(EOMONTH(_xlpm.m,0)-MAX($F5,_xlpm.m)+1)/(EOMONTH(_xlpm.m,0)-_xlpm.m+1))),"")) | AH5: =_xlfn.LET(_xlpm.m,IF(ISNUMBER(AH$4),DATE(YEAR(AH$4),MONTH(AH$4),1),DATEVALUE("1-"&AH$4)),IF(OR(COUNTA($A5:$F5)>0,$G5<>""),$N5/12*IF($F5="",1,MAX(0,(EOMONTH(_xlpm.m,0)-MAX($F5,_xlpm.m)+1)/(EOMONTH(_xlpm.m,0)-_xlpm.m+1))),"")) | AI5: =_xlfn.LET(_xlpm.m,IF(ISNUMBER(AI$4),DATE(YEAR(AI$4),MONTH(AI$4),1),DATEVALUE("1-"&AI$4)),IF(OR(COUNTA($A5:$F5)>0,$G5<>""),$N5/12*IF($F5="",1,MAX(0,(EOMONTH(_xlpm.m,0)-MAX($F5,_xlpm.m)+1)/(EOMONTH(_xlpm.m,0)-_xlpm.m+1))),"")) | ... AM5: =_xlfn.LET(_xlpm.m,IF(ISNUMBER(AM$4),DATE(YEAR(AM$4),MONTH(AM$4),1),DATEVALUE("1-"&AM$4)),IF(OR(COUNTA($A5:$F5)>0,$G5<>""),$N5/12*IF($F5="",1,MAX(0,(EOMONTH(_xlpm.m,0)-MAX($F5,_xlpm.m)+1)/(EOMONTH(_xlpm.m,0)-_xlpm.m+1))),"")) | AN5: =IF(OR(COUNTA($A5:$F5)>0,$G5<>""),SUM(AB5:AM5),"") | AO5: =_xlfn.LET(_xlpm.m,IF(ISNUMBER(AO$4),DATE(YEAR(AO$4),MONTH(AO$4),1),DATEVALUE("1-"&AO$4)),IF(OR(COUNTA($A5:$F5)>0,$G5<>""),$N5/12*IF($F5="",1,MAX(0,(EOMONTH(_xlpm.m,0)-MAX($F5,_xlpm.m)+1)/(EOMONTH(_xlpm.m,0)-_xlpm.m+1))),"")) | AP5: =_xlfn.LET(_xlpm.m,IF(ISNUMBER(AP$4),DATE(YEAR(AP$4),MONTH(AP$4),1),DATEVALUE("1-"&AP$4)),IF(OR(COUNTA($A5:$F5)>0,$G5<>""),$N5/12*IF($F5="",1,MAX(0,(EOMONTH(_xlpm.m,0)-MAX($F5,_xlpm.m)+1)/(EOMONTH(_xlpm.m,0)-_xlpm.m+1))),"")) | AQ5: =_xlfn.LET(_xlpm.m,IF(ISNUMBER(AQ$4),DATE(YEAR(AQ$4),MONTH(AQ$4),1),DATEVALUE("1-"&AQ$4)),IF(OR(COUNTA($A5:$F5)>0,$G5<>""),$N5/12*IF($F5="",1,MAX(0,(EOMONTH(_xlpm.m,0)-MAX($F5,_xlpm.m)+1)/(EOMONTH(_xlpm.m,0)-_xlpm.m+1))),"")) | AR5: =_xlfn.LET(_xlpm.m,IF(ISNUMBER(AR$4),DATE(YEAR(AR$4),MONTH(AR$4),1),DATEVALUE("1-"&AR$4)),IF(OR(COUNTA($A5:$F5)>0,$G5<>""),$N5/12*IF($F5="",1,MAX(0,(EOMONTH(_xlpm.m,0)-MAX($F5,_xlpm.m)+1)/(EOMONTH(_xlpm.m,0)-_xlpm.m+1))),"")) | AS5: =_xlfn.LET(_xlpm.m,IF(ISNUMBER(AS$4),DATE(YEAR(AS$4),MONTH(AS$4),1),DATEVALUE("1-"&AS$4)),IF(OR(COUNTA($A5:$F5)>0,$G5<>""),$N5/12*IF($F5="",1,MAX(0,(EOMONTH(_xlpm.m,0)-MAX($F5,_xlpm.m)+1)/(EOMONTH(_xlpm.m,0)-_xlpm.m+1))),"")) | AT5: =_xlfn.LET(_xlpm.m,IF(ISNUMBER(AT$4),DATE(YEAR(AT$4),MONTH(AT$4),1),DATEVALUE("1-"&AT$4)),IF(OR(COUNTA($A5:$F5)>0,$G5<>""),$N5/12*IF($F5="",1,MAX(0,(EOMONTH(_xlpm.m,0)-MAX($F5,_xlpm.m)+1)/(EOMONTH(_xlpm.m,0)-_xlpm.m+1))),"")) | AU5: =_xlfn.LET(_xlpm.m,IF(ISNUMBER(AU$4),DATE(YEAR(AU$4),MONTH(AU$4),1),DATEVALUE("1-"&AU$4)),IF(OR(COUNTA($A5:$F5)>0,$G5<>""),$N5/12*IF($F5="",1,MAX(0,(EOMONTH(_xlpm.m,0)-MAX($F5,_xlpm.m)+1)/(EOMONTH(_xlpm.m,0)-_xlpm.m+1))),"")) | AV5: =_xlfn.LET(_xlpm.m,IF(ISNUMBER(AV$4),DATE(YEAR(AV$4),MONTH(AV$4),1),DATEVALUE("1-"&AV$4)),IF(OR(COUNTA($A5:$F5)>0,$G5<>""),$N5/12*IF($F5="",1,MAX(0,(EOMONTH(_xlpm.m,0)-MAX($F5,_xlpm.m)+1)/(EOMONTH(_xlpm.m,0)-_xlpm.m+1))),"")) | ... AZ5: =_xlfn.LET(_xlpm.m,IF(ISNUMBER(AZ$4),DATE(YEAR(AZ$4),MONTH(AZ$4),1),DATEVALUE("1-"&AZ$4)),IF(OR(COUNTA($A5:$F5)>0,$G5<>""),$N5/12*IF($F5="",1,MAX(0,(EOMONTH(_xlpm.m,0)-MAX($F5,_xlpm.m)+1)/(EOMONTH(_xlpm.m,0)-_xlpm.m+1))),"")) | BA5: =IF(OR(COUNTA($A5:$F5)>0,$G5<>""),SUM(AO5:AZ5),"")
I6: =IF(OR(COUNTA(tblPayrollIncrementalSpend2[[#This Row],[Job Title]:[Hire Date]])>0,AND(ROW()=ROW(G6),tblPayrollIncrementalSpend2[[#This Row],[Base Salary]]<>"")),N(tblPayrollIncrementalSpend2[[#This Row],[Base Salary]])*N(tblPayrollIncrementalSpend2[[#This Row],[Bonus %]]),"") | J6: =IF(OR(COUNTA(tblPayrollIncrementalSpend2[[#This Row],[Job Title]:[Hire Date]])>0,AND(ROW()=ROW(G6),tblPayrollIncrementalSpend2[[#This Row],[Base Salary]]<>"")),N(tblPayrollIncrementalSpend2[[#This Row],[Base Salary]])*'Base - Payroll'!$E$12,"") | K6: =IF(OR(COUNTA(tblPayrollIncrementalSpend2[[#This Row],[Job Title]:[Hire Date]])>0,AND(ROW()=ROW(G6),tblPayrollIncrementalSpend2[[#This Row],[Base Salary]]<>"")),N(tblPayrollIncrementalSpend2[[#This Row],[Base Salary]])*'Base - Payroll'!$E$13,"") | L6: =IF(OR(COUNTA(tblPayrollIncrementalSpend2[[#This Row],[Job Title]:[Hire Date]])>0,AND(ROW()=ROW(G6),tblPayrollIncrementalSpend2[[#This Row],[Base Salary]]<>"")),N(tblPayrollIncrementalSpend2[[#This Row],[Base Salary]])*'Base - Payroll'!$E$15,"") | M6: =IF(OR(COUNTA(tblPayrollIncrementalSpend2[[#This Row],[Job Title]:[Hire Date]])>0,AND(ROW()=ROW(G6),tblPayrollIncrementalSpend2[[#This Row],[Base Salary]]<>"")),N(tblPayrollIncrementalSpend2[[#This Row],[Base Salary]])*'Base - Payroll'!$E$16,"") | N6: =IF(OR(COUNTA(tblPayrollIncrementalSpend2[[#This Row],[Job Title]:[Hire Date]])>0,AND(ROW()=ROW(G6),tblPayrollIncrementalSpend2[[#This Row],[Base Salary]]<>"")),N(tblPayrollIncrementalSpend2[[#This Row],[Base Salary]])+SUM(tblPayrollIncrementalSpend2[[#This Row],[Bonus]:[Other]]),"") | O6: =_xlfn.LET(_xlpm.m,IF(ISNUMBER(O$4),DATE(YEAR(O$4),MONTH(O$4),1),DATEVALUE("1-"&O$4)),IF(OR(COUNTA($A6:$F6)>0,$G6<>""),$N6/12*IF($F6="",1,MAX(0,(EOMONTH(_xlpm.m,0)-MAX($F6,_xlpm.m)+1)/(EOMONTH(_xlpm.m,0)-_xlpm.m+1))),"")) | P6: =_xlfn.LET(_xlpm.m,IF(ISNUMBER(P$4),DATE(YEAR(P$4),MONTH(P$4),1),DATEVALUE("1-"&P$4)),IF(OR(COUNTA($A6:$F6)>0,$G6<>""),$N6/12*IF($F6="",1,MAX(0,(EOMONTH(_xlpm.m,0)-MAX($F6,_xlpm.m)+1)/(EOMONTH(_xlpm.m,0)-_xlpm.m+1))),"")) | Q6: =_xlfn.LET(_xlpm.m,IF(ISNUMBER(Q$4),DATE(YEAR(Q$4),MONTH(Q$4),1),DATEVALUE("1-"&Q$4)),IF(OR(COUNTA($A6:$F6)>0,$G6<>""),$N6/12*IF($F6="",1,MAX(0,(EOMONTH(_xlpm.m,0)-MAX($F6,_xlpm.m)+1)/(EOMONTH(_xlpm.m,0)-_xlpm.m+1))),"")) | R6: =_xlfn.LET(_xlpm.m,IF(ISNUMBER(R$4),DATE(YEAR(R$4),MONTH(R$4),1),DATEVALUE("1-"&R$4)),IF(OR(COUNTA($A6:$F6)>0,$G6<>""),$N6/12*IF($F6="",1,MAX(0,(EOMONTH(_xlpm.m,0)-MAX($F6,_xlpm.m)+1)/(EOMONTH(_xlpm.m,0)-_xlpm.m+1))),"")) | S6: =_xlfn.LET(_xlpm.m,IF(ISNUMBER(S$4),DATE(YEAR(S$4),MONTH(S$4),1),DATEVALUE("1-"&S$4)),IF(OR(COUNTA($A6:$F6)>0,$G6<>""),$N6/12*IF($F6="",1,MAX(0,(EOMONTH(_xlpm.m,0)-MAX($F6,_xlpm.m)+1)/(EOMONTH(_xlpm.m,0)-_xlpm.m+1))),"")) | T6: =_xlfn.LET(_xlpm.m,IF(ISNUMBER(T$4),DATE(YEAR(T$4),MONTH(T$4),1),DATEVALUE("1-"&T$4)),IF(OR(COUNTA($A6:$F6)>0,$G6<>""),$N6/12*IF($F6="",1,MAX(0,(EOMONTH(_xlpm.m,0)-MAX($F6,_xlpm.m)+1)/(EOMONTH(_xlpm.m,0)-_xlpm.m+1))),"")) | U6: =_xlfn.LET(_xlpm.m,IF(ISNUMBER(U$4),DATE(YEAR(U$4),MONTH(U$4),1),DATEVALUE("1-"&U$4)),IF(OR(COUNTA($A6:$F6)>0,$G6<>""),$N6/12*IF($F6="",1,MAX(0,(EOMONTH(_xlpm.m,0)-MAX($F6,_xlpm.m)+1)/(EOMONTH(_xlpm.m,0)-_xlpm.m+1))),"")) | V6: =_xlfn.LET(_xlpm.m,IF(ISNUMBER(V$4),DATE(YEAR(V$4),MONTH(V$4),1),DATEVALUE("1-"&V$4)),IF(OR(COUNTA($A6:$F6)>0,$G6<>""),$N6/12*IF($F6="",1,MAX(0,(EOMONTH(_xlpm.m,0)-MAX($F6,_xlpm.m)+1)/(EOMONTH(_xlpm.m,0)-_xlpm.m+1))),"")) | ... Z6: =_xlfn.LET(_xlpm.m,IF(ISNUMBER(Z$4),DATE(YEAR(Z$4),MONTH(Z$4),1),DATEVALUE("1-"&Z$4)),IF(OR(COUNTA($A6:$F6)>0,$G6<>""),$N6/12*IF($F6="",1,MAX(0,(EOMONTH(_xlpm.m,0)-MAX($F6,_xlpm.m)+1)/(EOMONTH(_xlpm.m,0)-_xlpm.m+1))),"")) | AA6: =IF(OR(COUNTA($A6:$F6)>0,$G6<>""),SUM(O6:Z6),"") | AB6: =_xlfn.LET(_xlpm.m,IF(ISNUMBER(AB$4),DATE(YEAR(AB$4),MONTH(AB$4),1),DATEVALUE("1-"&AB$4)),IF(OR(COUNTA($A6:$F6)>0,$G6<>""),$N6/12*IF($F6="",1,MAX(0,(EOMONTH(_xlpm.m,0)-MAX($F6,_xlpm.m)+1)/(EOMONTH(_xlpm.m,0)-_xlpm.m+1))),"")) | AC6: =_xlfn.LET(_xlpm.m,IF(ISNUMBER(AC$4),DATE(YEAR(AC$4),MONTH(AC$4),1),DATEVALUE("1-"&AC$4)),IF(OR(COUNTA($A6:$F6)>0,$G6<>""),$N6/12*IF($F6="",1,MAX(0,(EOMONTH(_xlpm.m,0)-MAX($F6,_xlpm.m)+1)/(EOMONTH(_xlpm.m,0)-_xlpm.m+1))),"")) | AD6: =_xlfn.LET(_xlpm.m,IF(ISNUMBER(AD$4),DATE(YEAR(AD$4),MONTH(AD$4),1),DATEVALUE("1-"&AD$4)),IF(OR(COUNTA($A6:$F6)>0,$G6<>""),$N6/12*IF($F6="",1,MAX(0,(EOMONTH(_xlpm.m,0)-MAX($F6,_xlpm.m)+1)/(EOMONTH(_xlpm.m,0)-_xlpm.m+1))),"")) | AE6: =_xlfn.LET(_xlpm.m,IF(ISNUMBER(AE$4),DATE(YEAR(AE$4),MONTH(AE$4),1),DATEVALUE("1-"&AE$4)),IF(OR(COUNTA($A6:$F6)>0,$G6<>""),$N6/12*IF($F6="",1,MAX(0,(EOMONTH(_xlpm.m,0)-MAX($F6,_xlpm.m)+1)/(EOMONTH(_xlpm.m,0)-_xlpm.m+1))),"")) | AF6: =_xlfn.LET(_xlpm.m,IF(ISNUMBER(AF$4),DATE(YEAR(AF$4),MONTH(AF$4),1),DATEVALUE("1-"&AF$4)),IF(OR(COUNTA($A6:$F6)>0,$G6<>""),$N6/12*IF($F6="",1,MAX(0,(EOMONTH(_xlpm.m,0)-MAX($F6,_xlpm.m)+1)/(EOMONTH(_xlpm.m,0)-_xlpm.m+1))),"")) | AG6: =_xlfn.LET(_xlpm.m,IF(ISNUMBER(AG$4),DATE(YEAR(AG$4),MONTH(AG$4),1),DATEVALUE("1-"&AG$4)),IF(OR(COUNTA($A6:$F6)>0,$G6<>""),$N6/12*IF($F6="",1,MAX(0,(EOMONTH(_xlpm.m,0)-MAX($F6,_xlpm.m)+1)/(EOMONTH(_xlpm.m,0)-_xlpm.m+1))),"")) | AH6: =_xlfn.LET(_xlpm.m,IF(ISNUMBER(AH$4),DATE(YEAR(AH$4),MONTH(AH$4),1),DATEVALUE("1-"&AH$4)),IF(OR(COUNTA($A6:$F6)>0,$G6<>""),$N6/12*IF($F6="",1,MAX(0,(EOMONTH(_xlpm.m,0)-MAX($F6,_xlpm.m)+1)/(EOMONTH(_xlpm.m,0)-_xlpm.m+1))),"")) | AI6: =_xlfn.LET(_xlpm.m,IF(ISNUMBER(AI$4),DATE(YEAR(AI$4),MONTH(AI$4),1),DATEVALUE("1-"&AI$4)),IF(OR(COUNTA($A6:$F6)>0,$G6<>""),$N6/12*IF($F6="",1,MAX(0,(EOMONTH(_xlpm.m,0)-MAX($F6,_xlpm.m)+1)/(EOMONTH(_xlpm.m,0)-_xlpm.m+1))),"")) | ... AM6: =_xlfn.LET(_xlpm.m,IF(ISNUMBER(AM$4),DATE(YEAR(AM$4),MONTH(AM$4),1),DATEVALUE("1-"&AM$4)),IF(OR(COUNTA($A6:$F6)>0,$G6<>""),$N6/12*IF($F6="",1,MAX(0,(EOMONTH(_xlpm.m,0)-MAX($F6,_xlpm.m)+1)/(EOMONTH(_xlpm.m,0)-_xlpm.m+1))),"")) | AN6: =IF(OR(COUNTA($A6:$F6)>0,$G6<>""),SUM(AB6:AM6),"") | AO6: =_xlfn.LET(_xlpm.m,IF(ISNUMBER(AO$4),DATE(YEAR(AO$4),MONTH(AO$4),1),DATEVALUE("1-"&AO$4)),IF(OR(COUNTA($A6:$F6)>0,$G6<>""),$N6/12*IF($F6="",1,MAX(0,(EOMONTH(_xlpm.m,0)-MAX($F6,_xlpm.m)+1)/(EOMONTH(_xlpm.m,0)-_xlpm.m+1))),"")) | AP6: =_xlfn.LET(_xlpm.m,IF(ISNUMBER(AP$4),DATE(YEAR(AP$4),MONTH(AP$4),1),DATEVALUE("1-"&AP$4)),IF(OR(COUNTA($A6:$F6)>0,$G6<>""),$N6/12*IF($F6="",1,MAX(0,(EOMONTH(_xlpm.m,0)-MAX($F6,_xlpm.m)+1)/(EOMONTH(_xlpm.m,0)-_xlpm.m+1))),"")) | AQ6: =_xlfn.LET(_xlpm.m,IF(ISNUMBER(AQ$4),DATE(YEAR(AQ$4),MONTH(AQ$4),1),DATEVALUE("1-"&AQ$4)),IF(OR(COUNTA($A6:$F6)>0,$G6<>""),$N6/12*IF($F6="",1,MAX(0,(EOMONTH(_xlpm.m,0)-MAX($F6,_xlpm.m)+1)/(EOMONTH(_xlpm.m,0)-_xlpm.m+1))),"")) | AR6: =_xlfn.LET(_xlpm.m,IF(ISNUMBER(AR$4),DATE(YEAR(AR$4),MONTH(AR$4),1),DATEVALUE("1-"&AR$4)),IF(OR(COUNTA($A6:$F6)>0,$G6<>""),$N6/12*IF($F6="",1,MAX(0,(EOMONTH(_xlpm.m,0)-MAX($F6,_xlpm.m)+1)/(EOMONTH(_xlpm.m,0)-_xlpm.m+1))),"")) | AS6: =_xlfn.LET(_xlpm.m,IF(ISNUMBER(AS$4),DATE(YEAR(AS$4),MONTH(AS$4),1),DATEVALUE("1-"&AS$4)),IF(OR(COUNTA($A6:$F6)>0,$G6<>""),$N6/12*IF($F6="",1,MAX(0,(EOMONTH(_xlpm.m,0)-MAX($F6,_xlpm.m)+1)/(EOMONTH(_xlpm.m,0)-_xlpm.m+1))),"")) | AT6: =_xlfn.LET(_xlpm.m,IF(ISNUMBER(AT$4),DATE(YEAR(AT$4),MONTH(AT$4),1),DATEVALUE("1-"&AT$4)),IF(OR(COUNTA($A6:$F6)>0,$G6<>""),$N6/12*IF($F6="",1,MAX(0,(EOMONTH(_xlpm.m,0)-MAX($F6,_xlpm.m)+1)/(EOMONTH(_xlpm.m,0)-_xlpm.m+1))),"")) | AU6: =_xlfn.LET(_xlpm.m,IF(ISNUMBER(AU$4),DATE(YEAR(AU$4),MONTH(AU$4),1),DATEVALUE("1-"&AU$4)),IF(OR(COUNTA($A6:$F6)>0,$G6<>""),$N6/12*IF($F6="",1,MAX(0,(EOMONTH(_xlpm.m,0)-MAX($F6,_xlpm.m)+1)/(EOMONTH(_xlpm.m,0)-_xlpm.m+1))),"")) | AV6: =_xlfn.LET(_xlpm.m,IF(ISNUMBER(AV$4),DATE(YEAR(AV$4),MONTH(AV$4),1),DATEVALUE("1-"&AV$4)),IF(OR(COUNTA($A6:$F6)>0,$G6<>""),$N6/12*IF($F6="",1,MAX(0,(EOMONTH(_xlpm.m,0)-MAX($F6,_xlpm.m)+1)/(EOMONTH(_xlpm.m,0)-_xlpm.m+1))),"")) | ... AZ6: =_xlfn.LET(_xlpm.m,IF(ISNUMBER(AZ$4),DATE(YEAR(AZ$4),MONTH(AZ$4),1),DATEVALUE("1-"&AZ$4)),IF(OR(COUNTA($A6:$F6)>0,$G6<>""),$N6/12*IF($F6="",1,MAX(0,(EOMONTH(_xlpm.m,0)-MAX($F6,_xlpm.m)+1)/(EOMONTH(_xlpm.m,0)-_xlpm.m+1))),"")) | BA6: =IF(OR(COUNTA($A6:$F6)>0,$G6<>""),SUM(AO6:AZ6),"")
I7: =IF(OR(COUNTA(tblPayrollIncrementalSpend2[[#This Row],[Job Title]:[Hire Date]])>0,AND(ROW()=ROW(G7),tblPayrollIncrementalSpend2[[#This Row],[Base Salary]]<>"")),N(tblPayrollIncrementalSpend2[[#This Row],[Base Salary]])*N(tblPayrollIncrementalSpend2[[#This Row],[Bonus %]]),"") | J7: =IF(OR(COUNTA(tblPayrollIncrementalSpend2[[#This Row],[Job Title]:[Hire Date]])>0,AND(ROW()=ROW(G7),tblPayrollIncrementalSpend2[[#This Row],[Base Salary]]<>"")),N(tblPayrollIncrementalSpend2[[#This Row],[Base Salary]])*'Base - Payroll'!$E$12,"") | K7: =IF(OR(COUNTA(tblPayrollIncrementalSpend2[[#This Row],[Job Title]:[Hire Date]])>0,AND(ROW()=ROW(G7),tblPayrollIncrementalSpend2[[#This Row],[Base Salary]]<>"")),N(tblPayrollIncrementalSpend2[[#This Row],[Base Salary]])*'Base - Payroll'!$E$13,"") | L7: =IF(OR(COUNTA(tblPayrollIncrementalSpend2[[#This Row],[Job Title]:[Hire Date]])>0,AND(ROW()=ROW(G7),tblPayrollIncrementalSpend2[[#This Row],[Base Salary]]<>"")),N(tblPayrollIncrementalSpend2[[#This Row],[Base Salary]])*'Base - Payroll'!$E$15,"") | M7: =IF(OR(COUNTA(tblPayrollIncrementalSpend2[[#This Row],[Job Title]:[Hire Date]])>0,AND(ROW()=ROW(G7),tblPayrollIncrementalSpend2[[#This Row],[Base Salary]]<>"")),N(tblPayrollIncrementalSpend2[[#This Row],[Base Salary]])*'Base - Payroll'!$E$16,"") | N7: =IF(OR(COUNTA(tblPayrollIncrementalSpend2[[#This Row],[Job Title]:[Hire Date]])>0,AND(ROW()=ROW(G7),tblPayrollIncrementalSpend2[[#This Row],[Base Salary]]<>"")),N(tblPayrollIncrementalSpend2[[#This Row],[Base Salary]])+SUM(tblPayrollIncrementalSpend2[[#This Row],[Bonus]:[Other]]),"") | O7: =_xlfn.LET(_xlpm.m,IF(ISNUMBER(O$4),DATE(YEAR(O$4),MONTH(O$4),1),DATEVALUE("1-"&O$4)),IF(OR(COUNTA($A7:$F7)>0,$G7<>""),$N7/12*IF($F7="",1,MAX(0,(EOMONTH(_xlpm.m,0)-MAX($F7,_xlpm.m)+1)/(EOMONTH(_xlpm.m,0)-_xlpm.m+1))),"")) | P7: =_xlfn.LET(_xlpm.m,IF(ISNUMBER(P$4),DATE(YEAR(P$4),MONTH(P$4),1),DATEVALUE("1-"&P$4)),IF(OR(COUNTA($A7:$F7)>0,$G7<>""),$N7/12*IF($F7="",1,MAX(0,(EOMONTH(_xlpm.m,0)-MAX($F7,_xlpm.m)+1)/(EOMONTH(_xlpm.m,0)-_xlpm.m+1))),"")) | Q7: =_xlfn.LET(_xlpm.m,IF(ISNUMBER(Q$4),DATE(YEAR(Q$4),MONTH(Q$4),1),DATEVALUE("1-"&Q$4)),IF(OR(COUNTA($A7:$F7)>0,$G7<>""),$N7/12*IF($F7="",1,MAX(0,(EOMONTH(_xlpm.m,0)-MAX($F7,_xlpm.m)+1)/(EOMONTH(_xlpm.m,0)-_xlpm.m+1))),"")) | R7: =_xlfn.LET(_xlpm.m,IF(ISNUMBER(R$4),DATE(YEAR(R$4),MONTH(R$4),1),DATEVALUE("1-"&R$4)),IF(OR(COUNTA($A7:$F7)>0,$G7<>""),$N7/12*IF($F7="",1,MAX(0,(EOMONTH(_xlpm.m,0)-MAX($F7,_xlpm.m)+1)/(EOMONTH(_xlpm.m,0)-_xlpm.m+1))),"")) | S7: =_xlfn.LET(_xlpm.m,IF(ISNUMBER(S$4),DATE(YEAR(S$4),MONTH(S$4),1),DATEVALUE("1-"&S$4)),IF(OR(COUNTA($A7:$F7)>0,$G7<>""),$N7/12*IF($F7="",1,MAX(0,(EOMONTH(_xlpm.m,0)-MAX($F7,_xlpm.m)+1)/(EOMONTH(_xlpm.m,0)-_xlpm.m+1))),"")) | T7: =_xlfn.LET(_xlpm.m,IF(ISNUMBER(T$4),DATE(YEAR(T$4),MONTH(T$4),1),DATEVALUE("1-"&T$4)),IF(OR(COUNTA($A7:$F7)>0,$G7<>""),$N7/12*IF($F7="",1,MAX(0,(EOMONTH(_xlpm.m,0)-MAX($F7,_xlpm.m)+1)/(EOMONTH(_xlpm.m,0)-_xlpm.m+1))),"")) | U7: =_xlfn.LET(_xlpm.m,IF(ISNUMBER(U$4),DATE(YEAR(U$4),MONTH(U$4),1),DATEVALUE("1-"&U$4)),IF(OR(COUNTA($A7:$F7)>0,$G7<>""),$N7/12*IF($F7="",1,MAX(0,(EOMONTH(_xlpm.m,0)-MAX($F7,_xlpm.m)+1)/(EOMONTH(_xlpm.m,0)-_xlpm.m+1))),"")) | V7: =_xlfn.LET(_xlpm.m,IF(ISNUMBER(V$4),DATE(YEAR(V$4),MONTH(V$4),1),DATEVALUE("1-"&V$4)),IF(OR(COUNTA($A7:$F7)>0,$G7<>""),$N7/12*IF($F7="",1,MAX(0,(EOMONTH(_xlpm.m,0)-MAX($F7,_xlpm.m)+1)/(EOMONTH(_xlpm.m,0)-_xlpm.m+1))),"")) | ... Z7: =_xlfn.LET(_xlpm.m,IF(ISNUMBER(Z$4),DATE(YEAR(Z$4),MONTH(Z$4),1),DATEVALUE("1-"&Z$4)),IF(OR(COUNTA($A7:$F7)>0,$G7<>""),$N7/12*IF($F7="",1,MAX(0,(EOMONTH(_xlpm.m,0)-MAX($F7,_xlpm.m)+1)/(EOMONTH(_xlpm.m,0)-_xlpm.m+1))),"")) | AA7: =IF(OR(COUNTA($A7:$F7)>0,$G7<>""),SUM(O7:Z7),"") | AB7: =_xlfn.LET(_xlpm.m,IF(ISNUMBER(AB$4),DATE(YEAR(AB$4),MONTH(AB$4),1),DATEVALUE("1-"&AB$4)),IF(OR(COUNTA($A7:$F7)>0,$G7<>""),$N7/12*IF($F7="",1,MAX(0,(EOMONTH(_xlpm.m,0)-MAX($F7,_xlpm.m)+1)/(EOMONTH(_xlpm.m,0)-_xlpm.m+1))),"")) | AC7: =_xlfn.LET(_xlpm.m,IF(ISNUMBER(AC$4),DATE(YEAR(AC$4),MONTH(AC$4),1),DATEVALUE("1-"&AC$4)),IF(OR(COUNTA($A7:$F7)>0,$G7<>""),$N7/12*IF($F7="",1,MAX(0,(EOMONTH(_xlpm.m,0)-MAX($F7,_xlpm.m)+1)/(EOMONTH(_xlpm.m,0)-_xlpm.m+1))),"")) | AD7: =_xlfn.LET(_xlpm.m,IF(ISNUMBER(AD$4),DATE(YEAR(AD$4),MONTH(AD$4),1),DATEVALUE("1-"&AD$4)),IF(OR(COUNTA($A7:$F7)>0,$G7<>""),$N7/12*IF($F7="",1,MAX(0,(EOMONTH(_xlpm.m,0)-MAX($F7,_xlpm.m)+1)/(EOMONTH(_xlpm.m,0)-_xlpm.m+1))),"")) | AE7: =_xlfn.LET(_xlpm.m,IF(ISNUMBER(AE$4),DATE(YEAR(AE$4),MONTH(AE$4),1),DATEVALUE("1-"&AE$4)),IF(OR(COUNTA($A7:$F7)>0,$G7<>""),$N7/12*IF($F7="",1,MAX(0,(EOMONTH(_xlpm.m,0)-MAX($F7,_xlpm.m)+1)/(EOMONTH(_xlpm.m,0)-_xlpm.m+1))),"")) | AF7: =_xlfn.LET(_xlpm.m,IF(ISNUMBER(AF$4),DATE(YEAR(AF$4),MONTH(AF$4),1),DATEVALUE("1-"&AF$4)),IF(OR(COUNTA($A7:$F7)>0,$G7<>""),$N7/12*IF($F7="",1,MAX(0,(EOMONTH(_xlpm.m,0)-MAX($F7,_xlpm.m)+1)/(EOMONTH(_xlpm.m,0)-_xlpm.m+1))),"")) | AG7: =_xlfn.LET(_xlpm.m,IF(ISNUMBER(AG$4),DATE(YEAR(AG$4),MONTH(AG$4),1),DATEVALUE("1-"&AG$4)),IF(OR(COUNTA($A7:$F7)>0,$G7<>""),$N7/12*IF($F7="",1,MAX(0,(EOMONTH(_xlpm.m,0)-MAX($F7,_xlpm.m)+1)/(EOMONTH(_xlpm.m,0)-_xlpm.m+1))),"")) | AH7: =_xlfn.LET(_xlpm.m,IF(ISNUMBER(AH$4),DATE(YEAR(AH$4),MONTH(AH$4),1),DATEVALUE("1-"&AH$4)),IF(OR(COUNTA($A7:$F7)>0,$G7<>""),$N7/12*IF($F7="",1,MAX(0,(EOMONTH(_xlpm.m,0)-MAX($F7,_xlpm.m)+1)/(EOMONTH(_xlpm.m,0)-_xlpm.m+1))),"")) | AI7: =_xlfn.LET(_xlpm.m,IF(ISNUMBER(AI$4),DATE(YEAR(AI$4),MONTH(AI$4),1),DATEVALUE("1-"&AI$4)),IF(OR(COUNTA($A7:$F7)>0,$G7<>""),$N7/12*IF($F7="",1,MAX(0,(EOMONTH(_xlpm.m,0)-MAX($F7,_xlpm.m)+1)/(EOMONTH(_xlpm.m,0)-_xlpm.m+1))),"")) | ... AM7: =_xlfn.LET(_xlpm.m,IF(ISNUMBER(AM$4),DATE(YEAR(AM$4),MONTH(AM$4),1),DATEVALUE("1-"&AM$4)),IF(OR(COUNTA($A7:$F7)>0,$G7<>""),$N7/12*IF($F7="",1,MAX(0,(EOMONTH(_xlpm.m,0)-MAX($F7,_xlpm.m)+1)/(EOMONTH(_xlpm.m,0)-_xlpm.m+1))),"")) | AN7: =IF(OR(COUNTA($A7:$F7)>0,$G7<>""),SUM(AB7:AM7),"") | AO7: =_xlfn.LET(_xlpm.m,IF(ISNUMBER(AO$4),DATE(YEAR(AO$4),MONTH(AO$4),1),DATEVALUE("1-"&AO$4)),IF(OR(COUNTA($A7:$F7)>0,$G7<>""),$N7/12*IF($F7="",1,MAX(0,(EOMONTH(_xlpm.m,0)-MAX($F7,_xlpm.m)+1)/(EOMONTH(_xlpm.m,0)-_xlpm.m+1))),"")) | AP7: =_xlfn.LET(_xlpm.m,IF(ISNUMBER(AP$4),DATE(YEAR(AP$4),MONTH(AP$4),1),DATEVALUE("1-"&AP$4)),IF(OR(COUNTA($A7:$F7)>0,$G7<>""),$N7/12*IF($F7="",1,MAX(0,(EOMONTH(_xlpm.m,0)-MAX($F7,_xlpm.m)+1)/(EOMONTH(_xlpm.m,0)-_xlpm.m+1))),"")) | AQ7: =_xlfn.LET(_xlpm.m,IF(ISNUMBER(AQ$4),DATE(YEAR(AQ$4),MONTH(AQ$4),1),DATEVALUE("1-"&AQ$4)),IF(OR(COUNTA($A7:$F7)>0,$G7<>""),$N7/12*IF($F7="",1,MAX(0,(EOMONTH(_xlpm.m,0)-MAX($F7,_xlpm.m)+1)/(EOMONTH(_xlpm.m,0)-_xlpm.m+1))),"")) | AR7: =_xlfn.LET(_xlpm.m,IF(ISNUMBER(AR$4),DATE(YEAR(AR$4),MONTH(AR$4),1),DATEVALUE("1-"&AR$4)),IF(OR(COUNTA($A7:$F7)>0,$G7<>""),$N7/12*IF($F7="",1,MAX(0,(EOMONTH(_xlpm.m,0)-MAX($F7,_xlpm.m)+1)/(EOMONTH(_xlpm.m,0)-_xlpm.m+1))),"")) | AS7: =_xlfn.LET(_xlpm.m,IF(ISNUMBER(AS$4),DATE(YEAR(AS$4),MONTH(AS$4),1),DATEVALUE("1-"&AS$4)),IF(OR(COUNTA($A7:$F7)>0,$G7<>""),$N7/12*IF($F7="",1,MAX(0,(EOMONTH(_xlpm.m,0)-MAX($F7,_xlpm.m)+1)/(EOMONTH(_xlpm.m,0)-_xlpm.m+1))),"")) | AT7: =_xlfn.LET(_xlpm.m,IF(ISNUMBER(AT$4),DATE(YEAR(AT$4),MONTH(AT$4),1),DATEVALUE("1-"&AT$4)),IF(OR(COUNTA($A7:$F7)>0,$G7<>""),$N7/12*IF($F7="",1,MAX(0,(EOMONTH(_xlpm.m,0)-MAX($F7,_xlpm.m)+1)/(EOMONTH(_xlpm.m,0)-_xlpm.m+1))),"")) | AU7: =_xlfn.LET(_xlpm.m,IF(ISNUMBER(AU$4),DATE(YEAR(AU$4),MONTH(AU$4),1),DATEVALUE("1-"&AU$4)),IF(OR(COUNTA($A7:$F7)>0,$G7<>""),$N7/12*IF($F7="",1,MAX(0,(EOMONTH(_xlpm.m,0)-MAX($F7,_xlpm.m)+1)/(EOMONTH(_xlpm.m,0)-_xlpm.m+1))),"")) | AV7: =_xlfn.LET(_xlpm.m,IF(ISNUMBER(AV$4),DATE(YEAR(AV$4),MONTH(AV$4),1),DATEVALUE("1-"&AV$4)),IF(OR(COUNTA($A7:$F7)>0,$G7<>""),$N7/12*IF($F7="",1,MAX(0,(EOMONTH(_xlpm.m,0)-MAX($F7,_xlpm.m)+1)/(EOMONTH(_xlpm.m,0)-_xlpm.m+1))),"")) | ... AZ7: =_xlfn.LET(_xlpm.m,IF(ISNUMBER(AZ$4),DATE(YEAR(AZ$4),MONTH(AZ$4),1),DATEVALUE("1-"&AZ$4)),IF(OR(COUNTA($A7:$F7)>0,$G7<>""),$N7/12*IF($F7="",1,MAX(0,(EOMONTH(_xlpm.m,0)-MAX($F7,_xlpm.m)+1)/(EOMONTH(_xlpm.m,0)-_xlpm.m+1))),"")) | BA7: =IF(OR(COUNTA($A7:$F7)>0,$G7<>""),SUM(AO7:AZ7),"")
I8: =IF(OR(COUNTA(tblPayrollIncrementalSpend2[[#This Row],[Job Title]:[Hire Date]])>0,AND(ROW()=ROW(G8),tblPayrollIncrementalSpend2[[#This Row],[Base Salary]]<>"")),N(tblPayrollIncrementalSpend2[[#This Row],[Base Salary]])*N(tblPayrollIncrementalSpend2[[#This Row],[Bonus %]]),"") | J8: =IF(OR(COUNTA(tblPayrollIncrementalSpend2[[#This Row],[Job Title]:[Hire Date]])>0,AND(ROW()=ROW(G8),tblPayrollIncrementalSpend2[[#This Row],[Base Salary]]<>"")),N(tblPayrollIncrementalSpend2[[#This Row],[Base Salary]])*'Base - Payroll'!$E$12,"") | K8: =IF(OR(COUNTA(tblPayrollIncrementalSpend2[[#This Row],[Job Title]:[Hire Date]])>0,AND(ROW()=ROW(G8),tblPayrollIncrementalSpend2[[#This Row],[Base Salary]]<>"")),N(tblPayrollIncrementalSpend2[[#This Row],[Base Salary]])*'Base - Payroll'!$E$13,"") | L8: =IF(OR(COUNTA(tblPayrollIncrementalSpend2[[#This Row],[Job Title]:[Hire Date]])>0,AND(ROW()=ROW(G8),tblPayrollIncrementalSpend2[[#This Row],[Base Salary]]<>"")),N(tblPayrollIncrementalSpend2[[#This Row],[Base Salary]])*'Base - Payroll'!$E$15,"") | M8: =IF(OR(COUNTA(tblPayrollIncrementalSpend2[[#This Row],[Job Title]:[Hire Date]])>0,AND(ROW()=ROW(G8),tblPayrollIncrementalSpend2[[#This Row],[Base Salary]]<>"")),N(tblPayrollIncrementalSpend2[[#This Row],[Base Salary]])*'Base - Payroll'!$E$16,"") | N8: =IF(OR(COUNTA(tblPayrollIncrementalSpend2[[#This Row],[Job Title]:[Hire Date]])>0,AND(ROW()=ROW(G8),tblPayrollIncrementalSpend2[[#This Row],[Base Salary]]<>"")),N(tblPayrollIncrementalSpend2[[#This Row],[Base Salary]])+SUM(tblPayrollIncrementalSpend2[[#This Row],[Bonus]:[Other]]),"") | O8: =_xlfn.LET(_xlpm.m,IF(ISNUMBER(O$4),DATE(YEAR(O$4),MONTH(O$4),1),DATEVALUE("1-"&O$4)),IF(OR(COUNTA($A8:$F8)>0,$G8<>""),$N8/12*IF($F8="",1,MAX(0,(EOMONTH(_xlpm.m,0)-MAX($F8,_xlpm.m)+1)/(EOMONTH(_xlpm.m,0)-_xlpm.m+1))),"")) | P8: =_xlfn.LET(_xlpm.m,IF(ISNUMBER(P$4),DATE(YEAR(P$4),MONTH(P$4),1),DATEVALUE("1-"&P$4)),IF(OR(COUNTA($A8:$F8)>0,$G8<>""),$N8/12*IF($F8="",1,MAX(0,(EOMONTH(_xlpm.m,0)-MAX($F8,_xlpm.m)+1)/(EOMONTH(_xlpm.m,0)-_xlpm.m+1))),"")) | Q8: =_xlfn.LET(_xlpm.m,IF(ISNUMBER(Q$4),DATE(YEAR(Q$4),MONTH(Q$4),1),DATEVALUE("1-"&Q$4)),IF(OR(COUNTA($A8:$F8)>0,$G8<>""),$N8/12*IF($F8="",1,MAX(0,(EOMONTH(_xlpm.m,0)-MAX($F8,_xlpm.m)+1)/(EOMONTH(_xlpm.m,0)-_xlpm.m+1))),"")) | R8: =_xlfn.LET(_xlpm.m,IF(ISNUMBER(R$4),DATE(YEAR(R$4),MONTH(R$4),1),DATEVALUE("1-"&R$4)),IF(OR(COUNTA($A8:$F8)>0,$G8<>""),$N8/12*IF($F8="",1,MAX(0,(EOMONTH(_xlpm.m,0)-MAX($F8,_xlpm.m)+1)/(EOMONTH(_xlpm.m,0)-_xlpm.m+1))),"")) | S8: =_xlfn.LET(_xlpm.m,IF(ISNUMBER(S$4),DATE(YEAR(S$4),MONTH(S$4),1),DATEVALUE("1-"&S$4)),IF(OR(COUNTA($A8:$F8)>0,$G8<>""),$N8/12*IF($F8="",1,MAX(0,(EOMONTH(_xlpm.m,0)-MAX($F8,_xlpm.m)+1)/(EOMONTH(_xlpm.m,0)-_xlpm.m+1))),"")) | T8: =_xlfn.LET(_xlpm.m,IF(ISNUMBER(T$4),DATE(YEAR(T$4),MONTH(T$4),1),DATEVALUE("1-"&T$4)),IF(OR(COUNTA($A8:$F8)>0,$G8<>""),$N8/12*IF($F8="",1,MAX(0,(EOMONTH(_xlpm.m,0)-MAX($F8,_xlpm.m)+1)/(EOMONTH(_xlpm.m,0)-_xlpm.m+1))),"")) | U8: =_xlfn.LET(_xlpm.m,IF(ISNUMBER(U$4),DATE(YEAR(U$4),MONTH(U$4),1),DATEVALUE("1-"&U$4)),IF(OR(COUNTA($A8:$F8)>0,$G8<>""),$N8/12*IF($F8="",1,MAX(0,(EOMONTH(_xlpm.m,0)-MAX($F8,_xlpm.m)+1)/(EOMONTH(_xlpm.m,0)-_xlpm.m+1))),"")) | V8: =_xlfn.LET(_xlpm.m,IF(ISNUMBER(V$4),DATE(YEAR(V$4),MONTH(V$4),1),DATEVALUE("1-"&V$4)),IF(OR(COUNTA($A8:$F8)>0,$G8<>""),$N8/12*IF($F8="",1,MAX(0,(EOMONTH(_xlpm.m,0)-MAX($F8,_xlpm.m)+1)/(EOMONTH(_xlpm.m,0)-_xlpm.m+1))),"")) | ... Z8: =_xlfn.LET(_xlpm.m,IF(ISNUMBER(Z$4),DATE(YEAR(Z$4),MONTH(Z$4),1),DATEVALUE("1-"&Z$4)),IF(OR(COUNTA($A8:$F8)>0,$G8<>""),$N8/12*IF($F8="",1,MAX(0,(EOMONTH(_xlpm.m,0)-MAX($F8,_xlpm.m)+1)/(EOMONTH(_xlpm.m,0)-_xlpm.m+1))),"")) | AA8: =IF(OR(COUNTA($A8:$F8)>0,$G8<>""),SUM(O8:Z8),"") | AB8: =_xlfn.LET(_xlpm.m,IF(ISNUMBER(AB$4),DATE(YEAR(AB$4),MONTH(AB$4),1),DATEVALUE("1-"&AB$4)),IF(OR(COUNTA($A8:$F8)>0,$G8<>""),$N8/12*IF($F8="",1,MAX(0,(EOMONTH(_xlpm.m,0)-MAX($F8,_xlpm.m)+1)/(EOMONTH(_xlpm.m,0)-_xlpm.m+1))),"")) | AC8: =_xlfn.LET(_xlpm.m,IF(ISNUMBER(AC$4),DATE(YEAR(AC$4),MONTH(AC$4),1),DATEVALUE("1-"&AC$4)),IF(OR(COUNTA($A8:$F8)>0,$G8<>""),$N8/12*IF($F8="",1,MAX(0,(EOMONTH(_xlpm.m,0)-MAX($F8,_xlpm.m)+1)/(EOMONTH(_xlpm.m,0)-_xlpm.m+1))),"")) | AD8: =_xlfn.LET(_xlpm.m,IF(ISNUMBER(AD$4),DATE(YEAR(AD$4),MONTH(AD$4),1),DATEVALUE("1-"&AD$4)),IF(OR(COUNTA($A8:$F8)>0,$G8<>""),$N8/12*IF($F8="",1,MAX(0,(EOMONTH(_xlpm.m,0)-MAX($F8,_xlpm.m)+1)/(EOMONTH(_xlpm.m,0)-_xlpm.m+1))),"")) | AE8: =_xlfn.LET(_xlpm.m,IF(ISNUMBER(AE$4),DATE(YEAR(AE$4),MONTH(AE$4),1),DATEVALUE("1-"&AE$4)),IF(OR(COUNTA($A8:$F8)>0,$G8<>""),$N8/12*IF($F8="",1,MAX(0,(EOMONTH(_xlpm.m,0)-MAX($F8,_xlpm.m)+1)/(EOMONTH(_xlpm.m,0)-_xlpm.m+1))),"")) | AF8: =_xlfn.LET(_xlpm.m,IF(ISNUMBER(AF$4),DATE(YEAR(AF$4),MONTH(AF$4),1),DATEVALUE("1-"&AF$4)),IF(OR(COUNTA($A8:$F8)>0,$G8<>""),$N8/12*IF($F8="",1,MAX(0,(EOMONTH(_xlpm.m,0)-MAX($F8,_xlpm.m)+1)/(EOMONTH(_xlpm.m,0)-_xlpm.m+1))),"")) | AG8: =_xlfn.LET(_xlpm.m,IF(ISNUMBER(AG$4),DATE(YEAR(AG$4),MONTH(AG$4),1),DATEVALUE("1-"&AG$4)),IF(OR(COUNTA($A8:$F8)>0,$G8<>""),$N8/12*IF($F8="",1,MAX(0,(EOMONTH(_xlpm.m,0)-MAX($F8,_xlpm.m)+1)/(EOMONTH(_xlpm.m,0)-_xlpm.m+1))),"")) | AH8: =_xlfn.LET(_xlpm.m,IF(ISNUMBER(AH$4),DATE(YEAR(AH$4),MONTH(AH$4),1),DATEVALUE("1-"&AH$4)),IF(OR(COUNTA($A8:$F8)>0,$G8<>""),$N8/12*IF($F8="",1,MAX(0,(EOMONTH(_xlpm.m,0)-MAX($F8,_xlpm.m)+1)/(EOMONTH(_xlpm.m,0)-_xlpm.m+1))),"")) | AI8: =_xlfn.LET(_xlpm.m,IF(ISNUMBER(AI$4),DATE(YEAR(AI$4),MONTH(AI$4),1),DATEVALUE("1-"&AI$4)),IF(OR(COUNTA($A8:$F8)>0,$G8<>""),$N8/12*IF($F8="",1,MAX(0,(EOMONTH(_xlpm.m,0)-MAX($F8,_xlpm.m)+1)/(EOMONTH(_xlpm.m,0)-_xlpm.m+1))),"")) | ... AM8: =_xlfn.LET(_xlpm.m,IF(ISNUMBER(AM$4),DATE(YEAR(AM$4),MONTH(AM$4),1),DATEVALUE("1-"&AM$4)),IF(OR(COUNTA($A8:$F8)>0,$G8<>""),$N8/12*IF($F8="",1,MAX(0,(EOMONTH(_xlpm.m,0)-MAX($F8,_xlpm.m)+1)/(EOMONTH(_xlpm.m,0)-_xlpm.m+1))),"")) | AN8: =IF(OR(COUNTA($A8:$F8)>0,$G8<>""),SUM(AB8:AM8),"") | AO8: =_xlfn.LET(_xlpm.m,IF(ISNUMBER(AO$4),DATE(YEAR(AO$4),MONTH(AO$4),1),DATEVALUE("1-"&AO$4)),IF(OR(COUNTA($A8:$F8)>0,$G8<>""),$N8/12*IF($F8="",1,MAX(0,(EOMONTH(_xlpm.m,0)-MAX($F8,_xlpm.m)+1)/(EOMONTH(_xlpm.m,0)-_xlpm.m+1))),"")) | AP8: =_xlfn.LET(_xlpm.m,IF(ISNUMBER(AP$4),DATE(YEAR(AP$4),MONTH(AP$4),1),DATEVALUE("1-"&AP$4)),IF(OR(COUNTA($A8:$F8)>0,$G8<>""),$N8/12*IF($F8="",1,MAX(0,(EOMONTH(_xlpm.m,0)-MAX($F8,_xlpm.m)+1)/(EOMONTH(_xlpm.m,0)-_xlpm.m+1))),"")) | AQ8: =_xlfn.LET(_xlpm.m,IF(ISNUMBER(AQ$4),DATE(YEAR(AQ$4),MONTH(AQ$4),1),DATEVALUE("1-"&AQ$4)),IF(OR(COUNTA($A8:$F8)>0,$G8<>""),$N8/12*IF($F8="",1,MAX(0,(EOMONTH(_xlpm.m,0)-MAX($F8,_xlpm.m)+1)/(EOMONTH(_xlpm.m,0)-_xlpm.m+1))),"")) | AR8: =_xlfn.LET(_xlpm.m,IF(ISNUMBER(AR$4),DATE(YEAR(AR$4),MONTH(AR$4),1),DATEVALUE("1-"&AR$4)),IF(OR(COUNTA($A8:$F8)>0,$G8<>""),$N8/12*IF($F8="",1,MAX(0,(EOMONTH(_xlpm.m,0)-MAX($F8,_xlpm.m)+1)/(EOMONTH(_xlpm.m,0)-_xlpm.m+1))),"")) | AS8: =_xlfn.LET(_xlpm.m,IF(ISNUMBER(AS$4),DATE(YEAR(AS$4),MONTH(AS$4),1),DATEVALUE("1-"&AS$4)),IF(OR(COUNTA($A8:$F8)>0,$G8<>""),$N8/12*IF($F8="",1,MAX(0,(EOMONTH(_xlpm.m,0)-MAX($F8,_xlpm.m)+1)/(EOMONTH(_xlpm.m,0)-_xlpm.m+1))),"")) | AT8: =_xlfn.LET(_xlpm.m,IF(ISNUMBER(AT$4),DATE(YEAR(AT$4),MONTH(AT$4),1),DATEVALUE("1-"&AT$4)),IF(OR(COUNTA($A8:$F8)>0,$G8<>""),$N8/12*IF($F8="",1,MAX(0,(EOMONTH(_xlpm.m,0)-MAX($F8,_xlpm.m)+1)/(EOMONTH(_xlpm.m,0)-_xlpm.m+1))),"")) | AU8: =_xlfn.LET(_xlpm.m,IF(ISNUMBER(AU$4),DATE(YEAR(AU$4),MONTH(AU$4),1),DATEVALUE("1-"&AU$4)),IF(OR(COUNTA($A8:$F8)>0,$G8<>""),$N8/12*IF($F8="",1,MAX(0,(EOMONTH(_xlpm.m,0)-MAX($F8,_xlpm.m)+1)/(EOMONTH(_xlpm.m,0)-_xlpm.m+1))),"")) | AV8: =_xlfn.LET(_xlpm.m,IF(ISNUMBER(AV$4),DATE(YEAR(AV$4),MONTH(AV$4),1),DATEVALUE("1-"&AV$4)),IF(OR(COUNTA($A8:$F8)>0,$G8<>""),$N8/12*IF($F8="",1,MAX(0,(EOMONTH(_xlpm.m,0)-MAX($F8,_xlpm.m)+1)/(EOMONTH(_xlpm.m,0)-_xlpm.m+1))),"")) | ... AZ8: =_xlfn.LET(_xlpm.m,IF(ISNUMBER(AZ$4),DATE(YEAR(AZ$4),MONTH(AZ$4),1),DATEVALUE("1-"&AZ$4)),IF(OR(COUNTA($A8:$F8)>0,$G8<>""),$N8/12*IF($F8="",1,MAX(0,(EOMONTH(_xlpm.m,0)-MAX($F8,_xlpm.m)+1)/(EOMONTH(_xlpm.m,0)-_xlpm.m+1))),"")) | BA8: =IF(OR(COUNTA($A8:$F8)>0,$G8<>""),SUM(AO8:AZ8),"")
I9: =IF(OR(COUNTA(tblPayrollIncrementalSpend2[[#This Row],[Job Title]:[Hire Date]])>0,AND(ROW()=ROW(G9),tblPayrollIncrementalSpend2[[#This Row],[Base Salary]]<>"")),N(tblPayrollIncrementalSpend2[[#This Row],[Base Salary]])*N(tblPayrollIncrementalSpend2[[#This Row],[Bonus %]]),"") | J9: =IF(OR(COUNTA(tblPayrollIncrementalSpend2[[#This Row],[Job Title]:[Hire Date]])>0,AND(ROW()=ROW(G9),tblPayrollIncrementalSpend2[[#This Row],[Base Salary]]<>"")),N(tblPayrollIncrementalSpend2[[#This Row],[Base Salary]])*'Base - Payroll'!$E$12,"") | K9: =IF(OR(COUNTA(tblPayrollIncrementalSpend2[[#This Row],[Job Title]:[Hire Date]])>0,AND(ROW()=ROW(G9),tblPayrollIncrementalSpend2[[#This Row],[Base Salary]]<>"")),N(tblPayrollIncrementalSpend2[[#This Row],[Base Salary]])*'Base - Payroll'!$E$13,"") | L9: =IF(OR(COUNTA(tblPayrollIncrementalSpend2[[#This Row],[Job Title]:[Hire Date]])>0,AND(ROW()=ROW(G9),tblPayrollIncrementalSpend2[[#This Row],[Base Salary]]<>"")),N(tblPayrollIncrementalSpend2[[#This Row],[Base Salary]])*'Base - Payroll'!$E$15,"") | M9: =IF(OR(COUNTA(tblPayrollIncrementalSpend2[[#This Row],[Job Title]:[Hire Date]])>0,AND(ROW()=ROW(G9),tblPayrollIncrementalSpend2[[#This Row],[Base Salary]]<>"")),N(tblPayrollIncrementalSpend2[[#This Row],[Base Salary]])*'Base - Payroll'!$E$16,"") | N9: =IF(OR(COUNTA(tblPayrollIncrementalSpend2[[#This Row],[Job Title]:[Hire Date]])>0,AND(ROW()=ROW(G9),tblPayrollIncrementalSpend2[[#This Row],[Base Salary]]<>"")),N(tblPayrollIncrementalSpend2[[#This Row],[Base Salary]])+SUM(tblPayrollIncrementalSpend2[[#This Row],[Bonus]:[Other]]),"") | O9: =_xlfn.LET(_xlpm.m,IF(ISNUMBER(O$4),DATE(YEAR(O$4),MONTH(O$4),1),DATEVALUE("1-"&O$4)),IF(OR(COUNTA($A9:$F9)>0,$G9<>""),$N9/12*IF($F9="",1,MAX(0,(EOMONTH(_xlpm.m,0)-MAX($F9,_xlpm.m)+1)/(EOMONTH(_xlpm.m,0)-_xlpm.m+1))),"")) | P9: =_xlfn.LET(_xlpm.m,IF(ISNUMBER(P$4),DATE(YEAR(P$4),MONTH(P$4),1),DATEVALUE("1-"&P$4)),IF(OR(COUNTA($A9:$F9)>0,$G9<>""),$N9/12*IF($F9="",1,MAX(0,(EOMONTH(_xlpm.m,0)-MAX($F9,_xlpm.m)+1)/(EOMONTH(_xlpm.m,0)-_xlpm.m+1))),"")) | Q9: =_xlfn.LET(_xlpm.m,IF(ISNUMBER(Q$4),DATE(YEAR(Q$4),MONTH(Q$4),1),DATEVALUE("1-"&Q$4)),IF(OR(COUNTA($A9:$F9)>0,$G9<>""),$N9/12*IF($F9="",1,MAX(0,(EOMONTH(_xlpm.m,0)-MAX($F9,_xlpm.m)+1)/(EOMONTH(_xlpm.m,0)-_xlpm.m+1))),"")) | R9: =_xlfn.LET(_xlpm.m,IF(ISNUMBER(R$4),DATE(YEAR(R$4),MONTH(R$4),1),DATEVALUE("1-"&R$4)),IF(OR(COUNTA($A9:$F9)>0,$G9<>""),$N9/12*IF($F9="",1,MAX(0,(EOMONTH(_xlpm.m,0)-MAX($F9,_xlpm.m)+1)/(EOMONTH(_xlpm.m,0)-_xlpm.m+1))),"")) | S9: =_xlfn.LET(_xlpm.m,IF(ISNUMBER(S$4),DATE(YEAR(S$4),MONTH(S$4),1),DATEVALUE("1-"&S$4)),IF(OR(COUNTA($A9:$F9)>0,$G9<>""),$N9/12*IF($F9="",1,MAX(0,(EOMONTH(_xlpm.m,0)-MAX($F9,_xlpm.m)+1)/(EOMONTH(_xlpm.m,0)-_xlpm.m+1))),"")) | T9: =_xlfn.LET(_xlpm.m,IF(ISNUMBER(T$4),DATE(YEAR(T$4),MONTH(T$4),1),DATEVALUE("1-"&T$4)),IF(OR(COUNTA($A9:$F9)>0,$G9<>""),$N9/12*IF($F9="",1,MAX(0,(EOMONTH(_xlpm.m,0)-MAX($F9,_xlpm.m)+1)/(EOMONTH(_xlpm.m,0)-_xlpm.m+1))),"")) | U9: =_xlfn.LET(_xlpm.m,IF(ISNUMBER(U$4),DATE(YEAR(U$4),MONTH(U$4),1),DATEVALUE("1-"&U$4)),IF(OR(COUNTA($A9:$F9)>0,$G9<>""),$N9/12*IF($F9="",1,MAX(0,(EOMONTH(_xlpm.m,0)-MAX($F9,_xlpm.m)+1)/(EOMONTH(_xlpm.m,0)-_xlpm.m+1))),"")) | V9: =_xlfn.LET(_xlpm.m,IF(ISNUMBER(V$4),DATE(YEAR(V$4),MONTH(V$4),1),DATEVALUE("1-"&V$4)),IF(OR(COUNTA($A9:$F9)>0,$G9<>""),$N9/12*IF($F9="",1,MAX(0,(EOMONTH(_xlpm.m,0)-MAX($F9,_xlpm.m)+1)/(EOMONTH(_xlpm.m,0)-_xlpm.m+1))),"")) | ... Z9: =_xlfn.LET(_xlpm.m,IF(ISNUMBER(Z$4),DATE(YEAR(Z$4),MONTH(Z$4),1),DATEVALUE("1-"&Z$4)),IF(OR(COUNTA($A9:$F9)>0,$G9<>""),$N9/12*IF($F9="",1,MAX(0,(EOMONTH(_xlpm.m,0)-MAX($F9,_xlpm.m)+1)/(EOMONTH(_xlpm.m,0)-_xlpm.m+1))),"")) | AA9: =IF(OR(COUNTA($A9:$F9)>0,$G9<>""),SUM(O9:Z9),"") | AB9: =_xlfn.LET(_xlpm.m,IF(ISNUMBER(AB$4),DATE(YEAR(AB$4),MONTH(AB$4),1),DATEVALUE("1-"&AB$4)),IF(OR(COUNTA($A9:$F9)>0,$G9<>""),$N9/12*IF($F9="",1,MAX(0,(EOMONTH(_xlpm.m,0)-MAX($F9,_xlpm.m)+1)/(EOMONTH(_xlpm.m,0)-_xlpm.m+1))),"")) | AC9: =_xlfn.LET(_xlpm.m,IF(ISNUMBER(AC$4),DATE(YEAR(AC$4),MONTH(AC$4),1),DATEVALUE("1-"&AC$4)),IF(OR(COUNTA($A9:$F9)>0,$G9<>""),$N9/12*IF($F9="",1,MAX(0,(EOMONTH(_xlpm.m,0)-MAX($F9,_xlpm.m)+1)/(EOMONTH(_xlpm.m,0)-_xlpm.m+1))),"")) | AD9: =_xlfn.LET(_xlpm.m,IF(ISNUMBER(AD$4),DATE(YEAR(AD$4),MONTH(AD$4),1),DATEVALUE("1-"&AD$4)),IF(OR(COUNTA($A9:$F9)>0,$G9<>""),$N9/12*IF($F9="",1,MAX(0,(EOMONTH(_xlpm.m,0)-MAX($F9,_xlpm.m)+1)/(EOMONTH(_xlpm.m,0)-_xlpm.m+1))),"")) | AE9: =_xlfn.LET(_xlpm.m,IF(ISNUMBER(AE$4),DATE(YEAR(AE$4),MONTH(AE$4),1),DATEVALUE("1-"&AE$4)),IF(OR(COUNTA($A9:$F9)>0,$G9<>""),$N9/12*IF($F9="",1,MAX(0,(EOMONTH(_xlpm.m,0)-MAX($F9,_xlpm.m)+1)/(EOMONTH(_xlpm.m,0)-_xlpm.m+1))),"")) | AF9: =_xlfn.LET(_xlpm.m,IF(ISNUMBER(AF$4),DATE(YEAR(AF$4),MONTH(AF$4),1),DATEVALUE("1-"&AF$4)),IF(OR(COUNTA($A9:$F9)>0,$G9<>""),$N9/12*IF($F9="",1,MAX(0,(EOMONTH(_xlpm.m,0)-MAX($F9,_xlpm.m)+1)/(EOMONTH(_xlpm.m,0)-_xlpm.m+1))),"")) | AG9: =_xlfn.LET(_xlpm.m,IF(ISNUMBER(AG$4),DATE(YEAR(AG$4),MONTH(AG$4),1),DATEVALUE("1-"&AG$4)),IF(OR(COUNTA($A9:$F9)>0,$G9<>""),$N9/12*IF($F9="",1,MAX(0,(EOMONTH(_xlpm.m,0)-MAX($F9,_xlpm.m)+1)/(EOMONTH(_xlpm.m,0)-_xlpm.m+1))),"")) | AH9: =_xlfn.LET(_xlpm.m,IF(ISNUMBER(AH$4),DATE(YEAR(AH$4),MONTH(AH$4),1),DATEVALUE("1-"&AH$4)),IF(OR(COUNTA($A9:$F9)>0,$G9<>""),$N9/12*IF($F9="",1,MAX(0,(EOMONTH(_xlpm.m,0)-MAX($F9,_xlpm.m)+1)/(EOMONTH(_xlpm.m,0)-_xlpm.m+1))),"")) | AI9: =_xlfn.LET(_xlpm.m,IF(ISNUMBER(AI$4),DATE(YEAR(AI$4),MONTH(AI$4),1),DATEVALUE("1-"&AI$4)),IF(OR(COUNTA($A9:$F9)>0,$G9<>""),$N9/12*IF($F9="",1,MAX(0,(EOMONTH(_xlpm.m,0)-MAX($F9,_xlpm.m)+1)/(EOMONTH(_xlpm.m,0)-_xlpm.m+1))),"")) | ... AM9: =_xlfn.LET(_xlpm.m,IF(ISNUMBER(AM$4),DATE(YEAR(AM$4),MONTH(AM$4),1),DATEVALUE("1-"&AM$4)),IF(OR(COUNTA($A9:$F9)>0,$G9<>""),$N9/12*IF($F9="",1,MAX(0,(EOMONTH(_xlpm.m,0)-MAX($F9,_xlpm.m)+1)/(EOMONTH(_xlpm.m,0)-_xlpm.m+1))),"")) | AN9: =IF(OR(COUNTA($A9:$F9)>0,$G9<>""),SUM(AB9:AM9),"") | AO9: =_xlfn.LET(_xlpm.m,IF(ISNUMBER(AO$4),DATE(YEAR(AO$4),MONTH(AO$4),1),DATEVALUE("1-"&AO$4)),IF(OR(COUNTA($A9:$F9)>0,$G9<>""),$N9/12*IF($F9="",1,MAX(0,(EOMONTH(_xlpm.m,0)-MAX($F9,_xlpm.m)+1)/(EOMONTH(_xlpm.m,0)-_xlpm.m+1))),"")) | AP9: =_xlfn.LET(_xlpm.m,IF(ISNUMBER(AP$4),DATE(YEAR(AP$4),MONTH(AP$4),1),DATEVALUE("1-"&AP$4)),IF(OR(COUNTA($A9:$F9)>0,$G9<>""),$N9/12*IF($F9="",1,MAX(0,(EOMONTH(_xlpm.m,0)-MAX($F9,_xlpm.m)+1)/(EOMONTH(_xlpm.m,0)-_xlpm.m+1))),"")) | AQ9: =_xlfn.LET(_xlpm.m,IF(ISNUMBER(AQ$4),DATE(YEAR(AQ$4),MONTH(AQ$4),1),DATEVALUE("1-"&AQ$4)),IF(OR(COUNTA($A9:$F9)>0,$G9<>""),$N9/12*IF($F9="",1,MAX(0,(EOMONTH(_xlpm.m,0)-MAX($F9,_xlpm.m)+1)/(EOMONTH(_xlpm.m,0)-_xlpm.m+1))),"")) | AR9: =_xlfn.LET(_xlpm.m,IF(ISNUMBER(AR$4),DATE(YEAR(AR$4),MONTH(AR$4),1),DATEVALUE("1-"&AR$4)),IF(OR(COUNTA($A9:$F9)>0,$G9<>""),$N9/12*IF($F9="",1,MAX(0,(EOMONTH(_xlpm.m,0)-MAX($F9,_xlpm.m)+1)/(EOMONTH(_xlpm.m,0)-_xlpm.m+1))),"")) | AS9: =_xlfn.LET(_xlpm.m,IF(ISNUMBER(AS$4),DATE(YEAR(AS$4),MONTH(AS$4),1),DATEVALUE("1-"&AS$4)),IF(OR(COUNTA($A9:$F9)>0,$G9<>""),$N9/12*IF($F9="",1,MAX(0,(EOMONTH(_xlpm.m,0)-MAX($F9,_xlpm.m)+1)/(EOMONTH(_xlpm.m,0)-_xlpm.m+1))),"")) | AT9: =_xlfn.LET(_xlpm.m,IF(ISNUMBER(AT$4),DATE(YEAR(AT$4),MONTH(AT$4),1),DATEVALUE("1-"&AT$4)),IF(OR(COUNTA($A9:$F9)>0,$G9<>""),$N9/12*IF($F9="",1,MAX(0,(EOMONTH(_xlpm.m,0)-MAX($F9,_xlpm.m)+1)/(EOMONTH(_xlpm.m,0)-_xlpm.m+1))),"")) | AU9: =_xlfn.LET(_xlpm.m,IF(ISNUMBER(AU$4),DATE(YEAR(AU$4),MONTH(AU$4),1),DATEVALUE("1-"&AU$4)),IF(OR(COUNTA($A9:$F9)>0,$G9<>""),$N9/12*IF($F9="",1,MAX(0,(EOMONTH(_xlpm.m,0)-MAX($F9,_xlpm.m)+1)/(EOMONTH(_xlpm.m,0)-_xlpm.m+1))),"")) | AV9: =_xlfn.LET(_xlpm.m,IF(ISNUMBER(AV$4),DATE(YEAR(AV$4),MONTH(AV$4),1),DATEVALUE("1-"&AV$4)),IF(OR(COUNTA($A9:$F9)>0,$G9<>""),$N9/12*IF($F9="",1,MAX(0,(EOMONTH(_xlpm.m,0)-MAX($F9,_xlpm.m)+1)/(EOMONTH(_xlpm.m,0)-_xlpm.m+1))),"")) | ... AZ9: =_xlfn.LET(_xlpm.m,IF(ISNUMBER(AZ$4),DATE(YEAR(AZ$4),MONTH(AZ$4),1),DATEVALUE("1-"&AZ$4)),IF(OR(COUNTA($A9:$F9)>0,$G9<>""),$N9/12*IF($F9="",1,MAX(0,(EOMONTH(_xlpm.m,0)-MAX($F9,_xlpm.m)+1)/(EOMONTH(_xlpm.m,0)-_xlpm.m+1))),"")) | BA9: =IF(OR(COUNTA($A9:$F9)>0,$G9<>""),SUM(AO9:AZ9),"")
I10: =IF(OR(COUNTA(tblPayrollIncrementalSpend2[[#This Row],[Job Title]:[Hire Date]])>0,AND(ROW()=ROW(G10),tblPayrollIncrementalSpend2[[#This Row],[Base Salary]]<>"")),N(tblPayrollIncrementalSpend2[[#This Row],[Base Salary]])*N(tblPayrollIncrementalSpend2[[#This Row],[Bonus %]]),"") | J10: =IF(OR(COUNTA(tblPayrollIncrementalSpend2[[#This Row],[Job Title]:[Hire Date]])>0,AND(ROW()=ROW(G10),tblPayrollIncrementalSpend2[[#This Row],[Base Salary]]<>"")),N(tblPayrollIncrementalSpend2[[#This Row],[Base Salary]])*'Base - Payroll'!$E$12,"") | K10: =IF(OR(COUNTA(tblPayrollIncrementalSpend2[[#This Row],[Job Title]:[Hire Date]])>0,AND(ROW()=ROW(G10),tblPayrollIncrementalSpend2[[#This Row],[Base Salary]]<>"")),N(tblPayrollIncrementalSpend2[[#This Row],[Base Salary]])*'Base - Payroll'!$E$13,"") | L10: =IF(OR(COUNTA(tblPayrollIncrementalSpend2[[#This Row],[Job Title]:[Hire Date]])>0,AND(ROW()=ROW(G10),tblPayrollIncrementalSpend2[[#This Row],[Base Salary]]<>"")),N(tblPayrollIncrementalSpend2[[#This Row],[Base Salary]])*'Base - Payroll'!$E$15,"") | M10: =IF(OR(COUNTA(tblPayrollIncrementalSpend2[[#This Row],[Job Title]:[Hire Date]])>0,AND(ROW()=ROW(G10),tblPayrollIncrementalSpend2[[#This Row],[Base Salary]]<>"")),N(tblPayrollIncrementalSpend2[[#This Row],[Base Salary]])*'Base - Payroll'!$E$16,"") | N10: =IF(OR(COUNTA(tblPayrollIncrementalSpend2[[#This Row],[Job Title]:[Hire Date]])>0,AND(ROW()=ROW(G10),tblPayrollIncrementalSpend2[[#This Row],[Base Salary]]<>"")),N(tblPayrollIncrementalSpend2[[#This Row],[Base Salary]])+SUM(tblPayrollIncrementalSpend2[[#This Row],[Bonus]:[Other]]),"") | O10: =_xlfn.LET(_xlpm.m,IF(ISNUMBER(O$4),DATE(YEAR(O$4),MONTH(O$4),1),DATEVALUE("1-"&O$4)),IF(OR(COUNTA($A10:$F10)>0,$G10<>""),$N10/12*IF($F10="",1,MAX(0,(EOMONTH(_xlpm.m,0)-MAX($F10,_xlpm.m)+1)/(EOMONTH(_xlpm.m,0)-_xlpm.m+1))),"")) | P10: =_xlfn.LET(_xlpm.m,IF(ISNUMBER(P$4),DATE(YEAR(P$4),MONTH(P$4),1),DATEVALUE("1-"&P$4)),IF(OR(COUNTA($A10:$F10)>0,$G10<>""),$N10/12*IF($F10="",1,MAX(0,(EOMONTH(_xlpm.m,0)-MAX($F10,_xlpm.m)+1)/(EOMONTH(_xlpm.m,0)-_xlpm.m+1))),"")) | Q10: =_xlfn.LET(_xlpm.m,IF(ISNUMBER(Q$4),DATE(YEAR(Q$4),MONTH(Q$4),1),DATEVALUE("1-"&Q$4)),IF(OR(COUNTA($A10:$F10)>0,$G10<>""),$N10/12*IF($F10="",1,MAX(0,(EOMONTH(_xlpm.m,0)-MAX($F10,_xlpm.m)+1)/(EOMONTH(_xlpm.m,0)-_xlpm.m+1))),"")) | R10: =_xlfn.LET(_xlpm.m,IF(ISNUMBER(R$4),DATE(YEAR(R$4),MONTH(R$4),1),DATEVALUE("1-"&R$4)),IF(OR(COUNTA($A10:$F10)>0,$G10<>""),$N10/12*IF($F10="",1,MAX(0,(EOMONTH(_xlpm.m,0)-MAX($F10,_xlpm.m)+1)/(EOMONTH(_xlpm.m,0)-_xlpm.m+1))),"")) | S10: =_xlfn.LET(_xlpm.m,IF(ISNUMBER(S$4),DATE(YEAR(S$4),MONTH(S$4),1),DATEVALUE("1-"&S$4)),IF(OR(COUNTA($A10:$F10)>0,$G10<>""),$N10/12*IF($F10="",1,MAX(0,(EOMONTH(_xlpm.m,0)-MAX($F10,_xlpm.m)+1)/(EOMONTH(_xlpm.m,0)-_xlpm.m+1))),"")) | T10: =_xlfn.LET(_xlpm.m,IF(ISNUMBER(T$4),DATE(YEAR(T$4),MONTH(T$4),1),DATEVALUE("1-"&T$4)),IF(OR(COUNTA($A10:$F10)>0,$G10<>""),$N10/12*IF($F10="",1,MAX(0,(EOMONTH(_xlpm.m,0)-MAX($F10,_xlpm.m)+1)/(EOMONTH(_xlpm.m,0)-_xlpm.m+1))),"")) | U10: =_xlfn.LET(_xlpm.m,IF(ISNUMBER(U$4),DATE(YEAR(U$4),MONTH(U$4),1),DATEVALUE("1-"&U$4)),IF(OR(COUNTA($A10:$F10)>0,$G10<>""),$N10/12*IF($F10="",1,MAX(0,(EOMONTH(_xlpm.m,0)-MAX($F10,_xlpm.m)+1)/(EOMONTH(_xlpm.m,0)-_xlpm.m+1))),"")) | V10: =_xlfn.LET(_xlpm.m,IF(ISNUMBER(V$4),DATE(YEAR(V$4),MONTH(V$4),1),DATEVALUE("1-"&V$4)),IF(OR(COUNTA($A10:$F10)>0,$G10<>""),$N10/12*IF($F10="",1,MAX(0,(EOMONTH(_xlpm.m,0)-MAX($F10,_xlpm.m)+1)/(EOMONTH(_xlpm.m,0)-_xlpm.m+1))),"")) | ... Z10: =_xlfn.LET(_xlpm.m,IF(ISNUMBER(Z$4),DATE(YEAR(Z$4),MONTH(Z$4),1),DATEVALUE("1-"&Z$4)),IF(OR(COUNTA($A10:$F10)>0,$G10<>""),$N10/12*IF($F10="",1,MAX(0,(EOMONTH(_xlpm.m,0)-MAX($F10,_xlpm.m)+1)/(EOMONTH(_xlpm.m,0)-_xlpm.m+1))),"")) | AA10: =IF(OR(COUNTA($A10:$F10)>0,$G10<>""),SUM(O10:Z10),"") | AB10: =_xlfn.LET(_xlpm.m,IF(ISNUMBER(AB$4),DATE(YEAR(AB$4),MONTH(AB$4),1),DATEVALUE("1-"&AB$4)),IF(OR(COUNTA($A10:$F10)>0,$G10<>""),$N10/12*IF($F10="",1,MAX(0,(EOMONTH(_xlpm.m,0)-MAX($F10,_xlpm.m)+1)/(EOMONTH(_xlpm.m,0)-_xlpm.m+1))),"")) | AC10: =_xlfn.LET(_xlpm.m,IF(ISNUMBER(AC$4),DATE(YEAR(AC$4),MONTH(AC$4),1),DATEVALUE("1-"&AC$4)),IF(OR(COUNTA($A10:$F10)>0,$G10<>""),$N10/12*IF($F10="",1,MAX(0,(EOMONTH(_xlpm.m,0)-MAX($F10,_xlpm.m)+1)/(EOMONTH(_xlpm.m,0)-_xlpm.m+1))),"")) | AD10: =_xlfn.LET(_xlpm.m,IF(ISNUMBER(AD$4),DATE(YEAR(AD$4),MONTH(AD$4),1),DATEVALUE("1-"&AD$4)),IF(OR(COUNTA($A10:$F10)>0,$G10<>""),$N10/12*IF($F10="",1,MAX(0,(EOMONTH(_xlpm.m,0)-MAX($F10,_xlpm.m)+1)/(EOMONTH(_xlpm.m,0)-_xlpm.m+1))),"")) | AE10: =_xlfn.LET(_xlpm.m,IF(ISNUMBER(AE$4),DATE(YEAR(AE$4),MONTH(AE$4),1),DATEVALUE("1-"&AE$4)),IF(OR(COUNTA($A10:$F10)>0,$G10<>""),$N10/12*IF($F10="",1,MAX(0,(EOMONTH(_xlpm.m,0)-MAX($F10,_xlpm.m)+1)/(EOMONTH(_xlpm.m,0)-_xlpm.m+1))),"")) | AF10: =_xlfn.LET(_xlpm.m,IF(ISNUMBER(AF$4),DATE(YEAR(AF$4),MONTH(AF$4),1),DATEVALUE("1-"&AF$4)),IF(OR(COUNTA($A10:$F10)>0,$G10<>""),$N10/12*IF($F10="",1,MAX(0,(EOMONTH(_xlpm.m,0)-MAX($F10,_xlpm.m)+1)/(EOMONTH(_xlpm.m,0)-_xlpm.m+1))),"")) | AG10: =_xlfn.LET(_xlpm.m,IF(ISNUMBER(AG$4),DATE(YEAR(AG$4),MONTH(AG$4),1),DATEVALUE("1-"&AG$4)),IF(OR(COUNTA($A10:$F10)>0,$G10<>""),$N10/12*IF($F10="",1,MAX(0,(EOMONTH(_xlpm.m,0)-MAX($F10,_xlpm.m)+1)/(EOMONTH(_xlpm.m,0)-_xlpm.m+1))),"")) | AH10: =_xlfn.LET(_xlpm.m,IF(ISNUMBER(AH$4),DATE(YEAR(AH$4),MONTH(AH$4),1),DATEVALUE("1-"&AH$4)),IF(OR(COUNTA($A10:$F10)>0,$G10<>""),$N10/12*IF($F10="",1,MAX(0,(EOMONTH(_xlpm.m,0)-MAX($F10,_xlpm.m)+1)/(EOMONTH(_xlpm.m,0)-_xlpm.m+1))),"")) | AI10: =_xlfn.LET(_xlpm.m,IF(ISNUMBER(AI$4),DATE(YEAR(AI$4),MONTH(AI$4),1),DATEVALUE("1-"&AI$4)),IF(OR(COUNTA($A10:$F10)>0,$G10<>""),$N10/12*IF($F10="",1,MAX(0,(EOMONTH(_xlpm.m,0)-MAX($F10,_xlpm.m)+1)/(EOMONTH(_xlpm.m,0)-_xlpm.m+1))),"")) | ... AM10: =_xlfn.LET(_xlpm.m,IF(ISNUMBER(AM$4),DATE(YEAR(AM$4),MONTH(AM$4),1),DATEVALUE("1-"&AM$4)),IF(OR(COUNTA($A10:$F10)>0,$G10<>""),$N10/12*IF($F10="",1,MAX(0,(EOMONTH(_xlpm.m,0)-MAX($F10,_xlpm.m)+1)/(EOMONTH(_xlpm.m,0)-_xlpm.m+1))),"")) | AN10: =IF(OR(COUNTA($A10:$F10)>0,$G10<>""),SUM(AB10:AM10),"") | AO10: =_xlfn.LET(_xlpm.m,IF(ISNUMBER(AO$4),DATE(YEAR(AO$4),MONTH(AO$4),1),DATEVALUE("1-"&AO$4)),IF(OR(COUNTA($A10:$F10)>0,$G10<>""),$N10/12*IF($F10="",1,MAX(0,(EOMONTH(_xlpm.m,0)-MAX($F10,_xlpm.m)+1)/(EOMONTH(_xlpm.m,0)-_xlpm.m+1))),"")) | AP10: =_xlfn.LET(_xlpm.m,IF(ISNUMBER(AP$4),DATE(YEAR(AP$4),MONTH(AP$4),1),DATEVALUE("1-"&AP$4)),IF(OR(COUNTA($A10:$F10)>0,$G10<>""),$N10/12*IF($F10="",1,MAX(0,(EOMONTH(_xlpm.m,0)-MAX($F10,_xlpm.m)+1)/(EOMONTH(_xlpm.m,0)-_xlpm.m+1))),"")) | AQ10: =_xlfn.LET(_xlpm.m,IF(ISNUMBER(AQ$4),DATE(YEAR(AQ$4),MONTH(AQ$4),1),DATEVALUE("1-"&AQ$4)),IF(OR(COUNTA($A10:$F10)>0,$G10<>""),$N10/12*IF($F10="",1,MAX(0,(EOMONTH(_xlpm.m,0)-MAX($F10,_xlpm.m)+1)/(EOMONTH(_xlpm.m,0)-_xlpm.m+1))),"")) | AR10: =_xlfn.LET(_xlpm.m,IF(ISNUMBER(AR$4),DATE(YEAR(AR$4),MONTH(AR$4),1),DATEVALUE("1-"&AR$4)),IF(OR(COUNTA($A10:$F10)>0,$G10<>""),$N10/12*IF($F10="",1,MAX(0,(EOMONTH(_xlpm.m,0)-MAX($F10,_xlpm.m)+1)/(EOMONTH(_xlpm.m,0)-_xlpm.m+1))),"")) | AS10: =_xlfn.LET(_xlpm.m,IF(ISNUMBER(AS$4),DATE(YEAR(AS$4),MONTH(AS$4),1),DATEVALUE("1-"&AS$4)),IF(OR(COUNTA($A10:$F10)>0,$G10<>""),$N10/12*IF($F10="",1,MAX(0,(EOMONTH(_xlpm.m,0)-MAX($F10,_xlpm.m)+1)/(EOMONTH(_xlpm.m,0)-_xlpm.m+1))),"")) | AT10: =_xlfn.LET(_xlpm.m,IF(ISNUMBER(AT$4),DATE(YEAR(AT$4),MONTH(AT$4),1),DATEVALUE("1-"&AT$4)),IF(OR(COUNTA($A10:$F10)>0,$G10<>""),$N10/12*IF($F10="",1,MAX(0,(EOMONTH(_xlpm.m,0)-MAX($F10,_xlpm.m)+1)/(EOMONTH(_xlpm.m,0)-_xlpm.m+1))),"")) | AU10: =_xlfn.LET(_xlpm.m,IF(ISNUMBER(AU$4),DATE(YEAR(AU$4),MONTH(AU$4),1),DATEVALUE("1-"&AU$4)),IF(OR(COUNTA($A10:$F10)>0,$G10<>""),$N10/12*IF($F10="",1,MAX(0,(EOMONTH(_xlpm.m,0)-MAX($F10,_xlpm.m)+1)/(EOMONTH(_xlpm.m,0)-_xlpm.m+1))),"")) | AV10: =_xlfn.LET(_xlpm.m,IF(ISNUMBER(AV$4),DATE(YEAR(AV$4),MONTH(AV$4),1),DATEVALUE("1-"&AV$4)),IF(OR(COUNTA($A10:$F10)>0,$G10<>""),$N10/12*IF($F10="",1,MAX(0,(EOMONTH(_xlpm.m,0)-MAX($F10,_xlpm.m)+1)/(EOMONTH(_xlpm.m,0)-_xlpm.m+1))),"")) | ... AZ10: =_xlfn.LET(_xlpm.m,IF(ISNUMBER(AZ$4),DATE(YEAR(AZ$4),MONTH(AZ$4),1),DATEVALUE("1-"&AZ$4)),IF(OR(COUNTA($A10:$F10)>0,$G10<>""),$N10/12*IF($F10="",1,MAX(0,(EOMONTH(_xlpm.m,0)-MAX($F10,_xlpm.m)+1)/(EOMONTH(_xlpm.m,0)-_xlpm.m+1))),"")) | BA10: =IF(OR(COUNTA($A10:$F10)>0,$G10<>""),SUM(AO10:AZ10),"")
I11: =IF(OR(COUNTA(tblPayrollIncrementalSpend2[[#This Row],[Job Title]:[Hire Date]])>0,AND(ROW()=ROW(G11),tblPayrollIncrementalSpend2[[#This Row],[Base Salary]]<>"")),N(tblPayrollIncrementalSpend2[[#This Row],[Base Salary]])*N(tblPayrollIncrementalSpend2[[#This Row],[Bonus %]]),"") | J11: =IF(OR(COUNTA(tblPayrollIncrementalSpend2[[#This Row],[Job Title]:[Hire Date]])>0,AND(ROW()=ROW(G11),tblPayrollIncrementalSpend2[[#This Row],[Base Salary]]<>"")),N(tblPayrollIncrementalSpend2[[#This Row],[Base Salary]])*'Base - Payroll'!$E$12,"") | K11: =IF(OR(COUNTA(tblPayrollIncrementalSpend2[[#This Row],[Job Title]:[Hire Date]])>0,AND(ROW()=ROW(G11),tblPayrollIncrementalSpend2[[#This Row],[Base Salary]]<>"")),N(tblPayrollIncrementalSpend2[[#This Row],[Base Salary]])*'Base - Payroll'!$E$13,"") | L11: =IF(OR(COUNTA(tblPayrollIncrementalSpend2[[#This Row],[Job Title]:[Hire Date]])>0,AND(ROW()=ROW(G11),tblPayrollIncrementalSpend2[[#This Row],[Base Salary]]<>"")),N(tblPayrollIncrementalSpend2[[#This Row],[Base Salary]])*'Base - Payroll'!$E$15,"") | M11: =IF(OR(COUNTA(tblPayrollIncrementalSpend2[[#This Row],[Job Title]:[Hire Date]])>0,AND(ROW()=ROW(G11),tblPayrollIncrementalSpend2[[#This Row],[Base Salary]]<>"")),N(tblPayrollIncrementalSpend2[[#This Row],[Base Salary]])*'Base - Payroll'!$E$16,"") | N11: =IF(OR(COUNTA(tblPayrollIncrementalSpend2[[#This Row],[Job Title]:[Hire Date]])>0,AND(ROW()=ROW(G11),tblPayrollIncrementalSpend2[[#This Row],[Base Salary]]<>"")),N(tblPayrollIncrementalSpend2[[#This Row],[Base Salary]])+SUM(tblPayrollIncrementalSpend2[[#This Row],[Bonus]:[Other]]),"") | O11: =_xlfn.LET(_xlpm.m,IF(ISNUMBER(O$4),DATE(YEAR(O$4),MONTH(O$4),1),DATEVALUE("1-"&O$4)),IF(OR(COUNTA($A11:$F11)>0,$G11<>""),$N11/12*IF($F11="",1,MAX(0,(EOMONTH(_xlpm.m,0)-MAX($F11,_xlpm.m)+1)/(EOMONTH(_xlpm.m,0)-_xlpm.m+1))),"")) | P11: =_xlfn.LET(_xlpm.m,IF(ISNUMBER(P$4),DATE(YEAR(P$4),MONTH(P$4),1),DATEVALUE("1-"&P$4)),IF(OR(COUNTA($A11:$F11)>0,$G11<>""),$N11/12*IF($F11="",1,MAX(0,(EOMONTH(_xlpm.m,0)-MAX($F11,_xlpm.m)+1)/(EOMONTH(_xlpm.m,0)-_xlpm.m+1))),"")) | Q11: =_xlfn.LET(_xlpm.m,IF(ISNUMBER(Q$4),DATE(YEAR(Q$4),MONTH(Q$4),1),DATEVALUE("1-"&Q$4)),IF(OR(COUNTA($A11:$F11)>0,$G11<>""),$N11/12*IF($F11="",1,MAX(0,(EOMONTH(_xlpm.m,0)-MAX($F11,_xlpm.m)+1)/(EOMONTH(_xlpm.m,0)-_xlpm.m+1))),"")) | R11: =_xlfn.LET(_xlpm.m,IF(ISNUMBER(R$4),DATE(YEAR(R$4),MONTH(R$4),1),DATEVALUE("1-"&R$4)),IF(OR(COUNTA($A11:$F11)>0,$G11<>""),$N11/12*IF($F11="",1,MAX(0,(EOMONTH(_xlpm.m,0)-MAX($F11,_xlpm.m)+1)/(EOMONTH(_xlpm.m,0)-_xlpm.m+1))),"")) | S11: =_xlfn.LET(_xlpm.m,IF(ISNUMBER(S$4),DATE(YEAR(S$4),MONTH(S$4),1),DATEVALUE("1-"&S$4)),IF(OR(COUNTA($A11:$F11)>0,$G11<>""),$N11/12*IF($F11="",1,MAX(0,(EOMONTH(_xlpm.m,0)-MAX($F11,_xlpm.m)+1)/(EOMONTH(_xlpm.m,0)-_xlpm.m+1))),"")) | T11: =_xlfn.LET(_xlpm.m,IF(ISNUMBER(T$4),DATE(YEAR(T$4),MONTH(T$4),1),DATEVALUE("1-"&T$4)),IF(OR(COUNTA($A11:$F11)>0,$G11<>""),$N11/12*IF($F11="",1,MAX(0,(EOMONTH(_xlpm.m,0)-MAX($F11,_xlpm.m)+1)/(EOMONTH(_xlpm.m,0)-_xlpm.m+1))),"")) | U11: =_xlfn.LET(_xlpm.m,IF(ISNUMBER(U$4),DATE(YEAR(U$4),MONTH(U$4),1),DATEVALUE("1-"&U$4)),IF(OR(COUNTA($A11:$F11)>0,$G11<>""),$N11/12*IF($F11="",1,MAX(0,(EOMONTH(_xlpm.m,0)-MAX($F11,_xlpm.m)+1)/(EOMONTH(_xlpm.m,0)-_xlpm.m+1))),"")) | V11: =_xlfn.LET(_xlpm.m,IF(ISNUMBER(V$4),DATE(YEAR(V$4),MONTH(V$4),1),DATEVALUE("1-"&V$4)),IF(OR(COUNTA($A11:$F11)>0,$G11<>""),$N11/12*IF($F11="",1,MAX(0,(EOMONTH(_xlpm.m,0)-MAX($F11,_xlpm.m)+1)/(EOMONTH(_xlpm.m,0)-_xlpm.m+1))),"")) | ... Z11: =_xlfn.LET(_xlpm.m,IF(ISNUMBER(Z$4),DATE(YEAR(Z$4),MONTH(Z$4),1),DATEVALUE("1-"&Z$4)),IF(OR(COUNTA($A11:$F11)>0,$G11<>""),$N11/12*IF($F11="",1,MAX(0,(EOMONTH(_xlpm.m,0)-MAX($F11,_xlpm.m)+1)/(EOMONTH(_xlpm.m,0)-_xlpm.m+1))),"")) | AA11: =IF(OR(COUNTA($A11:$F11)>0,$G11<>""),SUM(O11:Z11),"") | AB11: =_xlfn.LET(_xlpm.m,IF(ISNUMBER(AB$4),DATE(YEAR(AB$4),MONTH(AB$4),1),DATEVALUE("1-"&AB$4)),IF(OR(COUNTA($A11:$F11)>0,$G11<>""),$N11/12*IF($F11="",1,MAX(0,(EOMONTH(_xlpm.m,0)-MAX($F11,_xlpm.m)+1)/(EOMONTH(_xlpm.m,0)-_xlpm.m+1))),"")) | AC11: =_xlfn.LET(_xlpm.m,IF(ISNUMBER(AC$4),DATE(YEAR(AC$4),MONTH(AC$4),1),DATEVALUE("1-"&AC$4)),IF(OR(COUNTA($A11:$F11)>0,$G11<>""),$N11/12*IF($F11="",1,MAX(0,(EOMONTH(_xlpm.m,0)-MAX($F11,_xlpm.m)+1)/(EOMONTH(_xlpm.m,0)-_xlpm.m+1))),"")) | AD11: =_xlfn.LET(_xlpm.m,IF(ISNUMBER(AD$4),DATE(YEAR(AD$4),MONTH(AD$4),1),DATEVALUE("1-"&AD$4)),IF(OR(COUNTA($A11:$F11)>0,$G11<>""),$N11/12*IF($F11="",1,MAX(0,(EOMONTH(_xlpm.m,0)-MAX($F11,_xlpm.m)+1)/(EOMONTH(_xlpm.m,0)-_xlpm.m+1))),"")) | AE11: =_xlfn.LET(_xlpm.m,IF(ISNUMBER(AE$4),DATE(YEAR(AE$4),MONTH(AE$4),1),DATEVALUE("1-"&AE$4)),IF(OR(COUNTA($A11:$F11)>0,$G11<>""),$N11/12*IF($F11="",1,MAX(0,(EOMONTH(_xlpm.m,0)-MAX($F11,_xlpm.m)+1)/(EOMONTH(_xlpm.m,0)-_xlpm.m+1))),"")) | AF11: =_xlfn.LET(_xlpm.m,IF(ISNUMBER(AF$4),DATE(YEAR(AF$4),MONTH(AF$4),1),DATEVALUE("1-"&AF$4)),IF(OR(COUNTA($A11:$F11)>0,$G11<>""),$N11/12*IF($F11="",1,MAX(0,(EOMONTH(_xlpm.m,0)-MAX($F11,_xlpm.m)+1)/(EOMONTH(_xlpm.m,0)-_xlpm.m+1))),"")) | AG11: =_xlfn.LET(_xlpm.m,IF(ISNUMBER(AG$4),DATE(YEAR(AG$4),MONTH(AG$4),1),DATEVALUE("1-"&AG$4)),IF(OR(COUNTA($A11:$F11)>0,$G11<>""),$N11/12*IF($F11="",1,MAX(0,(EOMONTH(_xlpm.m,0)-MAX($F11,_xlpm.m)+1)/(EOMONTH(_xlpm.m,0)-_xlpm.m+1))),"")) | AH11: =_xlfn.LET(_xlpm.m,IF(ISNUMBER(AH$4),DATE(YEAR(AH$4),MONTH(AH$4),1),DATEVALUE("1-"&AH$4)),IF(OR(COUNTA($A11:$F11)>0,$G11<>""),$N11/12*IF($F11="",1,MAX(0,(EOMONTH(_xlpm.m,0)-MAX($F11,_xlpm.m)+1)/(EOMONTH(_xlpm.m,0)-_xlpm.m+1))),"")) | AI11: =_xlfn.LET(_xlpm.m,IF(ISNUMBER(AI$4),DATE(YEAR(AI$4),MONTH(AI$4),1),DATEVALUE("1-"&AI$4)),IF(OR(COUNTA($A11:$F11)>0,$G11<>""),$N11/12*IF($F11="",1,MAX(0,(EOMONTH(_xlpm.m,0)-MAX($F11,_xlpm.m)+1)/(EOMONTH(_xlpm.m,0)-_xlpm.m+1))),"")) | ... AM11: =_xlfn.LET(_xlpm.m,IF(ISNUMBER(AM$4),DATE(YEAR(AM$4),MONTH(AM$4),1),DATEVALUE("1-"&AM$4)),IF(OR(COUNTA($A11:$F11)>0,$G11<>""),$N11/12*IF($F11="",1,MAX(0,(EOMONTH(_xlpm.m,0)-MAX($F11,_xlpm.m)+1)/(EOMONTH(_xlpm.m,0)-_xlpm.m+1))),"")) | AN11: =IF(OR(COUNTA($A11:$F11)>0,$G11<>""),SUM(AB11:AM11),"") | AO11: =_xlfn.LET(_xlpm.m,IF(ISNUMBER(AO$4),DATE(YEAR(AO$4),MONTH(AO$4),1),DATEVALUE("1-"&AO$4)),IF(OR(COUNTA($A11:$F11)>0,$G11<>""),$N11/12*IF($F11="",1,MAX(0,(EOMONTH(_xlpm.m,0)-MAX($F11,_xlpm.m)+1)/(EOMONTH(_xlpm.m,0)-_xlpm.m+1))),"")) | AP11: =_xlfn.LET(_xlpm.m,IF(ISNUMBER(AP$4),DATE(YEAR(AP$4),MONTH(AP$4),1),DATEVALUE("1-"&AP$4)),IF(OR(COUNTA($A11:$F11)>0,$G11<>""),$N11/12*IF($F11="",1,MAX(0,(EOMONTH(_xlpm.m,0)-MAX($F11,_xlpm.m)+1)/(EOMONTH(_xlpm.m,0)-_xlpm.m+1))),"")) | AQ11: =_xlfn.LET(_xlpm.m,IF(ISNUMBER(AQ$4),DATE(YEAR(AQ$4),MONTH(AQ$4),1),DATEVALUE("1-"&AQ$4)),IF(OR(COUNTA($A11:$F11)>0,$G11<>""),$N11/12*IF($F11="",1,MAX(0,(EOMONTH(_xlpm.m,0)-MAX($F11,_xlpm.m)+1)/(EOMONTH(_xlpm.m,0)-_xlpm.m+1))),"")) | AR11: =_xlfn.LET(_xlpm.m,IF(ISNUMBER(AR$4),DATE(YEAR(AR$4),MONTH(AR$4),1),DATEVALUE("1-"&AR$4)),IF(OR(COUNTA($A11:$F11)>0,$G11<>""),$N11/12*IF($F11="",1,MAX(0,(EOMONTH(_xlpm.m,0)-MAX($F11,_xlpm.m)+1)/(EOMONTH(_xlpm.m,0)-_xlpm.m+1))),"")) | AS11: =_xlfn.LET(_xlpm.m,IF(ISNUMBER(AS$4),DATE(YEAR(AS$4),MONTH(AS$4),1),DATEVALUE("1-"&AS$4)),IF(OR(COUNTA($A11:$F11)>0,$G11<>""),$N11/12*IF($F11="",1,MAX(0,(EOMONTH(_xlpm.m,0)-MAX($F11,_xlpm.m)+1)/(EOMONTH(_xlpm.m,0)-_xlpm.m+1))),"")) | AT11: =_xlfn.LET(_xlpm.m,IF(ISNUMBER(AT$4),DATE(YEAR(AT$4),MONTH(AT$4),1),DATEVALUE("1-"&AT$4)),IF(OR(COUNTA($A11:$F11)>0,$G11<>""),$N11/12*IF($F11="",1,MAX(0,(EOMONTH(_xlpm.m,0)-MAX($F11,_xlpm.m)+1)/(EOMONTH(_xlpm.m,0)-_xlpm.m+1))),"")) | AU11: =_xlfn.LET(_xlpm.m,IF(ISNUMBER(AU$4),DATE(YEAR(AU$4),MONTH(AU$4),1),DATEVALUE("1-"&AU$4)),IF(OR(COUNTA($A11:$F11)>0,$G11<>""),$N11/12*IF($F11="",1,MAX(0,(EOMONTH(_xlpm.m,0)-MAX($F11,_xlpm.m)+1)/(EOMONTH(_xlpm.m,0)-_xlpm.m+1))),"")) | AV11: =_xlfn.LET(_xlpm.m,IF(ISNUMBER(AV$4),DATE(YEAR(AV$4),MONTH(AV$4),1),DATEVALUE("1-"&AV$4)),IF(OR(COUNTA($A11:$F11)>0,$G11<>""),$N11/12*IF($F11="",1,MAX(0,(EOMONTH(_xlpm.m,0)-MAX($F11,_xlpm.m)+1)/(EOMONTH(_xlpm.m,0)-_xlpm.m+1))),"")) | ... AZ11: =_xlfn.LET(_xlpm.m,IF(ISNUMBER(AZ$4),DATE(YEAR(AZ$4),MONTH(AZ$4),1),DATEVALUE("1-"&AZ$4)),IF(OR(COUNTA($A11:$F11)>0,$G11<>""),$N11/12*IF($F11="",1,MAX(0,(EOMONTH(_xlpm.m,0)-MAX($F11,_xlpm.m)+1)/(EOMONTH(_xlpm.m,0)-_xlpm.m+1))),"")) | BA11: =IF(OR(COUNTA($A11:$F11)>0,$G11<>""),SUM(AO11:AZ11),"")
I12: =IF(OR(COUNTA(tblPayrollIncrementalSpend2[[#This Row],[Job Title]:[Hire Date]])>0,AND(ROW()=ROW(G12),tblPayrollIncrementalSpend2[[#This Row],[Base Salary]]<>"")),N(tblPayrollIncrementalSpend2[[#This Row],[Base Salary]])*N(tblPayrollIncrementalSpend2[[#This Row],[Bonus %]]),"") | J12: =IF(OR(COUNTA(tblPayrollIncrementalSpend2[[#This Row],[Job Title]:[Hire Date]])>0,AND(ROW()=ROW(G12),tblPayrollIncrementalSpend2[[#This Row],[Base Salary]]<>"")),N(tblPayrollIncrementalSpend2[[#This Row],[Base Salary]])*'Base - Payroll'!$E$12,"") | K12: =IF(OR(COUNTA(tblPayrollIncrementalSpend2[[#This Row],[Job Title]:[Hire Date]])>0,AND(ROW()=ROW(G12),tblPayrollIncrementalSpend2[[#This Row],[Base Salary]]<>"")),N(tblPayrollIncrementalSpend2[[#This Row],[Base Salary]])*'Base - Payroll'!$E$13,"") | L12: =IF(OR(COUNTA(tblPayrollIncrementalSpend2[[#This Row],[Job Title]:[Hire Date]])>0,AND(ROW()=ROW(G12),tblPayrollIncrementalSpend2[[#This Row],[Base Salary]]<>"")),N(tblPayrollIncrementalSpend2[[#This Row],[Base Salary]])*'Base - Payroll'!$E$15,"") | M12: =IF(OR(COUNTA(tblPayrollIncrementalSpend2[[#This Row],[Job Title]:[Hire Date]])>0,AND(ROW()=ROW(G12),tblPayrollIncrementalSpend2[[#This Row],[Base Salary]]<>"")),N(tblPayrollIncrementalSpend2[[#This Row],[Base Salary]])*'Base - Payroll'!$E$16,"") | N12: =IF(OR(COUNTA(tblPayrollIncrementalSpend2[[#This Row],[Job Title]:[Hire Date]])>0,AND(ROW()=ROW(G12),tblPayrollIncrementalSpend2[[#This Row],[Base Salary]]<>"")),N(tblPayrollIncrementalSpend2[[#This Row],[Base Salary]])+SUM(tblPayrollIncrementalSpend2[[#This Row],[Bonus]:[Other]]),"") | O12: =_xlfn.LET(_xlpm.m,IF(ISNUMBER(O$4),DATE(YEAR(O$4),MONTH(O$4),1),DATEVALUE("1-"&O$4)),IF(OR(COUNTA($A12:$F12)>0,$G12<>""),$N12/12*IF($F12="",1,MAX(0,(EOMONTH(_xlpm.m,0)-MAX($F12,_xlpm.m)+1)/(EOMONTH(_xlpm.m,0)-_xlpm.m+1))),"")) | P12: =_xlfn.LET(_xlpm.m,IF(ISNUMBER(P$4),DATE(YEAR(P$4),MONTH(P$4),1),DATEVALUE("1-"&P$4)),IF(OR(COUNTA($A12:$F12)>0,$G12<>""),$N12/12*IF($F12="",1,MAX(0,(EOMONTH(_xlpm.m,0)-MAX($F12,_xlpm.m)+1)/(EOMONTH(_xlpm.m,0)-_xlpm.m+1))),"")) | Q12: =_xlfn.LET(_xlpm.m,IF(ISNUMBER(Q$4),DATE(YEAR(Q$4),MONTH(Q$4),1),DATEVALUE("1-"&Q$4)),IF(OR(COUNTA($A12:$F12)>0,$G12<>""),$N12/12*IF($F12="",1,MAX(0,(EOMONTH(_xlpm.m,0)-MAX($F12,_xlpm.m)+1)/(EOMONTH(_xlpm.m,0)-_xlpm.m+1))),"")) | R12: =_xlfn.LET(_xlpm.m,IF(ISNUMBER(R$4),DATE(YEAR(R$4),MONTH(R$4),1),DATEVALUE("1-"&R$4)),IF(OR(COUNTA($A12:$F12)>0,$G12<>""),$N12/12*IF($F12="",1,MAX(0,(EOMONTH(_xlpm.m,0)-MAX($F12,_xlpm.m)+1)/(EOMONTH(_xlpm.m,0)-_xlpm.m+1))),"")) | S12: =_xlfn.LET(_xlpm.m,IF(ISNUMBER(S$4),DATE(YEAR(S$4),MONTH(S$4),1),DATEVALUE("1-"&S$4)),IF(OR(COUNTA($A12:$F12)>0,$G12<>""),$N12/12*IF($F12="",1,MAX(0,(EOMONTH(_xlpm.m,0)-MAX($F12,_xlpm.m)+1)/(EOMONTH(_xlpm.m,0)-_xlpm.m+1))),"")) | T12: =_xlfn.LET(_xlpm.m,IF(ISNUMBER(T$4),DATE(YEAR(T$4),MONTH(T$4),1),DATEVALUE("1-"&T$4)),IF(OR(COUNTA($A12:$F12)>0,$G12<>""),$N12/12*IF($F12="",1,MAX(0,(EOMONTH(_xlpm.m,0)-MAX($F12,_xlpm.m)+1)/(EOMONTH(_xlpm.m,0)-_xlpm.m+1))),"")) | U12: =_xlfn.LET(_xlpm.m,IF(ISNUMBER(U$4),DATE(YEAR(U$4),MONTH(U$4),1),DATEVALUE("1-"&U$4)),IF(OR(COUNTA($A12:$F12)>0,$G12<>""),$N12/12*IF($F12="",1,MAX(0,(EOMONTH(_xlpm.m,0)-MAX($F12,_xlpm.m)+1)/(EOMONTH(_xlpm.m,0)-_xlpm.m+1))),"")) | V12: =_xlfn.LET(_xlpm.m,IF(ISNUMBER(V$4),DATE(YEAR(V$4),MONTH(V$4),1),DATEVALUE("1-"&V$4)),IF(OR(COUNTA($A12:$F12)>0,$G12<>""),$N12/12*IF($F12="",1,MAX(0,(EOMONTH(_xlpm.m,0)-MAX($F12,_xlpm.m)+1)/(EOMONTH(_xlpm.m,0)-_xlpm.m+1))),"")) | ... Z12: =_xlfn.LET(_xlpm.m,IF(ISNUMBER(Z$4),DATE(YEAR(Z$4),MONTH(Z$4),1),DATEVALUE("1-"&Z$4)),IF(OR(COUNTA($A12:$F12)>0,$G12<>""),$N12/12*IF($F12="",1,MAX(0,(EOMONTH(_xlpm.m,0)-MAX($F12,_xlpm.m)+1)/(EOMONTH(_xlpm.m,0)-_xlpm.m+1))),"")) | AA12: =IF(OR(COUNTA($A12:$F12)>0,$G12<>""),SUM(O12:Z12),"") | AB12: =_xlfn.LET(_xlpm.m,IF(ISNUMBER(AB$4),DATE(YEAR(AB$4),MONTH(AB$4),1),DATEVALUE("1-"&AB$4)),IF(OR(COUNTA($A12:$F12)>0,$G12<>""),$N12/12*IF($F12="",1,MAX(0,(EOMONTH(_xlpm.m,0)-MAX($F12,_xlpm.m)+1)/(EOMONTH(_xlpm.m,0)-_xlpm.m+1))),"")) | AC12: =_xlfn.LET(_xlpm.m,IF(ISNUMBER(AC$4),DATE(YEAR(AC$4),MONTH(AC$4),1),DATEVALUE("1-"&AC$4)),IF(OR(COUNTA($A12:$F12)>0,$G12<>""),$N12/12*IF($F12="",1,MAX(0,(EOMONTH(_xlpm.m,0)-MAX($F12,_xlpm.m)+1)/(EOMONTH(_xlpm.m,0)-_xlpm.m+1))),"")) | AD12: =_xlfn.LET(_xlpm.m,IF(ISNUMBER(AD$4),DATE(YEAR(AD$4),MONTH(AD$4),1),DATEVALUE("1-"&AD$4)),IF(OR(COUNTA($A12:$F12)>0,$G12<>""),$N12/12*IF($F12="",1,MAX(0,(EOMONTH(_xlpm.m,0)-MAX($F12,_xlpm.m)+1)/(EOMONTH(_xlpm.m,0)-_xlpm.m+1))),"")) | AE12: =_xlfn.LET(_xlpm.m,IF(ISNUMBER(AE$4),DATE(YEAR(AE$4),MONTH(AE$4),1),DATEVALUE("1-"&AE$4)),IF(OR(COUNTA($A12:$F12)>0,$G12<>""),$N12/12*IF($F12="",1,MAX(0,(EOMONTH(_xlpm.m,0)-MAX($F12,_xlpm.m)+1)/(EOMONTH(_xlpm.m,0)-_xlpm.m+1))),"")) | AF12: =_xlfn.LET(_xlpm.m,IF(ISNUMBER(AF$4),DATE(YEAR(AF$4),MONTH(AF$4),1),DATEVALUE("1-"&AF$4)),IF(OR(COUNTA($A12:$F12)>0,$G12<>""),$N12/12*IF($F12="",1,MAX(0,(EOMONTH(_xlpm.m,0)-MAX($F12,_xlpm.m)+1)/(EOMONTH(_xlpm.m,0)-_xlpm.m+1))),"")) | AG12: =_xlfn.LET(_xlpm.m,IF(ISNUMBER(AG$4),DATE(YEAR(AG$4),MONTH(AG$4),1),DATEVALUE("1-"&AG$4)),IF(OR(COUNTA($A12:$F12)>0,$G12<>""),$N12/12*IF($F12="",1,MAX(0,(EOMONTH(_xlpm.m,0)-MAX($F12,_xlpm.m)+1)/(EOMONTH(_xlpm.m,0)-_xlpm.m+1))),"")) | AH12: =_xlfn.LET(_xlpm.m,IF(ISNUMBER(AH$4),DATE(YEAR(AH$4),MONTH(AH$4),1),DATEVALUE("1-"&AH$4)),IF(OR(COUNTA($A12:$F12)>0,$G12<>""),$N12/12*IF($F12="",1,MAX(0,(EOMONTH(_xlpm.m,0)-MAX($F12,_xlpm.m)+1)/(EOMONTH(_xlpm.m,0)-_xlpm.m+1))),"")) | AI12: =_xlfn.LET(_xlpm.m,IF(ISNUMBER(AI$4),DATE(YEAR(AI$4),MONTH(AI$4),1),DATEVALUE("1-"&AI$4)),IF(OR(COUNTA($A12:$F12)>0,$G12<>""),$N12/12*IF($F12="",1,MAX(0,(EOMONTH(_xlpm.m,0)-MAX($F12,_xlpm.m)+1)/(EOMONTH(_xlpm.m,0)-_xlpm.m+1))),"")) | ... AM12: =_xlfn.LET(_xlpm.m,IF(ISNUMBER(AM$4),DATE(YEAR(AM$4),MONTH(AM$4),1),DATEVALUE("1-"&AM$4)),IF(OR(COUNTA($A12:$F12)>0,$G12<>""),$N12/12*IF($F12="",1,MAX(0,(EOMONTH(_xlpm.m,0)-MAX($F12,_xlpm.m)+1)/(EOMONTH(_xlpm.m,0)-_xlpm.m+1))),"")) | AN12: =IF(OR(COUNTA($A12:$F12)>0,$G12<>""),SUM(AB12:AM12),"") | AO12: =_xlfn.LET(_xlpm.m,IF(ISNUMBER(AO$4),DATE(YEAR(AO$4),MONTH(AO$4),1),DATEVALUE("1-"&AO$4)),IF(OR(COUNTA($A12:$F12)>0,$G12<>""),$N12/12*IF($F12="",1,MAX(0,(EOMONTH(_xlpm.m,0)-MAX($F12,_xlpm.m)+1)/(EOMONTH(_xlpm.m,0)-_xlpm.m+1))),"")) | AP12: =_xlfn.LET(_xlpm.m,IF(ISNUMBER(AP$4),DATE(YEAR(AP$4),MONTH(AP$4),1),DATEVALUE("1-"&AP$4)),IF(OR(COUNTA($A12:$F12)>0,$G12<>""),$N12/12*IF($F12="",1,MAX(0,(EOMONTH(_xlpm.m,0)-MAX($F12,_xlpm.m)+1)/(EOMONTH(_xlpm.m,0)-_xlpm.m+1))),"")) | AQ12: =_xlfn.LET(_xlpm.m,IF(ISNUMBER(AQ$4),DATE(YEAR(AQ$4),MONTH(AQ$4),1),DATEVALUE("1-"&AQ$4)),IF(OR(COUNTA($A12:$F12)>0,$G12<>""),$N12/12*IF($F12="",1,MAX(0,(EOMONTH(_xlpm.m,0)-MAX($F12,_xlpm.m)+1)/(EOMONTH(_xlpm.m,0)-_xlpm.m+1))),"")) | AR12: =_xlfn.LET(_xlpm.m,IF(ISNUMBER(AR$4),DATE(YEAR(AR$4),MONTH(AR$4),1),DATEVALUE("1-"&AR$4)),IF(OR(COUNTA($A12:$F12)>0,$G12<>""),$N12/12*IF($F12="",1,MAX(0,(EOMONTH(_xlpm.m,0)-MAX($F12,_xlpm.m)+1)/(EOMONTH(_xlpm.m,0)-_xlpm.m+1))),"")) | AS12: =_xlfn.LET(_xlpm.m,IF(ISNUMBER(AS$4),DATE(YEAR(AS$4),MONTH(AS$4),1),DATEVALUE("1-"&AS$4)),IF(OR(COUNTA($A12:$F12)>0,$G12<>""),$N12/12*IF($F12="",1,MAX(0,(EOMONTH(_xlpm.m,0)-MAX($F12,_xlpm.m)+1)/(EOMONTH(_xlpm.m,0)-_xlpm.m+1))),"")) | AT12: =_xlfn.LET(_xlpm.m,IF(ISNUMBER(AT$4),DATE(YEAR(AT$4),MONTH(AT$4),1),DATEVALUE("1-"&AT$4)),IF(OR(COUNTA($A12:$F12)>0,$G12<>""),$N12/12*IF($F12="",1,MAX(0,(EOMONTH(_xlpm.m,0)-MAX($F12,_xlpm.m)+1)/(EOMONTH(_xlpm.m,0)-_xlpm.m+1))),"")) | AU12: =_xlfn.LET(_xlpm.m,IF(ISNUMBER(AU$4),DATE(YEAR(AU$4),MONTH(AU$4),1),DATEVALUE("1-"&AU$4)),IF(OR(COUNTA($A12:$F12)>0,$G12<>""),$N12/12*IF($F12="",1,MAX(0,(EOMONTH(_xlpm.m,0)-MAX($F12,_xlpm.m)+1)/(EOMONTH(_xlpm.m,0)-_xlpm.m+1))),"")) | AV12: =_xlfn.LET(_xlpm.m,IF(ISNUMBER(AV$4),DATE(YEAR(AV$4),MONTH(AV$4),1),DATEVALUE("1-"&AV$4)),IF(OR(COUNTA($A12:$F12)>0,$G12<>""),$N12/12*IF($F12="",1,MAX(0,(EOMONTH(_xlpm.m,0)-MAX($F12,_xlpm.m)+1)/(EOMONTH(_xlpm.m,0)-_xlpm.m+1))),"")) | ... AZ12: =_xlfn.LET(_xlpm.m,IF(ISNUMBER(AZ$4),DATE(YEAR(AZ$4),MONTH(AZ$4),1),DATEVALUE("1-"&AZ$4)),IF(OR(COUNTA($A12:$F12)>0,$G12<>""),$N12/12*IF($F12="",1,MAX(0,(EOMONTH(_xlpm.m,0)-MAX($F12,_xlpm.m)+1)/(EOMONTH(_xlpm.m,0)-_xlpm.m+1))),"")) | BA12: =IF(OR(COUNTA($A12:$F12)>0,$G12<>""),SUM(AO12:AZ12),"")
I13: =IF(OR(COUNTA(tblPayrollIncrementalSpend2[[#This Row],[Job Title]:[Hire Date]])>0,AND(ROW()=ROW(G13),tblPayrollIncrementalSpend2[[#This Row],[Base Salary]]<>"")),N(tblPayrollIncrementalSpend2[[#This Row],[Base Salary]])*N(tblPayrollIncrementalSpend2[[#This Row],[Bonus %]]),"") | J13: =IF(OR(COUNTA(tblPayrollIncrementalSpend2[[#This Row],[Job Title]:[Hire Date]])>0,AND(ROW()=ROW(G13),tblPayrollIncrementalSpend2[[#This Row],[Base Salary]]<>"")),N(tblPayrollIncrementalSpend2[[#This Row],[Base Salary]])*'Base - Payroll'!$E$12,"") | K13: =IF(OR(COUNTA(tblPayrollIncrementalSpend2[[#This Row],[Job Title]:[Hire Date]])>0,AND(ROW()=ROW(G13),tblPayrollIncrementalSpend2[[#This Row],[Base Salary]]<>"")),N(tblPayrollIncrementalSpend2[[#This Row],[Base Salary]])*'Base - Payroll'!$E$13,"") | L13: =IF(OR(COUNTA(tblPayrollIncrementalSpend2[[#This Row],[Job Title]:[Hire Date]])>0,AND(ROW()=ROW(G13),tblPayrollIncrementalSpend2[[#This Row],[Base Salary]]<>"")),N(tblPayrollIncrementalSpend2[[#This Row],[Base Salary]])*'Base - Payroll'!$E$15,"") | M13: =IF(OR(COUNTA(tblPayrollIncrementalSpend2[[#This Row],[Job Title]:[Hire Date]])>0,AND(ROW()=ROW(G13),tblPayrollIncrementalSpend2[[#This Row],[Base Salary]]<>"")),N(tblPayrollIncrementalSpend2[[#This Row],[Base Salary]])*'Base - Payroll'!$E$16,"") | N13: =IF(OR(COUNTA(tblPayrollIncrementalSpend2[[#This Row],[Job Title]:[Hire Date]])>0,AND(ROW()=ROW(G13),tblPayrollIncrementalSpend2[[#This Row],[Base Salary]]<>"")),N(tblPayrollIncrementalSpend2[[#This Row],[Base Salary]])+SUM(tblPayrollIncrementalSpend2[[#This Row],[Bonus]:[Other]]),"") | O13: =_xlfn.LET(_xlpm.m,IF(ISNUMBER(O$4),DATE(YEAR(O$4),MONTH(O$4),1),DATEVALUE("1-"&O$4)),IF(OR(COUNTA($A13:$F13)>0,$G13<>""),$N13/12*IF($F13="",1,MAX(0,(EOMONTH(_xlpm.m,0)-MAX($F13,_xlpm.m)+1)/(EOMONTH(_xlpm.m,0)-_xlpm.m+1))),"")) | P13: =_xlfn.LET(_xlpm.m,IF(ISNUMBER(P$4),DATE(YEAR(P$4),MONTH(P$4),1),DATEVALUE("1-"&P$4)),IF(OR(COUNTA($A13:$F13)>0,$G13<>""),$N13/12*IF($F13="",1,MAX(0,(EOMONTH(_xlpm.m,0)-MAX($F13,_xlpm.m)+1)/(EOMONTH(_xlpm.m,0)-_xlpm.m+1))),"")) | Q13: =_xlfn.LET(_xlpm.m,IF(ISNUMBER(Q$4),DATE(YEAR(Q$4),MONTH(Q$4),1),DATEVALUE("1-"&Q$4)),IF(OR(COUNTA($A13:$F13)>0,$G13<>""),$N13/12*IF($F13="",1,MAX(0,(EOMONTH(_xlpm.m,0)-MAX($F13,_xlpm.m)+1)/(EOMONTH(_xlpm.m,0)-_xlpm.m+1))),"")) | R13: =_xlfn.LET(_xlpm.m,IF(ISNUMBER(R$4),DATE(YEAR(R$4),MONTH(R$4),1),DATEVALUE("1-"&R$4)),IF(OR(COUNTA($A13:$F13)>0,$G13<>""),$N13/12*IF($F13="",1,MAX(0,(EOMONTH(_xlpm.m,0)-MAX($F13,_xlpm.m)+1)/(EOMONTH(_xlpm.m,0)-_xlpm.m+1))),"")) | S13: =_xlfn.LET(_xlpm.m,IF(ISNUMBER(S$4),DATE(YEAR(S$4),MONTH(S$4),1),DATEVALUE("1-"&S$4)),IF(OR(COUNTA($A13:$F13)>0,$G13<>""),$N13/12*IF($F13="",1,MAX(0,(EOMONTH(_xlpm.m,0)-MAX($F13,_xlpm.m)+1)/(EOMONTH(_xlpm.m,0)-_xlpm.m+1))),"")) | T13: =_xlfn.LET(_xlpm.m,IF(ISNUMBER(T$4),DATE(YEAR(T$4),MONTH(T$4),1),DATEVALUE("1-"&T$4)),IF(OR(COUNTA($A13:$F13)>0,$G13<>""),$N13/12*IF($F13="",1,MAX(0,(EOMONTH(_xlpm.m,0)-MAX($F13,_xlpm.m)+1)/(EOMONTH(_xlpm.m,0)-_xlpm.m+1))),"")) | U13: =_xlfn.LET(_xlpm.m,IF(ISNUMBER(U$4),DATE(YEAR(U$4),MONTH(U$4),1),DATEVALUE("1-"&U$4)),IF(OR(COUNTA($A13:$F13)>0,$G13<>""),$N13/12*IF($F13="",1,MAX(0,(EOMONTH(_xlpm.m,0)-MAX($F13,_xlpm.m)+1)/(EOMONTH(_xlpm.m,0)-_xlpm.m+1))),"")) | V13: =_xlfn.LET(_xlpm.m,IF(ISNUMBER(V$4),DATE(YEAR(V$4),MONTH(V$4),1),DATEVALUE("1-"&V$4)),IF(OR(COUNTA($A13:$F13)>0,$G13<>""),$N13/12*IF($F13="",1,MAX(0,(EOMONTH(_xlpm.m,0)-MAX($F13,_xlpm.m)+1)/(EOMONTH(_xlpm.m,0)-_xlpm.m+1))),"")) | ... Z13: =_xlfn.LET(_xlpm.m,IF(ISNUMBER(Z$4),DATE(YEAR(Z$4),MONTH(Z$4),1),DATEVALUE("1-"&Z$4)),IF(OR(COUNTA($A13:$F13)>0,$G13<>""),$N13/12*IF($F13="",1,MAX(0,(EOMONTH(_xlpm.m,0)-MAX($F13,_xlpm.m)+1)/(EOMONTH(_xlpm.m,0)-_xlpm.m+1))),"")) | AA13: =IF(OR(COUNTA($A13:$F13)>0,$G13<>""),SUM(O13:Z13),"") | AB13: =_xlfn.LET(_xlpm.m,IF(ISNUMBER(AB$4),DATE(YEAR(AB$4),MONTH(AB$4),1),DATEVALUE("1-"&AB$4)),IF(OR(COUNTA($A13:$F13)>0,$G13<>""),$N13/12*IF($F13="",1,MAX(0,(EOMONTH(_xlpm.m,0)-MAX($F13,_xlpm.m)+1)/(EOMONTH(_xlpm.m,0)-_xlpm.m+1))),"")) | AC13: =_xlfn.LET(_xlpm.m,IF(ISNUMBER(AC$4),DATE(YEAR(AC$4),MONTH(AC$4),1),DATEVALUE("1-"&AC$4)),IF(OR(COUNTA($A13:$F13)>0,$G13<>""),$N13/12*IF($F13="",1,MAX(0,(EOMONTH(_xlpm.m,0)-MAX($F13,_xlpm.m)+1)/(EOMONTH(_xlpm.m,0)-_xlpm.m+1))),"")) | AD13: =_xlfn.LET(_xlpm.m,IF(ISNUMBER(AD$4),DATE(YEAR(AD$4),MONTH(AD$4),1),DATEVALUE("1-"&AD$4)),IF(OR(COUNTA($A13:$F13)>0,$G13<>""),$N13/12*IF($F13="",1,MAX(0,(EOMONTH(_xlpm.m,0)-MAX($F13,_xlpm.m)+1)/(EOMONTH(_xlpm.m,0)-_xlpm.m+1))),"")) | AE13: =_xlfn.LET(_xlpm.m,IF(ISNUMBER(AE$4),DATE(YEAR(AE$4),MONTH(AE$4),1),DATEVALUE("1-"&AE$4)),IF(OR(COUNTA($A13:$F13)>0,$G13<>""),$N13/12*IF($F13="",1,MAX(0,(EOMONTH(_xlpm.m,0)-MAX($F13,_xlpm.m)+1)/(EOMONTH(_xlpm.m,0)-_xlpm.m+1))),"")) | AF13: =_xlfn.LET(_xlpm.m,IF(ISNUMBER(AF$4),DATE(YEAR(AF$4),MONTH(AF$4),1),DATEVALUE("1-"&AF$4)),IF(OR(COUNTA($A13:$F13)>0,$G13<>""),$N13/12*IF($F13="",1,MAX(0,(EOMONTH(_xlpm.m,0)-MAX($F13,_xlpm.m)+1)/(EOMONTH(_xlpm.m,0)-_xlpm.m+1))),"")) | AG13: =_xlfn.LET(_xlpm.m,IF(ISNUMBER(AG$4),DATE(YEAR(AG$4),MONTH(AG$4),1),DATEVALUE("1-"&AG$4)),IF(OR(COUNTA($A13:$F13)>0,$G13<>""),$N13/12*IF($F13="",1,MAX(0,(EOMONTH(_xlpm.m,0)-MAX($F13,_xlpm.m)+1)/(EOMONTH(_xlpm.m,0)-_xlpm.m+1))),"")) | AH13: =_xlfn.LET(_xlpm.m,IF(ISNUMBER(AH$4),DATE(YEAR(AH$4),MONTH(AH$4),1),DATEVALUE("1-"&AH$4)),IF(OR(COUNTA($A13:$F13)>0,$G13<>""),$N13/12*IF($F13="",1,MAX(0,(EOMONTH(_xlpm.m,0)-MAX($F13,_xlpm.m)+1)/(EOMONTH(_xlpm.m,0)-_xlpm.m+1))),"")) | AI13: =_xlfn.LET(_xlpm.m,IF(ISNUMBER(AI$4),DATE(YEAR(AI$4),MONTH(AI$4),1),DATEVALUE("1-"&AI$4)),IF(OR(COUNTA($A13:$F13)>0,$G13<>""),$N13/12*IF($F13="",1,MAX(0,(EOMONTH(_xlpm.m,0)-MAX($F13,_xlpm.m)+1)/(EOMONTH(_xlpm.m,0)-_xlpm.m+1))),"")) | ... AM13: =_xlfn.LET(_xlpm.m,IF(ISNUMBER(AM$4),DATE(YEAR(AM$4),MONTH(AM$4),1),DATEVALUE("1-"&AM$4)),IF(OR(COUNTA($A13:$F13)>0,$G13<>""),$N13/12*IF($F13="",1,MAX(0,(EOMONTH(_xlpm.m,0)-MAX($F13,_xlpm.m)+1)/(EOMONTH(_xlpm.m,0)-_xlpm.m+1))),"")) | AN13: =IF(OR(COUNTA($A13:$F13)>0,$G13<>""),SUM(AB13:AM13),"") | AO13: =_xlfn.LET(_xlpm.m,IF(ISNUMBER(AO$4),DATE(YEAR(AO$4),MONTH(AO$4),1),DATEVALUE("1-"&AO$4)),IF(OR(COUNTA($A13:$F13)>0,$G13<>""),$N13/12*IF($F13="",1,MAX(0,(EOMONTH(_xlpm.m,0)-MAX($F13,_xlpm.m)+1)/(EOMONTH(_xlpm.m,0)-_xlpm.m+1))),"")) | AP13: =_xlfn.LET(_xlpm.m,IF(ISNUMBER(AP$4),DATE(YEAR(AP$4),MONTH(AP$4),1),DATEVALUE("1-"&AP$4)),IF(OR(COUNTA($A13:$F13)>0,$G13<>""),$N13/12*IF($F13="",1,MAX(0,(EOMONTH(_xlpm.m,0)-MAX($F13,_xlpm.m)+1)/(EOMONTH(_xlpm.m,0)-_xlpm.m+1))),"")) | AQ13: =_xlfn.LET(_xlpm.m,IF(ISNUMBER(AQ$4),DATE(YEAR(AQ$4),MONTH(AQ$4),1),DATEVALUE("1-"&AQ$4)),IF(OR(COUNTA($A13:$F13)>0,$G13<>""),$N13/12*IF($F13="",1,MAX(0,(EOMONTH(_xlpm.m,0)-MAX($F13,_xlpm.m)+1)/(EOMONTH(_xlpm.m,0)-_xlpm.m+1))),"")) | AR13: =_xlfn.LET(_xlpm.m,IF(ISNUMBER(AR$4),DATE(YEAR(AR$4),MONTH(AR$4),1),DATEVALUE("1-"&AR$4)),IF(OR(COUNTA($A13:$F13)>0,$G13<>""),$N13/12*IF($F13="",1,MAX(0,(EOMONTH(_xlpm.m,0)-MAX($F13,_xlpm.m)+1)/(EOMONTH(_xlpm.m,0)-_xlpm.m+1))),"")) | AS13: =_xlfn.LET(_xlpm.m,IF(ISNUMBER(AS$4),DATE(YEAR(AS$4),MONTH(AS$4),1),DATEVALUE("1-"&AS$4)),IF(OR(COUNTA($A13:$F13)>0,$G13<>""),$N13/12*IF($F13="",1,MAX(0,(EOMONTH(_xlpm.m,0)-MAX($F13,_xlpm.m)+1)/(EOMONTH(_xlpm.m,0)-_xlpm.m+1))),"")) | AT13: =_xlfn.LET(_xlpm.m,IF(ISNUMBER(AT$4),DATE(YEAR(AT$4),MONTH(AT$4),1),DATEVALUE("1-"&AT$4)),IF(OR(COUNTA($A13:$F13)>0,$G13<>""),$N13/12*IF($F13="",1,MAX(0,(EOMONTH(_xlpm.m,0)-MAX($F13,_xlpm.m)+1)/(EOMONTH(_xlpm.m,0)-_xlpm.m+1))),"")) | AU13: =_xlfn.LET(_xlpm.m,IF(ISNUMBER(AU$4),DATE(YEAR(AU$4),MONTH(AU$4),1),DATEVALUE("1-"&AU$4)),IF(OR(COUNTA($A13:$F13)>0,$G13<>""),$N13/12*IF($F13="",1,MAX(0,(EOMONTH(_xlpm.m,0)-MAX($F13,_xlpm.m)+1)/(EOMONTH(_xlpm.m,0)-_xlpm.m+1))),"")) | AV13: =_xlfn.LET(_xlpm.m,IF(ISNUMBER(AV$4),DATE(YEAR(AV$4),MONTH(AV$4),1),DATEVALUE("1-"&AV$4)),IF(OR(COUNTA($A13:$F13)>0,$G13<>""),$N13/12*IF($F13="",1,MAX(0,(EOMONTH(_xlpm.m,0)-MAX($F13,_xlpm.m)+1)/(EOMONTH(_xlpm.m,0)-_xlpm.m+1))),"")) | ... AZ13: =_xlfn.LET(_xlpm.m,IF(ISNUMBER(AZ$4),DATE(YEAR(AZ$4),MONTH(AZ$4),1),DATEVALUE("1-"&AZ$4)),IF(OR(COUNTA($A13:$F13)>0,$G13<>""),$N13/12*IF($F13="",1,MAX(0,(EOMONTH(_xlpm.m,0)-MAX($F13,_xlpm.m)+1)/(EOMONTH(_xlpm.m,0)-_xlpm.m+1))),"")) | BA13: =IF(OR(COUNTA($A13:$F13)>0,$G13<>""),SUM(AO13:AZ13),"")
I14: =IF(OR(COUNTA(tblPayrollIncrementalSpend2[[#This Row],[Job Title]:[Hire Date]])>0,AND(ROW()=ROW(G14),tblPayrollIncrementalSpend2[[#This Row],[Base Salary]]<>"")),N(tblPayrollIncrementalSpend2[[#This Row],[Base Salary]])*N(tblPayrollIncrementalSpend2[[#This Row],[Bonus %]]),"") | J14: =IF(OR(COUNTA(tblPayrollIncrementalSpend2[[#This Row],[Job Title]:[Hire Date]])>0,AND(ROW()=ROW(G14),tblPayrollIncrementalSpend2[[#This Row],[Base Salary]]<>"")),N(tblPayrollIncrementalSpend2[[#This Row],[Base Salary]])*'Base - Payroll'!$E$12,"") | K14: =IF(OR(COUNTA(tblPayrollIncrementalSpend2[[#This Row],[Job Title]:[Hire Date]])>0,AND(ROW()=ROW(G14),tblPayrollIncrementalSpend2[[#This Row],[Base Salary]]<>"")),N(tblPayrollIncrementalSpend2[[#This Row],[Base Salary]])*'Base - Payroll'!$E$13,"") | L14: =IF(OR(COUNTA(tblPayrollIncrementalSpend2[[#This Row],[Job Title]:[Hire Date]])>0,AND(ROW()=ROW(G14),tblPayrollIncrementalSpend2[[#This Row],[Base Salary]]<>"")),N(tblPayrollIncrementalSpend2[[#This Row],[Base Salary]])*'Base - Payroll'!$E$15,"") | M14: =IF(OR(COUNTA(tblPayrollIncrementalSpend2[[#This Row],[Job Title]:[Hire Date]])>0,AND(ROW()=ROW(G14),tblPayrollIncrementalSpend2[[#This Row],[Base Salary]]<>"")),N(tblPayrollIncrementalSpend2[[#This Row],[Base Salary]])*'Base - Payroll'!$E$16,"") | N14: =IF(OR(COUNTA(tblPayrollIncrementalSpend2[[#This Row],[Job Title]:[Hire Date]])>0,AND(ROW()=ROW(G14),tblPayrollIncrementalSpend2[[#This Row],[Base Salary]]<>"")),N(tblPayrollIncrementalSpend2[[#This Row],[Base Salary]])+SUM(tblPayrollIncrementalSpend2[[#This Row],[Bonus]:[Other]]),"") | O14: =_xlfn.LET(_xlpm.m,IF(ISNUMBER(O$4),DATE(YEAR(O$4),MONTH(O$4),1),DATEVALUE("1-"&O$4)),IF(OR(COUNTA($A14:$F14)>0,$G14<>""),$N14/12*IF($F14="",1,MAX(0,(EOMONTH(_xlpm.m,0)-MAX($F14,_xlpm.m)+1)/(EOMONTH(_xlpm.m,0)-_xlpm.m+1))),"")) | P14: =_xlfn.LET(_xlpm.m,IF(ISNUMBER(P$4),DATE(YEAR(P$4),MONTH(P$4),1),DATEVALUE("1-"&P$4)),IF(OR(COUNTA($A14:$F14)>0,$G14<>""),$N14/12*IF($F14="",1,MAX(0,(EOMONTH(_xlpm.m,0)-MAX($F14,_xlpm.m)+1)/(EOMONTH(_xlpm.m,0)-_xlpm.m+1))),"")) | Q14: =_xlfn.LET(_xlpm.m,IF(ISNUMBER(Q$4),DATE(YEAR(Q$4),MONTH(Q$4),1),DATEVALUE("1-"&Q$4)),IF(OR(COUNTA($A14:$F14)>0,$G14<>""),$N14/12*IF($F14="",1,MAX(0,(EOMONTH(_xlpm.m,0)-MAX($F14,_xlpm.m)+1)/(EOMONTH(_xlpm.m,0)-_xlpm.m+1))),"")) | R14: =_xlfn.LET(_xlpm.m,IF(ISNUMBER(R$4),DATE(YEAR(R$4),MONTH(R$4),1),DATEVALUE("1-"&R$4)),IF(OR(COUNTA($A14:$F14)>0,$G14<>""),$N14/12*IF($F14="",1,MAX(0,(EOMONTH(_xlpm.m,0)-MAX($F14,_xlpm.m)+1)/(EOMONTH(_xlpm.m,0)-_xlpm.m+1))),"")) | S14: =_xlfn.LET(_xlpm.m,IF(ISNUMBER(S$4),DATE(YEAR(S$4),MONTH(S$4),1),DATEVALUE("1-"&S$4)),IF(OR(COUNTA($A14:$F14)>0,$G14<>""),$N14/12*IF($F14="",1,MAX(0,(EOMONTH(_xlpm.m,0)-MAX($F14,_xlpm.m)+1)/(EOMONTH(_xlpm.m,0)-_xlpm.m+1))),"")) | T14: =_xlfn.LET(_xlpm.m,IF(ISNUMBER(T$4),DATE(YEAR(T$4),MONTH(T$4),1),DATEVALUE("1-"&T$4)),IF(OR(COUNTA($A14:$F14)>0,$G14<>""),$N14/12*IF($F14="",1,MAX(0,(EOMONTH(_xlpm.m,0)-MAX($F14,_xlpm.m)+1)/(EOMONTH(_xlpm.m,0)-_xlpm.m+1))),"")) | U14: =_xlfn.LET(_xlpm.m,IF(ISNUMBER(U$4),DATE(YEAR(U$4),MONTH(U$4),1),DATEVALUE("1-"&U$4)),IF(OR(COUNTA($A14:$F14)>0,$G14<>""),$N14/12*IF($F14="",1,MAX(0,(EOMONTH(_xlpm.m,0)-MAX($F14,_xlpm.m)+1)/(EOMONTH(_xlpm.m,0)-_xlpm.m+1))),"")) | V14: =_xlfn.LET(_xlpm.m,IF(ISNUMBER(V$4),DATE(YEAR(V$4),MONTH(V$4),1),DATEVALUE("1-"&V$4)),IF(OR(COUNTA($A14:$F14)>0,$G14<>""),$N14/12*IF($F14="",1,MAX(0,(EOMONTH(_xlpm.m,0)-MAX($F14,_xlpm.m)+1)/(EOMONTH(_xlpm.m,0)-_xlpm.m+1))),"")) | ... Z14: =_xlfn.LET(_xlpm.m,IF(ISNUMBER(Z$4),DATE(YEAR(Z$4),MONTH(Z$4),1),DATEVALUE("1-"&Z$4)),IF(OR(COUNTA($A14:$F14)>0,$G14<>""),$N14/12*IF($F14="",1,MAX(0,(EOMONTH(_xlpm.m,0)-MAX($F14,_xlpm.m)+1)/(EOMONTH(_xlpm.m,0)-_xlpm.m+1))),"")) | AA14: =IF(OR(COUNTA($A14:$F14)>0,$G14<>""),SUM(O14:Z14),"") | AB14: =_xlfn.LET(_xlpm.m,IF(ISNUMBER(AB$4),DATE(YEAR(AB$4),MONTH(AB$4),1),DATEVALUE("1-"&AB$4)),IF(OR(COUNTA($A14:$F14)>0,$G14<>""),$N14/12*IF($F14="",1,MAX(0,(EOMONTH(_xlpm.m,0)-MAX($F14,_xlpm.m)+1)/(EOMONTH(_xlpm.m,0)-_xlpm.m+1))),"")) | AC14: =_xlfn.LET(_xlpm.m,IF(ISNUMBER(AC$4),DATE(YEAR(AC$4),MONTH(AC$4),1),DATEVALUE("1-"&AC$4)),IF(OR(COUNTA($A14:$F14)>0,$G14<>""),$N14/12*IF($F14="",1,MAX(0,(EOMONTH(_xlpm.m,0)-MAX($F14,_xlpm.m)+1)/(EOMONTH(_xlpm.m,0)-_xlpm.m+1))),"")) | AD14: =_xlfn.LET(_xlpm.m,IF(ISNUMBER(AD$4),DATE(YEAR(AD$4),MONTH(AD$4),1),DATEVALUE("1-"&AD$4)),IF(OR(COUNTA($A14:$F14)>0,$G14<>""),$N14/12*IF($F14="",1,MAX(0,(EOMONTH(_xlpm.m,0)-MAX($F14,_xlpm.m)+1)/(EOMONTH(_xlpm.m,0)-_xlpm.m+1))),"")) | AE14: =_xlfn.LET(_xlpm.m,IF(ISNUMBER(AE$4),DATE(YEAR(AE$4),MONTH(AE$4),1),DATEVALUE("1-"&AE$4)),IF(OR(COUNTA($A14:$F14)>0,$G14<>""),$N14/12*IF($F14="",1,MAX(0,(EOMONTH(_xlpm.m,0)-MAX($F14,_xlpm.m)+1)/(EOMONTH(_xlpm.m,0)-_xlpm.m+1))),"")) | AF14: =_xlfn.LET(_xlpm.m,IF(ISNUMBER(AF$4),DATE(YEAR(AF$4),MONTH(AF$4),1),DATEVALUE("1-"&AF$4)),IF(OR(COUNTA($A14:$F14)>0,$G14<>""),$N14/12*IF($F14="",1,MAX(0,(EOMONTH(_xlpm.m,0)-MAX($F14,_xlpm.m)+1)/(EOMONTH(_xlpm.m,0)-_xlpm.m+1))),"")) | AG14: =_xlfn.LET(_xlpm.m,IF(ISNUMBER(AG$4),DATE(YEAR(AG$4),MONTH(AG$4),1),DATEVALUE("1-"&AG$4)),IF(OR(COUNTA($A14:$F14)>0,$G14<>""),$N14/12*IF($F14="",1,MAX(0,(EOMONTH(_xlpm.m,0)-MAX($F14,_xlpm.m)+1)/(EOMONTH(_xlpm.m,0)-_xlpm.m+1))),"")) | AH14: =_xlfn.LET(_xlpm.m,IF(ISNUMBER(AH$4),DATE(YEAR(AH$4),MONTH(AH$4),1),DATEVALUE("1-"&AH$4)),IF(OR(COUNTA($A14:$F14)>0,$G14<>""),$N14/12*IF($F14="",1,MAX(0,(EOMONTH(_xlpm.m,0)-MAX($F14,_xlpm.m)+1)/(EOMONTH(_xlpm.m,0)-_xlpm.m+1))),"")) | AI14: =_xlfn.LET(_xlpm.m,IF(ISNUMBER(AI$4),DATE(YEAR(AI$4),MONTH(AI$4),1),DATEVALUE("1-"&AI$4)),IF(OR(COUNTA($A14:$F14)>0,$G14<>""),$N14/12*IF($F14="",1,MAX(0,(EOMONTH(_xlpm.m,0)-MAX($F14,_xlpm.m)+1)/(EOMONTH(_xlpm.m,0)-_xlpm.m+1))),"")) | ... AM14: =_xlfn.LET(_xlpm.m,IF(ISNUMBER(AM$4),DATE(YEAR(AM$4),MONTH(AM$4),1),DATEVALUE("1-"&AM$4)),IF(OR(COUNTA($A14:$F14)>0,$G14<>""),$N14/12*IF($F14="",1,MAX(0,(EOMONTH(_xlpm.m,0)-MAX($F14,_xlpm.m)+1)/(EOMONTH(_xlpm.m,0)-_xlpm.m+1))),"")) | AN14: =IF(OR(COUNTA($A14:$F14)>0,$G14<>""),SUM(AB14:AM14),"") | AO14: =_xlfn.LET(_xlpm.m,IF(ISNUMBER(AO$4),DATE(YEAR(AO$4),MONTH(AO$4),1),DATEVALUE("1-"&AO$4)),IF(OR(COUNTA($A14:$F14)>0,$G14<>""),$N14/12*IF($F14="",1,MAX(0,(EOMONTH(_xlpm.m,0)-MAX($F14,_xlpm.m)+1)/(EOMONTH(_xlpm.m,0)-_xlpm.m+1))),"")) | AP14: =_xlfn.LET(_xlpm.m,IF(ISNUMBER(AP$4),DATE(YEAR(AP$4),MONTH(AP$4),1),DATEVALUE("1-"&AP$4)),IF(OR(COUNTA($A14:$F14)>0,$G14<>""),$N14/12*IF($F14="",1,MAX(0,(EOMONTH(_xlpm.m,0)-MAX($F14,_xlpm.m)+1)/(EOMONTH(_xlpm.m,0)-_xlpm.m+1))),"")) | AQ14: =_xlfn.LET(_xlpm.m,IF(ISNUMBER(AQ$4),DATE(YEAR(AQ$4),MONTH(AQ$4),1),DATEVALUE("1-"&AQ$4)),IF(OR(COUNTA($A14:$F14)>0,$G14<>""),$N14/12*IF($F14="",1,MAX(0,(EOMONTH(_xlpm.m,0)-MAX($F14,_xlpm.m)+1)/(EOMONTH(_xlpm.m,0)-_xlpm.m+1))),"")) | AR14: =_xlfn.LET(_xlpm.m,IF(ISNUMBER(AR$4),DATE(YEAR(AR$4),MONTH(AR$4),1),DATEVALUE("1-"&AR$4)),IF(OR(COUNTA($A14:$F14)>0,$G14<>""),$N14/12*IF($F14="",1,MAX(0,(EOMONTH(_xlpm.m,0)-MAX($F14,_xlpm.m)+1)/(EOMONTH(_xlpm.m,0)-_xlpm.m+1))),"")) | AS14: =_xlfn.LET(_xlpm.m,IF(ISNUMBER(AS$4),DATE(YEAR(AS$4),MONTH(AS$4),1),DATEVALUE("1-"&AS$4)),IF(OR(COUNTA($A14:$F14)>0,$G14<>""),$N14/12*IF($F14="",1,MAX(0,(EOMONTH(_xlpm.m,0)-MAX($F14,_xlpm.m)+1)/(EOMONTH(_xlpm.m,0)-_xlpm.m+1))),"")) | AT14: =_xlfn.LET(_xlpm.m,IF(ISNUMBER(AT$4),DATE(YEAR(AT$4),MONTH(AT$4),1),DATEVALUE("1-"&AT$4)),IF(OR(COUNTA($A14:$F14)>0,$G14<>""),$N14/12*IF($F14="",1,MAX(0,(EOMONTH(_xlpm.m,0)-MAX($F14,_xlpm.m)+1)/(EOMONTH(_xlpm.m,0)-_xlpm.m+1))),"")) | AU14: =_xlfn.LET(_xlpm.m,IF(ISNUMBER(AU$4),DATE(YEAR(AU$4),MONTH(AU$4),1),DATEVALUE("1-"&AU$4)),IF(OR(COUNTA($A14:$F14)>0,$G14<>""),$N14/12*IF($F14="",1,MAX(0,(EOMONTH(_xlpm.m,0)-MAX($F14,_xlpm.m)+1)/(EOMONTH(_xlpm.m,0)-_xlpm.m+1))),"")) | AV14: =_xlfn.LET(_xlpm.m,IF(ISNUMBER(AV$4),DATE(YEAR(AV$4),MONTH(AV$4),1),DATEVALUE("1-"&AV$4)),IF(OR(COUNTA($A14:$F14)>0,$G14<>""),$N14/12*IF($F14="",1,MAX(0,(EOMONTH(_xlpm.m,0)-MAX($F14,_xlpm.m)+1)/(EOMONTH(_xlpm.m,0)-_xlpm.m+1))),"")) | ... AZ14: =_xlfn.LET(_xlpm.m,IF(ISNUMBER(AZ$4),DATE(YEAR(AZ$4),MONTH(AZ$4),1),DATEVALUE("1-"&AZ$4)),IF(OR(COUNTA($A14:$F14)>0,$G14<>""),$N14/12*IF($F14="",1,MAX(0,(EOMONTH(_xlpm.m,0)-MAX($F14,_xlpm.m)+1)/(EOMONTH(_xlpm.m,0)-_xlpm.m+1))),"")) | BA14: =IF(OR(COUNTA($A14:$F14)>0,$G14<>""),SUM(AO14:AZ14),"")
I15: =IF(OR(COUNTA(tblPayrollIncrementalSpend2[[#This Row],[Job Title]:[Hire Date]])>0,AND(ROW()=ROW(G15),tblPayrollIncrementalSpend2[[#This Row],[Base Salary]]<>"")),N(tblPayrollIncrementalSpend2[[#This Row],[Base Salary]])*N(tblPayrollIncrementalSpend2[[#This Row],[Bonus %]]),"") | J15: =IF(OR(COUNTA(tblPayrollIncrementalSpend2[[#This Row],[Job Title]:[Hire Date]])>0,AND(ROW()=ROW(G15),tblPayrollIncrementalSpend2[[#This Row],[Base Salary]]<>"")),N(tblPayrollIncrementalSpend2[[#This Row],[Base Salary]])*'Base - Payroll'!$E$12,"") | K15: =IF(OR(COUNTA(tblPayrollIncrementalSpend2[[#This Row],[Job Title]:[Hire Date]])>0,AND(ROW()=ROW(G15),tblPayrollIncrementalSpend2[[#This Row],[Base Salary]]<>"")),N(tblPayrollIncrementalSpend2[[#This Row],[Base Salary]])*'Base - Payroll'!$E$13,"") | L15: =IF(OR(COUNTA(tblPayrollIncrementalSpend2[[#This Row],[Job Title]:[Hire Date]])>0,AND(ROW()=ROW(G15),tblPayrollIncrementalSpend2[[#This Row],[Base Salary]]<>"")),N(tblPayrollIncrementalSpend2[[#This Row],[Base Salary]])*'Base - Payroll'!$E$15,"") | M15: =IF(OR(COUNTA(tblPayrollIncrementalSpend2[[#This Row],[Job Title]:[Hire Date]])>0,AND(ROW()=ROW(G15),tblPayrollIncrementalSpend2[[#This Row],[Base Salary]]<>"")),N(tblPayrollIncrementalSpend2[[#This Row],[Base Salary]])*'Base - Payroll'!$E$16,"") | N15: =IF(OR(COUNTA(tblPayrollIncrementalSpend2[[#This Row],[Job Title]:[Hire Date]])>0,AND(ROW()=ROW(G15),tblPayrollIncrementalSpend2[[#This Row],[Base Salary]]<>"")),N(tblPayrollIncrementalSpend2[[#This Row],[Base Salary]])+SUM(tblPayrollIncrementalSpend2[[#This Row],[Bonus]:[Other]]),"") | O15: =_xlfn.LET(_xlpm.m,IF(ISNUMBER(O$4),DATE(YEAR(O$4),MONTH(O$4),1),DATEVALUE("1-"&O$4)),IF(OR(COUNTA($A15:$F15)>0,$G15<>""),$N15/12*IF($F15="",1,MAX(0,(EOMONTH(_xlpm.m,0)-MAX($F15,_xlpm.m)+1)/(EOMONTH(_xlpm.m,0)-_xlpm.m+1))),"")) | P15: =_xlfn.LET(_xlpm.m,IF(ISNUMBER(P$4),DATE(YEAR(P$4),MONTH(P$4),1),DATEVALUE("1-"&P$4)),IF(OR(COUNTA($A15:$F15)>0,$G15<>""),$N15/12*IF($F15="",1,MAX(0,(EOMONTH(_xlpm.m,0)-MAX($F15,_xlpm.m)+1)/(EOMONTH(_xlpm.m,0)-_xlpm.m+1))),"")) | Q15: =_xlfn.LET(_xlpm.m,IF(ISNUMBER(Q$4),DATE(YEAR(Q$4),MONTH(Q$4),1),DATEVALUE("1-"&Q$4)),IF(OR(COUNTA($A15:$F15)>0,$G15<>""),$N15/12*IF($F15="",1,MAX(0,(EOMONTH(_xlpm.m,0)-MAX($F15,_xlpm.m)+1)/(EOMONTH(_xlpm.m,0)-_xlpm.m+1))),"")) | R15: =_xlfn.LET(_xlpm.m,IF(ISNUMBER(R$4),DATE(YEAR(R$4),MONTH(R$4),1),DATEVALUE("1-"&R$4)),IF(OR(COUNTA($A15:$F15)>0,$G15<>""),$N15/12*IF($F15="",1,MAX(0,(EOMONTH(_xlpm.m,0)-MAX($F15,_xlpm.m)+1)/(EOMONTH(_xlpm.m,0)-_xlpm.m+1))),"")) | S15: =_xlfn.LET(_xlpm.m,IF(ISNUMBER(S$4),DATE(YEAR(S$4),MONTH(S$4),1),DATEVALUE("1-"&S$4)),IF(OR(COUNTA($A15:$F15)>0,$G15<>""),$N15/12*IF($F15="",1,MAX(0,(EOMONTH(_xlpm.m,0)-MAX($F15,_xlpm.m)+1)/(EOMONTH(_xlpm.m,0)-_xlpm.m+1))),"")) | T15: =_xlfn.LET(_xlpm.m,IF(ISNUMBER(T$4),DATE(YEAR(T$4),MONTH(T$4),1),DATEVALUE("1-"&T$4)),IF(OR(COUNTA($A15:$F15)>0,$G15<>""),$N15/12*IF($F15="",1,MAX(0,(EOMONTH(_xlpm.m,0)-MAX($F15,_xlpm.m)+1)/(EOMONTH(_xlpm.m,0)-_xlpm.m+1))),"")) | U15: =_xlfn.LET(_xlpm.m,IF(ISNUMBER(U$4),DATE(YEAR(U$4),MONTH(U$4),1),DATEVALUE("1-"&U$4)),IF(OR(COUNTA($A15:$F15)>0,$G15<>""),$N15/12*IF($F15="",1,MAX(0,(EOMONTH(_xlpm.m,0)-MAX($F15,_xlpm.m)+1)/(EOMONTH(_xlpm.m,0)-_xlpm.m+1))),"")) | V15: =_xlfn.LET(_xlpm.m,IF(ISNUMBER(V$4),DATE(YEAR(V$4),MONTH(V$4),1),DATEVALUE("1-"&V$4)),IF(OR(COUNTA($A15:$F15)>0,$G15<>""),$N15/12*IF($F15="",1,MAX(0,(EOMONTH(_xlpm.m,0)-MAX($F15,_xlpm.m)+1)/(EOMONTH(_xlpm.m,0)-_xlpm.m+1))),"")) | ... Z15: =_xlfn.LET(_xlpm.m,IF(ISNUMBER(Z$4),DATE(YEAR(Z$4),MONTH(Z$4),1),DATEVALUE("1-"&Z$4)),IF(OR(COUNTA($A15:$F15)>0,$G15<>""),$N15/12*IF($F15="",1,MAX(0,(EOMONTH(_xlpm.m,0)-MAX($F15,_xlpm.m)+1)/(EOMONTH(_xlpm.m,0)-_xlpm.m+1))),"")) | AA15: =IF(OR(COUNTA($A15:$F15)>0,$G15<>""),SUM(O15:Z15),"") | AB15: =_xlfn.LET(_xlpm.m,IF(ISNUMBER(AB$4),DATE(YEAR(AB$4),MONTH(AB$4),1),DATEVALUE("1-"&AB$4)),IF(OR(COUNTA($A15:$F15)>0,$G15<>""),$N15/12*IF($F15="",1,MAX(0,(EOMONTH(_xlpm.m,0)-MAX($F15,_xlpm.m)+1)/(EOMONTH(_xlpm.m,0)-_xlpm.m+1))),"")) | AC15: =_xlfn.LET(_xlpm.m,IF(ISNUMBER(AC$4),DATE(YEAR(AC$4),MONTH(AC$4),1),DATEVALUE("1-"&AC$4)),IF(OR(COUNTA($A15:$F15)>0,$G15<>""),$N15/12*IF($F15="",1,MAX(0,(EOMONTH(_xlpm.m,0)-MAX($F15,_xlpm.m)+1)/(EOMONTH(_xlpm.m,0)-_xlpm.m+1))),"")) | AD15: =_xlfn.LET(_xlpm.m,IF(ISNUMBER(AD$4),DATE(YEAR(AD$4),MONTH(AD$4),1),DATEVALUE("1-"&AD$4)),IF(OR(COUNTA($A15:$F15)>0,$G15<>""),$N15/12*IF($F15="",1,MAX(0,(EOMONTH(_xlpm.m,0)-MAX($F15,_xlpm.m)+1)/(EOMONTH(_xlpm.m,0)-_xlpm.m+1))),"")) | AE15: =_xlfn.LET(_xlpm.m,IF(ISNUMBER(AE$4),DATE(YEAR(AE$4),MONTH(AE$4),1),DATEVALUE("1-"&AE$4)),IF(OR(COUNTA($A15:$F15)>0,$G15<>""),$N15/12*IF($F15="",1,MAX(0,(EOMONTH(_xlpm.m,0)-MAX($F15,_xlpm.m)+1)/(EOMONTH(_xlpm.m,0)-_xlpm.m+1))),"")) | AF15: =_xlfn.LET(_xlpm.m,IF(ISNUMBER(AF$4),DATE(YEAR(AF$4),MONTH(AF$4),1),DATEVALUE("1-"&AF$4)),IF(OR(COUNTA($A15:$F15)>0,$G15<>""),$N15/12*IF($F15="",1,MAX(0,(EOMONTH(_xlpm.m,0)-MAX($F15,_xlpm.m)+1)/(EOMONTH(_xlpm.m,0)-_xlpm.m+1))),"")) | AG15: =_xlfn.LET(_xlpm.m,IF(ISNUMBER(AG$4),DATE(YEAR(AG$4),MONTH(AG$4),1),DATEVALUE("1-"&AG$4)),IF(OR(COUNTA($A15:$F15)>0,$G15<>""),$N15/12*IF($F15="",1,MAX(0,(EOMONTH(_xlpm.m,0)-MAX($F15,_xlpm.m)+1)/(EOMONTH(_xlpm.m,0)-_xlpm.m+1))),"")) | AH15: =_xlfn.LET(_xlpm.m,IF(ISNUMBER(AH$4),DATE(YEAR(AH$4),MONTH(AH$4),1),DATEVALUE("1-"&AH$4)),IF(OR(COUNTA($A15:$F15)>0,$G15<>""),$N15/12*IF($F15="",1,MAX(0,(EOMONTH(_xlpm.m,0)-MAX($F15,_xlpm.m)+1)/(EOMONTH(_xlpm.m,0)-_xlpm.m+1))),"")) | AI15: =_xlfn.LET(_xlpm.m,IF(ISNUMBER(AI$4),DATE(YEAR(AI$4),MONTH(AI$4),1),DATEVALUE("1-"&AI$4)),IF(OR(COUNTA($A15:$F15)>0,$G15<>""),$N15/12*IF($F15="",1,MAX(0,(EOMONTH(_xlpm.m,0)-MAX($F15,_xlpm.m)+1)/(EOMONTH(_xlpm.m,0)-_xlpm.m+1))),"")) | ... AM15: =_xlfn.LET(_xlpm.m,IF(ISNUMBER(AM$4),DATE(YEAR(AM$4),MONTH(AM$4),1),DATEVALUE("1-"&AM$4)),IF(OR(COUNTA($A15:$F15)>0,$G15<>""),$N15/12*IF($F15="",1,MAX(0,(EOMONTH(_xlpm.m,0)-MAX($F15,_xlpm.m)+1)/(EOMONTH(_xlpm.m,0)-_xlpm.m+1))),"")) | AN15: =IF(OR(COUNTA($A15:$F15)>0,$G15<>""),SUM(AB15:AM15),"") | AO15: =_xlfn.LET(_xlpm.m,IF(ISNUMBER(AO$4),DATE(YEAR(AO$4),MONTH(AO$4),1),DATEVALUE("1-"&AO$4)),IF(OR(COUNTA($A15:$F15)>0,$G15<>""),$N15/12*IF($F15="",1,MAX(0,(EOMONTH(_xlpm.m,0)-MAX($F15,_xlpm.m)+1)/(EOMONTH(_xlpm.m,0)-_xlpm.m+1))),"")) | AP15: =_xlfn.LET(_xlpm.m,IF(ISNUMBER(AP$4),DATE(YEAR(AP$4),MONTH(AP$4),1),DATEVALUE("1-"&AP$4)),IF(OR(COUNTA($A15:$F15)>0,$G15<>""),$N15/12*IF($F15="",1,MAX(0,(EOMONTH(_xlpm.m,0)-MAX($F15,_xlpm.m)+1)/(EOMONTH(_xlpm.m,0)-_xlpm.m+1))),"")) | AQ15: =_xlfn.LET(_xlpm.m,IF(ISNUMBER(AQ$4),DATE(YEAR(AQ$4),MONTH(AQ$4),1),DATEVALUE("1-"&AQ$4)),IF(OR(COUNTA($A15:$F15)>0,$G15<>""),$N15/12*IF($F15="",1,MAX(0,(EOMONTH(_xlpm.m,0)-MAX($F15,_xlpm.m)+1)/(EOMONTH(_xlpm.m,0)-_xlpm.m+1))),"")) | AR15: =_xlfn.LET(_xlpm.m,IF(ISNUMBER(AR$4),DATE(YEAR(AR$4),MONTH(AR$4),1),DATEVALUE("1-"&AR$4)),IF(OR(COUNTA($A15:$F15)>0,$G15<>""),$N15/12*IF($F15="",1,MAX(0,(EOMONTH(_xlpm.m,0)-MAX($F15,_xlpm.m)+1)/(EOMONTH(_xlpm.m,0)-_xlpm.m+1))),"")) | AS15: =_xlfn.LET(_xlpm.m,IF(ISNUMBER(AS$4),DATE(YEAR(AS$4),MONTH(AS$4),1),DATEVALUE("1-"&AS$4)),IF(OR(COUNTA($A15:$F15)>0,$G15<>""),$N15/12*IF($F15="",1,MAX(0,(EOMONTH(_xlpm.m,0)-MAX($F15,_xlpm.m)+1)/(EOMONTH(_xlpm.m,0)-_xlpm.m+1))),"")) | AT15: =_xlfn.LET(_xlpm.m,IF(ISNUMBER(AT$4),DATE(YEAR(AT$4),MONTH(AT$4),1),DATEVALUE("1-"&AT$4)),IF(OR(COUNTA($A15:$F15)>0,$G15<>""),$N15/12*IF($F15="",1,MAX(0,(EOMONTH(_xlpm.m,0)-MAX($F15,_xlpm.m)+1)/(EOMONTH(_xlpm.m,0)-_xlpm.m+1))),"")) | AU15: =_xlfn.LET(_xlpm.m,IF(ISNUMBER(AU$4),DATE(YEAR(AU$4),MONTH(AU$4),1),DATEVALUE("1-"&AU$4)),IF(OR(COUNTA($A15:$F15)>0,$G15<>""),$N15/12*IF($F15="",1,MAX(0,(EOMONTH(_xlpm.m,0)-MAX($F15,_xlpm.m)+1)/(EOMONTH(_xlpm.m,0)-_xlpm.m+1))),"")) | AV15: =_xlfn.LET(_xlpm.m,IF(ISNUMBER(AV$4),DATE(YEAR(AV$4),MONTH(AV$4),1),DATEVALUE("1-"&AV$4)),IF(OR(COUNTA($A15:$F15)>0,$G15<>""),$N15/12*IF($F15="",1,MAX(0,(EOMONTH(_xlpm.m,0)-MAX($F15,_xlpm.m)+1)/(EOMONTH(_xlpm.m,0)-_xlpm.m+1))),"")) | ... AZ15: =_xlfn.LET(_xlpm.m,IF(ISNUMBER(AZ$4),DATE(YEAR(AZ$4),MONTH(AZ$4),1),DATEVALUE("1-"&AZ$4)),IF(OR(COUNTA($A15:$F15)>0,$G15<>""),$N15/12*IF($F15="",1,MAX(0,(EOMONTH(_xlpm.m,0)-MAX($F15,_xlpm.m)+1)/(EOMONTH(_xlpm.m,0)-_xlpm.m+1))),"")) | BA15: =IF(OR(COUNTA($A15:$F15)>0,$G15<>""),SUM(AO15:AZ15),"")
I16: =IF(OR(COUNTA(tblPayrollIncrementalSpend2[[#This Row],[Job Title]:[Hire Date]])>0,AND(ROW()=ROW(G16),tblPayrollIncrementalSpend2[[#This Row],[Base Salary]]<>"")),N(tblPayrollIncrementalSpend2[[#This Row],[Base Salary]])*N(tblPayrollIncrementalSpend2[[#This Row],[Bonus %]]),"") | J16: =IF(OR(COUNTA(tblPayrollIncrementalSpend2[[#This Row],[Job Title]:[Hire Date]])>0,AND(ROW()=ROW(G16),tblPayrollIncrementalSpend2[[#This Row],[Base Salary]]<>"")),N(tblPayrollIncrementalSpend2[[#This Row],[Base Salary]])*'Base - Payroll'!$E$12,"") | K16: =IF(OR(COUNTA(tblPayrollIncrementalSpend2[[#This Row],[Job Title]:[Hire Date]])>0,AND(ROW()=ROW(G16),tblPayrollIncrementalSpend2[[#This Row],[Base Salary]]<>"")),N(tblPayrollIncrementalSpend2[[#This Row],[Base Salary]])*'Base - Payroll'!$E$13,"") | L16: =IF(OR(COUNTA(tblPayrollIncrementalSpend2[[#This Row],[Job Title]:[Hire Date]])>0,AND(ROW()=ROW(G16),tblPayrollIncrementalSpend2[[#This Row],[Base Salary]]<>"")),N(tblPayrollIncrementalSpend2[[#This Row],[Base Salary]])*'Base - Payroll'!$E$15,"") | M16: =IF(OR(COUNTA(tblPayrollIncrementalSpend2[[#This Row],[Job Title]:[Hire Date]])>0,AND(ROW()=ROW(G16),tblPayrollIncrementalSpend2[[#This Row],[Base Salary]]<>"")),N(tblPayrollIncrementalSpend2[[#This Row],[Base Salary]])*'Base - Payroll'!$E$16,"") | N16: =IF(OR(COUNTA(tblPayrollIncrementalSpend2[[#This Row],[Job Title]:[Hire Date]])>0,AND(ROW()=ROW(G16),tblPayrollIncrementalSpend2[[#This Row],[Base Salary]]<>"")),N(tblPayrollIncrementalSpend2[[#This Row],[Base Salary]])+SUM(tblPayrollIncrementalSpend2[[#This Row],[Bonus]:[Other]]),"") | O16: =_xlfn.LET(_xlpm.m,IF(ISNUMBER(O$4),DATE(YEAR(O$4),MONTH(O$4),1),DATEVALUE("1-"&O$4)),IF(OR(COUNTA($A16:$F16)>0,$G16<>""),$N16/12*IF($F16="",1,MAX(0,(EOMONTH(_xlpm.m,0)-MAX($F16,_xlpm.m)+1)/(EOMONTH(_xlpm.m,0)-_xlpm.m+1))),"")) | P16: =_xlfn.LET(_xlpm.m,IF(ISNUMBER(P$4),DATE(YEAR(P$4),MONTH(P$4),1),DATEVALUE("1-"&P$4)),IF(OR(COUNTA($A16:$F16)>0,$G16<>""),$N16/12*IF($F16="",1,MAX(0,(EOMONTH(_xlpm.m,0)-MAX($F16,_xlpm.m)+1)/(EOMONTH(_xlpm.m,0)-_xlpm.m+1))),"")) | Q16: =_xlfn.LET(_xlpm.m,IF(ISNUMBER(Q$4),DATE(YEAR(Q$4),MONTH(Q$4),1),DATEVALUE("1-"&Q$4)),IF(OR(COUNTA($A16:$F16)>0,$G16<>""),$N16/12*IF($F16="",1,MAX(0,(EOMONTH(_xlpm.m,0)-MAX($F16,_xlpm.m)+1)/(EOMONTH(_xlpm.m,0)-_xlpm.m+1))),"")) | R16: =_xlfn.LET(_xlpm.m,IF(ISNUMBER(R$4),DATE(YEAR(R$4),MONTH(R$4),1),DATEVALUE("1-"&R$4)),IF(OR(COUNTA($A16:$F16)>0,$G16<>""),$N16/12*IF($F16="",1,MAX(0,(EOMONTH(_xlpm.m,0)-MAX($F16,_xlpm.m)+1)/(EOMONTH(_xlpm.m,0)-_xlpm.m+1))),"")) | S16: =_xlfn.LET(_xlpm.m,IF(ISNUMBER(S$4),DATE(YEAR(S$4),MONTH(S$4),1),DATEVALUE("1-"&S$4)),IF(OR(COUNTA($A16:$F16)>0,$G16<>""),$N16/12*IF($F16="",1,MAX(0,(EOMONTH(_xlpm.m,0)-MAX($F16,_xlpm.m)+1)/(EOMONTH(_xlpm.m,0)-_xlpm.m+1))),"")) | T16: =_xlfn.LET(_xlpm.m,IF(ISNUMBER(T$4),DATE(YEAR(T$4),MONTH(T$4),1),DATEVALUE("1-"&T$4)),IF(OR(COUNTA($A16:$F16)>0,$G16<>""),$N16/12*IF($F16="",1,MAX(0,(EOMONTH(_xlpm.m,0)-MAX($F16,_xlpm.m)+1)/(EOMONTH(_xlpm.m,0)-_xlpm.m+1))),"")) | U16: =_xlfn.LET(_xlpm.m,IF(ISNUMBER(U$4),DATE(YEAR(U$4),MONTH(U$4),1),DATEVALUE("1-"&U$4)),IF(OR(COUNTA($A16:$F16)>0,$G16<>""),$N16/12*IF($F16="",1,MAX(0,(EOMONTH(_xlpm.m,0)-MAX($F16,_xlpm.m)+1)/(EOMONTH(_xlpm.m,0)-_xlpm.m+1))),"")) | V16: =_xlfn.LET(_xlpm.m,IF(ISNUMBER(V$4),DATE(YEAR(V$4),MONTH(V$4),1),DATEVALUE("1-"&V$4)),IF(OR(COUNTA($A16:$F16)>0,$G16<>""),$N16/12*IF($F16="",1,MAX(0,(EOMONTH(_xlpm.m,0)-MAX($F16,_xlpm.m)+1)/(EOMONTH(_xlpm.m,0)-_xlpm.m+1))),"")) | ... Z16: =_xlfn.LET(_xlpm.m,IF(ISNUMBER(Z$4),DATE(YEAR(Z$4),MONTH(Z$4),1),DATEVALUE("1-"&Z$4)),IF(OR(COUNTA($A16:$F16)>0,$G16<>""),$N16/12*IF($F16="",1,MAX(0,(EOMONTH(_xlpm.m,0)-MAX($F16,_xlpm.m)+1)/(EOMONTH(_xlpm.m,0)-_xlpm.m+1))),"")) | AA16: =IF(OR(COUNTA($A16:$F16)>0,$G16<>""),SUM(O16:Z16),"") | AB16: =_xlfn.LET(_xlpm.m,IF(ISNUMBER(AB$4),DATE(YEAR(AB$4),MONTH(AB$4),1),DATEVALUE("1-"&AB$4)),IF(OR(COUNTA($A16:$F16)>0,$G16<>""),$N16/12*IF($F16="",1,MAX(0,(EOMONTH(_xlpm.m,0)-MAX($F16,_xlpm.m)+1)/(EOMONTH(_xlpm.m,0)-_xlpm.m+1))),"")) | AC16: =_xlfn.LET(_xlpm.m,IF(ISNUMBER(AC$4),DATE(YEAR(AC$4),MONTH(AC$4),1),DATEVALUE("1-"&AC$4)),IF(OR(COUNTA($A16:$F16)>0,$G16<>""),$N16/12*IF($F16="",1,MAX(0,(EOMONTH(_xlpm.m,0)-MAX($F16,_xlpm.m)+1)/(EOMONTH(_xlpm.m,0)-_xlpm.m+1))),"")) | AD16: =_xlfn.LET(_xlpm.m,IF(ISNUMBER(AD$4),DATE(YEAR(AD$4),MONTH(AD$4),1),DATEVALUE("1-"&AD$4)),IF(OR(COUNTA($A16:$F16)>0,$G16<>""),$N16/12*IF($F16="",1,MAX(0,(EOMONTH(_xlpm.m,0)-MAX($F16,_xlpm.m)+1)/(EOMONTH(_xlpm.m,0)-_xlpm.m+1))),"")) | AE16: =_xlfn.LET(_xlpm.m,IF(ISNUMBER(AE$4),DATE(YEAR(AE$4),MONTH(AE$4),1),DATEVALUE("1-"&AE$4)),IF(OR(COUNTA($A16:$F16)>0,$G16<>""),$N16/12*IF($F16="",1,MAX(0,(EOMONTH(_xlpm.m,0)-MAX($F16,_xlpm.m)+1)/(EOMONTH(_xlpm.m,0)-_xlpm.m+1))),"")) | AF16: =_xlfn.LET(_xlpm.m,IF(ISNUMBER(AF$4),DATE(YEAR(AF$4),MONTH(AF$4),1),DATEVALUE("1-"&AF$4)),IF(OR(COUNTA($A16:$F16)>0,$G16<>""),$N16/12*IF($F16="",1,MAX(0,(EOMONTH(_xlpm.m,0)-MAX($F16,_xlpm.m)+1)/(EOMONTH(_xlpm.m,0)-_xlpm.m+1))),"")) | AG16: =_xlfn.LET(_xlpm.m,IF(ISNUMBER(AG$4),DATE(YEAR(AG$4),MONTH(AG$4),1),DATEVALUE("1-"&AG$4)),IF(OR(COUNTA($A16:$F16)>0,$G16<>""),$N16/12*IF($F16="",1,MAX(0,(EOMONTH(_xlpm.m,0)-MAX($F16,_xlpm.m)+1)/(EOMONTH(_xlpm.m,0)-_xlpm.m+1))),"")) | AH16: =_xlfn.LET(_xlpm.m,IF(ISNUMBER(AH$4),DATE(YEAR(AH$4),MONTH(AH$4),1),DATEVALUE("1-"&AH$4)),IF(OR(COUNTA($A16:$F16)>0,$G16<>""),$N16/12*IF($F16="",1,MAX(0,(EOMONTH(_xlpm.m,0)-MAX($F16,_xlpm.m)+1)/(EOMONTH(_xlpm.m,0)-_xlpm.m+1))),"")) | AI16: =_xlfn.LET(_xlpm.m,IF(ISNUMBER(AI$4),DATE(YEAR(AI$4),MONTH(AI$4),1),DATEVALUE("1-"&AI$4)),IF(OR(COUNTA($A16:$F16)>0,$G16<>""),$N16/12*IF($F16="",1,MAX(0,(EOMONTH(_xlpm.m,0)-MAX($F16,_xlpm.m)+1)/(EOMONTH(_xlpm.m,0)-_xlpm.m+1))),"")) | ... AM16: =_xlfn.LET(_xlpm.m,IF(ISNUMBER(AM$4),DATE(YEAR(AM$4),MONTH(AM$4),1),DATEVALUE("1-"&AM$4)),IF(OR(COUNTA($A16:$F16)>0,$G16<>""),$N16/12*IF($F16="",1,MAX(0,(EOMONTH(_xlpm.m,0)-MAX($F16,_xlpm.m)+1)/(EOMONTH(_xlpm.m,0)-_xlpm.m+1))),"")) | AN16: =IF(OR(COUNTA($A16:$F16)>0,$G16<>""),SUM(AB16:AM16),"") | AO16: =_xlfn.LET(_xlpm.m,IF(ISNUMBER(AO$4),DATE(YEAR(AO$4),MONTH(AO$4),1),DATEVALUE("1-"&AO$4)),IF(OR(COUNTA($A16:$F16)>0,$G16<>""),$N16/12*IF($F16="",1,MAX(0,(EOMONTH(_xlpm.m,0)-MAX($F16,_xlpm.m)+1)/(EOMONTH(_xlpm.m,0)-_xlpm.m+1))),"")) | AP16: =_xlfn.LET(_xlpm.m,IF(ISNUMBER(AP$4),DATE(YEAR(AP$4),MONTH(AP$4),1),DATEVALUE("1-"&AP$4)),IF(OR(COUNTA($A16:$F16)>0,$G16<>""),$N16/12*IF($F16="",1,MAX(0,(EOMONTH(_xlpm.m,0)-MAX($F16,_xlpm.m)+1)/(EOMONTH(_xlpm.m,0)-_xlpm.m+1))),"")) | AQ16: =_xlfn.LET(_xlpm.m,IF(ISNUMBER(AQ$4),DATE(YEAR(AQ$4),MONTH(AQ$4),1),DATEVALUE("1-"&AQ$4)),IF(OR(COUNTA($A16:$F16)>0,$G16<>""),$N16/12*IF($F16="",1,MAX(0,(EOMONTH(_xlpm.m,0)-MAX($F16,_xlpm.m)+1)/(EOMONTH(_xlpm.m,0)-_xlpm.m+1))),"")) | AR16: =_xlfn.LET(_xlpm.m,IF(ISNUMBER(AR$4),DATE(YEAR(AR$4),MONTH(AR$4),1),DATEVALUE("1-"&AR$4)),IF(OR(COUNTA($A16:$F16)>0,$G16<>""),$N16/12*IF($F16="",1,MAX(0,(EOMONTH(_xlpm.m,0)-MAX($F16,_xlpm.m)+1)/(EOMONTH(_xlpm.m,0)-_xlpm.m+1))),"")) | AS16: =_xlfn.LET(_xlpm.m,IF(ISNUMBER(AS$4),DATE(YEAR(AS$4),MONTH(AS$4),1),DATEVALUE("1-"&AS$4)),IF(OR(COUNTA($A16:$F16)>0,$G16<>""),$N16/12*IF($F16="",1,MAX(0,(EOMONTH(_xlpm.m,0)-MAX($F16,_xlpm.m)+1)/(EOMONTH(_xlpm.m,0)-_xlpm.m+1))),"")) | AT16: =_xlfn.LET(_xlpm.m,IF(ISNUMBER(AT$4),DATE(YEAR(AT$4),MONTH(AT$4),1),DATEVALUE("1-"&AT$4)),IF(OR(COUNTA($A16:$F16)>0,$G16<>""),$N16/12*IF($F16="",1,MAX(0,(EOMONTH(_xlpm.m,0)-MAX($F16,_xlpm.m)+1)/(EOMONTH(_xlpm.m,0)-_xlpm.m+1))),"")) | AU16: =_xlfn.LET(_xlpm.m,IF(ISNUMBER(AU$4),DATE(YEAR(AU$4),MONTH(AU$4),1),DATEVALUE("1-"&AU$4)),IF(OR(COUNTA($A16:$F16)>0,$G16<>""),$N16/12*IF($F16="",1,MAX(0,(EOMONTH(_xlpm.m,0)-MAX($F16,_xlpm.m)+1)/(EOMONTH(_xlpm.m,0)-_xlpm.m+1))),"")) | AV16: =_xlfn.LET(_xlpm.m,IF(ISNUMBER(AV$4),DATE(YEAR(AV$4),MONTH(AV$4),1),DATEVALUE("1-"&AV$4)),IF(OR(COUNTA($A16:$F16)>0,$G16<>""),$N16/12*IF($F16="",1,MAX(0,(EOMONTH(_xlpm.m,0)-MAX($F16,_xlpm.m)+1)/(EOMONTH(_xlpm.m,0)-_xlpm.m+1))),"")) | ... AZ16: =_xlfn.LET(_xlpm.m,IF(ISNUMBER(AZ$4),DATE(YEAR(AZ$4),MONTH(AZ$4),1),DATEVALUE("1-"&AZ$4)),IF(OR(COUNTA($A16:$F16)>0,$G16<>""),$N16/12*IF($F16="",1,MAX(0,(EOMONTH(_xlpm.m,0)-MAX($F16,_xlpm.m)+1)/(EOMONTH(_xlpm.m,0)-_xlpm.m+1))),"")) | BA16: =IF(OR(COUNTA($A16:$F16)>0,$G16<>""),SUM(AO16:AZ16),"")
... I20: =IF(OR(COUNTA(tblPayrollIncrementalSpend2[[#This Row],[Job Title]:[Hire Date]])>0,AND(ROW()=ROW(G20),tblPayrollIncrementalSpend2[[#This Row],[Base Salary]]<>"")),N(tblPayrollIncrementalSpend2[[#This Row],[Base Salary]])*N(tblPayrollIncrementalSpend2[[#This Row],[Bonus %]]),"") | J20: =IF(OR(COUNTA(tblPayrollIncrementalSpend2[[#This Row],[Job Title]:[Hire Date]])>0,AND(ROW()=ROW(G20),tblPayrollIncrementalSpend2[[#This Row],[Base Salary]]<>"")),N(tblPayrollIncrementalSpend2[[#This Row],[Base Salary]])*'Base - Payroll'!$E$12,"") | K20: =IF(OR(COUNTA(tblPayrollIncrementalSpend2[[#This Row],[Job Title]:[Hire Date]])>0,AND(ROW()=ROW(G20),tblPayrollIncrementalSpend2[[#This Row],[Base Salary]]<>"")),N(tblPayrollIncrementalSpend2[[#This Row],[Base Salary]])*'Base - Payroll'!$E$13,"") | L20: =IF(OR(COUNTA(tblPayrollIncrementalSpend2[[#This Row],[Job Title]:[Hire Date]])>0,AND(ROW()=ROW(G20),tblPayrollIncrementalSpend2[[#This Row],[Base Salary]]<>"")),N(tblPayrollIncrementalSpend2[[#This Row],[Base Salary]])*'Base - Payroll'!$E$15,"") | M20: =IF(OR(COUNTA(tblPayrollIncrementalSpend2[[#This Row],[Job Title]:[Hire Date]])>0,AND(ROW()=ROW(G20),tblPayrollIncrementalSpend2[[#This Row],[Base Salary]]<>"")),N(tblPayrollIncrementalSpend2[[#This Row],[Base Salary]])*'Base - Payroll'!$E$16,"") | N20: =IF(OR(COUNTA(tblPayrollIncrementalSpend2[[#This Row],[Job Title]:[Hire Date]])>0,AND(ROW()=ROW(G20),tblPayrollIncrementalSpend2[[#This Row],[Base Salary]]<>"")),N(tblPayrollIncrementalSpend2[[#This Row],[Base Salary]])+SUM(tblPayrollIncrementalSpend2[[#This Row],[Bonus]:[Other]]),"") | O20: =_xlfn.LET(_xlpm.m,IF(ISNUMBER(O$4),DATE(YEAR(O$4),MONTH(O$4),1),DATEVALUE("1-"&O$4)),IF(OR(COUNTA($A20:$F20)>0,$G20<>""),$N20/12*IF($F20="",1,MAX(0,(EOMONTH(_xlpm.m,0)-MAX($F20,_xlpm.m)+1)/(EOMONTH(_xlpm.m,0)-_xlpm.m+1))),"")) | P20: =_xlfn.LET(_xlpm.m,IF(ISNUMBER(P$4),DATE(YEAR(P$4),MONTH(P$4),1),DATEVALUE("1-"&P$4)),IF(OR(COUNTA($A20:$F20)>0,$G20<>""),$N20/12*IF($F20="",1,MAX(0,(EOMONTH(_xlpm.m,0)-MAX($F20,_xlpm.m)+1)/(EOMONTH(_xlpm.m,0)-_xlpm.m+1))),"")) | Q20: =_xlfn.LET(_xlpm.m,IF(ISNUMBER(Q$4),DATE(YEAR(Q$4),MONTH(Q$4),1),DATEVALUE("1-"&Q$4)),IF(OR(COUNTA($A20:$F20)>0,$G20<>""),$N20/12*IF($F20="",1,MAX(0,(EOMONTH(_xlpm.m,0)-MAX($F20,_xlpm.m)+1)/(EOMONTH(_xlpm.m,0)-_xlpm.m+1))),"")) | R20: =_xlfn.LET(_xlpm.m,IF(ISNUMBER(R$4),DATE(YEAR(R$4),MONTH(R$4),1),DATEVALUE("1-"&R$4)),IF(OR(COUNTA($A20:$F20)>0,$G20<>""),$N20/12*IF($F20="",1,MAX(0,(EOMONTH(_xlpm.m,0)-MAX($F20,_xlpm.m)+1)/(EOMONTH(_xlpm.m,0)-_xlpm.m+1))),"")) | S20: =_xlfn.LET(_xlpm.m,IF(ISNUMBER(S$4),DATE(YEAR(S$4),MONTH(S$4),1),DATEVALUE("1-"&S$4)),IF(OR(COUNTA($A20:$F20)>0,$G20<>""),$N20/12*IF($F20="",1,MAX(0,(EOMONTH(_xlpm.m,0)-MAX($F20,_xlpm.m)+1)/(EOMONTH(_xlpm.m,0)-_xlpm.m+1))),"")) | T20: =_xlfn.LET(_xlpm.m,IF(ISNUMBER(T$4),DATE(YEAR(T$4),MONTH(T$4),1),DATEVALUE("1-"&T$4)),IF(OR(COUNTA($A20:$F20)>0,$G20<>""),$N20/12*IF($F20="",1,MAX(0,(EOMONTH(_xlpm.m,0)-MAX($F20,_xlpm.m)+1)/(EOMONTH(_xlpm.m,0)-_xlpm.m+1))),"")) | U20: =_xlfn.LET(_xlpm.m,IF(ISNUMBER(U$4),DATE(YEAR(U$4),MONTH(U$4),1),DATEVALUE("1-"&U$4)),IF(OR(COUNTA($A20:$F20)>0,$G20<>""),$N20/12*IF($F20="",1,MAX(0,(EOMONTH(_xlpm.m,0)-MAX($F20,_xlpm.m)+1)/(EOMONTH(_xlpm.m,0)-_xlpm.m+1))),"")) | V20: =_xlfn.LET(_xlpm.m,IF(ISNUMBER(V$4),DATE(YEAR(V$4),MONTH(V$4),1),DATEVALUE("1-"&V$4)),IF(OR(COUNTA($A20:$F20)>0,$G20<>""),$N20/12*IF($F20="",1,MAX(0,(EOMONTH(_xlpm.m,0)-MAX($F20,_xlpm.m)+1)/(EOMONTH(_xlpm.m,0)-_xlpm.m+1))),"")) | ... Z20: =_xlfn.LET(_xlpm.m,IF(ISNUMBER(Z$4),DATE(YEAR(Z$4),MONTH(Z$4),1),DATEVALUE("1-"&Z$4)),IF(OR(COUNTA($A20:$F20)>0,$G20<>""),$N20/12*IF($F20="",1,MAX(0,(EOMONTH(_xlpm.m,0)-MAX($F20,_xlpm.m)+1)/(EOMONTH(_xlpm.m,0)-_xlpm.m+1))),"")) | AA20: =IF(OR(COUNTA($A20:$F20)>0,$G20<>""),SUM(O20:Z20),"") | AB20: =_xlfn.LET(_xlpm.m,IF(ISNUMBER(AB$4),DATE(YEAR(AB$4),MONTH(AB$4),1),DATEVALUE("1-"&AB$4)),IF(OR(COUNTA($A20:$F20)>0,$G20<>""),$N20/12*IF($F20="",1,MAX(0,(EOMONTH(_xlpm.m,0)-MAX($F20,_xlpm.m)+1)/(EOMONTH(_xlpm.m,0)-_xlpm.m+1))),"")) | AC20: =_xlfn.LET(_xlpm.m,IF(ISNUMBER(AC$4),DATE(YEAR(AC$4),MONTH(AC$4),1),DATEVALUE("1-"&AC$4)),IF(OR(COUNTA($A20:$F20)>0,$G20<>""),$N20/12*IF($F20="",1,MAX(0,(EOMONTH(_xlpm.m,0)-MAX($F20,_xlpm.m)+1)/(EOMONTH(_xlpm.m,0)-_xlpm.m+1))),"")) | AD20: =_xlfn.LET(_xlpm.m,IF(ISNUMBER(AD$4),DATE(YEAR(AD$4),MONTH(AD$4),1),DATEVALUE("1-"&AD$4)),IF(OR(COUNTA($A20:$F20)>0,$G20<>""),$N20/12*IF($F20="",1,MAX(0,(EOMONTH(_xlpm.m,0)-MAX($F20,_xlpm.m)+1)/(EOMONTH(_xlpm.m,0)-_xlpm.m+1))),"")) | AE20: =_xlfn.LET(_xlpm.m,IF(ISNUMBER(AE$4),DATE(YEAR(AE$4),MONTH(AE$4),1),DATEVALUE("1-"&AE$4)),IF(OR(COUNTA($A20:$F20)>0,$G20<>""),$N20/12*IF($F20="",1,MAX(0,(EOMONTH(_xlpm.m,0)-MAX($F20,_xlpm.m)+1)/(EOMONTH(_xlpm.m,0)-_xlpm.m+1))),"")) | AF20: =_xlfn.LET(_xlpm.m,IF(ISNUMBER(AF$4),DATE(YEAR(AF$4),MONTH(AF$4),1),DATEVALUE("1-"&AF$4)),IF(OR(COUNTA($A20:$F20)>0,$G20<>""),$N20/12*IF($F20="",1,MAX(0,(EOMONTH(_xlpm.m,0)-MAX($F20,_xlpm.m)+1)/(EOMONTH(_xlpm.m,0)-_xlpm.m+1))),"")) | AG20: =_xlfn.LET(_xlpm.m,IF(ISNUMBER(AG$4),DATE(YEAR(AG$4),MONTH(AG$4),1),DATEVALUE("1-"&AG$4)),IF(OR(COUNTA($A20:$F20)>0,$G20<>""),$N20/12*IF($F20="",1,MAX(0,(EOMONTH(_xlpm.m,0)-MAX($F20,_xlpm.m)+1)/(EOMONTH(_xlpm.m,0)-_xlpm.m+1))),"")) | AH20: =_xlfn.LET(_xlpm.m,IF(ISNUMBER(AH$4),DATE(YEAR(AH$4),MONTH(AH$4),1),DATEVALUE("1-"&AH$4)),IF(OR(COUNTA($A20:$F20)>0,$G20<>""),$N20/12*IF($F20="",1,MAX(0,(EOMONTH(_xlpm.m,0)-MAX($F20,_xlpm.m)+1)/(EOMONTH(_xlpm.m,0)-_xlpm.m+1))),"")) | AI20: =_xlfn.LET(_xlpm.m,IF(ISNUMBER(AI$4),DATE(YEAR(AI$4),MONTH(AI$4),1),DATEVALUE("1-"&AI$4)),IF(OR(COUNTA($A20:$F20)>0,$G20<>""),$N20/12*IF($F20="",1,MAX(0,(EOMONTH(_xlpm.m,0)-MAX($F20,_xlpm.m)+1)/(EOMONTH(_xlpm.m,0)-_xlpm.m+1))),"")) | ... AM20: =_xlfn.LET(_xlpm.m,IF(ISNUMBER(AM$4),DATE(YEAR(AM$4),MONTH(AM$4),1),DATEVALUE("1-"&AM$4)),IF(OR(COUNTA($A20:$F20)>0,$G20<>""),$N20/12*IF($F20="",1,MAX(0,(EOMONTH(_xlpm.m,0)-MAX($F20,_xlpm.m)+1)/(EOMONTH(_xlpm.m,0)-_xlpm.m+1))),"")) | AN20: =IF(OR(COUNTA($A20:$F20)>0,$G20<>""),SUM(AB20:AM20),"") | AO20: =_xlfn.LET(_xlpm.m,IF(ISNUMBER(AO$4),DATE(YEAR(AO$4),MONTH(AO$4),1),DATEVALUE("1-"&AO$4)),IF(OR(COUNTA($A20:$F20)>0,$G20<>""),$N20/12*IF($F20="",1,MAX(0,(EOMONTH(_xlpm.m,0)-MAX($F20,_xlpm.m)+1)/(EOMONTH(_xlpm.m,0)-_xlpm.m+1))),"")) | AP20: =_xlfn.LET(_xlpm.m,IF(ISNUMBER(AP$4),DATE(YEAR(AP$4),MONTH(AP$4),1),DATEVALUE("1-"&AP$4)),IF(OR(COUNTA($A20:$F20)>0,$G20<>""),$N20/12*IF($F20="",1,MAX(0,(EOMONTH(_xlpm.m,0)-MAX($F20,_xlpm.m)+1)/(EOMONTH(_xlpm.m,0)-_xlpm.m+1))),"")) | AQ20: =_xlfn.LET(_xlpm.m,IF(ISNUMBER(AQ$4),DATE(YEAR(AQ$4),MONTH(AQ$4),1),DATEVALUE("1-"&AQ$4)),IF(OR(COUNTA($A20:$F20)>0,$G20<>""),$N20/12*IF($F20="",1,MAX(0,(EOMONTH(_xlpm.m,0)-MAX($F20,_xlpm.m)+1)/(EOMONTH(_xlpm.m,0)-_xlpm.m+1))),"")) | AR20: =_xlfn.LET(_xlpm.m,IF(ISNUMBER(AR$4),DATE(YEAR(AR$4),MONTH(AR$4),1),DATEVALUE("1-"&AR$4)),IF(OR(COUNTA($A20:$F20)>0,$G20<>""),$N20/12*IF($F20="",1,MAX(0,(EOMONTH(_xlpm.m,0)-MAX($F20,_xlpm.m)+1)/(EOMONTH(_xlpm.m,0)-_xlpm.m+1))),"")) | AS20: =_xlfn.LET(_xlpm.m,IF(ISNUMBER(AS$4),DATE(YEAR(AS$4),MONTH(AS$4),1),DATEVALUE("1-"&AS$4)),IF(OR(COUNTA($A20:$F20)>0,$G20<>""),$N20/12*IF($F20="",1,MAX(0,(EOMONTH(_xlpm.m,0)-MAX($F20,_xlpm.m)+1)/(EOMONTH(_xlpm.m,0)-_xlpm.m+1))),"")) | AT20: =_xlfn.LET(_xlpm.m,IF(ISNUMBER(AT$4),DATE(YEAR(AT$4),MONTH(AT$4),1),DATEVALUE("1-"&AT$4)),IF(OR(COUNTA($A20:$F20)>0,$G20<>""),$N20/12*IF($F20="",1,MAX(0,(EOMONTH(_xlpm.m,0)-MAX($F20,_xlpm.m)+1)/(EOMONTH(_xlpm.m,0)-_xlpm.m+1))),"")) | AU20: =_xlfn.LET(_xlpm.m,IF(ISNUMBER(AU$4),DATE(YEAR(AU$4),MONTH(AU$4),1),DATEVALUE("1-"&AU$4)),IF(OR(COUNTA($A20:$F20)>0,$G20<>""),$N20/12*IF($F20="",1,MAX(0,(EOMONTH(_xlpm.m,0)-MAX($F20,_xlpm.m)+1)/(EOMONTH(_xlpm.m,0)-_xlpm.m+1))),"")) | AV20: =_xlfn.LET(_xlpm.m,IF(ISNUMBER(AV$4),DATE(YEAR(AV$4),MONTH(AV$4),1),DATEVALUE("1-"&AV$4)),IF(OR(COUNTA($A20:$F20)>0,$G20<>""),$N20/12*IF($F20="",1,MAX(0,(EOMONTH(_xlpm.m,0)-MAX($F20,_xlpm.m)+1)/(EOMONTH(_xlpm.m,0)-_xlpm.m+1))),"")) | ... AZ20: =_xlfn.LET(_xlpm.m,IF(ISNUMBER(AZ$4),DATE(YEAR(AZ$4),MONTH(AZ$4),1),DATEVALUE("1-"&AZ$4)),IF(OR(COUNTA($A20:$F20)>0,$G20<>""),$N20/12*IF($F20="",1,MAX(0,(EOMONTH(_xlpm.m,0)-MAX($F20,_xlpm.m)+1)/(EOMONTH(_xlpm.m,0)-_xlpm.m+1))),"")) | BA20: =IF(OR(COUNTA($A20:$F20)>0,$G20<>""),SUM(AO20:AZ20),"")
A22: Total Payroll / Headcount Incremental Spend | G22: =SUM(tblPayrollIncrementalSpend2[Base Salary]) -> 0 | I22: =SUM(tblPayrollIncrementalSpend2[Bonus]) -> 0 | J22: =SUM(tblPayrollIncrementalSpend2[Payroll Taxes]) -> 0 | K22: =SUM(tblPayrollIncrementalSpend2[Benefits]) -> 0 | L22: =SUM(tblPayrollIncrementalSpend2[Vacation]) -> 0 | M22: =SUM(tblPayrollIncrementalSpend2[Other]) -> 0 | N22: =SUM(tblPayrollIncrementalSpend2[Annualized Spend]) -> 0 | O22: =SUM(tblPayrollIncrementalSpend2[Jan-27]) -> 0 | P22: =SUM(tblPayrollIncrementalSpend2[Feb-27]) -> 0 | Q22: =SUM(tblPayrollIncrementalSpend2[Mar-27]) -> 0 | R22: =SUM(tblPayrollIncrementalSpend2[Apr-27]) -> 0 | S22: =SUM(tblPayrollIncrementalSpend2[May-27]) -> 0 | T22: =SUM(tblPayrollIncrementalSpend2[Jun-27]) -> 0 | U22: =SUM(tblPayrollIncrementalSpend2[Jul-27]) -> 0 | V22: =SUM(tblPayrollIncrementalSpend2[Aug-27]) -> 0 | W22: =SUM(tblPayrollIncrementalSpend2[Sep-27]) -> 0 | X22: =SUM(tblPayrollIncrementalSpend2[Oct-27]) -> 0 | Y22: =SUM(tblPayrollIncrementalSpend2[Nov-27]) -> 0 | Z22: =SUM(tblPayrollIncrementalSpend2[Dec-27]) -> 0 | AA22: =SUM(tblPayrollIncrementalSpend2[2027 Incremental Spend]) -> 0 | AB22: =SUM(tblPayrollIncrementalSpend2[Jan-28]) -> 0 | AC22: =SUM(tblPayrollIncrementalSpend2[Feb-28]) -> 0 | AD22: =SUM(tblPayrollIncrementalSpend2[Mar-28]) -> 0 | AE22: =SUM(tblPayrollIncrementalSpend2[Apr-28]) -> 0 | AF22: =SUM(tblPayrollIncrementalSpend2[May-28]) -> 0 | AG22: =SUM(tblPayrollIncrementalSpend2[Jun-28]) -> 0 | AH22: =SUM(tblPayrollIncrementalSpend2[Jul-28]) -> 0 | AI22: =SUM(tblPayrollIncrementalSpend2[Aug-28]) -> 0 | AJ22: =SUM(tblPayrollIncrementalSpend2[Sep-28]) -> 0 | AK22: =SUM(tblPayrollIncrementalSpend2[Oct-28]) -> 0 | AL22: =SUM(tblPayrollIncrementalSpend2[Nov-28]) -> 0 | AM22: =SUM(tblPayrollIncrementalSpend2[Dec-28]) -> 0 | AN22: =SUM(tblPayrollIncrementalSpend2[2028 Incremental Spend]) -> 0 | AO22: =SUM(tblPayrollIncrementalSpend2[Jan-29]) -> 0 | AP22: =SUM(tblPayrollIncrementalSpend2[Feb-29]) -> 0 | AQ22: =SUM(tblPayrollIncrementalSpend2[Mar-29]) -> 0 | AR22: =SUM(tblPayrollIncrementalSpend2[Apr-29]) -> 0 | AS22: =SUM(tblPayrollIncrementalSpend2[May-29]) -> 0 | AT22: =SUM(tblPayrollIncrementalSpend2[Jun-29]) -> 0 | AU22: =SUM(tblPayrollIncrementalSpend2[Jul-29]) -> 0 | AV22: =SUM(tblPayrollIncrementalSpend2[Aug-29]) -> 0 | AW22: =SUM(tblPayrollIncrementalSpend2[Sep-29]) -> 0 | AX22: =SUM(tblPayrollIncrementalSpend2[Oct-29]) -> 0 | AY22: =SUM(tblPayrollIncrementalSpend2[Nov-29]) -> 0 | AZ22: =SUM(tblPayrollIncrementalSpend2[Dec-29]) -> 0 | BA22: =SUM(tblPayrollIncrementalSpend2[2029 Incremental Spend]) -> 0
A26: Essentials Bonus / Contract Labor / Non-Payroll Incremental Spend
A27: Expense Description | B27: Type of Expense | C27: Vendor | D27: Annualized Spend | E27: Jan-27 | F27: Feb-27 | G27: Mar-27 | H27: Apr-27 | I27: May-27 | J27: Jun-27 | K27: Jul-27 | L27: Aug-27 | M27: Sep-27 | N27: Oct-27 | O27: Nov-27 | P27: Dec-27 | Q27: 2027 Incremental Spend | R27: Jan-28 | S27: Feb-28 | T27: Mar-28 | U27: Apr-28 | V27: May-28 | W27: Jun-28 | X27: Jul-28 | Y27: Aug-28 | Z27: Sep-28 | AA27: Oct-28 | AB27: Nov-28 | AC27: Dec-28 | AD27: 2028 Incremental Spend | AE27: Jan-29 | AF27: Feb-29 | AG27: Mar-29 | AH27: Apr-29 | AI27: May-29 | AJ27: Jun-29 | AK27: Jul-29 | AL27: Aug-29 | AM27: Sep-29 | AN27: Oct-29 | AO27: Nov-29 | AP27: Dec-29 | AQ27: 2029 Incremental Spend | AR27: Notes / Rationale
E28: =IF(OR(COUNTA($A28:$C28)>0,$D28<>""),N($D28)/12,"") | F28: =IF(OR(COUNTA($A28:$C28)>0,$D28<>""),N($D28)/12,"") | G28: =IF(OR(COUNTA($A28:$C28)>0,$D28<>""),N($D28)/12,"") | H28: =IF(OR(COUNTA($A28:$C28)>0,$D28<>""),N($D28)/12,"") | I28: =IF(OR(COUNTA($A28:$C28)>0,$D28<>""),N($D28)/12,"") | J28: =IF(OR(COUNTA($A28:$C28)>0,$D28<>""),N($D28)/12,"") | K28: =IF(OR(COUNTA($A28:$C28)>0,$D28<>""),N($D28)/12,"") | L28: =IF(OR(COUNTA($A28:$C28)>0,$D28<>""),N($D28)/12,"") | ... P28: =IF(OR(COUNTA($A28:$C28)>0,$D28<>""),N($D28)/12,"") | Q28: =IF(OR(COUNTA($A28:$C28)>0,$D28<>""),SUM(E28:P28),"") | R28: =IF(OR(COUNTA($A28:$C28)>0,$D28<>""),N($D28)/12,"") | S28: =IF(OR(COUNTA($A28:$C28)>0,$D28<>""),N($D28)/12,"") | T28: =IF(OR(COUNTA($A28:$C28)>0,$D28<>""),N($D28)/12,"") | U28: =IF(OR(COUNTA($A28:$C28)>0,$D28<>""),N($D28)/12,"") | V28: =IF(OR(COUNTA($A28:$C28)>0,$D28<>""),N($D28)/12,"") | W28: =IF(OR(COUNTA($A28:$C28)>0,$D28<>""),N($D28)/12,"") | X28: =IF(OR(COUNTA($A28:$C28)>0,$D28<>""),N($D28)/12,"") | Y28: =IF(OR(COUNTA($A28:$C28)>0,$D28<>""),N($D28)/12,"") | ... AC28: =IF(OR(COUNTA($A28:$C28)>0,$D28<>""),N($D28)/12,"") | AD28: =IF(OR(COUNTA($A28:$C28)>0,$D28<>""),SUM(R28:AC28),"") | AE28: =IF(OR(COUNTA($A28:$C28)>0,$D28<>""),N($D28)/12,"") | AF28: =IF(OR(COUNTA($A28:$C28)>0,$D28<>""),N($D28)/12,"") | AG28: =IF(OR(COUNTA($A28:$C28)>0,$D28<>""),N($D28)/12,"") | AH28: =IF(OR(COUNTA($A28:$C28)>0,$D28<>""),N($D28)/12,"") | AI28: =IF(OR(COUNTA($A28:$C28)>0,$D28<>""),N($D28)/12,"") | AJ28: =IF(OR(COUNTA($A28:$C28)>0,$D28<>""),N($D28)/12,"") | AK28: =IF(OR(COUNTA($A28:$C28)>0,$D28<>""),N($D28)/12,"") | AL28: =IF(OR(COUNTA($A28:$C28)>0,$D28<>""),N($D28)/12,"") | ... AP28: =IF(OR(COUNTA($A28:$C28)>0,$D28<>""),N($D28)/12,"") | AQ28: =IF(OR(COUNTA($A28:$C28)>0,$D28<>""),SUM(AE28:AP28),"")
E29: =IF(OR(COUNTA($A29:$C29)>0,$D29<>""),N($D29)/12,"") | F29: =IF(OR(COUNTA($A29:$C29)>0,$D29<>""),N($D29)/12,"") | G29: =IF(OR(COUNTA($A29:$C29)>0,$D29<>""),N($D29)/12,"") | H29: =IF(OR(COUNTA($A29:$C29)>0,$D29<>""),N($D29)/12,"") | I29: =IF(OR(COUNTA($A29:$C29)>0,$D29<>""),N($D29)/12,"") | J29: =IF(OR(COUNTA($A29:$C29)>0,$D29<>""),N($D29)/12,"") | K29: =IF(OR(COUNTA($A29:$C29)>0,$D29<>""),N($D29)/12,"") | L29: =IF(OR(COUNTA($A29:$C29)>0,$D29<>""),N($D29)/12,"") | ... P29: =IF(OR(COUNTA($A29:$C29)>0,$D29<>""),N($D29)/12,"") | Q29: =IF(OR(COUNTA($A29:$C29)>0,$D29<>""),SUM(E29:P29),"") | R29: =IF(OR(COUNTA($A29:$C29)>0,$D29<>""),N($D29)/12,"") | S29: =IF(OR(COUNTA($A29:$C29)>0,$D29<>""),N($D29)/12,"") | T29: =IF(OR(COUNTA($A29:$C29)>0,$D29<>""),N($D29)/12,"") | U29: =IF(OR(COUNTA($A29:$C29)>0,$D29<>""),N($D29)/12,"") | V29: =IF(OR(COUNTA($A29:$C29)>0,$D29<>""),N($D29)/12,"") | W29: =IF(OR(COUNTA($A29:$C29)>0,$D29<>""),N($D29)/12,"") | X29: =IF(OR(COUNTA($A29:$C29)>0,$D29<>""),N($D29)/12,"") | Y29: =IF(OR(COUNTA($A29:$C29)>0,$D29<>""),N($D29)/12,"") | ... AC29: =IF(OR(COUNTA($A29:$C29)>0,$D29<>""),N($D29)/12,"") | AD29: =IF(OR(COUNTA($A29:$C29)>0,$D29<>""),SUM(R29:AC29),"") | AE29: =IF(OR(COUNTA($A29:$C29)>0,$D29<>""),N($D29)/12,"") | AF29: =IF(OR(COUNTA($A29:$C29)>0,$D29<>""),N($D29)/12,"") | AG29: =IF(OR(COUNTA($A29:$C29)>0,$D29<>""),N($D29)/12,"") | AH29: =IF(OR(COUNTA($A29:$C29)>0,$D29<>""),N($D29)/12,"") | AI29: =IF(OR(COUNTA($A29:$C29)>0,$D29<>""),N($D29)/12,"") | AJ29: =IF(OR(COUNTA($A29:$C29)>0,$D29<>""),N($D29)/12,"") | AK29: =IF(OR(COUNTA($A29:$C29)>0,$D29<>""),N($D29)/12,"") | AL29: =IF(OR(COUNTA($A29:$C29)>0,$D29<>""),N($D29)/12,"") | ... AP29: =IF(OR(COUNTA($A29:$C29)>0,$D29<>""),N($D29)/12,"") | AQ29: =IF(OR(COUNTA($A29:$C29)>0,$D29<>""),SUM(AE29:AP29),"")
E30: =IF(OR(COUNTA($A30:$C30)>0,$D30<>""),N($D30)/12,"") | F30: =IF(OR(COUNTA($A30:$C30)>0,$D30<>""),N($D30)/12,"") | G30: =IF(OR(COUNTA($A30:$C30)>0,$D30<>""),N($D30)/12,"") | H30: =IF(OR(COUNTA($A30:$C30)>0,$D30<>""),N($D30)/12,"") | I30: =IF(OR(COUNTA($A30:$C30)>0,$D30<>""),N($D30)/12,"") | J30: =IF(OR(COUNTA($A30:$C30)>0,$D30<>""),N($D30)/12,"") | K30: =IF(OR(COUNTA($A30:$C30)>0,$D30<>""),N($D30)/12,"") | L30: =IF(OR(COUNTA($A30:$C30)>0,$D30<>""),N($D30)/12,"") | ... P30: =IF(OR(COUNTA($A30:$C30)>0,$D30<>""),N($D30)/12,"") | Q30: =IF(OR(COUNTA($A30:$C30)>0,$D30<>""),SUM(E30:P30),"") | R30: =IF(OR(COUNTA($A30:$C30)>0,$D30<>""),N($D30)/12,"") | S30: =IF(OR(COUNTA($A30:$C30)>0,$D30<>""),N($D30)/12,"") | T30: =IF(OR(COUNTA($A30:$C30)>0,$D30<>""),N($D30)/12,"") | U30: =IF(OR(COUNTA($A30:$C30)>0,$D30<>""),N($D30)/12,"") | V30: =IF(OR(COUNTA($A30:$C30)>0,$D30<>""),N($D30)/12,"") | W30: =IF(OR(COUNTA($A30:$C30)>0,$D30<>""),N($D30)/12,"") | X30: =IF(OR(COUNTA($A30:$C30)>0,$D30<>""),N($D30)/12,"") | Y30: =IF(OR(COUNTA($A30:$C30)>0,$D30<>""),N($D30)/12,"") | ... AC30: =IF(OR(COUNTA($A30:$C30)>0,$D30<>""),N($D30)/12,"") | AD30: =IF(OR(COUNTA($A30:$C30)>0,$D30<>""),SUM(R30:AC30),"") | AE30: =IF(OR(COUNTA($A30:$C30)>0,$D30<>""),N($D30)/12,"") | AF30: =IF(OR(COUNTA($A30:$C30)>0,$D30<>""),N($D30)/12,"") | AG30: =IF(OR(COUNTA($A30:$C30)>0,$D30<>""),N($D30)/12,"") | AH30: =IF(OR(COUNTA($A30:$C30)>0,$D30<>""),N($D30)/12,"") | AI30: =IF(OR(COUNTA($A30:$C30)>0,$D30<>""),N($D30)/12,"") | AJ30: =IF(OR(COUNTA($A30:$C30)>0,$D30<>""),N($D30)/12,"") | AK30: =IF(OR(COUNTA($A30:$C30)>0,$D30<>""),N($D30)/12,"") | AL30: =IF(OR(COUNTA($A30:$C30)>0,$D30<>""),N($D30)/12,"") | ... AP30: =IF(OR(COUNTA($A30:$C30)>0,$D30<>""),N($D30)/12,"") | AQ30: =IF(OR(COUNTA($A30:$C30)>0,$D30<>""),SUM(AE30:AP30),"")
E31: =IF(OR(COUNTA($A31:$C31)>0,$D31<>""),N($D31)/12,"") | F31: =IF(OR(COUNTA($A31:$C31)>0,$D31<>""),N($D31)/12,"") | G31: =IF(OR(COUNTA($A31:$C31)>0,$D31<>""),N($D31)/12,"") | H31: =IF(OR(COUNTA($A31:$C31)>0,$D31<>""),N($D31)/12,"") | I31: =IF(OR(COUNTA($A31:$C31)>0,$D31<>""),N($D31)/12,"") | J31: =IF(OR(COUNTA($A31:$C31)>0,$D31<>""),N($D31)/12,"") | K31: =IF(OR(COUNTA($A31:$C31)>0,$D31<>""),N($D31)/12,"") | L31: =IF(OR(COUNTA($A31:$C31)>0,$D31<>""),N($D31)/12,"") | ... P31: =IF(OR(COUNTA($A31:$C31)>0,$D31<>""),N($D31)/12,"") | Q31: =IF(OR(COUNTA($A31:$C31)>0,$D31<>""),SUM(E31:P31),"") | R31: =IF(OR(COUNTA($A31:$C31)>0,$D31<>""),N($D31)/12,"") | S31: =IF(OR(COUNTA($A31:$C31)>0,$D31<>""),N($D31)/12,"") | T31: =IF(OR(COUNTA($A31:$C31)>0,$D31<>""),N($D31)/12,"") | U31: =IF(OR(COUNTA($A31:$C31)>0,$D31<>""),N($D31)/12,"") | V31: =IF(OR(COUNTA($A31:$C31)>0,$D31<>""),N($D31)/12,"") | W31: =IF(OR(COUNTA($A31:$C31)>0,$D31<>""),N($D31)/12,"") | X31: =IF(OR(COUNTA($A31:$C31)>0,$D31<>""),N($D31)/12,"") | Y31: =IF(OR(COUNTA($A31:$C31)>0,$D31<>""),N($D31)/12,"") | ... AC31: =IF(OR(COUNTA($A31:$C31)>0,$D31<>""),N($D31)/12,"") | AD31: =IF(OR(COUNTA($A31:$C31)>0,$D31<>""),SUM(R31:AC31),"") | AE31: =IF(OR(COUNTA($A31:$C31)>0,$D31<>""),N($D31)/12,"") | AF31: =IF(OR(COUNTA($A31:$C31)>0,$D31<>""),N($D31)/12,"") | AG31: =IF(OR(COUNTA($A31:$C31)>0,$D31<>""),N($D31)/12,"") | AH31: =IF(OR(COUNTA($A31:$C31)>0,$D31<>""),N($D31)/12,"") | AI31: =IF(OR(COUNTA($A31:$C31)>0,$D31<>""),N($D31)/12,"") | AJ31: =IF(OR(COUNTA($A31:$C31)>0,$D31<>""),N($D31)/12,"") | AK31: =IF(OR(COUNTA($A31:$C31)>0,$D31<>""),N($D31)/12,"") | AL31: =IF(OR(COUNTA($A31:$C31)>0,$D31<>""),N($D31)/12,"") | ... AP31: =IF(OR(COUNTA($A31:$C31)>0,$D31<>""),N($D31)/12,"") | AQ31: =IF(OR(COUNTA($A31:$C31)>0,$D31<>""),SUM(AE31:AP31),"")
E32: =IF(OR(COUNTA($A32:$C32)>0,$D32<>""),N($D32)/12,"") | F32: =IF(OR(COUNTA($A32:$C32)>0,$D32<>""),N($D32)/12,"") | G32: =IF(OR(COUNTA($A32:$C32)>0,$D32<>""),N($D32)/12,"") | H32: =IF(OR(COUNTA($A32:$C32)>0,$D32<>""),N($D32)/12,"") | I32: =IF(OR(COUNTA($A32:$C32)>0,$D32<>""),N($D32)/12,"") | J32: =IF(OR(COUNTA($A32:$C32)>0,$D32<>""),N($D32)/12,"") | K32: =IF(OR(COUNTA($A32:$C32)>0,$D32<>""),N($D32)/12,"") | L32: =IF(OR(COUNTA($A32:$C32)>0,$D32<>""),N($D32)/12,"") | ... P32: =IF(OR(COUNTA($A32:$C32)>0,$D32<>""),N($D32)/12,"") | Q32: =IF(OR(COUNTA($A32:$C32)>0,$D32<>""),SUM(E32:P32),"") | R32: =IF(OR(COUNTA($A32:$C32)>0,$D32<>""),N($D32)/12,"") | S32: =IF(OR(COUNTA($A32:$C32)>0,$D32<>""),N($D32)/12,"") | T32: =IF(OR(COUNTA($A32:$C32)>0,$D32<>""),N($D32)/12,"") | U32: =IF(OR(COUNTA($A32:$C32)>0,$D32<>""),N($D32)/12,"") | V32: =IF(OR(COUNTA($A32:$C32)>0,$D32<>""),N($D32)/12,"") | W32: =IF(OR(COUNTA($A32:$C32)>0,$D32<>""),N($D32)/12,"") | X32: =IF(OR(COUNTA($A32:$C32)>0,$D32<>""),N($D32)/12,"") | Y32: =IF(OR(COUNTA($A32:$C32)>0,$D32<>""),N($D32)/12,"") | ... AC32: =IF(OR(COUNTA($A32:$C32)>0,$D32<>""),N($D32)/12,"") | AD32: =IF(OR(COUNTA($A32:$C32)>0,$D32<>""),SUM(R32:AC32),"") | AE32: =IF(OR(COUNTA($A32:$C32)>0,$D32<>""),N($D32)/12,"") | AF32: =IF(OR(COUNTA($A32:$C32)>0,$D32<>""),N($D32)/12,"") | AG32: =IF(OR(COUNTA($A32:$C32)>0,$D32<>""),N($D32)/12,"") | AH32: =IF(OR(COUNTA($A32:$C32)>0,$D32<>""),N($D32)/12,"") | AI32: =IF(OR(COUNTA($A32:$C32)>0,$D32<>""),N($D32)/12,"") | AJ32: =IF(OR(COUNTA($A32:$C32)>0,$D32<>""),N($D32)/12,"") | AK32: =IF(OR(COUNTA($A32:$C32)>0,$D32<>""),N($D32)/12,"") | AL32: =IF(OR(COUNTA($A32:$C32)>0,$D32<>""),N($D32)/12,"") | ... AP32: =IF(OR(COUNTA($A32:$C32)>0,$D32<>""),N($D32)/12,"") | AQ32: =IF(OR(COUNTA($A32:$C32)>0,$D32<>""),SUM(AE32:AP32),"")
E33: =IF(OR(COUNTA($A33:$C33)>0,$D33<>""),N($D33)/12,"") | F33: =IF(OR(COUNTA($A33:$C33)>0,$D33<>""),N($D33)/12,"") | G33: =IF(OR(COUNTA($A33:$C33)>0,$D33<>""),N($D33)/12,"") | H33: =IF(OR(COUNTA($A33:$C33)>0,$D33<>""),N($D33)/12,"") | I33: =IF(OR(COUNTA($A33:$C33)>0,$D33<>""),N($D33)/12,"") | J33: =IF(OR(COUNTA($A33:$C33)>0,$D33<>""),N($D33)/12,"") | K33: =IF(OR(COUNTA($A33:$C33)>0,$D33<>""),N($D33)/12,"") | L33: =IF(OR(COUNTA($A33:$C33)>0,$D33<>""),N($D33)/12,"") | ... P33: =IF(OR(COUNTA($A33:$C33)>0,$D33<>""),N($D33)/12,"") | Q33: =IF(OR(COUNTA($A33:$C33)>0,$D33<>""),SUM(E33:P33),"") | R33: =IF(OR(COUNTA($A33:$C33)>0,$D33<>""),N($D33)/12,"") | S33: =IF(OR(COUNTA($A33:$C33)>0,$D33<>""),N($D33)/12,"") | T33: =IF(OR(COUNTA($A33:$C33)>0,$D33<>""),N($D33)/12,"") | U33: =IF(OR(COUNTA($A33:$C33)>0,$D33<>""),N($D33)/12,"") | V33: =IF(OR(COUNTA($A33:$C33)>0,$D33<>""),N($D33)/12,"") | W33: =IF(OR(COUNTA($A33:$C33)>0,$D33<>""),N($D33)/12,"") | X33: =IF(OR(COUNTA($A33:$C33)>0,$D33<>""),N($D33)/12,"") | Y33: =IF(OR(COUNTA($A33:$C33)>0,$D33<>""),N($D33)/12,"") | ... AC33: =IF(OR(COUNTA($A33:$C33)>0,$D33<>""),N($D33)/12,"") | AD33: =IF(OR(COUNTA($A33:$C33)>0,$D33<>""),SUM(R33:AC33),"") | AE33: =IF(OR(COUNTA($A33:$C33)>0,$D33<>""),N($D33)/12,"") | AF33: =IF(OR(COUNTA($A33:$C33)>0,$D33<>""),N($D33)/12,"") | AG33: =IF(OR(COUNTA($A33:$C33)>0,$D33<>""),N($D33)/12,"") | AH33: =IF(OR(COUNTA($A33:$C33)>0,$D33<>""),N($D33)/12,"") | AI33: =IF(OR(COUNTA($A33:$C33)>0,$D33<>""),N($D33)/12,"") | AJ33: =IF(OR(COUNTA($A33:$C33)>0,$D33<>""),N($D33)/12,"") | AK33: =IF(OR(COUNTA($A33:$C33)>0,$D33<>""),N($D33)/12,"") | AL33: =IF(OR(COUNTA($A33:$C33)>0,$D33<>""),N($D33)/12,"") | ... AP33: =IF(OR(COUNTA($A33:$C33)>0,$D33<>""),N($D33)/12,"") | AQ33: =IF(OR(COUNTA($A33:$C33)>0,$D33<>""),SUM(AE33:AP33),"")
E34: =IF(OR(COUNTA($A34:$C34)>0,$D34<>""),N($D34)/12,"") | F34: =IF(OR(COUNTA($A34:$C34)>0,$D34<>""),N($D34)/12,"") | G34: =IF(OR(COUNTA($A34:$C34)>0,$D34<>""),N($D34)/12,"") | H34: =IF(OR(COUNTA($A34:$C34)>0,$D34<>""),N($D34)/12,"") | I34: =IF(OR(COUNTA($A34:$C34)>0,$D34<>""),N($D34)/12,"") | J34: =IF(OR(COUNTA($A34:$C34)>0,$D34<>""),N($D34)/12,"") | K34: =IF(OR(COUNTA($A34:$C34)>0,$D34<>""),N($D34)/12,"") | L34: =IF(OR(COUNTA($A34:$C34)>0,$D34<>""),N($D34)/12,"") | ... P34: =IF(OR(COUNTA($A34:$C34)>0,$D34<>""),N($D34)/12,"") | Q34: =IF(OR(COUNTA($A34:$C34)>0,$D34<>""),SUM(E34:P34),"") | R34: =IF(OR(COUNTA($A34:$C34)>0,$D34<>""),N($D34)/12,"") | S34: =IF(OR(COUNTA($A34:$C34)>0,$D34<>""),N($D34)/12,"") | T34: =IF(OR(COUNTA($A34:$C34)>0,$D34<>""),N($D34)/12,"") | U34: =IF(OR(COUNTA($A34:$C34)>0,$D34<>""),N($D34)/12,"") | V34: =IF(OR(COUNTA($A34:$C34)>0,$D34<>""),N($D34)/12,"") | W34: =IF(OR(COUNTA($A34:$C34)>0,$D34<>""),N($D34)/12,"") | X34: =IF(OR(COUNTA($A34:$C34)>0,$D34<>""),N($D34)/12,"") | Y34: =IF(OR(COUNTA($A34:$C34)>0,$D34<>""),N($D34)/12,"") | ... AC34: =IF(OR(COUNTA($A34:$C34)>0,$D34<>""),N($D34)/12,"") | AD34: =IF(OR(COUNTA($A34:$C34)>0,$D34<>""),SUM(R34:AC34),"") | AE34: =IF(OR(COUNTA($A34:$C34)>0,$D34<>""),N($D34)/12,"") | AF34: =IF(OR(COUNTA($A34:$C34)>0,$D34<>""),N($D34)/12,"") | AG34: =IF(OR(COUNTA($A34:$C34)>0,$D34<>""),N($D34)/12,"") | AH34: =IF(OR(COUNTA($A34:$C34)>0,$D34<>""),N($D34)/12,"") | AI34: =IF(OR(COUNTA($A34:$C34)>0,$D34<>""),N($D34)/12,"") | AJ34: =IF(OR(COUNTA($A34:$C34)>0,$D34<>""),N($D34)/12,"") | AK34: =IF(OR(COUNTA($A34:$C34)>0,$D34<>""),N($D34)/12,"") | AL34: =IF(OR(COUNTA($A34:$C34)>0,$D34<>""),N($D34)/12,"") | ... AP34: =IF(OR(COUNTA($A34:$C34)>0,$D34<>""),N($D34)/12,"") | AQ34: =IF(OR(COUNTA($A34:$C34)>0,$D34<>""),SUM(AE34:AP34),"")
E35: =IF(OR(COUNTA($A35:$C35)>0,$D35<>""),N($D35)/12,"") | F35: =IF(OR(COUNTA($A35:$C35)>0,$D35<>""),N($D35)/12,"") | G35: =IF(OR(COUNTA($A35:$C35)>0,$D35<>""),N($D35)/12,"") | H35: =IF(OR(COUNTA($A35:$C35)>0,$D35<>""),N($D35)/12,"") | I35: =IF(OR(COUNTA($A35:$C35)>0,$D35<>""),N($D35)/12,"") | J35: =IF(OR(COUNTA($A35:$C35)>0,$D35<>""),N($D35)/12,"") | K35: =IF(OR(COUNTA($A35:$C35)>0,$D35<>""),N($D35)/12,"") | L35: =IF(OR(COUNTA($A35:$C35)>0,$D35<>""),N($D35)/12,"") | ... P35: =IF(OR(COUNTA($A35:$C35)>0,$D35<>""),N($D35)/12,"") | Q35: =IF(OR(COUNTA($A35:$C35)>0,$D35<>""),SUM(E35:P35),"") | R35: =IF(OR(COUNTA($A35:$C35)>0,$D35<>""),N($D35)/12,"") | S35: =IF(OR(COUNTA($A35:$C35)>0,$D35<>""),N($D35)/12,"") | T35: =IF(OR(COUNTA($A35:$C35)>0,$D35<>""),N($D35)/12,"") | U35: =IF(OR(COUNTA($A35:$C35)>0,$D35<>""),N($D35)/12,"") | V35: =IF(OR(COUNTA($A35:$C35)>0,$D35<>""),N($D35)/12,"") | W35: =IF(OR(COUNTA($A35:$C35)>0,$D35<>""),N($D35)/12,"") | X35: =IF(OR(COUNTA($A35:$C35)>0,$D35<>""),N($D35)/12,"") | Y35: =IF(OR(COUNTA($A35:$C35)>0,$D35<>""),N($D35)/12,"") | ... AC35: =IF(OR(COUNTA($A35:$C35)>0,$D35<>""),N($D35)/12,"") | AD35: =IF(OR(COUNTA($A35:$C35)>0,$D35<>""),SUM(R35:AC35),"") | AE35: =IF(OR(COUNTA($A35:$C35)>0,$D35<>""),N($D35)/12,"") | AF35: =IF(OR(COUNTA($A35:$C35)>0,$D35<>""),N($D35)/12,"") | AG35: =IF(OR(COUNTA($A35:$C35)>0,$D35<>""),N($D35)/12,"") | AH35: =IF(OR(COUNTA($A35:$C35)>0,$D35<>""),N($D35)/12,"") | AI35: =IF(OR(COUNTA($A35:$C35)>0,$D35<>""),N($D35)/12,"") | AJ35: =IF(OR(COUNTA($A35:$C35)>0,$D35<>""),N($D35)/12,"") | AK35: =IF(OR(COUNTA($A35:$C35)>0,$D35<>""),N($D35)/12,"") | AL35: =IF(OR(COUNTA($A35:$C35)>0,$D35<>""),N($D35)/12,"") | ... AP35: =IF(OR(COUNTA($A35:$C35)>0,$D35<>""),N($D35)/12,"") | AQ35: =IF(OR(COUNTA($A35:$C35)>0,$D35<>""),SUM(AE35:AP35),"")
E36: =IF(OR(COUNTA($A36:$C36)>0,$D36<>""),N($D36)/12,"") | F36: =IF(OR(COUNTA($A36:$C36)>0,$D36<>""),N($D36)/12,"") | G36: =IF(OR(COUNTA($A36:$C36)>0,$D36<>""),N($D36)/12,"") | H36: =IF(OR(COUNTA($A36:$C36)>0,$D36<>""),N($D36)/12,"") | I36: =IF(OR(COUNTA($A36:$C36)>0,$D36<>""),N($D36)/12,"") | J36: =IF(OR(COUNTA($A36:$C36)>0,$D36<>""),N($D36)/12,"") | K36: =IF(OR(COUNTA($A36:$C36)>0,$D36<>""),N($D36)/12,"") | L36: =IF(OR(COUNTA($A36:$C36)>0,$D36<>""),N($D36)/12,"") | ... P36: =IF(OR(COUNTA($A36:$C36)>0,$D36<>""),N($D36)/12,"") | Q36: =IF(OR(COUNTA($A36:$C36)>0,$D36<>""),SUM(E36:P36),"") | R36: =IF(OR(COUNTA($A36:$C36)>0,$D36<>""),N($D36)/12,"") | S36: =IF(OR(COUNTA($A36:$C36)>0,$D36<>""),N($D36)/12,"") | T36: =IF(OR(COUNTA($A36:$C36)>0,$D36<>""),N($D36)/12,"") | U36: =IF(OR(COUNTA($A36:$C36)>0,$D36<>""),N($D36)/12,"") | V36: =IF(OR(COUNTA($A36:$C36)>0,$D36<>""),N($D36)/12,"") | W36: =IF(OR(COUNTA($A36:$C36)>0,$D36<>""),N($D36)/12,"") | X36: =IF(OR(COUNTA($A36:$C36)>0,$D36<>""),N($D36)/12,"") | Y36: =IF(OR(COUNTA($A36:$C36)>0,$D36<>""),N($D36)/12,"") | ... AC36: =IF(OR(COUNTA($A36:$C36)>0,$D36<>""),N($D36)/12,"") | AD36: =IF(OR(COUNTA($A36:$C36)>0,$D36<>""),SUM(R36:AC36),"") | AE36: =IF(OR(COUNTA($A36:$C36)>0,$D36<>""),N($D36)/12,"") | AF36: =IF(OR(COUNTA($A36:$C36)>0,$D36<>""),N($D36)/12,"") | AG36: =IF(OR(COUNTA($A36:$C36)>0,$D36<>""),N($D36)/12,"") | AH36: =IF(OR(COUNTA($A36:$C36)>0,$D36<>""),N($D36)/12,"") | AI36: =IF(OR(COUNTA($A36:$C36)>0,$D36<>""),N($D36)/12,"") | AJ36: =IF(OR(COUNTA($A36:$C36)>0,$D36<>""),N($D36)/12,"") | AK36: =IF(OR(COUNTA($A36:$C36)>0,$D36<>""),N($D36)/12,"") | AL36: =IF(OR(COUNTA($A36:$C36)>0,$D36<>""),N($D36)/12,"") | ... AP36: =IF(OR(COUNTA($A36:$C36)>0,$D36<>""),N($D36)/12,"") | AQ36: =IF(OR(COUNTA($A36:$C36)>0,$D36<>""),SUM(AE36:AP36),"")
E37: =IF(OR(COUNTA($A37:$C37)>0,$D37<>""),N($D37)/12,"") | F37: =IF(OR(COUNTA($A37:$C37)>0,$D37<>""),N($D37)/12,"") | G37: =IF(OR(COUNTA($A37:$C37)>0,$D37<>""),N($D37)/12,"") | H37: =IF(OR(COUNTA($A37:$C37)>0,$D37<>""),N($D37)/12,"") | I37: =IF(OR(COUNTA($A37:$C37)>0,$D37<>""),N($D37)/12,"") | J37: =IF(OR(COUNTA($A37:$C37)>0,$D37<>""),N($D37)/12,"") | K37: =IF(OR(COUNTA($A37:$C37)>0,$D37<>""),N($D37)/12,"") | L37: =IF(OR(COUNTA($A37:$C37)>0,$D37<>""),N($D37)/12,"") | ... P37: =IF(OR(COUNTA($A37:$C37)>0,$D37<>""),N($D37)/12,"") | Q37: =IF(OR(COUNTA($A37:$C37)>0,$D37<>""),SUM(E37:P37),"") | R37: =IF(OR(COUNTA($A37:$C37)>0,$D37<>""),N($D37)/12,"") | S37: =IF(OR(COUNTA($A37:$C37)>0,$D37<>""),N($D37)/12,"") | T37: =IF(OR(COUNTA($A37:$C37)>0,$D37<>""),N($D37)/12,"") | U37: =IF(OR(COUNTA($A37:$C37)>0,$D37<>""),N($D37)/12,"") | V37: =IF(OR(COUNTA($A37:$C37)>0,$D37<>""),N($D37)/12,"") | W37: =IF(OR(COUNTA($A37:$C37)>0,$D37<>""),N($D37)/12,"") | X37: =IF(OR(COUNTA($A37:$C37)>0,$D37<>""),N($D37)/12,"") | Y37: =IF(OR(COUNTA($A37:$C37)>0,$D37<>""),N($D37)/12,"") | ... AC37: =IF(OR(COUNTA($A37:$C37)>0,$D37<>""),N($D37)/12,"") | AD37: =IF(OR(COUNTA($A37:$C37)>0,$D37<>""),SUM(R37:AC37),"") | AE37: =IF(OR(COUNTA($A37:$C37)>0,$D37<>""),N($D37)/12,"") | AF37: =IF(OR(COUNTA($A37:$C37)>0,$D37<>""),N($D37)/12,"") | AG37: =IF(OR(COUNTA($A37:$C37)>0,$D37<>""),N($D37)/12,"") | AH37: =IF(OR(COUNTA($A37:$C37)>0,$D37<>""),N($D37)/12,"") | AI37: =IF(OR(COUNTA($A37:$C37)>0,$D37<>""),N($D37)/12,"") | AJ37: =IF(OR(COUNTA($A37:$C37)>0,$D37<>""),N($D37)/12,"") | AK37: =IF(OR(COUNTA($A37:$C37)>0,$D37<>""),N($D37)/12,"") | AL37: =IF(OR(COUNTA($A37:$C37)>0,$D37<>""),N($D37)/12,"") | ... AP37: =IF(OR(COUNTA($A37:$C37)>0,$D37<>""),N($D37)/12,"") | AQ37: =IF(OR(COUNTA($A37:$C37)>0,$D37<>""),SUM(AE37:AP37),"")
E38: =IF(OR(COUNTA($A38:$C38)>0,$D38<>""),N($D38)/12,"") | F38: =IF(OR(COUNTA($A38:$C38)>0,$D38<>""),N($D38)/12,"") | G38: =IF(OR(COUNTA($A38:$C38)>0,$D38<>""),N($D38)/12,"") | H38: =IF(OR(COUNTA($A38:$C38)>0,$D38<>""),N($D38)/12,"") | I38: =IF(OR(COUNTA($A38:$C38)>0,$D38<>""),N($D38)/12,"") | J38: =IF(OR(COUNTA($A38:$C38)>0,$D38<>""),N($D38)/12,"") | K38: =IF(OR(COUNTA($A38:$C38)>0,$D38<>""),N($D38)/12,"") | L38: =IF(OR(COUNTA($A38:$C38)>0,$D38<>""),N($D38)/12,"") | ... P38: =IF(OR(COUNTA($A38:$C38)>0,$D38<>""),N($D38)/12,"") | Q38: =IF(OR(COUNTA($A38:$C38)>0,$D38<>""),SUM(E38:P38),"") | R38: =IF(OR(COUNTA($A38:$C38)>0,$D38<>""),N($D38)/12,"") | S38: =IF(OR(COUNTA($A38:$C38)>0,$D38<>""),N($D38)/12,"") | T38: =IF(OR(COUNTA($A38:$C38)>0,$D38<>""),N($D38)/12,"") | U38: =IF(OR(COUNTA($A38:$C38)>0,$D38<>""),N($D38)/12,"") | V38: =IF(OR(COUNTA($A38:$C38)>0,$D38<>""),N($D38)/12,"") | W38: =IF(OR(COUNTA($A38:$C38)>0,$D38<>""),N($D38)/12,"") | X38: =IF(OR(COUNTA($A38:$C38)>0,$D38<>""),N($D38)/12,"") | Y38: =IF(OR(COUNTA($A38:$C38)>0,$D38<>""),N($D38)/12,"") | ... AC38: =IF(OR(COUNTA($A38:$C38)>0,$D38<>""),N($D38)/12,"") | AD38: =IF(OR(COUNTA($A38:$C38)>0,$D38<>""),SUM(R38:AC38),"") | AE38: =IF(OR(COUNTA($A38:$C38)>0,$D38<>""),N($D38)/12,"") | AF38: =IF(OR(COUNTA($A38:$C38)>0,$D38<>""),N($D38)/12,"") | AG38: =IF(OR(COUNTA($A38:$C38)>0,$D38<>""),N($D38)/12,"") | AH38: =IF(OR(COUNTA($A38:$C38)>0,$D38<>""),N($D38)/12,"") | AI38: =IF(OR(COUNTA($A38:$C38)>0,$D38<>""),N($D38)/12,"") | AJ38: =IF(OR(COUNTA($A38:$C38)>0,$D38<>""),N($D38)/12,"") | AK38: =IF(OR(COUNTA($A38:$C38)>0,$D38<>""),N($D38)/12,"") | AL38: =IF(OR(COUNTA($A38:$C38)>0,$D38<>""),N($D38)/12,"") | ... AP38: =IF(OR(COUNTA($A38:$C38)>0,$D38<>""),N($D38)/12,"") | AQ38: =IF(OR(COUNTA($A38:$C38)>0,$D38<>""),SUM(AE38:AP38),"")
E39: =IF(OR(COUNTA($A39:$C39)>0,$D39<>""),N($D39)/12,"") | F39: =IF(OR(COUNTA($A39:$C39)>0,$D39<>""),N($D39)/12,"") | G39: =IF(OR(COUNTA($A39:$C39)>0,$D39<>""),N($D39)/12,"") | H39: =IF(OR(COUNTA($A39:$C39)>0,$D39<>""),N($D39)/12,"") | I39: =IF(OR(COUNTA($A39:$C39)>0,$D39<>""),N($D39)/12,"") | J39: =IF(OR(COUNTA($A39:$C39)>0,$D39<>""),N($D39)/12,"") | K39: =IF(OR(COUNTA($A39:$C39)>0,$D39<>""),N($D39)/12,"") | L39: =IF(OR(COUNTA($A39:$C39)>0,$D39<>""),N($D39)/12,"") | ... P39: =IF(OR(COUNTA($A39:$C39)>0,$D39<>""),N($D39)/12,"") | Q39: =IF(OR(COUNTA($A39:$C39)>0,$D39<>""),SUM(E39:P39),"") | R39: =IF(OR(COUNTA($A39:$C39)>0,$D39<>""),N($D39)/12,"") | S39: =IF(OR(COUNTA($A39:$C39)>0,$D39<>""),N($D39)/12,"") | T39: =IF(OR(COUNTA($A39:$C39)>0,$D39<>""),N($D39)/12,"") | U39: =IF(OR(COUNTA($A39:$C39)>0,$D39<>""),N($D39)/12,"") | V39: =IF(OR(COUNTA($A39:$C39)>0,$D39<>""),N($D39)/12,"") | W39: =IF(OR(COUNTA($A39:$C39)>0,$D39<>""),N($D39)/12,"") | X39: =IF(OR(COUNTA($A39:$C39)>0,$D39<>""),N($D39)/12,"") | Y39: =IF(OR(COUNTA($A39:$C39)>0,$D39<>""),N($D39)/12,"") | ... AC39: =IF(OR(COUNTA($A39:$C39)>0,$D39<>""),N($D39)/12,"") | AD39: =IF(OR(COUNTA($A39:$C39)>0,$D39<>""),SUM(R39:AC39),"") | AE39: =IF(OR(COUNTA($A39:$C39)>0,$D39<>""),N($D39)/12,"") | AF39: =IF(OR(COUNTA($A39:$C39)>0,$D39<>""),N($D39)/12,"") | AG39: =IF(OR(COUNTA($A39:$C39)>0,$D39<>""),N($D39)/12,"") | AH39: =IF(OR(COUNTA($A39:$C39)>0,$D39<>""),N($D39)/12,"") | AI39: =IF(OR(COUNTA($A39:$C39)>0,$D39<>""),N($D39)/12,"") | AJ39: =IF(OR(COUNTA($A39:$C39)>0,$D39<>""),N($D39)/12,"") | AK39: =IF(OR(COUNTA($A39:$C39)>0,$D39<>""),N($D39)/12,"") | AL39: =IF(OR(COUNTA($A39:$C39)>0,$D39<>""),N($D39)/12,"") | ... AP39: =IF(OR(COUNTA($A39:$C39)>0,$D39<>""),N($D39)/12,"") | AQ39: =IF(OR(COUNTA($A39:$C39)>0,$D39<>""),SUM(AE39:AP39),"")
... E42: =IF(OR(COUNTA($A42:$C42)>0,$D42<>""),N($D42)/12,"") | F42: =IF(OR(COUNTA($A42:$C42)>0,$D42<>""),N($D42)/12,"") | G42: =IF(OR(COUNTA($A42:$C42)>0,$D42<>""),N($D42)/12,"") | H42: =IF(OR(COUNTA($A42:$C42)>0,$D42<>""),N($D42)/12,"") | I42: =IF(OR(COUNTA($A42:$C42)>0,$D42<>""),N($D42)/12,"") | J42: =IF(OR(COUNTA($A42:$C42)>0,$D42<>""),N($D42)/12,"") | K42: =IF(OR(COUNTA($A42:$C42)>0,$D42<>""),N($D42)/12,"") | L42: =IF(OR(COUNTA($A42:$C42)>0,$D42<>""),N($D42)/12,"") | ... P42: =IF(OR(COUNTA($A42:$C42)>0,$D42<>""),N($D42)/12,"") | Q42: =IF(OR(COUNTA($A42:$C42)>0,$D42<>""),SUM(E42:P42),"") | R42: =IF(OR(COUNTA($A42:$C42)>0,$D42<>""),N($D42)/12,"") | S42: =IF(OR(COUNTA($A42:$C42)>0,$D42<>""),N($D42)/12,"") | T42: =IF(OR(COUNTA($A42:$C42)>0,$D42<>""),N($D42)/12,"") | U42: =IF(OR(COUNTA($A42:$C42)>0,$D42<>""),N($D42)/12,"") | V42: =IF(OR(COUNTA($A42:$C42)>0,$D42<>""),N($D42)/12,"") | W42: =IF(OR(COUNTA($A42:$C42)>0,$D42<>""),N($D42)/12,"") | X42: =IF(OR(COUNTA($A42:$C42)>0,$D42<>""),N($D42)/12,"") | Y42: =IF(OR(COUNTA($A42:$C42)>0,$D42<>""),N($D42)/12,"") | ... AC42: =IF(OR(COUNTA($A42:$C42)>0,$D42<>""),N($D42)/12,"") | AD42: =IF(OR(COUNTA($A42:$C42)>0,$D42<>""),SUM(R42:AC42),"") | AE42: =IF(OR(COUNTA($A42:$C42)>0,$D42<>""),N($D42)/12,"") | AF42: =IF(OR(COUNTA($A42:$C42)>0,$D42<>""),N($D42)/12,"") | AG42: =IF(OR(COUNTA($A42:$C42)>0,$D42<>""),N($D42)/12,"") | AH42: =IF(OR(COUNTA($A42:$C42)>0,$D42<>""),N($D42)/12,"") | AI42: =IF(OR(COUNTA($A42:$C42)>0,$D42<>""),N($D42)/12,"") | AJ42: =IF(OR(COUNTA($A42:$C42)>0,$D42<>""),N($D42)/12,"") | AK42: =IF(OR(COUNTA($A42:$C42)>0,$D42<>""),N($D42)/12,"") | AL42: =IF(OR(COUNTA($A42:$C42)>0,$D42<>""),N($D42)/12,"") | ... AP42: =IF(OR(COUNTA($A42:$C42)>0,$D42<>""),N($D42)/12,"") | AQ42: =IF(OR(COUNTA($A42:$C42)>0,$D42<>""),SUM(AE42:AP42),"")
A44: Total Essentials Bonus / Contract Labor / Non-Payroll Incremental Spend | D44: =SUM(tblNonPayrollIncrementalSpend3[Annualized Spend]) -> 0 | E44: =SUM(tblNonPayrollIncrementalSpend3[Jan-27]) -> 0 | F44: =SUM(tblNonPayrollIncrementalSpend3[Feb-27]) -> 0 | G44: =SUM(tblNonPayrollIncrementalSpend3[Mar-27]) -> 0 | H44: =SUM(tblNonPayrollIncrementalSpend3[Apr-27]) -> 0 | I44: =SUM(tblNonPayrollIncrementalSpend3[May-27]) -> 0 | J44: =SUM(tblNonPayrollIncrementalSpend3[Jun-27]) -> 0 | K44: =SUM(tblNonPayrollIncrementalSpend3[Jul-27]) -> 0 | L44: =SUM(tblNonPayrollIncrementalSpend3[Aug-27]) -> 0 | M44: =SUM(tblNonPayrollIncrementalSpend3[Sep-27]) -> 0 | N44: =SUM(tblNonPayrollIncrementalSpend3[Oct-27]) -> 0 | O44: =SUM(tblNonPayrollIncrementalSpend3[Nov-27]) -> 0 | P44: =SUM(tblNonPayrollIncrementalSpend3[Dec-27]) -> 0 | Q44: =SUM(tblNonPayrollIncrementalSpend3[2027 Incremental Spend]) -> 0 | R44: =SUM(tblNonPayrollIncrementalSpend3[Jan-28]) -> 0 | S44: =SUM(tblNonPayrollIncrementalSpend3[Feb-28]) -> 0 | T44: =SUM(tblNonPayrollIncrementalSpend3[Mar-28]) -> 0 | U44: =SUM(tblNonPayrollIncrementalSpend3[Apr-28]) -> 0 | V44: =SUM(tblNonPayrollIncrementalSpend3[May-28]) -> 0 | W44: =SUM(tblNonPayrollIncrementalSpend3[Jun-28]) -> 0 | X44: =SUM(tblNonPayrollIncrementalSpend3[Jul-28]) -> 0 | Y44: =SUM(tblNonPayrollIncrementalSpend3[Aug-28]) -> 0 | Z44: =SUM(tblNonPayrollIncrementalSpend3[Sep-28]) -> 0 | AA44: =SUM(tblNonPayrollIncrementalSpend3[Oct-28]) -> 0 | AB44: =SUM(tblNonPayrollIncrementalSpend3[Nov-28]) -> 0 | AC44: =SUM(tblNonPayrollIncrementalSpend3[Dec-28]) -> 0 | AD44: =SUM(tblNonPayrollIncrementalSpend3[2028 Incremental Spend]) -> 0 | AE44: =SUM(tblNonPayrollIncrementalSpend3[Jan-29]) -> 0 | AF44: =SUM(tblNonPayrollIncrementalSpend3[Feb-29]) -> 0 | AG44: =SUM(tblNonPayrollIncrementalSpend3[Mar-29]) -> 0 | AH44: =SUM(tblNonPayrollIncrementalSpend3[Apr-29]) -> 0 | AI44: =SUM(tblNonPayrollIncrementalSpend3[May-29]) -> 0 | AJ44: =SUM(tblNonPayrollIncrementalSpend3[Jun-29]) -> 0 | AK44: =SUM(tblNonPayrollIncrementalSpend3[Jul-29]) -> 0 | AL44: =SUM(tblNonPayrollIncrementalSpend3[Aug-29]) -> 0 | AM44: =SUM(tblNonPayrollIncrementalSpend3[Sep-29]) -> 0 | AN44: =SUM(tblNonPayrollIncrementalSpend3[Oct-29]) -> 0 | AO44: =SUM(tblNonPayrollIncrementalSpend3[Nov-29]) -> 0 | AP44: =SUM(tblNonPayrollIncrementalSpend3[Dec-29]) -> 0 | AQ44: =SUM(tblNonPayrollIncrementalSpend3[2029 Incremental Spend]) -> 0

Sheet Questions to Ask
A1: Questions to Ask - Investment Case
A3: # | B3: Question | C3: Guidance / What to Address
A4: 1 | B4: What strategic objective or growth opportunity does this investment enable? | C4: • What business objective, strategic initiative, or growth opportunity does this investment support? • How does the investment align with priorities and outcomes in the 2027–2029 business plan?
A5: 2 | B5: What business milestone should trigger this investment? | C5: • Describe why the investment is needed now, or identify the business milestone that would warrant the investment in the future. • Explain how the timing of the investment aligns with the expected growth of the business.
A6: 3 | B6: What alternatives were considered? | C6: • What alternatives were evaluated before requesting incremental spend, including process improvements, AI/automation, technology solutions, third-party providers, or redeployment of existing resources? • Why is incremental headcount or G&A the most effective solution?
A7: 4 | B7: What measurable business outcome will this investment deliver? | C7: • What are the expected business outcomes and how will success be measured? • Tie the request to measurable growth or scale, e.g., revenue, AUM, MW deployed, customers served, operating sites, projects delivered, cost savings, or risk reduction.
A8: 5 | B8: What is the impact if this investment is not approved? | C8: • What is the expected business impact if the investment is deferred or not approved? • What are the implications for growth, execution of strategic initiatives, customer commitments, operational performance, financial results, or risk management?

Sheet Baseline Support -->

Sheet Base - Payroll
B1: CC_CL | C1: Account | D1: Actual | E1: 04/2026 - Q126 Earnings FCST | F1: Growth Rate | G1: Model | H1: Model | I1: Model
D2: 2025 | E2: 2026 | F2: 2026 vs. 2025 | G2: 2027 | H2: 2028 | I2: 2029
A3: Compensation | B3: Essentials Operations | C3: COMP - Compensation | D3: 9991465 | E3: 11677112 | F3: =E3/D3-1 -> 0.16870869 | G3: 12353631 | H3: =G3 -> 12353631 | I3: =H3 -> 12353631 | J3: 2027 From Current FCST excluding Merit
A4: Payroll Taxes | B4: Essentials Operations | C4: PAYROLL_TAX - Payroll tax | D4: 1268881 | E4: 1500352 | F4: =E4/D4-1 -> 0.18242136 | G4: =$G$3*E12 -> 1587275.6 | H4: =G4 -> 1587275.6 | I4: =H4 -> 1587275.6
A5: Benefits | B5: Essentials Operations | C5: BEN - Benefits | D5: 1491681 | E5: 1806053 | F5: =E5/D5-1 -> 0.21075015 | G5: =$G$3*E13 -> 1910687.5 | H5: =G5 -> 1910687.5 | I5: =H5 -> 1910687.5
A6: Bonus | B6: Essentials Operations | C6: BON - Bonus | D6: 2069738 | E6: 2316552 | F6: =E6/D6-1 -> 0.11924891 | G6: =$G$3*E14 -> 2450762.5 | H6: =G6 -> 2450762.5 | I6: =H6 -> 2450762.5
A7: Vacation | B7: Essentials Operations | C7: VAC - Vacation | D7: 141769 | E7: 127917 | F7: =E7/D7-1 -> -0.097708244 | G7: =$G$3*E15 -> 135327.93 | H7: =G7 -> 135327.93 | I7: =H7 -> 135327.93
A8: Other | B8: Essentials Operations | C8: OTHER - Other | D8: 39950 | E8: 50 | F8: =E8/D8-1 -> -0.99874844 | G8: =$G$3*E16 -> 52.896774 | H8: =G8 -> 52.896774 | I8: =H8 -> 52.896774
A9: LTIP Compensation | B9: Essentials Operations | C9: LTIP_COMP - LTIP Compensation | D9: 1340507.9 | E9: 1515941.8 | F9: =E9/D9-1 -> 0.13087125 | G9: =((E9/D9-1)+1)*E9 -> 1714335 | H9: =G9 -> 1714335 | I9: =H9 -> 1714335
D10: =SUM(D3:D9) -> 16343992 | E10: =SUM(E3:E9) -> 18943978 | G10: =SUM(G3:G9) -> 20152072 | H10: =SUM(H3:H9) -> 20152072 | I10: =SUM(I3:I9) -> 20152072
B12: Essentials Operations | C12: PAYROLL_TAX - Payroll tax | D12: =D4/$D$3 -> 0.12699649 | E12: =E4/$E$3 -> 0.12848656 | G12: =G4/$G$3 -> 0.12848656 | H12: =H4/$H$3 -> 0.12848656 | I12: =I4/$I$3 -> 0.12848656
