Workbook
Name dvTypeOfExpenseList: 'Base - Non-Payroll'!$A$3:$A$25

Sheet Summary
B1: Energy Solutions | H1: Energy | N1: Energy Finance | T1: Mobility | Z1: ES Leadership
B3: Total | H3: Total | N3: Total | T3: Total | Z3: Total
C4: 2026 | D4: 2027 | E4: 2028 | F4: 2029 | I4: 2026 | J4: 2027 | K4: 2028 | L4: 2029 | O4: 2026 | P4: 2027 | Q4: 2028 | R4: 2029 | U4: 2026 | V4: 2027 | W4: 2028 | X4: 2029 | AA4: 2026 | AB4: 2027 | AC4: 2028 | AD4: 2029
B5: Compensation | C5: =C43+C81 -> 27021147 | D5: =D43+D81 -> 28096812 | E5: =E43+E81 -> 28096812 | F5: =F43+F81 -> 28096812 | H5: Compensation | I5: =I43+I81 -> 17132061 | J5: =J43+J81 -> 17864963 | K5: =K43+K81 -> 17864963 | L5: =L43+L81 -> 17864963 | N5: Compensation | O5: =O43+O81 -> 2947996.3 | P5: =P43+P81 -> 3072936.5 | Q5: =Q43+Q81 -> 3072936.5 | R5: =R43+R81 -> 3072936.5 | T5: Compensation | U5: =U43+U81 -> 5943317.7 | V5: =V43+V81 -> 6160231.7 | W5: =W43+W81 -> 6160231.7 | X5: =X43+X81 -> 6160231.7 | Z5: Compensation | AA5: =AA43+AA81 -> 997771.84 | AB5: =AB43+AB81 -> 998680.58 | AC5: =AC43+AC81 -> 998680.58 | AD5: =AD43+AD81 -> 998680.58
B6: Bonus | C6: =C44+C82 -> 7777198.6 | D6: =D44+D82 -> 8060204.2 | E6: =E44+E82 -> 8060204.2 | F6: =F44+F82 -> 8060204.2 | H6: Bonus | I6: =I44+I82 -> 4275135.5 | J6: =J44+J82 -> 4458023.8 | K6: =K44+K82 -> 4458023.8 | L6: =L44+L82 -> 4458023.8 | N6: Bonus | O6: =O44+O82 -> 843955.68 | P6: =P44+P82 -> 879723.71 | Q6: =Q44+Q82 -> 879723.71 | R6: =R44+R82 -> 879723.71 | T6: Bonus | U6: =U44+U82 -> 1740227.4 | V6: =V44+V82 -> 1803740.7 | W6: =W44+W82 -> 1803740.7 | X6: =X44+X82 -> 1803740.7 | Z6: Bonus | AA6: =AA44+AA82 -> 917880.07 | AB6: =AB44+AB82 -> 918716.04 | AC6: =AC44+AC82 -> 918716.04 | AD6: =AD44+AD82 -> 918716.04
B7: Essentials Bonus | C7: =C45+C83 -> 1285296.4 | D7: =D45+D83 -> 1285296.4 | E7: =E45+E83 -> 1285296.4 | F7: =F45+F83 -> 1285296.4 | H7: Essentials Bonus | I7: =I45+I83 -> 876620.84 | J7: =J45+J83 -> 876620.84 | K7: =K45+K83 -> 876620.84 | L7: =L45+L83 -> 876620.84 | N7: Essentials Bonus | O7: =O45+O83 -> 0 | P7: =P45+P83 -> 0 | Q7: =Q45+Q83 -> 0 | R7: =R45+R83 -> 0 | T7: Essentials Bonus | U7: =U45+U83 -> 408675.58 | V7: =V45+V83 -> 408675.58 | W7: =W45+W83 -> 408675.58 | X7: =X45+X83 -> 408675.58 | Z7: Essentials Bonus | AA7: =AA45+AA83 -> 0 | AB7: =AB45+AB83 -> 0 | AC7: =AC45+AC83 -> 0 | AD7: =AD45+AD83 -> 0
B8: Payroll Taxes | C8: =C46+C84 -> 3096763 | D8: =D46+D84 -> 3222133.9 | E8: =E46+E84 -> 3222133.9 | F8: =F46+F84 -> 3222133.9 | H8: Payroll Taxes | I8: =I46+I84 -> 1954237.2 | J8: =J46+J84 -> 2037838.5 | K8: =K46+K84 -> 2037838.5 | L8: =L46+L84 -> 2037838.5 | N8: Payroll Taxes | O8: =O46+O84 -> 321560.41 | P8: =P46+P84 -> 335188.59 | Q8: =Q46+Q84 -> 335188.59 | R8: =R46+R84 -> 335188.59 | T8: Payroll Taxes | U8: =U46+U84 -> 769778.04 | V8: =V46+V84 -> 797872.74 | W8: =W46+W84 -> 797872.74 | X8: =X46+X84 -> 797872.74 | Z8: Payroll Taxes | AA8: =AA46+AA84 -> 51187.428 | AB8: =AB46+AB84 -> 51234.048 | AC8: =AC46+AC84 -> 51234.048 | AD8: =AD46+AD84 -> 51234.048
B9: Benefits | C9: =C47+C85 -> 3960803.5 | D9: =D47+D85 -> 4121887.8 | E9: =E47+E85 -> 4121887.8 | F9: =F47+F85 -> 4121887.8 | H9: Benefits | I9: =I47+I85 -> 2599951 | J9: =J47+J85 -> 2711175.7 | K9: =K47+K85 -> 2711175.7 | L9: =L47+L85 -> 2711175.7 | N9: Benefits | O9: =O47+O85 -> 426285.43 | P9: =P47+P85 -> 444352.01 | Q9: =Q47+Q85 -> 444352.01 | R9: =R47+R85 -> 444352.01 | T9: Benefits | U9: =U47+U85 -> 869486.31 | V9: =V47+V85 -> 901220.07 | W9: =W47+W85 -> 901220.07 | X9: =X47+X85 -> 901220.07 | Z9: Benefits | AA9: =AA47+AA85 -> 65080.753 | AB9: =AB47+AB85 -> 65140.026 | AC9: =AC47+AC85 -> 65140.026 | AD9: =AD47+AD85 -> 65140.026
B10: Vacation | C10: =C48+C86 -> 173675.52 | D10: =D48+D86 -> 180708.81 | E10: =E48+E86 -> 180708.81 | F10: =F48+F86 -> 180708.81 | H10: Vacation | I10: =I48+I86 -> 97547.456 | J10: =J48+J86 -> 101720.49 | K10: =K48+K86 -> 101720.49 | L10: =L48+L86 -> 101720.49 | N10: Vacation | O10: =O48+O86 -> 13900.738 | P10: =P48+P86 -> 14489.871 | Q10: =Q48+Q86 -> 14489.871 | R10: =R48+R86 -> 14489.871 | T10: Vacation | U10: =U48+U86 -> 62227.33 | V10: =V48+V86 -> 64498.449 | W10: =W48+W86 -> 64498.449 | X10: =X48+X86 -> 64498.449 | Z10: Vacation | AA10: =AA48+AA86 -> 0 | AB10: =AB48+AB86 -> 0 | AC10: =AC48+AC86 -> 0 | AD10: =AD48+AD86 -> 0
B11: Other | C11: =C49+C87 -> -421719.89 | D11: =D49+D87 -> 377.897 | E11: =E49+E87 -> 377.897 | F11: =F49+F87 -> 377.897 | H11: Other | I11: =I49+I87 -> 362.39396 | J11: =J49+J87 -> 377.897 | K11: =K49+K87 -> 377.897 | L11: =L49+L87 -> 377.897 | N11: Other | O11: =O49+O87 -> 0 | P11: =P49+P87 -> 0 | Q11: =Q49+Q87 -> 0 | R11: =R49+R87 -> 0 | T11: Other | U11: =U49+U87 -> -422082.28 | V11: =V49+V87 -> 0 | W11: =W49+W87 -> 0 | X11: =X49+X87 -> 0 | Z11: Other | AA11: =AA49+AA87 -> 0 | AB11: =AB49+AB87 -> 0 | AC11: =AC49+AC87 -> 0 | AD11: =AD49+AD87 -> 0
B12: Contract Labor | C12: =C50+C88 -> 1899752.6 | D12: =D50+D88 -> 1899752.6 | E12: =E50+E88 -> 1899752.6 | F12: =F50+F88 -> 1899752.6 | H12: Contract Labor | I12: =I50+I88 -> 1359752.6 | J12: =J50+J88 -> 1359752.6 | K12: =K50+K88 -> 1359752.6 | L12: =L50+L88 -> 1359752.6 | N12: Contract Labor | O12: =O50+O88 -> 0 | P12: =P50+P88 -> 0 | Q12: =Q50+Q88 -> 0 | R12: =R50+R88 -> 0 | T12: Contract Labor | U12: =U50+U88 -> 540000 | V12: =V50+V88 -> 540000 | W12: =W50+W88 -> 540000 | X12: =X50+X88 -> 540000 | Z12: Contract Labor | AA12: =AA50+AA88 -> 0 | AB12: =AB50+AB88 -> 0 | AC12: =AC50+AC88 -> 0 | AD12: =AD50+AD88 -> 0
B13: LTIP Compensation | C13: =C51+C89 -> 3602361.1 | D13: =D51+D89 -> 3903500.8 | E13: =E51+E89 -> 3903500.8 | F13: =F51+F89 -> 3903500.8 | H13: LTIP Compensation | I13: =I51+I89 -> 1203507.6 | J13: =J51+J89 -> 1373047.6 | K13: =K51+K89 -> 1373047.6 | L13: =L51+L89 -> 1373047.6 | N13: LTIP Compensation | O13: =O51+O89 -> 339126.66 | P13: =P51+P89 -> 456329.4 | Q13: =Q51+Q89 -> 456329.4 | R13: =R51+R89 -> 456329.4 | T13: LTIP Compensation | U13: =U51+U89 -> 351851.21 | V13: =V51+V89 -> 364692.77 | W13: =W51+W89 -> 364692.77 | X13: =X51+X89 -> 364692.77 | Z13: LTIP Compensation | AA13: =AA51+AA89 -> 1707875.6 | AB13: =AB51+AB89 -> 1709431.1 | AC13: =AC51+AC89 -> 1709431.1 | AD13: =AD51+AD89 -> 1709431.1
B14: Total Payroll | C14: =SUM(C5:C13) -> 48395278 | D14: =SUM(D5:D13) -> 50770674 | E14: =E52+E90 -> 50770674 | F14: =F52+F90 -> 50770674 | H14: Total Payroll | I14: =SUM(I5:I13) -> 29499176 | J14: =SUM(J5:J13) -> 30783520 | K14: =K52+K90 -> 30783520 | L14: =L52+L90 -> 30783520 | N14: Total Payroll | O14: =SUM(O5:O13) -> 4892825.2 | P14: =SUM(P5:P13) -> 5203020.1 | Q14: =Q52+Q90 -> 5203020.1 | R14: =R52+R90 -> 5203020.1 | T14: Total Payroll | U14: =SUM(U5:U13) -> 10263481 | V14: =SUM(V5:V13) -> 11040932 | W14: =W52+W90 -> 11040932 | X14: =X52+X90 -> 11040932 | Z14: Total Payroll | AA14: =SUM(AA5:AA13) -> 3739795.7 | AB14: =SUM(AB5:AB13) -> 3743201.8 | AC14: =AC52+AC90 -> 3743201.8 | AD14: =AD52+AD90 -> 3743201.8
B16: Professional Fees | C16: =C54+C92 -> 7181209.5 | D16: =D54+D92 -> 7181209.5 | E16: =E54+E92 -> 7181209.5 | F16: =F54+F92 -> 7181209.5 | H16: Professional Fees | I16: =I54+I92 -> 1689705.4 | J16: =J54+J92 -> 1689705.4 | K16: =K54+K92 -> 1689705.4 | L16: =L54+L92 -> 1689705.4 | N16: Professional Fees | O16: =O54+O92 -> 769992 | P16: =P54+P92 -> 769992 | Q16: =Q54+Q92 -> 769992 | R16: =R54+R92 -> 769992 | T16: Professional Fees | U16: =U54+U92 -> 4361510.7 | V16: =V54+V92 -> 4361510.7 | W16: =W54+W92 -> 4361510.7 | X16: =X54+X92 -> 4361510.7 | Z16: Professional Fees | AA16: =AA54+AA92 -> 360001.33 | AB16: =AB54+AB92 -> 360001.33 | AC16: =AC54+AC92 -> 360001.33 | AD16: =AD54+AD92 -> 360001.33
B17: Occupancy | C17: =C55+C93 -> 100003.17 | D17: =D55+D93 -> 100003.17 | E17: =E55+E93 -> 100003.17 | F17: =F55+F93 -> 100003.17 | H17: Occupancy | I17: =I55+I93 -> 100001.28 | J17: =J55+J93 -> 100001.28 | K17: =K55+K93 -> 100001.28 | L17: =L55+L93 -> 100001.28 | N17: Occupancy | O17: =O55+O93 -> 0 | P17: =P55+P93 -> 0 | Q17: =Q55+Q93 -> 0 | R17: =R55+R93 -> 0 | T17: Occupancy | U17: =U55+U93 -> 1.89 | V17: =V55+V93 -> 1.89 | W17: =W55+W93 -> 1.89 | X17: =X55+X93 -> 1.89 | Z17: Occupancy | AA17: =AA55+AA93 -> 0 | AB17: =AB55+AB93 -> 0 | AC17: =AC55+AC93 -> 0 | AD17: =AD55+AD93 -> 0
B18: Office Expenses | C18: =C56+C94 -> 6598.26 | D18: =D56+D94 -> 6598.26 | E18: =E56+E94 -> 6598.26 | F18: =F56+F94 -> 6598.26 | H18: Office Expenses | I18: =I56+I94 -> 1596.31 | J18: =J56+J94 -> 1596.31 | K18: =K56+K94 -> 1596.31 | L18: =L56+L94 -> 1596.31 | N18: Office Expenses | O18: =O56+O94 -> -2.04 | P18: =P56+P94 -> -2.04 | Q18: =Q56+Q94 -> -2.04 | R18: =R56+R94 -> -2.04 | T18: Office Expenses | U18: =U56+U94 -> 5007.59 | V18: =V56+V94 -> 5007.59 | W18: =W56+W94 -> 5007.59 | X18: =X56+X94 -> 5007.59 | Z18: Office Expenses | AA18: =AA56+AA94 -> -3.6 | AB18: =AB56+AB94 -> -3.6 | AC18: =AC56+AC94 -> -3.6 | AD18: =AD56+AD94 -> -3.6
B19: IT Costs | C19: =C57+C95 -> 621855.21 | D19: =D57+D95 -> 621855.21 | E19: =E57+E95 -> 621855.21 | F19: =F57+F95 -> 621855.21 | H19: IT Costs | I19: =I57+I95 -> 575609.31 | J19: =J57+J95 -> 575609.31 | K19: =K57+K95 -> 575609.31 | L19: =L57+L95 -> 575609.31 | N19: IT Costs | O19: =O57+O95 -> 2.95 | P19: =P57+P95 -> 2.95 | Q19: =Q57+Q95 -> 2.95 | R19: =R57+R95 -> 2.95 | T19: IT Costs | U19: =U57+U95 -> 46239.61 | V19: =V57+V95 -> 46239.61 | W19: =W57+W95 -> 46239.61 | X19: =X57+X95 -> 46239.61 | Z19: IT Costs | AA19: =AA57+AA95 -> 3.34 | AB19: =AB57+AB95 -> 3.34 | AC19: =AC57+AC95 -> 3.34 | AD19: =AD57+AD95 -> 3.34
B20: Marketing and Presentation | C20: =C58+C96 -> 747958 | D20: =D58+D96 -> 747958 | E20: =E58+E96 -> 747958 | F20: =F58+F96 -> 747958 | H20: Marketing and Presentation | I20: =I58+I96 -> 0 | J20: =J58+J96 -> 0 | K20: =K58+K96 -> 0 | L20: =L58+L96 -> 0 | N20: Marketing and Presentation | O20: =O58+O96 -> 0 | P20: =P58+P96 -> 0 | Q20: =Q58+Q96 -> 0 | R20: =R58+R96 -> 0 | T20: Marketing and Presentation | U20: =U58+U96 -> 747958 | V20: =V58+V96 -> 747958 | W20: =W58+W96 -> 747958 | X20: =X58+X96 -> 747958 | Z20: Marketing and Presentation | AA20: =AA58+AA96 -> 0 | AB20: =AB58+AB96 -> 0 | AC20: =AC58+AC96 -> 0 | AD20: =AD58+AD96 -> 0
B21: Travel and Entertainment | C21: =C59+C97 -> 3003935.5 | D21: =D59+D97 -> 3003935.5 | E21: =E59+E97 -> 3003935.5 | F21: =F59+F97 -> 3003935.5 | H21: Travel and Entertainment | I21: =I59+I97 -> 1892769.3 | J21: =J59+J97 -> 1892769.3 | K21: =K59+K97 -> 1892769.3 | L21: =L59+L97 -> 1892769.3 | N21: Travel and Entertainment | O21: =O59+O97 -> 203998.22 | P21: =P59+P97 -> 203998.22 | Q21: =Q59+Q97 -> 203998.22 | R21: =R59+R97 -> 203998.22 | T21: Travel and Entertainment | U21: =U59+U97 -> 594403.83 | V21: =V59+V97 -> 594403.83 | W21: =W59+W97 -> 594403.83 | X21: =X59+X97 -> 594403.83 | Z21: Travel and Entertainment | AA21: =AA59+AA97 -> 312764.14 | AB21: =AB59+AB97 -> 312764.14 | AC21: =AC59+AC97 -> 312764.14 | AD21: =AD59+AD97 -> 312764.14
B22: Employee events | C22: =C60+C98 -> 232642.23 | D22: =D60+D98 -> 232642.23 | E22: =E60+E98 -> 232642.23 | F22: =F60+F98 -> 232642.23 | H22: Employee events | I22: =I60+I98 -> 167102.54 | J22: =J60+J98 -> 167102.54 | K22: =K60+K98 -> 167102.54 | L22: =L60+L98 -> 167102.54 | N22: Employee events | O22: =O60+O98 -> 23996 | P22: =P60+P98 -> 23996 | Q22: =Q60+Q98 -> 23996 | R22: =R60+R98 -> 23996 | T22: Employee events | U22: =U60+U98 -> 11544 | V22: =V60+V98 -> 11544 | W22: =W60+W98 -> 11544 | X22: =X60+X98 -> 11544 | Z22: Employee events | AA22: =AA60+AA98 -> 29999.69 | AB22: =AB60+AB98 -> 29999.69 | AC22: =AC60+AC98 -> 29999.69 | AD22: =AD60+AD98 -> 29999.69
B23: Insurance Non Property | C23: =C61+C99 -> 0 | D23: =D61+D99 -> 0 | E23: =E61+E99 -> 0 | F23: =F61+F99 -> 0 | H23: Insurance Non Property | I23: =I61+I99 -> 0 | J23: =J61+J99 -> 0 | K23: =K61+K99 -> 0 | L23: =L61+L99 -> 0 | N23: Insurance Non Property | O23: =O61+O99 -> 0 | P23: =P61+P99 -> 0 | Q23: =Q61+Q99 -> 0 | R23: =R61+R99 -> 0 | T23: Insurance Non Property | U23: =U61+U99 -> 0 | V23: =V61+V99 -> 0 | W23: =W61+W99 -> 0 | X23: =X61+X99 -> 0 | Z23: Insurance Non Property | AA23: =AA61+AA99 -> 0 | AB23: =AB61+AB99 -> 0 | AC23: =AC61+AC99 -> 0 | AD23: =AD61+AD99 -> 0
B24: Licenses | C24: =C62+C100 -> 0 | D24: =D62+D100 -> 0 | E24: =E62+E100 -> 0 | F24: =F62+F100 -> 0 | H24: Licenses | I24: =I62+I100 -> 0 | J24: =J62+J100 -> 0 | K24: =K62+K100 -> 0 | L24: =L62+L100 -> 0 | N24: Licenses | O24: =O62+O100 -> 0 | P24: =P62+P100 -> 0 | Q24: =Q62+Q100 -> 0 | R24: =R62+R100 -> 0 | T24: Licenses | U24: =U62+U100 -> 0 | V24: =V62+V100 -> 0 | W24: =W62+W100 -> 0 | X24: =X62+X100 -> 0 | Z24: Licenses | AA24: =AA62+AA100 -> 0 | AB24: =AB62+AB100 -> 0 | AC24: =AC62+AC100 -> 0 | AD24: =AD62+AD100 -> 0
B25: Recruiting and Relocation | C25: =C63+C101 -> 83995.69 | D25: =D63+D101 -> 83995.69 | E25: =E63+E101 -> 83995.69 | F25: =F63+F101 -> 83995.69 | H25: Recruiting and Relocation | I25: =I63+I101 -> 63989.86 | J25: =J63+J101 -> 63989.86 | K25: =K63+K101 -> 63989.86 | L25: =L63+L101 -> 63989.86 | N25: Recruiting and Relocation | O25: =O63+O101 -> 0 | P25: =P63+P101 -> 0 | Q25: =Q63+Q101 -> 0 | R25: =R63+R101 -> 0 | T25: Recruiting and Relocation | U25: =U63+U101 -> 20005.83 | V25: =V63+V101 -> 20005.83 | W25: =W63+W101 -> 20005.83 | X25: =X63+X101 -> 20005.83 | Z25: Recruiting and Relocation | AA25: =AA63+AA101 -> 0 | AB25: =AB63+AB101 -> 0 | AC25: =AC63+AC101 -> 0 | AD25: =AD63+AD101 -> 0
B26: Seminars and Training | C26: =C64+C102 -> 251825.74 | D26: =D64+D102 -> 251825.74 | E26: =E64+E102 -> 251825.74 | F26: =F64+F102 -> 251825.74 | H26: Seminars and Training | I26: =I64+I102 -> 164413.16 | J26: =J64+J102 -> 164413.16 | K26: =K64+K102 -> 164413.16 | L26: =L64+L102 -> 164413.16 | N26: Seminars and Training | O26: =O64+O102 -> 48003.38 | P26: =P64+P102 -> 48003.38 | Q26: =Q64+Q102 -> 48003.38 | R26: =R64+R102 -> 48003.38 | T26: Seminars and Training | U26: =U64+U102 -> 34403.22 | V26: =V64+V102 -> 34403.22 | W26: =W64+W102 -> 34403.22 | X26: =X64+X102 -> 34403.22 | Z26: Seminars and Training | AA26: =AA64+AA102 -> 5005.98 | AB26: =AB64+AB102 -> 5005.98 | AC26: =AC64+AC102 -> 5005.98 | AD26: =AD64+AD102 -> 5005.98
B27: Shareholder Relations | C27: =C65+C103 -> 0 | D27: =D65+D103 -> 0 | E27: =E65+E103 -> 0 | F27: =F65+F103 -> 0 | H27: Shareholder Relations | I27: =I65+I103 -> 0 | J27: =J65+J103 -> 0 | K27: =K65+K103 -> 0 | L27: =L65+L103 -> 0 | N27: Shareholder Relations | O27: =O65+O103 -> 0 | P27: =P65+P103 -> 0 | Q27: =Q65+Q103 -> 0 | R27: =R65+R103 -> 0 | T27: Shareholder Relations | U27: =U65+U103 -> 0 | V27: =V65+V103 -> 0 | W27: =W65+W103 -> 0 | X27: =X65+X103 -> 0 | Z27: Shareholder Relations | AA27: =AA65+AA103 -> 0 | AB27: =AB65+AB103 -> 0 | AC27: =AC65+AC103 -> 0 | AD27: =AD65+AD103 -> 0
... B36: Allocated IT & Office Contra | C36: =C74+C112 -> 0 | D36: =D74+D112 -> 0 | E36: =E74+E112 -> 0 | F36: =F74+F112 -> 0 | H36: Allocated IT & Office Contra | I36: =I74+I112 -> 0 | J36: =J74+J112 -> 0 | K36: =K74+K112 -> 0 | L36: =L74+L112 -> 0 | N36: Allocated IT & Office Contra | O36: =O74+O112 -> 0 | P36: =P74+P112 -> 0 | Q36: =Q74+Q112 -> 0 | R36: =R74+R112 -> 0 | T36: Allocated IT & Office Contra | U36: =U74+U112 -> 0 | V36: =V74+V112 -> 0 | W36: =W74+W112 -> 0 | X36: =X74+X112 -> 0 | Z36: Allocated IT & Office Contra | AA36: =AA74+AA112 -> 0 | AB36: =AB74+AB112 -> 0 | AC36: =AC74+AC112 -> 0 | AD36: =AD74+AD112 -> 0
B37: Total Non-Payroll | C37: =SUM(C16:C36) -> 13032305 | D37: =SUM(D16:D36) -> 13032305 | E37: =E75+E113 -> 13032305 | F37: =F75+F113 -> 13032305 | H37: Total Non-Payroll | I37: =SUM(I16:I36) -> 5266629.5 | J37: =SUM(J16:J36) -> 5266629.5 | K37: =K75+K113 -> 5266629.5 | L37: =L75+L113 -> 5266629.5 | N37: Total Non-Payroll | O37: =SUM(O16:O36) -> 1050998.5 | P37: =SUM(P16:P36) -> 1050998.5 | Q37: =Q75+Q113 -> 1050998.5 | R37: =R75+R113 -> 1050998.5 | T37: Total Non-Payroll | U37: =SUM(U16:U36) -> 5961905.7 | V37: =SUM(V16:V36) -> 5961905.7 | W37: =W75+W113 -> 5961905.7 | X37: =X75+X113 -> 5961905.7 | Z37: Total Non-Payroll | AA37: =SUM(AA16:AA36) -> 752770.88 | AB37: =SUM(AB16:AB36) -> 752770.88 | AC37: =AC75+AC113 -> 752770.88 | AD37: =AD75+AD113 -> 752770.88
B39: Total | C39: =C14+C37 -> 61427583 | D39: =D14+D37 -> 63802979 | E39: =E77+E115 -> 63802979 | F39: =F77+F115 -> 63802979 | H39: Total | I39: =I14+I37 -> 34765805 | J39: =J14+J37 -> 36050150 | K39: =K77+K115 -> 36050150 | L39: =L77+L115 -> 36050150 | N39: Total | O39: =O14+O37 -> 5943823.7 | P39: =P14+P37 -> 6254018.6 | Q39: =Q77+Q115 -> 6254018.6 | R39: =R77+R115 -> 6254018.6 | T39: Total | U39: =U14+U37 -> 16225387 | V39: =V14+V37 -> 17002838 | W39: =W77+W115 -> 17002838 | X39: =X77+X115 -> 17002838 | Z39: Total | AA39: =AA14+AA37 -> 4492566.6 | AB39: =AB14+AB37 -> 4495972.6 | AC39: =AC77+AC115 -> 4495972.6 | AD39: =AD77+AD115 -> 4495972.6
B41: Baseline | H41: Baseline | N41: Baseline | T41: Baseline | Z41: Baseline
C42: 2026 | D42: 2027 | E42: 2028 | F42: 2029 | I42: 2026 | J42: 2027 | K42: 2028 | L42: 2029 | O42: 2026 | P42: 2027 | Q42: 2028 | R42: 2029 | U42: 2026 | V42: 2027 | W42: 2028 | X42: 2029 | AA42: 2026 | AB42: 2027 | AC42: 2028 | AD42: 2029
B43: Compensation | C43: =SUMIFS('Base - Payroll'!$E:$E,'Base - Payroll'!$A:$A,Summary!$B43) -> 27021147 | D43: =SUMIFS('Base - Payroll'!$G:$G,'Base - Payroll'!$A:$A,Summary!$B43) -> 28096812 | E43: =SUMIFS('Base - Payroll'!$H:$H,'Base - Payroll'!$A:$A,Summary!$B43) -> 28096812 | F43: =SUMIFS('Base - Payroll'!$I:$I,'Base - Payroll'!$A:$A,Summary!$B43) -> 28096812 | H43: Compensation | I43: =SUMIFS('Base - Payroll'!$E:$E,'Base - Payroll'!$A:$A,$H43,'Base - Payroll'!$B:$B," "&$H$1) -> 17132061 | J43: =SUMIFS('Base - Payroll'!$G:$G,'Base - Payroll'!$A:$A,$H43,'Base - Payroll'!$B:$B," "&$H$1) -> 17864963 | K43: =SUMIFS('Base - Payroll'!$H:$H,'Base - Payroll'!$A:$A,$H43,'Base - Payroll'!$B:$B," "&$H$1) -> 17864963 | L43: =SUMIFS('Base - Payroll'!$I:$I,'Base - Payroll'!$A:$A,$H43,'Base - Payroll'!$B:$B," "&$H$1) -> 17864963 | N43: Compensation | O43: =SUMIFS('Base - Payroll'!$E:$E,'Base - Payroll'!$A:$A,$N43,'Base - Payroll'!$B:$B," "&$N$1) -> 2947996.3 | P43: =SUMIFS('Base - Payroll'!$G:$G,'Base - Payroll'!$A:$A,$N43,'Base - Payroll'!$B:$B," "&$N$1) -> 3072936.5 | Q43: =SUMIFS('Base - Payroll'!$H:$H,'Base - Payroll'!$A:$A,$N43,'Base - Payroll'!$B:$B," "&$N$1) -> 3072936.5 | R43: =SUMIFS('Base - Payroll'!$I:$I,'Base - Payroll'!$A:$A,$N43,'Base - Payroll'!$B:$B," "&$N$1) -> 3072936.5 | T43: Compensation | U43: =SUMIFS('Base - Payroll'!$E:$E,'Base - Payroll'!$A:$A,$T43,'Base - Payroll'!$B:$B," "&$T$1) -> 5943317.7 | V43: =SUMIFS('Base - Payroll'!$G:$G,'Base - Payroll'!$A:$A,$T43,'Base - Payroll'!$B:$B," "&$T$1) -> 6160231.7 | W43: =SUMIFS('Base - Payroll'!$H:$H,'Base - Payroll'!$A:$A,$T43,'Base - Payroll'!$B:$B," "&$T$1) -> 6160231.7 | X43: =SUMIFS('Base - Payroll'!$I:$I,'Base - Payroll'!$A:$A,$T43,'Base - Payroll'!$B:$B," "&$T$1) -> 6160231.7 | Z43: Compensation | AA43: =SUMIFS('Base - Payroll'!$E:$E,'Base - Payroll'!$A:$A,$Z43,'Base - Payroll'!$B:$B," "&$Z$1) -> 997771.84 | AB43: =SUMIFS('Base - Payroll'!$G:$G,'Base - Payroll'!$A:$A,$Z43,'Base - Payroll'!$B:$B," "&$Z$1) -> 998680.58 | AC43: =SUMIFS('Base - Payroll'!$H:$H,'Base - Payroll'!$A:$A,$Z43,'Base - Payroll'!$B:$B," "&$Z$1) -> 998680.58 | AD43: =SUMIFS('Base - Payroll'!$I:$I,'Base - Payroll'!$A:$A,$Z43,'Base - Payroll'!$B:$B," "&$Z$1) -> 998680.58
B44: Bonus | C44: =SUMIFS('Base - Payroll'!$E:$E,'Base - Payroll'!$A:$A,Summary!$B44) -> 7777198.6 | D44: =SUMIFS('Base - Payroll'!$G:$G,'Base - Payroll'!$A:$A,Summary!$B44) -> 8060204.2 | E44: =SUMIFS('Base - Payroll'!$H:$H,'Base - Payroll'!$A:$A,Summary!$B44) -> 8060204.2 | F44: =SUMIFS('Base - Payroll'!$I:$I,'Base - Payroll'!$A:$A,Summary!$B44) -> 8060204.2 | H44: Bonus | I44: =SUMIFS('Base - Payroll'!$E:$E,'Base - Payroll'!$A:$A,$H44,'Base - Payroll'!$B:$B," "&$H$1) -> 4275135.5 | J44: =SUMIFS('Base - Payroll'!$G:$G,'Base - Payroll'!$A:$A,$H44,'Base - Payroll'!$B:$B," "&$H$1) -> 4458023.8 | K44: =SUMIFS('Base - Payroll'!$H:$H,'Base - Payroll'!$A:$A,$H44,'Base - Payroll'!$B:$B," "&$H$1) -> 4458023.8 | L44: =SUMIFS('Base - Payroll'!$I:$I,'Base - Payroll'!$A:$A,$H44,'Base - Payroll'!$B:$B," "&$H$1) -> 4458023.8 | N44: Bonus | O44: =SUMIFS('Base - Payroll'!$E:$E,'Base - Payroll'!$A:$A,$N44,'Base - Payroll'!$B:$B," "&$N$1) -> 843955.68 | P44: =SUMIFS('Base - Payroll'!$G:$G,'Base - Payroll'!$A:$A,$N44,'Base - Payroll'!$B:$B," "&$N$1) -> 879723.71 | Q44: =SUMIFS('Base - Payroll'!$H:$H,'Base - Payroll'!$A:$A,$N44,'Base - Payroll'!$B:$B," "&$N$1) -> 879723.71 | R44: =SUMIFS('Base - Payroll'!$I:$I,'Base - Payroll'!$A:$A,$N44,'Base - Payroll'!$B:$B," "&$N$1) -> 879723.71 | T44: Bonus | U44: =SUMIFS('Base - Payroll'!$E:$E,'Base - Payroll'!$A:$A,$T44,'Base - Payroll'!$B:$B," "&$T$1) -> 1740227.4 | V44: =SUMIFS('Base - Payroll'!$G:$G,'Base - Payroll'!$A:$A,$T44,'Base - Payroll'!$B:$B," "&$T$1) -> 1803740.7 | W44: =SUMIFS('Base - Payroll'!$H:$H,'Base - Payroll'!$A:$A,$T44,'Base - Payroll'!$B:$B," "&$T$1) -> 1803740.7 | X44: =SUMIFS('Base - Payroll'!$I:$I,'Base - Payroll'!$A:$A,$T44,'Base - Payroll'!$B:$B," "&$T$1) -> 1803740.7 | Z44: Bonus | AA44: =SUMIFS('Base - Payroll'!$E:$E,'Base - Payroll'!$A:$A,$Z44,'Base - Payroll'!$B:$B," "&$Z$1) -> 917880.07 | AB44: =SUMIFS('Base - Payroll'!$G:$G,'Base - Payroll'!$A:$A,$Z44,'Base - Payroll'!$B:$B," "&$Z$1) -> 918716.04 | AC44: =SUMIFS('Base - Payroll'!$H:$H,'Base - Payroll'!$A:$A,$Z44,'Base - Payroll'!$B:$B," "&$Z$1) -> 918716.04 | AD44: =SUMIFS('Base - Payroll'!$I:$I,'Base - Payroll'!$A:$A,$Z44,'Base - Payroll'!$B:$B," "&$Z$1) -> 918716.04
B45: Essentials Bonus | C45: =SUMIFS('Base - Non-Payroll'!$E:$E,'Base - Non-Payroll'!$A:$A,Summary!$B45) -> 1285296.4 | D45: =SUMIFS('Base - Non-Payroll'!$H:$H,'Base - Non-Payroll'!$A:$A,Summary!$B45) -> 1285296.4 | E45: =SUMIFS('Base - Non-Payroll'!$J:$J,'Base - Non-Payroll'!$A:$A,Summary!$B45) -> 1285296.4 | F45: =SUMIFS('Base - Non-Payroll'!$L:$L,'Base - Non-Payroll'!$A:$A,Summary!$B45) -> 1285296.4 | H45: Essentials Bonus | I45: =SUMIFS('Base - Non-Payroll'!$E:$E,'Base - Non-Payroll'!$A:$A,$H45,'Base - Non-Payroll'!$B:$B," "&$H$1) -> 876620.84 | J45: =SUMIFS('Base - Non-Payroll'!$H:$H,'Base - Non-Payroll'!$A:$A,$H45,'Base - Non-Payroll'!$B:$B," "&$H$1) -> 876620.84 | K45: =SUMIFS('Base - Non-Payroll'!$J:$J,'Base - Non-Payroll'!$A:$A,$H45,'Base - Non-Payroll'!$B:$B," "&$H$1) -> 876620.84 | L45: =SUMIFS('Base - Non-Payroll'!$L:$L,'Base - Non-Payroll'!$A:$A,$H45,'Base - Non-Payroll'!$B:$B," "&$H$1) -> 876620.84 | N45: Essentials Bonus | O45: =SUMIFS('Base - Non-Payroll'!$E:$E,'Base - Non-Payroll'!$A:$A,$N45,'Base - Non-Payroll'!$B:$B," "&$N$1) -> 0 | P45: =SUMIFS('Base - Non-Payroll'!$H:$H,'Base - Non-Payroll'!$A:$A,$N45,'Base - Non-Payroll'!$B:$B," "&$N$1) -> 0 | Q45: =SUMIFS('Base - Non-Payroll'!$J:$J,'Base - Non-Payroll'!$A:$A,$N45,'Base - Non-Payroll'!$B:$B," "&$N$1) -> 0 | R45: =SUMIFS('Base - Non-Payroll'!$L:$L,'Base - Non-Payroll'!$A:$A,$N45,'Base - Non-Payroll'!$B:$B," "&$N$1) -> 0 | T45: Essentials Bonus | U45: =SUMIFS('Base - Non-Payroll'!$E:$E,'Base - Non-Payroll'!$A:$A,$T45,'Base - Non-Payroll'!$B:$B," "&$T$1) -> 408675.58 | V45: =SUMIFS('Base - Non-Payroll'!$H:$H,'Base - Non-Payroll'!$A:$A,$T45,'Base - Non-Payroll'!$B:$B," "&$T$1) -> 408675.58 | W45: =SUMIFS('Base - Non-Payroll'!$J:$J,'Base - Non-Payroll'!$A:$A,$T45,'Base - Non-Payroll'!$B:$B," "&$T$1) -> 408675.58 | X45: =SUMIFS('Base - Non-Payroll'!$L:$L,'Base - Non-Payroll'!$A:$A,$T45,'Base - Non-Payroll'!$B:$B," "&$T$1) -> 408675.58 | Z45: Essentials Bonus | AA45: =SUMIFS('Base - Non-Payroll'!$E:$E,'Base - Non-Payroll'!$A:$A,$Z45,'Base - Non-Payroll'!$B:$B," "&$Z$1) -> 0 | AB45: =SUMIFS('Base - Non-Payroll'!$H:$H,'Base - Non-Payroll'!$A:$A,$Z45,'Base - Non-Payroll'!$B:$B," "&$Z$1) -> 0 | AC45: =SUMIFS('Base - Non-Payroll'!$J:$J,'Base - Non-Payroll'!$A:$A,$Z45,'Base - Non-Payroll'!$B:$B," "&$Z$1) -> 0 | AD45: =SUMIFS('Base - Non-Payroll'!$L:$L,'Base - Non-Payroll'!$A:$A,$Z45,'Base - Non-Payroll'!$B:$B," "&$Z$1) -> 0
B46: Payroll Taxes | C46: =SUMIFS('Base - Payroll'!$E:$E,'Base - Payroll'!$A:$A,Summary!$B46) -> 3096763 | D46: =SUMIFS('Base - Payroll'!$G:$G,'Base - Payroll'!$A:$A,Summary!$B46) -> 3222133.9 | E46: =SUMIFS('Base - Payroll'!$H:$H,'Base - Payroll'!$A:$A,Summary!$B46) -> 3222133.9 | F46: =SUMIFS('Base - Payroll'!$I:$I,'Base - Payroll'!$A:$A,Summary!$B46) -> 3222133.9 | H46: Payroll Taxes | I46: =SUMIFS('Base - Payroll'!$E:$E,'Base - Payroll'!$A:$A,$H46,'Base - Payroll'!$B:$B," "&$H$1) -> 1954237.2 | J46: =SUMIFS('Base - Payroll'!$G:$G,'Base - Payroll'!$A:$A,$H46,'Base - Payroll'!$B:$B," "&$H$1) -> 2037838.5 | K46: =SUMIFS('Base - Payroll'!$H:$H,'Base - Payroll'!$A:$A,$H46,'Base - Payroll'!$B:$B," "&$H$1) -> 2037838.5 | L46: =SUMIFS('Base - Payroll'!$I:$I,'Base - Payroll'!$A:$A,$H46,'Base - Payroll'!$B:$B," "&$H$1) -> 2037838.5 | N46: Payroll Taxes | O46: =SUMIFS('Base - Payroll'!$E:$E,'Base - Payroll'!$A:$A,$N46,'Base - Payroll'!$B:$B," "&$N$1) -> 321560.41 | P46: =SUMIFS('Base - Payroll'!$G:$G,'Base - Payroll'!$A:$A,$N46,'Base - Payroll'!$B:$B," "&$N$1) -> 335188.59 | Q46: =SUMIFS('Base - Payroll'!$H:$H,'Base - Payroll'!$A:$A,$N46,'Base - Payroll'!$B:$B," "&$N$1) -> 335188.59 | R46: =SUMIFS('Base - Payroll'!$I:$I,'Base - Payroll'!$A:$A,$N46,'Base - Payroll'!$B:$B," "&$N$1) -> 335188.59 | T46: Payroll Taxes | U46: =SUMIFS('Base - Payroll'!$E:$E,'Base - Payroll'!$A:$A,$T46,'Base - Payroll'!$B:$B," "&$T$1) -> 769778.04 | V46: =SUMIFS('Base - Payroll'!$G:$G,'Base - Payroll'!$A:$A,$T46,'Base - Payroll'!$B:$B," "&$T$1) -> 797872.74 | W46: =SUMIFS('Base - Payroll'!$H:$H,'Base - Payroll'!$A:$A,$T46,'Base - Payroll'!$B:$B," "&$T$1) -> 797872.74 | X46: =SUMIFS('Base - Payroll'!$I:$I,'Base - Payroll'!$A:$A,$T46,'Base - Payroll'!$B:$B," "&$T$1) -> 797872.74 | Z46: Payroll Taxes | AA46: =SUMIFS('Base - Payroll'!$E:$E,'Base - Payroll'!$A:$A,$Z46,'Base - Payroll'!$B:$B," "&$Z$1) -> 51187.428 | AB46: =SUMIFS('Base - Payroll'!$G:$G,'Base - Payroll'!$A:$A,$Z46,'Base - Payroll'!$B:$B," "&$Z$1) -> 51234.048 | AC46: =SUMIFS('Base - Payroll'!$H:$H,'Base - Payroll'!$A:$A,$Z46,'Base - Payroll'!$B:$B," "&$Z$1) -> 51234.048 | AD46: =SUMIFS('Base - Payroll'!$I:$I,'Base - Payroll'!$A:$A,$Z46,'Base - Payroll'!$B:$B," "&$Z$1) -> 51234.048
B47: Benefits | C47: =SUMIFS('Base - Payroll'!$E:$E,'Base - Payroll'!$A:$A,Summary!$B47) -> 3960803.5 | D47: =SUMIFS('Base - Payroll'!$G:$G,'Base - Payroll'!$A:$A,Summary!$B47) -> 4121887.8 | E47: =SUMIFS('Base - Payroll'!$H:$H,'Base - Payroll'!$A:$A,Summary!$B47) -> 4121887.8 | F47: =SUMIFS('Base - Payroll'!$I:$I,'Base - Payroll'!$A:$A,Summary!$B47) -> 4121887.8 | H47: Benefits | I47: =SUMIFS('Base - Payroll'!$E:$E,'Base - Payroll'!$A:$A,$H47,'Base - Payroll'!$B:$B," "&$H$1) -> 2599951 | J47: =SUMIFS('Base - Payroll'!$G:$G,'Base - Payroll'!$A:$A,$H47,'Base - Payroll'!$B:$B," "&$H$1) -> 2711175.7 | K47: =SUMIFS('Base - Payroll'!$H:$H,'Base - Payroll'!$A:$A,$H47,'Base - Payroll'!$B:$B," "&$H$1) -> 2711175.7 | L47: =SUMIFS('Base - Payroll'!$I:$I,'Base - Payroll'!$A:$A,$H47,'Base - Payroll'!$B:$B," "&$H$1) -> 2711175.7 | N47: Benefits | O47: =SUMIFS('Base - Payroll'!$E:$E,'Base - Payroll'!$A:$A,$N47,'Base - Payroll'!$B:$B," "&$N$1) -> 426285.43 | P47: =SUMIFS('Base - Payroll'!$G:$G,'Base - Payroll'!$A:$A,$N47,'Base - Payroll'!$B:$B," "&$N$1) -> 444352.01 | Q47: =SUMIFS('Base - Payroll'!$H:$H,'Base - Payroll'!$A:$A,$N47,'Base - Payroll'!$B:$B," "&$N$1) -> 444352.01 | R47: =SUMIFS('Base - Payroll'!$I:$I,'Base - Payroll'!$A:$A,$N47,'Base - Payroll'!$B:$B," "&$N$1) -> 444352.01 | T47: Benefits | U47: =SUMIFS('Base - Payroll'!$E:$E,'Base - Payroll'!$A:$A,$T47,'Base - Payroll'!$B:$B," "&$T$1) -> 869486.31 | V47: =SUMIFS('Base - Payroll'!$G:$G,'Base - Payroll'!$A:$A,$T47,'Base - Payroll'!$B:$B," "&$T$1) -> 901220.07 | W47: =SUMIFS('Base - Payroll'!$H:$H,'Base - Payroll'!$A:$A,$T47,'Base - Payroll'!$B:$B," "&$T$1) -> 901220.07 | X47: =SUMIFS('Base - Payroll'!$I:$I,'Base - Payroll'!$A:$A,$T47,'Base - Payroll'!$B:$B," "&$T$1) -> 901220.07 | Z47: Benefits | AA47: =SUMIFS('Base - Payroll'!$E:$E,'Base - Payroll'!$A:$A,$Z47,'Base - Payroll'!$B:$B," "&$Z$1) -> 65080.753 | AB47: =SUMIFS('Base - Payroll'!$G:$G,'Base - Payroll'!$A:$A,$Z47,'Base - Payroll'!$B:$B," "&$Z$1) -> 65140.026 | AC47: =SUMIFS('Base - Payroll'!$H:$H,'Base - Payroll'!$A:$A,$Z47,'Base - Payroll'!$B:$B," "&$Z$1) -> 65140.026 | AD47: =SUMIFS('Base - Payroll'!$I:$I,'Base - Payroll'!$A:$A,$Z47,'Base - Payroll'!$B:$B," "&$Z$1) -> 65140.026
B48: Vacation | C48: =SUMIFS('Base - Payroll'!$E:$E,'Base - Payroll'!$A:$A,Summary!$B48) -> 173675.52 | D48: =SUMIFS('Base - Payroll'!$G:$G,'Base - Payroll'!$A:$A,Summary!$B48) -> 180708.81 | E48: =SUMIFS('Base - Payroll'!$H:$H,'Base - Payroll'!$A:$A,Summary!$B48) -> 180708.81 | F48: =SUMIFS('Base - Payroll'!$I:$I,'Base - Payroll'!$A:$A,Summary!$B48) -> 180708.81 | H48: Vacation | I48: =SUMIFS('Base - Payroll'!$E:$E,'Base - Payroll'!$A:$A,$H48,'Base - Payroll'!$B:$B," "&$H$1) -> 97547.456 | J48: =SUMIFS('Base - Payroll'!$G:$G,'Base - Payroll'!$A:$A,$H48,'Base - Payroll'!$B:$B," "&$H$1) -> 101720.49 | K48: =SUMIFS('Base - Payroll'!$H:$H,'Base - Payroll'!$A:$A,$H48,'Base - Payroll'!$B:$B," "&$H$1) -> 101720.49 | L48: =SUMIFS('Base - Payroll'!$I:$I,'Base - Payroll'!$A:$A,$H48,'Base - Payroll'!$B:$B," "&$H$1) -> 101720.49 | N48: Vacation | O48: =SUMIFS('Base - Payroll'!$E:$E,'Base - Payroll'!$A:$A,$N48,'Base - Payroll'!$B:$B," "&$N$1) -> 13900.738 | P48: =SUMIFS('Base - Payroll'!$G:$G,'Base - Payroll'!$A:$A,$N48,'Base - Payroll'!$B:$B," "&$N$1) -> 14489.871 | Q48: =SUMIFS('Base - Payroll'!$H:$H,'Base - Payroll'!$A:$A,$N48,'Base - Payroll'!$B:$B," "&$N$1) -> 14489.871 | R48: =SUMIFS('Base - Payroll'!$I:$I,'Base - Payroll'!$A:$A,$N48,'Base - Payroll'!$B:$B," "&$N$1) -> 14489.871 | T48: Vacation | U48: =SUMIFS('Base - Payroll'!$E:$E,'Base - Payroll'!$A:$A,$T48,'Base - Payroll'!$B:$B," "&$T$1) -> 62227.33 | V48: =SUMIFS('Base - Payroll'!$G:$G,'Base - Payroll'!$A:$A,$T48,'Base - Payroll'!$B:$B," "&$T$1) -> 64498.449 | W48: =SUMIFS('Base - Payroll'!$H:$H,'Base - Payroll'!$A:$A,$T48,'Base - Payroll'!$B:$B," "&$T$1) -> 64498.449 | X48: =SUMIFS('Base - Payroll'!$I:$I,'Base - Payroll'!$A:$A,$T48,'Base - Payroll'!$B:$B," "&$T$1) -> 64498.449 | Z48: Vacation | AA48: =SUMIFS('Base - Payroll'!$E:$E,'Base - Payroll'!$A:$A,$Z48,'Base - Payroll'!$B:$B," "&$Z$1) -> 0 | AB48: =SUMIFS('Base - Payroll'!$G:$G,'Base - Payroll'!$A:$A,$Z48,'Base - Payroll'!$B:$B," "&$Z$1) -> 0 | AC48: =SUMIFS('Base - Payroll'!$H:$H,'Base - Payroll'!$A:$A,$Z48,'Base - Payroll'!$B:$B," "&$Z$1) -> 0 | AD48: =SUMIFS('Base - Payroll'!$I:$I,'Base - Payroll'!$A:$A,$Z48,'Base - Payroll'!$B:$B," "&$Z$1) -> 0
B49: Other | C49: =SUMIFS('Base - Payroll'!$E:$E,'Base - Payroll'!$A:$A,Summary!$B49) -> -421719.89 | D49: =SUMIFS('Base - Payroll'!$G:$G,'Base - Payroll'!$A:$A,Summary!$B49) -> 377.897 | E49: =SUMIFS('Base - Payroll'!$H:$H,'Base - Payroll'!$A:$A,Summary!$B49) -> 377.897 | F49: =SUMIFS('Base - Payroll'!$I:$I,'Base - Payroll'!$A:$A,Summary!$B49) -> 377.897 | H49: Other | I49: =SUMIFS('Base - Payroll'!$E:$E,'Base - Payroll'!$A:$A,$H49,'Base - Payroll'!$B:$B," "&$H$1) -> 362.39396 | J49: =SUMIFS('Base - Payroll'!$G:$G,'Base - Payroll'!$A:$A,$H49,'Base - Payroll'!$B:$B," "&$H$1) -> 377.897 | K49: =SUMIFS('Base - Payroll'!$H:$H,'Base - Payroll'!$A:$A,$H49,'Base - Payroll'!$B:$B," "&$H$1) -> 377.897 | L49: =SUMIFS('Base - Payroll'!$I:$I,'Base - Payroll'!$A:$A,$H49,'Base - Payroll'!$B:$B," "&$H$1) -> 377.897 | N49: Other | O49: =SUMIFS('Base - Payroll'!$E:$E,'Base - Payroll'!$A:$A,$N49,'Base - Payroll'!$B:$B," "&$N$1) -> 0 | P49: =SUMIFS('Base - Payroll'!$G:$G,'Base - Payroll'!$A:$A,$N49,'Base - Payroll'!$B:$B," "&$N$1) -> 0 | Q49: =SUMIFS('Base - Payroll'!$H:$H,'Base - Payroll'!$A:$A,$N49,'Base - Payroll'!$B:$B," "&$N$1) -> 0 | R49: =SUMIFS('Base - Payroll'!$I:$I,'Base - Payroll'!$A:$A,$N49,'Base - Payroll'!$B:$B," "&$N$1) -> 0 | T49: Other | U49: =SUMIFS('Base - Payroll'!$E:$E,'Base - Payroll'!$A:$A,$T49,'Base - Payroll'!$B:$B," "&$T$1) -> -422082.28 | V49: =SUMIFS('Base - Payroll'!$G:$G,'Base - Payroll'!$A:$A,$T49,'Base - Payroll'!$B:$B," "&$T$1) -> 0 | W49: =SUMIFS('Base - Payroll'!$H:$H,'Base - Payroll'!$A:$A,$T49,'Base - Payroll'!$B:$B," "&$T$1) -> 0 | X49: =SUMIFS('Base - Payroll'!$I:$I,'Base - Payroll'!$A:$A,$T49,'Base - Payroll'!$B:$B," "&$T$1) -> 0 | Z49: Other | AA49: =SUMIFS('Base - Payroll'!$E:$E,'Base - Payroll'!$A:$A,$Z49,'Base - Payroll'!$B:$B," "&$Z$1) -> 0 | AB49: =SUMIFS('Base - Payroll'!$G:$G,'Base - Payroll'!$A:$A,$Z49,'Base - Payroll'!$B:$B," "&$Z$1) -> 0 | AC49: =SUMIFS('Base - Payroll'!$H:$H,'Base - Payroll'!$A:$A,$Z49,'Base - Payroll'!$B:$B," "&$Z$1) -> 0 | AD49: =SUMIFS('Base - Payroll'!$I:$I,'Base - Payroll'!$A:$A,$Z49,'Base - Payroll'!$B:$B," "&$Z$1) -> 0
B50: Contract Labor | C50: =SUMIFS('Base - Non-Payroll'!$E:$E,'Base - Non-Payroll'!$A:$A,Summary!$B50) -> 1899752.6 | D50: =SUMIFS('Base - Non-Payroll'!$H:$H,'Base - Non-Payroll'!$A:$A,Summary!$B50) -> 1899752.6 | E50: =SUMIFS('Base - Non-Payroll'!$J:$J,'Base - Non-Payroll'!$A:$A,Summary!$B50) -> 1899752.6 | F50: =SUMIFS('Base - Non-Payroll'!$L:$L,'Base - Non-Payroll'!$A:$A,Summary!$B50) -> 1899752.6 | H50: Contract Labor | I50: =SUMIFS('Base - Non-Payroll'!$E:$E,'Base - Non-Payroll'!$A:$A,$H50,'Base - Non-Payroll'!$B:$B," "&$H$1) -> 1359752.6 | J50: =SUMIFS('Base - Non-Payroll'!$H:$H,'Base - Non-Payroll'!$A:$A,$H50,'Base - Non-Payroll'!$B:$B," "&$H$1) -> 1359752.6 | K50: =SUMIFS('Base - Non-Payroll'!$J:$J,'Base - Non-Payroll'!$A:$A,$H50,'Base - Non-Payroll'!$B:$B," "&$H$1) -> 1359752.6 | L50: =SUMIFS('Base - Non-Payroll'!$L:$L,'Base - Non-Payroll'!$A:$A,$H50,'Base - Non-Payroll'!$B:$B," "&$H$1) -> 1359752.6 | N50: Contract Labor | O50: =SUMIFS('Base - Non-Payroll'!$E:$E,'Base - Non-Payroll'!$A:$A,$N50,'Base - Non-Payroll'!$B:$B," "&$N$1) -> 0 | P50: =SUMIFS('Base - Non-Payroll'!$H:$H,'Base - Non-Payroll'!$A:$A,$N50,'Base - Non-Payroll'!$B:$B," "&$N$1) -> 0 | Q50: =SUMIFS('Base - Non-Payroll'!$J:$J,'Base - Non-Payroll'!$A:$A,$N50,'Base - Non-Payroll'!$B:$B," "&$N$1) -> 0 | R50: =SUMIFS('Base - Non-Payroll'!$L:$L,'Base - Non-Payroll'!$A:$A,$N50,'Base - Non-Payroll'!$B:$B," "&$N$1) -> 0 | T50: Contract Labor | U50: =SUMIFS('Base - Non-Payroll'!$E:$E,'Base - Non-Payroll'!$A:$A,$T50,'Base - Non-Payroll'!$B:$B," "&$T$1) -> 540000 | V50: =SUMIFS('Base - Non-Payroll'!$H:$H,'Base - Non-Payroll'!$A:$A,$T50,'Base - Non-Payroll'!$B:$B," "&$T$1) -> 540000 | W50: =SUMIFS('Base - Non-Payroll'!$J:$J,'Base - Non-Payroll'!$A:$A,$T50,'Base - Non-Payroll'!$B:$B," "&$T$1) -> 540000 | X50: =SUMIFS('Base - Non-Payroll'!$L:$L,'Base - Non-Payroll'!$A:$A,$T50,'Base - Non-Payroll'!$B:$B," "&$T$1) -> 540000 | Z50: Contract Labor | AA50: =SUMIFS('Base - Non-Payroll'!$E:$E,'Base - Non-Payroll'!$A:$A,$Z50,'Base - Non-Payroll'!$B:$B," "&$Z$1) -> 0 | AB50: =SUMIFS('Base - Non-Payroll'!$H:$H,'Base - Non-Payroll'!$A:$A,$Z50,'Base - Non-Payroll'!$B:$B," "&$Z$1) -> 0 | AC50: =SUMIFS('Base - Non-Payroll'!$J:$J,'Base - Non-Payroll'!$A:$A,$Z50,'Base - Non-Payroll'!$B:$B," "&$Z$1) -> 0 | AD50: =SUMIFS('Base - Non-Payroll'!$L:$L,'Base - Non-Payroll'!$A:$A,$Z50,'Base - Non-Payroll'!$B:$B," "&$Z$1) -> 0
B51: LTIP Compensation | C51: =SUMIFS('Base - Payroll'!$E:$E,'Base - Payroll'!$A:$A,Summary!$B51) -> 3602361.1 | D51: =SUMIFS('Base - Payroll'!$G:$G,'Base - Payroll'!$A:$A,Summary!$B51) -> 3903500.8 | E51: =SUMIFS('Base - Payroll'!$H:$H,'Base - Payroll'!$A:$A,Summary!$B51) -> 3903500.8 | F51: =SUMIFS('Base - Payroll'!$I:$I,'Base - Payroll'!$A:$A,Summary!$B51) -> 3903500.8 | H51: LTIP Compensation | I51: =SUMIFS('Base - Payroll'!$E:$E,'Base - Payroll'!$A:$A,$H51,'Base - Payroll'!$B:$B," "&$H$1) -> 1203507.6 | J51: =SUMIFS('Base - Payroll'!$G:$G,'Base - Payroll'!$A:$A,$H51,'Base - Payroll'!$B:$B," "&$H$1) -> 1373047.6 | K51: =SUMIFS('Base - Payroll'!$H:$H,'Base - Payroll'!$A:$A,$H51,'Base - Payroll'!$B:$B," "&$H$1) -> 1373047.6 | L51: =SUMIFS('Base - Payroll'!$I:$I,'Base - Payroll'!$A:$A,$H51,'Base - Payroll'!$B:$B," "&$H$1) -> 1373047.6 | N51: LTIP Compensation | O51: =SUMIFS('Base - Payroll'!$E:$E,'Base - Payroll'!$A:$A,$N51,'Base - Payroll'!$B:$B," "&$N$1) -> 339126.66 | P51: =SUMIFS('Base - Payroll'!$G:$G,'Base - Payroll'!$A:$A,$N51,'Base - Payroll'!$B:$B," "&$N$1) -> 456329.4 | Q51: =SUMIFS('Base - Payroll'!$H:$H,'Base - Payroll'!$A:$A,$N51,'Base - Payroll'!$B:$B," "&$N$1) -> 456329.4 | R51: =SUMIFS('Base - Payroll'!$I:$I,'Base - Payroll'!$A:$A,$N51,'Base - Payroll'!$B:$B," "&$N$1) -> 456329.4 | T51: LTIP Compensation | U51: =SUMIFS('Base - Payroll'!$E:$E,'Base - Payroll'!$A:$A,$T51,'Base - Payroll'!$B:$B," "&$T$1) -> 351851.21 | V51: =SUMIFS('Base - Payroll'!$G:$G,'Base - Payroll'!$A:$A,$T51,'Base - Payroll'!$B:$B," "&$T$1) -> 364692.77 | W51: =SUMIFS('Base - Payroll'!$H:$H,'Base - Payroll'!$A:$A,$T51,'Base - Payroll'!$B:$B," "&$T$1) -> 364692.77 | X51: =SUMIFS('Base - Payroll'!$I:$I,'Base - Payroll'!$A:$A,$T51,'Base - Payroll'!$B:$B," "&$T$1) -> 364692.77 | Z51: LTIP Compensation | AA51: =SUMIFS('Base - Payroll'!$E:$E,'Base - Payroll'!$A:$A,$Z51,'Base - Payroll'!$B:$B," "&$Z$1) -> 1707875.6 | AB51: =SUMIFS('Base - Payroll'!$G:$G,'Base - Payroll'!$A:$A,$Z51,'Base - Payroll'!$B:$B," "&$Z$1) -> 1709431.1 | AC51: =SUMIFS('Base - Payroll'!$H:$H,'Base - Payroll'!$A:$A,$Z51,'Base - Payroll'!$B:$B," "&$Z$1) -> 1709431.1 | AD51: =SUMIFS('Base - Payroll'!$I:$I,'Base - Payroll'!$A:$A,$Z51,'Base - Payroll'!$B:$B," "&$Z$1) -> 1709431.1
B52: Baseline Payroll | C52: =SUM(C43:C51) -> 48395278 | D52: =SUM(D43:D51) -> 50770674 | E52: =SUM(E43:E51) -> 50770674 | F52: =SUM(F43:F51) -> 50770674 | H52: Baseline Payroll | I52: =SUM(I43:I51) -> 29499176 | J52: =SUM(J43:J51) -> 30783520 | K52: =SUM(K43:K51) -> 30783520 | L52: =SUM(L43:L51) -> 30783520 | N52: Baseline Payroll | O52: =SUM(O43:O51) -> 4892825.2 | P52: =SUM(P43:P51) -> 5203020.1 | Q52: =SUM(Q43:Q51) -> 5203020.1 | R52: =SUM(R43:R51) -> 5203020.1 | T52: Baseline Payroll | U52: =SUM(U43:U51) -> 10263481 | V52: =SUM(V43:V51) -> 11040932 | W52: =SUM(W43:W51) -> 11040932 | X52: =SUM(X43:X51) -> 11040932 | Z52: Baseline Payroll | AA52: =SUM(AA43:AA51) -> 3739795.7 | AB52: =SUM(AB43:AB51) -> 3743201.8 | AC52: =SUM(AC43:AC51) -> 3743201.8 | AD52: =SUM(AD43:AD51) -> 3743201.8
B54: Professional Fees | C54: =SUMIFS('Base - Non-Payroll'!$E:$E,'Base - Non-Payroll'!$A:$A,Summary!$B54) -> 7181209.5 | D54: =SUMIFS('Base - Non-Payroll'!$H:$H,'Base - Non-Payroll'!$A:$A,Summary!$B54) -> 7181209.5 | E54: =SUMIFS('Base - Non-Payroll'!$J:$J,'Base - Non-Payroll'!$A:$A,Summary!$B54) -> 7181209.5 | F54: =SUMIFS('Base - Non-Payroll'!$L:$L,'Base - Non-Payroll'!$A:$A,Summary!$B54) -> 7181209.5 | H54: Professional Fees | I54: =SUMIFS('Base - Non-Payroll'!$E:$E,'Base - Non-Payroll'!$A:$A,$H54,'Base - Non-Payroll'!$B:$B," "&$H$1) -> 1689705.4 | J54: =SUMIFS('Base - Non-Payroll'!$H:$H,'Base - Non-Payroll'!$A:$A,$H54,'Base - Non-Payroll'!$B:$B," "&$H$1) -> 1689705.4 | K54: =SUMIFS('Base - Non-Payroll'!$J:$J,'Base - Non-Payroll'!$A:$A,$H54,'Base - Non-Payroll'!$B:$B," "&$H$1) -> 1689705.4 | L54: =SUMIFS('Base - Non-Payroll'!$L:$L,'Base - Non-Payroll'!$A:$A,$H54,'Base - Non-Payroll'!$B:$B," "&$H$1) -> 1689705.4 | N54: Professional Fees | O54: =SUMIFS('Base - Non-Payroll'!$E:$E,'Base - Non-Payroll'!$A:$A,$N54,'Base - Non-Payroll'!$B:$B," "&$N$1) -> 769992 | P54: =SUMIFS('Base - Non-Payroll'!$H:$H,'Base - Non-Payroll'!$A:$A,$N54,'Base - Non-Payroll'!$B:$B," "&$N$1) -> 769992 | Q54: =SUMIFS('Base - Non-Payroll'!$J:$J,'Base - Non-Payroll'!$A:$A,$N54,'Base - Non-Payroll'!$B:$B," "&$N$1) -> 769992 | R54: =SUMIFS('Base - Non-Payroll'!$L:$L,'Base - Non-Payroll'!$A:$A,$N54,'Base - Non-Payroll'!$B:$B," "&$N$1) -> 769992 | T54: Professional Fees | U54: =SUMIFS('Base - Non-Payroll'!$E:$E,'Base - Non-Payroll'!$A:$A,$T54,'Base - Non-Payroll'!$B:$B," "&$T$1) -> 4361510.7 | V54: =SUMIFS('Base - Non-Payroll'!$H:$H,'Base - Non-Payroll'!$A:$A,$T54,'Base - Non-Payroll'!$B:$B," "&$T$1) -> 4361510.7 | W54: =SUMIFS('Base - Non-Payroll'!$J:$J,'Base - Non-Payroll'!$A:$A,$T54,'Base - Non-Payroll'!$B:$B," "&$T$1) -> 4361510.7 | X54: =SUMIFS('Base - Non-Payroll'!$L:$L,'Base - Non-Payroll'!$A:$A,$T54,'Base - Non-Payroll'!$B:$B," "&$T$1) -> 4361510.7 | Z54: Professional Fees | AA54: =SUMIFS('Base - Non-Payroll'!$E:$E,'Base - Non-Payroll'!$A:$A,$Z54,'Base - Non-Payroll'!$B:$B," "&$Z$1) -> 360001.33 | AB54: =SUMIFS('Base - Non-Payroll'!$H:$H,'Base - Non-Payroll'!$A:$A,$Z54,'Base - Non-Payroll'!$B:$B," "&$Z$1) -> 360001.33 | AC54: =SUMIFS('Base - Non-Payroll'!$J:$J,'Base - Non-Payroll'!$A:$A,$Z54,'Base - Non-Payroll'!$B:$B," "&$Z$1) -> 360001.33 | AD54: =SUMIFS('Base - Non-Payroll'!$L:$L,'Base - Non-Payroll'!$A:$A,$Z54,'Base - Non-Payroll'!$B:$B," "&$Z$1) -> 360001.33
B55: Occupancy | C55: =SUMIFS('Base - Non-Payroll'!$E:$E,'Base - Non-Payroll'!$A:$A,Summary!$B55) -> 100003.17 | D55: =SUMIFS('Base - Non-Payroll'!$H:$H,'Base - Non-Payroll'!$A:$A,Summary!$B55) -> 100003.17 | E55: =SUMIFS('Base - Non-Payroll'!$J:$J,'Base - Non-Payroll'!$A:$A,Summary!$B55) -> 100003.17 | F55: =SUMIFS('Base - Non-Payroll'!$L:$L,'Base - Non-Payroll'!$A:$A,Summary!$B55) -> 100003.17 | H55: Occupancy | I55: =SUMIFS('Base - Non-Payroll'!$E:$E,'Base - Non-Payroll'!$A:$A,$H55,'Base - Non-Payroll'!$B:$B," "&$H$1) -> 100001.28 | J55: =SUMIFS('Base - Non-Payroll'!$H:$H,'Base - Non-Payroll'!$A:$A,$H55,'Base - Non-Payroll'!$B:$B," "&$H$1) -> 100001.28 | K55: =SUMIFS('Base - Non-Payroll'!$J:$J,'Base - Non-Payroll'!$A:$A,$H55,'Base - Non-Payroll'!$B:$B," "&$H$1) -> 100001.28 | L55: =SUMIFS('Base - Non-Payroll'!$L:$L,'Base - Non-Payroll'!$A:$A,$H55,'Base - Non-Payroll'!$B:$B," "&$H$1) -> 100001.28 | N55: Occupancy | O55: =SUMIFS('Base - Non-Payroll'!$E:$E,'Base - Non-Payroll'!$A:$A,$N55,'Base - Non-Payroll'!$B:$B," "&$N$1) -> 0 | P55: =SUMIFS('Base - Non-Payroll'!$H:$H,'Base - Non-Payroll'!$A:$A,$N55,'Base - Non-Payroll'!$B:$B," "&$N$1) -> 0 | Q55: =SUMIFS('Base - Non-Payroll'!$J:$J,'Base - Non-Payroll'!$A:$A,$N55,'Base - Non-Payroll'!$B:$B," "&$N$1) -> 0 | R55: =SUMIFS('Base - Non-Payroll'!$L:$L,'Base - Non-Payroll'!$A:$A,$N55,'Base - Non-Payroll'!$B:$B," "&$N$1) -> 0 | T55: Occupancy | U55: =SUMIFS('Base - Non-Payroll'!$E:$E,'Base - Non-Payroll'!$A:$A,$T55,'Base - Non-Payroll'!$B:$B," "&$T$1) -> 1.89 | V55: =SUMIFS('Base - Non-Payroll'!$H:$H,'Base - Non-Payroll'!$A:$A,$T55,'Base - Non-Payroll'!$B:$B," "&$T$1) -> 1.89 | W55: =SUMIFS('Base - Non-Payroll'!$J:$J,'Base - Non-Payroll'!$A:$A,$T55,'Base - Non-Payroll'!$B:$B," "&$T$1) -> 1.89 | X55: =SUMIFS('Base - Non-Payroll'!$L:$L,'Base - Non-Payroll'!$A:$A,$T55,'Base - Non-Payroll'!$B:$B," "&$T$1) -> 1.89 | Z55: Occupancy | AA55: =SUMIFS('Base - Non-Payroll'!$E:$E,'Base - Non-Payroll'!$A:$A,$Z55,'Base - Non-Payroll'!$B:$B," "&$Z$1) -> 0 | AB55: =SUMIFS('Base - Non-Payroll'!$H:$H,'Base - Non-Payroll'!$A:$A,$Z55,'Base - Non-Payroll'!$B:$B," "&$Z$1) -> 0 | AC55: =SUMIFS('Base - Non-Payroll'!$J:$J,'Base - Non-Payroll'!$A:$A,$Z55,'Base - Non-Payroll'!$B:$B," "&$Z$1) -> 0 | AD55: =SUMIFS('Base - Non-Payroll'!$L:$L,'Base - Non-Payroll'!$A:$A,$Z55,'Base - Non-Payroll'!$B:$B," "&$Z$1) -> 0
B56: Office Expenses | C56: =SUMIFS('Base - Non-Payroll'!$E:$E,'Base - Non-Payroll'!$A:$A,Summary!$B56) -> 6598.26 | D56: =SUMIFS('Base - Non-Payroll'!$H:$H,'Base - Non-Payroll'!$A:$A,Summary!$B56) -> 6598.26 | E56: =SUMIFS('Base - Non-Payroll'!$J:$J,'Base - Non-Payroll'!$A:$A,Summary!$B56) -> 6598.26 | F56: =SUMIFS('Base - Non-Payroll'!$L:$L,'Base - Non-Payroll'!$A:$A,Summary!$B56) -> 6598.26 | H56: Office Expenses | I56: =SUMIFS('Base - Non-Payroll'!$E:$E,'Base - Non-Payroll'!$A:$A,$H56,'Base - Non-Payroll'!$B:$B," "&$H$1) -> 1596.31 | J56: =SUMIFS('Base - Non-Payroll'!$H:$H,'Base - Non-Payroll'!$A:$A,$H56,'Base - Non-Payroll'!$B:$B," "&$H$1) -> 1596.31 | K56: =SUMIFS('Base - Non-Payroll'!$J:$J,'Base - Non-Payroll'!$A:$A,$H56,'Base - Non-Payroll'!$B:$B," "&$H$1) -> 1596.31 | L56: =SUMIFS('Base - Non-Payroll'!$L:$L,'Base - Non-Payroll'!$A:$A,$H56,'Base - Non-Payroll'!$B:$B," "&$H$1) -> 1596.31 | N56: Office Expenses | O56: =SUMIFS('Base - Non-Payroll'!$E:$E,'Base - Non-Payroll'!$A:$A,$N56,'Base - Non-Payroll'!$B:$B," "&$N$1) -> -2.04 | P56: =SUMIFS('Base - Non-Payroll'!$H:$H,'Base - Non-Payroll'!$A:$A,$N56,'Base - Non-Payroll'!$B:$B," "&$N$1) -> -2.04 | Q56: =SUMIFS('Base - Non-Payroll'!$J:$J,'Base - Non-Payroll'!$A:$A,$N56,'Base - Non-Payroll'!$B:$B," "&$N$1) -> -2.04 | R56: =SUMIFS('Base - Non-Payroll'!$L:$L,'Base - Non-Payroll'!$A:$A,$N56,'Base - Non-Payroll'!$B:$B," "&$N$1) -> -2.04 | T56: Office Expenses | U56: =SUMIFS('Base - Non-Payroll'!$E:$E,'Base - Non-Payroll'!$A:$A,$T56,'Base - Non-Payroll'!$B:$B," "&$T$1) -> 5007.59 | V56: =SUMIFS('Base - Non-Payroll'!$H:$H,'Base - Non-Payroll'!$A:$A,$T56,'Base - Non-Payroll'!$B:$B," "&$T$1) -> 5007.59 | W56: =SUMIFS('Base - Non-Payroll'!$J:$J,'Base - Non-Payroll'!$A:$A,$T56,'Base - Non-Payroll'!$B:$B," "&$T$1) -> 5007.59 | X56: =SUMIFS('Base - Non-Payroll'!$L:$L,'Base - Non-Payroll'!$A:$A,$T56,'Base - Non-Payroll'!$B:$B," "&$T$1) -> 5007.59 | Z56: Office Expenses | AA56: =SUMIFS('Base - Non-Payroll'!$E:$E,'Base - Non-Payroll'!$A:$A,$Z56,'Base - Non-Payroll'!$B:$B," "&$Z$1) -> -3.6 | AB56: =SUMIFS('Base - Non-Payroll'!$H:$H,'Base - Non-Payroll'!$A:$A,$Z56,'Base - Non-Payroll'!$B:$B," "&$Z$1) -> -3.6 | AC56: =SUMIFS('Base - Non-Payroll'!$J:$J,'Base - Non-Payroll'!$A:$A,$Z56,'Base - Non-Payroll'!$B:$B," "&$Z$1) -> -3.6 | AD56: =SUMIFS('Base - Non-Payroll'!$L:$L,'Base - Non-Payroll'!$A:$A,$Z56,'Base - Non-Payroll'!$B:$B," "&$Z$1) -> -3.6
B57: IT Costs | C57: =SUMIFS('Base - Non-Payroll'!$E:$E,'Base - Non-Payroll'!$A:$A,Summary!$B57) -> 621855.21 | D57: =SUMIFS('Base - Non-Payroll'!$H:$H,'Base - Non-Payroll'!$A:$A,Summary!$B57) -> 621855.21 | E57: =SUMIFS('Base - Non-Payroll'!$J:$J,'Base - Non-Payroll'!$A:$A,Summary!$B57) -> 621855.21 | F57: =SUMIFS('Base - Non-Payroll'!$L:$L,'Base - Non-Payroll'!$A:$A,Summary!$B57) -> 621855.21 | H57: IT Costs | I57: =SUMIFS('Base - Non-Payroll'!$E:$E,'Base - Non-Payroll'!$A:$A,$H57,'Base - Non-Payroll'!$B:$B," "&$H$1) -> 575609.31 | J57: =SUMIFS('Base - Non-Payroll'!$H:$H,'Base - Non-Payroll'!$A:$A,$H57,'Base - Non-Payroll'!$B:$B," "&$H$1) -> 575609.31 | K57: =SUMIFS('Base - Non-Payroll'!$J:$J,'Base - Non-Payroll'!$A:$A,$H57,'Base - Non-Payroll'!$B:$B," "&$H$1) -> 575609.31 | L57: =SUMIFS('Base - Non-Payroll'!$L:$L,'Base - Non-Payroll'!$A:$A,$H57,'Base - Non-Payroll'!$B:$B," "&$H$1) -> 575609.31 | N57: IT Costs | O57: =SUMIFS('Base - Non-Payroll'!$E:$E,'Base - Non-Payroll'!$A:$A,$N57,'Base - Non-Payroll'!$B:$B," "&$N$1) -> 2.95 | P57: =SUMIFS('Base - Non-Payroll'!$H:$H,'Base - Non-Payroll'!$A:$A,$N57,'Base - Non-Payroll'!$B:$B," "&$N$1) -> 2.95 | Q57: =SUMIFS('Base - Non-Payroll'!$J:$J,'Base - Non-Payroll'!$A:$A,$N57,'Base - Non-Payroll'!$B:$B," "&$N$1) -> 2.95 | R57: =SUMIFS('Base - Non-Payroll'!$L:$L,'Base - Non-Payroll'!$A:$A,$N57,'Base - Non-Payroll'!$B:$B," "&$N$1) -> 2.95 | T57: IT Costs | U57: =SUMIFS('Base - Non-Payroll'!$E:$E,'Base - Non-Payroll'!$A:$A,$T57,'Base - Non-Payroll'!$B:$B," "&$T$1) -> 46239.61 | V57: =SUMIFS('Base - Non-Payroll'!$H:$H,'Base - Non-Payroll'!$A:$A,$T57,'Base - Non-Payroll'!$B:$B," "&$T$1) -> 46239.61 | W57: =SUMIFS('Base - Non-Payroll'!$J:$J,'Base - Non-Payroll'!$A:$A,$T57,'Base - Non-Payroll'!$B:$B," "&$T$1) -> 46239.61 | X57: =SUMIFS('Base - Non-Payroll'!$L:$L,'Base - Non-Payroll'!$A:$A,$T57,'Base - Non-Payroll'!$B:$B," "&$T$1) -> 46239.61 | Z57: IT Costs | AA57: =SUMIFS('Base - Non-Payroll'!$E:$E,'Base - Non-Payroll'!$A:$A,$Z57,'Base - Non-Payroll'!$B:$B," "&$Z$1) -> 3.34 | AB57: =SUMIFS('Base - Non-Payroll'!$H:$H,'Base - Non-Payroll'!$A:$A,$Z57,'Base - Non-Payroll'!$B:$B," "&$Z$1) -> 3.34 | AC57: =SUMIFS('Base - Non-Payroll'!$J:$J,'Base - Non-Payroll'!$A:$A,$Z57,'Base - Non-Payroll'!$B:$B," "&$Z$1) -> 3.34 | AD57: =SUMIFS('Base - Non-Payroll'!$L:$L,'Base - Non-Payroll'!$A:$A,$Z57,'Base - Non-Payroll'!$B:$B," "&$Z$1) -> 3.34
B58: Marketing and Presentation | C58: =SUMIFS('Base - Non-Payroll'!$E:$E,'Base - Non-Payroll'!$A:$A,Summary!$B58) -> 747958 | D58: =SUMIFS('Base - Non-Payroll'!$H:$H,'Base - Non-Payroll'!$A:$A,Summary!$B58) -> 747958 | E58: =SUMIFS('Base - Non-Payroll'!$J:$J,'Base - Non-Payroll'!$A:$A,Summary!$B58) -> 747958 | F58: =SUMIFS('Base - Non-Payroll'!$L:$L,'Base - Non-Payroll'!$A:$A,Summary!$B58) -> 747958 | H58: Marketing and Presentation | I58: =SUMIFS('Base - Non-Payroll'!$E:$E,'Base - Non-Payroll'!$A:$A,$H58,'Base - Non-Payroll'!$B:$B," "&$H$1) -> 0 | J58: =SUMIFS('Base - Non-Payroll'!$H:$H,'Base - Non-Payroll'!$A:$A,$H58,'Base - Non-Payroll'!$B:$B," "&$H$1) -> 0 | K58: =SUMIFS('Base - Non-Payroll'!$J:$J,'Base - Non-Payroll'!$A:$A,$H58,'Base - Non-Payroll'!$B:$B," "&$H$1) -> 0 | L58: =SUMIFS('Base - Non-Payroll'!$L:$L,'Base - Non-Payroll'!$A:$A,$H58,'Base - Non-Payroll'!$B:$B," "&$H$1) -> 0 | N58: Marketing and Presentation | O58: =SUMIFS('Base - Non-Payroll'!$E:$E,'Base - Non-Payroll'!$A:$A,$N58,'Base - Non-Payroll'!$B:$B," "&$N$1) -> 0 | P58: =SUMIFS('Base - Non-Payroll'!$H:$H,'Base - Non-Payroll'!$A:$A,$N58,'Base - Non-Payroll'!$B:$B," "&$N$1) -> 0 | Q58: =SUMIFS('Base - Non-Payroll'!$J:$J,'Base - Non-Payroll'!$A:$A,$N58,'Base - Non-Payroll'!$B:$B," "&$N$1) -> 0 | R58: =SUMIFS('Base - Non-Payroll'!$L:$L,'Base - Non-Payroll'!$A:$A,$N58,'Base - Non-Payroll'!$B:$B," "&$N$1) -> 0 | T58: Marketing and Presentation | U58: =SUMIFS('Base - Non-Payroll'!$E:$E,'Base - Non-Payroll'!$A:$A,$T58,'Base - Non-Payroll'!$B:$B," "&$T$1) -> 747958 | V58: =SUMIFS('Base - Non-Payroll'!$H:$H,'Base - Non-Payroll'!$A:$A,$T58,'Base - Non-Payroll'!$B:$B," "&$T$1) -> 747958 | W58: =SUMIFS('Base - Non-Payroll'!$J:$J,'Base - Non-Payroll'!$A:$A,$T58,'Base - Non-Payroll'!$B:$B," "&$T$1) -> 747958 | X58: =SUMIFS('Base - Non-Payroll'!$L:$L,'Base - Non-Payroll'!$A:$A,$T58,'Base - Non-Payroll'!$B:$B," "&$T$1) -> 747958 | Z58: Marketing and Presentation | AA58: =SUMIFS('Base - Non-Payroll'!$E:$E,'Base - Non-Payroll'!$A:$A,$Z58,'Base - Non-Payroll'!$B:$B," "&$Z$1) -> 0 | AB58: =SUMIFS('Base - Non-Payroll'!$H:$H,'Base - Non-Payroll'!$A:$A,$Z58,'Base - Non-Payroll'!$B:$B," "&$Z$1) -> 0 | AC58: =SUMIFS('Base - Non-Payroll'!$J:$J,'Base - Non-Payroll'!$A:$A,$Z58,'Base - Non-Payroll'!$B:$B," "&$Z$1) -> 0 | AD58: =SUMIFS('Base - Non-Payroll'!$L:$L,'Base - Non-Payroll'!$A:$A,$Z58,'Base - Non-Payroll'!$B:$B," "&$Z$1) -> 0
B59: Travel and Entertainment | C59: =SUMIFS('Base - Non-Payroll'!$E:$E,'Base - Non-Payroll'!$A:$A,Summary!$B59) -> 3003935.5 | D59: =SUMIFS('Base - Non-Payroll'!$H:$H,'Base - Non-Payroll'!$A:$A,Summary!$B59) -> 3003935.5 | E59: =SUMIFS('Base - Non-Payroll'!$J:$J,'Base - Non-Payroll'!$A:$A,Summary!$B59) -> 3003935.5 | F59: =SUMIFS('Base - Non-Payroll'!$L:$L,'Base - Non-Payroll'!$A:$A,Summary!$B59) -> 3003935.5 | H59: Travel and Entertainment | I59: =SUMIFS('Base - Non-Payroll'!$E:$E,'Base - Non-Payroll'!$A:$A,$H59,'Base - Non-Payroll'!$B:$B," "&$H$1) -> 1892769.3 | J59: =SUMIFS('Base - Non-Payroll'!$H:$H,'Base - Non-Payroll'!$A:$A,$H59,'Base - Non-Payroll'!$B:$B," "&$H$1) -> 1892769.3 | K59: =SUMIFS('Base - Non-Payroll'!$J:$J,'Base - Non-Payroll'!$A:$A,$H59,'Base - Non-Payroll'!$B:$B," "&$H$1) -> 1892769.3 | L59: =SUMIFS('Base - Non-Payroll'!$L:$L,'Base - Non-Payroll'!$A:$A,$H59,'Base - Non-Payroll'!$B:$B," "&$H$1) -> 1892769.3 | N59: Travel and Entertainment | O59: =SUMIFS('Base - Non-Payroll'!$E:$E,'Base - Non-Payroll'!$A:$A,$N59,'Base - Non-Payroll'!$B:$B," "&$N$1) -> 203998.22 | P59: =SUMIFS('Base - Non-Payroll'!$H:$H,'Base - Non-Payroll'!$A:$A,$N59,'Base - Non-Payroll'!$B:$B," "&$N$1) -> 203998.22 | Q59: =SUMIFS('Base - Non-Payroll'!$J:$J,'Base - Non-Payroll'!$A:$A,$N59,'Base - Non-Payroll'!$B:$B," "&$N$1) -> 203998.22 | R59: =SUMIFS('Base - Non-Payroll'!$L:$L,'Base - Non-Payroll'!$A:$A,$N59,'Base - Non-Payroll'!$B:$B," "&$N$1) -> 203998.22 | T59: Travel and Entertainment | U59: =SUMIFS('Base - Non-Payroll'!$E:$E,'Base - Non-Payroll'!$A:$A,$T59,'Base - Non-Payroll'!$B:$B," "&$T$1) -> 594403.83 | V59: =SUMIFS('Base - Non-Payroll'!$H:$H,'Base - Non-Payroll'!$A:$A,$T59,'Base - Non-Payroll'!$B:$B," "&$T$1) -> 594403.83 | W59: =SUMIFS('Base - Non-Payroll'!$J:$J,'Base - Non-Payroll'!$A:$A,$T59,'Base - Non-Payroll'!$B:$B," "&$T$1) -> 594403.83 | X59: =SUMIFS('Base - Non-Payroll'!$L:$L,'Base - Non-Payroll'!$A:$A,$T59,'Base - Non-Payroll'!$B:$B," "&$T$1) -> 594403.83 | Z59: Travel and Entertainment | AA59: =SUMIFS('Base - Non-Payroll'!$E:$E,'Base - Non-Payroll'!$A:$A,$Z59,'Base - Non-Payroll'!$B:$B," "&$Z$1) -> 312764.14 | AB59: =SUMIFS('Base - Non-Payroll'!$H:$H,'Base - Non-Payroll'!$A:$A,$Z59,'Base - Non-Payroll'!$B:$B," "&$Z$1) -> 312764.14 | AC59: =SUMIFS('Base - Non-Payroll'!$J:$J,'Base - Non-Payroll'!$A:$A,$Z59,'Base - Non-Payroll'!$B:$B," "&$Z$1) -> 312764.14 | AD59: =SUMIFS('Base - Non-Payroll'!$L:$L,'Base - Non-Payroll'!$A:$A,$Z59,'Base - Non-Payroll'!$B:$B," "&$Z$1) -> 312764.14
B60: Employee events | C60: =SUMIFS('Base - Non-Payroll'!$E:$E,'Base - Non-Payroll'!$A:$A,Summary!$B60) -> 232642.23 | D60: =SUMIFS('Base - Non-Payroll'!$H:$H,'Base - Non-Payroll'!$A:$A,Summary!$B60) -> 232642.23 | E60: =SUMIFS('Base - Non-Payroll'!$J:$J,'Base - Non-Payroll'!$A:$A,Summary!$B60) -> 232642.23 | F60: =SUMIFS('Base - Non-Payroll'!$L:$L,'Base - Non-Payroll'!$A:$A,Summary!$B60) -> 232642.23 | H60: Employee events | I60: =SUMIFS('Base - Non-Payroll'!$E:$E,'Base - Non-Payroll'!$A:$A,$H60,'Base - Non-Payroll'!$B:$B," "&$H$1) -> 167102.54 | J60: =SUMIFS('Base - Non-Payroll'!$H:$H,'Base - Non-Payroll'!$A:$A,$H60,'Base - Non-Payroll'!$B:$B," "&$H$1) -> 167102.54 | K60: =SUMIFS('Base - Non-Payroll'!$J:$J,'Base - Non-Payroll'!$A:$A,$H60,'Base - Non-Payroll'!$B:$B," "&$H$1) -> 167102.54 | L60: =SUMIFS('Base - Non-Payroll'!$L:$L,'Base - Non-Payroll'!$A:$A,$H60,'Base - Non-Payroll'!$B:$B," "&$H$1) -> 167102.54 | N60: Employee events | O60: =SUMIFS('Base - Non-Payroll'!$E:$E,'Base - Non-Payroll'!$A:$A,$N60,'Base - Non-Payroll'!$B:$B," "&$N$1) -> 23996 | P60: =SUMIFS('Base - Non-Payroll'!$H:$H,'Base - Non-Payroll'!$A:$A,$N60,'Base - Non-Payroll'!$B:$B," "&$N$1) -> 23996 | Q60: =SUMIFS('Base - Non-Payroll'!$J:$J,'Base - Non-Payroll'!$A:$A,$N60,'Base - Non-Payroll'!$B:$B," "&$N$1) -> 23996 | R60: =SUMIFS('Base - Non-Payroll'!$L:$L,'Base - Non-Payroll'!$A:$A,$N60,'Base - Non-Payroll'!$B:$B," "&$N$1) -> 23996 | T60: Employee events | U60: =SUMIFS('Base - Non-Payroll'!$E:$E,'Base - Non-Payroll'!$A:$A,$T60,'Base - Non-Payroll'!$B:$B," "&$T$1) -> 11544 | V60: =SUMIFS('Base - Non-Payroll'!$H:$H,'Base - Non-Payroll'!$A:$A,$T60,'Base - Non-Payroll'!$B:$B," "&$T$1) -> 11544 | W60: =SUMIFS('Base - Non-Payroll'!$J:$J,'Base - Non-Payroll'!$A:$A,$T60,'Base - Non-Payroll'!$B:$B," "&$T$1) -> 11544 | X60: =SUMIFS('Base - Non-Payroll'!$L:$L,'Base - Non-Payroll'!$A:$A,$T60,'Base - Non-Payroll'!$B:$B," "&$T$1) -> 11544 | Z60: Employee events | AA60: =SUMIFS('Base - Non-Payroll'!$E:$E,'Base - Non-Payroll'!$A:$A,$Z60,'Base - Non-Payroll'!$B:$B," "&$Z$1) -> 29999.69 | AB60: =SUMIFS('Base - Non-Payroll'!$H:$H,'Base - Non-Payroll'!$A:$A,$Z60,'Base - Non-Payroll'!$B:$B," "&$Z$1) -> 29999.69 | AC60: =SUMIFS('Base - Non-Payroll'!$J:$J,'Base - Non-Payroll'!$A:$A,$Z60,'Base - Non-Payroll'!$B:$B," "&$Z$1) -> 29999.69 | AD60: =SUMIFS('Base - Non-Payroll'!$L:$L,'Base - Non-Payroll'!$A:$A,$Z60,'Base - Non-Payroll'!$B:$B," "&$Z$1) -> 29999.69
B61: Insurance Non Property | C61: =SUMIFS('Base - Non-Payroll'!$E:$E,'Base - Non-Payroll'!$A:$A,Summary!$B61) -> 0 | D61: =SUMIFS('Base - Non-Payroll'!$H:$H,'Base - Non-Payroll'!$A:$A,Summary!$B61) -> 0 | E61: =SUMIFS('Base - Non-Payroll'!$J:$J,'Base - Non-Payroll'!$A:$A,Summary!$B61) -> 0 | F61: =SUMIFS('Base - Non-Payroll'!$L:$L,'Base - Non-Payroll'!$A:$A,Summary!$B61) -> 0 | H61: Insurance Non Property | I61: =SUMIFS('Base - Non-Payroll'!$E:$E,'Base - Non-Payroll'!$A:$A,$H61,'Base - Non-Payroll'!$B:$B," "&$H$1) -> 0 | J61: =SUMIFS('Base - Non-Payroll'!$H:$H,'Base - Non-Payroll'!$A:$A,$H61,'Base - Non-Payroll'!$B:$B," "&$H$1) -> 0 | K61: =SUMIFS('Base - Non-Payroll'!$J:$J,'Base - Non-Payroll'!$A:$A,$H61,'Base - Non-Payroll'!$B:$B," "&$H$1) -> 0 | L61: =SUMIFS('Base - Non-Payroll'!$L:$L,'Base - Non-Payroll'!$A:$A,$H61,'Base - Non-Payroll'!$B:$B," "&$H$1) -> 0 | N61: Insurance Non Property | O61: =SUMIFS('Base - Non-Payroll'!$E:$E,'Base - Non-Payroll'!$A:$A,$N61,'Base - Non-Payroll'!$B:$B," "&$N$1) -> 0 | P61: =SUMIFS('Base - Non-Payroll'!$H:$H,'Base - Non-Payroll'!$A:$A,$N61,'Base - Non-Payroll'!$B:$B," "&$N$1) -> 0 | Q61: =SUMIFS('Base - Non-Payroll'!$J:$J,'Base - Non-Payroll'!$A:$A,$N61,'Base - Non-Payroll'!$B:$B," "&$N$1) -> 0 | R61: =SUMIFS('Base - Non-Payroll'!$L:$L,'Base - Non-Payroll'!$A:$A,$N61,'Base - Non-Payroll'!$B:$B," "&$N$1) -> 0 | T61: Insurance Non Property | U61: =SUMIFS('Base - Non-Payroll'!$E:$E,'Base - Non-Payroll'!$A:$A,$T61,'Base - Non-Payroll'!$B:$B," "&$T$1) -> 0 | V61: =SUMIFS('Base - Non-Payroll'!$H:$H,'Base - Non-Payroll'!$A:$A,$T61,'Base - Non-Payroll'!$B:$B," "&$T$1) -> 0 | W61: =SUMIFS('Base - Non-Payroll'!$J:$J,'Base - Non-Payroll'!$A:$A,$T61,'Base - Non-Payroll'!$B:$B," "&$T$1) -> 0 | X61: =SUMIFS('Base - Non-Payroll'!$L:$L,'Base - Non-Payroll'!$A:$A,$T61,'Base - Non-Payroll'!$B:$B," "&$T$1) -> 0 | Z61: Insurance Non Property | AA61: =SUMIFS('Base - Non-Payroll'!$E:$E,'Base - Non-Payroll'!$A:$A,$Z61,'Base - Non-Payroll'!$B:$B," "&$Z$1) -> 0 | AB61: =SUMIFS('Base - Non-Payroll'!$H:$H,'Base - Non-Payroll'!$A:$A,$Z61,'Base - Non-Payroll'!$B:$B," "&$Z$1) -> 0 | AC61: =SUMIFS('Base - Non-Payroll'!$J:$J,'Base - Non-Payroll'!$A:$A,$Z61,'Base - Non-Payroll'!$B:$B," "&$Z$1) -> 0 | AD61: =SUMIFS('Base - Non-Payroll'!$L:$L,'Base - Non-Payroll'!$A:$A,$Z61,'Base - Non-Payroll'!$B:$B," "&$Z$1) -> 0
B62: Licenses | C62: =SUMIFS('Base - Non-Payroll'!$E:$E,'Base - Non-Payroll'!$A:$A,Summary!$B62) -> 0 | D62: =SUMIFS('Base - Non-Payroll'!$H:$H,'Base - Non-Payroll'!$A:$A,Summary!$B62) -> 0 | E62: =SUMIFS('Base - Non-Payroll'!$J:$J,'Base - Non-Payroll'!$A:$A,Summary!$B62) -> 0 | F62: =SUMIFS('Base - Non-Payroll'!$L:$L,'Base - Non-Payroll'!$A:$A,Summary!$B62) -> 0 | H62: Licenses | I62: =SUMIFS('Base - Non-Payroll'!$E:$E,'Base - Non-Payroll'!$A:$A,$H62,'Base - Non-Payroll'!$B:$B," "&$H$1) -> 0 | J62: =SUMIFS('Base - Non-Payroll'!$H:$H,'Base - Non-Payroll'!$A:$A,$H62,'Base - Non-Payroll'!$B:$B," "&$H$1) -> 0 | K62: =SUMIFS('Base - Non-Payroll'!$J:$J,'Base - Non-Payroll'!$A:$A,$H62,'Base - Non-Payroll'!$B:$B," "&$H$1) -> 0 | L62: =SUMIFS('Base - Non-Payroll'!$L:$L,'Base - Non-Payroll'!$A:$A,$H62,'Base - Non-Payroll'!$B:$B," "&$H$1) -> 0 | N62: Licenses | O62: =SUMIFS('Base - Non-Payroll'!$E:$E,'Base - Non-Payroll'!$A:$A,$N62,'Base - Non-Payroll'!$B:$B," "&$N$1) -> 0 | P62: =SUMIFS('Base - Non-Payroll'!$H:$H,'Base - Non-Payroll'!$A:$A,$N62,'Base - Non-Payroll'!$B:$B," "&$N$1) -> 0 | Q62: =SUMIFS('Base - Non-Payroll'!$J:$J,'Base - Non-Payroll'!$A:$A,$N62,'Base - Non-Payroll'!$B:$B," "&$N$1) -> 0 | R62: =SUMIFS('Base - Non-Payroll'!$L:$L,'Base - Non-Payroll'!$A:$A,$N62,'Base - Non-Payroll'!$B:$B," "&$N$1) -> 0 | T62: Licenses | U62: =SUMIFS('Base - Non-Payroll'!$E:$E,'Base - Non-Payroll'!$A:$A,$T62,'Base - Non-Payroll'!$B:$B," "&$T$1) -> 0 | V62: =SUMIFS('Base - Non-Payroll'!$H:$H,'Base - Non-Payroll'!$A:$A,$T62,'Base - Non-Payroll'!$B:$B," "&$T$1) -> 0 | W62: =SUMIFS('Base - Non-Payroll'!$J:$J,'Base - Non-Payroll'!$A:$A,$T62,'Base - Non-Payroll'!$B:$B," "&$T$1) -> 0 | X62: =SUMIFS('Base - Non-Payroll'!$L:$L,'Base - Non-Payroll'!$A:$A,$T62,'Base - Non-Payroll'!$B:$B," "&$T$1) -> 0 | Z62: Licenses | AA62: =SUMIFS('Base - Non-Payroll'!$E:$E,'Base - Non-Payroll'!$A:$A,$Z62,'Base - Non-Payroll'!$B:$B," "&$Z$1) -> 0 | AB62: =SUMIFS('Base - Non-Payroll'!$H:$H,'Base - Non-Payroll'!$A:$A,$Z62,'Base - Non-Payroll'!$B:$B," "&$Z$1) -> 0 | AC62: =SUMIFS('Base - Non-Payroll'!$J:$J,'Base - Non-Payroll'!$A:$A,$Z62,'Base - Non-Payroll'!$B:$B," "&$Z$1) -> 0 | AD62: =SUMIFS('Base - Non-Payroll'!$L:$L,'Base - Non-Payroll'!$A:$A,$Z62,'Base - Non-Payroll'!$B:$B," "&$Z$1) -> 0
B63: Recruiting and Relocation | C63: =SUMIFS('Base - Non-Payroll'!$E:$E,'Base - Non-Payroll'!$A:$A,Summary!$B63) -> 83995.69 | D63: =SUMIFS('Base - Non-Payroll'!$H:$H,'Base - Non-Payroll'!$A:$A,Summary!$B63) -> 83995.69 | E63: =SUMIFS('Base - Non-Payroll'!$J:$J,'Base - Non-Payroll'!$A:$A,Summary!$B63) -> 83995.69 | F63: =SUMIFS('Base - Non-Payroll'!$L:$L,'Base - Non-Payroll'!$A:$A,Summary!$B63) -> 83995.69 | H63: Recruiting and Relocation | I63: =SUMIFS('Base - Non-Payroll'!$E:$E,'Base - Non-Payroll'!$A:$A,$H63,'Base - Non-Payroll'!$B:$B," "&$H$1) -> 63989.86 | J63: =SUMIFS('Base - Non-Payroll'!$H:$H,'Base - Non-Payroll'!$A:$A,$H63,'Base - Non-Payroll'!$B:$B," "&$H$1) -> 63989.86 | K63: =SUMIFS('Base - Non-Payroll'!$J:$J,'Base - Non-Payroll'!$A:$A,$H63,'Base - Non-Payroll'!$B:$B," "&$H$1) -> 63989.86 | L63: =SUMIFS('Base - Non-Payroll'!$L:$L,'Base - Non-Payroll'!$A:$A,$H63,'Base - Non-Payroll'!$B:$B," "&$H$1) -> 63989.86 | N63: Recruiting and Relocation | O63: =SUMIFS('Base - Non-Payroll'!$E:$E,'Base - Non-Payroll'!$A:$A,$N63,'Base - Non-Payroll'!$B:$B," "&$N$1) -> 0 | P63: =SUMIFS('Base - Non-Payroll'!$H:$H,'Base - Non-Payroll'!$A:$A,$N63,'Base - Non-Payroll'!$B:$B," "&$N$1) -> 0 | Q63: =SUMIFS('Base - Non-Payroll'!$J:$J,'Base - Non-Payroll'!$A:$A,$N63,'Base - Non-Payroll'!$B:$B," "&$N$1) -> 0 | R63: =SUMIFS('Base - Non-Payroll'!$L:$L,'Base - Non-Payroll'!$A:$A,$N63,'Base - Non-Payroll'!$B:$B," "&$N$1) -> 0 | T63: Recruiting and Relocation | U63: =SUMIFS('Base - Non-Payroll'!$E:$E,'Base - Non-Payroll'!$A:$A,$T63,'Base - Non-Payroll'!$B:$B," "&$T$1) -> 20005.83 | V63: =SUMIFS('Base - Non-Payroll'!$H:$H,'Base - Non-Payroll'!$A:$A,$T63,'Base - Non-Payroll'!$B:$B," "&$T$1) -> 20005.83 | W63: =SUMIFS('Base - Non-Payroll'!$J:$J,'Base - Non-Payroll'!$A:$A,$T63,'Base - Non-Payroll'!$B:$B," "&$T$1) -> 20005.83 | X63: =SUMIFS('Base - Non-Payroll'!$L:$L,'Base - Non-Payroll'!$A:$A,$T63,'Base - Non-Payroll'!$B:$B," "&$T$1) -> 20005.83 | Z63: Recruiting and Relocation | AA63: =SUMIFS('Base - Non-Payroll'!$E:$E,'Base - Non-Payroll'!$A:$A,$Z63,'Base - Non-Payroll'!$B:$B," "&$Z$1) -> 0 | AB63: =SUMIFS('Base - Non-Payroll'!$H:$H,'Base - Non-Payroll'!$A:$A,$Z63,'Base - Non-Payroll'!$B:$B," "&$Z$1) -> 0 | AC63: =SUMIFS('Base - Non-Payroll'!$J:$J,'Base - Non-Payroll'!$A:$A,$Z63,'Base - Non-Payroll'!$B:$B," "&$Z$1) -> 0 | AD63: =SUMIFS('Base - Non-Payroll'!$L:$L,'Base - Non-Payroll'!$A:$A,$Z63,'Base - Non-Payroll'!$B:$B," "&$Z$1) -> 0
B64: Seminars and Training | C64: =SUMIFS('Base - Non-Payroll'!$E:$E,'Base - Non-Payroll'!$A:$A,Summary!$B64) -> 251825.74 | D64: =SUMIFS('Base - Non-Payroll'!$H:$H,'Base - Non-Payroll'!$A:$A,Summary!$B64) -> 251825.74 | E64: =SUMIFS('Base - Non-Payroll'!$J:$J,'Base - Non-Payroll'!$A:$A,Summary!$B64) -> 251825.74 | F64: =SUMIFS('Base - Non-Payroll'!$L:$L,'Base - Non-Payroll'!$A:$A,Summary!$B64) -> 251825.74 | H64: Seminars and Training | I64: =SUMIFS('Base - Non-Payroll'!$E:$E,'Base - Non-Payroll'!$A:$A,$H64,'Base - Non-Payroll'!$B:$B," "&$H$1) -> 164413.16 | J64: =SUMIFS('Base - Non-Payroll'!$H:$H,'Base - Non-Payroll'!$A:$A,$H64,'Base - Non-Payroll'!$B:$B," "&$H$1) -> 164413.16 | K64: =SUMIFS('Base - Non-Payroll'!$J:$J,'Base - Non-Payroll'!$A:$A,$H64,'Base - Non-Payroll'!$B:$B," "&$H$1) -> 164413.16 | L64: =SUMIFS('Base - Non-Payroll'!$L:$L,'Base - Non-Payroll'!$A:$A,$H64,'Base - Non-Payroll'!$B:$B," "&$H$1) -> 164413.16 | N64: Seminars and Training | O64: =SUMIFS('Base - Non-Payroll'!$E:$E,'Base - Non-Payroll'!$A:$A,$N64,'Base - Non-Payroll'!$B:$B," "&$N$1) -> 48003.38 | P64: =SUMIFS('Base - Non-Payroll'!$H:$H,'Base - Non-Payroll'!$A:$A,$N64,'Base - Non-Payroll'!$B:$B," "&$N$1) -> 48003.38 | Q64: =SUMIFS('Base - Non-Payroll'!$J:$J,'Base - Non-Payroll'!$A:$A,$N64,'Base - Non-Payroll'!$B:$B," "&$N$1) -> 48003.38 | R64: =SUMIFS('Base - Non-Payroll'!$L:$L,'Base - Non-Payroll'!$A:$A,$N64,'Base - Non-Payroll'!$B:$B," "&$N$1) -> 48003.38 | T64: Seminars and Training | U64: =SUMIFS('Base - Non-Payroll'!$E:$E,'Base - Non-Payroll'!$A:$A,$T64,'Base - Non-Payroll'!$B:$B," "&$T$1) -> 34403.22 | V64: =SUMIFS('Base - Non-Payroll'!$H:$H,'Base - Non-Payroll'!$A:$A,$T64,'Base - Non-Payroll'!$B:$B," "&$T$1) -> 34403.22 | W64: =SUMIFS('Base - Non-Payroll'!$J:$J,'Base - Non-Payroll'!$A:$A,$T64,'Base - Non-Payroll'!$B:$B," "&$T$1) -> 34403.22 | X64: =SUMIFS('Base - Non-Payroll'!$L:$L,'Base - Non-Payroll'!$A:$A,$T64,'Base - Non-Payroll'!$B:$B," "&$T$1) -> 34403.22 | Z64: Seminars and Training | AA64: =SUMIFS('Base - Non-Payroll'!$E:$E,'Base - Non-Payroll'!$A:$A,$Z64,'Base - Non-Payroll'!$B:$B," "&$Z$1) -> 5005.98 | AB64: =SUMIFS('Base - Non-Payroll'!$H:$H,'Base - Non-Payroll'!$A:$A,$Z64,'Base - Non-Payroll'!$B:$B," "&$Z$1) -> 5005.98 | AC64: =SUMIFS('Base - Non-Payroll'!$J:$J,'Base - Non-Payroll'!$A:$A,$Z64,'Base - Non-Payroll'!$B:$B," "&$Z$1) -> 5005.98 | AD64: =SUMIFS('Base - Non-Payroll'!$L:$L,'Base - Non-Payroll'!$A:$A,$Z64,'Base - Non-Payroll'!$B:$B," "&$Z$1) -> 5005.98
B65: Shareholder Relations | C65: =SUMIFS('Base - Non-Payroll'!$E:$E,'Base - Non-Payroll'!$A:$A,Summary!$B65) -> 0 | D65: =SUMIFS('Base - Non-Payroll'!$H:$H,'Base - Non-Payroll'!$A:$A,Summary!$B65) -> 0 | E65: =SUMIFS('Base - Non-Payroll'!$J:$J,'Base - Non-Payroll'!$A:$A,Summary!$B65) -> 0 | F65: =SUMIFS('Base - Non-Payroll'!$L:$L,'Base - Non-Payroll'!$A:$A,Summary!$B65) -> 0 | H65: Shareholder Relations | I65: =SUMIFS('Base - Non-Payroll'!$E:$E,'Base - Non-Payroll'!$A:$A,$H65,'Base - Non-Payroll'!$B:$B," "&$H$1) -> 0 | J65: =SUMIFS('Base - Non-Payroll'!$H:$H,'Base - Non-Payroll'!$A:$A,$H65,'Base - Non-Payroll'!$B:$B," "&$H$1) -> 0 | K65: =SUMIFS('Base - Non-Payroll'!$J:$J,'Base - Non-Payroll'!$A:$A,$H65,'Base - Non-Payroll'!$B:$B," "&$H$1) -> 0 | L65: =SUMIFS('Base - Non-Payroll'!$L:$L,'Base - Non-Payroll'!$A:$A,$H65,'Base - Non-Payroll'!$B:$B," "&$H$1) -> 0 | N65: Shareholder Relations | O65: =SUMIFS('Base - Non-Payroll'!$E:$E,'Base - Non-Payroll'!$A:$A,$N65,'Base - Non-Payroll'!$B:$B," "&$N$1) -> 0 | P65: =SUMIFS('Base - Non-Payroll'!$H:$H,'Base - Non-Payroll'!$A:$A,$N65,'Base - Non-Payroll'!$B:$B," "&$N$1) -> 0 | Q65: =SUMIFS('Base - Non-Payroll'!$J:$J,'Base - Non-Payroll'!$A:$A,$N65,'Base - Non-Payroll'!$B:$B," "&$N$1) -> 0 | R65: =SUMIFS('Base - Non-Payroll'!$L:$L,'Base - Non-Payroll'!$A:$A,$N65,'Base - Non-Payroll'!$B:$B," "&$N$1) -> 0 | T65: Shareholder Relations | U65: =SUMIFS('Base - Non-Payroll'!$E:$E,'Base - Non-Payroll'!$A:$A,$T65,'Base - Non-Payroll'!$B:$B," "&$T$1) -> 0 | V65: =SUMIFS('Base - Non-Payroll'!$H:$H,'Base - Non-Payroll'!$A:$A,$T65,'Base - Non-Payroll'!$B:$B," "&$T$1) -> 0 | W65: =SUMIFS('Base - Non-Payroll'!$J:$J,'Base - Non-Payroll'!$A:$A,$T65,'Base - Non-Payroll'!$B:$B," "&$T$1) -> 0 | X65: =SUMIFS('Base - Non-Payroll'!$L:$L,'Base - Non-Payroll'!$A:$A,$T65,'Base - Non-Payroll'!$B:$B," "&$T$1) -> 0 | Z65: Shareholder Relations | AA65: =SUMIFS('Base - Non-Payroll'!$E:$E,'Base - Non-Payroll'!$A:$A,$Z65,'Base - Non-Payroll'!$B:$B," "&$Z$1) -> 0 | AB65: =SUMIFS('Base - Non-Payroll'!$H:$H,'Base - Non-Payroll'!$A:$A,$Z65,'Base - Non-Payroll'!$B:$B," "&$Z$1) -> 0 | AC65: =SUMIFS('Base - Non-Payroll'!$J:$J,'Base - Non-Payroll'!$A:$A,$Z65,'Base - Non-Payroll'!$B:$B," "&$Z$1) -> 0 | AD65: =SUMIFS('Base - Non-Payroll'!$L:$L,'Base - Non-Payroll'!$A:$A,$Z65,'Base - Non-Payroll'!$B:$B," "&$Z$1) -> 0
... B74: Allocated IT & Office Contra | C74: =SUMIFS('Base - Non-Payroll'!$E:$E,'Base - Non-Payroll'!$A:$A,Summary!$B74) -> 0 | D74: =SUMIFS('Base - Non-Payroll'!$H:$H,'Base - Non-Payroll'!$A:$A,Summary!$B74) -> 0 | E74: =SUMIFS('Base - Non-Payroll'!$J:$J,'Base - Non-Payroll'!$A:$A,Summary!$B74) -> 0 | F74: =SUMIFS('Base - Non-Payroll'!$L:$L,'Base - Non-Payroll'!$A:$A,Summary!$B74) -> 0 | H74: Allocated IT & Office Contra | I74: =SUMIFS('Base - Non-Payroll'!$E:$E,'Base - Non-Payroll'!$A:$A,$H74,'Base - Non-Payroll'!$B:$B," "&$H$1) -> 0 | J74: =SUMIFS('Base - Non-Payroll'!$H:$H,'Base - Non-Payroll'!$A:$A,$H74,'Base - Non-Payroll'!$B:$B," "&$H$1) -> 0 | K74: =SUMIFS('Base - Non-Payroll'!$J:$J,'Base - Non-Payroll'!$A:$A,$H74,'Base - Non-Payroll'!$B:$B," "&$H$1) -> 0 | L74: =SUMIFS('Base - Non-Payroll'!$L:$L,'Base - Non-Payroll'!$A:$A,$H74,'Base - Non-Payroll'!$B:$B," "&$H$1) -> 0 | N74: Allocated IT & Office Contra | O74: =SUMIFS('Base - Non-Payroll'!$E:$E,'Base - Non-Payroll'!$A:$A,$N74,'Base - Non-Payroll'!$B:$B," "&$N$1) -> 0 | P74: =SUMIFS('Base - Non-Payroll'!$H:$H,'Base - Non-Payroll'!$A:$A,$N74,'Base - Non-Payroll'!$B:$B," "&$N$1) -> 0 | Q74: =SUMIFS('Base - Non-Payroll'!$J:$J,'Base - Non-Payroll'!$A:$A,$N74,'Base - Non-Payroll'!$B:$B," "&$N$1) -> 0 | R74: =SUMIFS('Base - Non-Payroll'!$L:$L,'Base - Non-Payroll'!$A:$A,$N74,'Base - Non-Payroll'!$B:$B," "&$N$1) -> 0 | T74: Allocated IT & Office Contra | U74: =SUMIFS('Base - Non-Payroll'!$E:$E,'Base - Non-Payroll'!$A:$A,$T74,'Base - Non-Payroll'!$B:$B," "&$T$1) -> 0 | V74: =SUMIFS('Base - Non-Payroll'!$H:$H,'Base - Non-Payroll'!$A:$A,$T74,'Base - Non-Payroll'!$B:$B," "&$T$1) -> 0 | W74: =SUMIFS('Base - Non-Payroll'!$J:$J,'Base - Non-Payroll'!$A:$A,$T74,'Base - Non-Payroll'!$B:$B," "&$T$1) -> 0 | X74: =SUMIFS('Base - Non-Payroll'!$L:$L,'Base - Non-Payroll'!$A:$A,$T74,'Base - Non-Payroll'!$B:$B," "&$T$1) -> 0 | Z74: Allocated IT & Office Contra | AA74: =SUMIFS('Base - Non-Payroll'!$E:$E,'Base - Non-Payroll'!$A:$A,$Z74,'Base - Non-Payroll'!$B:$B," "&$Z$1) -> 0 | AB74: =SUMIFS('Base - Non-Payroll'!$H:$H,'Base - Non-Payroll'!$A:$A,$Z74,'Base - Non-Payroll'!$B:$B," "&$Z$1) -> 0 | AC74: =SUMIFS('Base - Non-Payroll'!$J:$J,'Base - Non-Payroll'!$A:$A,$Z74,'Base - Non-Payroll'!$B:$B," "&$Z$1) -> 0 | AD74: =SUMIFS('Base - Non-Payroll'!$L:$L,'Base - Non-Payroll'!$A:$A,$Z74,'Base - Non-Payroll'!$B:$B," "&$Z$1) -> 0
B75: Baseline Non-Payroll | C75: =SUM(C54:C74) -> 13032305 | D75: =SUM(D54:D74) -> 13032305 | E75: =SUM(E54:E74) -> 13032305 | F75: =SUM(F54:F74) -> 13032305 | H75: Baseline Non-Payroll | I75: =SUM(I54:I74) -> 5266629.5 | J75: =SUM(J54:J74) -> 5266629.5 | K75: =SUM(K54:K74) -> 5266629.5 | L75: =SUM(L54:L74) -> 5266629.5 | N75: Baseline Non-Payroll | O75: =SUM(O54:O74) -> 1050998.5 | P75: =SUM(P54:P74) -> 1050998.5 | Q75: =SUM(Q54:Q74) -> 1050998.5 | R75: =SUM(R54:R74) -> 1050998.5 | T75: Baseline Non-Payroll | U75: =SUM(U54:U74) -> 5961905.7 | V75: =SUM(V54:V74) -> 5961905.7 | W75: =SUM(W54:W74) -> 5961905.7 | X75: =SUM(X54:X74) -> 5961905.7 | Z75: Baseline Non-Payroll | AA75: =SUM(AA54:AA74) -> 752770.88 | AB75: =SUM(AB54:AB74) -> 752770.88 | AC75: =SUM(AC54:AC74) -> 752770.88 | AD75: =SUM(AD54:AD74) -> 752770.88
B77: Total | C77: =C52+C75 -> 61427583 | D77: =D52+D75 -> 63802979 | E77: =E52+E75 -> 63802979 | F77: =F52+F75 -> 63802979 | H77: Total | I77: =I52+I75 -> 34765805 | J77: =J52+J75 -> 36050150 | K77: =K52+K75 -> 36050150 | L77: =L52+L75 -> 36050150 | N77: Total | O77: =O52+O75 -> 5943823.7 | P77: =P52+P75 -> 6254018.6 | Q77: =Q52+Q75 -> 6254018.6 | R77: =R52+R75 -> 6254018.6 | T77: Total | U77: =U52+U75 -> 16225387 | V77: =V52+V75 -> 17002838 | W77: =W52+W75 -> 17002838 | X77: =X52+X75 -> 17002838 | Z77: Total | AA77: =AA52+AA75 -> 4492566.6 | AB77: =AB52+AB75 -> 4495972.6 | AC77: =AC52+AC75 -> 4495972.6 | AD77: =AD52+AD75 -> 4495972.6
B79: Incremental | H79: Incremental | N79: Incremental | T79: Incremental | Z79: Incremental
D80: 2027 Incremental Spend | E80: 2028 Incremental Spend | F80: 2029 Incremental Spend | J80: 2027 Incremental Spend | K80: 2028 Incremental Spend | L80: 2029 Incremental Spend | P80: 2027 Incremental Spend | Q80: 2028 Incremental Spend | R80: 2029 Incremental Spend | V80: 2027 Incremental Spend | W80: 2028 Incremental Spend | X80: 2029 Incremental Spend | AB80: 2027 Incremental Spend | AC80: 2028 Incremental Spend | AD80: 2029 Incremental Spend
B81: Compensation | D81: {=SUMPRODUCT(IFERROR(tblPayrollIncrementalSpend[Base Salary]*tblPayrollIncrementalSpend[2027 Incremental Spend]/(tblPayrollIncrementalSpend[Base Salary]+tblPayrollIncrementalSpend[Bonus]+tblPayrollIncrementalSpend[Payroll Taxes]+tblPayrollIncrementalSpend[Benefits]+tblPayrollIncrementalSpend[Vacation]+tblPayrollIncrementalSpend[Other]),0))} -> 0 | E81: {=SUMPRODUCT(IFERROR(tblPayrollIncrementalSpend[Base Salary]*tblPayrollIncrementalSpend[2028 Incremental Spend]/(tblPayrollIncrementalSpend[Base Salary]+tblPayrollIncrementalSpend[Bonus]+tblPayrollIncrementalSpend[Payroll Taxes]+tblPayrollIncrementalSpend[Benefits]+tblPayrollIncrementalSpend[Vacation]+tblPayrollIncrementalSpend[Other]),0))} -> 0 | F81: {=SUMPRODUCT(IFERROR(tblPayrollIncrementalSpend[Base Salary]*tblPayrollIncrementalSpend[2029 Incremental Spend]/(tblPayrollIncrementalSpend[Base Salary]+tblPayrollIncrementalSpend[Bonus]+tblPayrollIncrementalSpend[Payroll Taxes]+tblPayrollIncrementalSpend[Benefits]+tblPayrollIncrementalSpend[Vacation]+tblPayrollIncrementalSpend[Other]),0))} -> 0 | H81: Compensation | J81: {=SUMPRODUCT(IFERROR((tblPayrollIncrementalSpend[Group]=$H$1)*tblPayrollIncrementalSpend[Base Salary]*tblPayrollIncrementalSpend[2027 Incremental Spend]/(tblPayrollIncrementalSpend[Base Salary]+tblPayrollIncrementalSpend[Bonus]+tblPayrollIncrementalSpend[Payroll Taxes]+tblPayrollIncrementalSpend[Benefits]+tblPayrollIncrementalSpend[Vacation]+tblPayrollIncrementalSpend[Other]),0))} -> 0 | K81: {=SUMPRODUCT(IFERROR((tblPayrollIncrementalSpend[Group]=$H$1)*tblPayrollIncrementalSpend[Base Salary]*tblPayrollIncrementalSpend[2028 Incremental Spend]/(tblPayrollIncrementalSpend[Base Salary]+tblPayrollIncrementalSpend[Bonus]+tblPayrollIncrementalSpend[Payroll Taxes]+tblPayrollIncrementalSpend[Benefits]+tblPayrollIncrementalSpend[Vacation]+tblPayrollIncrementalSpend[Other]),0))} -> 0 | L81: {=SUMPRODUCT(IFERROR((tblPayrollIncrementalSpend[Group]=$H$1)*tblPayrollIncrementalSpend[Base Salary]*tblPayrollIncrementalSpend[2029 Incremental Spend]/(tblPayrollIncrementalSpend[Base Salary]+tblPayrollIncrementalSpend[Bonus]+tblPayrollIncrementalSpend[Payroll Taxes]+tblPayrollIncrementalSpend[Benefits]+tblPayrollIncrementalSpend[Vacation]+tblPayrollIncrementalSpend[Other]),0))} -> 0 | N81: Compensation | P81: {=SUMPRODUCT(IFERROR((tblPayrollIncrementalSpend[Group]=$N$1)*tblPayrollIncrementalSpend[Base Salary]*tblPayrollIncrementalSpend[2027 Incremental Spend]/(tblPayrollIncrementalSpend[Base Salary]+tblPayrollIncrementalSpend[Bonus]+tblPayrollIncrementalSpend[Payroll Taxes]+tblPayrollIncrementalSpend[Benefits]+tblPayrollIncrementalSpend[Vacation]+tblPayrollIncrementalSpend[Other]),0))} -> 0 | Q81: {=SUMPRODUCT(IFERROR((tblPayrollIncrementalSpend[Group]=$N$1)*tblPayrollIncrementalSpend[Base Salary]*tblPayrollIncrementalSpend[2028 Incremental Spend]/(tblPayrollIncrementalSpend[Base Salary]+tblPayrollIncrementalSpend[Bonus]+tblPayrollIncrementalSpend[Payroll Taxes]+tblPayrollIncrementalSpend[Benefits]+tblPayrollIncrementalSpend[Vacation]+tblPayrollIncrementalSpend[Other]),0))} -> 0 | R81: {=SUMPRODUCT(IFERROR((tblPayrollIncrementalSpend[Group]=$N$1)*tblPayrollIncrementalSpend[Base Salary]*tblPayrollIncrementalSpend[2029 Incremental Spend]/(tblPayrollIncrementalSpend[Base Salary]+tblPayrollIncrementalSpend[Bonus]+tblPayrollIncrementalSpend[Payroll Taxes]+tblPayrollIncrementalSpend[Benefits]+tblPayrollIncrementalSpend[Vacation]+tblPayrollIncrementalSpend[Other]),0))} -> 0 | T81: Compensation | V81: {=SUMPRODUCT(IFERROR((tblPayrollIncrementalSpend[Group]=$T$1)*tblPayrollIncrementalSpend[Base Salary]*tblPayrollIncrementalSpend[2027 Incremental Spend]/(tblPayrollIncrementalSpend[Base Salary]+tblPayrollIncrementalSpend[Bonus]+tblPayrollIncrementalSpend[Payroll Taxes]+tblPayrollIncrementalSpend[Benefits]+tblPayrollIncrementalSpend[Vacation]+tblPayrollIncrementalSpend[Other]),0))} -> 0 | W81: {=SUMPRODUCT(IFERROR((tblPayrollIncrementalSpend[Group]=$T$1)*tblPayrollIncrementalSpend[Base Salary]*tblPayrollIncrementalSpend[2028 Incremental Spend]/(tblPayrollIncrementalSpend[Base Salary]+tblPayrollIncrementalSpend[Bonus]+tblPayrollIncrementalSpend[Payroll Taxes]+tblPayrollIncrementalSpend[Benefits]+tblPayrollIncrementalSpend[Vacation]+tblPayrollIncrementalSpend[Other]),0))} -> 0 | X81: {=SUMPRODUCT(IFERROR((tblPayrollIncrementalSpend[Group]=$T$1)*tblPayrollIncrementalSpend[Base Salary]*tblPayrollIncrementalSpend[2029 Incremental Spend]/(tblPayrollIncrementalSpend[Base Salary]+tblPayrollIncrementalSpend[Bonus]+tblPayrollIncrementalSpend[Payroll Taxes]+tblPayrollIncrementalSpend[Benefits]+tblPayrollIncrementalSpend[Vacation]+tblPayrollIncrementalSpend[Other]),0))} -> 0 | Z81: Compensation | AB81: {=SUMPRODUCT(IFERROR((tblPayrollIncrementalSpend[Group]=$Z$1)*tblPayrollIncrementalSpend[Base Salary]*tblPayrollIncrementalSpend[2027 Incremental Spend]/(tblPayrollIncrementalSpend[Base Salary]+tblPayrollIncrementalSpend[Bonus]+tblPayrollIncrementalSpend[Payroll Taxes]+tblPayrollIncrementalSpend[Benefits]+tblPayrollIncrementalSpend[Vacation]+tblPayrollIncrementalSpend[Other]),0))} -> 0 | AC81: {=SUMPRODUCT(IFERROR((tblPayrollIncrementalSpend[Group]=$Z$1)*tblPayrollIncrementalSpend[Base Salary]*tblPayrollIncrementalSpend[2028 Incremental Spend]/(tblPayrollIncrementalSpend[Base Salary]+tblPayrollIncrementalSpend[Bonus]+tblPayrollIncrementalSpend[Payroll Taxes]+tblPayrollIncrementalSpend[Benefits]+tblPayrollIncrementalSpend[Vacation]+tblPayrollIncrementalSpend[Other]),0))} -> 0 | AD81: {=SUMPRODUCT(IFERROR((tblPayrollIncrementalSpend[Group]=$Z$1)*tblPayrollIncrementalSpend[Base Salary]*tblPayrollIncrementalSpend[2029 Incremental Spend]/(tblPayrollIncrementalSpend[Base Salary]+tblPayrollIncrementalSpend[Bonus]+tblPayrollIncrementalSpend[Payroll Taxes]+tblPayrollIncrementalSpend[Benefits]+tblPayrollIncrementalSpend[Vacation]+tblPayrollIncrementalSpend[Other]),0))} -> 0
B82: Bonus | D82: {=SUMPRODUCT(IFERROR(tblPayrollIncrementalSpend[Bonus]*tblPayrollIncrementalSpend[2027 Incremental Spend]/(tblPayrollIncrementalSpend[Base Salary]+tblPayrollIncrementalSpend[Bonus]+tblPayrollIncrementalSpend[Payroll Taxes]+tblPayrollIncrementalSpend[Benefits]+tblPayrollIncrementalSpend[Vacation]+tblPayrollIncrementalSpend[Other]),0))} -> 0 | E82: {=SUMPRODUCT(IFERROR(tblPayrollIncrementalSpend[Bonus]*tblPayrollIncrementalSpend[2028 Incremental Spend]/(tblPayrollIncrementalSpend[Base Salary]+tblPayrollIncrementalSpend[Bonus]+tblPayrollIncrementalSpend[Payroll Taxes]+tblPayrollIncrementalSpend[Benefits]+tblPayrollIncrementalSpend[Vacation]+tblPayrollIncrementalSpend[Other]),0))} -> 0 | F82: {=SUMPRODUCT(IFERROR(tblPayrollIncrementalSpend[Bonus]*tblPayrollIncrementalSpend[2029 Incremental Spend]/(tblPayrollIncrementalSpend[Base Salary]+tblPayrollIncrementalSpend[Bonus]+tblPayrollIncrementalSpend[Payroll Taxes]+tblPayrollIncrementalSpend[Benefits]+tblPayrollIncrementalSpend[Vacation]+tblPayrollIncrementalSpend[Other]),0))} -> 0 | H82: Bonus | J82: {=SUMPRODUCT(IFERROR((tblPayrollIncrementalSpend[Group]=$H$1)*tblPayrollIncrementalSpend[Bonus]*tblPayrollIncrementalSpend[2027 Incremental Spend]/(tblPayrollIncrementalSpend[Base Salary]+tblPayrollIncrementalSpend[Bonus]+tblPayrollIncrementalSpend[Payroll Taxes]+tblPayrollIncrementalSpend[Benefits]+tblPayrollIncrementalSpend[Vacation]+tblPayrollIncrementalSpend[Other]),0))} -> 0 | K82: {=SUMPRODUCT(IFERROR((tblPayrollIncrementalSpend[Group]=$H$1)*tblPayrollIncrementalSpend[Bonus]*tblPayrollIncrementalSpend[2028 Incremental Spend]/(tblPayrollIncrementalSpend[Base Salary]+tblPayrollIncrementalSpend[Bonus]+tblPayrollIncrementalSpend[Payroll Taxes]+tblPayrollIncrementalSpend[Benefits]+tblPayrollIncrementalSpend[Vacation]+tblPayrollIncrementalSpend[Other]),0))} -> 0 | L82: {=SUMPRODUCT(IFERROR((tblPayrollIncrementalSpend[Group]=$H$1)*tblPayrollIncrementalSpend[Bonus]*tblPayrollIncrementalSpend[2029 Incremental Spend]/(tblPayrollIncrementalSpend[Base Salary]+tblPayrollIncrementalSpend[Bonus]+tblPayrollIncrementalSpend[Payroll Taxes]+tblPayrollIncrementalSpend[Benefits]+tblPayrollIncrementalSpend[Vacation]+tblPayrollIncrementalSpend[Other]),0))} -> 0 | N82: Bonus | P82: {=SUMPRODUCT(IFERROR((tblPayrollIncrementalSpend[Group]=$N$1)*tblPayrollIncrementalSpend[Bonus]*tblPayrollIncrementalSpend[2027 Incremental Spend]/(tblPayrollIncrementalSpend[Base Salary]+tblPayrollIncrementalSpend[Bonus]+tblPayrollIncrementalSpend[Payroll Taxes]+tblPayrollIncrementalSpend[Benefits]+tblPayrollIncrementalSpend[Vacation]+tblPayrollIncrementalSpend[Other]),0))} -> 0 | Q82: {=SUMPRODUCT(IFERROR((tblPayrollIncrementalSpend[Group]=$N$1)*tblPayrollIncrementalSpend[Bonus]*tblPayrollIncrementalSpend[2028 Incremental Spend]/(tblPayrollIncrementalSpend[Base Salary]+tblPayrollIncrementalSpend[Bonus]+tblPayrollIncrementalSpend[Payroll Taxes]+tblPayrollIncrementalSpend[Benefits]+tblPayrollIncrementalSpend[Vacation]+tblPayrollIncrementalSpend[Other]),0))} -> 0 | R82: {=SUMPRODUCT(IFERROR((tblPayrollIncrementalSpend[Group]=$N$1)*tblPayrollIncrementalSpend[Bonus]*tblPayrollIncrementalSpend[2029 Incremental Spend]/(tblPayrollIncrementalSpend[Base Salary]+tblPayrollIncrementalSpend[Bonus]+tblPayrollIncrementalSpend[Payroll Taxes]+tblPayrollIncrementalSpend[Benefits]+tblPayrollIncrementalSpend[Vacation]+tblPayrollIncrementalSpend[Other]),0))} -> 0 | T82: Bonus | V82: {=SUMPRODUCT(IFERROR((tblPayrollIncrementalSpend[Group]=$T$1)*tblPayrollIncrementalSpend[Bonus]*tblPayrollIncrementalSpend[2027 Incremental Spend]/(tblPayrollIncrementalSpend[Base Salary]+tblPayrollIncrementalSpend[Bonus]+tblPayrollIncrementalSpend[Payroll Taxes]+tblPayrollIncrementalSpend[Benefits]+tblPayrollIncrementalSpend[Vacation]+tblPayrollIncrementalSpend[Other]),0))} -> 0 | W82: {=SUMPRODUCT(IFERROR((tblPayrollIncrementalSpend[Group]=$T$1)*tblPayrollIncrementalSpend[Bonus]*tblPayrollIncrementalSpend[2028 Incremental Spend]/(tblPayrollIncrementalSpend[Base Salary]+tblPayrollIncrementalSpend[Bonus]+tblPayrollIncrementalSpend[Payroll Taxes]+tblPayrollIncrementalSpend[Benefits]+tblPayrollIncrementalSpend[Vacation]+tblPayrollIncrementalSpend[Other]),0))} -> 0 | X82: {=SUMPRODUCT(IFERROR((tblPayrollIncrementalSpend[Group]=$T$1)*tblPayrollIncrementalSpend[Bonus]*tblPayrollIncrementalSpend[2029 Incremental Spend]/(tblPayrollIncrementalSpend[Base Salary]+tblPayrollIncrementalSpend[Bonus]+tblPayrollIncrementalSpend[Payroll Taxes]+tblPayrollIncrementalSpend[Benefits]+tblPayrollIncrementalSpend[Vacation]+tblPayrollIncrementalSpend[Other]),0))} -> 0 | Z82: Bonus | AB82: {=SUMPRODUCT(IFERROR((tblPayrollIncrementalSpend[Group]=$Z$1)*tblPayrollIncrementalSpend[Bonus]*tblPayrollIncrementalSpend[2027 Incremental Spend]/(tblPayrollIncrementalSpend[Base Salary]+tblPayrollIncrementalSpend[Bonus]+tblPayrollIncrementalSpend[Payroll Taxes]+tblPayrollIncrementalSpend[Benefits]+tblPayrollIncrementalSpend[Vacation]+tblPayrollIncrementalSpend[Other]),0))} -> 0 | AC82: {=SUMPRODUCT(IFERROR((tblPayrollIncrementalSpend[Group]=$Z$1)*tblPayrollIncrementalSpend[Bonus]*tblPayrollIncrementalSpend[2028 Incremental Spend]/(tblPayrollIncrementalSpend[Base Salary]+tblPayrollIncrementalSpend[Bonus]+tblPayrollIncrementalSpend[Payroll Taxes]+tblPayrollIncrementalSpend[Benefits]+tblPayrollIncrementalSpend[Vacation]+tblPayrollIncrementalSpend[Other]),0))} -> 0 | AD82: {=SUMPRODUCT(IFERROR((tblPayrollIncrementalSpend[Group]=$Z$1)*tblPayrollIncrementalSpend[Bonus]*tblPayrollIncrementalSpend[2029 Incremental Spend]/(tblPayrollIncrementalSpend[Base Salary]+tblPayrollIncrementalSpend[Bonus]+tblPayrollIncrementalSpend[Payroll Taxes]+tblPayrollIncrementalSpend[Benefits]+tblPayrollIncrementalSpend[Vacation]+tblPayrollIncrementalSpend[Other]),0))} -> 0
B83: Essentials Bonus | D83: =SUMIF(tblNonPayrollIncrementalSpend[Type of Expense],$B83,tblNonPayrollIncrementalSpend[2027 Incremental Spend]) -> 0 | E83: =SUMIF(tblNonPayrollIncrementalSpend3[Type of Expense],$B83,tblNonPayrollIncrementalSpend3[2028 Incremental Spend]) -> 0 | F83: =SUMIF(tblNonPayrollIncrementalSpend3[Type of Expense],$B83,tblNonPayrollIncrementalSpend3[2029 Incremental Spend]) -> 0 | H83: Essentials Bonus | J83: =SUMIFS(tblNonPayrollIncrementalSpend[2027 Incremental Spend],tblNonPayrollIncrementalSpend[Type of Expense],$H83,tblNonPayrollIncrementalSpend[Group],$H$1) -> 0 | K83: =SUMIFS(tblNonPayrollIncrementalSpend[2028 Incremental Spend],tblNonPayrollIncrementalSpend[Type of Expense],$H83,tblNonPayrollIncrementalSpend[Group],$H$1) -> 0 | L83: =SUMIFS(tblNonPayrollIncrementalSpend[2029 Incremental Spend],tblNonPayrollIncrementalSpend[Type of Expense],$H83,tblNonPayrollIncrementalSpend[Group],$H$1) -> 0 | N83: Essentials Bonus | P83: =SUMIFS(tblNonPayrollIncrementalSpend[2027 Incremental Spend],tblNonPayrollIncrementalSpend[Type of Expense],$N83,tblNonPayrollIncrementalSpend[Group],$N$1) -> 0 | Q83: =SUMIFS(tblNonPayrollIncrementalSpend[2028 Incremental Spend],tblNonPayrollIncrementalSpend[Type of Expense],$N83,tblNonPayrollIncrementalSpend[Group],$N$1) -> 0 | R83: =SUMIFS(tblNonPayrollIncrementalSpend[2029 Incremental Spend],tblNonPayrollIncrementalSpend[Type of Expense],$N83,tblNonPayrollIncrementalSpend[Group],$N$1) -> 0 | T83: Essentials Bonus | V83: =SUMIFS(tblNonPayrollIncrementalSpend[2027 Incremental Spend],tblNonPayrollIncrementalSpend[Type of Expense],$T83,tblNonPayrollIncrementalSpend[Group],$T$1) -> 0 | W83: =SUMIFS(tblNonPayrollIncrementalSpend[2028 Incremental Spend],tblNonPayrollIncrementalSpend[Type of Expense],$T83,tblNonPayrollIncrementalSpend[Group],$T$1) -> 0 | X83: =SUMIFS(tblNonPayrollIncrementalSpend[2029 Incremental Spend],tblNonPayrollIncrementalSpend[Type of Expense],$T83,tblNonPayrollIncrementalSpend[Group],$T$1) -> 0 | Z83: Essentials Bonus | AB83: =SUMIFS(tblNonPayrollIncrementalSpend[2027 Incremental Spend],tblNonPayrollIncrementalSpend[Type of Expense],$Z83,tblNonPayrollIncrementalSpend[Group],$Z$1) -> 0 | AC83: =SUMIFS(tblNonPayrollIncrementalSpend[2028 Incremental Spend],tblNonPayrollIncrementalSpend[Type of Expense],$Z83,tblNonPayrollIncrementalSpend[Group],$Z$1) -> 0 | AD83: =SUMIFS(tblNonPayrollIncrementalSpend[2029 Incremental Spend],tblNonPayrollIncrementalSpend[Type of Expense],$Z83,tblNonPayrollIncrementalSpend[Group],$Z$1) -> 0
B84: Payroll Taxes | D84: {=SUMPRODUCT(IFERROR(tblPayrollIncrementalSpend[Payroll Taxes]*tblPayrollIncrementalSpend[2027 Incremental Spend]/(tblPayrollIncrementalSpend[Base Salary]+tblPayrollIncrementalSpend[Bonus]+tblPayrollIncrementalSpend[Payroll Taxes]+tblPayrollIncrementalSpend[Benefits]+tblPayrollIncrementalSpend[Vacation]+tblPayrollIncrementalSpend[Other]),0))} -> 0 | E84: {=SUMPRODUCT(IFERROR(tblPayrollIncrementalSpend[Payroll Taxes]*tblPayrollIncrementalSpend[2028 Incremental Spend]/(tblPayrollIncrementalSpend[Base Salary]+tblPayrollIncrementalSpend[Bonus]+tblPayrollIncrementalSpend[Payroll Taxes]+tblPayrollIncrementalSpend[Benefits]+tblPayrollIncrementalSpend[Vacation]+tblPayrollIncrementalSpend[Other]),0))} -> 0 | F84: {=SUMPRODUCT(IFERROR(tblPayrollIncrementalSpend[Payroll Taxes]*tblPayrollIncrementalSpend[2029 Incremental Spend]/(tblPayrollIncrementalSpend[Base Salary]+tblPayrollIncrementalSpend[Bonus]+tblPayrollIncrementalSpend[Payroll Taxes]+tblPayrollIncrementalSpend[Benefits]+tblPayrollIncrementalSpend[Vacation]+tblPayrollIncrementalSpend[Other]),0))} -> 0 | H84: Payroll Taxes | J84: {=SUMPRODUCT(IFERROR((tblPayrollIncrementalSpend[Group]=$H$1)*tblPayrollIncrementalSpend[Payroll Taxes]*tblPayrollIncrementalSpend[2027 Incremental Spend]/(tblPayrollIncrementalSpend[Base Salary]+tblPayrollIncrementalSpend[Bonus]+tblPayrollIncrementalSpend[Payroll Taxes]+tblPayrollIncrementalSpend[Benefits]+tblPayrollIncrementalSpend[Vacation]+tblPayrollIncrementalSpend[Other]),0))} -> 0 | K84: {=SUMPRODUCT(IFERROR((tblPayrollIncrementalSpend[Group]=$H$1)*tblPayrollIncrementalSpend[Payroll Taxes]*tblPayrollIncrementalSpend[2028 Incremental Spend]/(tblPayrollIncrementalSpend[Base Salary]+tblPayrollIncrementalSpend[Bonus]+tblPayrollIncrementalSpend[Payroll Taxes]+tblPayrollIncrementalSpend[Benefits]+tblPayrollIncrementalSpend[Vacation]+tblPayrollIncrementalSpend[Other]),0))} -> 0 | L84: {=SUMPRODUCT(IFERROR((tblPayrollIncrementalSpend[Group]=$H$1)*tblPayrollIncrementalSpend[Payroll Taxes]*tblPayrollIncrementalSpend[2029 Incremental Spend]/(tblPayrollIncrementalSpend[Base Salary]+tblPayrollIncrementalSpend[Bonus]+tblPayrollIncrementalSpend[Payroll Taxes]+tblPayrollIncrementalSpend[Benefits]+tblPayrollIncrementalSpend[Vacation]+tblPayrollIncrementalSpend[Other]),0))} -> 0 | N84: Payroll Taxes | P84: {=SUMPRODUCT(IFERROR((tblPayrollIncrementalSpend[Group]=$N$1)*tblPayrollIncrementalSpend[Payroll Taxes]*tblPayrollIncrementalSpend[2027 Incremental Spend]/(tblPayrollIncrementalSpend[Base Salary]+tblPayrollIncrementalSpend[Bonus]+tblPayrollIncrementalSpend[Payroll Taxes]+tblPayrollIncrementalSpend[Benefits]+tblPayrollIncrementalSpend[Vacation]+tblPayrollIncrementalSpend[Other]),0))} -> 0 | Q84: {=SUMPRODUCT(IFERROR((tblPayrollIncrementalSpend[Group]=$N$1)*tblPayrollIncrementalSpend[Payroll Taxes]*tblPayrollIncrementalSpend[2028 Incremental Spend]/(tblPayrollIncrementalSpend[Base Salary]+tblPayrollIncrementalSpend[Bonus]+tblPayrollIncrementalSpend[Payroll Taxes]+tblPayrollIncrementalSpend[Benefits]+tblPayrollIncrementalSpend[Vacation]+tblPayrollIncrementalSpend[Other]),0))} -> 0 | R84: {=SUMPRODUCT(IFERROR((tblPayrollIncrementalSpend[Group]=$N$1)*tblPayrollIncrementalSpend[Payroll Taxes]*tblPayrollIncrementalSpend[2029 Incremental Spend]/(tblPayrollIncrementalSpend[Base Salary]+tblPayrollIncrementalSpend[Bonus]+tblPayrollIncrementalSpend[Payroll Taxes]+tblPayrollIncrementalSpend[Benefits]+tblPayrollIncrementalSpend[Vacation]+tblPayrollIncrementalSpend[Other]),0))} -> 0 | T84: Payroll Taxes | V84: {=SUMPRODUCT(IFERROR((tblPayrollIncrementalSpend[Group]=$T$1)*tblPayrollIncrementalSpend[Payroll Taxes]*tblPayrollIncrementalSpend[2027 Incremental Spend]/(tblPayrollIncrementalSpend[Base Salary]+tblPayrollIncrementalSpend[Bonus]+tblPayrollIncrementalSpend[Payroll Taxes]+tblPayrollIncrementalSpend[Benefits]+tblPayrollIncrementalSpend[Vacation]+tblPayrollIncrementalSpend[Other]),0))} -> 0 | W84: {=SUMPRODUCT(IFERROR((tblPayrollIncrementalSpend[Group]=$T$1)*tblPayrollIncrementalSpend[Payroll Taxes]*tblPayrollIncrementalSpend[2028 Incremental Spend]/(tblPayrollIncrementalSpend[Base Salary]+tblPayrollIncrementalSpend[Bonus]+tblPayrollIncrementalSpend[Payroll Taxes]+tblPayrollIncrementalSpend[Benefits]+tblPayrollIncrementalSpend[Vacation]+tblPayrollIncrementalSpend[Other]),0))} -> 0 | X84: {=SUMPRODUCT(IFERROR((tblPayrollIncrementalSpend[Group]=$T$1)*tblPayrollIncrementalSpend[Payroll Taxes]*tblPayrollIncrementalSpend[2029 Incremental Spend]/(tblPayrollIncrementalSpend[Base Salary]+tblPayrollIncrementalSpend[Bonus]+tblPayrollIncrementalSpend[Payroll Taxes]+tblPayrollIncrementalSpend[Benefits]+tblPayrollIncrementalSpend[Vacation]+tblPayrollIncrementalSpend[Other]),0))} -> 0 | Z84: Payroll Taxes | AB84: {=SUMPRODUCT(IFERROR((tblPayrollIncrementalSpend[Group]=$Z$1)*tblPayrollIncrementalSpend[Payroll Taxes]*tblPayrollIncrementalSpend[2027 Incremental Spend]/(tblPayrollIncrementalSpend[Base Salary]+tblPayrollIncrementalSpend[Bonus]+tblPayrollIncrementalSpend[Payroll Taxes]+tblPayrollIncrementalSpend[Benefits]+tblPayrollIncrementalSpend[Vacation]+tblPayrollIncrementalSpend[Other]),0))} -> 0 | AC84: {=SUMPRODUCT(IFERROR((tblPayrollIncrementalSpend[Group]=$Z$1)*tblPayrollIncrementalSpend[Payroll Taxes]*tblPayrollIncrementalSpend[2028 Incremental Spend]/(tblPayrollIncrementalSpend[Base Salary]+tblPayrollIncrementalSpend[Bonus]+tblPayrollIncrementalSpend[Payroll Taxes]+tblPayrollIncrementalSpend[Benefits]+tblPayrollIncrementalSpend[Vacation]+tblPayrollIncrementalSpend[Other]),0))} -> 0 | AD84: {=SUMPRODUCT(IFERROR((tblPayrollIncrementalSpend[Group]=$Z$1)*tblPayrollIncrementalSpend[Payroll Taxes]*tblPayrollIncrementalSpend[2029 Incremental Spend]/(tblPayrollIncrementalSpend[Base Salary]+tblPayrollIncrementalSpend[Bonus]+tblPayrollIncrementalSpend[Payroll Taxes]+tblPayrollIncrementalSpend[Benefits]+tblPayrollIncrementalSpend[Vacation]+tblPayrollIncrementalSpend[Other]),0))} -> 0
B85: Benefits | D85: {=SUMPRODUCT(IFERROR(tblPayrollIncrementalSpend[Benefits]*tblPayrollIncrementalSpend[2027 Incremental Spend]/(tblPayrollIncrementalSpend[Base Salary]+tblPayrollIncrementalSpend[Bonus]+tblPayrollIncrementalSpend[Payroll Taxes]+tblPayrollIncrementalSpend[Benefits]+tblPayrollIncrementalSpend[Vacation]+tblPayrollIncrementalSpend[Other]),0))} -> 0 | E85: {=SUMPRODUCT(IFERROR(tblPayrollIncrementalSpend[Benefits]*tblPayrollIncrementalSpend[2028 Incremental Spend]/(tblPayrollIncrementalSpend[Base Salary]+tblPayrollIncrementalSpend[Bonus]+tblPayrollIncrementalSpend[Payroll Taxes]+tblPayrollIncrementalSpend[Benefits]+tblPayrollIncrementalSpend[Vacation]+tblPayrollIncrementalSpend[Other]),0))} -> 0 | F85: {=SUMPRODUCT(IFERROR(tblPayrollIncrementalSpend[Benefits]*tblPayrollIncrementalSpend[2029 Incremental Spend]/(tblPayrollIncrementalSpend[Base Salary]+tblPayrollIncrementalSpend[Bonus]+tblPayrollIncrementalSpend[Payroll Taxes]+tblPayrollIncrementalSpend[Benefits]+tblPayrollIncrementalSpend[Vacation]+tblPayrollIncrementalSpend[Other]),0))} -> 0 | H85: Benefits | J85: {=SUMPRODUCT(IFERROR((tblPayrollIncrementalSpend[Group]=$H$1)*tblPayrollIncrementalSpend[Benefits]*tblPayrollIncrementalSpend[2027 Incremental Spend]/(tblPayrollIncrementalSpend[Base Salary]+tblPayrollIncrementalSpend[Bonus]+tblPayrollIncrementalSpend[Payroll Taxes]+tblPayrollIncrementalSpend[Benefits]+tblPayrollIncrementalSpend[Vacation]+tblPayrollIncrementalSpend[Other]),0))} -> 0 | K85: {=SUMPRODUCT(IFERROR((tblPayrollIncrementalSpend[Group]=$H$1)*tblPayrollIncrementalSpend[Benefits]*tblPayrollIncrementalSpend[2028 Incremental Spend]/(tblPayrollIncrementalSpend[Base Salary]+tblPayrollIncrementalSpend[Bonus]+tblPayrollIncrementalSpend[Payroll Taxes]+tblPayrollIncrementalSpend[Benefits]+tblPayrollIncrementalSpend[Vacation]+tblPayrollIncrementalSpend[Other]),0))} -> 0 | L85: {=SUMPRODUCT(IFERROR((tblPayrollIncrementalSpend[Group]=$H$1)*tblPayrollIncrementalSpend[Benefits]*tblPayrollIncrementalSpend[2029 Incremental Spend]/(tblPayrollIncrementalSpend[Base Salary]+tblPayrollIncrementalSpend[Bonus]+tblPayrollIncrementalSpend[Payroll Taxes]+tblPayrollIncrementalSpend[Benefits]+tblPayrollIncrementalSpend[Vacation]+tblPayrollIncrementalSpend[Other]),0))} -> 0 | N85: Benefits | P85: {=SUMPRODUCT(IFERROR((tblPayrollIncrementalSpend[Group]=$N$1)*tblPayrollIncrementalSpend[Benefits]*tblPayrollIncrementalSpend[2027 Incremental Spend]/(tblPayrollIncrementalSpend[Base Salary]+tblPayrollIncrementalSpend[Bonus]+tblPayrollIncrementalSpend[Payroll Taxes]+tblPayrollIncrementalSpend[Benefits]+tblPayrollIncrementalSpend[Vacation]+tblPayrollIncrementalSpend[Other]),0))} -> 0 | Q85: {=SUMPRODUCT(IFERROR((tblPayrollIncrementalSpend[Group]=$N$1)*tblPayrollIncrementalSpend[Benefits]*tblPayrollIncrementalSpend[2028 Incremental Spend]/(tblPayrollIncrementalSpend[Base Salary]+tblPayrollIncrementalSpend[Bonus]+tblPayrollIncrementalSpend[Payroll Taxes]+tblPayrollIncrementalSpend[Benefits]+tblPayrollIncrementalSpend[Vacation]+tblPayrollIncrementalSpend[Other]),0))} -> 0 | R85: {=SUMPRODUCT(IFERROR((tblPayrollIncrementalSpend[Group]=$N$1)*tblPayrollIncrementalSpend[Benefits]*tblPayrollIncrementalSpend[2029 Incremental Spend]/(tblPayrollIncrementalSpend[Base Salary]+tblPayrollIncrementalSpend[Bonus]+tblPayrollIncrementalSpend[Payroll Taxes]+tblPayrollIncrementalSpend[Benefits]+tblPayrollIncrementalSpend[Vacation]+tblPayrollIncrementalSpend[Other]),0))} -> 0 | T85: Benefits | V85: {=SUMPRODUCT(IFERROR((tblPayrollIncrementalSpend[Group]=$T$1)*tblPayrollIncrementalSpend[Benefits]*tblPayrollIncrementalSpend[2027 Incremental Spend]/(tblPayrollIncrementalSpend[Base Salary]+tblPayrollIncrementalSpend[Bonus]+tblPayrollIncrementalSpend[Payroll Taxes]+tblPayrollIncrementalSpend[Benefits]+tblPayrollIncrementalSpend[Vacation]+tblPayrollIncrementalSpend[Other]),0))} -> 0 | W85: {=SUMPRODUCT(IFERROR((tblPayrollIncrementalSpend[Group]=$T$1)*tblPayrollIncrementalSpend[Benefits]*tblPayrollIncrementalSpend[2028 Incremental Spend]/(tblPayrollIncrementalSpend[Base Salary]+tblPayrollIncrementalSpend[Bonus]+tblPayrollIncrementalSpend[Payroll Taxes]+tblPayrollIncrementalSpend[Benefits]+tblPayrollIncrementalSpend[Vacation]+tblPayrollIncrementalSpend[Other]),0))} -> 0 | X85: {=SUMPRODUCT(IFERROR((tblPayrollIncrementalSpend[Group]=$T$1)*tblPayrollIncrementalSpend[Benefits]*tblPayrollIncrementalSpend[2029 Incremental Spend]/(tblPayrollIncrementalSpend[Base Salary]+tblPayrollIncrementalSpend[Bonus]+tblPayrollIncrementalSpend[Payroll Taxes]+tblPayrollIncrementalSpend[Benefits]+tblPayrollIncrementalSpend[Vacation]+tblPayrollIncrementalSpend[Other]),0))} -> 0 | Z85: Benefits | AB85: {=SUMPRODUCT(IFERROR((tblPayrollIncrementalSpend[Group]=$Z$1)*tblPayrollIncrementalSpend[Benefits]*tblPayrollIncrementalSpend[2027 Incremental Spend]/(tblPayrollIncrementalSpend[Base Salary]+tblPayrollIncrementalSpend[Bonus]+tblPayrollIncrementalSpend[Payroll Taxes]+tblPayrollIncrementalSpend[Benefits]+tblPayrollIncrementalSpend[Vacation]+tblPayrollIncrementalSpend[Other]),0))} -> 0 | AC85: {=SUMPRODUCT(IFERROR((tblPayrollIncrementalSpend[Group]=$Z$1)*tblPayrollIncrementalSpend[Benefits]*tblPayrollIncrementalSpend[2028 Incremental Spend]/(tblPayrollIncrementalSpend[Base Salary]+tblPayrollIncrementalSpend[Bonus]+tblPayrollIncrementalSpend[Payroll Taxes]+tblPayrollIncrementalSpend[Benefits]+tblPayrollIncrementalSpend[Vacation]+tblPayrollIncrementalSpend[Other]),0))} -> 0 | AD85: {=SUMPRODUCT(IFERROR((tblPayrollIncrementalSpend[Group]=$Z$1)*tblPayrollIncrementalSpend[Benefits]*tblPayrollIncrementalSpend[2029 Incremental Spend]/(tblPayrollIncrementalSpend[Base Salary]+tblPayrollIncrementalSpend[Bonus]+tblPayrollIncrementalSpend[Payroll Taxes]+tblPayrollIncrementalSpend[Benefits]+tblPayrollIncrementalSpend[Vacation]+tblPayrollIncrementalSpend[Other]),0))} -> 0
B86: Vacation | D86: {=SUMPRODUCT(IFERROR(tblPayrollIncrementalSpend[Vacation]*tblPayrollIncrementalSpend[2027 Incremental Spend]/(tblPayrollIncrementalSpend[Base Salary]+tblPayrollIncrementalSpend[Bonus]+tblPayrollIncrementalSpend[Payroll Taxes]+tblPayrollIncrementalSpend[Benefits]+tblPayrollIncrementalSpend[Vacation]+tblPayrollIncrementalSpend[Other]),0))} -> 0 | E86: {=SUMPRODUCT(IFERROR(tblPayrollIncrementalSpend[Vacation]*tblPayrollIncrementalSpend[2028 Incremental Spend]/(tblPayrollIncrementalSpend[Base Salary]+tblPayrollIncrementalSpend[Bonus]+tblPayrollIncrementalSpend[Payroll Taxes]+tblPayrollIncrementalSpend[Benefits]+tblPayrollIncrementalSpend[Vacation]+tblPayrollIncrementalSpend[Other]),0))} -> 0 | F86: {=SUMPRODUCT(IFERROR(tblPayrollIncrementalSpend[Vacation]*tblPayrollIncrementalSpend[2029 Incremental Spend]/(tblPayrollIncrementalSpend[Base Salary]+tblPayrollIncrementalSpend[Bonus]+tblPayrollIncrementalSpend[Payroll Taxes]+tblPayrollIncrementalSpend[Benefits]+tblPayrollIncrementalSpend[Vacation]+tblPayrollIncrementalSpend[Other]),0))} -> 0 | H86: Vacation | J86: {=SUMPRODUCT(IFERROR((tblPayrollIncrementalSpend[Group]=$H$1)*tblPayrollIncrementalSpend[Vacation]*tblPayrollIncrementalSpend[2027 Incremental Spend]/(tblPayrollIncrementalSpend[Base Salary]+tblPayrollIncrementalSpend[Bonus]+tblPayrollIncrementalSpend[Payroll Taxes]+tblPayrollIncrementalSpend[Benefits]+tblPayrollIncrementalSpend[Vacation]+tblPayrollIncrementalSpend[Other]),0))} -> 0 | K86: {=SUMPRODUCT(IFERROR((tblPayrollIncrementalSpend[Group]=$H$1)*tblPayrollIncrementalSpend[Vacation]*tblPayrollIncrementalSpend[2028 Incremental Spend]/(tblPayrollIncrementalSpend[Base Salary]+tblPayrollIncrementalSpend[Bonus]+tblPayrollIncrementalSpend[Payroll Taxes]+tblPayrollIncrementalSpend[Benefits]+tblPayrollIncrementalSpend[Vacation]+tblPayrollIncrementalSpend[Other]),0))} -> 0 | L86: {=SUMPRODUCT(IFERROR((tblPayrollIncrementalSpend[Group]=$H$1)*tblPayrollIncrementalSpend[Vacation]*tblPayrollIncrementalSpend[2029 Incremental Spend]/(tblPayrollIncrementalSpend[Base Salary]+tblPayrollIncrementalSpend[Bonus]+tblPayrollIncrementalSpend[Payroll Taxes]+tblPayrollIncrementalSpend[Benefits]+tblPayrollIncrementalSpend[Vacation]+tblPayrollIncrementalSpend[Other]),0))} -> 0 | N86: Vacation | P86: {=SUMPRODUCT(IFERROR((tblPayrollIncrementalSpend[Group]=$N$1)*tblPayrollIncrementalSpend[Vacation]*tblPayrollIncrementalSpend[2027 Incremental Spend]/(tblPayrollIncrementalSpend[Base Salary]+tblPayrollIncrementalSpend[Bonus]+tblPayrollIncrementalSpend[Payroll Taxes]+tblPayrollIncrementalSpend[Benefits]+tblPayrollIncrementalSpend[Vacation]+tblPayrollIncrementalSpend[Other]),0))} -> 0 | Q86: {=SUMPRODUCT(IFERROR((tblPayrollIncrementalSpend[Group]=$N$1)*tblPayrollIncrementalSpend[Vacation]*tblPayrollIncrementalSpend[2028 Incremental Spend]/(tblPayrollIncrementalSpend[Base Salary]+tblPayrollIncrementalSpend[Bonus]+tblPayrollIncrementalSpend[Payroll Taxes]+tblPayrollIncrementalSpend[Benefits]+tblPayrollIncrementalSpend[Vacation]+tblPayrollIncrementalSpend[Other]),0))} -> 0 | R86: {=SUMPRODUCT(IFERROR((tblPayrollIncrementalSpend[Group]=$N$1)*tblPayrollIncrementalSpend[Vacation]*tblPayrollIncrementalSpend[2029 Incremental Spend]/(tblPayrollIncrementalSpend[Base Salary]+tblPayrollIncrementalSpend[Bonus]+tblPayrollIncrementalSpend[Payroll Taxes]+tblPayrollIncrementalSpend[Benefits]+tblPayrollIncrementalSpend[Vacation]+tblPayrollIncrementalSpend[Other]),0))} -> 0 | T86: Vacation | V86: {=SUMPRODUCT(IFERROR((tblPayrollIncrementalSpend[Group]=$T$1)*tblPayrollIncrementalSpend[Vacation]*tblPayrollIncrementalSpend[2027 Incremental Spend]/(tblPayrollIncrementalSpend[Base Salary]+tblPayrollIncrementalSpend[Bonus]+tblPayrollIncrementalSpend[Payroll Taxes]+tblPayrollIncrementalSpend[Benefits]+tblPayrollIncrementalSpend[Vacation]+tblPayrollIncrementalSpend[Other]),0))} -> 0 | W86: {=SUMPRODUCT(IFERROR((tblPayrollIncrementalSpend[Group]=$T$1)*tblPayrollIncrementalSpend[Vacation]*tblPayrollIncrementalSpend[2028 Incremental Spend]/(tblPayrollIncrementalSpend[Base Salary]+tblPayrollIncrementalSpend[Bonus]+tblPayrollIncrementalSpend[Payroll Taxes]+tblPayrollIncrementalSpend[Benefits]+tblPayrollIncrementalSpend[Vacation]+tblPayrollIncrementalSpend[Other]),0))} -> 0 | X86: {=SUMPRODUCT(IFERROR((tblPayrollIncrementalSpend[Group]=$T$1)*tblPayrollIncrementalSpend[Vacation]*tblPayrollIncrementalSpend[2029 Incremental Spend]/(tblPayrollIncrementalSpend[Base Salary]+tblPayrollIncrementalSpend[Bonus]+tblPayrollIncrementalSpend[Payroll Taxes]+tblPayrollIncrementalSpend[Benefits]+tblPayrollIncrementalSpend[Vacation]+tblPayrollIncrementalSpend[Other]),0))} -> 0 | Z86: Vacation | AB86: {=SUMPRODUCT(IFERROR((tblPayrollIncrementalSpend[Group]=$Z$1)*tblPayrollIncrementalSpend[Vacation]*tblPayrollIncrementalSpend[2027 Incremental Spend]/(tblPayrollIncrementalSpend[Base Salary]+tblPayrollIncrementalSpend[Bonus]+tblPayrollIncrementalSpend[Payroll Taxes]+tblPayrollIncrementalSpend[Benefits]+tblPayrollIncrementalSpend[Vacation]+tblPayrollIncrementalSpend[Other]),0))} -> 0 | AC86: {=SUMPRODUCT(IFERROR((tblPayrollIncrementalSpend[Group]=$Z$1)*tblPayrollIncrementalSpend[Vacation]*tblPayrollIncrementalSpend[2028 Incremental Spend]/(tblPayrollIncrementalSpend[Base Salary]+tblPayrollIncrementalSpend[Bonus]+tblPayrollIncrementalSpend[Payroll Taxes]+tblPayrollIncrementalSpend[Benefits]+tblPayrollIncrementalSpend[Vacation]+tblPayrollIncrementalSpend[Other]),0))} -> 0 | AD86: {=SUMPRODUCT(IFERROR((tblPayrollIncrementalSpend[Group]=$Z$1)*tblPayrollIncrementalSpend[Vacation]*tblPayrollIncrementalSpend[2029 Incremental Spend]/(tblPayrollIncrementalSpend[Base Salary]+tblPayrollIncrementalSpend[Bonus]+tblPayrollIncrementalSpend[Payroll Taxes]+tblPayrollIncrementalSpend[Benefits]+tblPayrollIncrementalSpend[Vacation]+tblPayrollIncrementalSpend[Other]),0))} -> 0
B87: Other | D87: {=SUMPRODUCT(IFERROR(tblPayrollIncrementalSpend[Other]*tblPayrollIncrementalSpend[2027 Incremental Spend]/(tblPayrollIncrementalSpend[Base Salary]+tblPayrollIncrementalSpend[Bonus]+tblPayrollIncrementalSpend[Payroll Taxes]+tblPayrollIncrementalSpend[Benefits]+tblPayrollIncrementalSpend[Vacation]+tblPayrollIncrementalSpend[Other]),0))} -> 0 | E87: {=SUMPRODUCT(IFERROR(tblPayrollIncrementalSpend[Other]*tblPayrollIncrementalSpend[2028 Incremental Spend]/(tblPayrollIncrementalSpend[Base Salary]+tblPayrollIncrementalSpend[Bonus]+tblPayrollIncrementalSpend[Payroll Taxes]+tblPayrollIncrementalSpend[Benefits]+tblPayrollIncrementalSpend[Vacation]+tblPayrollIncrementalSpend[Other]),0))} -> 0 | F87: {=SUMPRODUCT(IFERROR(tblPayrollIncrementalSpend[Other]*tblPayrollIncrementalSpend[2029 Incremental Spend]/(tblPayrollIncrementalSpend[Base Salary]+tblPayrollIncrementalSpend[Bonus]+tblPayrollIncrementalSpend[Payroll Taxes]+tblPayrollIncrementalSpend[Benefits]+tblPayrollIncrementalSpend[Vacation]+tblPayrollIncrementalSpend[Other]),0))} -> 0 | H87: Other | J87: {=SUMPRODUCT(IFERROR((tblPayrollIncrementalSpend[Group]=$H$1)*tblPayrollIncrementalSpend[Other]*tblPayrollIncrementalSpend[2027 Incremental Spend]/(tblPayrollIncrementalSpend[Base Salary]+tblPayrollIncrementalSpend[Bonus]+tblPayrollIncrementalSpend[Payroll Taxes]+tblPayrollIncrementalSpend[Benefits]+tblPayrollIncrementalSpend[Vacation]+tblPayrollIncrementalSpend[Other]),0))} -> 0 | K87: {=SUMPRODUCT(IFERROR((tblPayrollIncrementalSpend[Group]=$H$1)*tblPayrollIncrementalSpend[Other]*tblPayrollIncrementalSpend[2028 Incremental Spend]/(tblPayrollIncrementalSpend[Base Salary]+tblPayrollIncrementalSpend[Bonus]+tblPayrollIncrementalSpend[Payroll Taxes]+tblPayrollIncrementalSpend[Benefits]+tblPayrollIncrementalSpend[Vacation]+tblPayrollIncrementalSpend[Other]),0))} -> 0 | L87: {=SUMPRODUCT(IFERROR((tblPayrollIncrementalSpend[Group]=$H$1)*tblPayrollIncrementalSpend[Other]*tblPayrollIncrementalSpend[2029 Incremental Spend]/(tblPayrollIncrementalSpend[Base Salary]+tblPayrollIncrementalSpend[Bonus]+tblPayrollIncrementalSpend[Payroll Taxes]+tblPayrollIncrementalSpend[Benefits]+tblPayrollIncrementalSpend[Vacation]+tblPayrollIncrementalSpend[Other]),0))} -> 0 | N87: Other | P87: {=SUMPRODUCT(IFERROR((tblPayrollIncrementalSpend[Group]=$N$1)*tblPayrollIncrementalSpend[Other]*tblPayrollIncrementalSpend[2027 Incremental Spend]/(tblPayrollIncrementalSpend[Base Salary]+tblPayrollIncrementalSpend[Bonus]+tblPayrollIncrementalSpend[Payroll Taxes]+tblPayrollIncrementalSpend[Benefits]+tblPayrollIncrementalSpend[Vacation]+tblPayrollIncrementalSpend[Other]),0))} -> 0 | Q87: {=SUMPRODUCT(IFERROR((tblPayrollIncrementalSpend[Group]=$N$1)*tblPayrollIncrementalSpend[Other]*tblPayrollIncrementalSpend[2028 Incremental Spend]/(tblPayrollIncrementalSpend[Base Salary]+tblPayrollIncrementalSpend[Bonus]+tblPayrollIncrementalSpend[Payroll Taxes]+tblPayrollIncrementalSpend[Benefits]+tblPayrollIncrementalSpend[Vacation]+tblPayrollIncrementalSpend[Other]),0))} -> 0 | R87: {=SUMPRODUCT(IFERROR((tblPayrollIncrementalSpend[Group]=$N$1)*tblPayrollIncrementalSpend[Other]*tblPayrollIncrementalSpend[2029 Incremental Spend]/(tblPayrollIncrementalSpend[Base Salary]+tblPayrollIncrementalSpend[Bonus]+tblPayrollIncrementalSpend[Payroll Taxes]+tblPayrollIncrementalSpend[Benefits]+tblPayrollIncrementalSpend[Vacation]+tblPayrollIncrementalSpend[Other]),0))} -> 0 | T87: Other | V87: {=SUMPRODUCT(IFERROR((tblPayrollIncrementalSpend[Group]=$T$1)*tblPayrollIncrementalSpend[Other]*tblPayrollIncrementalSpend[2027 Incremental Spend]/(tblPayrollIncrementalSpend[Base Salary]+tblPayrollIncrementalSpend[Bonus]+tblPayrollIncrementalSpend[Payroll Taxes]+tblPayrollIncrementalSpend[Benefits]+tblPayrollIncrementalSpend[Vacation]+tblPayrollIncrementalSpend[Other]),0))} -> 0 | W87: {=SUMPRODUCT(IFERROR((tblPayrollIncrementalSpend[Group]=$T$1)*tblPayrollIncrementalSpend[Other]*tblPayrollIncrementalSpend[2028 Incremental Spend]/(tblPayrollIncrementalSpend[Base Salary]+tblPayrollIncrementalSpend[Bonus]+tblPayrollIncrementalSpend[Payroll Taxes]+tblPayrollIncrementalSpend[Benefits]+tblPayrollIncrementalSpend[Vacation]+tblPayrollIncrementalSpend[Other]),0))} -> 0 | X87: {=SUMPRODUCT(IFERROR((tblPayrollIncrementalSpend[Group]=$T$1)*tblPayrollIncrementalSpend[Other]*tblPayrollIncrementalSpend[2029 Incremental Spend]/(tblPayrollIncrementalSpend[Base Salary]+tblPayrollIncrementalSpend[Bonus]+tblPayrollIncrementalSpend[Payroll Taxes]+tblPayrollIncrementalSpend[Benefits]+tblPayrollIncrementalSpend[Vacation]+tblPayrollIncrementalSpend[Other]),0))} -> 0 | Z87: Other | AB87: {=SUMPRODUCT(IFERROR((tblPayrollIncrementalSpend[Group]=$Z$1)*tblPayrollIncrementalSpend[Other]*tblPayrollIncrementalSpend[2027 Incremental Spend]/(tblPayrollIncrementalSpend[Base Salary]+tblPayrollIncrementalSpend[Bonus]+tblPayrollIncrementalSpend[Payroll Taxes]+tblPayrollIncrementalSpend[Benefits]+tblPayrollIncrementalSpend[Vacation]+tblPayrollIncrementalSpend[Other]),0))} -> 0 | AC87: {=SUMPRODUCT(IFERROR((tblPayrollIncrementalSpend[Group]=$Z$1)*tblPayrollIncrementalSpend[Other]*tblPayrollIncrementalSpend[2028 Incremental Spend]/(tblPayrollIncrementalSpend[Base Salary]+tblPayrollIncrementalSpend[Bonus]+tblPayrollIncrementalSpend[Payroll Taxes]+tblPayrollIncrementalSpend[Benefits]+tblPayrollIncrementalSpend[Vacation]+tblPayrollIncrementalSpend[Other]),0))} -> 0 | AD87: {=SUMPRODUCT(IFERROR((tblPayrollIncrementalSpend[Group]=$Z$1)*tblPayrollIncrementalSpend[Other]*tblPayrollIncrementalSpend[2029 Incremental Spend]/(tblPayrollIncrementalSpend[Base Salary]+tblPayrollIncrementalSpend[Bonus]+tblPayrollIncrementalSpend[Payroll Taxes]+tblPayrollIncrementalSpend[Benefits]+tblPayrollIncrementalSpend[Vacation]+tblPayrollIncrementalSpend[Other]),0))} -> 0
B88: Contract Labor | D88: =SUMIF(tblNonPayrollIncrementalSpend[Type of Expense],$B88,tblNonPayrollIncrementalSpend[2027 Incremental Spend]) -> 0 | E88: =SUMIF(tblNonPayrollIncrementalSpend3[Type of Expense],$B88,tblNonPayrollIncrementalSpend3[2028 Incremental Spend]) -> 0 | F88: =SUMIF(tblNonPayrollIncrementalSpend3[Type of Expense],$B88,tblNonPayrollIncrementalSpend3[2029 Incremental Spend]) -> 0 | H88: Contract Labor | J88: =SUMIFS(tblNonPayrollIncrementalSpend[2027 Incremental Spend],tblNonPayrollIncrementalSpend[Type of Expense],$H88,tblNonPayrollIncrementalSpend[Group],$H$1) -> 0 | K88: =SUMIFS(tblNonPayrollIncrementalSpend[2028 Incremental Spend],tblNonPayrollIncrementalSpend[Type of Expense],$H88,tblNonPayrollIncrementalSpend[Group],$H$1) -> 0 | L88: =SUMIFS(tblNonPayrollIncrementalSpend[2029 Incremental Spend],tblNonPayrollIncrementalSpend[Type of Expense],$H88,tblNonPayrollIncrementalSpend[Group],$H$1) -> 0 | N88: Contract Labor | P88: =SUMIFS(tblNonPayrollIncrementalSpend[2027 Incremental Spend],tblNonPayrollIncrementalSpend[Type of Expense],$N88,tblNonPayrollIncrementalSpend[Group],$N$1) -> 0 | Q88: =SUMIFS(tblNonPayrollIncrementalSpend[2028 Incremental Spend],tblNonPayrollIncrementalSpend[Type of Expense],$N88,tblNonPayrollIncrementalSpend[Group],$N$1) -> 0 | R88: =SUMIFS(tblNonPayrollIncrementalSpend[2029 Incremental Spend],tblNonPayrollIncrementalSpend[Type of Expense],$N88,tblNonPayrollIncrementalSpend[Group],$N$1) -> 0 | T88: Contract Labor | V88: =SUMIFS(tblNonPayrollIncrementalSpend[2027 Incremental Spend],tblNonPayrollIncrementalSpend[Type of Expense],$T88,tblNonPayrollIncrementalSpend[Group],$T$1) -> 0 | W88: =SUMIFS(tblNonPayrollIncrementalSpend[2028 Incremental Spend],tblNonPayrollIncrementalSpend[Type of Expense],$T88,tblNonPayrollIncrementalSpend[Group],$T$1) -> 0 | X88: =SUMIFS(tblNonPayrollIncrementalSpend[2029 Incremental Spend],tblNonPayrollIncrementalSpend[Type of Expense],$T88,tblNonPayrollIncrementalSpend[Group],$T$1) -> 0 | Z88: Contract Labor | AB88: =SUMIFS(tblNonPayrollIncrementalSpend[2027 Incremental Spend],tblNonPayrollIncrementalSpend[Type of Expense],$Z88,tblNonPayrollIncrementalSpend[Group],$Z$1) -> 0 | AC88: =SUMIFS(tblNonPayrollIncrementalSpend[2028 Incremental Spend],tblNonPayrollIncrementalSpend[Type of Expense],$Z88,tblNonPayrollIncrementalSpend[Group],$Z$1) -> 0 | AD88: =SUMIFS(tblNonPayrollIncrementalSpend[2029 Incremental Spend],tblNonPayrollIncrementalSpend[Type of Expense],$Z88,tblNonPayrollIncrementalSpend[Group],$Z$1) -> 0
B89: LTIP Compensation | D89: =SUMIF(tblNonPayrollIncrementalSpend[Type of Expense],$B89,tblNonPayrollIncrementalSpend[2027 Incremental Spend]) -> 0 | E89: =SUMIF(tblNonPayrollIncrementalSpend3[Type of Expense],$B89,tblNonPayrollIncrementalSpend3[2028 Incremental Spend]) -> 0 | F89: =SUMIF(tblNonPayrollIncrementalSpend3[Type of Expense],$B89,tblNonPayrollIncrementalSpend3[2029 Incremental Spend]) -> 0 | H89: LTIP Compensation | J89: =SUMIFS(tblNonPayrollIncrementalSpend[2027 Incremental Spend],tblNonPayrollIncrementalSpend[Type of Expense],$H89,tblNonPayrollIncrementalSpend[Group],$H$1) -> 0 | K89: =SUMIFS(tblNonPayrollIncrementalSpend[2028 Incremental Spend],tblNonPayrollIncrementalSpend[Type of Expense],$H89,tblNonPayrollIncrementalSpend[Group],$H$1) -> 0 | L89: =SUMIFS(tblNonPayrollIncrementalSpend[2029 Incremental Spend],tblNonPayrollIncrementalSpend[Type of Expense],$H89,tblNonPayrollIncrementalSpend[Group],$H$1) -> 0 | N89: LTIP Compensation | P89: =SUMIFS(tblNonPayrollIncrementalSpend[2027 Incremental Spend],tblNonPayrollIncrementalSpend[Type of Expense],$N89,tblNonPayrollIncrementalSpend[Group],$N$1) -> 0 | Q89: =SUMIFS(tblNonPayrollIncrementalSpend[2028 Incremental Spend],tblNonPayrollIncrementalSpend[Type of Expense],$N89,tblNonPayrollIncrementalSpend[Group],$N$1) -> 0 | R89: =SUMIFS(tblNonPayrollIncrementalSpend[2029 Incremental Spend],tblNonPayrollIncrementalSpend[Type of Expense],$N89,tblNonPayrollIncrementalSpend[Group],$N$1) -> 0 | T89: LTIP Compensation | V89: =SUMIFS(tblNonPayrollIncrementalSpend[2027 Incremental Spend],tblNonPayrollIncrementalSpend[Type of Expense],$T89,tblNonPayrollIncrementalSpend[Group],$T$1) -> 0 | W89: =SUMIFS(tblNonPayrollIncrementalSpend[2028 Incremental Spend],tblNonPayrollIncrementalSpend[Type of Expense],$T89,tblNonPayrollIncrementalSpend[Group],$T$1) -> 0 | X89: =SUMIFS(tblNonPayrollIncrementalSpend[2029 Incremental Spend],tblNonPayrollIncrementalSpend[Type of Expense],$T89,tblNonPayrollIncrementalSpend[Group],$T$1) -> 0 | Z89: LTIP Compensation | AB89: =SUMIFS(tblNonPayrollIncrementalSpend[2027 Incremental Spend],tblNonPayrollIncrementalSpend[Type of Expense],$Z89,tblNonPayrollIncrementalSpend[Group],$Z$1) -> 0 | AC89: =SUMIFS(tblNonPayrollIncrementalSpend[2028 Incremental Spend],tblNonPayrollIncrementalSpend[Type of Expense],$Z89,tblNonPayrollIncrementalSpend[Group],$Z$1) -> 0 | AD89: =SUMIFS(tblNonPayrollIncrementalSpend[2029 Incremental Spend],tblNonPayrollIncrementalSpend[Type of Expense],$Z89,tblNonPayrollIncrementalSpend[Group],$Z$1) -> 0
B90: Incremental Payroll | D90: =SUM(D81:D89) -> 0 | E90: =SUM(E81:E89) -> 0 | F90: =SUM(F81:F89) -> 0 | H90: Incremental Payroll | J90: =SUM(J81:J89) -> 0 | K90: =SUM(K81:K89) -> 0 | L90: =SUM(L81:L89) -> 0 | N90: Incremental Payroll | P90: =SUM(P81:P89) -> 0 | Q90: =SUM(Q81:Q89) -> 0 | R90: =SUM(R81:R89) -> 0 | T90: Incremental Payroll | V90: =SUM(V81:V89) -> 0 | W90: =SUM(W81:W89) -> 0 | X90: =SUM(X81:X89) -> 0 | Z90: Incremental Payroll | AB90: =SUM(AB81:AB89) -> 0 | AC90: =SUM(AC81:AC89) -> 0 | AD90: =SUM(AD81:AD89) -> 0
B92: Professional Fees | D92: =SUMIF(tblNonPayrollIncrementalSpend[Type of Expense],$B92,tblNonPayrollIncrementalSpend[2027 Incremental Spend]) -> 0 | E92: =SUMIF(tblNonPayrollIncrementalSpend[Type of Expense],$B92,tblNonPayrollIncrementalSpend[2028 Incremental Spend]) -> 0 | F92: =SUMIF(tblNonPayrollIncrementalSpend[Type of Expense],$B92,tblNonPayrollIncrementalSpend[2029 Incremental Spend]) -> 0 | H92: Professional Fees | J92: =SUMIFS(tblNonPayrollIncrementalSpend[2027 Incremental Spend],tblNonPayrollIncrementalSpend[Type of Expense],$H92,tblNonPayrollIncrementalSpend[Group],$H$1) -> 0 | K92: =SUMIFS(tblNonPayrollIncrementalSpend[2028 Incremental Spend],tblNonPayrollIncrementalSpend[Type of Expense],$H92,tblNonPayrollIncrementalSpend[Group],$H$1) -> 0 | L92: =SUMIFS(tblNonPayrollIncrementalSpend[2029 Incremental Spend],tblNonPayrollIncrementalSpend[Type of Expense],$H92,tblNonPayrollIncrementalSpend[Group],$H$1) -> 0 | N92: Professional Fees | P92: =SUMIFS(tblNonPayrollIncrementalSpend[2027 Incremental Spend],tblNonPayrollIncrementalSpend[Type of Expense],$N92,tblNonPayrollIncrementalSpend[Group],$N$1) -> 0 | Q92: =SUMIFS(tblNonPayrollIncrementalSpend[2028 Incremental Spend],tblNonPayrollIncrementalSpend[Type of Expense],$N92,tblNonPayrollIncrementalSpend[Group],$N$1) -> 0 | R92: =SUMIFS(tblNonPayrollIncrementalSpend[2029 Incremental Spend],tblNonPayrollIncrementalSpend[Type of Expense],$N92,tblNonPayrollIncrementalSpend[Group],$N$1) -> 0 | T92: Professional Fees | V92: =SUMIFS(tblNonPayrollIncrementalSpend[2027 Incremental Spend],tblNonPayrollIncrementalSpend[Type of Expense],$T92,tblNonPayrollIncrementalSpend[Group],$T$1) -> 0 | W92: =SUMIFS(tblNonPayrollIncrementalSpend[2028 Incremental Spend],tblNonPayrollIncrementalSpend[Type of Expense],$T92,tblNonPayrollIncrementalSpend[Group],$T$1) -> 0 | X92: =SUMIFS(tblNonPayrollIncrementalSpend[2029 Incremental Spend],tblNonPayrollIncrementalSpend[Type of Expense],$T92,tblNonPayrollIncrementalSpend[Group],$T$1) -> 0 | Z92: Professional Fees | AB92: =SUMIFS(tblNonPayrollIncrementalSpend[2027 Incremental Spend],tblNonPayrollIncrementalSpend[Type of Expense],$Z92,tblNonPayrollIncrementalSpend[Group],$Z$1) -> 0 | AC92: =SUMIFS(tblNonPayrollIncrementalSpend[2028 Incremental Spend],tblNonPayrollIncrementalSpend[Type of Expense],$Z92,tblNonPayrollIncrementalSpend[Group],$Z$1) -> 0 | AD92: =SUMIFS(tblNonPayrollIncrementalSpend[2029 Incremental Spend],tblNonPayrollIncrementalSpend[Type of Expense],$Z92,tblNonPayrollIncrementalSpend[Group],$Z$1) -> 0
B93: Occupancy | D93: =SUMIF(tblNonPayrollIncrementalSpend[Type of Expense],$B93,tblNonPayrollIncrementalSpend[2027 Incremental Spend]) -> 0 | E93: =SUMIF(tblNonPayrollIncrementalSpend[Type of Expense],$B93,tblNonPayrollIncrementalSpend[2028 Incremental Spend]) -> 0 | F93: =SUMIF(tblNonPayrollIncrementalSpend[Type of Expense],$B93,tblNonPayrollIncrementalSpend[2029 Incremental Spend]) -> 0 | H93: Occupancy | J93: =SUMIFS(tblNonPayrollIncrementalSpend[2027 Incremental Spend],tblNonPayrollIncrementalSpend[Type of Expense],$H93,tblNonPayrollIncrementalSpend[Group],$H$1) -> 0 | K93: =SUMIFS(tblNonPayrollIncrementalSpend[2028 Incremental Spend],tblNonPayrollIncrementalSpend[Type of Expense],$H93,tblNonPayrollIncrementalSpend[Group],$H$1) -> 0 | L93: =SUMIFS(tblNonPayrollIncrementalSpend[2029 Incremental Spend],tblNonPayrollIncrementalSpend[Type of Expense],$H93,tblNonPayrollIncrementalSpend[Group],$H$1) -> 0 | N93: Occupancy | P93: =SUMIFS(tblNonPayrollIncrementalSpend[2027 Incremental Spend],tblNonPayrollIncrementalSpend[Type of Expense],$N93,tblNonPayrollIncrementalSpend[Group],$N$1) -> 0 | Q93: =SUMIFS(tblNonPayrollIncrementalSpend[2028 Incremental Spend],tblNonPayrollIncrementalSpend[Type of Expense],$N93,tblNonPayrollIncrementalSpend[Group],$N$1) -> 0 | R93: =SUMIFS(tblNonPayrollIncrementalSpend[2029 Incremental Spend],tblNonPayrollIncrementalSpend[Type of Expense],$N93,tblNonPayrollIncrementalSpend[Group],$N$1) -> 0 | T93: Occupancy | V93: =SUMIFS(tblNonPayrollIncrementalSpend[2027 Incremental Spend],tblNonPayrollIncrementalSpend[Type of Expense],$T93,tblNonPayrollIncrementalSpend[Group],$T$1) -> 0 | W93: =SUMIFS(tblNonPayrollIncrementalSpend[2028 Incremental Spend],tblNonPayrollIncrementalSpend[Type of Expense],$T93,tblNonPayrollIncrementalSpend[Group],$T$1) -> 0 | X93: =SUMIFS(tblNonPayrollIncrementalSpend[2029 Incremental Spend],tblNonPayrollIncrementalSpend[Type of Expense],$T93,tblNonPayrollIncrementalSpend[Group],$T$1) -> 0 | Z93: Occupancy | AB93: =SUMIFS(tblNonPayrollIncrementalSpend[2027 Incremental Spend],tblNonPayrollIncrementalSpend[Type of Expense],$Z93,tblNonPayrollIncrementalSpend[Group],$Z$1) -> 0 | AC93: =SUMIFS(tblNonPayrollIncrementalSpend[2028 Incremental Spend],tblNonPayrollIncrementalSpend[Type of Expense],$Z93,tblNonPayrollIncrementalSpend[Group],$Z$1) -> 0 | AD93: =SUMIFS(tblNonPayrollIncrementalSpend[2029 Incremental Spend],tblNonPayrollIncrementalSpend[Type of Expense],$Z93,tblNonPayrollIncrementalSpend[Group],$Z$1) -> 0
B94: Office Expenses | D94: =SUMIF(tblNonPayrollIncrementalSpend[Type of Expense],$B94,tblNonPayrollIncrementalSpend[2027 Incremental Spend]) -> 0 | E94: =SUMIF(tblNonPayrollIncrementalSpend[Type of Expense],$B94,tblNonPayrollIncrementalSpend[2028 Incremental Spend]) -> 0 | F94: =SUMIF(tblNonPayrollIncrementalSpend[Type of Expense],$B94,tblNonPayrollIncrementalSpend[2029 Incremental Spend]) -> 0 | H94: Office Expenses | J94: =SUMIFS(tblNonPayrollIncrementalSpend[2027 Incremental Spend],tblNonPayrollIncrementalSpend[Type of Expense],$H94,tblNonPayrollIncrementalSpend[Group],$H$1) -> 0 | K94: =SUMIFS(tblNonPayrollIncrementalSpend[2028 Incremental Spend],tblNonPayrollIncrementalSpend[Type of Expense],$H94,tblNonPayrollIncrementalSpend[Group],$H$1) -> 0 | L94: =SUMIFS(tblNonPayrollIncrementalSpend[2029 Incremental Spend],tblNonPayrollIncrementalSpend[Type of Expense],$H94,tblNonPayrollIncrementalSpend[Group],$H$1) -> 0 | N94: Office Expenses | P94: =SUMIFS(tblNonPayrollIncrementalSpend[2027 Incremental Spend],tblNonPayrollIncrementalSpend[Type of Expense],$N94,tblNonPayrollIncrementalSpend[Group],$N$1) -> 0 | Q94: =SUMIFS(tblNonPayrollIncrementalSpend[2028 Incremental Spend],tblNonPayrollIncrementalSpend[Type of Expense],$N94,tblNonPayrollIncrementalSpend[Group],$N$1) -> 0 | R94: =SUMIFS(tblNonPayrollIncrementalSpend[2029 Incremental Spend],tblNonPayrollIncrementalSpend[Type of Expense],$N94,tblNonPayrollIncrementalSpend[Group],$N$1) -> 0 | T94: Office Expenses | V94: =SUMIFS(tblNonPayrollIncrementalSpend[2027 Incremental Spend],tblNonPayrollIncrementalSpend[Type of Expense],$T94,tblNonPayrollIncrementalSpend[Group],$T$1) -> 0 | W94: =SUMIFS(tblNonPayrollIncrementalSpend[2028 Incremental Spend],tblNonPayrollIncrementalSpend[Type of Expense],$T94,tblNonPayrollIncrementalSpend[Group],$T$1) -> 0 | X94: =SUMIFS(tblNonPayrollIncrementalSpend[2029 Incremental Spend],tblNonPayrollIncrementalSpend[Type of Expense],$T94,tblNonPayrollIncrementalSpend[Group],$T$1) -> 0 | Z94: Office Expenses | AB94: =SUMIFS(tblNonPayrollIncrementalSpend[2027 Incremental Spend],tblNonPayrollIncrementalSpend[Type of Expense],$Z94,tblNonPayrollIncrementalSpend[Group],$Z$1) -> 0 | AC94: =SUMIFS(tblNonPayrollIncrementalSpend[2028 Incremental Spend],tblNonPayrollIncrementalSpend[Type of Expense],$Z94,tblNonPayrollIncrementalSpend[Group],$Z$1) -> 0 | AD94: =SUMIFS(tblNonPayrollIncrementalSpend[2029 Incremental Spend],tblNonPayrollIncrementalSpend[Type of Expense],$Z94,tblNonPayrollIncrementalSpend[Group],$Z$1) -> 0
B95: IT Costs | D95: =SUMIF(tblNonPayrollIncrementalSpend[Type of Expense],$B95,tblNonPayrollIncrementalSpend[2027 Incremental Spend]) -> 0 | E95: =SUMIF(tblNonPayrollIncrementalSpend[Type of Expense],$B95,tblNonPayrollIncrementalSpend[2028 Incremental Spend]) -> 0 | F95: =SUMIF(tblNonPayrollIncrementalSpend[Type of Expense],$B95,tblNonPayrollIncrementalSpend[2029 Incremental Spend]) -> 0 | H95: IT Costs | J95: =SUMIFS(tblNonPayrollIncrementalSpend[2027 Incremental Spend],tblNonPayrollIncrementalSpend[Type of Expense],$H95,tblNonPayrollIncrementalSpend[Group],$H$1) -> 0 | K95: =SUMIFS(tblNonPayrollIncrementalSpend[2028 Incremental Spend],tblNonPayrollIncrementalSpend[Type of Expense],$H95,tblNonPayrollIncrementalSpend[Group],$H$1) -> 0 | L95: =SUMIFS(tblNonPayrollIncrementalSpend[2029 Incremental Spend],tblNonPayrollIncrementalSpend[Type of Expense],$H95,tblNonPayrollIncrementalSpend[Group],$H$1) -> 0 | N95: IT Costs | P95: =SUMIFS(tblNonPayrollIncrementalSpend[2027 Incremental Spend],tblNonPayrollIncrementalSpend[Type of Expense],$N95,tblNonPayrollIncrementalSpend[Group],$N$1) -> 0 | Q95: =SUMIFS(tblNonPayrollIncrementalSpend[2028 Incremental Spend],tblNonPayrollIncrementalSpend[Type of Expense],$N95,tblNonPayrollIncrementalSpend[Group],$N$1) -> 0 | R95: =SUMIFS(tblNonPayrollIncrementalSpend[2029 Incremental Spend],tblNonPayrollIncrementalSpend[Type of Expense],$N95,tblNonPayrollIncrementalSpend[Group],$N$1) -> 0 | T95: IT Costs | V95: =SUMIFS(tblNonPayrollIncrementalSpend[2027 Incremental Spend],tblNonPayrollIncrementalSpend[Type of Expense],$T95,tblNonPayrollIncrementalSpend[Group],$T$1) -> 0 | W95: =SUMIFS(tblNonPayrollIncrementalSpend[2028 Incremental Spend],tblNonPayrollIncrementalSpend[Type of Expense],$T95,tblNonPayrollIncrementalSpend[Group],$T$1) -> 0 | X95: =SUMIFS(tblNonPayrollIncrementalSpend[2029 Incremental Spend],tblNonPayrollIncrementalSpend[Type of Expense],$T95,tblNonPayrollIncrementalSpend[Group],$T$1) -> 0 | Z95: IT Costs | AB95: =SUMIFS(tblNonPayrollIncrementalSpend[2027 Incremental Spend],tblNonPayrollIncrementalSpend[Type of Expense],$Z95,tblNonPayrollIncrementalSpend[Group],$Z$1) -> 0 | AC95: =SUMIFS(tblNonPayrollIncrementalSpend[2028 Incremental Spend],tblNonPayrollIncrementalSpend[Type of Expense],$Z95,tblNonPayrollIncrementalSpend[Group],$Z$1) -> 0 | AD95: =SUMIFS(tblNonPayrollIncrementalSpend[2029 Incremental Spend],tblNonPayrollIncrementalSpend[Type of Expense],$Z95,tblNonPayrollIncrementalSpend[Group],$Z$1) -> 0
B96: Marketing and Presentation | D96: =SUMIF(tblNonPayrollIncrementalSpend[Type of Expense],$B96,tblNonPayrollIncrementalSpend[2027 Incremental Spend]) -> 0 | E96: =SUMIF(tblNonPayrollIncrementalSpend[Type of Expense],$B96,tblNonPayrollIncrementalSpend[2028 Incremental Spend]) -> 0 | F96: =SUMIF(tblNonPayrollIncrementalSpend[Type of Expense],$B96,tblNonPayrollIncrementalSpend[2029 Incremental Spend]) -> 0 | H96: Marketing and Presentation | J96: =SUMIFS(tblNonPayrollIncrementalSpend[2027 Incremental Spend],tblNonPayrollIncrementalSpend[Type of Expense],$H96,tblNonPayrollIncrementalSpend[Group],$H$1) -> 0 | K96: =SUMIFS(tblNonPayrollIncrementalSpend[2028 Incremental Spend],tblNonPayrollIncrementalSpend[Type of Expense],$H96,tblNonPayrollIncrementalSpend[Group],$H$1) -> 0 | L96: =SUMIFS(tblNonPayrollIncrementalSpend[2029 Incremental Spend],tblNonPayrollIncrementalSpend[Type of Expense],$H96,tblNonPayrollIncrementalSpend[Group],$H$1) -> 0 | N96: Marketing and Presentation | P96: =SUMIFS(tblNonPayrollIncrementalSpend[2027 Incremental Spend],tblNonPayrollIncrementalSpend[Type of Expense],$N96,tblNonPayrollIncrementalSpend[Group],$N$1) -> 0 | Q96: =SUMIFS(tblNonPayrollIncrementalSpend[2028 Incremental Spend],tblNonPayrollIncrementalSpend[Type of Expense],$N96,tblNonPayrollIncrementalSpend[Group],$N$1) -> 0 | R96: =SUMIFS(tblNonPayrollIncrementalSpend[2029 Incremental Spend],tblNonPayrollIncrementalSpend[Type of Expense],$N96,tblNonPayrollIncrementalSpend[Group],$N$1) -> 0 | T96: Marketing and Presentation | V96: =SUMIFS(tblNonPayrollIncrementalSpend[2027 Incremental Spend],tblNonPayrollIncrementalSpend[Type of Expense],$T96,tblNonPayrollIncrementalSpend[Group],$T$1) -> 0 | W96: =SUMIFS(tblNonPayrollIncrementalSpend[2028 Incremental Spend],tblNonPayrollIncrementalSpend[Type of Expense],$T96,tblNonPayrollIncrementalSpend[Group],$T$1) -> 0 | X96: =SUMIFS(tblNonPayrollIncrementalSpend[2029 Incremental Spend],tblNonPayrollIncrementalSpend[Type of Expense],$T96,tblNonPayrollIncrementalSpend[Group],$T$1) -> 0 | Z96: Marketing and Presentation | AB96: =SUMIFS(tblNonPayrollIncrementalSpend[2027 Incremental Spend],tblNonPayrollIncrementalSpend[Type of Expense],$Z96,tblNonPayrollIncrementalSpend[Group],$Z$1) -> 0 | AC96: =SUMIFS(tblNonPayrollIncrementalSpend[2028 Incremental Spend],tblNonPayrollIncrementalSpend[Type of Expense],$Z96,tblNonPayrollIncrementalSpend[Group],$Z$1) -> 0 | AD96: =SUMIFS(tblNonPayrollIncrementalSpend[2029 Incremental Spend],tblNonPayrollIncrementalSpend[Type of Expense],$Z96,tblNonPayrollIncrementalSpend[Group],$Z$1) -> 0
B97: Travel and Entertainment | D97: =SUMIF(tblNonPayrollIncrementalSpend[Type of Expense],$B97,tblNonPayrollIncrementalSpend[2027 Incremental Spend]) -> 0 | E97: =SUMIF(tblNonPayrollIncrementalSpend[Type of Expense],$B97,tblNonPayrollIncrementalSpend[2028 Incremental Spend]) -> 0 | F97: =SUMIF(tblNonPayrollIncrementalSpend[Type of Expense],$B97,tblNonPayrollIncrementalSpend[2029 Incremental Spend]) -> 0 | H97: Travel and Entertainment | J97: =SUMIFS(tblNonPayrollIncrementalSpend[2027 Incremental Spend],tblNonPayrollIncrementalSpend[Type of Expense],$H97,tblNonPayrollIncrementalSpend[Group],$H$1) -> 0 | K97: =SUMIFS(tblNonPayrollIncrementalSpend[2028 Incremental Spend],tblNonPayrollIncrementalSpend[Type of Expense],$H97,tblNonPayrollIncrementalSpend[Group],$H$1) -> 0 | L97: =SUMIFS(tblNonPayrollIncrementalSpend[2029 Incremental Spend],tblNonPayrollIncrementalSpend[Type of Expense],$H97,tblNonPayrollIncrementalSpend[Group],$H$1) -> 0 | N97: Travel and Entertainment | P97: =SUMIFS(tblNonPayrollIncrementalSpend[2027 Incremental Spend],tblNonPayrollIncrementalSpend[Type of Expense],$N97,tblNonPayrollIncrementalSpend[Group],$N$1) -> 0 | Q97: =SUMIFS(tblNonPayrollIncrementalSpend[2028 Incremental Spend],tblNonPayrollIncrementalSpend[Type of Expense],$N97,tblNonPayrollIncrementalSpend[Group],$N$1) -> 0 | R97: =SUMIFS(tblNonPayrollIncrementalSpend[2029 Incremental Spend],tblNonPayrollIncrementalSpend[Type of Expense],$N97,tblNonPayrollIncrementalSpend[Group],$N$1) -> 0 | T97: Travel and Entertainment | V97: =SUMIFS(tblNonPayrollIncrementalSpend[2027 Incremental Spend],tblNonPayrollIncrementalSpend[Type of Expense],$T97,tblNonPayrollIncrementalSpend[Group],$T$1) -> 0 | W97: =SUMIFS(tblNonPayrollIncrementalSpend[2028 Incremental Spend],tblNonPayrollIncrementalSpend[Type of Expense],$T97,tblNonPayrollIncrementalSpend[Group],$T$1) -> 0 | X97: =SUMIFS(tblNonPayrollIncrementalSpend[2029 Incremental Spend],tblNonPayrollIncrementalSpend[Type of Expense],$T97,tblNonPayrollIncrementalSpend[Group],$T$1) -> 0 | Z97: Travel and Entertainment | AB97: =SUMIFS(tblNonPayrollIncrementalSpend[2027 Incremental Spend],tblNonPayrollIncrementalSpend[Type of Expense],$Z97,tblNonPayrollIncrementalSpend[Group],$Z$1) -> 0 | AC97: =SUMIFS(tblNonPayrollIncrementalSpend[2028 Incremental Spend],tblNonPayrollIncrementalSpend[Type of Expense],$Z97,tblNonPayrollIncrementalSpend[Group],$Z$1) -> 0 | AD97: =SUMIFS(tblNonPayrollIncrementalSpend[2029 Incremental Spend],tblNonPayrollIncrementalSpend[Type of Expense],$Z97,tblNonPayrollIncrementalSpend[Group],$Z$1) -> 0
B98: Employee events | D98: =SUMIF(tblNonPayrollIncrementalSpend[Type of Expense],$B98,tblNonPayrollIncrementalSpend[2027 Incremental Spend]) -> 0 | E98: =SUMIF(tblNonPayrollIncrementalSpend[Type of Expense],$B98,tblNonPayrollIncrementalSpend[2028 Incremental Spend]) -> 0 | F98: =SUMIF(tblNonPayrollIncrementalSpend[Type of Expense],$B98,tblNonPayrollIncrementalSpend[2029 Incremental Spend]) -> 0 | H98: Employee events | J98: =SUMIFS(tblNonPayrollIncrementalSpend[2027 Incremental Spend],tblNonPayrollIncrementalSpend[Type of Expense],$H98,tblNonPayrollIncrementalSpend[Group],$H$1) -> 0 | K98: =SUMIFS(tblNonPayrollIncrementalSpend[2028 Incremental Spend],tblNonPayrollIncrementalSpend[Type of Expense],$H98,tblNonPayrollIncrementalSpend[Group],$H$1) -> 0 | L98: =SUMIFS(tblNonPayrollIncrementalSpend[2029 Incremental Spend],tblNonPayrollIncrementalSpend[Type of Expense],$H98,tblNonPayrollIncrementalSpend[Group],$H$1) -> 0 | N98: Employee events | P98: =SUMIFS(tblNonPayrollIncrementalSpend[2027 Incremental Spend],tblNonPayrollIncrementalSpend[Type of Expense],$N98,tblNonPayrollIncrementalSpend[Group],$N$1) -> 0 | Q98: =SUMIFS(tblNonPayrollIncrementalSpend[2028 Incremental Spend],tblNonPayrollIncrementalSpend[Type of Expense],$N98,tblNonPayrollIncrementalSpend[Group],$N$1) -> 0 | R98: =SUMIFS(tblNonPayrollIncrementalSpend[2029 Incremental Spend],tblNonPayrollIncrementalSpend[Type of Expense],$N98,tblNonPayrollIncrementalSpend[Group],$N$1) -> 0 | T98: Employee events | V98: =SUMIFS(tblNonPayrollIncrementalSpend[2027 Incremental Spend],tblNonPayrollIncrementalSpend[Type of Expense],$T98,tblNonPayrollIncrementalSpend[Group],$T$1) -> 0 | W98: =SUMIFS(tblNonPayrollIncrementalSpend[2028 Incremental Spend],tblNonPayrollIncrementalSpend[Type of Expense],$T98,tblNonPayrollIncrementalSpend[Group],$T$1) -> 0 | X98: =SUMIFS(tblNonPayrollIncrementalSpend[2029 Incremental Spend],tblNonPayrollIncrementalSpend[Type of Expense],$T98,tblNonPayrollIncrementalSpend[Group],$T$1) -> 0 | Z98: Employee events | AB98: =SUMIFS(tblNonPayrollIncrementalSpend[2027 Incremental Spend],tblNonPayrollIncrementalSpend[Type of Expense],$Z98,tblNonPayrollIncrementalSpend[Group],$Z$1) -> 0 | AC98: =SUMIFS(tblNonPayrollIncrementalSpend[2028 Incremental Spend],tblNonPayrollIncrementalSpend[Type of Expense],$Z98,tblNonPayrollIncrementalSpend[Group],$Z$1) -> 0 | AD98: =SUMIFS(tblNonPayrollIncrementalSpend[2029 Incremental Spend],tblNonPayrollIncrementalSpend[Type of Expense],$Z98,tblNonPayrollIncrementalSpend[Group],$Z$1) -> 0
B99: Insurance Non Property | D99: =SUMIF(tblNonPayrollIncrementalSpend[Type of Expense],$B99,tblNonPayrollIncrementalSpend[2027 Incremental Spend]) -> 0 | E99: =SUMIF(tblNonPayrollIncrementalSpend[Type of Expense],$B99,tblNonPayrollIncrementalSpend[2028 Incremental Spend]) -> 0 | F99: =SUMIF(tblNonPayrollIncrementalSpend[Type of Expense],$B99,tblNonPayrollIncrementalSpend[2029 Incremental Spend]) -> 0 | H99: Insurance Non Property | J99: =SUMIFS(tblNonPayrollIncrementalSpend[2027 Incremental Spend],tblNonPayrollIncrementalSpend[Type of Expense],$H99,tblNonPayrollIncrementalSpend[Group],$H$1) -> 0 | K99: =SUMIFS(tblNonPayrollIncrementalSpend[2028 Incremental Spend],tblNonPayrollIncrementalSpend[Type of Expense],$H99,tblNonPayrollIncrementalSpend[Group],$H$1) -> 0 | L99: =SUMIFS(tblNonPayrollIncrementalSpend[2029 Incremental Spend],tblNonPayrollIncrementalSpend[Type of Expense],$H99,tblNonPayrollIncrementalSpend[Group],$H$1) -> 0 | N99: Insurance Non Property | P99: =SUMIFS(tblNonPayrollIncrementalSpend[2027 Incremental Spend],tblNonPayrollIncrementalSpend[Type of Expense],$N99,tblNonPayrollIncrementalSpend[Group],$N$1) -> 0 | Q99: =SUMIFS(tblNonPayrollIncrementalSpend[2028 Incremental Spend],tblNonPayrollIncrementalSpend[Type of Expense],$N99,tblNonPayrollIncrementalSpend[Group],$N$1) -> 0 | R99: =SUMIFS(tblNonPayrollIncrementalSpend[2029 Incremental Spend],tblNonPayrollIncrementalSpend[Type of Expense],$N99,tblNonPayrollIncrementalSpend[Group],$N$1) -> 0 | T99: Insurance Non Property | V99: =SUMIFS(tblNonPayrollIncrementalSpend[2027 Incremental Spend],tblNonPayrollIncrementalSpend[Type of Expense],$T99,tblNonPayrollIncrementalSpend[Group],$T$1) -> 0 | W99: =SUMIFS(tblNonPayrollIncrementalSpend[2028 Incremental Spend],tblNonPayrollIncrementalSpend[Type of Expense],$T99,tblNonPayrollIncrementalSpend[Group],$T$1) -> 0 | X99: =SUMIFS(tblNonPayrollIncrementalSpend[2029 Incremental Spend],tblNonPayrollIncrementalSpend[Type of Expense],$T99,tblNonPayrollIncrementalSpend[Group],$T$1) -> 0 | Z99: Insurance Non Property | AB99: =SUMIFS(tblNonPayrollIncrementalSpend[2027 Incremental Spend],tblNonPayrollIncrementalSpend[Type of Expense],$Z99,tblNonPayrollIncrementalSpend[Group],$Z$1) -> 0 | AC99: =SUMIFS(tblNonPayrollIncrementalSpend[2028 Incremental Spend],tblNonPayrollIncrementalSpend[Type of Expense],$Z99,tblNonPayrollIncrementalSpend[Group],$Z$1) -> 0 | AD99: =SUMIFS(tblNonPayrollIncrementalSpend[2029 Incremental Spend],tblNonPayrollIncrementalSpend[Type of Expense],$Z99,tblNonPayrollIncrementalSpend[Group],$Z$1) -> 0
B100: Licenses | D100: =SUMIF(tblNonPayrollIncrementalSpend[Type of Expense],$B100,tblNonPayrollIncrementalSpend[2027 Incremental Spend]) -> 0 | E100: =SUMIF(tblNonPayrollIncrementalSpend[Type of Expense],$B100,tblNonPayrollIncrementalSpend[2028 Incremental Spend]) -> 0 | F100: =SUMIF(tblNonPayrollIncrementalSpend[Type of Expense],$B100,tblNonPayrollIncrementalSpend[2029 Incremental Spend]) -> 0 | H100: Licenses | J100: =SUMIFS(tblNonPayrollIncrementalSpend[2027 Incremental Spend],tblNonPayrollIncrementalSpend[Type of Expense],$H100,tblNonPayrollIncrementalSpend[Group],$H$1) -> 0 | K100: =SUMIFS(tblNonPayrollIncrementalSpend[2028 Incremental Spend],tblNonPayrollIncrementalSpend[Type of Expense],$H100,tblNonPayrollIncrementalSpend[Group],$H$1) -> 0 | L100: =SUMIFS(tblNonPayrollIncrementalSpend[2029 Incremental Spend],tblNonPayrollIncrementalSpend[Type of Expense],$H100,tblNonPayrollIncrementalSpend[Group],$H$1) -> 0 | N100: Licenses | P100: =SUMIFS(tblNonPayrollIncrementalSpend[2027 Incremental Spend],tblNonPayrollIncrementalSpend[Type of Expense],$N100,tblNonPayrollIncrementalSpend[Group],$N$1) -> 0 | Q100: =SUMIFS(tblNonPayrollIncrementalSpend[2028 Incremental Spend],tblNonPayrollIncrementalSpend[Type of Expense],$N100,tblNonPayrollIncrementalSpend[Group],$N$1) -> 0 | R100: =SUMIFS(tblNonPayrollIncrementalSpend[2029 Incremental Spend],tblNonPayrollIncrementalSpend[Type of Expense],$N100,tblNonPayrollIncrementalSpend[Group],$N$1) -> 0 | T100: Licenses | V100: =SUMIFS(tblNonPayrollIncrementalSpend[2027 Incremental Spend],tblNonPayrollIncrementalSpend[Type of Expense],$T100,tblNonPayrollIncrementalSpend[Group],$T$1) -> 0 | W100: =SUMIFS(tblNonPayrollIncrementalSpend[2028 Incremental Spend],tblNonPayrollIncrementalSpend[Type of Expense],$T100,tblNonPayrollIncrementalSpend[Group],$T$1) -> 0 | X100: =SUMIFS(tblNonPayrollIncrementalSpend[2029 Incremental Spend],tblNonPayrollIncrementalSpend[Type of Expense],$T100,tblNonPayrollIncrementalSpend[Group],$T$1) -> 0 | Z100: Licenses | AB100: =SUMIFS(tblNonPayrollIncrementalSpend[2027 Incremental Spend],tblNonPayrollIncrementalSpend[Type of Expense],$Z100,tblNonPayrollIncrementalSpend[Group],$Z$1) -> 0 | AC100: =SUMIFS(tblNonPayrollIncrementalSpend[2028 Incremental Spend],tblNonPayrollIncrementalSpend[Type of Expense],$Z100,tblNonPayrollIncrementalSpend[Group],$Z$1) -> 0 | AD100: =SUMIFS(tblNonPayrollIncrementalSpend[2029 Incremental Spend],tblNonPayrollIncrementalSpend[Type of Expense],$Z100,tblNonPayrollIncrementalSpend[Group],$Z$1) -> 0
B101: Recruiting and Relocation | D101: =SUMIF(tblNonPayrollIncrementalSpend[Type of Expense],$B101,tblNonPayrollIncrementalSpend[2027 Incremental Spend]) -> 0 | E101: =SUMIF(tblNonPayrollIncrementalSpend[Type of Expense],$B101,tblNonPayrollIncrementalSpend[2028 Incremental Spend]) -> 0 | F101: =SUMIF(tblNonPayrollIncrementalSpend[Type of Expense],$B101,tblNonPayrollIncrementalSpend[2029 Incremental Spend]) -> 0 | H101: Recruiting and Relocation | J101: =SUMIFS(tblNonPayrollIncrementalSpend[2027 Incremental Spend],tblNonPayrollIncrementalSpend[Type of Expense],$H101,tblNonPayrollIncrementalSpend[Group],$H$1) -> 0 | K101: =SUMIFS(tblNonPayrollIncrementalSpend[2028 Incremental Spend],tblNonPayrollIncrementalSpend[Type of Expense],$H101,tblNonPayrollIncrementalSpend[Group],$H$1) -> 0 | L101: =SUMIFS(tblNonPayrollIncrementalSpend[2029 Incremental Spend],tblNonPayrollIncrementalSpend[Type of Expense],$H101,tblNonPayrollIncrementalSpend[Group],$H$1) -> 0 | N101: Recruiting and Relocation | P101: =SUMIFS(tblNonPayrollIncrementalSpend[2027 Incremental Spend],tblNonPayrollIncrementalSpend[Type of Expense],$N101,tblNonPayrollIncrementalSpend[Group],$N$1) -> 0 | Q101: =SUMIFS(tblNonPayrollIncrementalSpend[2028 Incremental Spend],tblNonPayrollIncrementalSpend[Type of Expense],$N101,tblNonPayrollIncrementalSpend[Group],$N$1) -> 0 | R101: =SUMIFS(tblNonPayrollIncrementalSpend[2029 Incremental Spend],tblNonPayrollIncrementalSpend[Type of Expense],$N101,tblNonPayrollIncrementalSpend[Group],$N$1) -> 0 | T101: Recruiting and Relocation | V101: =SUMIFS(tblNonPayrollIncrementalSpend[2027 Incremental Spend],tblNonPayrollIncrementalSpend[Type of Expense],$T101,tblNonPayrollIncrementalSpend[Group],$T$1) -> 0 | W101: =SUMIFS(tblNonPayrollIncrementalSpend[2028 Incremental Spend],tblNonPayrollIncrementalSpend[Type of Expense],$T101,tblNonPayrollIncrementalSpend[Group],$T$1) -> 0 | X101: =SUMIFS(tblNonPayrollIncrementalSpend[2029 Incremental Spend],tblNonPayrollIncrementalSpend[Type of Expense],$T101,tblNonPayrollIncrementalSpend[Group],$T$1) -> 0 | Z101: Recruiting and Relocation | AB101: =SUMIFS(tblNonPayrollIncrementalSpend[2027 Incremental Spend],tblNonPayrollIncrementalSpend[Type of Expense],$Z101,tblNonPayrollIncrementalSpend[Group],$Z$1) -> 0 | AC101: =SUMIFS(tblNonPayrollIncrementalSpend[2028 Incremental Spend],tblNonPayrollIncrementalSpend[Type of Expense],$Z101,tblNonPayrollIncrementalSpend[Group],$Z$1) -> 0 | AD101: =SUMIFS(tblNonPayrollIncrementalSpend[2029 Incremental Spend],tblNonPayrollIncrementalSpend[Type of Expense],$Z101,tblNonPayrollIncrementalSpend[Group],$Z$1) -> 0
B102: Seminars and Training | D102: =SUMIF(tblNonPayrollIncrementalSpend[Type of Expense],$B102,tblNonPayrollIncrementalSpend[2027 Incremental Spend]) -> 0 | E102: =SUMIF(tblNonPayrollIncrementalSpend[Type of Expense],$B102,tblNonPayrollIncrementalSpend[2028 Incremental Spend]) -> 0 | F102: =SUMIF(tblNonPayrollIncrementalSpend[Type of Expense],$B102,tblNonPayrollIncrementalSpend[2029 Incremental Spend]) -> 0 | H102: Seminars and Training | J102: =SUMIFS(tblNonPayrollIncrementalSpend[2027 Incremental Spend],tblNonPayrollIncrementalSpend[Type of Expense],$H102,tblNonPayrollIncrementalSpend[Group],$H$1) -> 0 | K102: =SUMIFS(tblNonPayrollIncrementalSpend[2028 Incremental Spend],tblNonPayrollIncrementalSpend[Type of Expense],$H102,tblNonPayrollIncrementalSpend[Group],$H$1) -> 0 | L102: =SUMIFS(tblNonPayrollIncrementalSpend[2029 Incremental Spend],tblNonPayrollIncrementalSpend[Type of Expense],$H102,tblNonPayrollIncrementalSpend[Group],$H$1) -> 0 | N102: Seminars and Training | P102: =SUMIFS(tblNonPayrollIncrementalSpend[2027 Incremental Spend],tblNonPayrollIncrementalSpend[Type of Expense],$N102,tblNonPayrollIncrementalSpend[Group],$N$1) -> 0 | Q102: =SUMIFS(tblNonPayrollIncrementalSpend[2028 Incremental Spend],tblNonPayrollIncrementalSpend[Type of Expense],$N102,tblNonPayrollIncrementalSpend[Group],$N$1) -> 0 | R102: =SUMIFS(tblNonPayrollIncrementalSpend[2029 Incremental Spend],tblNonPayrollIncrementalSpend[Type of Expense],$N102,tblNonPayrollIncrementalSpend[Group],$N$1) -> 0 | T102: Seminars and Training | V102: =SUMIFS(tblNonPayrollIncrementalSpend[2027 Incremental Spend],tblNonPayrollIncrementalSpend[Type of Expense],$T102,tblNonPayrollIncrementalSpend[Group],$T$1) -> 0 | W102: =SUMIFS(tblNonPayrollIncrementalSpend[2028 Incremental Spend],tblNonPayrollIncrementalSpend[Type of Expense],$T102,tblNonPayrollIncrementalSpend[Group],$T$1) -> 0 | X102: =SUMIFS(tblNonPayrollIncrementalSpend[2029 Incremental Spend],tblNonPayrollIncrementalSpend[Type of Expense],$T102,tblNonPayrollIncrementalSpend[Group],$T$1) -> 0 | Z102: Seminars and Training | AB102: =SUMIFS(tblNonPayrollIncrementalSpend[2027 Incremental Spend],tblNonPayrollIncrementalSpend[Type of Expense],$Z102,tblNonPayrollIncrementalSpend[Group],$Z$1) -> 0 | AC102: =SUMIFS(tblNonPayrollIncrementalSpend[2028 Incremental Spend],tblNonPayrollIncrementalSpend[Type of Expense],$Z102,tblNonPayrollIncrementalSpend[Group],$Z$1) -> 0 | AD102: =SUMIFS(tblNonPayrollIncrementalSpend[2029 Incremental Spend],tblNonPayrollIncrementalSpend[Type of Expense],$Z102,tblNonPayrollIncrementalSpend[Group],$Z$1) -> 0
B103: Shareholder Relations | D103: =SUMIF(tblNonPayrollIncrementalSpend[Type of Expense],$B103,tblNonPayrollIncrementalSpend[2027 Incremental Spend]) -> 0 | E103: =SUMIF(tblNonPayrollIncrementalSpend[Type of Expense],$B103,tblNonPayrollIncrementalSpend[2028 Incremental Spend]) -> 0 | F103: =SUMIF(tblNonPayrollIncrementalSpend[Type of Expense],$B103,tblNonPayrollIncrementalSpend[2029 Incremental Spend]) -> 0 | H103: Shareholder Relations | J103: =SUMIFS(tblNonPayrollIncrementalSpend[2027 Incremental Spend],tblNonPayrollIncrementalSpend[Type of Expense],$H103,tblNonPayrollIncrementalSpend[Group],$H$1) -> 0 | K103: =SUMIFS(tblNonPayrollIncrementalSpend[2028 Incremental Spend],tblNonPayrollIncrementalSpend[Type of Expense],$H103,tblNonPayrollIncrementalSpend[Group],$H$1) -> 0 | L103: =SUMIFS(tblNonPayrollIncrementalSpend[2029 Incremental Spend],tblNonPayrollIncrementalSpend[Type of Expense],$H103,tblNonPayrollIncrementalSpend[Group],$H$1) -> 0 | N103: Shareholder Relations | P103: =SUMIFS(tblNonPayrollIncrementalSpend[2027 Incremental Spend],tblNonPayrollIncrementalSpend[Type of Expense],$N103,tblNonPayrollIncrementalSpend[Group],$N$1) -> 0 | Q103: =SUMIFS(tblNonPayrollIncrementalSpend[2028 Incremental Spend],tblNonPayrollIncrementalSpend[Type of Expense],$N103,tblNonPayrollIncrementalSpend[Group],$N$1) -> 0 | R103: =SUMIFS(tblNonPayrollIncrementalSpend[2029 Incremental Spend],tblNonPayrollIncrementalSpend[Type of Expense],$N103,tblNonPayrollIncrementalSpend[Group],$N$1) -> 0 | T103: Shareholder Relations | V103: =SUMIFS(tblNonPayrollIncrementalSpend[2027 Incremental Spend],tblNonPayrollIncrementalSpend[Type of Expense],$T103,tblNonPayrollIncrementalSpend[Group],$T$1) -> 0 | W103: =SUMIFS(tblNonPayrollIncrementalSpend[2028 Incremental Spend],tblNonPayrollIncrementalSpend[Type of Expense],$T103,tblNonPayrollIncrementalSpend[Group],$T$1) -> 0 | X103: =SUMIFS(tblNonPayrollIncrementalSpend[2029 Incremental Spend],tblNonPayrollIncrementalSpend[Type of Expense],$T103,tblNonPayrollIncrementalSpend[Group],$T$1) -> 0 | Z103: Shareholder Relations | AB103: =SUMIFS(tblNonPayrollIncrementalSpend[2027 Incremental Spend],tblNonPayrollIncrementalSpend[Type of Expense],$Z103,tblNonPayrollIncrementalSpend[Group],$Z$1) -> 0 | AC103: =SUMIFS(tblNonPayrollIncrementalSpend[2028 Incremental Spend],tblNonPayrollIncrementalSpend[Type of Expense],$Z103,tblNonPayrollIncrementalSpend[Group],$Z$1) -> 0 | AD103: =SUMIFS(tblNonPayrollIncrementalSpend[2029 Incremental Spend],tblNonPayrollIncrementalSpend[Type of Expense],$Z103,tblNonPayrollIncrementalSpend[Group],$Z$1) -> 0
... B112: Allocated IT & Office Contra | D112: =SUMIF(tblNonPayrollIncrementalSpend[Type of Expense],$B112,tblNonPayrollIncrementalSpend[2027 Incremental Spend]) -> 0 | E112: =SUMIF(tblNonPayrollIncrementalSpend[Type of Expense],$B112,tblNonPayrollIncrementalSpend[2028 Incremental Spend]) -> 0 | F112: =SUMIF(tblNonPayrollIncrementalSpend[Type of Expense],$B112,tblNonPayrollIncrementalSpend[2029 Incremental Spend]) -> 0 | H112: Allocated IT & Office Contra | J112: =SUMIFS(tblNonPayrollIncrementalSpend[2027 Incremental Spend],tblNonPayrollIncrementalSpend[Type of Expense],$H112,tblNonPayrollIncrementalSpend[Group],$H$1) -> 0 | K112: =SUMIFS(tblNonPayrollIncrementalSpend[2028 Incremental Spend],tblNonPayrollIncrementalSpend[Type of Expense],$H112,tblNonPayrollIncrementalSpend[Group],$H$1) -> 0 | L112: =SUMIFS(tblNonPayrollIncrementalSpend[2029 Incremental Spend],tblNonPayrollIncrementalSpend[Type of Expense],$H112,tblNonPayrollIncrementalSpend[Group],$H$1) -> 0 | N112: Allocated IT & Office Contra | P112: =SUMIFS(tblNonPayrollIncrementalSpend[2027 Incremental Spend],tblNonPayrollIncrementalSpend[Type of Expense],$N112,tblNonPayrollIncrementalSpend[Group],$N$1) -> 0 | Q112: =SUMIFS(tblNonPayrollIncrementalSpend[2028 Incremental Spend],tblNonPayrollIncrementalSpend[Type of Expense],$N112,tblNonPayrollIncrementalSpend[Group],$N$1) -> 0 | R112: =SUMIFS(tblNonPayrollIncrementalSpend[2029 Incremental Spend],tblNonPayrollIncrementalSpend[Type of Expense],$N112,tblNonPayrollIncrementalSpend[Group],$N$1) -> 0 | T112: Allocated IT & Office Contra | V112: =SUMIFS(tblNonPayrollIncrementalSpend[2027 Incremental Spend],tblNonPayrollIncrementalSpend[Type of Expense],$T112,tblNonPayrollIncrementalSpend[Group],$T$1) -> 0 | W112: =SUMIFS(tblNonPayrollIncrementalSpend[2028 Incremental Spend],tblNonPayrollIncrementalSpend[Type of Expense],$T112,tblNonPayrollIncrementalSpend[Group],$T$1) -> 0 | X112: =SUMIFS(tblNonPayrollIncrementalSpend[2029 Incremental Spend],tblNonPayrollIncrementalSpend[Type of Expense],$T112,tblNonPayrollIncrementalSpend[Group],$T$1) -> 0 | Z112: Allocated IT & Office Contra | AB112: =SUMIFS(tblNonPayrollIncrementalSpend[2027 Incremental Spend],tblNonPayrollIncrementalSpend[Type of Expense],$Z112,tblNonPayrollIncrementalSpend[Group],$Z$1) -> 0 | AC112: =SUMIFS(tblNonPayrollIncrementalSpend[2028 Incremental Spend],tblNonPayrollIncrementalSpend[Type of Expense],$Z112,tblNonPayrollIncrementalSpend[Group],$Z$1) -> 0 | AD112: =SUMIFS(tblNonPayrollIncrementalSpend[2029 Incremental Spend],tblNonPayrollIncrementalSpend[Type of Expense],$Z112,tblNonPayrollIncrementalSpend[Group],$Z$1) -> 0
B113: Incremental Non-Payroll | D113: =SUM(D92:D112) -> 0 | E113: =SUM(E92:E112) -> 0 | F113: =SUM(F92:F112) -> 0 | H113: Incremental Non-Payroll | J113: =SUM(J92:J112) -> 0 | K113: =SUM(K92:K112) -> 0 | L113: =SUM(L92:L112) -> 0 | N113: Incremental Non-Payroll | P113: =SUM(P92:P112) -> 0 | Q113: =SUM(Q92:Q112) -> 0 | R113: =SUM(R92:R112) -> 0 | T113: Incremental Non-Payroll | V113: =SUM(V92:V112) -> 0 | W113: =SUM(W92:W112) -> 0 | X113: =SUM(X92:X112) -> 0 | Z113: Incremental Non-Payroll | AB113: =SUM(AB92:AB112) -> 0 | AC113: =SUM(AC92:AC112) -> 0 | AD113: =SUM(AD92:AD112) -> 0
B115: Total | D115: =D90+D113 -> 0 | E115: =E90+E113 -> 0 | F115: =F90+F113 -> 0 | H115: Total | J115: =J90+J113 -> 0 | K115: =K90+K113 -> 0 | L115: =L90+L113 -> 0 | N115: Total | P115: =P90+P113 -> 0 | Q115: =Q90+Q113 -> 0 | R115: =R90+R113 -> 0 | T115: Total | V115: =V90+V113 -> 0 | W115: =W90+W113 -> 0 | X115: =X90+X113 -> 0 | Z115: Total | AB115: =AB90+AB113 -> 0 | AC115: =AC90+AC113 -> 0 | AD115: =AD90+AD113 -> 0

Sheet Investment Case Asks - Summary
A1: Investment Case Asks - Incremental Spend Input
A3: Payroll / Headcount Incremental Spend | U3: Incremental Spend Summary
A4: Job Title | B4: Group | C4: Job Level | D4: Role / Hire | E4: Location (City/Country) | F4: Key Job Responsibilities | G4: Hire Date | H4: Base Salary | I4: Bonus % | J4: Bonus | K4: Payroll Taxes | L4: Benefits | M4: Vacation | N4: Other | O4: 2027 Annualized Spend | P4: 2027 Incremental Spend | Q4: 2028 Incremental Spend | R4: 2029 Incremental Spend | S4: Notes / Rationale | U4: Spend Type | V4: 2027 | W4: 2028 | X4: 2029
A5: =IFERROR(IF('Investment Case Asks - Monthly'!A5="","",'Investment Case Asks - Monthly'!A5),"") | B5: =IFERROR(IF('Investment Case Asks - Monthly'!B5="","",'Investment Case Asks - Monthly'!B5),"") | C5: =IFERROR(IF('Investment Case Asks - Monthly'!C5="","",'Investment Case Asks - Monthly'!C5),"") | D5: =IFERROR(IF('Investment Case Asks - Monthly'!D5="","",'Investment Case Asks - Monthly'!D5),"") | E5: =IFERROR(IF('Investment Case Asks - Monthly'!E5="","",'Investment Case Asks - Monthly'!E5),"") | F5: =IFERROR(IF('Investment Case Asks - Monthly'!F5="","",'Investment Case Asks - Monthly'!F5),"") | G5: =IFERROR(IF('Investment Case Asks - Monthly'!G5="","",'Investment Case Asks - Monthly'!G5),"") | H5: =IFERROR(IF('Investment Case Asks - Monthly'!H5="","",'Investment Case Asks - Monthly'!H5),"") | ... O5: =IFERROR(IF('Investment Case Asks - Monthly'!O5="","",'Investment Case Asks - Monthly'!O5),"") | P5: =IFERROR(IF('Investment Case Asks - Monthly'!AB5="","",'Investment Case Asks - Monthly'!AB5),"") | Q5: =IFERROR(IF('Investment Case Asks - Monthly'!AO5="","",'Investment Case Asks - Monthly'!AO5),"") | R5: =IFERROR(IF('Investment Case Asks - Monthly'!BB5="","",'Investment Case Asks - Monthly'!BB5),"") | S5: =IFERROR(IF('Investment Case Asks - Monthly'!BC5="","",'Investment Case Asks - Monthly'!BC5),"") | U5: Payroll / Headcount | V5: =O22 -> 0 | W5: =P22 -> 0 | X5: =Q22 -> 0
A6: =IFERROR(IF('Investment Case Asks - Monthly'!A6="","",'Investment Case Asks - Monthly'!A6),"") | B6: =IFERROR(IF('Investment Case Asks - Monthly'!B6="","",'Investment Case Asks - Monthly'!B6),"") | C6: =IFERROR(IF('Investment Case Asks - Monthly'!C6="","",'Investment Case Asks - Monthly'!C6),"") | D6: =IFERROR(IF('Investment Case Asks - Monthly'!D6="","",'Investment Case Asks - Monthly'!D6),"") | E6: =IFERROR(IF('Investment Case Asks - Monthly'!E6="","",'Investment Case Asks - Monthly'!E6),"") | F6: =IFERROR(IF('Investment Case Asks - Monthly'!F6="","",'Investment Case Asks - Monthly'!F6),"") | G6: =IFERROR(IF('Investment Case Asks - Monthly'!G6="","",'Investment Case Asks - Monthly'!G6),"") | H6: =IFERROR(IF('Investment Case Asks - Monthly'!H6="","",'Investment Case Asks - Monthly'!H6),"") | ... O6: =IFERROR(IF('Investment Case Asks - Monthly'!O6="","",'Investment Case Asks - Monthly'!O6),"") | P6: =IFERROR(IF('Investment Case Asks - Monthly'!AB6="","",'Investment Case Asks - Monthly'!AB6),"") | Q6: =IFERROR(IF('Investment Case Asks - Monthly'!AO6="","",'Investment Case Asks - Monthly'!AO6),"") | R6: =IFERROR(IF('Investment Case Asks - Monthly'!BB6="","",'Investment Case Asks - Monthly'!BB6),"") | S6: =IFERROR(IF('Investment Case Asks - Monthly'!BC6="","",'Investment Case Asks - Monthly'!BC6),"") | U6: Non-Payroll | V6: =D44 -> 0 | W6: =E44 -> 0 | X6: =F44 -> 0
A7: =IFERROR(IF('Investment Case Asks - Monthly'!A7="","",'Investment Case Asks - Monthly'!A7),"") | B7: =IFERROR(IF('Investment Case Asks - Monthly'!B7="","",'Investment Case Asks - Monthly'!B7),"") | C7: =IFERROR(IF('Investment Case Asks - Monthly'!C7="","",'Investment Case Asks - Monthly'!C7),"") | D7: =IFERROR(IF('Investment Case Asks - Monthly'!D7="","",'Investment Case Asks - Monthly'!D7),"") | E7: =IFERROR(IF('Investment Case Asks - Monthly'!E7="","",'Investment Case Asks - Monthly'!E7),"") | F7: =IFERROR(IF('Investment Case Asks - Monthly'!F7="","",'Investment Case Asks - Monthly'!F7),"") | G7: =IFERROR(IF('Investment Case Asks - Monthly'!G7="","",'Investment Case Asks - Monthly'!G7),"") | H7: =IFERROR(IF('Investment Case Asks - Monthly'!H7="","",'Investment Case Asks - Monthly'!H7),"") | ... O7: =IFERROR(IF('Investment Case Asks - Monthly'!O7="","",'Investment Case Asks - Monthly'!O7),"") | P7: =IFERROR(IF('Investment Case Asks - Monthly'!AB7="","",'Investment Case Asks - Monthly'!AB7),"") | Q7: =IFERROR(IF('Investment Case Asks - Monthly'!AO7="","",'Investment Case Asks - Monthly'!AO7),"") | R7: =IFERROR(IF('Investment Case Asks - Monthly'!BB7="","",'Investment Case Asks - Monthly'!BB7),"") | S7: =IFERROR(IF('Investment Case Asks - Monthly'!BC7="","",'Investment Case Asks - Monthly'!BC7),"") | U7: Total Incremental Spend | V7: =SUM(V5:V6) -> 0 | W7: =SUM(W5:W6) -> 0 | X7: =SUM(X5:X6) -> 0
A8: =IFERROR(IF('Investment Case Asks - Monthly'!A8="","",'Investment Case Asks - Monthly'!A8),"") | B8: =IFERROR(IF('Investment Case Asks - Monthly'!B8="","",'Investment Case Asks - Monthly'!B8),"") | C8: =IFERROR(IF('Investment Case Asks - Monthly'!C8="","",'Investment Case Asks - Monthly'!C8),"") | D8: =IFERROR(IF('Investment Case Asks - Monthly'!D8="","",'Investment Case Asks - Monthly'!D8),"") | E8: =IFERROR(IF('Investment Case Asks - Monthly'!E8="","",'Investment Case Asks - Monthly'!E8),"") | F8: =IFERROR(IF('Investment Case Asks - Monthly'!F8="","",'Investment Case Asks - Monthly'!F8),"") | G8: =IFERROR(IF('Investment Case Asks - Monthly'!G8="","",'Investment Case Asks - Monthly'!G8),"") | H8: =IFERROR(IF('Investment Case Asks - Monthly'!H8="","",'Investment Case Asks - Monthly'!H8),"") | ... O8: =IFERROR(IF('Investment Case Asks - Monthly'!O8="","",'Investment Case Asks - Monthly'!O8),"") | P8: =IFERROR(IF('Investment Case Asks - Monthly'!AB8="","",'Investment Case Asks - Monthly'!AB8),"") | Q8: =IFERROR(IF('Investment Case Asks - Monthly'!AO8="","",'Investment Case Asks - Monthly'!AO8),"") | R8: =IFERROR(IF('Investment Case Asks - Monthly'!BB8="","",'Investment Case Asks - Monthly'!BB8),"") | S8: =IFERROR(IF('Investment Case Asks - Monthly'!BC8="","",'Investment Case Asks - Monthly'!BC8),"")
A9: =IFERROR(IF('Investment Case Asks - Monthly'!A9="","",'Investment Case Asks - Monthly'!A9),"") | B9: =IFERROR(IF('Investment Case Asks - Monthly'!B9="","",'Investment Case Asks - Monthly'!B9),"") | C9: =IFERROR(IF('Investment Case Asks - Monthly'!C9="","",'Investment Case Asks - Monthly'!C9),"") | D9: =IFERROR(IF('Investment Case Asks - Monthly'!D9="","",'Investment Case Asks - Monthly'!D9),"") | E9: =IFERROR(IF('Investment Case Asks - Monthly'!E9="","",'Investment Case Asks - Monthly'!E9),"") | F9: =IFERROR(IF('Investment Case Asks - Monthly'!F9="","",'Investment Case Asks - Monthly'!F9),"") | G9: =IFERROR(IF('Investment Case Asks - Monthly'!G9="","",'Investment Case Asks - Monthly'!G9),"") | H9: =IFERROR(IF('Investment Case Asks - Monthly'!H9="","",'Investment Case Asks - Monthly'!H9),"") | ... O9: =IFERROR(IF('Investment Case Asks - Monthly'!O9="","",'Investment Case Asks - Monthly'!O9),"") | P9: =IFERROR(IF('Investment Case Asks - Monthly'!AB9="","",'Investment Case Asks - Monthly'!AB9),"") | Q9: =IFERROR(IF('Investment Case Asks - Monthly'!AO9="","",'Investment Case Asks - Monthly'!AO9),"") | R9: =IFERROR(IF('Investment Case Asks - Monthly'!BB9="","",'Investment Case Asks - Monthly'!BB9),"") | S9: =IFERROR(IF('Investment Case Asks - Monthly'!BC9="","",'Investment Case Asks - Monthly'!BC9),"")
A10: =IFERROR(IF('Investment Case Asks - Monthly'!A10="","",'Investment Case Asks - Monthly'!A10),"") | B10: =IFERROR(IF('Investment Case Asks - Monthly'!B10="","",'Investment Case Asks - Monthly'!B10),"") | C10: =IFERROR(IF('Investment Case Asks - Monthly'!C10="","",'Investment Case Asks - Monthly'!C10),"") | D10: =IFERROR(IF('Investment Case Asks - Monthly'!D10="","",'Investment Case Asks - Monthly'!D10),"") | E10: =IFERROR(IF('Investment Case Asks - Monthly'!E10="","",'Investment Case Asks - Monthly'!E10),"") | F10: =IFERROR(IF('Investment Case Asks - Monthly'!F10="","",'Investment Case Asks - Monthly'!F10),"") | G10: =IFERROR(IF('Investment Case Asks - Monthly'!G10="","",'Investment Case Asks - Monthly'!G10),"") | H10: =IFERROR(IF('Investment Case Asks - Monthly'!H10="","",'Investment Case Asks - Monthly'!H10),"") | ... O10: =IFERROR(IF('Investment Case Asks - Monthly'!O10="","",'Investment Case Asks - Monthly'!O10),"") | P10: =IFERROR(IF('Investment Case Asks - Monthly'!AB10="","",'Investment Case Asks - Monthly'!AB10),"") | Q10: =IFERROR(IF('Investment Case Asks - Monthly'!AO10="","",'Investment Case Asks - Monthly'!AO10),"") | R10: =IFERROR(IF('Investment Case Asks - Monthly'!BB10="","",'Investment Case Asks - Monthly'!BB10),"") | S10: =IFERROR(IF('Investment Case Asks - Monthly'!BC10="","",'Investment Case Asks - Monthly'!BC10),"")
A11: =IFERROR(IF('Investment Case Asks - Monthly'!A11="","",'Investment Case Asks - Monthly'!A11),"") | B11: =IFERROR(IF('Investment Case Asks - Monthly'!B11="","",'Investment Case Asks - Monthly'!B11),"") | C11: =IFERROR(IF('Investment Case Asks - Monthly'!C11="","",'Investment Case Asks - Monthly'!C11),"") | D11: =IFERROR(IF('Investment Case Asks - Monthly'!D11="","",'Investment Case Asks - Monthly'!D11),"") | E11: =IFERROR(IF('Investment Case Asks - Monthly'!E11="","",'Investment Case Asks - Monthly'!E11),"") | F11: =IFERROR(IF('Investment Case Asks - Monthly'!F11="","",'Investment Case Asks - Monthly'!F11),"") | G11: =IFERROR(IF('Investment Case Asks - Monthly'!G11="","",'Investment Case Asks - Monthly'!G11),"") | H11: =IFERROR(IF('Investment Case Asks - Monthly'!H11="","",'Investment Case Asks - Monthly'!H11),"") | ... O11: =IFERROR(IF('Investment Case Asks - Monthly'!O11="","",'Investment Case Asks - Monthly'!O11),"") | P11: =IFERROR(IF('Investment Case Asks - Monthly'!AB11="","",'Investment Case Asks - Monthly'!AB11),"") | Q11: =IFERROR(IF('Investment Case Asks - Monthly'!AO11="","",'Investment Case Asks - Monthly'!AO11),"") | R11: =IFERROR(IF('Investment Case Asks - Monthly'!BB11="","",'Investment Case Asks - Monthly'!BB11),"") | S11: =IFERROR(IF('Investment Case Asks - Monthly'!BC11="","",'Investment Case Asks - Monthly'!BC11),"")
A12: =IFERROR(IF('Investment Case Asks - Monthly'!A12="","",'Investment Case Asks - Monthly'!A12),"") | B12: =IFERROR(IF('Investment Case Asks - Monthly'!B12="","",'Investment Case Asks - Monthly'!B12),"") | C12: =IFERROR(IF('Investment Case Asks - Monthly'!C12="","",'Investment Case Asks - Monthly'!C12),"") | D12: =IFERROR(IF('Investment Case Asks - Monthly'!D12="","",'Investment Case Asks - Monthly'!D12),"") | E12: =IFERROR(IF('Investment Case Asks - Monthly'!E12="","",'Investment Case Asks - Monthly'!E12),"") | F12: =IFERROR(IF('Investment Case Asks - Monthly'!F12="","",'Investment Case Asks - Monthly'!F12),"") | G12: =IFERROR(IF('Investment Case Asks - Monthly'!G12="","",'Investment Case Asks - Monthly'!G12),"") | H12: =IFERROR(IF('Investment Case Asks - Monthly'!H12="","",'Investment Case Asks - Monthly'!H12),"") | ... O12: =IFERROR(IF('Investment Case Asks - Monthly'!O12="","",'Investment Case Asks - Monthly'!O12),"") | P12: =IFERROR(IF('Investment Case Asks - Monthly'!AB12="","",'Investment Case Asks - Monthly'!AB12),"") | Q12: =IFERROR(IF('Investment Case Asks - Monthly'!AO12="","",'Investment Case Asks - Monthly'!AO12),"") | R12: =IFERROR(IF('Investment Case Asks - Monthly'!BB12="","",'Investment Case Asks - Monthly'!BB12),"") | S12: =IFERROR(IF('Investment Case Asks - Monthly'!BC12="","",'Investment Case Asks - Monthly'!BC12),"")
A13: =IFERROR(IF('Investment Case Asks - Monthly'!A13="","",'Investment Case Asks - Monthly'!A13),"") | B13: =IFERROR(IF('Investment Case Asks - Monthly'!B13="","",'Investment Case Asks - Monthly'!B13),"") | C13: =IFERROR(IF('Investment Case Asks - Monthly'!C13="","",'Investment Case Asks - Monthly'!C13),"") | D13: =IFERROR(IF('Investment Case Asks - Monthly'!D13="","",'Investment Case Asks - Monthly'!D13),"") | E13: =IFERROR(IF('Investment Case Asks - Monthly'!E13="","",'Investment Case Asks - Monthly'!E13),"") | F13: =IFERROR(IF('Investment Case Asks - Monthly'!F13="","",'Investment Case Asks - Monthly'!F13),"") | G13: =IFERROR(IF('Investment Case Asks - Monthly'!G13="","",'Investment Case Asks - Monthly'!G13),"") | H13: =IFERROR(IF('Investment Case Asks - Monthly'!H13="","",'Investment Case Asks - Monthly'!H13),"") | ... O13: =IFERROR(IF('Investment Case Asks - Monthly'!O13="","",'Investment Case Asks - Monthly'!O13),"") | P13: =IFERROR(IF('Investment Case Asks - Monthly'!AB13="","",'Investment Case Asks - Monthly'!AB13),"") | Q13: =IFERROR(IF('Investment Case Asks - Monthly'!AO13="","",'Investment Case Asks - Monthly'!AO13),"") | R13: =IFERROR(IF('Investment Case Asks - Monthly'!BB13="","",'Investment Case Asks - Monthly'!BB13),"") | S13: =IFERROR(IF('Investment Case Asks - Monthly'!BC13="","",'Investment Case Asks - Monthly'!BC13),"")
A14: =IFERROR(IF('Investment Case Asks - Monthly'!A14="","",'Investment Case Asks - Monthly'!A14),"") | B14: =IFERROR(IF('Investment Case Asks - Monthly'!B14="","",'Investment Case Asks - Monthly'!B14),"") | C14: =IFERROR(IF('Investment Case Asks - Monthly'!C14="","",'Investment Case Asks - Monthly'!C14),"") | D14: =IFERROR(IF('Investment Case Asks - Monthly'!D14="","",'Investment Case Asks - Monthly'!D14),"") | E14: =IFERROR(IF('Investment Case Asks - Monthly'!E14="","",'Investment Case Asks - Monthly'!E14),"") | F14: =IFERROR(IF('Investment Case Asks - Monthly'!F14="","",'Investment Case Asks - Monthly'!F14),"") | G14: =IFERROR(IF('Investment Case Asks - Monthly'!G14="","",'Investment Case Asks - Monthly'!G14),"") | H14: =IFERROR(IF('Investment Case Asks - Monthly'!H14="","",'Investment Case Asks - Monthly'!H14),"") | ... O14: =IFERROR(IF('Investment Case Asks - Monthly'!O14="","",'Investment Case Asks - Monthly'!O14),"") | P14: =IFERROR(IF('Investment Case Asks - Monthly'!AB14="","",'Investment Case Asks - Monthly'!AB14),"") | Q14: =IFERROR(IF('Investment Case Asks - Monthly'!AO14="","",'Investment Case Asks - Monthly'!AO14),"") | R14: =IFERROR(IF('Investment Case Asks - Monthly'!BB14="","",'Investment Case Asks - Monthly'!BB14),"") | S14: =IFERROR(IF('Investment Case Asks - Monthly'!BC14="","",'Investment Case Asks - Monthly'!BC14),"")
A15: =IFERROR(IF('Investment Case Asks - Monthly'!A15="","",'Investment Case Asks - Monthly'!A15),"") | B15: =IFERROR(IF('Investment Case Asks - Monthly'!B15="","",'Investment Case Asks - Monthly'!B15),"") | C15: =IFERROR(IF('Investment Case Asks - Monthly'!C15="","",'Investment Case Asks - Monthly'!C15),"") | D15: =IFERROR(IF('Investment Case Asks - Monthly'!D15="","",'Investment Case Asks - Monthly'!D15),"") | E15: =IFERROR(IF('Investment Case Asks - Monthly'!E15="","",'Investment Case Asks - Monthly'!E15),"") | F15: =IFERROR(IF('Investment Case Asks - Monthly'!F15="","",'Investment Case Asks - Monthly'!F15),"") | G15: =IFERROR(IF('Investment Case Asks - Monthly'!G15="","",'Investment Case Asks - Monthly'!G15),"") | H15: =IFERROR(IF('Investment Case Asks - Monthly'!H15="","",'Investment Case Asks - Monthly'!H15),"") | ... O15: =IFERROR(IF('Investment Case Asks - Monthly'!O15="","",'Investment Case Asks - Monthly'!O15),"") | P15: =IFERROR(IF('Investment Case Asks - Monthly'!AB15="","",'Investment Case Asks - Monthly'!AB15),"") | Q15: =IFERROR(IF('Investment Case Asks - Monthly'!AO15="","",'Investment Case Asks - Monthly'!AO15),"") | R15: =IFERROR(IF('Investment Case Asks - Monthly'!BB15="","",'Investment Case Asks - Monthly'!BB15),"") | S15: =IFERROR(IF('Investment Case Asks - Monthly'!BC15="","",'Investment Case Asks - Monthly'!BC15),"")
A16: =IFERROR(IF('Investment Case Asks - Monthly'!A16="","",'Investment Case Asks - Monthly'!A16),"") | B16: =IFERROR(IF('Investment Case Asks - Monthly'!B16="","",'Investment Case Asks - Monthly'!B16),"") | C16: =IFERROR(IF('Investment Case Asks - Monthly'!C16="","",'Investment Case Asks - Monthly'!C16),"") | D16: =IFERROR(IF('Investment Case Asks - Monthly'!D16="","",'Investment Case Asks - Monthly'!D16),"") | E16: =IFERROR(IF('Investment Case Asks - Monthly'!E16="","",'Investment Case Asks - Monthly'!E16),"") | F16: =IFERROR(IF('Investment Case Asks - Monthly'!F16="","",'Investment Case Asks - Monthly'!F16),"") | G16: =IFERROR(IF('Investment Case Asks - Monthly'!G16="","",'Investment Case Asks - Monthly'!G16),"") | H16: =IFERROR(IF('Investment Case Asks - Monthly'!H16="","",'Investment Case Asks - Monthly'!H16),"") | ... O16: =IFERROR(IF('Investment Case Asks - Monthly'!O16="","",'Investment Case Asks - Monthly'!O16),"") | P16: =IFERROR(IF('Investment Case Asks - Monthly'!AB16="","",'Investment Case Asks - Monthly'!AB16),"") | Q16: =IFERROR(IF('Investment Case Asks - Monthly'!AO16="","",'Investment Case Asks - Monthly'!AO16),"") | R16: =IFERROR(IF('Investment Case Asks - Monthly'!BB16="","",'Investment Case Asks - Monthly'!BB16),"") | S16: =IFERROR(IF('Investment Case Asks - Monthly'!BC16="","",'Investment Case Asks - Monthly'!BC16),"")
A17: =IFERROR(IF('Investment Case Asks - Monthly'!A17="","",'Investment Case Asks - Monthly'!A17),"") | B17: =IFERROR(IF('Investment Case Asks - Monthly'!B17="","",'Investment Case Asks - Monthly'!B17),"") | C17: =IFERROR(IF('Investment Case Asks - Monthly'!C17="","",'Investment Case Asks - Monthly'!C17),"") | D17: =IFERROR(IF('Investment Case Asks - Monthly'!D17="","",'Investment Case Asks - Monthly'!D17),"") | E17: =IFERROR(IF('Investment Case Asks - Monthly'!E17="","",'Investment Case Asks - Monthly'!E17),"") | F17: =IFERROR(IF('Investment Case Asks - Monthly'!F17="","",'Investment Case Asks - Monthly'!F17),"") | G17: =IFERROR(IF('Investment Case Asks - Monthly'!G17="","",'Investment Case Asks - Monthly'!G17),"") | H17: =IFERROR(IF('Investment Case Asks - Monthly'!H17="","",'Investment Case Asks - Monthly'!H17),"") | ... O17: =IFERROR(IF('Investment Case Asks - Monthly'!O17="","",'Investment Case Asks - Monthly'!O17),"") | P17: =IFERROR(IF('Investment Case Asks - Monthly'!AB17="","",'Investment Case Asks - Monthly'!AB17),"") | Q17: =IFERROR(IF('Investment Case Asks - Monthly'!AO17="","",'Investment Case Asks - Monthly'!AO17),"") | R17: =IFERROR(IF('Investment Case Asks - Monthly'!BB17="","",'Investment Case Asks - Monthly'!BB17),"") | S17: =IFERROR(IF('Investment Case Asks - Monthly'!BC17="","",'Investment Case Asks - Monthly'!BC17),"")
A18: =IFERROR(IF('Investment Case Asks - Monthly'!A18="","",'Investment Case Asks - Monthly'!A18),"") | B18: =IFERROR(IF('Investment Case Asks - Monthly'!B18="","",'Investment Case Asks - Monthly'!B18),"") | C18: =IFERROR(IF('Investment Case Asks - Monthly'!C18="","",'Investment Case Asks - Monthly'!C18),"") | D18: =IFERROR(IF('Investment Case Asks - Monthly'!D18="","",'Investment Case Asks - Monthly'!D18),"") | E18: =IFERROR(IF('Investment Case Asks - Monthly'!E18="","",'Investment Case Asks - Monthly'!E18),"") | F18: =IFERROR(IF('Investment Case Asks - Monthly'!F18="","",'Investment Case Asks - Monthly'!F18),"") | G18: =IFERROR(IF('Investment Case Asks - Monthly'!G18="","",'Investment Case Asks - Monthly'!G18),"") | H18: =IFERROR(IF('Investment Case Asks - Monthly'!H18="","",'Investment Case Asks - Monthly'!H18),"") | ... O18: =IFERROR(IF('Investment Case Asks - Monthly'!O18="","",'Investment Case Asks - Monthly'!O18),"") | P18: =IFERROR(IF('Investment Case Asks - Monthly'!AB18="","",'Investment Case Asks - Monthly'!AB18),"") | Q18: =IFERROR(IF('Investment Case Asks - Monthly'!AO18="","",'Investment Case Asks - Monthly'!AO18),"") | R18: =IFERROR(IF('Investment Case Asks - Monthly'!BB18="","",'Investment Case Asks - Monthly'!BB18),"") | S18: =IFERROR(IF('Investment Case Asks - Monthly'!BC18="","",'Investment Case Asks - Monthly'!BC18),"")
A19: =IFERROR(IF('Investment Case Asks - Monthly'!A19="","",'Investment Case Asks - Monthly'!A19),"") | B19: =IFERROR(IF('Investment Case Asks - Monthly'!B19="","",'Investment Case Asks - Monthly'!B19),"") | C19: =IFERROR(IF('Investment Case Asks - Monthly'!C19="","",'Investment Case Asks - Monthly'!C19),"") | D19: =IFERROR(IF('Investment Case Asks - Monthly'!D19="","",'Investment Case Asks - Monthly'!D19),"") | E19: =IFERROR(IF('Investment Case Asks - Monthly'!E19="","",'Investment Case Asks - Monthly'!E19),"") | F19: =IFERROR(IF('Investment Case Asks - Monthly'!F19="","",'Investment Case Asks - Monthly'!F19),"") | G19: =IFERROR(IF('Investment Case Asks - Monthly'!G19="","",'Investment Case Asks - Monthly'!G19),"") | H19: =IFERROR(IF('Investment Case Asks - Monthly'!H19="","",'Investment Case Asks - Monthly'!H19),"") | ... O19: =IFERROR(IF('Investment Case Asks - Monthly'!O19="","",'Investment Case Asks - Monthly'!O19),"") | P19: =IFERROR(IF('Investment Case Asks - Monthly'!AB19="","",'Investment Case Asks - Monthly'!AB19),"") | Q19: =IFERROR(IF('Investment Case Asks - Monthly'!AO19="","",'Investment Case Asks - Monthly'!AO19),"") | R19: =IFERROR(IF('Investment Case Asks - Monthly'!BB19="","",'Investment Case Asks - Monthly'!BB19),"") | S19: =IFERROR(IF('Investment Case Asks - Monthly'!BC19="","",'Investment Case Asks - Monthly'!BC19),"")
A20: =IFERROR(IF('Investment Case Asks - Monthly'!A20="","",'Investment Case Asks - Monthly'!A20),"") | B20: =IFERROR(IF('Investment Case Asks - Monthly'!B20="","",'Investment Case Asks - Monthly'!B20),"") | C20: =IFERROR(IF('Investment Case Asks - Monthly'!C20="","",'Investment Case Asks - Monthly'!C20),"") | D20: =IFERROR(IF('Investment Case Asks - Monthly'!D20="","",'Investment Case Asks - Monthly'!D20),"") | E20: =IFERROR(IF('Investment Case Asks - Monthly'!E20="","",'Investment Case Asks - Monthly'!E20),"") | F20: =IFERROR(IF('Investment Case Asks - Monthly'!F20="","",'Investment Case Asks - Monthly'!F20),"") | G20: =IFERROR(IF('Investment Case Asks - Monthly'!G20="","",'Investment Case Asks - Monthly'!G20),"") | H20: =IFERROR(IF('Investment Case Asks - Monthly'!H20="","",'Investment Case Asks - Monthly'!H20),"") | ... O20: =IFERROR(IF('Investment Case Asks - Monthly'!O20="","",'Investment Case Asks - Monthly'!O20),"") | P20: =IFERROR(IF('Investment Case Asks - Monthly'!AB20="","",'Investment Case Asks - Monthly'!AB20),"") | Q20: =IFERROR(IF('Investment Case Asks - Monthly'!AO20="","",'Investment Case Asks - Monthly'!AO20),"") | R20: =IFERROR(IF('Investment Case Asks - Monthly'!BB20="","",'Investment Case Asks - Monthly'!BB20),"") | S20: =IFERROR(IF('Investment Case Asks - Monthly'!BC20="","",'Investment Case Asks - Monthly'!BC20),"")
A22: Total Payroll / Headcount Incremental Spend | H22: =SUM(H5:H20) -> 0 | J22: =SUM(J5:J20) -> 0 | K22: =SUM(K5:K20) -> 0 | L22: =SUM(L5:L20) -> 0 | M22: =SUM(M5:M20) -> 0 | N22: =SUM(N5:N20) -> 0 | O22: =SUM(O5:O20) -> 0 | P22: =SUM(P5:P20) -> 0 | Q22: =SUM(Q5:Q20) -> 0 | R22: =SUM(R5:R20) -> 0
A26: Essentials Bonus / Contract Labor / Non-Payroll Incremental Spend
A27: Expense Description | B27: Group | C27: Type of Expense | D27: Vendor | E27: 2027 Incremental Spend | F27: 2028 Incremental Spend | G27: 2029 Incremental Spend | H27: Notes / Rationale
A28: =IFERROR(IF('Investment Case Asks - Monthly'!A28="","",'Investment Case Asks - Monthly'!A28),"") | B28: =IFERROR(IF('Investment Case Asks - Monthly'!B28="","",'Investment Case Asks - Monthly'!B28),"") | C28: =IFERROR(IF('Investment Case Asks - Monthly'!C28="","",'Investment Case Asks - Monthly'!C28),"") | D28: =IFERROR(IF('Investment Case Asks - Monthly'!D28="","",'Investment Case Asks - Monthly'!D28),"") | E28: =IFERROR(IF('Investment Case Asks - Monthly'!R28="","",'Investment Case Asks - Monthly'!R28),"") | F28: =IFERROR(IF('Investment Case Asks - Monthly'!AE28="","",'Investment Case Asks - Monthly'!AE28),"") | G28: =IFERROR(IF('Investment Case Asks - Monthly'!AR28="","",'Investment Case Asks - Monthly'!AR28),"") | H28: =IFERROR(IF('Investment Case Asks - Monthly'!AS28="","",'Investment Case Asks - Monthly'!AS28),"")
A29: =IFERROR(IF('Investment Case Asks - Monthly'!A29="","",'Investment Case Asks - Monthly'!A29),"") | B29: =IFERROR(IF('Investment Case Asks - Monthly'!B29="","",'Investment Case Asks - Monthly'!B29),"") | C29: =IFERROR(IF('Investment Case Asks - Monthly'!C29="","",'Investment Case Asks - Monthly'!C29),"") | D29: =IFERROR(IF('Investment Case Asks - Monthly'!D29="","",'Investment Case Asks - Monthly'!D29),"") | E29: =IFERROR(IF('Investment Case Asks - Monthly'!R29="","",'Investment Case Asks - Monthly'!R29),"") | F29: =IFERROR(IF('Investment Case Asks - Monthly'!AE29="","",'Investment Case Asks - Monthly'!AE29),"") | G29: =IFERROR(IF('Investment Case Asks - Monthly'!AR29="","",'Investment Case Asks - Monthly'!AR29),"") | H29: =IFERROR(IF('Investment Case Asks - Monthly'!AS29="","",'Investment Case Asks - Monthly'!AS29),"")
A30: =IFERROR(IF('Investment Case Asks - Monthly'!A30="","",'Investment Case Asks - Monthly'!A30),"") | B30: =IFERROR(IF('Investment Case Asks - Monthly'!B30="","",'Investment Case Asks - Monthly'!B30),"") | C30: =IFERROR(IF('Investment Case Asks - Monthly'!C30="","",'Investment Case Asks - Monthly'!C30),"") | D30: =IFERROR(IF('Investment Case Asks - Monthly'!D30="","",'Investment Case Asks - Monthly'!D30),"") | E30: =IFERROR(IF('Investment Case Asks - Monthly'!R30="","",'Investment Case Asks - Monthly'!R30),"") | F30: =IFERROR(IF('Investment Case Asks - Monthly'!AE30="","",'Investment Case Asks - Monthly'!AE30),"") | G30: =IFERROR(IF('Investment Case Asks - Monthly'!AR30="","",'Investment Case Asks - Monthly'!AR30),"") | H30: =IFERROR(IF('Investment Case Asks - Monthly'!AS30="","",'Investment Case Asks - Monthly'!AS30),"")
A31: =IFERROR(IF('Investment Case Asks - Monthly'!A31="","",'Investment Case Asks - Monthly'!A31),"") | B31: =IFERROR(IF('Investment Case Asks - Monthly'!B31="","",'Investment Case Asks - Monthly'!B31),"") | C31: =IFERROR(IF('Investment Case Asks - Monthly'!C31="","",'Investment Case Asks - Monthly'!C31),"") | D31: =IFERROR(IF('Investment Case Asks - Monthly'!D31="","",'Investment Case Asks - Monthly'!D31),"") | E31: =IFERROR(IF('Investment Case Asks - Monthly'!R31="","",'Investment Case Asks - Monthly'!R31),"") | F31: =IFERROR(IF('Investment Case Asks - Monthly'!AE31="","",'Investment Case Asks - Monthly'!AE31),"") | G31: =IFERROR(IF('Investment Case Asks - Monthly'!AR31="","",'Investment Case Asks - Monthly'!AR31),"") | H31: =IFERROR(IF('Investment Case Asks - Monthly'!AS31="","",'Investment Case Asks - Monthly'!AS31),"")
A32: =IFERROR(IF('Investment Case Asks - Monthly'!A32="","",'Investment Case Asks - Monthly'!A32),"") | B32: =IFERROR(IF('Investment Case Asks - Monthly'!B32="","",'Investment Case Asks - Monthly'!B32),"") | C32: =IFERROR(IF('Investment Case Asks - Monthly'!C32="","",'Investment Case Asks - Monthly'!C32),"") | D32: =IFERROR(IF('Investment Case Asks - Monthly'!D32="","",'Investment Case Asks - Monthly'!D32),"") | E32: =IFERROR(IF('Investment Case Asks - Monthly'!R32="","",'Investment Case Asks - Monthly'!R32),"") | F32: =IFERROR(IF('Investment Case Asks - Monthly'!AE32="","",'Investment Case Asks - Monthly'!AE32),"") | G32: =IFERROR(IF('Investment Case Asks - Monthly'!AR32="","",'Investment Case Asks - Monthly'!AR32),"") | H32: =IFERROR(IF('Investment Case Asks - Monthly'!AS32="","",'Investment Case Asks - Monthly'!AS32),"")
A33: =IFERROR(IF('Investment Case Asks - Monthly'!A33="","",'Investment Case Asks - Monthly'!A33),"") | B33: =IFERROR(IF('Investment Case Asks - Monthly'!B33="","",'Investment Case Asks - Monthly'!B33),"") | C33: =IFERROR(IF('Investment Case Asks - Monthly'!C33="","",'Investment Case Asks - Monthly'!C33),"") | D33: =IFERROR(IF('Investment Case Asks - Monthly'!D33="","",'Investment Case Asks - Monthly'!D33),"") | E33: =IFERROR(IF('Investment Case Asks - Monthly'!R33="","",'Investment Case Asks - Monthly'!R33),"") | F33: =IFERROR(IF('Investment Case Asks - Monthly'!AE33="","",'Investment Case Asks - Monthly'!AE33),"") | G33: =IFERROR(IF('Investment Case Asks - Monthly'!AR33="","",'Investment Case Asks - Monthly'!AR33),"") | H33: =IFERROR(IF('Investment Case Asks - Monthly'!AS33="","",'Investment Case Asks - Monthly'!AS33),"")
A34: =IFERROR(IF('Investment Case Asks - Monthly'!A34="","",'Investment Case Asks - Monthly'!A34),"") | B34: =IFERROR(IF('Investment Case Asks - Monthly'!B34="","",'Investment Case Asks - Monthly'!B34),"") | C34: =IFERROR(IF('Investment Case Asks - Monthly'!C34="","",'Investment Case Asks - Monthly'!C34),"") | D34: =IFERROR(IF('Investment Case Asks - Monthly'!D34="","",'Investment Case Asks - Monthly'!D34),"") | E34: =IFERROR(IF('Investment Case Asks - Monthly'!R34="","",'Investment Case Asks - Monthly'!R34),"") | F34: =IFERROR(IF('Investment Case Asks - Monthly'!AE34="","",'Investment Case Asks - Monthly'!AE34),"") | G34: =IFERROR(IF('Investment Case Asks - Monthly'!AR34="","",'Investment Case Asks - Monthly'!AR34),"") | H34: =IFERROR(IF('Investment Case Asks - Monthly'!AS34="","",'Investment Case Asks - Monthly'!AS34),"")
A35: =IFERROR(IF('Investment Case Asks - Monthly'!A35="","",'Investment Case Asks - Monthly'!A35),"") | B35: =IFERROR(IF('Investment Case Asks - Monthly'!B35="","",'Investment Case Asks - Monthly'!B35),"") | C35: =IFERROR(IF('Investment Case Asks - Monthly'!C35="","",'Investment Case Asks - Monthly'!C35),"") | D35: =IFERROR(IF('Investment Case Asks - Monthly'!D35="","",'Investment Case Asks - Monthly'!D35),"") | E35: =IFERROR(IF('Investment Case Asks - Monthly'!R35="","",'Investment Case Asks - Monthly'!R35),"") | F35: =IFERROR(IF('Investment Case Asks - Monthly'!AE35="","",'Investment Case Asks - Monthly'!AE35),"") | G35: =IFERROR(IF('Investment Case Asks - Monthly'!AR35="","",'Investment Case Asks - Monthly'!AR35),"") | H35: =IFERROR(IF('Investment Case Asks - Monthly'!AS35="","",'Investment Case Asks - Monthly'!AS35),"")
A36: =IFERROR(IF('Investment Case Asks - Monthly'!A36="","",'Investment Case Asks - Monthly'!A36),"") | B36: =IFERROR(IF('Investment Case Asks - Monthly'!B36="","",'Investment Case Asks - Monthly'!B36),"") | C36: =IFERROR(IF('Investment Case Asks - Monthly'!C36="","",'Investment Case Asks - Monthly'!C36),"") | D36: =IFERROR(IF('Investment Case Asks - Monthly'!D36="","",'Investment Case Asks - Monthly'!D36),"") | E36: =IFERROR(IF('Investment Case Asks - Monthly'!R36="","",'Investment Case Asks - Monthly'!R36),"") | F36: =IFERROR(IF('Investment Case Asks - Monthly'!AE36="","",'Investment Case Asks - Monthly'!AE36),"") | G36: =IFERROR(IF('Investment Case Asks - Monthly'!AR36="","",'Investment Case Asks - Monthly'!AR36),"") | H36: =IFERROR(IF('Investment Case Asks - Monthly'!AS36="","",'Investment Case Asks - Monthly'!AS36),"")
A37: =IFERROR(IF('Investment Case Asks - Monthly'!A37="","",'Investment Case Asks - Monthly'!A37),"") | B37: =IFERROR(IF('Investment Case Asks - Monthly'!B37="","",'Investment Case Asks - Monthly'!B37),"") | C37: =IFERROR(IF('Investment Case Asks - Monthly'!C37="","",'Investment Case Asks - Monthly'!C37),"") | D37: =IFERROR(IF('Investment Case Asks - Monthly'!D37="","",'Investment Case Asks - Monthly'!D37),"") | E37: =IFERROR(IF('Investment Case Asks - Monthly'!R37="","",'Investment Case Asks - Monthly'!R37),"") | F37: =IFERROR(IF('Investment Case Asks - Monthly'!AE37="","",'Investment Case Asks - Monthly'!AE37),"") | G37: =IFERROR(IF('Investment Case Asks - Monthly'!AR37="","",'Investment Case Asks - Monthly'!AR37),"") | H37: =IFERROR(IF('Investment Case Asks - Monthly'!AS37="","",'Investment Case Asks - Monthly'!AS37),"")
A38: =IFERROR(IF('Investment Case Asks - Monthly'!A38="","",'Investment Case Asks - Monthly'!A38),"") | B38: =IFERROR(IF('Investment Case Asks - Monthly'!B38="","",'Investment Case Asks - Monthly'!B38),"") | C38: =IFERROR(IF('Investment Case Asks - Monthly'!C38="","",'Investment Case Asks - Monthly'!C38),"") | D38: =IFERROR(IF('Investment Case Asks - Monthly'!D38="","",'Investment Case Asks - Monthly'!D38),"") | E38: =IFERROR(IF('Investment Case Asks - Monthly'!R38="","",'Investment Case Asks - Monthly'!R38),"") | F38: =IFERROR(IF('Investment Case Asks - Monthly'!AE38="","",'Investment Case Asks - Monthly'!AE38),"") | G38: =IFERROR(IF('Investment Case Asks - Monthly'!AR38="","",'Investment Case Asks - Monthly'!AR38),"") | H38: =IFERROR(IF('Investment Case Asks - Monthly'!AS38="","",'Investment Case Asks - Monthly'!AS38),"")
A39: =IFERROR(IF('Investment Case Asks - Monthly'!A39="","",'Investment Case Asks - Monthly'!A39),"") | B39: =IFERROR(IF('Investment Case Asks - Monthly'!B39="","",'Investment Case Asks - Monthly'!B39),"") | C39: =IFERROR(IF('Investment Case Asks - Monthly'!C39="","",'Investment Case Asks - Monthly'!C39),"") | D39: =IFERROR(IF('Investment Case Asks - Monthly'!D39="","",'Investment Case Asks - Monthly'!D39),"") | E39: =IFERROR(IF('Investment Case Asks - Monthly'!R39="","",'Investment Case Asks - Monthly'!R39),"") | F39: =IFERROR(IF('Investment Case Asks - Monthly'!AE39="","",'Investment Case Asks - Monthly'!AE39),"") | G39: =IFERROR(IF('Investment Case Asks - Monthly'!AR39="","",'Investment Case Asks - Monthly'!AR39),"") | H39: =IFERROR(IF('Investment Case Asks - Monthly'!AS39="","",'Investment Case Asks - Monthly'!AS39),"")
... A42: =IFERROR(IF('Investment Case Asks - Monthly'!A42="","",'Investment Case Asks - Monthly'!A42),"") | B42: =IFERROR(IF('Investment Case Asks - Monthly'!B42="","",'Investment Case Asks - Monthly'!B42),"") | C42: =IFERROR(IF('Investment Case Asks - Monthly'!C42="","",'Investment Case Asks - Monthly'!C42),"") | D42: =IFERROR(IF('Investment Case Asks - Monthly'!D42="","",'Investment Case Asks - Monthly'!D42),"") | E42: =IFERROR(IF('Investment Case Asks - Monthly'!R42="","",'Investment Case Asks - Monthly'!R42),"") | F42: =IFERROR(IF('Investment Case Asks - Monthly'!AE42="","",'Investment Case Asks - Monthly'!AE42),"") | G42: =IFERROR(IF('Investment Case Asks - Monthly'!AR42="","",'Investment Case Asks - Monthly'!AR42),"") | H42: =IFERROR(IF('Investment Case Asks - Monthly'!AS42="","",'Investment Case Asks - Monthly'!AS42),"")
A44: Total Essentials Bonus / Contract Labor / Non-Payroll Incremental Spend | E44: =SUM(E28:E42) -> 0 | F44: =SUM(F28:F42) -> 0 | G44: =SUM(G28:G42) -> 0

Sheet Investment Case Asks - Monthly
A1: Investment Case Asks - Incremental Spend Input
A3: Payroll / Headcount Incremental Spend
A4: Job Title | B4: Group | C4: Job Level | D4: Role / Hire | E4: Location (City/Country) | F4: Key Job Responsibilities | G4: Hire Date | H4: Base Salary | I4: Bonus % | J4: Bonus | K4: Payroll Taxes | L4: Benefits | M4: Vacation | N4: Other | O4: Annualized Spend | P4: Jan-27 | Q4: Feb-27 | R4: Mar-27 | S4: Apr-27 | T4: May-27 | U4: Jun-27 | V4: Jul-27 | W4: Aug-27 | X4: Sep-27 | Y4: Oct-27 | Z4: Nov-27 | AA4: Dec-27 | AB4: 2027 Incremental Spend | AC4: Jan-28 | AD4: Feb-28 | AE4: Mar-28 | AF4: Apr-28 | AG4: May-28 | AH4: Jun-28 | AI4: Jul-28 | AJ4: Aug-28 | AK4: Sep-28 | AL4: Oct-28 | AM4: Nov-28 | AN4: Dec-28 | AO4: 2028 Incremental Spend | AP4: Jan-29 | AQ4: Feb-29 | AR4: Mar-29 | AS4: Apr-29 | AT4: May-29 | AU4: Jun-29 | AV4: Jul-29 | AW4: Aug-29 | AX4: Sep-29 | AY4: Oct-29 | AZ4: Nov-29 | BA4: Dec-29 | BB4: 2029 Incremental Spend | BC4: Notes / Rationale
J5: =IF(COUNTA($A5:$I5)>0,IFERROR($H5*$I5,0),"") | K5: =IF(COUNTA($A5:$I5)>0,IFERROR($H5*Summary!$C$46/Summary!$C$43,0),"") | L5: =IF(COUNTA($A5:$I5)>0,IFERROR($H5*Summary!$C$47/Summary!$C$43,0),"") | M5: =IF(COUNTA($A5:$I5)>0,IFERROR($H5*Summary!$C$48/Summary!$C$43,0),"") | N5: =IF(COUNTA($A5:$I5)>0,IFERROR($H5*Summary!$C$49/Summary!$C$43,0),"") | O5: =IF(COUNTA($A5:$I5)>0,IFERROR($H5,0)+SUM(J5:N5),"") | P5: =_xlfn.LET(_xlpm.m,IF(ISNUMBER(P$4),DATE(YEAR(P$4),MONTH(P$4),1),DATEVALUE("1-"&P$4)),IF(OR(COUNTA($A5:$G5)>0,$H5<>""),$O5/12*IF($G5="",1,MAX(0,(EOMONTH(_xlpm.m,0)-MAX($G5,_xlpm.m)+1)/(EOMONTH(_xlpm.m,0)-_xlpm.m+1))),"")) | Q5: =_xlfn.LET(_xlpm.m,IF(ISNUMBER(Q$4),DATE(YEAR(Q$4),MONTH(Q$4),1),DATEVALUE("1-"&Q$4)),IF(OR(COUNTA($A5:$G5)>0,$H5<>""),$O5/12*IF($G5="",1,MAX(0,(EOMONTH(_xlpm.m,0)-MAX($G5,_xlpm.m)+1)/(EOMONTH(_xlpm.m,0)-_xlpm.m+1))),"")) | R5: =_xlfn.LET(_xlpm.m,IF(ISNUMBER(R$4),DATE(YEAR(R$4),MONTH(R$4),1),DATEVALUE("1-"&R$4)),IF(OR(COUNTA($A5:$G5)>0,$H5<>""),$O5/12*IF($G5="",1,MAX(0,(EOMONTH(_xlpm.m,0)-MAX($G5,_xlpm.m)+1)/(EOMONTH(_xlpm.m,0)-_xlpm.m+1))),"")) | S5: =_xlfn.LET(_xlpm.m,IF(ISNUMBER(S$4),DATE(YEAR(S$4),MONTH(S$4),1),DATEVALUE("1-"&S$4)),IF(OR(COUNTA($A5:$G5)>0,$H5<>""),$O5/12*IF($G5="",1,MAX(0,(EOMONTH(_xlpm.m,0)-MAX($G5,_xlpm.m)+1)/(EOMONTH(_xlpm.m,0)-_xlpm.m+1))),"")) | T5: =_xlfn.LET(_xlpm.m,IF(ISNUMBER(T$4),DATE(YEAR(T$4),MONTH(T$4),1),DATEVALUE("1-"&T$4)),IF(OR(COUNTA($A5:$G5)>0,$H5<>""),$O5/12*IF($G5="",1,MAX(0,(EOMONTH(_xlpm.m,0)-MAX($G5,_xlpm.m)+1)/(EOMONTH(_xlpm.m,0)-_xlpm.m+1))),"")) | U5: =_xlfn.LET(_xlpm.m,IF(ISNUMBER(U$4),DATE(YEAR(U$4),MONTH(U$4),1),DATEVALUE("1-"&U$4)),IF(OR(COUNTA($A5:$G5)>0,$H5<>""),$O5/12*IF($G5="",1,MAX(0,(EOMONTH(_xlpm.m,0)-MAX($G5,_xlpm.m)+1)/(EOMONTH(_xlpm.m,0)-_xlpm.m+1))),"")) | V5: =_xlfn.LET(_xlpm.m,IF(ISNUMBER(V$4),DATE(YEAR(V$4),MONTH(V$4),1),DATEVALUE("1-"&V$4)),IF(OR(COUNTA($A5:$G5)>0,$H5<>""),$O5/12*IF($G5="",1,MAX(0,(EOMONTH(_xlpm.m,0)-MAX($G5,_xlpm.m)+1)/(EOMONTH(_xlpm.m,0)-_xlpm.m+1))),"")) | W5: =_xlfn.LET(_xlpm.m,IF(ISNUMBER(W$4),DATE(YEAR(W$4),MONTH(W$4),1),DATEVALUE("1-"&W$4)),IF(OR(COUNTA($A5:$G5)>0,$H5<>""),$O5/12*IF($G5="",1,MAX(0,(EOMONTH(_xlpm.m,0)-MAX($G5,_xlpm.m)+1)/(EOMONTH(_xlpm.m,0)-_xlpm.m+1))),"")) | ... AA5: =_xlfn.LET(_xlpm.m,IF(ISNUMBER(AA$4),DATE(YEAR(AA$4),MONTH(AA$4),1),DATEVALUE("1-"&AA$4)),IF(OR(COUNTA($A5:$G5)>0,$H5<>""),$O5/12*IF($G5="",1,MAX(0,(EOMONTH(_xlpm.m,0)-MAX($G5,_xlpm.m)+1)/(EOMONTH(_xlpm.m,0)-_xlpm.m+1))),"")) | AB5: =IF(OR(COUNTA($A5:$G5)>0,$H5<>""),SUM(P5:AA5),"") | AC5: =_xlfn.LET(_xlpm.m,IF(ISNUMBER(AC$4),DATE(YEAR(AC$4),MONTH(AC$4),1),DATEVALUE("1-"&AC$4)),IF(OR(COUNTA($A5:$G5)>0,$H5<>""),$O5/12*IF($G5="",1,MAX(0,(EOMONTH(_xlpm.m,0)-MAX($G5,_xlpm.m)+1)/(EOMONTH(_xlpm.m,0)-_xlpm.m+1))),"")) | AD5: =_xlfn.LET(_xlpm.m,IF(ISNUMBER(AD$4),DATE(YEAR(AD$4),MONTH(AD$4),1),DATEVALUE("1-"&AD$4)),IF(OR(COUNTA($A5:$G5)>0,$H5<>""),$O5/12*IF($G5="",1,MAX(0,(EOMONTH(_xlpm.m,0)-MAX($G5,_xlpm.m)+1)/(EOMONTH(_xlpm.m,0)-_xlpm.m+1))),"")) | AE5: =_xlfn.LET(_xlpm.m,IF(ISNUMBER(AE$4),DATE(YEAR(AE$4),MONTH(AE$4),1),DATEVALUE("1-"&AE$4)),IF(OR(COUNTA($A5:$G5)>0,$H5<>""),$O5/12*IF($G5="",1,MAX(0,(EOMONTH(_xlpm.m,0)-MAX($G5,_xlpm.m)+1)/(EOMONTH(_xlpm.m,0)-_xlpm.m+1))),"")) | AF5: =_xlfn.LET(_xlpm.m,IF(ISNUMBER(AF$4),DATE(YEAR(AF$4),MONTH(AF$4),1),DATEVALUE("1-"&AF$4)),IF(OR(COUNTA($A5:$G5)>0,$H5<>""),$O5/12*IF($G5="",1,MAX(0,(EOMONTH(_xlpm.m,0)-MAX($G5,_xlpm.m)+1)/(EOMONTH(_xlpm.m,0)-_xlpm.m+1))),"")) | AG5: =_xlfn.LET(_xlpm.m,IF(ISNUMBER(AG$4),DATE(YEAR(AG$4),MONTH(AG$4),1),DATEVALUE("1-"&AG$4)),IF(OR(COUNTA($A5:$G5)>0,$H5<>""),$O5/12*IF($G5="",1,MAX(0,(EOMONTH(_xlpm.m,0)-MAX($G5,_xlpm.m)+1)/(EOMONTH(_xlpm.m,0)-_xlpm.m+1))),"")) | AH5: =_xlfn.LET(_xlpm.m,IF(ISNUMBER(AH$4),DATE(YEAR(AH$4),MONTH(AH$4),1),DATEVALUE("1-"&AH$4)),IF(OR(COUNTA($A5:$G5)>0,$H5<>""),$O5/12*IF($G5="",1,MAX(0,(EOMONTH(_xlpm.m,0)-MAX($G5,_xlpm.m)+1)/(EOMONTH(_xlpm.m,0)-_xlpm.m+1))),"")) | AI5: =_xlfn.LET(_xlpm.m,IF(ISNUMBER(AI$4),DATE(YEAR(AI$4),MONTH(AI$4),1),DATEVALUE("1-"&AI$4)),IF(OR(COUNTA($A5:$G5)>0,$H5<>""),$O5/12*IF($G5="",1,MAX(0,(EOMONTH(_xlpm.m,0)-MAX($G5,_xlpm.m)+1)/(EOMONTH(_xlpm.m,0)-_xlpm.m+1))),"")) | AJ5: =_xlfn.LET(_xlpm.m,IF(ISNUMBER(AJ$4),DATE(YEAR(AJ$4),MONTH(AJ$4),1),DATEVALUE("1-"&AJ$4)),IF(OR(COUNTA($A5:$G5)>0,$H5<>""),$O5/12*IF($G5="",1,MAX(0,(EOMONTH(_xlpm.m,0)-MAX($G5,_xlpm.m)+1)/(EOMONTH(_xlpm.m,0)-_xlpm.m+1))),"")) | ... AN5: =_xlfn.LET(_xlpm.m,IF(ISNUMBER(AN$4),DATE(YEAR(AN$4),MONTH(AN$4),1),DATEVALUE("1-"&AN$4)),IF(OR(COUNTA($A5:$G5)>0,$H5<>""),$O5/12*IF($G5="",1,MAX(0,(EOMONTH(_xlpm.m,0)-MAX($G5,_xlpm.m)+1)/(EOMONTH(_xlpm.m,0)-_xlpm.m+1))),"")) | AO5: =IF(OR(COUNTA($A5:$G5)>0,$H5<>""),SUM(AC5:AN5),"") | AP5: =_xlfn.LET(_xlpm.m,IF(ISNUMBER(AP$4),DATE(YEAR(AP$4),MONTH(AP$4),1),DATEVALUE("1-"&AP$4)),IF(OR(COUNTA($A5:$G5)>0,$H5<>""),$O5/12*IF($G5="",1,MAX(0,(EOMONTH(_xlpm.m,0)-MAX($G5,_xlpm.m)+1)/(EOMONTH(_xlpm.m,0)-_xlpm.m+1))),"")) | AQ5: =_xlfn.LET(_xlpm.m,IF(ISNUMBER(AQ$4),DATE(YEAR(AQ$4),MONTH(AQ$4),1),DATEVALUE("1-"&AQ$4)),IF(OR(COUNTA($A5:$G5)>0,$H5<>""),$O5/12*IF($G5="",1,MAX(0,(EOMONTH(_xlpm.m,0)-MAX($G5,_xlpm.m)+1)/(EOMONTH(_xlpm.m,0)-_xlpm.m+1))),"")) | AR5: =_xlfn.LET(_xlpm.m,IF(ISNUMBER(AR$4),DATE(YEAR(AR$4),MONTH(AR$4),1),DATEVALUE("1-"&AR$4)),IF(OR(COUNTA($A5:$G5)>0,$H5<>""),$O5/12*IF($G5="",1,MAX(0,(EOMONTH(_xlpm.m,0)-MAX($G5,_xlpm.m)+1)/(EOMONTH(_xlpm.m,0)-_xlpm.m+1))),"")) | AS5: =_xlfn.LET(_xlpm.m,IF(ISNUMBER(AS$4),DATE(YEAR(AS$4),MONTH(AS$4),1),DATEVALUE("1-"&AS$4)),IF(OR(COUNTA($A5:$G5)>0,$H5<>""),$O5/12*IF($G5="",1,MAX(0,(EOMONTH(_xlpm.m,0)-MAX($G5,_xlpm.m)+1)/(EOMONTH(_xlpm.m,0)-_xlpm.m+1))),"")) | AT5: =_xlfn.LET(_xlpm.m,IF(ISNUMBER(AT$4),DATE(YEAR(AT$4),MONTH(AT$4),1),DATEVALUE("1-"&AT$4)),IF(OR(COUNTA($A5:$G5)>0,$H5<>""),$O5/12*IF($G5="",1,MAX(0,(EOMONTH(_xlpm.m,0)-MAX($G5,_xlpm.m)+1)/(EOMONTH(_xlpm.m,0)-_xlpm.m+1))),"")) | AU5: =_xlfn.LET(_xlpm.m,IF(ISNUMBER(AU$4),DATE(YEAR(AU$4),MONTH(AU$4),1),DATEVALUE("1-"&AU$4)),IF(OR(COUNTA($A5:$G5)>0,$H5<>""),$O5/12*IF($G5="",1,MAX(0,(EOMONTH(_xlpm.m,0)-MAX($G5,_xlpm.m)+1)/(EOMONTH(_xlpm.m,0)-_xlpm.m+1))),"")) | AV5: =_xlfn.LET(_xlpm.m,IF(ISNUMBER(AV$4),DATE(YEAR(AV$4),MONTH(AV$4),1),DATEVALUE("1-"&AV$4)),IF(OR(COUNTA($A5:$G5)>0,$H5<>""),$O5/12*IF($G5="",1,MAX(0,(EOMONTH(_xlpm.m,0)-MAX($G5,_xlpm.m)+1)/(EOMONTH(_xlpm.m,0)-_xlpm.m+1))),"")) | AW5: =_xlfn.LET(_xlpm.m,IF(ISNUMBER(AW$4),DATE(YEAR(AW$4),MONTH(AW$4),1),DATEVALUE("1-"&AW$4)),IF(OR(COUNTA($A5:$G5)>0,$H5<>""),$O5/12*IF($G5="",1,MAX(0,(EOMONTH(_xlpm.m,0)-MAX($G5,_xlpm.m)+1)/(EOMONTH(_xlpm.m,0)-_xlpm.m+1))),"")) | ... BA5: =_xlfn.LET(_xlpm.m,IF(ISNUMBER(BA$4),DATE(YEAR(BA$4),MONTH(BA$4),1),DATEVALUE("1-"&BA$4)),IF(OR(COUNTA($A5:$G5)>0,$H5<>""),$O5/12*IF($G5="",1,MAX(0,(EOMONTH(_xlpm.m,0)-MAX($G5,_xlpm.m)+1)/(EOMONTH(_xlpm.m,0)-_xlpm.m+1))),"")) | BB5: =IF(OR(COUNTA($A5:$G5)>0,$H5<>""),SUM(AP5:BA5),"")
J6: =IF(COUNTA($A6:$I6)>0,IFERROR($H6*$I6,0),"") | K6: =IF(COUNTA($A6:$I6)>0,IFERROR($H6*Summary!$C$46/Summary!$C$43,0),"") | L6: =IF(COUNTA($A6:$I6)>0,IFERROR($H6*Summary!$C$47/Summary!$C$43,0),"") | M6: =IF(COUNTA($A6:$I6)>0,IFERROR($H6*Summary!$C$48/Summary!$C$43,0),"") | N6: =IF(COUNTA($A6:$I6)>0,IFERROR($H6*Summary!$C$49/Summary!$C$43,0),"") | O6: =IF(COUNTA($A6:$I6)>0,IFERROR($H6,0)+SUM(J6:N6),"") | P6: =IF(COUNTA($A6:$I6)>0,$O6/12*IF($G6="",1,MAX(0,(EOMONTH(P$4,0)-MAX($G6,P$4)+1)/(EOMONTH(P$4,0)-P$4+1))),"") | Q6: =IF(COUNTA($A6:$I6)>0,$O6/12*IF($G6="",1,MAX(0,(EOMONTH(Q$4,0)-MAX($G6,Q$4)+1)/(EOMONTH(Q$4,0)-Q$4+1))),"") | R6: =IF(COUNTA($A6:$I6)>0,$O6/12*IF($G6="",1,MAX(0,(EOMONTH(R$4,0)-MAX($G6,R$4)+1)/(EOMONTH(R$4,0)-R$4+1))),"") | S6: =IF(COUNTA($A6:$I6)>0,$O6/12*IF($G6="",1,MAX(0,(EOMONTH(S$4,0)-MAX($G6,S$4)+1)/(EOMONTH(S$4,0)-S$4+1))),"") | T6: =IF(COUNTA($A6:$I6)>0,$O6/12*IF($G6="",1,MAX(0,(EOMONTH(T$4,0)-MAX($G6,T$4)+1)/(EOMONTH(T$4,0)-T$4+1))),"") | U6: =IF(COUNTA($A6:$I6)>0,$O6/12*IF($G6="",1,MAX(0,(EOMONTH(U$4,0)-MAX($G6,U$4)+1)/(EOMONTH(U$4,0)-U$4+1))),"") | V6: =IF(COUNTA($A6:$I6)>0,$O6/12*IF($G6="",1,MAX(0,(EOMONTH(V$4,0)-MAX($G6,V$4)+1)/(EOMONTH(V$4,0)-V$4+1))),"") | W6: =IF(COUNTA($A6:$I6)>0,$O6/12*IF($G6="",1,MAX(0,(EOMONTH(W$4,0)-MAX($G6,W$4)+1)/(EOMONTH(W$4,0)-W$4+1))),"") | ... AA6: =IF(COUNTA($A6:$I6)>0,$O6/12*IF($G6="",1,MAX(0,(EOMONTH(AA$4,0)-MAX($G6,AA$4)+1)/(EOMONTH(AA$4,0)-AA$4+1))),"") | AB6: =IF(COUNTA($A6:$I6)>0,SUM(P6:AA6),"") | AC6: =IF(COUNTA($A6:$I6)>0,$O6/12*IF($G6="",1,MAX(0,(EOMONTH(AC$4,0)-MAX($G6,AC$4)+1)/(EOMONTH(AC$4,0)-AC$4+1))),"") | AD6: =IF(COUNTA($A6:$I6)>0,$O6/12*IF($G6="",1,MAX(0,(EOMONTH(AD$4,0)-MAX($G6,AD$4)+1)/(EOMONTH(AD$4,0)-AD$4+1))),"") | AE6: =IF(COUNTA($A6:$I6)>0,$O6/12*IF($G6="",1,MAX(0,(EOMONTH(AE$4,0)-MAX($G6,AE$4)+1)/(EOMONTH(AE$4,0)-AE$4+1))),"") | AF6: =IF(COUNTA($A6:$I6)>0,$O6/12*IF($G6="",1,MAX(0,(EOMONTH(AF$4,0)-MAX($G6,AF$4)+1)/(EOMONTH(AF$4,0)-AF$4+1))),"") | AG6: =IF(COUNTA($A6:$I6)>0,$O6/12*IF($G6="",1,MAX(0,(EOMONTH(AG$4,0)-MAX($G6,AG$4)+1)/(EOMONTH(AG$4,0)-AG$4+1))),"") | AH6: =IF(COUNTA($A6:$I6)>0,$O6/12*IF($G6="",1,MAX(0,(EOMONTH(AH$4,0)-MAX($G6,AH$4)+1)/(EOMONTH(AH$4,0)-AH$4+1))),"") | AI6: =IF(COUNTA($A6:$I6)>0,$O6/12*IF($G6="",1,MAX(0,(EOMONTH(AI$4,0)-MAX($G6,AI$4)+1)/(EOMONTH(AI$4,0)-AI$4+1))),"") | AJ6: =IF(COUNTA($A6:$I6)>0,$O6/12*IF($G6="",1,MAX(0,(EOMONTH(AJ$4,0)-MAX($G6,AJ$4)+1)/(EOMONTH(AJ$4,0)-AJ$4+1))),"") | ... AN6: =IF(COUNTA($A6:$I6)>0,$O6/12*IF($G6="",1,MAX(0,(EOMONTH(AN$4,0)-MAX($G6,AN$4)+1)/(EOMONTH(AN$4,0)-AN$4+1))),"") | AO6: =IF(COUNTA($A6:$I6)>0,SUM(AC6:AN6),"") | AP6: =IF(COUNTA($A6:$I6)>0,$O6/12*IF($G6="",1,MAX(0,(EOMONTH(AP$4,0)-MAX($G6,AP$4)+1)/(EOMONTH(AP$4,0)-AP$4+1))),"") | AQ6: =IF(COUNTA($A6:$I6)>0,$O6/12*IF($G6="",1,MAX(0,(EOMONTH(AQ$4,0)-MAX($G6,AQ$4)+1)/(EOMONTH(AQ$4,0)-AQ$4+1))),"") | AR6: =IF(COUNTA($A6:$I6)>0,$O6/12*IF($G6="",1,MAX(0,(EOMONTH(AR$4,0)-MAX($G6,AR$4)+1)/(EOMONTH(AR$4,0)-AR$4+1))),"") | AS6: =IF(COUNTA($A6:$I6)>0,$O6/12*IF($G6="",1,MAX(0,(EOMONTH(AS$4,0)-MAX($G6,AS$4)+1)/(EOMONTH(AS$4,0)-AS$4+1))),"") | AT6: =IF(COUNTA($A6:$I6)>0,$O6/12*IF($G6="",1,MAX(0,(EOMONTH(AT$4,0)-MAX($G6,AT$4)+1)/(EOMONTH(AT$4,0)-AT$4+1))),"") | AU6: =IF(COUNTA($A6:$I6)>0,$O6/12*IF($G6="",1,MAX(0,(EOMONTH(AU$4,0)-MAX($G6,AU$4)+1)/(EOMONTH(AU$4,0)-AU$4+1))),"") | AV6: =IF(COUNTA($A6:$I6)>0,$O6/12*IF($G6="",1,MAX(0,(EOMONTH(AV$4,0)-MAX($G6,AV$4)+1)/(EOMONTH(AV$4,0)-AV$4+1))),"") | AW6: =IF(COUNTA($A6:$I6)>0,$O6/12*IF($G6="",1,MAX(0,(EOMONTH(AW$4,0)-MAX($G6,AW$4)+1)/(EOMONTH(AW$4,0)-AW$4+1))),"") | ... BA6: =IF(COUNTA($A6:$I6)>0,$O6/12*IF($G6="",1,MAX(0,(EOMONTH(BA$4,0)-MAX($G6,BA$4)+1)/(EOMONTH(BA$4,0)-BA$4+1))),"") | BB6: =IF(COUNTA($A6:$I6)>0,SUM(AP6:BA6),"")
J7: =IF(COUNTA($A7:$I7)>0,IFERROR($H7*$I7,0),"") | K7: =IF(COUNTA($A7:$I7)>0,IFERROR($H7*Summary!$C$46/Summary!$C$43,0),"") | L7: =IF(COUNTA($A7:$I7)>0,IFERROR($H7*Summary!$C$47/Summary!$C$43,0),"") | M7: =IF(COUNTA($A7:$I7)>0,IFERROR($H7*Summary!$C$48/Summary!$C$43,0),"") | N7: =IF(COUNTA($A7:$I7)>0,IFERROR($H7*Summary!$C$49/Summary!$C$43,0),"") | O7: =IF(COUNTA($A7:$I7)>0,IFERROR($H7,0)+SUM(J7:N7),"") | P7: =IF(COUNTA($A7:$I7)>0,$O7/12*IF($G7="",1,MAX(0,(EOMONTH(P$4,0)-MAX($G7,P$4)+1)/(EOMONTH(P$4,0)-P$4+1))),"") | Q7: =IF(COUNTA($A7:$I7)>0,$O7/12*IF($G7="",1,MAX(0,(EOMONTH(Q$4,0)-MAX($G7,Q$4)+1)/(EOMONTH(Q$4,0)-Q$4+1))),"") | R7: =IF(COUNTA($A7:$I7)>0,$O7/12*IF($G7="",1,MAX(0,(EOMONTH(R$4,0)-MAX($G7,R$4)+1)/(EOMONTH(R$4,0)-R$4+1))),"") | S7: =IF(COUNTA($A7:$I7)>0,$O7/12*IF($G7="",1,MAX(0,(EOMONTH(S$4,0)-MAX($G7,S$4)+1)/(EOMONTH(S$4,0)-S$4+1))),"") | T7: =IF(COUNTA($A7:$I7)>0,$O7/12*IF($G7="",1,MAX(0,(EOMONTH(T$4,0)-MAX($G7,T$4)+1)/(EOMONTH(T$4,0)-T$4+1))),"") | U7: =IF(COUNTA($A7:$I7)>0,$O7/12*IF($G7="",1,MAX(0,(EOMONTH(U$4,0)-MAX($G7,U$4)+1)/(EOMONTH(U$4,0)-U$4+1))),"") | V7: =IF(COUNTA($A7:$I7)>0,$O7/12*IF($G7="",1,MAX(0,(EOMONTH(V$4,0)-MAX($G7,V$4)+1)/(EOMONTH(V$4,0)-V$4+1))),"") | W7: =IF(COUNTA($A7:$I7)>0,$O7/12*IF($G7="",1,MAX(0,(EOMONTH(W$4,0)-MAX($G7,W$4)+1)/(EOMONTH(W$4,0)-W$4+1))),"") | ... AA7: =IF(COUNTA($A7:$I7)>0,$O7/12*IF($G7="",1,MAX(0,(EOMONTH(AA$4,0)-MAX($G7,AA$4)+1)/(EOMONTH(AA$4,0)-AA$4+1))),"") | AB7: =IF(COUNTA($A7:$I7)>0,SUM(P7:AA7),"") | AC7: =IF(COUNTA($A7:$I7)>0,$O7/12*IF($G7="",1,MAX(0,(EOMONTH(AC$4,0)-MAX($G7,AC$4)+1)/(EOMONTH(AC$4,0)-AC$4+1))),"") | AD7: =IF(COUNTA($A7:$I7)>0,$O7/12*IF($G7="",1,MAX(0,(EOMONTH(AD$4,0)-MAX($G7,AD$4)+1)/(EOMONTH(AD$4,0)-AD$4+1))),"") | AE7: =IF(COUNTA($A7:$I7)>0,$O7/12*IF($G7="",1,MAX(0,(EOMONTH(AE$4,0)-MAX($G7,AE$4)+1)/(EOMONTH(AE$4,0)-AE$4+1))),"") | AF7: =IF(COUNTA($A7:$I7)>0,$O7/12*IF($G7="",1,MAX(0,(EOMONTH(AF$4,0)-MAX($G7,AF$4)+1)/(EOMONTH(AF$4,0)-AF$4+1))),"") | AG7: =IF(COUNTA($A7:$I7)>0,$O7/12*IF($G7="",1,MAX(0,(EOMONTH(AG$4,0)-MAX($G7,AG$4)+1)/(EOMONTH(AG$4,0)-AG$4+1))),"") | AH7: =IF(COUNTA($A7:$I7)>0,$O7/12*IF($G7="",1,MAX(0,(EOMONTH(AH$4,0)-MAX($G7,AH$4)+1)/(EOMONTH(AH$4,0)-AH$4+1))),"") | AI7: =IF(COUNTA($A7:$I7)>0,$O7/12*IF($G7="",1,MAX(0,(EOMONTH(AI$4,0)-MAX($G7,AI$4)+1)/(EOMONTH(AI$4,0)-AI$4+1))),"") | AJ7: =IF(COUNTA($A7:$I7)>0,$O7/12*IF($G7="",1,MAX(0,(EOMONTH(AJ$4,0)-MAX($G7,AJ$4)+1)/(EOMONTH(AJ$4,0)-AJ$4+1))),"") | ... AN7: =IF(COUNTA($A7:$I7)>0,$O7/12*IF($G7="",1,MAX(0,(EOMONTH(AN$4,0)-MAX($G7,AN$4)+1)/(EOMONTH(AN$4,0)-AN$4+1))),"") | AO7: =IF(COUNTA($A7:$I7)>0,SUM(AC7:AN7),"") | AP7: =IF(COUNTA($A7:$I7)>0,$O7/12*IF($G7="",1,MAX(0,(EOMONTH(AP$4,0)-MAX($G7,AP$4)+1)/(EOMONTH(AP$4,0)-AP$4+1))),"") | AQ7: =IF(COUNTA($A7:$I7)>0,$O7/12*IF($G7="",1,MAX(0,(EOMONTH(AQ$4,0)-MAX($G7,AQ$4)+1)/(EOMONTH(AQ$4,0)-AQ$4+1))),"") | AR7: =IF(COUNTA($A7:$I7)>0,$O7/12*IF($G7="",1,MAX(0,(EOMONTH(AR$4,0)-MAX($G7,AR$4)+1)/(EOMONTH(AR$4,0)-AR$4+1))),"") | AS7: =IF(COUNTA($A7:$I7)>0,$O7/12*IF($G7="",1,MAX(0,(EOMONTH(AS$4,0)-MAX($G7,AS$4)+1)/(EOMONTH(AS$4,0)-AS$4+1))),"") | AT7: =IF(COUNTA($A7:$I7)>0,$O7/12*IF($G7="",1,MAX(0,(EOMONTH(AT$4,0)-MAX($G7,AT$4)+1)/(EOMONTH(AT$4,0)-AT$4+1))),"") | AU7: =IF(COUNTA($A7:$I7)>0,$O7/12*IF($G7="",1,MAX(0,(EOMONTH(AU$4,0)-MAX($G7,AU$4)+1)/(EOMONTH(AU$4,0)-AU$4+1))),"") | AV7: =IF(COUNTA($A7:$I7)>0,$O7/12*IF($G7="",1,MAX(0,(EOMONTH(AV$4,0)-MAX($G7,AV$4)+1)/(EOMONTH(AV$4,0)-AV$4+1))),"") | AW7: =IF(COUNTA($A7:$I7)>0,$O7/12*IF($G7="",1,MAX(0,(EOMONTH(AW$4,0)-MAX($G7,AW$4)+1)/(EOMONTH(AW$4,0)-AW$4+1))),"") | ... BA7: =IF(COUNTA($A7:$I7)>0,$O7/12*IF($G7="",1,MAX(0,(EOMONTH(BA$4,0)-MAX($G7,BA$4)+1)/(EOMONTH(BA$4,0)-BA$4+1))),"") | BB7: =IF(COUNTA($A7:$I7)>0,SUM(AP7:BA7),"")
